Workbook
Name ANA_Anni_Adeguamento: Parametri!$M$4:$M$23
Name ANA_Attenzione_Supervisore: Parametri!$N$4:$N$23
Name ANA_Driver: Parametri!$K$4:$K$23
Name ANA_Event_Type: Parametri!$J$4:$J$23
Name ANA_ID: Parametri!$H$4:$H$23
Name ANA_Nome: Parametri!$I$4:$I$23
Name ANA_Owner: Parametri!$L$4:$L$23
Name ANA_Presidio_Controlli: Parametri!$O$4:$O$23
Name anagrafica: Parametri!$H$4:$O$23
Name anniProssimita: Parametri!$B$51:$B$55
Name AZ_Ciclo: Azioni!$A$6:$A$20029
Name AZ_Data_Decisione: Azioni!$J$6:$J$20029
Name AZ_Decisa_Da: Azioni!$K$6:$K$20029
Name AZ_Descrizione: Azioni!$D$6:$D$20029
Name AZ_ID_Azione: Azioni!$C$6:$C$20029
Name AZ_ID_Rischio: Azioni!$B$6:$B$20029
Name AZ_Mesi_Orizzonte: Azioni!$G$6:$G$20029
Name AZ_Orizzonte: Azioni!$F$6:$F$20029
Name AZ_Owner: Azioni!$E$6:$E$20029
Name AZ_Razionale: Azioni!$H$6:$H$20029
Name AZ_Stato: Azioni!$I$6:$I$20029
Name AZ_Validazione: Azioni!$L$6:$L$20029
Name capienzaElencoKRI: 150
Name capienzaKRICorrenti: 60
Name capienzaOsservazione: 20
Name capienzaPianoAzioni: 150
Name capienzaRadar: Parametri!$B$66
Name cicliTrend: Parametri!$B$20:$B$27
Name cicliUscitaRadar: Parametri!$B$69
Name cicloCorrente: Parametri!$B$15
Name cicloMeno2: Parametri!$B$17
Name cicloPrecedente: Parametri!$B$16
Name classificaAgire: OFFSET(Classifica!$V$5,0,0,MAX(1,COUNT(Classifica!$D$5:$D$24)),1)
Name classificaEntro: OFFSET(Classifica!$W$5,0,0,MAX(1,COUNT(Classifica!$D$5:$D$24)),1)
Name classificaEtichette: OFFSET(Classifica!$K$5,0,0,MAX(1,COUNT(Classifica!$D$5:$D$24)),1)
Name classificaID: OFFSET(Classifica!$B$5,0,0,MAX(1,COUNT(Classifica!$D$5:$D$24)),1)
Name classificaMargine: OFFSET(Classifica!$X$5,0,0,MAX(1,COUNT(Classifica!$D$5:$D$24)),1)
Name codiciDriver: Parametri!$E$15:$E$22
Name codiciL1: Parametri!$E$4:$E$12
Name coperturaAnagrafica: Registro!$D$5
Name coperturaValutati: Registro!$G$5
Name dataRiferimento: Parametri!$B$18
Name decisioniDaPrendere: Registro!$D$4
Name deltaEtichette: OFFSET(Delta!$AL$5,0,0,MAX(1,COUNT(Delta!$AI$5:$AI$24)),1)
Name deltaGiu: OFFSET(Delta!$AN$5,0,0,MAX(1,COUNT(Delta!$AI$5:$AI$24)),1)
Name deltaMotivi: Delta!$K$6:$Q$25
Name deltaSu: OFFSET(Delta!$AM$5,0,0,MAX(1,COUNT(Delta!$AI$5:$AI$24)),1)
Name deltaZero: OFFSET(Delta!$AO$5,0,0,MAX(1,COUNT(Delta!$AI$5:$AI$24)),1)
Name elencoKRI: OFFSET(Indicatori!$AB$12,0,0,MAX(1,COUNTIF(Indicatori!$AB$12:$AB$161,"?*")),1)
Name etichettaCiclo: Parametri!$B$57
Name fenomeniLista: Fenomeni!$A$7:$K$26
Name fenomeniUscite: Fenomeni!$A$30:$K$35
Name inizioFinestra4: Parametri!$B$31
Name KRI_Chiave: KRI!$S$6:$S$20051
Name KRI_Ciclo: KRI!$A$6:$A$20051
Name KRI_Ciclo_Aggiornamento: KRI!$Q$6:$Q$20051
Name KRI_Ciclo_Definizione: KRI!$P$6:$P$20051
Name KRI_Data_Rilevazione: KRI!$K$6:$K$20051
Name KRI_Fonte_Dati: KRI!$G$6:$G$20051
Name KRI_Fonte_Rilevazione: KRI!$L$6:$L$20051

Sheet Guida
A1: ="Horizon Scan NFR — Guida: come si usa questo workbook · "&etichettaCiclo -> Horizon Scan NFR — Guida: come si usa questo workbook · Ciclo 2026Q4 · dati al 31/12/2026 · da validare · Uso interno
A3: A COSA SERVE
A4: Horizon Scan NFR: registro dei rischi non finanziari emergenti della Banca. Ogni trimestre gli agenti valutano i rischi, lo script controlla e scrive qui, il validatore decide; i fogli da Quadro a Metodologia sono il report al comitato, le schede dei rischi un file a parte. Ogni foglio ha in testa (riga 2) chi lo aggiorna, cosa contiene e come si legge; il foglio Dizionario spiega ogni dato.
A6: CHI AGGIORNA COSA E QUANDO
A7: Foglio | B7: Settimanale · lunedi', A3 | C7: Trimestrale · A1, poi A5 | D7: Validatore · dopo il trimestre | E7: A che cosa serve
A8: REPORT AL COMITATO
A9: Quadro | C9: commento di A1, sintesi di A5, segnalazioni da motivare, numeri | D9: stato della validazione; avviso rettifiche | E9: prima pagina: il quadro e il perche'
A10: Classifica | C10: score e urgenza | D10: valori validati | E10: rischi per score; lente di Mosca
A11: Radar_Mosca | B11: segnali netti (livello) | C11: score, azioni (Y), KRI | D11: anni di adeguamento, presidio, attenzione del supervisore | E11: quanto presto agire, quanto e' grande, livello di allerta
A12: Matrice | C12: Probabilita e Impatto | D12: valori validati | E12: gravita' dei rischi
A13: Delta | C13: confronto con il ciclo prima | E13: che cosa e' cambiato e perche'
A14: Fenomeni | C14: rischi in osservazione, entrati e usciti | D14: valori e decisioni sullo stato | E14: rischi fuori dal radar, perche', con il segnale
A15: Metodologia | D15: pesi e parametri (Parametri) | E15: come si leggono i numeri
A16: LAVORO
A17: Registro | B17: segnali netti (colonna Q) | C17: dimensioni, score, urgenza, KRI, rilievi | D17: righe 4-5; presidio (anagrafica) | E17: il ciclo corrente, un rischio per riga
A18: Storico, Indicatori | C18: si aggiornano | E18: score negli ultimi cicli; KRI del ciclo e storia di uno
A19: Notizie | B19: si aggiorna; sintesi e flag di A3 | E19: pressione delle notizie, aree non presidiate, sintesi della settimana
A20: Piano_azioni | C20: azioni proposte da A1 | D20: decisione; Stato In corso/Completata (foglio Azioni) | E20: tutte le azioni e la loro scadenza
A21: Osservazione | C21: si aggiorna | E21: rischi in osservazione e dove si concentrano (driver x categoria)
A22: Validazione | B22: righe delle notizie | C22: righe di rischi, KRI, azioni; stato dei rischi | D22: valori gialli, decisione sullo stato, Motivazione, Respingi (a mano) | E22: unico foglio da compilare: una riga per oggetto
A23: Parametri | B23: settimana corrente | C23: ciclo corrente; anagrafica H-K (= il radar) | D23: celle gialle | E23: pesi, soglie, urgenza, regola del radar, anagrafica
A24: Dizionario | E24: ogni dato: chi lo scrive, come si calcola
A25: DATI (solo lo script)
A26: RiskRegister | C26: valutazioni di A1; stato nel registro unico | D26: valori validati, decisione sullo stato | E26: una riga per rischio per ciclo, radar e osservazione
A27: Azioni | C27: azioni proposte da A1 | D27: delibera; Stato In corso/Completata a mano | E27: una riga per azione
A28: KRI | C28: KRI e valori riletti da A1 | D28: rettifiche, KRI respinti | E28: storico, una riga per KRI per ciclo
A29: NewsLog | B29: notizie valutate da A3 | D29: rettifiche (facoltative) | E29: una riga per notizia
A30: Sintesi_Cicli | C30: commento di A1 e di A5 | E30: una riga per ciclo
A31: Sintesi_Settimane | B31: sintesi di A3 e flag proposti | E31: una riga per settimana
A32: Storico_Validazioni | B32: proposte delle notizie | C32: proposte di rischi, KRI, azioni | D32: decisioni (comando valida) | E32: una riga per oggetto e campo: proposta, valore deciso, motivo
A33: FILE A PARTE
A34: Schede_<ciclo>.xlsx | C34: testi di A6 dopo la validazione | D34: dati validati | E34: una scheda per rischio (comando schede)
A35: Giornaliero: la raccolta delle notizie riempie la cartella News_Inbox, non questo file. A4 (pareri su richiesta, in qualsiasi momento) non scrive qui: se un parere suggerisce di rivedere un rischio, la via e' il ciclo trimestrale successivo.
A37: QUANDO SI LANCIANO A5 E A6
A38: A5 (challenger), facoltativo (D-71): se lo si usa, dopo A1 e prima del comando trimestrale, allegando SOLO l'output di A1 e Baseline_corrente.json, e di nuovo ogni volta che A1 viene rifatto (vale solo per l'output esaminato). I suoi rilievi non fermano il ciclo: vanno nella colonna Segnalazioni del foglio Validazione, e un suo Bloccante rende obbligatoria la Motivazione del rischio. Lo script ferma solo i difetti di integrita' del registro. Non si lancia per le settimane, per A4 ne' dopo la validazione.
A39: A6 (schede): dopo la validazione del trimestre. Il comando schede-input prepara i dati validati; A6 scrive i testi; il comando schede li controlla e produce Schede_<ciclo>.xlsx. Senza A6 il comando schede produce comunque le schede con i testi del registro.
A41: DOVE SI SCRIVE A MANO (solo qui)
A42: Validazione: una riga per rischio, KRI, azione e notizia; si cambiano solo le celle gialle, la Motivazione e Respingi (istruzioni e criteri in testa al foglio), poi il comando valida.
A43: Parametri, celle gialle: pesi, soglie, urgenza (decisione della funzione di rischio); nell'anagrafica Owner, anni di adeguamento, attenzione del supervisore e presidio dei controlli (decisi dal validatore, restano da un ciclo all'altro).
A44: Azioni, colonna Stato: avanzamento di un'azione approvata (In corso, Completata); il Piano_azioni si aggiorna da solo.
A45: Indicatori, cella N4: il KRI di cui guardare la storia.
A46: Testi delle tabelle dati, per correggerne la forma (D-76): RiskRegister Descrizione e Razionale (lasciando le etichette RISCHIO:, IMPATTO:...); KRI Nome, Unita, Fonte_Dati, Razionale, Nota_Rilevazione; Azioni Descrizione e Razionale; RiskRegister Segnale_Avvicinamento dei rischi in osservazione. Mai ID, numeri, date, Validazione o righe intere. Non resta traccia automatica: dopo, salvare, chiudere e lanciare python esegui_ciclo_locale.py baseline (riallinea baseline e knowledge di A7).
A47: Valori di un ciclo gia' validato (punteggi, decisione sullo stato, KRI, owner e orizzonte delle azioni): non qui, ma con python esegui_ciclo_locale.py riapri, poi la griglia del foglio Validazione e valida, quante volte serve.
A48: Tutto il resto lo scrive lo script o e' una formula: non modificarlo.
... A61: Generato da 03_Excel/genera_dashboard.py (versione della struttura 2026-10-09). Per rifarlo a mano: 03_Excel/costruzione_manuale_template.md.

Sheet Quadro
A1: ="Horizon Scan NFR — Quadro d'insieme · "&etichettaCiclo -> Horizon Scan NFR — Quadro d'insieme · Ciclo 2026Q4 · dati al 31/12/2026 · da validare · Uso interno
A2: CICLO TRIMESTRALE — A1 valuta i rischi, lo script la controlla (e A5, se usato), il validatore la conferma o la rettifica. Come si legge: i cinque riquadri in alto dicono se il ciclo e' completo e validato; poi le priorita' per score, la gravita' (matrice) e l'urgenza (radar). A pagina 2 il commento di A1 (scritto prima della validazione: se dopo ci sono state rettifiche lo dice la riga "Dopo il commento" e valgono i numeri validati), le segnalazioni portate in validazione e i rischi segnalati, con il perche' calcolato dal foglio. Metodo e scale: Metodologia; ogni dato: Dizionario. Note dell'analista (cella gialla in prima pagina): testo libero scritto a mano, per esempio la sintesi delle spiegazioni chieste ad A7; a un ciclo nuovo passa nel foglio Sintesi_Cicli.
BH3: Appoggio del grafico: non modificare | BY3: Attivazione | BZ3: Attivazione | CA3: Attivazione | CB3: Attivazione | CC3: Attivazione | CD3: Attivazione | CE3: Attivazione | CF3: Attivazione | CG3: Attivazione | CH3: Attivazione | CI3: Attivazione | CJ3: Attivazione | CK3: Attivazione | CL3: Attivazione | CM3: Attenzione | CN3: Attenzione | CO3: Attenzione | CP3: Attenzione | CQ3: Attenzione | CR3: Attenzione | CS3: Attenzione | CT3: Attenzione | CU3: Attenzione | CV3: Attenzione | CW3: Attenzione | CX3: Attenzione | CY3: Attenzione | CZ3: Attenzione | DA3: Monitoraggio | DB3: Monitoraggio | DC3: Monitoraggio | DD3: Monitoraggio | DE3: Monitoraggio | DF3: Monitoraggio | DG3: Monitoraggio | DH3: Monitoraggio | DI3: Monitoraggio | DJ3: Monitoraggio | DK3: Monitoraggio | DL3: Monitoraggio | DM3: Monitoraggio | DN3: Monitoraggio
A4: Rischi valutati | D4: Livello di allerta: attivazione · attenzione | G4: Variati · nuovi (radar) | J4: KRI in rosso | M4: Validazione | T4: =COUNTIF(Radar_Mosca!$AA$5:$AA$24,"Attivazione") -> 2 | BY4: 1 | BZ4: 2 | CA4: 3 | CB4: 4 | CC4: 5 | CD4: 6 | CE4: 8 | CF4: 9 | CG4: 10 | CH4: 12 | CI4: 15 | CJ4: 16 | CK4: 20 | CL4: 25 | CM4: 1 | CN4: 2 | CO4: 3 | CP4: 4 | CQ4: 5 | CR4: 6 | CS4: 8 | CT4: 9 | CU4: 10 | CV4: 12 | CW4: 15 | CX4: 16 | CY4: 20 | CZ4: 25 | DA4: 1 | DB4: 2 | DC4: 3 | DD4: 4 | DE4: 5 | DF4: 6 | DG4: 8 | DH4: 9 | DI4: 10 | DJ4: 12 | DK4: 15 | DL4: 16 | DM4: 20 | DN4: 25
A5: =coperturaValutati -> 13 | D5: =$T$4&" · "&COUNTIF(Radar_Mosca!$AA$5:$AA$24,"Attenzione") -> 2 · 5 | G5: =COUNTIFS(RR_Ciclo,cicloCorrente,RR_Stato,"Radar*",RR_Esito,"Variato")&" · "&COUNTIFS(RR_Ciclo,cicloCorrente,RR_Stato,"Radar*",RR_Esito,"Nuovo") -> 2 · 0 | J5: =COUNTIFS(KRI_Ciclo,cicloCorrente,KRI_In_Vigore,"Sì",KRI_Stato,"Rosso") -> 2 | M5: =IF(decisioniDaPrendere>0,decisioniDaPrendere,"✓") -> 55 | T5: =IF(Radar_Mosca!$AA$5="Attivazione",Radar_Mosca!$A$5,"") -> NFR-01 | BH5: =2*PI()*0/72 -> 0 | BI5: =2*SIN($BH5) -> 0 | BJ5: =2*COS($BH5) -> 2 | BK5: =3*SIN($BH5) -> 0 | BL5: =3*COS($BH5) -> 3 | BM5: =4*SIN($BH5) -> 0 | BN5: =4*COS($BH5) -> 4 | BO5: =5*SIN($BH5) -> 0 | BP5: =5*COS($BH5) -> 5 | BR5: 0 | BS5: 0 | BU5: 9.1 Condotta | BV5: =6.95*SIN(2*PI()*(0+0.5)/ROWS(codiciL1)) -> 2.37704 | BW5: =6.95*COS(2*PI()*(0+0.5)/ROWS(codiciL1)) -> 6.5308637 | BY5: =IF(AND(ISNUMBER(Radar_Mosca!$F5),ISNUMBER(Radar_Mosca!$S5)),IF(AND(Radar_Mosca!$F5=BY$4,Radar_Mosca!$AA5=BY$3),Radar_Mosca!$S5,NA()),NA()) -> #N/A | BZ5: =IF(AND(ISNUMBER(Radar_Mosca!$F5),ISNUMBER(Radar_Mosca!$S5)),IF(AND(Radar_Mosca!$F5=BZ$4,Radar_Mosca!$AA5=BZ$3),Radar_Mosca!$S5,NA()),NA()) -> #N/A | CA5: =IF(AND(ISNUMBER(Radar_Mosca!$F5),ISNUMBER(Radar_Mosca!$S5)),IF(AND(Radar_Mosca!$F5=CA$4,Radar_Mosca!$AA5=CA$3),Radar_Mosca!$S5,NA()),NA()) -> #N/A | CB5: =IF(AND(ISNUMBER(Radar_Mosca!$F5),ISNUMBER(Radar_Mosca!$S5)),IF(AND(Radar_Mosca!$F5=CB$4,Radar_Mosca!$AA5=CB$3),Radar_Mosca!$S5,NA()),NA()) -> #N/A | CC5: =IF(AND(ISNUMBER(Radar_Mosca!$F5),ISNUMBER(Radar_Mosca!$S5)),IF(AND(Radar_Mosca!$F5=CC$4,Radar_Mosca!$AA5=CC$3),Radar_Mosca!$S5,NA()),NA()) -> #N/A | CD5: =IF(AND(ISNUMBER(Radar_Mosca!$F5),ISNUMBER(Radar_Mosca!$S5)),IF(AND(Radar_Mosca!$F5=CD$4,Radar_Mosca!$AA5=CD$3),Radar_Mosca!$S5,NA()),NA()) -> #N/A | CE5: =IF(AND(ISNUMBER(Radar_Mosca!$F5),ISNUMBER(Radar_Mosca!$S5)),IF(AND(Radar_Mosca!$F5=CE$4,Radar_Mosca!$AA5=CE$3),Radar_Mosca!$S5,NA()),NA()) -> #N/A | CF5: =IF(AND(ISNUMBER(Radar_Mosca!$F5),ISNUMBER(Radar_Mosca!$S5)),IF(AND(Radar_Mosca!$F5=CF$4,Radar_Mosca!$AA5=CF$3),Radar_Mosca!$S5,NA()),NA()) -> #N/A | ... DN5: =IF(AND(ISNUMBER(Radar_Mosca!$F5),ISNUMBER(Radar_Mosca!$S5)),IF(AND(Radar_Mosca!$F5=DN$4,Radar_Mosca!$AA5=DN$3),Radar_Mosca!$S5,NA()),NA()) -> #N/A | DO5: =IF(ISNUMBER(Radar_Mosca!$R5),Radar_Mosca!$R5,NA()) -> 0.34592381 | DP5: =IF(Radar_Mosca!$A5="","",MID(Radar_Mosca!$A5,5,3)&IF(Radar_Mosca!$T5="Sì"," ◆","")) -> 01 ◆ | DQ5: =IF(ISNUMBER(Radar_Mosca!$S5),Radar_Mosca!$S5,NA()) -> -1.4595673 | DR5: Attivazione | DS5: -7 | DT5: -8.05
A6: ="su "&coperturaAnagrafica&" in anagrafica · "&IF(coperturaValutati=coperturaAnagrafica,"completo","INCOMPLETO") -> su 13 in anagrafica · completo | D6: =IF($T$4=0,"nessun rischio in attivazione","in attivazione: "&_xlfn.TEXTJOIN(", ",TRUE,$T$5:$T$24))&" · in monitoraggio "&COUNTIF(Radar_Mosca!$AA$5:$AA$24,"Monitoraggio") -> in attivazione: NFR-01, NFR-11 · in monitoraggio 6 | G6: ="rispetto al "&cicloPrecedente&" · entrati nel radar "&COUNTIFS(RR_Ciclo,cicloCorrente,RR_Movimento,"Entrato")&", usciti "&COUNTIFS(RR_Ciclo,cicloCorrente,RR_Movimento,"Uscito")&" · in osservazione "&COUNTIFS(RR_Ciclo,cicloCorrente,RR_Stato,"Osservazione") -> rispetto al 2026Q3 · entrati nel radar 1, usciti 0 · in osservazione 3 | J6: ="su "&COUNTIFS(KRI_Ciclo,cicloCorrente,KRI_In_Vigore,"Sì")&" in vigore" -> su 26 in vigore | M6: =IF(decisioniDaPrendere>0,"righe da validare: ciclo non validato","ciclo validato") -> righe da validare: ciclo non validato | T6: =IF(Radar_Mosca!$AA$6="Attivazione",Radar_Mosca!$A$6,"") | BH6: =2*PI()*1/72 -> 0.087266463 | BI6: =2*SIN($BH6) -> 0.17431149 | BJ6: =2*COS($BH6) -> 1.9923894 | BK6: =3*SIN($BH6) -> 0.26146723 | BL6: =3*COS($BH6) -> 2.9885841 | BM6: =4*SIN($BH6) -> 0.34862297 | BN6: =4*COS($BH6) -> 3.9847788 | BO6: =5*SIN($BH6) -> 0.43577871 | BP6: =5*COS($BH6) -> 4.9809735 | BR6: =6.3*SIN(2*PI()*0/ROWS(codiciL1)) -> 0 | BS6: =6.3*COS(2*PI()*0/ROWS(codiciL1)) -> 6.3 | BU6: 9.4 Legale | BV6: =6.95*SIN(2*PI()*(1+0.5)/ROWS(codiciL1)) -> 6.0188766 | BW6: =6.95*COS(2*PI()*(1+0.5)/ROWS(codiciL1)) -> 3.475 | BY6: =IF(AND(ISNUMBER(Radar_Mosca!$F6),ISNUMBER(Radar_Mosca!$S6)),IF(AND(Radar_Mosca!$F6=BY$4,Radar_Mosca!$AA6=BY$3),Radar_Mosca!$S6,NA()),NA()) -> #N/A | BZ6: =IF(AND(ISNUMBER(Radar_Mosca!$F6),ISNUMBER(Radar_Mosca!$S6)),IF(AND(Radar_Mosca!$F6=BZ$4,Radar_Mosca!$AA6=BZ$3),Radar_Mosca!$S6,NA()),NA()) -> #N/A | CA6: =IF(AND(ISNUMBER(Radar_Mosca!$F6),ISNUMBER(Radar_Mosca!$S6)),IF(AND(Radar_Mosca!$F6=CA$4,Radar_Mosca!$AA6=CA$3),Radar_Mosca!$S6,NA()),NA()) -> #N/A | CB6: =IF(AND(ISNUMBER(Radar_Mosca!$F6),ISNUMBER(Radar_Mosca!$S6)),IF(AND(Radar_Mosca!$F6=CB$4,Radar_Mosca!$AA6=CB$3),Radar_Mosca!$S6,NA()),NA()) -> #N/A | CC6: =IF(AND(ISNUMBER(Radar_Mosca!$F6),ISNUMBER(Radar_Mosca!$S6)),IF(AND(Radar_Mosca!$F6=CC$4,Radar_Mosca!$AA6=CC$3),Radar_Mosca!$S6,NA()),NA()) -> #N/A | CD6: =IF(AND(ISNUMBER(Radar_Mosca!$F6),ISNUMBER(Radar_Mosca!$S6)),IF(AND(Radar_Mosca!$F6=CD$4,Radar_Mosca!$AA6=CD$3),Radar_Mosca!$S6,NA()),NA()) -> #N/A | CE6: =IF(AND(ISNUMBER(Radar_Mosca!$F6),ISNUMBER(Radar_Mosca!$S6)),IF(AND(Radar_Mosca!$F6=CE$4,Radar_Mosca!$AA6=CE$3),Radar_Mosca!$S6,NA()),NA()) -> #N/A | CF6: =IF(AND(ISNUMBER(Radar_Mosca!$F6),ISNUMBER(Radar_Mosca!$S6)),IF(AND(Radar_Mosca!$F6=CF$4,Radar_Mosca!$AA6=CF$3),Radar_Mosca!$S6,NA()),NA()) -> #N/A | ... DN6: =IF(AND(ISNUMBER(Radar_Mosca!$F6),ISNUMBER(Radar_Mosca!$S6)),IF(AND(Radar_Mosca!$F6=DN$4,Radar_Mosca!$AA6=DN$3),Radar_Mosca!$S6,NA()),NA()) -> #N/A | DO6: =IF(ISNUMBER(Radar_Mosca!$R6),Radar_Mosca!$R6,NA()) -> -2.8190779 | DP6: =IF(Radar_Mosca!$A6="","",MID(Radar_Mosca!$A6,5,3)&IF(Radar_Mosca!$T6="Sì"," ◆","")) -> 02 ◆ | DQ6: =IF(ISNUMBER(Radar_Mosca!$S6),Radar_Mosca!$S6,NA()) -> -1.0260604 | DR6: Attenzione | DS6: 0.3 | DT6: -8.05
T7: =IF(Radar_Mosca!$AA$7="Attivazione",Radar_Mosca!$A$7,"") | BH7: =2*PI()*2/72 -> 0.17453293 | BI7: =2*SIN($BH7) -> 0.34729636 | BJ7: =2*COS($BH7) -> 1.9696155 | BK7: =3*SIN($BH7) -> 0.52094453 | BL7: =3*COS($BH7) -> 2.9544233 | BM7: =4*SIN($BH7) -> 0.69459271 | BN7: =4*COS($BH7) -> 3.939231 | BO7: =5*SIN($BH7) -> 0.86824089 | BP7: =5*COS($BH7) -> 4.9240388 | BR7: 0 | BS7: 0 | BU7: 9.5 Fiscale | BV7: =6.95*SIN(2*PI()*(2+0.5)/ROWS(codiciL1)) -> 6.8444139 | BW7: =6.95*COS(2*PI()*(2+0.5)/ROWS(codiciL1)) -> -1.2068548 | BY7: =IF(AND(ISNUMBER(Radar_Mosca!$F7),ISNUMBER(Radar_Mosca!$S7)),IF(AND(Radar_Mosca!$F7=BY$4,Radar_Mosca!$AA7=BY$3),Radar_Mosca!$S7,NA()),NA()) -> #N/A | BZ7: =IF(AND(ISNUMBER(Radar_Mosca!$F7),ISNUMBER(Radar_Mosca!$S7)),IF(AND(Radar_Mosca!$F7=BZ$4,Radar_Mosca!$AA7=BZ$3),Radar_Mosca!$S7,NA()),NA()) -> #N/A | CA7: =IF(AND(ISNUMBER(Radar_Mosca!$F7),ISNUMBER(Radar_Mosca!$S7)),IF(AND(Radar_Mosca!$F7=CA$4,Radar_Mosca!$AA7=CA$3),Radar_Mosca!$S7,NA()),NA()) -> #N/A | CB7: =IF(AND(ISNUMBER(Radar_Mosca!$F7),ISNUMBER(Radar_Mosca!$S7)),IF(AND(Radar_Mosca!$F7=CB$4,Radar_Mosca!$AA7=CB$3),Radar_Mosca!$S7,NA()),NA()) -> #N/A | CC7: =IF(AND(ISNUMBER(Radar_Mosca!$F7),ISNUMBER(Radar_Mosca!$S7)),IF(AND(Radar_Mosca!$F7=CC$4,Radar_Mosca!$AA7=CC$3),Radar_Mosca!$S7,NA()),NA()) -> #N/A | CD7: =IF(AND(ISNUMBER(Radar_Mosca!$F7),ISNUMBER(Radar_Mosca!$S7)),IF(AND(Radar_Mosca!$F7=CD$4,Radar_Mosca!$AA7=CD$3),Radar_Mosca!$S7,NA()),NA()) -> #N/A | CE7: =IF(AND(ISNUMBER(Radar_Mosca!$F7),ISNUMBER(Radar_Mosca!$S7)),IF(AND(Radar_Mosca!$F7=CE$4,Radar_Mosca!$AA7=CE$3),Radar_Mosca!$S7,NA()),NA()) -> #N/A | CF7: =IF(AND(ISNUMBER(Radar_Mosca!$F7),ISNUMBER(Radar_Mosca!$S7)),IF(AND(Radar_Mosca!$F7=CF$4,Radar_Mosca!$AA7=CF$3),Radar_Mosca!$S7,NA()),NA()) -> #N/A | ... DN7: =IF(AND(ISNUMBER(Radar_Mosca!$F7),ISNUMBER(Radar_Mosca!$S7)),IF(AND(Radar_Mosca!$F7=DN$4,Radar_Mosca!$AA7=DN$3),Radar_Mosca!$S7,NA()),NA()) -> #N/A | DO7: =IF(ISNUMBER(Radar_Mosca!$R7),Radar_Mosca!$R7,NA()) -> 0.34729636 | DP7: =IF(Radar_Mosca!$A7="","",MID(Radar_Mosca!$A7,5,3)&IF(Radar_Mosca!$T7="Sì"," ◆","")) -> 03 | DQ7: =IF(ISNUMBER(Radar_Mosca!$S7),Radar_Mosca!$S7,NA()) -> 1.9696155 | DR7: Monitoraggio | DS7: -7 | DT7: -9.4
A8: Priorita' — primi cinque per score composito | J8: Gravita': Probabilita x Impatto | T8: =IF(Radar_Mosca!$AA$8="Attivazione",Radar_Mosca!$A$8,"") | BH8: =2*PI()*3/72 -> 0.26179939 | BI8: =2*SIN($BH8) -> 0.51763809 | BJ8: =2*COS($BH8) -> 1.9318517 | BK8: =3*SIN($BH8) -> 0.77645714 | BL8: =3*COS($BH8) -> 2.8977775 | BM8: =4*SIN($BH8) -> 1.0352762 | BN8: =4*COS($BH8) -> 3.8637033 | BO8: =5*SIN($BH8) -> 1.2940952 | BP8: =5*COS($BH8) -> 4.8296291 | BR8: =6.3*SIN(2*PI()*1/ROWS(codiciL1)) -> 4.0495619 | BS8: =6.3*COS(2*PI()*1/ROWS(codiciL1)) -> 4.82608 | BU8: 9.6 Tecnologico | BV8: =6.95*SIN(2*PI()*(3+0.5)/ROWS(codiciL1)) -> 4.4673739 | BW8: =6.95*COS(2*PI()*(3+0.5)/ROWS(codiciL1)) -> -5.3240089 | BY8: =IF(AND(ISNUMBER(Radar_Mosca!$F8),ISNUMBER(Radar_Mosca!$S8)),IF(AND(Radar_Mosca!$F8=BY$4,Radar_Mosca!$AA8=BY$3),Radar_Mosca!$S8,NA()),NA()) -> #N/A | BZ8: =IF(AND(ISNUMBER(Radar_Mosca!$F8),ISNUMBER(Radar_Mosca!$S8)),IF(AND(Radar_Mosca!$F8=BZ$4,Radar_Mosca!$AA8=BZ$3),Radar_Mosca!$S8,NA()),NA()) -> #N/A | CA8: =IF(AND(ISNUMBER(Radar_Mosca!$F8),ISNUMBER(Radar_Mosca!$S8)),IF(AND(Radar_Mosca!$F8=CA$4,Radar_Mosca!$AA8=CA$3),Radar_Mosca!$S8,NA()),NA()) -> #N/A | CB8: =IF(AND(ISNUMBER(Radar_Mosca!$F8),ISNUMBER(Radar_Mosca!$S8)),IF(AND(Radar_Mosca!$F8=CB$4,Radar_Mosca!$AA8=CB$3),Radar_Mosca!$S8,NA()),NA()) -> #N/A | CC8: =IF(AND(ISNUMBER(Radar_Mosca!$F8),ISNUMBER(Radar_Mosca!$S8)),IF(AND(Radar_Mosca!$F8=CC$4,Radar_Mosca!$AA8=CC$3),Radar_Mosca!$S8,NA()),NA()) -> #N/A | CD8: =IF(AND(ISNUMBER(Radar_Mosca!$F8),ISNUMBER(Radar_Mosca!$S8)),IF(AND(Radar_Mosca!$F8=CD$4,Radar_Mosca!$AA8=CD$3),Radar_Mosca!$S8,NA()),NA()) -> #N/A | CE8: =IF(AND(ISNUMBER(Radar_Mosca!$F8),ISNUMBER(Radar_Mosca!$S8)),IF(AND(Radar_Mosca!$F8=CE$4,Radar_Mosca!$AA8=CE$3),Radar_Mosca!$S8,NA()),NA()) -> #N/A | CF8: =IF(AND(ISNUMBER(Radar_Mosca!$F8),ISNUMBER(Radar_Mosca!$S8)),IF(AND(Radar_Mosca!$F8=CF$4,Radar_Mosca!$AA8=CF$3),Radar_Mosca!$S8,NA()),NA()) -> #N/A | ... DN8: =IF(AND(ISNUMBER(Radar_Mosca!$F8),ISNUMBER(Radar_Mosca!$S8)),IF(AND(Radar_Mosca!$F8=DN$4,Radar_Mosca!$AA8=DN$3),Radar_Mosca!$S8,NA()),NA()) -> #N/A | DO8: =IF(ISNUMBER(Radar_Mosca!$R8),Radar_Mosca!$R8,NA()) -> -1.7676659 | DP8: =IF(Radar_Mosca!$A8="","",MID(Radar_Mosca!$A8,5,3)&IF(Radar_Mosca!$T8="Sì"," ◆","")) -> 04 | DQ8: =IF(ISNUMBER(Radar_Mosca!$S8),Radar_Mosca!$S8,NA()) -> -2.1066222 | DR8: AGIRE ORA (X+Y>Z) | DS8: -0.15 | DT8: -9.4
A9: # | B9: Rischio | F9: Score | G9: Variazione | H9: Urgenza | J9: P \ S | K9: 1 | L9: 2 | M9: 3 | N9: 4 | O9: 5 | T9: =IF(Radar_Mosca!$AA$9="Attivazione",Radar_Mosca!$A$9,"") | BH9: =2*PI()*4/72 -> 0.34906585 | BI9: =2*SIN($BH9) -> 0.68404029 | BJ9: =2*COS($BH9) -> 1.8793852 | BK9: =3*SIN($BH9) -> 1.0260604 | BL9: =3*COS($BH9) -> 2.8190779 | BM9: =4*SIN($BH9) -> 1.3680806 | BN9: =4*COS($BH9) -> 3.7587705 | BO9: =5*SIN($BH9) -> 1.7101007 | BP9: =5*COS($BH9) -> 4.6984631 | BR9: 0 | BS9: 0 | BU9: 9.7 Sicurezza informatica | BV9: =6.95*SIN(2*PI()*(4+0.5)/ROWS(codiciL1)) -> 8.5147818e-16 | BW9: =6.95*COS(2*PI()*(4+0.5)/ROWS(codiciL1)) -> -6.95 | BY9: =IF(AND(ISNUMBER(Radar_Mosca!$F9),ISNUMBER(Radar_Mosca!$S9)),IF(AND(Radar_Mosca!$F9=BY$4,Radar_Mosca!$AA9=BY$3),Radar_Mosca!$S9,NA()),NA()) -> #N/A | BZ9: =IF(AND(ISNUMBER(Radar_Mosca!$F9),ISNUMBER(Radar_Mosca!$S9)),IF(AND(Radar_Mosca!$F9=BZ$4,Radar_Mosca!$AA9=BZ$3),Radar_Mosca!$S9,NA()),NA()) -> #N/A | CA9: =IF(AND(ISNUMBER(Radar_Mosca!$F9),ISNUMBER(Radar_Mosca!$S9)),IF(AND(Radar_Mosca!$F9=CA$4,Radar_Mosca!$AA9=CA$3),Radar_Mosca!$S9,NA()),NA()) -> #N/A | CB9: =IF(AND(ISNUMBER(Radar_Mosca!$F9),ISNUMBER(Radar_Mosca!$S9)),IF(AND(Radar_Mosca!$F9=CB$4,Radar_Mosca!$AA9=CB$3),Radar_Mosca!$S9,NA()),NA()) -> #N/A | CC9: =IF(AND(ISNUMBER(Radar_Mosca!$F9),ISNUMBER(Radar_Mosca!$S9)),IF(AND(Radar_Mosca!$F9=CC$4,Radar_Mosca!$AA9=CC$3),Radar_Mosca!$S9,NA()),NA()) -> #N/A | CD9: =IF(AND(ISNUMBER(Radar_Mosca!$F9),ISNUMBER(Radar_Mosca!$S9)),IF(AND(Radar_Mosca!$F9=CD$4,Radar_Mosca!$AA9=CD$3),Radar_Mosca!$S9,NA()),NA()) -> #N/A | CE9: =IF(AND(ISNUMBER(Radar_Mosca!$F9),ISNUMBER(Radar_Mosca!$S9)),IF(AND(Radar_Mosca!$F9=CE$4,Radar_Mosca!$AA9=CE$3),Radar_Mosca!$S9,NA()),NA()) -> #N/A | CF9: =IF(AND(ISNUMBER(Radar_Mosca!$F9),ISNUMBER(Radar_Mosca!$S9)),IF(AND(Radar_Mosca!$F9=CF$4,Radar_Mosca!$AA9=CF$3),Radar_Mosca!$S9,NA()),NA()) -> #N/A | ... DN9: =IF(AND(ISNUMBER(Radar_Mosca!$F9),ISNUMBER(Radar_Mosca!$S9)),IF(AND(Radar_Mosca!$F9=DN$4,Radar_Mosca!$AA9=DN$3),Radar_Mosca!$S9,NA()),NA()) -> #N/A | DO9: =IF(ISNUMBER(Radar_Mosca!$R9),Radar_Mosca!$R9,NA()) -> -1.5 | DP9: =IF(Radar_Mosca!$A9="","",MID(Radar_Mosca!$A9,5,3)&IF(Radar_Mosca!$T9="Sì"," ◆","")) -> 05 | DQ9: =IF(ISNUMBER(Radar_Mosca!$S9),Radar_Mosca!$S9,NA()) -> 2.5980762 | DS9: 0.75 | DT9: -9.4
A10: =Classifica!$A$5 -> 1 | B10: =IF(Classifica!$B$5="","",Classifica!$B$5&" "&Classifica!$C$5&IFERROR(IF(INDEX(ANA_Attenzione_Supervisore,Classifica!$U$5)="Sì"," ◆",""),"")) -> NFR-01 Frodi su pagamenti istantanei abilitate da AI generativa ◆ | F10: =IF(Classifica!$B$5="","",Classifica!$D$5) -> 4.4 | G10: =IF(Classifica!$B$5="","",IF(ISNUMBER(Classifica!$F$5),Classifica!$F$5,"nuovo")) -> 0.2 | H10: =IF(Classifica!$B$5="","",IF(LEFT(Classifica!$H$5,9)="AGIRE ORA","AGIRE ORA",IF(LEFT(Classifica!$H$5,11)="Agire entro","Entro l'anno",Classifica!$H$5))) -> AGIRE ORA | J10: 5 | K10: =SUBSTITUTE(SUBSTITUTE(Matrice!C5," ◆",""),"NFR-","") | L10: =SUBSTITUTE(SUBSTITUTE(Matrice!D5," ◆",""),"NFR-","") | M10: =SUBSTITUTE(SUBSTITUTE(Matrice!E5," ◆",""),"NFR-","") | N10: =SUBSTITUTE(SUBSTITUTE(Matrice!F5," ◆",""),"NFR-","") | O10: =SUBSTITUTE(SUBSTITUTE(Matrice!G5," ◆",""),"NFR-","") | T10: =IF(Radar_Mosca!$AA$10="Attivazione",Radar_Mosca!$A$10,"") | BH10: =2*PI()*5/72 -> 0.43633231 | BI10: =2*SIN($BH10) -> 0.84523652 | BJ10: =2*COS($BH10) -> 1.8126156 | BK10: =3*SIN($BH10) -> 1.2678548 | BL10: =3*COS($BH10) -> 2.7189234 | BM10: =4*SIN($BH10) -> 1.690473 | BN10: =4*COS($BH10) -> 3.6252311 | BO10: =5*SIN($BH10) -> 2.1130913 | BP10: =5*COS($BH10) -> 4.5315389 | BR10: =6.3*SIN(2*PI()*2/ROWS(codiciL1)) -> 6.2042888 | BS10: =6.3*COS(2*PI()*2/ROWS(codiciL1)) -> 1.0939835 | BU10: 9.8 Sicurezza fisica | BV10: =6.95*SIN(2*PI()*(5+0.5)/ROWS(codiciL1)) -> -4.4673739 | BW10: =6.95*COS(2*PI()*(5+0.5)/ROWS(codiciL1)) -> -5.3240089 | BY10: =IF(AND(ISNUMBER(Radar_Mosca!$F10),ISNUMBER(Radar_Mosca!$S10)),IF(AND(Radar_Mosca!$F10=BY$4,Radar_Mosca!$AA10=BY$3),Radar_Mosca!$S10,NA()),NA()) -> #N/A | BZ10: =IF(AND(ISNUMBER(Radar_Mosca!$F10),ISNUMBER(Radar_Mosca!$S10)),IF(AND(Radar_Mosca!$F10=BZ$4,Radar_Mosca!$AA10=BZ$3),Radar_Mosca!$S10,NA()),NA()) -> #N/A | CA10: =IF(AND(ISNUMBER(Radar_Mosca!$F10),ISNUMBER(Radar_Mosca!$S10)),IF(AND(Radar_Mosca!$F10=CA$4,Radar_Mosca!$AA10=CA$3),Radar_Mosca!$S10,NA()),NA()) -> #N/A | CB10: =IF(AND(ISNUMBER(Radar_Mosca!$F10),ISNUMBER(Radar_Mosca!$S10)),IF(AND(Radar_Mosca!$F10=CB$4,Radar_Mosca!$AA10=CB$3),Radar_Mosca!$S10,NA()),NA()) -> #N/A | CC10: =IF(AND(ISNUMBER(Radar_Mosca!$F10),ISNUMBER(Radar_Mosca!$S10)),IF(AND(Radar_Mosca!$F10=CC$4,Radar_Mosca!$AA10=CC$3),Radar_Mosca!$S10,NA()),NA()) -> #N/A | CD10: =IF(AND(ISNUMBER(Radar_Mosca!$F10),ISNUMBER(Radar_Mosca!$S10)),IF(AND(Radar_Mosca!$F10=CD$4,Radar_Mosca!$AA10=CD$3),Radar_Mosca!$S10,NA()),NA()) -> #N/A | CE10: =IF(AND(ISNUMBER(Radar_Mosca!$F10),ISNUMBER(Radar_Mosca!$S10)),IF(AND(Radar_Mosca!$F10=CE$4,Radar_Mosca!$AA10=CE$3),Radar_Mosca!$S10,NA()),NA()) -> #N/A | CF10: =IF(AND(ISNUMBER(Radar_Mosca!$F10),ISNUMBER(Radar_Mosca!$S10)),IF(AND(Radar_Mosca!$F10=CF$4,Radar_Mosca!$AA10=CF$3),Radar_Mosca!$S10,NA()),NA()) -> #N/A | ... DN10: =IF(AND(ISNUMBER(Radar_Mosca!$F10),ISNUMBER(Radar_Mosca!$S10)),IF(AND(Radar_Mosca!$F10=DN$4,Radar_Mosca!$AA10=DN$3),Radar_Mosca!$S10,NA()),NA()) -> #N/A | DO10: =IF(ISNUMBER(Radar_Mosca!$R10),Radar_Mosca!$R10,NA()) -> 2.756584e-16 | DP10: =IF(Radar_Mosca!$A10="","",MID(Radar_Mosca!$A10,5,3)&IF(Radar_Mosca!$T10="Sì"," ◆","")) -> 06 | DQ10: =IF(ISNUMBER(Radar_Mosca!$S10),Radar_Mosca!$S10,NA()) -> -2.25 | DR10: Area del cerchio = P x I | DS10: 4.4 | DT10: -8.05
A11: =Classifica!$A$6 -> 2 | B11: =IF(Classifica!$B$6="","",Classifica!$B$6&" "&Classifica!$C$6&IFERROR(IF(INDEX(ANA_Attenzione_Supervisore,Classifica!$U$6)="Sì"," ◆",""),"")) -> NFR-07 Ransomware presso un fornitore di servizi di pagamento ◆ | F11: =IF(Classifica!$B$6="","",Classifica!$D$6) -> 3.75 | G11: =IF(Classifica!$B$6="","",IF(ISNUMBER(Classifica!$F$6),Classifica!$F$6,"nuovo")) -> 0 | H11: =IF(Classifica!$B$6="","",IF(LEFT(Classifica!$H$6,9)="AGIRE ORA","AGIRE ORA",IF(LEFT(Classifica!$H$6,11)="Agire entro","Entro l'anno",Classifica!$H$6))) -> Entro l'anno | J11: 4 | K11: =SUBSTITUTE(SUBSTITUTE(Matrice!C6," ◆",""),"NFR-","") | L11: =SUBSTITUTE(SUBSTITUTE(Matrice!D6," ◆",""),"NFR-","") | M11: =SUBSTITUTE(SUBSTITUTE(Matrice!E6," ◆",""),"NFR-","") -> 12 | N11: =SUBSTITUTE(SUBSTITUTE(Matrice!F6," ◆",""),"NFR-","") -> 01 | O11: =SUBSTITUTE(SUBSTITUTE(Matrice!G6," ◆",""),"NFR-","") | T11: =IF(Radar_Mosca!$AA$11="Attivazione",Radar_Mosca!$A$11,"") | BH11: =2*PI()*6/72 -> 0.52359878 | BI11: =2*SIN($BH11) -> 1 | BJ11: =2*COS($BH11) -> 1.7320508 | BK11: =3*SIN($BH11) -> 1.5 | BL11: =3*COS($BH11) -> 2.5980762 | BM11: =4*SIN($BH11) -> 2 | BN11: =4*COS($BH11) -> 3.4641016 | BO11: =5*SIN($BH11) -> 2.5 | BP11: =5*COS($BH11) -> 4.330127 | BR11: 0 | BS11: 0 | BU11: 9.9 Terze parti | BV11: =6.95*SIN(2*PI()*(6+0.5)/ROWS(codiciL1)) -> -6.8444139 | BW11: =6.95*COS(2*PI()*(6+0.5)/ROWS(codiciL1)) -> -1.2068548 | BY11: =IF(AND(ISNUMBER(Radar_Mosca!$F11),ISNUMBER(Radar_Mosca!$S11)),IF(AND(Radar_Mosca!$F11=BY$4,Radar_Mosca!$AA11=BY$3),Radar_Mosca!$S11,NA()),NA()) -> #N/A | BZ11: =IF(AND(ISNUMBER(Radar_Mosca!$F11),ISNUMBER(Radar_Mosca!$S11)),IF(AND(Radar_Mosca!$F11=BZ$4,Radar_Mosca!$AA11=BZ$3),Radar_Mosca!$S11,NA()),NA()) -> #N/A | CA11: =IF(AND(ISNUMBER(Radar_Mosca!$F11),ISNUMBER(Radar_Mosca!$S11)),IF(AND(Radar_Mosca!$F11=CA$4,Radar_Mosca!$AA11=CA$3),Radar_Mosca!$S11,NA()),NA()) -> #N/A | CB11: =IF(AND(ISNUMBER(Radar_Mosca!$F11),ISNUMBER(Radar_Mosca!$S11)),IF(AND(Radar_Mosca!$F11=CB$4,Radar_Mosca!$AA11=CB$3),Radar_Mosca!$S11,NA()),NA()) -> #N/A | CC11: =IF(AND(ISNUMBER(Radar_Mosca!$F11),ISNUMBER(Radar_Mosca!$S11)),IF(AND(Radar_Mosca!$F11=CC$4,Radar_Mosca!$AA11=CC$3),Radar_Mosca!$S11,NA()),NA()) -> #N/A | CD11: =IF(AND(ISNUMBER(Radar_Mosca!$F11),ISNUMBER(Radar_Mosca!$S11)),IF(AND(Radar_Mosca!$F11=CD$4,Radar_Mosca!$AA11=CD$3),Radar_Mosca!$S11,NA()),NA()) -> #N/A | CE11: =IF(AND(ISNUMBER(Radar_Mosca!$F11),ISNUMBER(Radar_Mosca!$S11)),IF(AND(Radar_Mosca!$F11=CE$4,Radar_Mosca!$AA11=CE$3),Radar_Mosca!$S11,NA()),NA()) -> #N/A | CF11: =IF(AND(ISNUMBER(Radar_Mosca!$F11),ISNUMBER(Radar_Mosca!$S11)),IF(AND(Radar_Mosca!$F11=CF$4,Radar_Mosca!$AA11=CF$3),Radar_Mosca!$S11,NA()),NA()) -> #N/A | ... DN11: =IF(AND(ISNUMBER(Radar_Mosca!$F11),ISNUMBER(Radar_Mosca!$S11)),IF(AND(Radar_Mosca!$F11=DN$4,Radar_Mosca!$AA11=DN$3),Radar_Mosca!$S11,NA()),NA()) -> #N/A | DO11: =IF(ISNUMBER(Radar_Mosca!$R11),Radar_Mosca!$R11,NA()) -> -2.75 | DP11: =IF(Radar_Mosca!$A11="","",MID(Radar_Mosca!$A11,5,3)&IF(Radar_Mosca!$T11="Sì"," ◆","")) -> 07 ◆ | DQ11: =IF(ISNUMBER(Radar_Mosca!$S11),Radar_Mosca!$S11,NA()) -> -5.0537374e-16 | DR11: 4 | DS11: 3.5 | DT11: -9.1
A12: =Classifica!$A$7 -> 3 | B12: =IF(Classifica!$B$7="","",Classifica!$B$7&" "&Classifica!$C$7&IFERROR(IF(INDEX(ANA_Attenzione_Supervisore,Classifica!$U$7)="Sì"," ◆",""),"")) -> NFR-12 Errori operativi nei pagamenti istantanei obbligatori | F12: =IF(Classifica!$B$7="","",Classifica!$D$7) -> 3.65 | G12: =IF(Classifica!$B$7="","",IF(ISNUMBER(Classifica!$F$7),Classifica!$F$7,"nuovo")) -> 0 | H12: =IF(Classifica!$B$7="","",IF(LEFT(Classifica!$H$7,9)="AGIRE ORA","AGIRE ORA",IF(LEFT(Classifica!$H$7,11)="Agire entro","Entro l'anno",Classifica!$H$7))) -> Entro l'anno | J12: 3 | K12: =SUBSTITUTE(SUBSTITUTE(Matrice!C7," ◆",""),"NFR-","") | L12: =SUBSTITUTE(SUBSTITUTE(Matrice!D7," ◆",""),"NFR-","") | M12: =SUBSTITUTE(SUBSTITUTE(Matrice!E7," ◆",""),"NFR-","") -> 03 04 05 06 10 11 16 | N12: =SUBSTITUTE(SUBSTITUTE(Matrice!F7," ◆",""),"NFR-","") -> 07 | O12: =SUBSTITUTE(SUBSTITUTE(Matrice!G7," ◆",""),"NFR-","") | T12: =IF(Radar_Mosca!$AA$12="Attivazione",Radar_Mosca!$A$12,"") | BH12: =2*PI()*7/72 -> 0.61086524 | BI12: =2*SIN($BH12) -> 1.1471529 | BJ12: =2*COS($BH12) -> 1.6383041 | BK12: =3*SIN($BH12) -> 1.7207293 | BL12: =3*COS($BH12) -> 2.4574561 | BM12: =4*SIN($BH12) -> 2.2943057 | BN12: =4*COS($BH12) -> 3.2766082 | BO12: =5*SIN($BH12) -> 2.8678822 | BP12: =5*COS($BH12) -> 4.0957602 | BR12: =6.3*SIN(2*PI()*3/ROWS(codiciL1)) -> 5.45596 | BS12: =6.3*COS(2*PI()*3/ROWS(codiciL1)) -> -3.15 | BU12: 9.11 Employer | BV12: =6.95*SIN(2*PI()*(7+0.5)/ROWS(codiciL1)) -> -6.0188766 | BW12: =6.95*COS(2*PI()*(7+0.5)/ROWS(codiciL1)) -> 3.475 | BY12: =IF(AND(ISNUMBER(Radar_Mosca!$F12),ISNUMBER(Radar_Mosca!$S12)),IF(AND(Radar_Mosca!$F12=BY$4,Radar_Mosca!$AA12=BY$3),Radar_Mosca!$S12,NA()),NA()) -> #N/A | BZ12: =IF(AND(ISNUMBER(Radar_Mosca!$F12),ISNUMBER(Radar_Mosca!$S12)),IF(AND(Radar_Mosca!$F12=BZ$4,Radar_Mosca!$AA12=BZ$3),Radar_Mosca!$S12,NA()),NA()) -> #N/A | CA12: =IF(AND(ISNUMBER(Radar_Mosca!$F12),ISNUMBER(Radar_Mosca!$S12)),IF(AND(Radar_Mosca!$F12=CA$4,Radar_Mosca!$AA12=CA$3),Radar_Mosca!$S12,NA()),NA()) -> #N/A | CB12: =IF(AND(ISNUMBER(Radar_Mosca!$F12),ISNUMBER(Radar_Mosca!$S12)),IF(AND(Radar_Mosca!$F12=CB$4,Radar_Mosca!$AA12=CB$3),Radar_Mosca!$S12,NA()),NA()) -> #N/A | CC12: =IF(AND(ISNUMBER(Radar_Mosca!$F12),ISNUMBER(Radar_Mosca!$S12)),IF(AND(Radar_Mosca!$F12=CC$4,Radar_Mosca!$AA12=CC$3),Radar_Mosca!$S12,NA()),NA()) -> #N/A | CD12: =IF(AND(ISNUMBER(Radar_Mosca!$F12),ISNUMBER(Radar_Mosca!$S12)),IF(AND(Radar_Mosca!$F12=CD$4,Radar_Mosca!$AA12=CD$3),Radar_Mosca!$S12,NA()),NA()) -> #N/A | CE12: =IF(AND(ISNUMBER(Radar_Mosca!$F12),ISNUMBER(Radar_Mosca!$S12)),IF(AND(Radar_Mosca!$F12=CE$4,Radar_Mosca!$AA12=CE$3),Radar_Mosca!$S12,NA()),NA()) -> #N/A | CF12: =IF(AND(ISNUMBER(Radar_Mosca!$F12),ISNUMBER(Radar_Mosca!$S12)),IF(AND(Radar_Mosca!$F12=CF$4,Radar_Mosca!$AA12=CF$3),Radar_Mosca!$S12,NA()),NA()) -> #N/A | ... DN12: =IF(AND(ISNUMBER(Radar_Mosca!$F12),ISNUMBER(Radar_Mosca!$S12)),IF(AND(Radar_Mosca!$F12=DN$4,Radar_Mosca!$AA12=DN$3),Radar_Mosca!$S12,NA()),NA()) -> #N/A | DO12: =IF(ISNUMBER(Radar_Mosca!$R12),Radar_Mosca!$R12,NA()) -> -0.69184761 | DP12: =IF(Radar_Mosca!$A12="","",MID(Radar_Mosca!$A12,5,3)&IF(Radar_Mosca!$T12="Sì"," ◆","")) -> 08 | DQ12: =IF(ISNUMBER(Radar_Mosca!$S12),Radar_Mosca!$S12,NA()) -> -2.9191346 | DR12: 12 | DS12: 4.8 | DT12: -9.1
A13: =Classifica!$A$8 -> 4 | B13: =IF(Classifica!$B$8="","",Classifica!$B$8&" "&Classifica!$C$8&IFERROR(IF(INDEX(ANA_Attenzione_Supervisore,Classifica!$U$8)="Sì"," ◆",""),"")) -> NFR-02 Concentrazione su un fornitore cloud critico ◆ | F13: =IF(Classifica!$B$8="","",Classifica!$D$8) -> 3.3 | G13: =IF(Classifica!$B$8="","",IF(ISNUMBER(Classifica!$F$8),Classifica!$F$8,"nuovo")) -> 0 | H13: =IF(Classifica!$B$8="","",IF(LEFT(Classifica!$H$8,9)="AGIRE ORA","AGIRE ORA",IF(LEFT(Classifica!$H$8,11)="Agire entro","Entro l'anno",Classifica!$H$8))) -> Margine 1 anno | J13: 2 | K13: =SUBSTITUTE(SUBSTITUTE(Matrice!C8," ◆",""),"NFR-","") | L13: =SUBSTITUTE(SUBSTITUTE(Matrice!D8," ◆",""),"NFR-","") | M13: =SUBSTITUTE(SUBSTITUTE(Matrice!E8," ◆",""),"NFR-","") -> 08 | N13: =SUBSTITUTE(SUBSTITUTE(Matrice!F8," ◆",""),"NFR-","") -> 02 09 | O13: =SUBSTITUTE(SUBSTITUTE(Matrice!G8," ◆",""),"NFR-","") | T13: =IF(Radar_Mosca!$AA$13="Attivazione",Radar_Mosca!$A$13,"") | BH13: =2*PI()*8/72 -> 0.6981317 | BI13: =2*SIN($BH13) -> 1.2855752 | BJ13: =2*COS($BH13) -> 1.5320889 | BK13: =3*SIN($BH13) -> 1.9283628 | BL13: =3*COS($BH13) -> 2.2981333 | BM13: =4*SIN($BH13) -> 2.5711504 | BN13: =4*COS($BH13) -> 3.0641778 | BO13: =5*SIN($BH13) -> 3.213938 | BP13: =5*COS($BH13) -> 3.8302222 | BR13: 0 | BS13: 0 | BU13: 9.13 Processo | BV13: =6.95*SIN(2*PI()*(8+0.5)/ROWS(codiciL1)) -> -2.37704 | BW13: =6.95*COS(2*PI()*(8+0.5)/ROWS(codiciL1)) -> 6.5308637 | BY13: =IF(AND(ISNUMBER(Radar_Mosca!$F13),ISNUMBER(Radar_Mosca!$S13)),IF(AND(Radar_Mosca!$F13=BY$4,Radar_Mosca!$AA13=BY$3),Radar_Mosca!$S13,NA()),NA()) -> #N/A | BZ13: =IF(AND(ISNUMBER(Radar_Mosca!$F13),ISNUMBER(Radar_Mosca!$S13)),IF(AND(Radar_Mosca!$F13=BZ$4,Radar_Mosca!$AA13=BZ$3),Radar_Mosca!$S13,NA()),NA()) -> #N/A | CA13: =IF(AND(ISNUMBER(Radar_Mosca!$F13),ISNUMBER(Radar_Mosca!$S13)),IF(AND(Radar_Mosca!$F13=CA$4,Radar_Mosca!$AA13=CA$3),Radar_Mosca!$S13,NA()),NA()) -> #N/A | CB13: =IF(AND(ISNUMBER(Radar_Mosca!$F13),ISNUMBER(Radar_Mosca!$S13)),IF(AND(Radar_Mosca!$F13=CB$4,Radar_Mosca!$AA13=CB$3),Radar_Mosca!$S13,NA()),NA()) -> #N/A | CC13: =IF(AND(ISNUMBER(Radar_Mosca!$F13),ISNUMBER(Radar_Mosca!$S13)),IF(AND(Radar_Mosca!$F13=CC$4,Radar_Mosca!$AA13=CC$3),Radar_Mosca!$S13,NA()),NA()) -> #N/A | CD13: =IF(AND(ISNUMBER(Radar_Mosca!$F13),ISNUMBER(Radar_Mosca!$S13)),IF(AND(Radar_Mosca!$F13=CD$4,Radar_Mosca!$AA13=CD$3),Radar_Mosca!$S13,NA()),NA()) -> #N/A | CE13: =IF(AND(ISNUMBER(Radar_Mosca!$F13),ISNUMBER(Radar_Mosca!$S13)),IF(AND(Radar_Mosca!$F13=CE$4,Radar_Mosca!$AA13=CE$3),Radar_Mosca!$S13,NA()),NA()) -> #N/A | CF13: =IF(AND(ISNUMBER(Radar_Mosca!$F13),ISNUMBER(Radar_Mosca!$S13)),IF(AND(Radar_Mosca!$F13=CF$4,Radar_Mosca!$AA13=CF$3),Radar_Mosca!$S13,NA()),NA()) -> #N/A | ... DN13: =IF(AND(ISNUMBER(Radar_Mosca!$F13),ISNUMBER(Radar_Mosca!$S13)),IF(AND(Radar_Mosca!$F13=DN$4,Radar_Mosca!$AA13=DN$3),Radar_Mosca!$S13,NA()),NA()) -> #N/A | DO13: =IF(ISNUMBER(Radar_Mosca!$R13),Radar_Mosca!$R13,NA()) -> 2.8145826 | DP13: =IF(Radar_Mosca!$A13="","",MID(Radar_Mosca!$A13,5,3)&IF(Radar_Mosca!$T13="Sì"," ◆","")) -> 09 ◆ | DQ13: =IF(ISNUMBER(Radar_Mosca!$S13),Radar_Mosca!$S13,NA()) -> 1.625 | DR13: 25 | DS13: 6.5 | DT13: -9.1
A14: =Classifica!$A$9 -> 5 | B14: =IF(Classifica!$B$9="","",Classifica!$B$9&" "&Classifica!$C$9&IFERROR(IF(INDEX(ANA_Attenzione_Supervisore,Classifica!$U$9)="Sì"," ◆",""),"")) -> NFR-03 Greenwashing nella commercializzazione di prodotti ESG | F14: =IF(Classifica!$B$9="","",Classifica!$D$9) -> 3 | G14: =IF(Classifica!$B$9="","",IF(ISNUMBER(Classifica!$F$9),Classifica!$F$9,"nuovo")) -> 0 | H14: =IF(Classifica!$B$9="","",IF(LEFT(Classifica!$H$9,9)="AGIRE ORA","AGIRE ORA",IF(LEFT(Classifica!$H$9,11)="Agire entro","Entro l'anno",Classifica!$H$9))) -> Entro l'anno | J14: 1 | K14: =SUBSTITUTE(SUBSTITUTE(Matrice!C9," ◆",""),"NFR-","") | L14: =SUBSTITUTE(SUBSTITUTE(Matrice!D9," ◆",""),"NFR-","") | M14: =SUBSTITUTE(SUBSTITUTE(Matrice!E9," ◆",""),"NFR-","") | N14: =SUBSTITUTE(SUBSTITUTE(Matrice!F9," ◆",""),"NFR-","") | O14: =SUBSTITUTE(SUBSTITUTE(Matrice!G9," ◆",""),"NFR-","") | T14: =IF(Radar_Mosca!$AA$14="Attivazione",Radar_Mosca!$A$14,"") | BH14: =2*PI()*9/72 -> 0.78539816 | BI14: =2*SIN($BH14) -> 1.4142136 | BJ14: =2*COS($BH14) -> 1.4142136 | BK14: =3*SIN($BH14) -> 2.1213203 | BL14: =3*COS($BH14) -> 2.1213203 | BM14: =4*SIN($BH14) -> 2.8284271 | BN14: =4*COS($BH14) -> 2.8284271 | BO14: =5*SIN($BH14) -> 3.5355339 | BP14: =5*COS($BH14) -> 3.5355339 | BR14: =6.3*SIN(2*PI()*4/ROWS(codiciL1)) -> 2.1547269 | BS14: =6.3*COS(2*PI()*4/ROWS(codiciL1)) -> -5.9200635 | BY14: =IF(AND(ISNUMBER(Radar_Mosca!$F14),ISNUMBER(Radar_Mosca!$S14)),IF(AND(Radar_Mosca!$F14=BY$4,Radar_Mosca!$AA14=BY$3),Radar_Mosca!$S14,NA()),NA()) -> #N/A | BZ14: =IF(AND(ISNUMBER(Radar_Mosca!$F14),ISNUMBER(Radar_Mosca!$S14)),IF(AND(Radar_Mosca!$F14=BZ$4,Radar_Mosca!$AA14=BZ$3),Radar_Mosca!$S14,NA()),NA()) -> #N/A | CA14: =IF(AND(ISNUMBER(Radar_Mosca!$F14),ISNUMBER(Radar_Mosca!$S14)),IF(AND(Radar_Mosca!$F14=CA$4,Radar_Mosca!$AA14=CA$3),Radar_Mosca!$S14,NA()),NA()) -> #N/A | CB14: =IF(AND(ISNUMBER(Radar_Mosca!$F14),ISNUMBER(Radar_Mosca!$S14)),IF(AND(Radar_Mosca!$F14=CB$4,Radar_Mosca!$AA14=CB$3),Radar_Mosca!$S14,NA()),NA()) -> #N/A | CC14: =IF(AND(ISNUMBER(Radar_Mosca!$F14),ISNUMBER(Radar_Mosca!$S14)),IF(AND(Radar_Mosca!$F14=CC$4,Radar_Mosca!$AA14=CC$3),Radar_Mosca!$S14,NA()),NA()) -> #N/A | CD14: =IF(AND(ISNUMBER(Radar_Mosca!$F14),ISNUMBER(Radar_Mosca!$S14)),IF(AND(Radar_Mosca!$F14=CD$4,Radar_Mosca!$AA14=CD$3),Radar_Mosca!$S14,NA()),NA()) -> #N/A | CE14: =IF(AND(ISNUMBER(Radar_Mosca!$F14),ISNUMBER(Radar_Mosca!$S14)),IF(AND(Radar_Mosca!$F14=CE$4,Radar_Mosca!$AA14=CE$3),Radar_Mosca!$S14,NA()),NA()) -> #N/A | CF14: =IF(AND(ISNUMBER(Radar_Mosca!$F14),ISNUMBER(Radar_Mosca!$S14)),IF(AND(Radar_Mosca!$F14=CF$4,Radar_Mosca!$AA14=CF$3),Radar_Mosca!$S14,NA()),NA()) -> #N/A | ... DN14: =IF(AND(ISNUMBER(Radar_Mosca!$F14),ISNUMBER(Radar_Mosca!$S14)),IF(AND(Radar_Mosca!$F14=DN$4,Radar_Mosca!$AA14=DN$3),Radar_Mosca!$S14,NA()),NA()) -> #N/A | DO14: =IF(ISNUMBER(Radar_Mosca!$R14),Radar_Mosca!$R14,NA()) -> 1.5 | DP14: =IF(Radar_Mosca!$A14="","",MID(Radar_Mosca!$A14,5,3)&IF(Radar_Mosca!$T14="Sì"," ◆","")) -> 10 | DQ14: =IF(ISNUMBER(Radar_Mosca!$S14),Radar_Mosca!$S14,NA()) -> 2.5980762
A15: Score 1-5, 5 = peggiore; barra su scala fissa 0-5. Variazione sul ciclo precedente. | J15: Numeri = NFR-nn. Verde P x I fino a 6, ambra 8-12, rosso da 15. | T15: =IF(Radar_Mosca!$AA$15="Attivazione",Radar_Mosca!$A$15,"") -> NFR-11 | BH15: =2*PI()*10/72 -> 0.87266463 | BI15: =2*SIN($BH15) -> 1.5320889 | BJ15: =2*COS($BH15) -> 1.2855752 | BK15: =3*SIN($BH15) -> 2.2981333 | BL15: =3*COS($BH15) -> 1.9283628 | BM15: =4*SIN($BH15) -> 3.0641778 | BN15: =4*COS($BH15) -> 2.5711504 | BO15: =5*SIN($BH15) -> 3.8302222 | BP15: =5*COS($BH15) -> 3.213938 | BR15: 0 | BS15: 0 | BY15: =IF(AND(ISNUMBER(Radar_Mosca!$F15),ISNUMBER(Radar_Mosca!$S15)),IF(AND(Radar_Mosca!$F15=BY$4,Radar_Mosca!$AA15=BY$3),Radar_Mosca!$S15,NA()),NA()) -> #N/A | BZ15: =IF(AND(ISNUMBER(Radar_Mosca!$F15),ISNUMBER(Radar_Mosca!$S15)),IF(AND(Radar_Mosca!$F15=BZ$4,Radar_Mosca!$AA15=BZ$3),Radar_Mosca!$S15,NA()),NA()) -> #N/A | CA15: =IF(AND(ISNUMBER(Radar_Mosca!$F15),ISNUMBER(Radar_Mosca!$S15)),IF(AND(Radar_Mosca!$F15=CA$4,Radar_Mosca!$AA15=CA$3),Radar_Mosca!$S15,NA()),NA()) -> #N/A | CB15: =IF(AND(ISNUMBER(Radar_Mosca!$F15),ISNUMBER(Radar_Mosca!$S15)),IF(AND(Radar_Mosca!$F15=CB$4,Radar_Mosca!$AA15=CB$3),Radar_Mosca!$S15,NA()),NA()) -> #N/A | CC15: =IF(AND(ISNUMBER(Radar_Mosca!$F15),ISNUMBER(Radar_Mosca!$S15)),IF(AND(Radar_Mosca!$F15=CC$4,Radar_Mosca!$AA15=CC$3),Radar_Mosca!$S15,NA()),NA()) -> #N/A | CD15: =IF(AND(ISNUMBER(Radar_Mosca!$F15),ISNUMBER(Radar_Mosca!$S15)),IF(AND(Radar_Mosca!$F15=CD$4,Radar_Mosca!$AA15=CD$3),Radar_Mosca!$S15,NA()),NA()) -> #N/A | CE15: =IF(AND(ISNUMBER(Radar_Mosca!$F15),ISNUMBER(Radar_Mosca!$S15)),IF(AND(Radar_Mosca!$F15=CE$4,Radar_Mosca!$AA15=CE$3),Radar_Mosca!$S15,NA()),NA()) -> #N/A | CF15: =IF(AND(ISNUMBER(Radar_Mosca!$F15),ISNUMBER(Radar_Mosca!$S15)),IF(AND(Radar_Mosca!$F15=CF$4,Radar_Mosca!$AA15=CF$3),Radar_Mosca!$S15,NA()),NA()) -> -0.45962667 | ... DN15: =IF(AND(ISNUMBER(Radar_Mosca!$F15),ISNUMBER(Radar_Mosca!$S15)),IF(AND(Radar_Mosca!$F15=DN$4,Radar_Mosca!$AA15=DN$3),Radar_Mosca!$S15,NA()),NA()) -> #N/A | DO15: =IF(ISNUMBER(Radar_Mosca!$R15),Radar_Mosca!$R15,NA()) -> 0.38567257 | DP15: =IF(Radar_Mosca!$A15="","",MID(Radar_Mosca!$A15,5,3)&IF(Radar_Mosca!$T15="Sì"," ◆","")) -> 11 | DQ15: =IF(ISNUMBER(Radar_Mosca!$S15),Radar_Mosca!$S15,NA()) -> -0.45962667
A16: Note dell'analista | T16: =IF(Radar_Mosca!$AA$16="Attivazione",Radar_Mosca!$A$16,"") | BH16: =2*PI()*11/72 -> 0.95993109 | BI16: =2*SIN($BH16) -> 1.6383041 | BJ16: =2*COS($BH16) -> 1.1471529 | BK16: =3*SIN($BH16) -> 2.4574561 | BL16: =3*COS($BH16) -> 1.7207293 | BM16: =4*SIN($BH16) -> 3.2766082 | BN16: =4*COS($BH16) -> 2.2943057 | BO16: =5*SIN($BH16) -> 4.0957602 | BP16: =5*COS($BH16) -> 2.8678822 | BR16: =6.3*SIN(2*PI()*5/ROWS(codiciL1)) -> -2.1547269 | BS16: =6.3*COS(2*PI()*5/ROWS(codiciL1)) -> -5.9200635 | BY16: =IF(AND(ISNUMBER(Radar_Mosca!$F16),ISNUMBER(Radar_Mosca!$S16)),IF(AND(Radar_Mosca!$F16=BY$4,Radar_Mosca!$AA16=BY$3),Radar_Mosca!$S16,NA()),NA()) -> #N/A | BZ16: =IF(AND(ISNUMBER(Radar_Mosca!$F16),ISNUMBER(Radar_Mosca!$S16)),IF(AND(Radar_Mosca!$F16=BZ$4,Radar_Mosca!$AA16=BZ$3),Radar_Mosca!$S16,NA()),NA()) -> #N/A | CA16: =IF(AND(ISNUMBER(Radar_Mosca!$F16),ISNUMBER(Radar_Mosca!$S16)),IF(AND(Radar_Mosca!$F16=CA$4,Radar_Mosca!$AA16=CA$3),Radar_Mosca!$S16,NA()),NA()) -> #N/A | CB16: =IF(AND(ISNUMBER(Radar_Mosca!$F16),ISNUMBER(Radar_Mosca!$S16)),IF(AND(Radar_Mosca!$F16=CB$4,Radar_Mosca!$AA16=CB$3),Radar_Mosca!$S16,NA()),NA()) -> #N/A | CC16: =IF(AND(ISNUMBER(Radar_Mosca!$F16),ISNUMBER(Radar_Mosca!$S16)),IF(AND(Radar_Mosca!$F16=CC$4,Radar_Mosca!$AA16=CC$3),Radar_Mosca!$S16,NA()),NA()) -> #N/A | CD16: =IF(AND(ISNUMBER(Radar_Mosca!$F16),ISNUMBER(Radar_Mosca!$S16)),IF(AND(Radar_Mosca!$F16=CD$4,Radar_Mosca!$AA16=CD$3),Radar_Mosca!$S16,NA()),NA()) -> #N/A | CE16: =IF(AND(ISNUMBER(Radar_Mosca!$F16),ISNUMBER(Radar_Mosca!$S16)),IF(AND(Radar_Mosca!$F16=CE$4,Radar_Mosca!$AA16=CE$3),Radar_Mosca!$S16,NA()),NA()) -> #N/A | CF16: =IF(AND(ISNUMBER(Radar_Mosca!$F16),ISNUMBER(Radar_Mosca!$S16)),IF(AND(Radar_Mosca!$F16=CF$4,Radar_Mosca!$AA16=CF$3),Radar_Mosca!$S16,NA()),NA()) -> #N/A | ... DN16: =IF(AND(ISNUMBER(Radar_Mosca!$F16),ISNUMBER(Radar_Mosca!$S16)),IF(AND(Radar_Mosca!$F16=DN$4,Radar_Mosca!$AA16=DN$3),Radar_Mosca!$S16,NA()),NA()) -> #N/A | DO16: =IF(ISNUMBER(Radar_Mosca!$R16),Radar_Mosca!$R16,NA()) -> -0.34729636 | DP16: =IF(Radar_Mosca!$A16="","",MID(Radar_Mosca!$A16,5,3)&IF(Radar_Mosca!$T16="Sì"," ◆","")) -> 12 | DQ16: =IF(ISNUMBER(Radar_Mosca!$S16),Radar_Mosca!$S16,NA()) -> 1.9696155
A17: Urgenza: radar di Mosca | J17: I rischi del ciclo | T17: =IF(Radar_Mosca!$AA$17="Attivazione",Radar_Mosca!$A$17,"") | BH17: =2*PI()*12/72 -> 1.0471976 | BI17: =2*SIN($BH17) -> 1.7320508 | BJ17: =2*COS($BH17) -> 1 | BK17: =3*SIN($BH17) -> 2.5980762 | BL17: =3*COS($BH17) -> 1.5 | BM17: =4*SIN($BH17) -> 3.4641016 | BN17: =4*COS($BH17) -> 2 | BO17: =5*SIN($BH17) -> 4.330127 | BP17: =5*COS($BH17) -> 2.5 | BR17: 0 | BS17: 0 | BY17: =IF(AND(ISNUMBER(Radar_Mosca!$F17),ISNUMBER(Radar_Mosca!$S17)),IF(AND(Radar_Mosca!$F17=BY$4,Radar_Mosca!$AA17=BY$3),Radar_Mosca!$S17,NA()),NA()) -> #N/A | BZ17: =IF(AND(ISNUMBER(Radar_Mosca!$F17),ISNUMBER(Radar_Mosca!$S17)),IF(AND(Radar_Mosca!$F17=BZ$4,Radar_Mosca!$AA17=BZ$3),Radar_Mosca!$S17,NA()),NA()) -> #N/A | CA17: =IF(AND(ISNUMBER(Radar_Mosca!$F17),ISNUMBER(Radar_Mosca!$S17)),IF(AND(Radar_Mosca!$F17=CA$4,Radar_Mosca!$AA17=CA$3),Radar_Mosca!$S17,NA()),NA()) -> #N/A | CB17: =IF(AND(ISNUMBER(Radar_Mosca!$F17),ISNUMBER(Radar_Mosca!$S17)),IF(AND(Radar_Mosca!$F17=CB$4,Radar_Mosca!$AA17=CB$3),Radar_Mosca!$S17,NA()),NA()) -> #N/A | CC17: =IF(AND(ISNUMBER(Radar_Mosca!$F17),ISNUMBER(Radar_Mosca!$S17)),IF(AND(Radar_Mosca!$F17=CC$4,Radar_Mosca!$AA17=CC$3),Radar_Mosca!$S17,NA()),NA()) -> #N/A | CD17: =IF(AND(ISNUMBER(Radar_Mosca!$F17),ISNUMBER(Radar_Mosca!$S17)),IF(AND(Radar_Mosca!$F17=CD$4,Radar_Mosca!$AA17=CD$3),Radar_Mosca!$S17,NA()),NA()) -> #N/A | CE17: =IF(AND(ISNUMBER(Radar_Mosca!$F17),ISNUMBER(Radar_Mosca!$S17)),IF(AND(Radar_Mosca!$F17=CE$4,Radar_Mosca!$AA17=CE$3),Radar_Mosca!$S17,NA()),NA()) -> #N/A | CF17: =IF(AND(ISNUMBER(Radar_Mosca!$F17),ISNUMBER(Radar_Mosca!$S17)),IF(AND(Radar_Mosca!$F17=CF$4,Radar_Mosca!$AA17=CF$3),Radar_Mosca!$S17,NA()),NA()) -> #N/A | ... DN17: =IF(AND(ISNUMBER(Radar_Mosca!$F17),ISNUMBER(Radar_Mosca!$S17)),IF(AND(Radar_Mosca!$F17=DN$4,Radar_Mosca!$AA17=DN$3),Radar_Mosca!$S17,NA()),NA()) -> #N/A | DO17: =IF(ISNUMBER(Radar_Mosca!$R17),Radar_Mosca!$R17,NA()) -> -3.2475953 | DP17: =IF(Radar_Mosca!$A17="","",MID(Radar_Mosca!$A17,5,3)&IF(Radar_Mosca!$T17="Sì"," ◆","")) -> 16 | DQ17: =IF(ISNUMBER(Radar_Mosca!$S17),Radar_Mosca!$S17,NA()) -> 1.875
J18: =INDEX(posID,1)&"" -> NFR-01 | K18: =IF(J18="","",INDEX(posNome,1)&IF(INDEX(ANA_Attenzione_Supervisore,1)="Sì"," ◆","")) -> Frodi su pagamenti istantanei abilitate da AI generativa ◆ | T18: =IF(Radar_Mosca!$AA$18="Attivazione",Radar_Mosca!$A$18,"") | BH18: =2*PI()*13/72 -> 1.134464 | BI18: =2*SIN($BH18) -> 1.8126156 | BJ18: =2*COS($BH18) -> 0.84523652 | BK18: =3*SIN($BH18) -> 2.7189234 | BL18: =3*COS($BH18) -> 1.2678548 | BM18: =4*SIN($BH18) -> 3.6252311 | BN18: =4*COS($BH18) -> 1.690473 | BO18: =5*SIN($BH18) -> 4.5315389 | BP18: =5*COS($BH18) -> 2.1130913 | BR18: =6.3*SIN(2*PI()*6/ROWS(codiciL1)) -> -5.45596 | BS18: =6.3*COS(2*PI()*6/ROWS(codiciL1)) -> -3.15 | BY18: =IF(AND(ISNUMBER(Radar_Mosca!$F18),ISNUMBER(Radar_Mosca!$S18)),IF(AND(Radar_Mosca!$F18=BY$4,Radar_Mosca!$AA18=BY$3),Radar_Mosca!$S18,NA()),NA()) -> #N/A | BZ18: =IF(AND(ISNUMBER(Radar_Mosca!$F18),ISNUMBER(Radar_Mosca!$S18)),IF(AND(Radar_Mosca!$F18=BZ$4,Radar_Mosca!$AA18=BZ$3),Radar_Mosca!$S18,NA()),NA()) -> #N/A | CA18: =IF(AND(ISNUMBER(Radar_Mosca!$F18),ISNUMBER(Radar_Mosca!$S18)),IF(AND(Radar_Mosca!$F18=CA$4,Radar_Mosca!$AA18=CA$3),Radar_Mosca!$S18,NA()),NA()) -> #N/A | CB18: =IF(AND(ISNUMBER(Radar_Mosca!$F18),ISNUMBER(Radar_Mosca!$S18)),IF(AND(Radar_Mosca!$F18=CB$4,Radar_Mosca!$AA18=CB$3),Radar_Mosca!$S18,NA()),NA()) -> #N/A | CC18: =IF(AND(ISNUMBER(Radar_Mosca!$F18),ISNUMBER(Radar_Mosca!$S18)),IF(AND(Radar_Mosca!$F18=CC$4,Radar_Mosca!$AA18=CC$3),Radar_Mosca!$S18,NA()),NA()) -> #N/A | CD18: =IF(AND(ISNUMBER(Radar_Mosca!$F18),ISNUMBER(Radar_Mosca!$S18)),IF(AND(Radar_Mosca!$F18=CD$4,Radar_Mosca!$AA18=CD$3),Radar_Mosca!$S18,NA()),NA()) -> #N/A | CE18: =IF(AND(ISNUMBER(Radar_Mosca!$F18),ISNUMBER(Radar_Mosca!$S18)),IF(AND(Radar_Mosca!$F18=CE$4,Radar_Mosca!$AA18=CE$3),Radar_Mosca!$S18,NA()),NA()) -> #N/A | CF18: =IF(AND(ISNUMBER(Radar_Mosca!$F18),ISNUMBER(Radar_Mosca!$S18)),IF(AND(Radar_Mosca!$F18=CF$4,Radar_Mosca!$AA18=CF$3),Radar_Mosca!$S18,NA()),NA()) -> #N/A | ... DN18: =IF(AND(ISNUMBER(Radar_Mosca!$F18),ISNUMBER(Radar_Mosca!$S18)),IF(AND(Radar_Mosca!$F18=DN$4,Radar_Mosca!$AA18=DN$3),Radar_Mosca!$S18,NA()),NA()) -> #N/A | DO18: =IF(ISNUMBER(Radar_Mosca!$R18),Radar_Mosca!$R18,NA()) -> #N/A | DP18: =IF(Radar_Mosca!$A18="","",MID(Radar_Mosca!$A18,5,3)&IF(Radar_Mosca!$T18="Sì"," ◆","")) | DQ18: =IF(ISNUMBER(Radar_Mosca!$S18),Radar_Mosca!$S18,NA()) -> #N/A
J19: =INDEX(posID,2)&"" -> NFR-02 | K19: =IF(J19="","",INDEX(posNome,2)&IF(INDEX(ANA_Attenzione_Supervisore,2)="Sì"," ◆","")) -> Concentrazione su un fornitore cloud critico ◆ | T19: =IF(Radar_Mosca!$AA$19="Attivazione",Radar_Mosca!$A$19,"") | BH19: =2*PI()*14/72 -> 1.2217305 | BI19: =2*SIN($BH19) -> 1.8793852 | BJ19: =2*COS($BH19) -> 0.68404029 | BK19: =3*SIN($BH19) -> 2.8190779 | BL19: =3*COS($BH19) -> 1.0260604 | BM19: =4*SIN($BH19) -> 3.7587705 | BN19: =4*COS($BH19) -> 1.3680806 | BO19: =5*SIN($BH19) -> 4.6984631 | BP19: =5*COS($BH19) -> 1.7101007 | BR19: 0 | BS19: 0 | BY19: =IF(AND(ISNUMBER(Radar_Mosca!$F19),ISNUMBER(Radar_Mosca!$S19)),IF(AND(Radar_Mosca!$F19=BY$4,Radar_Mosca!$AA19=BY$3),Radar_Mosca!$S19,NA()),NA()) -> #N/A | BZ19: =IF(AND(ISNUMBER(Radar_Mosca!$F19),ISNUMBER(Radar_Mosca!$S19)),IF(AND(Radar_Mosca!$F19=BZ$4,Radar_Mosca!$AA19=BZ$3),Radar_Mosca!$S19,NA()),NA()) -> #N/A | CA19: =IF(AND(ISNUMBER(Radar_Mosca!$F19),ISNUMBER(Radar_Mosca!$S19)),IF(AND(Radar_Mosca!$F19=CA$4,Radar_Mosca!$AA19=CA$3),Radar_Mosca!$S19,NA()),NA()) -> #N/A | CB19: =IF(AND(ISNUMBER(Radar_Mosca!$F19),ISNUMBER(Radar_Mosca!$S19)),IF(AND(Radar_Mosca!$F19=CB$4,Radar_Mosca!$AA19=CB$3),Radar_Mosca!$S19,NA()),NA()) -> #N/A | CC19: =IF(AND(ISNUMBER(Radar_Mosca!$F19),ISNUMBER(Radar_Mosca!$S19)),IF(AND(Radar_Mosca!$F19=CC$4,Radar_Mosca!$AA19=CC$3),Radar_Mosca!$S19,NA()),NA()) -> #N/A | CD19: =IF(AND(ISNUMBER(Radar_Mosca!$F19),ISNUMBER(Radar_Mosca!$S19)),IF(AND(Radar_Mosca!$F19=CD$4,Radar_Mosca!$AA19=CD$3),Radar_Mosca!$S19,NA()),NA()) -> #N/A | CE19: =IF(AND(ISNUMBER(Radar_Mosca!$F19),ISNUMBER(Radar_Mosca!$S19)),IF(AND(Radar_Mosca!$F19=CE$4,Radar_Mosca!$AA19=CE$3),Radar_Mosca!$S19,NA()),NA()) -> #N/A | CF19: =IF(AND(ISNUMBER(Radar_Mosca!$F19),ISNUMBER(Radar_Mosca!$S19)),IF(AND(Radar_Mosca!$F19=CF$4,Radar_Mosca!$AA19=CF$3),Radar_Mosca!$S19,NA()),NA()) -> #N/A | ... DN19: =IF(AND(ISNUMBER(Radar_Mosca!$F19),ISNUMBER(Radar_Mosca!$S19)),IF(AND(Radar_Mosca!$F19=DN$4,Radar_Mosca!$AA19=DN$3),Radar_Mosca!$S19,NA()),NA()) -> #N/A | DO19: =IF(ISNUMBER(Radar_Mosca!$R19),Radar_Mosca!$R19,NA()) -> #N/A | DP19: =IF(Radar_Mosca!$A19="","",MID(Radar_Mosca!$A19,5,3)&IF(Radar_Mosca!$T19="Sì"," ◆","")) | DQ19: =IF(ISNUMBER(Radar_Mosca!$S19),Radar_Mosca!$S19,NA()) -> #N/A
J20: =INDEX(posID,3)&"" -> NFR-03 | K20: =IF(J20="","",INDEX(posNome,3)&IF(INDEX(ANA_Attenzione_Supervisore,3)="Sì"," ◆","")) -> Greenwashing nella commercializzazione di prodotti ESG | T20: =IF(Radar_Mosca!$AA$20="Attivazione",Radar_Mosca!$A$20,"") | BH20: =2*PI()*15/72 -> 1.3089969 | BI20: =2*SIN($BH20) -> 1.9318517 | BJ20: =2*COS($BH20) -> 0.51763809 | BK20: =3*SIN($BH20) -> 2.8977775 | BL20: =3*COS($BH20) -> 0.77645714 | BM20: =4*SIN($BH20) -> 3.8637033 | BN20: =4*COS($BH20) -> 1.0352762 | BO20: =5*SIN($BH20) -> 4.8296291 | BP20: =5*COS($BH20) -> 1.2940952 | BR20: =6.3*SIN(2*PI()*7/ROWS(codiciL1)) -> -6.2042888 | BS20: =6.3*COS(2*PI()*7/ROWS(codiciL1)) -> 1.0939835 | BY20: =IF(AND(ISNUMBER(Radar_Mosca!$F20),ISNUMBER(Radar_Mosca!$S20)),IF(AND(Radar_Mosca!$F20=BY$4,Radar_Mosca!$AA20=BY$3),Radar_Mosca!$S20,NA()),NA()) -> #N/A | BZ20: =IF(AND(ISNUMBER(Radar_Mosca!$F20),ISNUMBER(Radar_Mosca!$S20)),IF(AND(Radar_Mosca!$F20=BZ$4,Radar_Mosca!$AA20=BZ$3),Radar_Mosca!$S20,NA()),NA()) -> #N/A | CA20: =IF(AND(ISNUMBER(Radar_Mosca!$F20),ISNUMBER(Radar_Mosca!$S20)),IF(AND(Radar_Mosca!$F20=CA$4,Radar_Mosca!$AA20=CA$3),Radar_Mosca!$S20,NA()),NA()) -> #N/A | CB20: =IF(AND(ISNUMBER(Radar_Mosca!$F20),ISNUMBER(Radar_Mosca!$S20)),IF(AND(Radar_Mosca!$F20=CB$4,Radar_Mosca!$AA20=CB$3),Radar_Mosca!$S20,NA()),NA()) -> #N/A | CC20: =IF(AND(ISNUMBER(Radar_Mosca!$F20),ISNUMBER(Radar_Mosca!$S20)),IF(AND(Radar_Mosca!$F20=CC$4,Radar_Mosca!$AA20=CC$3),Radar_Mosca!$S20,NA()),NA()) -> #N/A | CD20: =IF(AND(ISNUMBER(Radar_Mosca!$F20),ISNUMBER(Radar_Mosca!$S20)),IF(AND(Radar_Mosca!$F20=CD$4,Radar_Mosca!$AA20=CD$3),Radar_Mosca!$S20,NA()),NA()) -> #N/A | CE20: =IF(AND(ISNUMBER(Radar_Mosca!$F20),ISNUMBER(Radar_Mosca!$S20)),IF(AND(Radar_Mosca!$F20=CE$4,Radar_Mosca!$AA20=CE$3),Radar_Mosca!$S20,NA()),NA()) -> #N/A | CF20: =IF(AND(ISNUMBER(Radar_Mosca!$F20),ISNUMBER(Radar_Mosca!$S20)),IF(AND(Radar_Mosca!$F20=CF$4,Radar_Mosca!$AA20=CF$3),Radar_Mosca!$S20,NA()),NA()) -> #N/A | ... DN20: =IF(AND(ISNUMBER(Radar_Mosca!$F20),ISNUMBER(Radar_Mosca!$S20)),IF(AND(Radar_Mosca!$F20=DN$4,Radar_Mosca!$AA20=DN$3),Radar_Mosca!$S20,NA()),NA()) -> #N/A | DO20: =IF(ISNUMBER(Radar_Mosca!$R20),Radar_Mosca!$R20,NA()) -> #N/A | DP20: =IF(Radar_Mosca!$A20="","",MID(Radar_Mosca!$A20,5,3)&IF(Radar_Mosca!$T20="Sì"," ◆","")) | DQ20: =IF(ISNUMBER(Radar_Mosca!$S20),Radar_Mosca!$S20,NA()) -> #N/A
J21: =INDEX(posID,4)&"" -> NFR-04 | K21: =IF(J21="","",INDEX(posNome,4)&IF(INDEX(ANA_Attenzione_Supervisore,4)="Sì"," ◆","")) -> Eventi climatici estremi su sedi e data center | T21: =IF(Radar_Mosca!$AA$21="Attivazione",Radar_Mosca!$A$21,"") | BH21: =2*PI()*16/72 -> 1.3962634 | BI21: =2*SIN($BH21) -> 1.9696155 | BJ21: =2*COS($BH21) -> 0.34729636 | BK21: =3*SIN($BH21) -> 2.9544233 | BL21: =3*COS($BH21) -> 0.52094453 | BM21: =4*SIN($BH21) -> 3.939231 | BN21: =4*COS($BH21) -> 0.69459271 | BO21: =5*SIN($BH21) -> 4.9240388 | BP21: =5*COS($BH21) -> 0.86824089 | BR21: 0 | BS21: 0 | BY21: =IF(AND(ISNUMBER(Radar_Mosca!$F21),ISNUMBER(Radar_Mosca!$S21)),IF(AND(Radar_Mosca!$F21=BY$4,Radar_Mosca!$AA21=BY$3),Radar_Mosca!$S21,NA()),NA()) -> #N/A | BZ21: =IF(AND(ISNUMBER(Radar_Mosca!$F21),ISNUMBER(Radar_Mosca!$S21)),IF(AND(Radar_Mosca!$F21=BZ$4,Radar_Mosca!$AA21=BZ$3),Radar_Mosca!$S21,NA()),NA()) -> #N/A | CA21: =IF(AND(ISNUMBER(Radar_Mosca!$F21),ISNUMBER(Radar_Mosca!$S21)),IF(AND(Radar_Mosca!$F21=CA$4,Radar_Mosca!$AA21=CA$3),Radar_Mosca!$S21,NA()),NA()) -> #N/A | CB21: =IF(AND(ISNUMBER(Radar_Mosca!$F21),ISNUMBER(Radar_Mosca!$S21)),IF(AND(Radar_Mosca!$F21=CB$4,Radar_Mosca!$AA21=CB$3),Radar_Mosca!$S21,NA()),NA()) -> #N/A | CC21: =IF(AND(ISNUMBER(Radar_Mosca!$F21),ISNUMBER(Radar_Mosca!$S21)),IF(AND(Radar_Mosca!$F21=CC$4,Radar_Mosca!$AA21=CC$3),Radar_Mosca!$S21,NA()),NA()) -> #N/A | CD21: =IF(AND(ISNUMBER(Radar_Mosca!$F21),ISNUMBER(Radar_Mosca!$S21)),IF(AND(Radar_Mosca!$F21=CD$4,Radar_Mosca!$AA21=CD$3),Radar_Mosca!$S21,NA()),NA()) -> #N/A | CE21: =IF(AND(ISNUMBER(Radar_Mosca!$F21),ISNUMBER(Radar_Mosca!$S21)),IF(AND(Radar_Mosca!$F21=CE$4,Radar_Mosca!$AA21=CE$3),Radar_Mosca!$S21,NA()),NA()) -> #N/A | CF21: =IF(AND(ISNUMBER(Radar_Mosca!$F21),ISNUMBER(Radar_Mosca!$S21)),IF(AND(Radar_Mosca!$F21=CF$4,Radar_Mosca!$AA21=CF$3),Radar_Mosca!$S21,NA()),NA()) -> #N/A | ... DN21: =IF(AND(ISNUMBER(Radar_Mosca!$F21),ISNUMBER(Radar_Mosca!$S21)),IF(AND(Radar_Mosca!$F21=DN$4,Radar_Mosca!$AA21=DN$3),Radar_Mosca!$S21,NA()),NA()) -> #N/A | DO21: =IF(ISNUMBER(Radar_Mosca!$R21),Radar_Mosca!$R21,NA()) -> #N/A | DP21: =IF(Radar_Mosca!$A21="","",MID(Radar_Mosca!$A21,5,3)&IF(Radar_Mosca!$T21="Sì"," ◆","")) | DQ21: =IF(ISNUMBER(Radar_Mosca!$S21),Radar_Mosca!$S21,NA()) -> #N/A
J22: =INDEX(posID,5)&"" -> NFR-05 | K22: =IF(J22="","",INDEX(posNome,5)&IF(INDEX(ANA_Attenzione_Supervisore,5)="Sì"," ◆","")) -> Errori di processo nella migrazione del core banking | T22: =IF(Radar_Mosca!$AA$22="Attivazione",Radar_Mosca!$A$22,"") | BH22: =2*PI()*17/72 -> 1.4835299 | BI22: =2*SIN($BH22) -> 1.9923894 | BJ22: =2*COS($BH22) -> 0.17431149 | BK22: =3*SIN($BH22) -> 2.9885841 | BL22: =3*COS($BH22) -> 0.26146723 | BM22: =4*SIN($BH22) -> 3.9847788 | BN22: =4*COS($BH22) -> 0.34862297 | BO22: =5*SIN($BH22) -> 4.9809735 | BP22: =5*COS($BH22) -> 0.43577871 | BR22: =6.3*SIN(2*PI()*8/ROWS(codiciL1)) -> -4.0495619 | BS22: =6.3*COS(2*PI()*8/ROWS(codiciL1)) -> 4.82608 | BY22: =IF(AND(ISNUMBER(Radar_Mosca!$F22),ISNUMBER(Radar_Mosca!$S22)),IF(AND(Radar_Mosca!$F22=BY$4,Radar_Mosca!$AA22=BY$3),Radar_Mosca!$S22,NA()),NA()) -> #N/A | BZ22: =IF(AND(ISNUMBER(Radar_Mosca!$F22),ISNUMBER(Radar_Mosca!$S22)),IF(AND(Radar_Mosca!$F22=BZ$4,Radar_Mosca!$AA22=BZ$3),Radar_Mosca!$S22,NA()),NA()) -> #N/A | CA22: =IF(AND(ISNUMBER(Radar_Mosca!$F22),ISNUMBER(Radar_Mosca!$S22)),IF(AND(Radar_Mosca!$F22=CA$4,Radar_Mosca!$AA22=CA$3),Radar_Mosca!$S22,NA()),NA()) -> #N/A | CB22: =IF(AND(ISNUMBER(Radar_Mosca!$F22),ISNUMBER(Radar_Mosca!$S22)),IF(AND(Radar_Mosca!$F22=CB$4,Radar_Mosca!$AA22=CB$3),Radar_Mosca!$S22,NA()),NA()) -> #N/A | CC22: =IF(AND(ISNUMBER(Radar_Mosca!$F22),ISNUMBER(Radar_Mosca!$S22)),IF(AND(Radar_Mosca!$F22=CC$4,Radar_Mosca!$AA22=CC$3),Radar_Mosca!$S22,NA()),NA()) -> #N/A | CD22: =IF(AND(ISNUMBER(Radar_Mosca!$F22),ISNUMBER(Radar_Mosca!$S22)),IF(AND(Radar_Mosca!$F22=CD$4,Radar_Mosca!$AA22=CD$3),Radar_Mosca!$S22,NA()),NA()) -> #N/A | CE22: =IF(AND(ISNUMBER(Radar_Mosca!$F22),ISNUMBER(Radar_Mosca!$S22)),IF(AND(Radar_Mosca!$F22=CE$4,Radar_Mosca!$AA22=CE$3),Radar_Mosca!$S22,NA()),NA()) -> #N/A | CF22: =IF(AND(ISNUMBER(Radar_Mosca!$F22),ISNUMBER(Radar_Mosca!$S22)),IF(AND(Radar_Mosca!$F22=CF$4,Radar_Mosca!$AA22=CF$3),Radar_Mosca!$S22,NA()),NA()) -> #N/A | ... DN22: =IF(AND(ISNUMBER(Radar_Mosca!$F22),ISNUMBER(Radar_Mosca!$S22)),IF(AND(Radar_Mosca!$F22=DN$4,Radar_Mosca!$AA22=DN$3),Radar_Mosca!$S22,NA()),NA()) -> #N/A | DO22: =IF(ISNUMBER(Radar_Mosca!$R22),Radar_Mosca!$R22,NA()) -> #N/A | DP22: =IF(Radar_Mosca!$A22="","",MID(Radar_Mosca!$A22,5,3)&IF(Radar_Mosca!$T22="Sì"," ◆","")) | DQ22: =IF(ISNUMBER(Radar_Mosca!$S22),Radar_Mosca!$S22,NA()) -> #N/A
J23: =INDEX(posID,6)&"" -> NFR-06 | K23: =IF(J23="","",INDEX(posNome,6)&IF(INDEX(ANA_Attenzione_Supervisore,6)="Sì"," ◆","")) -> Esfiltrazione di dati tramite strumenti di AI non autorizzati | T23: =IF(Radar_Mosca!$AA$23="Attivazione",Radar_Mosca!$A$23,"") | BH23: =2*PI()*18/72 -> 1.5707963 | BI23: =2*SIN($BH23) -> 2 | BJ23: =2*COS($BH23) -> 1.2251485e-16 | BK23: =3*SIN($BH23) -> 3 | BL23: =3*COS($BH23) -> 1.8377227e-16 | BM23: =4*SIN($BH23) -> 4 | BN23: =4*COS($BH23) -> 2.4502969e-16 | BO23: =5*SIN($BH23) -> 5 | BP23: =5*COS($BH23) -> 3.0628711e-16 | BY23: =IF(AND(ISNUMBER(Radar_Mosca!$F23),ISNUMBER(Radar_Mosca!$S23)),IF(AND(Radar_Mosca!$F23=BY$4,Radar_Mosca!$AA23=BY$3),Radar_Mosca!$S23,NA()),NA()) -> #N/A | BZ23: =IF(AND(ISNUMBER(Radar_Mosca!$F23),ISNUMBER(Radar_Mosca!$S23)),IF(AND(Radar_Mosca!$F23=BZ$4,Radar_Mosca!$AA23=BZ$3),Radar_Mosca!$S23,NA()),NA()) -> #N/A | CA23: =IF(AND(ISNUMBER(Radar_Mosca!$F23),ISNUMBER(Radar_Mosca!$S23)),IF(AND(Radar_Mosca!$F23=CA$4,Radar_Mosca!$AA23=CA$3),Radar_Mosca!$S23,NA()),NA()) -> #N/A | CB23: =IF(AND(ISNUMBER(Radar_Mosca!$F23),ISNUMBER(Radar_Mosca!$S23)),IF(AND(Radar_Mosca!$F23=CB$4,Radar_Mosca!$AA23=CB$3),Radar_Mosca!$S23,NA()),NA()) -> #N/A | CC23: =IF(AND(ISNUMBER(Radar_Mosca!$F23),ISNUMBER(Radar_Mosca!$S23)),IF(AND(Radar_Mosca!$F23=CC$4,Radar_Mosca!$AA23=CC$3),Radar_Mosca!$S23,NA()),NA()) -> #N/A | CD23: =IF(AND(ISNUMBER(Radar_Mosca!$F23),ISNUMBER(Radar_Mosca!$S23)),IF(AND(Radar_Mosca!$F23=CD$4,Radar_Mosca!$AA23=CD$3),Radar_Mosca!$S23,NA()),NA()) -> #N/A | CE23: =IF(AND(ISNUMBER(Radar_Mosca!$F23),ISNUMBER(Radar_Mosca!$S23)),IF(AND(Radar_Mosca!$F23=CE$4,Radar_Mosca!$AA23=CE$3),Radar_Mosca!$S23,NA()),NA()) -> #N/A | CF23: =IF(AND(ISNUMBER(Radar_Mosca!$F23),ISNUMBER(Radar_Mosca!$S23)),IF(AND(Radar_Mosca!$F23=CF$4,Radar_Mosca!$AA23=CF$3),Radar_Mosca!$S23,NA()),NA()) -> #N/A | ... DN23: =IF(AND(ISNUMBER(Radar_Mosca!$F23),ISNUMBER(Radar_Mosca!$S23)),IF(AND(Radar_Mosca!$F23=DN$4,Radar_Mosca!$AA23=DN$3),Radar_Mosca!$S23,NA()),NA()) -> #N/A | DO23: =IF(ISNUMBER(Radar_Mosca!$R23),Radar_Mosca!$R23,NA()) -> #N/A | DP23: =IF(Radar_Mosca!$A23="","",MID(Radar_Mosca!$A23,5,3)&IF(Radar_Mosca!$T23="Sì"," ◆","")) | DQ23: =IF(ISNUMBER(Radar_Mosca!$S23),Radar_Mosca!$S23,NA()) -> #N/A
J24: =INDEX(posID,7)&"" -> NFR-07 | K24: =IF(J24="","",INDEX(posNome,7)&IF(INDEX(ANA_Attenzione_Supervisore,7)="Sì"," ◆","")) -> Ransomware presso un fornitore di servizi di pagamento ◆ | T24: =IF(Radar_Mosca!$AA$24="Attivazione",Radar_Mosca!$A$24,"") | BH24: =2*PI()*19/72 -> 1.6580628 | BI24: =2*SIN($BH24) -> 1.9923894 | BJ24: =2*COS($BH24) -> -0.17431149 | BK24: =3*SIN($BH24) -> 2.9885841 | BL24: =3*COS($BH24) -> -0.26146723 | BM24: =4*SIN($BH24) -> 3.9847788 | BN24: =4*COS($BH24) -> -0.34862297 | BO24: =5*SIN($BH24) -> 4.9809735 | BP24: =5*COS($BH24) -> -0.43577871 | BY24: =IF(AND(ISNUMBER(Radar_Mosca!$F24),ISNUMBER(Radar_Mosca!$S24)),IF(AND(Radar_Mosca!$F24=BY$4,Radar_Mosca!$AA24=BY$3),Radar_Mosca!$S24,NA()),NA()) -> #N/A | BZ24: =IF(AND(ISNUMBER(Radar_Mosca!$F24),ISNUMBER(Radar_Mosca!$S24)),IF(AND(Radar_Mosca!$F24=BZ$4,Radar_Mosca!$AA24=BZ$3),Radar_Mosca!$S24,NA()),NA()) -> #N/A | CA24: =IF(AND(ISNUMBER(Radar_Mosca!$F24),ISNUMBER(Radar_Mosca!$S24)),IF(AND(Radar_Mosca!$F24=CA$4,Radar_Mosca!$AA24=CA$3),Radar_Mosca!$S24,NA()),NA()) -> #N/A | CB24: =IF(AND(ISNUMBER(Radar_Mosca!$F24),ISNUMBER(Radar_Mosca!$S24)),IF(AND(Radar_Mosca!$F24=CB$4,Radar_Mosca!$AA24=CB$3),Radar_Mosca!$S24,NA()),NA()) -> #N/A | CC24: =IF(AND(ISNUMBER(Radar_Mosca!$F24),ISNUMBER(Radar_Mosca!$S24)),IF(AND(Radar_Mosca!$F24=CC$4,Radar_Mosca!$AA24=CC$3),Radar_Mosca!$S24,NA()),NA()) -> #N/A | CD24: =IF(AND(ISNUMBER(Radar_Mosca!$F24),ISNUMBER(Radar_Mosca!$S24)),IF(AND(Radar_Mosca!$F24=CD$4,Radar_Mosca!$AA24=CD$3),Radar_Mosca!$S24,NA()),NA()) -> #N/A | CE24: =IF(AND(ISNUMBER(Radar_Mosca!$F24),ISNUMBER(Radar_Mosca!$S24)),IF(AND(Radar_Mosca!$F24=CE$4,Radar_Mosca!$AA24=CE$3),Radar_Mosca!$S24,NA()),NA()) -> #N/A | CF24: =IF(AND(ISNUMBER(Radar_Mosca!$F24),ISNUMBER(Radar_Mosca!$S24)),IF(AND(Radar_Mosca!$F24=CF$4,Radar_Mosca!$AA24=CF$3),Radar_Mosca!$S24,NA()),NA()) -> #N/A | ... DN24: =IF(AND(ISNUMBER(Radar_Mosca!$F24),ISNUMBER(Radar_Mosca!$S24)),IF(AND(Radar_Mosca!$F24=DN$4,Radar_Mosca!$AA24=DN$3),Radar_Mosca!$S24,NA()),NA()) -> #N/A | DO24: =IF(ISNUMBER(Radar_Mosca!$R24),Radar_Mosca!$R24,NA()) -> #N/A | DP24: =IF(Radar_Mosca!$A24="","",MID(Radar_Mosca!$A24,5,3)&IF(Radar_Mosca!$T24="Sì"," ◆","")) | DQ24: =IF(ISNUMBER(Radar_Mosca!$S24),Radar_Mosca!$S24,NA()) -> #N/A
J25: =INDEX(posID,8)&"" -> NFR-08 | K25: =IF(J25="","",INDEX(posNome,8)&IF(INDEX(ANA_Attenzione_Supervisore,8)="Sì"," ◆","")) -> Accessi impropri di dipendenti ai dati dei clienti | BH25: =2*PI()*20/72 -> 1.7453293 | BI25: =2*SIN($BH25) -> 1.9696155 | BJ25: =2*COS($BH25) -> -0.34729636 | BK25: =3*SIN($BH25) -> 2.9544233 | BL25: =3*COS($BH25) -> -0.52094453 | BM25: =4*SIN($BH25) -> 3.939231 | BN25: =4*COS($BH25) -> -0.69459271 | BO25: =5*SIN($BH25) -> 4.9240388 | BP25: =5*COS($BH25) -> -0.86824089
J26: =INDEX(posID,9)&"" -> NFR-09 | K26: =IF(J26="","",INDEX(posNome,9)&IF(INDEX(ANA_Attenzione_Supervisore,9)="Sì"," ◆","")) -> Violazione di sanzioni internazionali tramite triangolazioni ◆ | BH26: =2*PI()*21/72 -> 1.8325957 | BI26: =2*SIN($BH26) -> 1.9318517 | BJ26: =2*COS($BH26) -> -0.51763809 | BK26: =3*SIN($BH26) -> 2.8977775 | BL26: =3*COS($BH26) -> -0.77645714 | BM26: =4*SIN($BH26) -> 3.8637033 | BN26: =4*COS($BH26) -> -1.0352762 | BO26: =5*SIN($BH26) -> 4.8296291 | BP26: =5*COS($BH26) -> -1.2940952
J27: =INDEX(posID,10)&"" -> NFR-10 | K27: =IF(J27="","",INDEX(posNome,10)&IF(INDEX(ANA_Attenzione_Supervisore,10)="Sì"," ◆","")) -> Informazioni errate ai clienti da assistenti di AI generativa | BH27: =2*PI()*22/72 -> 1.9198622 | BI27: =2*SIN($BH27) -> 1.8793852 | BJ27: =2*COS($BH27) -> -0.68404029 | BK27: =3*SIN($BH27) -> 2.8190779 | BL27: =3*COS($BH27) -> -1.0260604 | BM27: =4*SIN($BH27) -> 3.7587705 | BN27: =4*COS($BH27) -> -1.3680806 | BO27: =5*SIN($BH27) -> 4.6984631 | BP27: =5*COS($BH27) -> -1.7101007
J28: =INDEX(posID,11)&"" -> NFR-11 | K28: =IF(J28="","",INDEX(posNome,11)&IF(INDEX(ANA_Attenzione_Supervisore,11)="Sì"," ◆","")) -> Fine del supporto dei sistemi di pagamento legacy | BH28: =2*PI()*23/72 -> 2.0071286 | BI28: =2*SIN($BH28) -> 1.8126156 | BJ28: =2*COS($BH28) -> -0.84523652 | BK28: =3*SIN($BH28) -> 2.7189234 | BL28: =3*COS($BH28) -> -1.2678548 | BM28: =4*SIN($BH28) -> 3.6252311 | BN28: =4*COS($BH28) -> -1.690473 | BO28: =5*SIN($BH28) -> 4.5315389 | BP28: =5*COS($BH28) -> -2.1130913
J29: =INDEX(posID,12)&"" -> NFR-12 | K29: =IF(J29="","",INDEX(posNome,12)&IF(INDEX(ANA_Attenzione_Supervisore,12)="Sì"," ◆","")) -> Errori operativi nei pagamenti istantanei obbligatori | BH29: =2*PI()*24/72 -> 2.0943951 | BI29: =2*SIN($BH29) -> 1.7320508 | BJ29: =2*COS($BH29) -> -1 | BK29: =3*SIN($BH29) -> 2.5980762 | BL29: =3*COS($BH29) -> -1.5 | BM29: =4*SIN($BH29) -> 3.4641016 | BN29: =4*COS($BH29) -> -2 | BO29: =5*SIN($BH29) -> 4.330127 | BP29: =5*COS($BH29) -> -2.5
J30: =INDEX(posID,13)&"" -> NFR-16 | K30: =IF(J30="","",INDEX(posNome,13)&IF(INDEX(ANA_Attenzione_Supervisore,13)="Sì"," ◆","")) -> Vertenze e carenza di tecnici nei ruoli IT critici | BH30: =2*PI()*25/72 -> 2.1816616 | BI30: =2*SIN($BH30) -> 1.6383041 | BJ30: =2*COS($BH30) -> -1.1471529 | BK30: =3*SIN($BH30) -> 2.4574561 | BL30: =3*COS($BH30) -> -1.7207293 | BM30: =4*SIN($BH30) -> 3.2766082 | BN30: =4*COS($BH30) -> -2.2943057 | BO30: =5*SIN($BH30) -> 4.0957602 | BP30: =5*COS($BH30) -> -2.8678822
J31: =INDEX(posID,14)&"" | K31: =IF(J31="","",INDEX(posNome,14)&IF(INDEX(ANA_Attenzione_Supervisore,14)="Sì"," ◆","")) | BH31: =2*PI()*26/72 -> 2.268928 | BI31: =2*SIN($BH31) -> 1.5320889 | BJ31: =2*COS($BH31) -> -1.2855752 | BK31: =3*SIN($BH31) -> 2.2981333 | BL31: =3*COS($BH31) -> -1.9283628 | BM31: =4*SIN($BH31) -> 3.0641778 | BN31: =4*COS($BH31) -> -2.5711504 | BO31: =5*SIN($BH31) -> 3.8302222 | BP31: =5*COS($BH31) -> -3.213938
J32: =INDEX(posID,15)&"" | K32: =IF(J32="","",INDEX(posNome,15)&IF(INDEX(ANA_Attenzione_Supervisore,15)="Sì"," ◆","")) | BH32: =2*PI()*27/72 -> 2.3561945 | BI32: =2*SIN($BH32) -> 1.4142136 | BJ32: =2*COS($BH32) -> -1.4142136 | BK32: =3*SIN($BH32) -> 2.1213203 | BL32: =3*COS($BH32) -> -2.1213203 | BM32: =4*SIN($BH32) -> 2.8284271 | BN32: =4*COS($BH32) -> -2.8284271 | BO32: =5*SIN($BH32) -> 3.5355339 | BP32: =5*COS($BH32) -> -3.5355339
J33: =INDEX(posID,16)&"" | K33: =IF(J33="","",INDEX(posNome,16)&IF(INDEX(ANA_Attenzione_Supervisore,16)="Sì"," ◆","")) | BH33: =2*PI()*28/72 -> 2.443461 | BI33: =2*SIN($BH33) -> 1.2855752 | BJ33: =2*COS($BH33) -> -1.5320889 | BK33: =3*SIN($BH33) -> 1.9283628 | BL33: =3*COS($BH33) -> -2.2981333 | BM33: =4*SIN($BH33) -> 2.5711504 | BN33: =4*COS($BH33) -> -3.0641778 | BO33: =5*SIN($BH33) -> 3.213938 | BP33: =5*COS($BH33) -> -3.8302222
J34: =INDEX(posID,17)&"" | K34: =IF(J34="","",INDEX(posNome,17)&IF(INDEX(ANA_Attenzione_Supervisore,17)="Sì"," ◆","")) | BH34: =2*PI()*29/72 -> 2.5307274 | BI34: =2*SIN($BH34) -> 1.1471529 | BJ34: =2*COS($BH34) -> -1.6383041 | BK34: =3*SIN($BH34) -> 1.7207293 | BL34: =3*COS($BH34) -> -2.4574561 | BM34: =4*SIN($BH34) -> 2.2943057 | BN34: =4*COS($BH34) -> -3.2766082 | BO34: =5*SIN($BH34) -> 2.8678822 | BP34: =5*COS($BH34) -> -4.0957602
J35: =INDEX(posID,18)&"" | K35: =IF(J35="","",INDEX(posNome,18)&IF(INDEX(ANA_Attenzione_Supervisore,18)="Sì"," ◆","")) | BH35: =2*PI()*30/72 -> 2.6179939 | BI35: =2*SIN($BH35) -> 1 | BJ35: =2*COS($BH35) -> -1.7320508 | BK35: =3*SIN($BH35) -> 1.5 | BL35: =3*COS($BH35) -> -2.5980762 | BM35: =4*SIN($BH35) -> 2 | BN35: =4*COS($BH35) -> -3.4641016 | BO35: =5*SIN($BH35) -> 2.5 | BP35: =5*COS($BH35) -> -4.330127
J36: =INDEX(posID,19)&"" | K36: =IF(J36="","",INDEX(posNome,19)&IF(INDEX(ANA_Attenzione_Supervisore,19)="Sì"," ◆","")) | BH36: =2*PI()*31/72 -> 2.7052603 | BI36: =2*SIN($BH36) -> 0.84523652 | BJ36: =2*COS($BH36) -> -1.8126156 | BK36: =3*SIN($BH36) -> 1.2678548 | BL36: =3*COS($BH36) -> -2.7189234 | BM36: =4*SIN($BH36) -> 1.690473 | BN36: =4*COS($BH36) -> -3.6252311 | BO36: =5*SIN($BH36) -> 2.1130913 | BP36: =5*COS($BH36) -> -4.5315389
J37: =INDEX(posID,20)&"" | K37: =IF(J37="","",INDEX(posNome,20)&IF(INDEX(ANA_Attenzione_Supervisore,20)="Sì"," ◆","")) | BH37: =2*PI()*32/72 -> 2.7925268 | BI37: =2*SIN($BH37) -> 0.68404029 | BJ37: =2*COS($BH37) -> -1.8793852 | BK37: =3*SIN($BH37) -> 1.0260604 | BL37: =3*COS($BH37) -> -2.8190779 | BM37: =4*SIN($BH37) -> 1.3680806 | BN37: =4*COS($BH37) -> -3.7587705 | BO37: =5*SIN($BH37) -> 1.7101007 | BP37: =5*COS($BH37) -> -4.6984631
A38: Radar: piu' vicino al centro = agire prima; area del cerchio = P x I; colore = livello di allerta (rosso attivazione, giallo attenzione, verde monitoraggio); ◆ = attenzione del supervisore. Numeri nel radar = NFR-nn. | BH38: =2*PI()*33/72 -> 2.8797933 | BI38: =2*SIN($BH38) -> 0.51763809 | BJ38: =2*COS($BH38) -> -1.9318517 | BK38: =3*SIN($BH38) -> 0.77645714 | BL38: =3*COS($BH38) -> -2.8977775 | BM38: =4*SIN($BH38) -> 1.0352762 | BN38: =4*COS($BH38) -> -3.8637033 | BO38: =5*SIN($BH38) -> 1.2940952 | BP38: =5*COS($BH38) -> -4.8296291
BH39: =2*PI()*34/72 -> 2.9670597 | BI39: =2*SIN($BH39) -> 0.34729636 | BJ39: =2*COS($BH39) -> -1.9696155 | BK39: =3*SIN($BH39) -> 0.52094453 | BL39: =3*COS($BH39) -> -2.9544233 | BM39: =4*SIN($BH39) -> 0.69459271 | BN39: =4*COS($BH39) -> -3.939231 | BO39: =5*SIN($BH39) -> 0.86824089 | BP39: =5*COS($BH39) -> -4.9240388
A40: Il commento dell'analisi (agente A1, scritto prima della validazione) | BH40: =2*PI()*35/72 -> 3.0543262 | BI40: =2*SIN($BH40) -> 0.17431149 | BJ40: =2*COS($BH40) -> -1.9923894 | BK40: =3*SIN($BH40) -> 0.26146723 | BL40: =3*COS($BH40) -> -2.9885841 | BM40: =4*SIN($BH40) -> 0.34862297 | BN40: =4*COS($BH40) -> -3.9847788 | BO40: =5*SIN($BH40) -> 0.43577871 | BP40: =5*COS($BH40) -> -4.9809735
A41: Messaggio chiave | D41: =IF(T41="","Nessun commento registrato per il ciclo corrente.",TRIM(SUBSTITUTE(SUBSTITUTE(IF(T42>0,LEFT(T41,T42-1),T41),"MESSAGGIO:",""),"Messaggio:",""))) -> Nel quarto trimestre 2026 entra nel radar il rischio sui rapporti di impiego (NFR-16), in osservazione dal 2026Q3: la vertenza nazionale del settore e la carenza di tecnici in ruoli IT critici, segnalate dall'aggiornamento settimanale, hanno ora un riscontro interno. Sale la prossimita' delle frodi con voce sintetica (NFR-01) dopo i primi casi su clienti della Banca. Gli altri undici rischi del radar sono confermati. In osservazione si avvicinano i cavi sottomarini (NFR-14, Probabilita da 2 a 3), ancora lontani dalle rotte italiane. | T41: =IFERROR(INDEX(SI_Sintesi_A1,MATCH(cicloCorrente,SI_Ciclo,0))&"","") -> Nel quarto trimestre 2026 entra nel radar il rischio sui rapporti di impiego (NFR-16), in osservazione dal 2026Q3: la vertenza nazionale del settore e la carenza di tecnici in ruoli IT critici, segnalate dall'aggiornamento settimanale, hanno ora un riscontro interno. Sale la prossimita' delle frodi con voce sintetica (NFR-01) dopo i primi casi su clienti della Banca. Gli altri undici rischi del radar sono confermati. In osservazione si avvicinano i cavi sottomarini (NFR-14, Probabilita da 2 a 3), ancora lontani dalle rotte italiane. | BH41: =2*PI()*36/72 -> 3.1415927 | BI41: =2*SIN($BH41) -> 2.4502969e-16 | BJ41: =2*COS($BH41) -> -2 | BK41: =3*SIN($BH41) -> 3.6754454e-16 | BL41: =3*COS($BH41) -> -3 | BM41: =4*SIN($BH41) -> 4.9005938e-16 | BN41: =4*COS($BH41) -> -4 | BO41: =5*SIN($BH41) -> 6.1257423e-16 | BP41: =5*COS($BH41) -> -5
A42: Decisioni richieste | D42: =IF(T42>0,TRIM(MID(T41,T42+10,4000)),"—") -> — | T42: =IFERROR(SEARCH("DECISIONI:",T41),0) -> 0 | BH42: =2*PI()*37/72 -> 3.2288591 | BI42: =2*SIN($BH42) -> -0.17431149 | BJ42: =2*COS($BH42) -> -1.9923894 | BK42: =3*SIN($BH42) -> -0.26146723 | BL42: =3*COS($BH42) -> -2.9885841 | BM42: =4*SIN($BH42) -> -0.34862297 | BN42: =4*COS($BH42) -> -3.9847788 | BO42: =5*SIN($BH42) -> -0.43577871 | BP42: =5*COS($BH42) -> -4.9809735
A43: Controlli (A5 se usato) | D43: =IFERROR(INDEX(SI_Sintesi_A5,MATCH(cicloCorrente,SI_Ciclo,0))&"","")&IFERROR(" Osservazioni: "&INDEX(SI_Osservazioni_Controlli,MATCH(cicloCorrente,SI_Ciclo,0))&".","") -> A5 non usato in questo ciclo (facoltativo, D-71): valgono i controlli dello script e la validazione. Osservazioni: 0. | BH43: =2*PI()*38/72 -> 3.3161256 | BI43: =2*SIN($BH43) -> -0.34729636 | BJ43: =2*COS($BH43) -> -1.9696155 | BK43: =3*SIN($BH43) -> -0.52094453 | BL43: =3*COS($BH43) -> -2.9544233 | BM43: =4*SIN($BH43) -> -0.69459271 | BN43: =4*COS($BH43) -> -3.939231 | BO43: =5*SIN($BH43) -> -0.86824089 | BP43: =5*COS($BH43) -> -4.9240388
A44: Dopo il commento | D44: =IF((COUNTIFS(VAL_Periodo,cicloCorrente,VAL_Stato,"Applicata",VAL_Decisione,"Rettificato")+COUNTIFS(VAL_Periodo,cicloCorrente,VAL_Stato,"Applicata",VAL_Decisione,"Respinto",VAL_Oggetto,"KRI",VAL_Campo,"Valore_Corrente")+COUNTIFS(VAL_Periodo,cicloCorrente,VAL_Stato,"Applicata",VAL_Decisione,"Respinto",VAL_Oggetto,"Azione",VAL_Campo,"Owner"))>0,"Il validatore ha applicato "&(COUNTIFS(VAL_Periodo,cicloCorrente,VAL_Stato,"Applicata",VAL_Decisione,"Rettificato")+COUNTIFS(VAL_Periodo,cicloCorrente,VAL_Stato,"Applicata",VAL_Decisione,"Respinto",VAL_Oggetto,"KRI",VAL_Campo,"Valore_Corrente")+COUNTIFS(VAL_Periodo,cicloCorrente,VAL_Stato,"Applicata",VAL_Decisione,"Respinto",VAL_Oggetto,"Azione",VAL_Campo,"Owner"))&" rettifiche o respingimenti: numeri e grafici del report sono quelli validati e prevalgono sul commento.","") | BH44: =2*PI()*39/72 -> 3.403392 | BI44: =2*SIN($BH44) -> -0.51763809 | BJ44: =2*COS($BH44) -> -1.9318517 | BK44: =3*SIN($BH44) -> -0.77645714 | BL44: =3*COS($BH44) -> -2.8977775 | BM44: =4*SIN($BH44) -> -1.0352762 | BN44: =4*COS($BH44) -> -3.8637033 | BO44: =5*SIN($BH44) -> -1.2940952 | BP44: =5*COS($BH44) -> -4.8296291
A45: Segnalazioni da motivare | D45: =IFERROR(IF(INDEX(SI_Rilievi_Superati,MATCH(cicloCorrente,SI_Ciclo,0))="","",INDEX(SI_Rilievi_Superati,MATCH(cicloCorrente,SI_Ciclo,0))&" In validazione ogni rischio interessato chiede una motivazione (colonna Segnalazioni)."),"") | BH45: =2*PI()*40/72 -> 3.4906585 | BI45: =2*SIN($BH45) -> -0.68404029 | BJ45: =2*COS($BH45) -> -1.8793852 | BK45: =3*SIN($BH45) -> -1.0260604 | BL45: =3*COS($BH45) -> -2.8190779 | BM45: =4*SIN($BH45) -> -1.3680806 | BN45: =4*COS($BH45) -> -3.7587705 | BO45: =5*SIN($BH45) -> -1.7101007 | BP45: =5*COS($BH45) -> -4.6984631
BH46: =2*PI()*41/72 -> 3.577925 | BI46: =2*SIN($BH46) -> -0.84523652 | BJ46: =2*COS($BH46) -> -1.8126156 | BK46: =3*SIN($BH46) -> -1.2678548 | BL46: =3*COS($BH46) -> -2.7189234 | BM46: =4*SIN($BH46) -> -1.690473 | BN46: =4*COS($BH46) -> -3.6252311 | BO46: =5*SIN($BH46) -> -2.1130913 | BP46: =5*COS($BH46) -> -4.5315389
A47: Rischi segnalati e perche' | BH47: =2*PI()*42/72 -> 3.6651914 | BI47: =2*SIN($BH47) -> -1 | BJ47: =2*COS($BH47) -> -1.7320508 | BK47: =3*SIN($BH47) -> -1.5 | BL47: =3*COS($BH47) -> -2.5980762 | BM47: =4*SIN($BH47) -> -2 | BN47: =4*COS($BH47) -> -3.4641016 | BO47: =5*SIN($BH47) -> -2.5 | BP47: =5*COS($BH47) -> -4.330127
A48: Rischi fra i primi tre per score, in attivazione o in attenzione, variati o nuovi nel ciclo. Tutto calcolato dai dati validati del registro. | BH48: =2*PI()*43/72 -> 3.7524579 | BI48: =2*SIN($BH48) -> -1.1471529 | BJ48: =2*COS($BH48) -> -1.6383041 | BK48: =3*SIN($BH48) -> -1.7207293 | BL48: =3*COS($BH48) -> -2.4574561 | BM48: =4*SIN($BH48) -> -2.2943057 | BN48: =4*COS($BH48) -> -3.2766082 | BO48: =5*SIN($BH48) -> -2.8678822 | BP48: =5*COS($BH48) -> -4.0957602
A49: Rischio | D49: Livello | E49: Perche' lo segnaliamo | I49: Cosa e' cambiato, e su quale evidenza | BH49: =2*PI()*44/72 -> 3.8397244 | BI49: =2*SIN($BH49) -> -1.2855752 | BJ49: =2*COS($BH49) -> -1.5320889 | BK49: =3*SIN($BH49) -> -1.9283628 | BL49: =3*COS($BH49) -> -2.2981333 | BM49: =4*SIN($BH49) -> -2.5711504 | BN49: =4*COS($BH49) -> -3.0641778 | BO49: =5*SIN($BH49) -> -3.213938 | BP49: =5*COS($BH49) -> -3.8302222
A50: =IF($V50="","",INDEX(Classifica!$B$5:$B$24,$V50)&CHAR(10)&INDEX(Classifica!$C$5:$C$24,$V50)&IF(INDEX(ANA_Attenzione_Supervisore,INDEX(Classifica!$U$5:$U$24,$V50))="Sì",CHAR(10)&"◆ attenzione del supervisore","")) -> NFR-01 Frodi su pagamenti istantanei abilitate da AI generativa ◆ attenzione del supervisore | D50: =IF($V50="","",INDEX(Radar_Mosca!$AA$5:$AA$24,INDEX(Classifica!$U$5:$U$24,$V50))&"") -> Attivazione | E50: =IF($W50="","",LEFT($W50,LEN($W50)-2)&".") -> 1° per score composito (4,40, +0,20 sul ciclo prima); AGIRE ORA: servono X + Y = 0,50 anni per decidere e mitigare; ne restano Z = 0,0 prima che possa manifestarsi; variato nel ciclo: peggiora; tema all'attenzione del supervisore; 1 KRI in rosso; notizie in peggioramento (+3 segnali netti in 4 settimane). | I50: =IF($V50="","",IF(INDEX(Classifica!$G$5:$G$24,$V50)="Nuovo","Rischio nuovo nel ciclo.",IFERROR(IF(INDEX(RR_Variazioni,MATCH(cicloCorrente&"|"&INDEX(Classifica!$B$5:$B$24,$V50),RR_Chiave,0))&""="[]","Nessun valore cambiato: confermato sulle fonti del ciclo precedente.",SUBSTITUTE(SUBSTITUTE(SUBSTITUTE(SUBSTITUTE(SUBSTITUTE(SUBSTITUTE(SUBSTITUTE(SUBSTITUTE(SUBSTITUTE(SUBSTITUTE(SUBSTITUTE(SUBSTITUTE(SUBSTITUTE(SUBSTITUTE(SUBSTITUTE(INDEX(RR_Variazioni,MATCH(cicloCorrente&"|"&INDEX(Classifica!$B$5:$B$24,$V50),RR_Chiave,0))&"","[{""dimensione"": ""","• "),"""}, {""dimensione"": """,")"&CHAR(10)&"• "),""", ""da"": "," "),", ""a"": "," → "),", ""evidenza"": """,": "),""", ""data_evidenza"": """," ("),"""}]",")")," null → "," n.v. → ")," → null:"," → n.v.:"),"• impatto","• Impatto"),"• velocity","• Velocity"),"• prossimita","• Prossimita"),"• confidence","• Confidence"),"• probabilita","• Probabilita"),"• severity","• Impatto")),""))) -> • Prossimita 4 → 5: L'incident report del 20 novembre 2026 documenta due frodi con voce sintetica su clienti corporate della Banca, per bonifici istantanei gia' eseguiti. (2026-11-20) | U50: =IF(Classifica!$B$5="","",IF(OR(1<=3,INDEX(Radar_Mosca!$AA$5:$AA$24,Classifica!$U$5)="Attivazione",INDEX(Radar_Mosca!$AA$5:$AA$24,Classifica!$U$5)="Attenzione",Classifica!$G$5="Variato",Classifica!$G$5="Nuovo"),1,"")) -> 1 | V50: =IFERROR(_xlfn.AGGREGATE(15,6,$U$50:$U$69,1),"") -> 1 | W50: =IF($V50="","",IF($V50<=3,$V50&"° per score composito ("&FIXED(INDEX(Classifica!$D$5:$D$24,$V50),2)&IF(ISNUMBER(INDEX(Classifica!$F$5:$F$24,$V50)),IF(INDEX(Classifica!$F$5:$F$24,$V50)<>0,", "&IF(INDEX(Classifica!$F$5:$F$24,$V50)>0,"+","")&FIXED(INDEX(Classifica!$F$5:$F$24,$V50),2)&" sul ciclo prima",""),"")&"); ","")&IF(LEFT(INDEX(Classifica!$H$5:$H$24,$V50),9)="AGIRE ORA","AGIRE ORA: servono X + Y = "&FIXED(INDEX(Classifica!$Y$5:$Y$24,$V50)+INDEX(Classifica!$Z$5:$Z$24,$V50),2)&" anni per decidere e mitigare"&IF(N(INDEX(ANA_Anni_Adeguamento,INDEX(Classifica!$U$5:$U$24,$V50)))>0,", di cui "&N(INDEX(ANA_Anni_Adeguamento,INDEX(Classifica!$U$5:$U$24,$V50)))&" di adeguamento strutturale","")&"; ne restano Z = "&FIXED(INDEX(Classifica!$AA$5:$AA$24,$V50),1)&" prima che possa manifestarsi; ",IF(AND($V50<=3,LEFT(INDEX(Classifica!$H$5:$H$24,$V50),11)="Agire entro"),"margine di Mosca sotto l'anno ("&FIXED(INDEX(Classifica!$I$5:$I$24,$V50),2)&"); ",""))&IF(INDEX(Classifica!$G$5:$G$24,$V50)="Variato","variato nel ciclo"&IF(ISNUMBER(INDEX(Classifica!$F$5:$F$24,$V50)),IF(INDEX(Classifica!$F$5:$F$24,$V50)>0,": peggiora",IF(INDEX(Classifica!$F$5:$F$24,$V50)<0,": migliora","")),"")&"; ",IF(INDEX(Classifica!$G$5:$G$24,$V50)="Nuovo","nuovo nel ciclo; ",""))&IF(INDEX(ANA_Attenzione_Supervisore,INDEX(Classifica!$U$5:$U$24,$V50))="Sì","tema all'attenzione del supervisore; ","")&IF(INDEX(ANA_Presidio_Controlli,INDEX(Classifica!$U$5:$U$24,$V50))="Assente","presidio dei controlli assente; ","")&IF(COUNTIFS(KRI_ID_Rischio,INDEX(Classifica!$B$5:$B$24,$V50),KRI_Ciclo,cicloCorrente,KRI_In_Vigore,"Sì",KRI_Stato,"Rosso")>0,COUNTIFS(KRI_ID_Rischio,INDEX(Classifica!$B$5:$B$24,$V50),KRI_Ciclo,cicloCorrente,KRI_In_Vigore,"Sì",KRI_Stato,"Rosso")&" KRI in rosso; ","")&IF(INDEX(posNetti,INDEX(Classifica!$U$5:$U$24,$V50))>=sogliaDirezione,"notizie in peggioramento (+"&INDEX(posNetti,INDEX(Classifica!$U$5:$U$24,$V50))&" segnali netti in 4 settimane); ",IF(INDEX(posNetti,INDEX(Classifica!$U$5:$U$24,$V50))<=-sogliaDirezione,"notizie in miglioramento ("&INDEX(posNetti,INDEX(Classifica!$U$5:$U$24,$V50))&" segnali netti in 4 settimane); ",""))) -> 1° per score composito (4,40, +0,20 sul ciclo prima); AGIRE ORA: servono X + Y = 0,50 anni per decidere e mitigare; ne restano Z = 0,0 prima che possa manifestarsi; variato nel ciclo: peggiora; tema all'attenzione del supervisore; 1 KRI in rosso; notizie in peggioramento (+3 segnali netti in 4 settimane); | BH50: =2*PI()*45/72 -> 3.9269908 | BI50: =2*SIN($BH50) -> -1.4142136 | BJ50: =2*COS($BH50) -> -1.4142136 | BK50: =3*SIN($BH50) -> -2.1213203 | BL50: =3*COS($BH50) -> -2.1213203 | BM50: =4*SIN($BH50) -> -2.8284271 | BN50: =4*COS($BH50) -> -2.8284271 | BO50: =5*SIN($BH50) -> -3.5355339 | BP50: =5*COS($BH50) -> -3.5355339
A51: =IF($V51="","",INDEX(Classifica!$B$5:$B$24,$V51)&CHAR(10)&INDEX(Classifica!$C$5:$C$24,$V51)&IF(INDEX(ANA_Attenzione_Supervisore,INDEX(Classifica!$U$5:$U$24,$V51))="Sì",CHAR(10)&"◆ attenzione del supervisore","")) -> NFR-07 Ransomware presso un fornitore di servizi di pagamento ◆ attenzione del supervisore | D51: =IF($V51="","",INDEX(Radar_Mosca!$AA$5:$AA$24,INDEX(Classifica!$U$5:$U$24,$V51))&"") -> Attenzione | E51: =IF($W51="","",LEFT($W51,LEN($W51)-2)&".") -> 2° per score composito (3,75); margine di Mosca sotto l'anno (0,75); tema all'attenzione del supervisore. | I51: =IF($V51="","",IF(INDEX(Classifica!$G$5:$G$24,$V51)="Nuovo","Rischio nuovo nel ciclo.",IFERROR(IF(INDEX(RR_Variazioni,MATCH(cicloCorrente&"|"&INDEX(Classifica!$B$5:$B$24,$V51),RR_Chiave,0))&""="[]","Nessun valore cambiato: confermato sulle fonti del ciclo precedente.",SUBSTITUTE(SUBSTITUTE(SUBSTITUTE(SUBSTITUTE(SUBSTITUTE(SUBSTITUTE(SUBSTITUTE(SUBSTITUTE(SUBSTITUTE(SUBSTITUTE(SUBSTITUTE(SUBSTITUTE(SUBSTITUTE(SUBSTITUTE(SUBSTITUTE(INDEX(RR_Variazioni,MATCH(cicloCorrente&"|"&INDEX(Classifica!$B$5:$B$24,$V51),RR_Chiave,0))&"","[{""dimensione"": ""","• "),"""}, {""dimensione"": """,")"&CHAR(10)&"• "),""", ""da"": "," "),", ""a"": "," → "),", ""evidenza"": """,": "),""", ""data_evidenza"": """," ("),"""}]",")")," null → "," n.v. → ")," → null:"," → n.v.:"),"• impatto","• Impatto"),"• velocity","• Velocity"),"• prossimita","• Prossimita"),"• confidence","• Confidence"),"• probabilita","• Probabilita"),"• severity","• Impatto")),""))) -> Nessun valore cambiato: confermato sulle fonti del ciclo precedente. | U51: =IF(Classifica!$B$6="","",IF(OR(2<=3,INDEX(Radar_Mosca!$AA$5:$AA$24,Classifica!$U$6)="Attivazione",INDEX(Radar_Mosca!$AA$5:$AA$24,Classifica!$U$6)="Attenzione",Classifica!$G$6="Variato",Classifica!$G$6="Nuovo"),2,"")) -> 2 | V51: =IFERROR(_xlfn.AGGREGATE(15,6,$U$50:$U$69,2),"") -> 2 | W51: =IF($V51="","",IF($V51<=3,$V51&"° per score composito ("&FIXED(INDEX(Classifica!$D$5:$D$24,$V51),2)&IF(ISNUMBER(INDEX(Classifica!$F$5:$F$24,$V51)),IF(INDEX(Classifica!$F$5:$F$24,$V51)<>0,", "&IF(INDEX(Classifica!$F$5:$F$24,$V51)>0,"+","")&FIXED(INDEX(Classifica!$F$5:$F$24,$V51),2)&" sul ciclo prima",""),"")&"); ","")&IF(LEFT(INDEX(Classifica!$H$5:$H$24,$V51),9)="AGIRE ORA","AGIRE ORA: servono X + Y = "&FIXED(INDEX(Classifica!$Y$5:$Y$24,$V51)+INDEX(Classifica!$Z$5:$Z$24,$V51),2)&" anni per decidere e mitigare"&IF(N(INDEX(ANA_Anni_Adeguamento,INDEX(Classifica!$U$5:$U$24,$V51)))>0,", di cui "&N(INDEX(ANA_Anni_Adeguamento,INDEX(Classifica!$U$5:$U$24,$V51)))&" di adeguamento strutturale","")&"; ne restano Z = "&FIXED(INDEX(Classifica!$AA$5:$AA$24,$V51),1)&" prima che possa manifestarsi; ",IF(AND($V51<=3,LEFT(INDEX(Classifica!$H$5:$H$24,$V51),11)="Agire entro"),"margine di Mosca sotto l'anno ("&FIXED(INDEX(Classifica!$I$5:$I$24,$V51),2)&"); ",""))&IF(INDEX(Classifica!$G$5:$G$24,$V51)="Variato","variato nel ciclo"&IF(ISNUMBER(INDEX(Classifica!$F$5:$F$24,$V51)),IF(INDEX(Classifica!$F$5:$F$24,$V51)>0,": peggiora",IF(INDEX(Classifica!$F$5:$F$24,$V51)<0,": migliora","")),"")&"; ",IF(INDEX(Classifica!$G$5:$G$24,$V51)="Nuovo","nuovo nel ciclo; ",""))&IF(INDEX(ANA_Attenzione_Supervisore,INDEX(Classifica!$U$5:$U$24,$V51))="Sì","tema all'attenzione del supervisore; ","")&IF(INDEX(ANA_Presidio_Controlli,INDEX(Classifica!$U$5:$U$24,$V51))="Assente","presidio dei controlli assente; ","")&IF(COUNTIFS(KRI_ID_Rischio,INDEX(Classifica!$B$5:$B$24,$V51),KRI_Ciclo,cicloCorrente,KRI_In_Vigore,"Sì",KRI_Stato,"Rosso")>0,COUNTIFS(KRI_ID_Rischio,INDEX(Classifica!$B$5:$B$24,$V51),KRI_Ciclo,cicloCorrente,KRI_In_Vigore,"Sì",KRI_Stato,"Rosso")&" KRI in rosso; ","")&IF(INDEX(posNetti,INDEX(Classifica!$U$5:$U$24,$V51))>=sogliaDirezione,"notizie in peggioramento (+"&INDEX(posNetti,INDEX(Classifica!$U$5:$U$24,$V51))&" segnali netti in 4 settimane); ",IF(INDEX(posNetti,INDEX(Classifica!$U$5:$U$24,$V51))<=-sogliaDirezione,"notizie in miglioramento ("&INDEX(posNetti,INDEX(Classifica!$U$5:$U$24,$V51))&" segnali netti in 4 settimane); ",""))) -> 2° per score composito (3,75); margine di Mosca sotto l'anno (0,75); tema all'attenzione del supervisore; | BH51: =2*PI()*46/72 -> 4.0142573 | BI51: =2*SIN($BH51) -> -1.5320889 | BJ51: =2*COS($BH51) -> -1.2855752 | BK51: =3*SIN($BH51) -> -2.2981333 | BL51: =3*COS($BH51) -> -1.9283628 | BM51: =4*SIN($BH51) -> -3.0641778 | BN51: =4*COS($BH51) -> -2.5711504 | BO51: =5*SIN($BH51) -> -3.8302222 | BP51: =5*COS($BH51) -> -3.213938
A52: =IF($V52="","",INDEX(Classifica!$B$5:$B$24,$V52)&CHAR(10)&INDEX(Classifica!$C$5:$C$24,$V52)&IF(INDEX(ANA_Attenzione_Supervisore,INDEX(Classifica!$U$5:$U$24,$V52))="Sì",CHAR(10)&"◆ attenzione del supervisore","")) -> NFR-12 Errori operativi nei pagamenti istantanei obbligatori | D52: =IF($V52="","",INDEX(Radar_Mosca!$AA$5:$AA$24,INDEX(Classifica!$U$5:$U$24,$V52))&"") -> Attenzione | E52: =IF($W52="","",LEFT($W52,LEN($W52)-2)&".") -> 3° per score composito (3,65); margine di Mosca sotto l'anno (0,00). | I52: =IF($V52="","",IF(INDEX(Classifica!$G$5:$G$24,$V52)="Nuovo","Rischio nuovo nel ciclo.",IFERROR(IF(INDEX(RR_Variazioni,MATCH(cicloCorrente&"|"&INDEX(Classifica!$B$5:$B$24,$V52),RR_Chiave,0))&""="[]","Nessun valore cambiato: confermato sulle fonti del ciclo precedente.",SUBSTITUTE(SUBSTITUTE(SUBSTITUTE(SUBSTITUTE(SUBSTITUTE(SUBSTITUTE(SUBSTITUTE(SUBSTITUTE(SUBSTITUTE(SUBSTITUTE(SUBSTITUTE(SUBSTITUTE(SUBSTITUTE(SUBSTITUTE(SUBSTITUTE(INDEX(RR_Variazioni,MATCH(cicloCorrente&"|"&INDEX(Classifica!$B$5:$B$24,$V52),RR_Chiave,0))&"","[{""dimensione"": ""","• "),"""}, {""dimensione"": """,")"&CHAR(10)&"• "),""", ""da"": "," "),", ""a"": "," → "),", ""evidenza"": """,": "),""", ""data_evidenza"": """," ("),"""}]",")")," null → "," n.v. → ")," → null:"," → n.v.:"),"• impatto","• Impatto"),"• velocity","• Velocity"),"• prossimita","• Prossimita"),"• confidence","• Confidence"),"• probabilita","• Probabilita"),"• severity","• Impatto")),""))) -> Nessun valore cambiato: confermato sulle fonti del ciclo precedente. | U52: =IF(Classifica!$B$7="","",IF(OR(3<=3,INDEX(Radar_Mosca!$AA$5:$AA$24,Classifica!$U$7)="Attivazione",INDEX(Radar_Mosca!$AA$5:$AA$24,Classifica!$U$7)="Attenzione",Classifica!$G$7="Variato",Classifica!$G$7="Nuovo"),3,"")) -> 3 | V52: =IFERROR(_xlfn.AGGREGATE(15,6,$U$50:$U$69,3),"") -> 3 | W52: =IF($V52="","",IF($V52<=3,$V52&"° per score composito ("&FIXED(INDEX(Classifica!$D$5:$D$24,$V52),2)&IF(ISNUMBER(INDEX(Classifica!$F$5:$F$24,$V52)),IF(INDEX(Classifica!$F$5:$F$24,$V52)<>0,", "&IF(INDEX(Classifica!$F$5:$F$24,$V52)>0,"+","")&FIXED(INDEX(Classifica!$F$5:$F$24,$V52),2)&" sul ciclo prima",""),"")&"); ","")&IF(LEFT(INDEX(Classifica!$H$5:$H$24,$V52),9)="AGIRE ORA","AGIRE ORA: servono X + Y = "&FIXED(INDEX(Classifica!$Y$5:$Y$24,$V52)+INDEX(Classifica!$Z$5:$Z$24,$V52),2)&" anni per decidere e mitigare"&IF(N(INDEX(ANA_Anni_Adeguamento,INDEX(Classifica!$U$5:$U$24,$V52)))>0,", di cui "&N(INDEX(ANA_Anni_Adeguamento,INDEX(Classifica!$U$5:$U$24,$V52)))&" di adeguamento strutturale","")&"; ne restano Z = "&FIXED(INDEX(Classifica!$AA$5:$AA$24,$V52),1)&" prima che possa manifestarsi; ",IF(AND($V52<=3,LEFT(INDEX(Classifica!$H$5:$H$24,$V52),11)="Agire entro"),"margine di Mosca sotto l'anno ("&FIXED(INDEX(Classifica!$I$5:$I$24,$V52),2)&"); ",""))&IF(INDEX(Classifica!$G$5:$G$24,$V52)="Variato","variato nel ciclo"&IF(ISNUMBER(INDEX(Classifica!$F$5:$F$24,$V52)),IF(INDEX(Classifica!$F$5:$F$24,$V52)>0,": peggiora",IF(INDEX(Classifica!$F$5:$F$24,$V52)<0,": migliora","")),"")&"; ",IF(INDEX(Classifica!$G$5:$G$24,$V52)="Nuovo","nuovo nel ciclo; ",""))&IF(INDEX(ANA_Attenzione_Supervisore,INDEX(Classifica!$U$5:$U$24,$V52))="Sì","tema all'attenzione del supervisore; ","")&IF(INDEX(ANA_Presidio_Controlli,INDEX(Classifica!$U$5:$U$24,$V52))="Assente","presidio dei controlli assente; ","")&IF(COUNTIFS(KRI_ID_Rischio,INDEX(Classifica!$B$5:$B$24,$V52),KRI_Ciclo,cicloCorrente,KRI_In_Vigore,"Sì",KRI_Stato,"Rosso")>0,COUNTIFS(KRI_ID_Rischio,INDEX(Classifica!$B$5:$B$24,$V52),KRI_Ciclo,cicloCorrente,KRI_In_Vigore,"Sì",KRI_Stato,"Rosso")&" KRI in rosso; ","")&IF(INDEX(posNetti,INDEX(Classifica!$U$5:$U$24,$V52))>=sogliaDirezione,"notizie in peggioramento (+"&INDEX(posNetti,INDEX(Classifica!$U$5:$U$24,$V52))&" segnali netti in 4 settimane); ",IF(INDEX(posNetti,INDEX(Classifica!$U$5:$U$24,$V52))<=-sogliaDirezione,"notizie in miglioramento ("&INDEX(posNetti,INDEX(Classifica!$U$5:$U$24,$V52))&" segnali netti in 4 settimane); ",""))) -> 3° per score composito (3,65); margine di Mosca sotto l'anno (0,00); | BH52: =2*PI()*47/72 -> 4.1015237 | BI52: =2*SIN($BH52) -> -1.6383041 | BJ52: =2*COS($BH52) -> -1.1471529 | BK52: =3*SIN($BH52) -> -2.4574561 | BL52: =3*COS($BH52) -> -1.7207293 | BM52: =4*SIN($BH52) -> -3.2766082 | BN52: =4*COS($BH52) -> -2.2943057 | BO52: =5*SIN($BH52) -> -4.0957602 | BP52: =5*COS($BH52) -> -2.8678822
A53: =IF($V53="","",INDEX(Classifica!$B$5:$B$24,$V53)&CHAR(10)&INDEX(Classifica!$C$5:$C$24,$V53)&IF(INDEX(ANA_Attenzione_Supervisore,INDEX(Classifica!$U$5:$U$24,$V53))="Sì",CHAR(10)&"◆ attenzione del supervisore","")) -> NFR-03 Greenwashing nella commercializzazione di prodotti ESG | D53: =IF($V53="","",INDEX(Radar_Mosca!$AA$5:$AA$24,INDEX(Classifica!$U$5:$U$24,$V53))&"") -> Attenzione | E53: =IF($W53="","",LEFT($W53,LEN($W53)-2)&".") | I53: =IF($V53="","",IF(INDEX(Classifica!$G$5:$G$24,$V53)="Nuovo","Rischio nuovo nel ciclo.",IFERROR(IF(INDEX(RR_Variazioni,MATCH(cicloCorrente&"|"&INDEX(Classifica!$B$5:$B$24,$V53),RR_Chiave,0))&""="[]","Nessun valore cambiato: confermato sulle fonti del ciclo precedente.",SUBSTITUTE(SUBSTITUTE(SUBSTITUTE(SUBSTITUTE(SUBSTITUTE(SUBSTITUTE(SUBSTITUTE(SUBSTITUTE(SUBSTITUTE(SUBSTITUTE(SUBSTITUTE(SUBSTITUTE(SUBSTITUTE(SUBSTITUTE(SUBSTITUTE(INDEX(RR_Variazioni,MATCH(cicloCorrente&"|"&INDEX(Classifica!$B$5:$B$24,$V53),RR_Chiave,0))&"","[{""dimensione"": ""","• "),"""}, {""dimensione"": """,")"&CHAR(10)&"• "),""", ""da"": "," "),", ""a"": "," → "),", ""evidenza"": """,": "),""", ""data_evidenza"": """," ("),"""}]",")")," null → "," n.v. → ")," → null:"," → n.v.:"),"• impatto","• Impatto"),"• velocity","• Velocity"),"• prossimita","• Prossimita"),"• confidence","• Confidence"),"• probabilita","• Probabilita"),"• severity","• Impatto")),""))) -> Nessun valore cambiato: confermato sulle fonti del ciclo precedente. | U53: =IF(Classifica!$B$8="","",IF(OR(4<=3,INDEX(Radar_Mosca!$AA$5:$AA$24,Classifica!$U$8)="Attivazione",INDEX(Radar_Mosca!$AA$5:$AA$24,Classifica!$U$8)="Attenzione",Classifica!$G$8="Variato",Classifica!$G$8="Nuovo"),4,"")) | V53: =IFERROR(_xlfn.AGGREGATE(15,6,$U$50:$U$69,4),"") -> 5 | W53: =IF($V53="","",IF($V53<=3,$V53&"° per score composito ("&FIXED(INDEX(Classifica!$D$5:$D$24,$V53),2)&IF(ISNUMBER(INDEX(Classifica!$F$5:$F$24,$V53)),IF(INDEX(Classifica!$F$5:$F$24,$V53)<>0,", "&IF(INDEX(Classifica!$F$5:$F$24,$V53)>0,"+","")&FIXED(INDEX(Classifica!$F$5:$F$24,$V53),2)&" sul ciclo prima",""),"")&"); ","")&IF(LEFT(INDEX(Classifica!$H$5:$H$24,$V53),9)="AGIRE ORA","AGIRE ORA: servono X + Y = "&FIXED(INDEX(Classifica!$Y$5:$Y$24,$V53)+INDEX(Classifica!$Z$5:$Z$24,$V53),2)&" anni per decidere e mitigare"&IF(N(INDEX(ANA_Anni_Adeguamento,INDEX(Classifica!$U$5:$U$24,$V53)))>0,", di cui "&N(INDEX(ANA_Anni_Adeguamento,INDEX(Classifica!$U$5:$U$24,$V53)))&" di adeguamento strutturale","")&"; ne restano Z = "&FIXED(INDEX(Classifica!$AA$5:$AA$24,$V53),1)&" prima che possa manifestarsi; ",IF(AND($V53<=3,LEFT(INDEX(Classifica!$H$5:$H$24,$V53),11)="Agire entro"),"margine di Mosca sotto l'anno ("&FIXED(INDEX(Classifica!$I$5:$I$24,$V53),2)&"); ",""))&IF(INDEX(Classifica!$G$5:$G$24,$V53)="Variato","variato nel ciclo"&IF(ISNUMBER(INDEX(Classifica!$F$5:$F$24,$V53)),IF(INDEX(Classifica!$F$5:$F$24,$V53)>0,": peggiora",IF(INDEX(Classifica!$F$5:$F$24,$V53)<0,": migliora","")),"")&"; ",IF(INDEX(Classifica!$G$5:$G$24,$V53)="Nuovo","nuovo nel ciclo; ",""))&IF(INDEX(ANA_Attenzione_Supervisore,INDEX(Classifica!$U$5:$U$24,$V53))="Sì","tema all'attenzione del supervisore; ","")&IF(INDEX(ANA_Presidio_Controlli,INDEX(Classifica!$U$5:$U$24,$V53))="Assente","presidio dei controlli assente; ","")&IF(COUNTIFS(KRI_ID_Rischio,INDEX(Classifica!$B$5:$B$24,$V53),KRI_Ciclo,cicloCorrente,KRI_In_Vigore,"Sì",KRI_Stato,"Rosso")>0,COUNTIFS(KRI_ID_Rischio,INDEX(Classifica!$B$5:$B$24,$V53),KRI_Ciclo,cicloCorrente,KRI_In_Vigore,"Sì",KRI_Stato,"Rosso")&" KRI in rosso; ","")&IF(INDEX(posNetti,INDEX(Classifica!$U$5:$U$24,$V53))>=sogliaDirezione,"notizie in peggioramento (+"&INDEX(posNetti,INDEX(Classifica!$U$5:$U$24,$V53))&" segnali netti in 4 settimane); ",IF(INDEX(posNetti,INDEX(Classifica!$U$5:$U$24,$V53))<=-sogliaDirezione,"notizie in miglioramento ("&INDEX(posNetti,INDEX(Classifica!$U$5:$U$24,$V53))&" segnali netti in 4 settimane); ",""))) | BH53: =2*PI()*48/72 -> 4.1887902 | BI53: =2*SIN($BH53) -> -1.7320508 | BJ53: =2*COS($BH53) -> -1 | BK53: =3*SIN($BH53) -> -2.5980762 | BL53: =3*COS($BH53) -> -1.5 | BM53: =4*SIN($BH53) -> -3.4641016 | BN53: =4*COS($BH53) -> -2 | BO53: =5*SIN($BH53) -> -4.330127 | BP53: =5*COS($BH53) -> -2.5
A54: =IF($V54="","",INDEX(Classifica!$B$5:$B$24,$V54)&CHAR(10)&INDEX(Classifica!$C$5:$C$24,$V54)&IF(INDEX(ANA_Attenzione_Supervisore,INDEX(Classifica!$U$5:$U$24,$V54))="Sì",CHAR(10)&"◆ attenzione del supervisore","")) -> NFR-06 Esfiltrazione di dati tramite strumenti di AI non autorizzati | D54: =IF($V54="","",INDEX(Radar_Mosca!$AA$5:$AA$24,INDEX(Classifica!$U$5:$U$24,$V54))&"") -> Attenzione | E54: =IF($W54="","",LEFT($W54,LEN($W54)-2)&".") -> presidio dei controlli assente. | I54: =IF($V54="","",IF(INDEX(Classifica!$G$5:$G$24,$V54)="Nuovo","Rischio nuovo nel ciclo.",IFERROR(IF(INDEX(RR_Variazioni,MATCH(cicloCorrente&"|"&INDEX(Classifica!$B$5:$B$24,$V54),RR_Chiave,0))&""="[]","Nessun valore cambiato: confermato sulle fonti del ciclo precedente.",SUBSTITUTE(SUBSTITUTE(SUBSTITUTE(SUBSTITUTE(SUBSTITUTE(SUBSTITUTE(SUBSTITUTE(SUBSTITUTE(SUBSTITUTE(SUBSTITUTE(SUBSTITUTE(SUBSTITUTE(SUBSTITUTE(SUBSTITUTE(SUBSTITUTE(INDEX(RR_Variazioni,MATCH(cicloCorrente&"|"&INDEX(Classifica!$B$5:$B$24,$V54),RR_Chiave,0))&"","[{""dimensione"": ""","• "),"""}, {""dimensione"": """,")"&CHAR(10)&"• "),""", ""da"": "," "),", ""a"": "," → "),", ""evidenza"": """,": "),""", ""data_evidenza"": """," ("),"""}]",")")," null → "," n.v. → ")," → null:"," → n.v.:"),"• impatto","• Impatto"),"• velocity","• Velocity"),"• prossimita","• Prossimita"),"• confidence","• Confidence"),"• probabilita","• Probabilita"),"• severity","• Impatto")),""))) -> Nessun valore cambiato: confermato sulle fonti del ciclo precedente. | U54: =IF(Classifica!$B$9="","",IF(OR(5<=3,INDEX(Radar_Mosca!$AA$5:$AA$24,Classifica!$U$9)="Attivazione",INDEX(Radar_Mosca!$AA$5:$AA$24,Classifica!$U$9)="Attenzione",Classifica!$G$9="Variato",Classifica!$G$9="Nuovo"),5,"")) -> 5 | V54: =IFERROR(_xlfn.AGGREGATE(15,6,$U$50:$U$69,5),"") -> 7 | W54: =IF($V54="","",IF($V54<=3,$V54&"° per score composito ("&FIXED(INDEX(Classifica!$D$5:$D$24,$V54),2)&IF(ISNUMBER(INDEX(Classifica!$F$5:$F$24,$V54)),IF(INDEX(Classifica!$F$5:$F$24,$V54)<>0,", "&IF(INDEX(Classifica!$F$5:$F$24,$V54)>0,"+","")&FIXED(INDEX(Classifica!$F$5:$F$24,$V54),2)&" sul ciclo prima",""),"")&"); ","")&IF(LEFT(INDEX(Classifica!$H$5:$H$24,$V54),9)="AGIRE ORA","AGIRE ORA: servono X + Y = "&FIXED(INDEX(Classifica!$Y$5:$Y$24,$V54)+INDEX(Classifica!$Z$5:$Z$24,$V54),2)&" anni per decidere e mitigare"&IF(N(INDEX(ANA_Anni_Adeguamento,INDEX(Classifica!$U$5:$U$24,$V54)))>0,", di cui "&N(INDEX(ANA_Anni_Adeguamento,INDEX(Classifica!$U$5:$U$24,$V54)))&" di adeguamento strutturale","")&"; ne restano Z = "&FIXED(INDEX(Classifica!$AA$5:$AA$24,$V54),1)&" prima che possa manifestarsi; ",IF(AND($V54<=3,LEFT(INDEX(Classifica!$H$5:$H$24,$V54),11)="Agire entro"),"margine di Mosca sotto l'anno ("&FIXED(INDEX(Classifica!$I$5:$I$24,$V54),2)&"); ",""))&IF(INDEX(Classifica!$G$5:$G$24,$V54)="Variato","variato nel ciclo"&IF(ISNUMBER(INDEX(Classifica!$F$5:$F$24,$V54)),IF(INDEX(Classifica!$F$5:$F$24,$V54)>0,": peggiora",IF(INDEX(Classifica!$F$5:$F$24,$V54)<0,": migliora","")),"")&"; ",IF(INDEX(Classifica!$G$5:$G$24,$V54)="Nuovo","nuovo nel ciclo; ",""))&IF(INDEX(ANA_Attenzione_Supervisore,INDEX(Classifica!$U$5:$U$24,$V54))="Sì","tema all'attenzione del supervisore; ","")&IF(INDEX(ANA_Presidio_Controlli,INDEX(Classifica!$U$5:$U$24,$V54))="Assente","presidio dei controlli assente; ","")&IF(COUNTIFS(KRI_ID_Rischio,INDEX(Classifica!$B$5:$B$24,$V54),KRI_Ciclo,cicloCorrente,KRI_In_Vigore,"Sì",KRI_Stato,"Rosso")>0,COUNTIFS(KRI_ID_Rischio,INDEX(Classifica!$B$5:$B$24,$V54),KRI_Ciclo,cicloCorrente,KRI_In_Vigore,"Sì",KRI_Stato,"Rosso")&" KRI in rosso; ","")&IF(INDEX(posNetti,INDEX(Classifica!$U$5:$U$24,$V54))>=sogliaDirezione,"notizie in peggioramento (+"&INDEX(posNetti,INDEX(Classifica!$U$5:$U$24,$V54))&" segnali netti in 4 settimane); ",IF(INDEX(posNetti,INDEX(Classifica!$U$5:$U$24,$V54))<=-sogliaDirezione,"notizie in miglioramento ("&INDEX(posNetti,INDEX(Classifica!$U$5:$U$24,$V54))&" segnali netti in 4 settimane); ",""))) -> presidio dei controlli assente; | BH54: =2*PI()*49/72 -> 4.2760567 | BI54: =2*SIN($BH54) -> -1.8126156 | BJ54: =2*COS($BH54) -> -0.84523652 | BK54: =3*SIN($BH54) -> -2.7189234 | BL54: =3*COS($BH54) -> -1.2678548 | BM54: =4*SIN($BH54) -> -3.6252311 | BN54: =4*COS($BH54) -> -1.690473 | BO54: =5*SIN($BH54) -> -4.5315389 | BP54: =5*COS($BH54) -> -2.1130913
A55: =IF($V55="","",INDEX(Classifica!$B$5:$B$24,$V55)&CHAR(10)&INDEX(Classifica!$C$5:$C$24,$V55)&IF(INDEX(ANA_Attenzione_Supervisore,INDEX(Classifica!$U$5:$U$24,$V55))="Sì",CHAR(10)&"◆ attenzione del supervisore","")) -> NFR-04 Eventi climatici estremi su sedi e data center | D55: =IF($V55="","",INDEX(Radar_Mosca!$AA$5:$AA$24,INDEX(Classifica!$U$5:$U$24,$V55))&"") -> Attenzione | E55: =IF($W55="","",LEFT($W55,LEN($W55)-2)&".") | I55: =IF($V55="","",IF(INDEX(Classifica!$G$5:$G$24,$V55)="Nuovo","Rischio nuovo nel ciclo.",IFERROR(IF(INDEX(RR_Variazioni,MATCH(cicloCorrente&"|"&INDEX(Classifica!$B$5:$B$24,$V55),RR_Chiave,0))&""="[]","Nessun valore cambiato: confermato sulle fonti del ciclo precedente.",SUBSTITUTE(SUBSTITUTE(SUBSTITUTE(SUBSTITUTE(SUBSTITUTE(SUBSTITUTE(SUBSTITUTE(SUBSTITUTE(SUBSTITUTE(SUBSTITUTE(SUBSTITUTE(SUBSTITUTE(SUBSTITUTE(SUBSTITUTE(SUBSTITUTE(INDEX(RR_Variazioni,MATCH(cicloCorrente&"|"&INDEX(Classifica!$B$5:$B$24,$V55),RR_Chiave,0))&"","[{""dimensione"": ""","• "),"""}, {""dimensione"": """,")"&CHAR(10)&"• "),""", ""da"": "," "),", ""a"": "," → "),", ""evidenza"": """,": "),""", ""data_evidenza"": """," ("),"""}]",")")," null → "," n.v. → ")," → null:"," → n.v.:"),"• impatto","• Impatto"),"• velocity","• Velocity"),"• prossimita","• Prossimita"),"• confidence","• Confidence"),"• probabilita","• Probabilita"),"• severity","• Impatto")),""))) -> Nessun valore cambiato: confermato sulle fonti del ciclo precedente. | U55: =IF(Classifica!$B$10="","",IF(OR(6<=3,INDEX(Radar_Mosca!$AA$5:$AA$24,Classifica!$U$10)="Attivazione",INDEX(Radar_Mosca!$AA$5:$AA$24,Classifica!$U$10)="Attenzione",Classifica!$G$10="Variato",Classifica!$G$10="Nuovo"),6,"")) | V55: =IFERROR(_xlfn.AGGREGATE(15,6,$U$50:$U$69,6),"") -> 10 | W55: =IF($V55="","",IF($V55<=3,$V55&"° per score composito ("&FIXED(INDEX(Classifica!$D$5:$D$24,$V55),2)&IF(ISNUMBER(INDEX(Classifica!$F$5:$F$24,$V55)),IF(INDEX(Classifica!$F$5:$F$24,$V55)<>0,", "&IF(INDEX(Classifica!$F$5:$F$24,$V55)>0,"+","")&FIXED(INDEX(Classifica!$F$5:$F$24,$V55),2)&" sul ciclo prima",""),"")&"); ","")&IF(LEFT(INDEX(Classifica!$H$5:$H$24,$V55),9)="AGIRE ORA","AGIRE ORA: servono X + Y = "&FIXED(INDEX(Classifica!$Y$5:$Y$24,$V55)+INDEX(Classifica!$Z$5:$Z$24,$V55),2)&" anni per decidere e mitigare"&IF(N(INDEX(ANA_Anni_Adeguamento,INDEX(Classifica!$U$5:$U$24,$V55)))>0,", di cui "&N(INDEX(ANA_Anni_Adeguamento,INDEX(Classifica!$U$5:$U$24,$V55)))&" di adeguamento strutturale","")&"; ne restano Z = "&FIXED(INDEX(Classifica!$AA$5:$AA$24,$V55),1)&" prima che possa manifestarsi; ",IF(AND($V55<=3,LEFT(INDEX(Classifica!$H$5:$H$24,$V55),11)="Agire entro"),"margine di Mosca sotto l'anno ("&FIXED(INDEX(Classifica!$I$5:$I$24,$V55),2)&"); ",""))&IF(INDEX(Classifica!$G$5:$G$24,$V55)="Variato","variato nel ciclo"&IF(ISNUMBER(INDEX(Classifica!$F$5:$F$24,$V55)),IF(INDEX(Classifica!$F$5:$F$24,$V55)>0,": peggiora",IF(INDEX(Classifica!$F$5:$F$24,$V55)<0,": migliora","")),"")&"; ",IF(INDEX(Classifica!$G$5:$G$24,$V55)="Nuovo","nuovo nel ciclo; ",""))&IF(INDEX(ANA_Attenzione_Supervisore,INDEX(Classifica!$U$5:$U$24,$V55))="Sì","tema all'attenzione del supervisore; ","")&IF(INDEX(ANA_Presidio_Controlli,INDEX(Classifica!$U$5:$U$24,$V55))="Assente","presidio dei controlli assente; ","")&IF(COUNTIFS(KRI_ID_Rischio,INDEX(Classifica!$B$5:$B$24,$V55),KRI_Ciclo,cicloCorrente,KRI_In_Vigore,"Sì",KRI_Stato,"Rosso")>0,COUNTIFS(KRI_ID_Rischio,INDEX(Classifica!$B$5:$B$24,$V55),KRI_Ciclo,cicloCorrente,KRI_In_Vigore,"Sì",KRI_Stato,"Rosso")&" KRI in rosso; ","")&IF(INDEX(posNetti,INDEX(Classifica!$U$5:$U$24,$V55))>=sogliaDirezione,"notizie in peggioramento (+"&INDEX(posNetti,INDEX(Classifica!$U$5:$U$24,$V55))&" segnali netti in 4 settimane); ",IF(INDEX(posNetti,INDEX(Classifica!$U$5:$U$24,$V55))<=-sogliaDirezione,"notizie in miglioramento ("&INDEX(posNetti,INDEX(Classifica!$U$5:$U$24,$V55))&" segnali netti in 4 settimane); ",""))) | BH55: =2*PI()*50/72 -> 4.3633231 | BI55: =2*SIN($BH55) -> -1.8793852 | BJ55: =2*COS($BH55) -> -0.68404029 | BK55: =3*SIN($BH55) -> -2.8190779 | BL55: =3*COS($BH55) -> -1.0260604 | BM55: =4*SIN($BH55) -> -3.7587705 | BN55: =4*COS($BH55) -> -1.3680806 | BO55: =5*SIN($BH55) -> -4.6984631 | BP55: =5*COS($BH55) -> -1.7101007
A56: =IF($V56="","",INDEX(Classifica!$B$5:$B$24,$V56)&CHAR(10)&INDEX(Classifica!$C$5:$C$24,$V56)&IF(INDEX(ANA_Attenzione_Supervisore,INDEX(Classifica!$U$5:$U$24,$V56))="Sì",CHAR(10)&"◆ attenzione del supervisore","")) -> NFR-11 Fine del supporto dei sistemi di pagamento legacy | D56: =IF($V56="","",INDEX(Radar_Mosca!$AA$5:$AA$24,INDEX(Classifica!$U$5:$U$24,$V56))&"") -> Attivazione | E56: =IF($W56="","",LEFT($W56,LEN($W56)-2)&".") -> AGIRE ORA: servono X + Y = 3,25 anni per decidere e mitigare, di cui 3 di adeguamento strutturale; ne restano Z = 1,5 prima che possa manifestarsi; presidio dei controlli assente; 1 KRI in rosso. | I56: =IF($V56="","",IF(INDEX(Classifica!$G$5:$G$24,$V56)="Nuovo","Rischio nuovo nel ciclo.",IFERROR(IF(INDEX(RR_Variazioni,MATCH(cicloCorrente&"|"&INDEX(Classifica!$B$5:$B$24,$V56),RR_Chiave,0))&""="[]","Nessun valore cambiato: confermato sulle fonti del ciclo precedente.",SUBSTITUTE(SUBSTITUTE(SUBSTITUTE(SUBSTITUTE(SUBSTITUTE(SUBSTITUTE(SUBSTITUTE(SUBSTITUTE(SUBSTITUTE(SUBSTITUTE(SUBSTITUTE(SUBSTITUTE(SUBSTITUTE(SUBSTITUTE(SUBSTITUTE(INDEX(RR_Variazioni,MATCH(cicloCorrente&"|"&INDEX(Classifica!$B$5:$B$24,$V56),RR_Chiave,0))&"","[{""dimensione"": ""","• "),"""}, {""dimensione"": """,")"&CHAR(10)&"• "),""", ""da"": "," "),", ""a"": "," → "),", ""evidenza"": """,": "),""", ""data_evidenza"": """," ("),"""}]",")")," null → "," n.v. → ")," → null:"," → n.v.:"),"• impatto","• Impatto"),"• velocity","• Velocity"),"• prossimita","• Prossimita"),"• confidence","• Confidence"),"• probabilita","• Probabilita"),"• severity","• Impatto")),""))) -> Nessun valore cambiato: confermato sulle fonti del ciclo precedente. | U56: =IF(Classifica!$B$11="","",IF(OR(7<=3,INDEX(Radar_Mosca!$AA$5:$AA$24,Classifica!$U$11)="Attivazione",INDEX(Radar_Mosca!$AA$5:$AA$24,Classifica!$U$11)="Attenzione",Classifica!$G$11="Variato",Classifica!$G$11="Nuovo"),7,"")) -> 7 | V56: =IFERROR(_xlfn.AGGREGATE(15,6,$U$50:$U$69,7),"") -> 11 | W56: =IF($V56="","",IF($V56<=3,$V56&"° per score composito ("&FIXED(INDEX(Classifica!$D$5:$D$24,$V56),2)&IF(ISNUMBER(INDEX(Classifica!$F$5:$F$24,$V56)),IF(INDEX(Classifica!$F$5:$F$24,$V56)<>0,", "&IF(INDEX(Classifica!$F$5:$F$24,$V56)>0,"+","")&FIXED(INDEX(Classifica!$F$5:$F$24,$V56),2)&" sul ciclo prima",""),"")&"); ","")&IF(LEFT(INDEX(Classifica!$H$5:$H$24,$V56),9)="AGIRE ORA","AGIRE ORA: servono X + Y = "&FIXED(INDEX(Classifica!$Y$5:$Y$24,$V56)+INDEX(Classifica!$Z$5:$Z$24,$V56),2)&" anni per decidere e mitigare"&IF(N(INDEX(ANA_Anni_Adeguamento,INDEX(Classifica!$U$5:$U$24,$V56)))>0,", di cui "&N(INDEX(ANA_Anni_Adeguamento,INDEX(Classifica!$U$5:$U$24,$V56)))&" di adeguamento strutturale","")&"; ne restano Z = "&FIXED(INDEX(Classifica!$AA$5:$AA$24,$V56),1)&" prima che possa manifestarsi; ",IF(AND($V56<=3,LEFT(INDEX(Classifica!$H$5:$H$24,$V56),11)="Agire entro"),"margine di Mosca sotto l'anno ("&FIXED(INDEX(Classifica!$I$5:$I$24,$V56),2)&"); ",""))&IF(INDEX(Classifica!$G$5:$G$24,$V56)="Variato","variato nel ciclo"&IF(ISNUMBER(INDEX(Classifica!$F$5:$F$24,$V56)),IF(INDEX(Classifica!$F$5:$F$24,$V56)>0,": peggiora",IF(INDEX(Classifica!$F$5:$F$24,$V56)<0,": migliora","")),"")&"; ",IF(INDEX(Classifica!$G$5:$G$24,$V56)="Nuovo","nuovo nel ciclo; ",""))&IF(INDEX(ANA_Attenzione_Supervisore,INDEX(Classifica!$U$5:$U$24,$V56))="Sì","tema all'attenzione del supervisore; ","")&IF(INDEX(ANA_Presidio_Controlli,INDEX(Classifica!$U$5:$U$24,$V56))="Assente","presidio dei controlli assente; ","")&IF(COUNTIFS(KRI_ID_Rischio,INDEX(Classifica!$B$5:$B$24,$V56),KRI_Ciclo,cicloCorrente,KRI_In_Vigore,"Sì",KRI_Stato,"Rosso")>0,COUNTIFS(KRI_ID_Rischio,INDEX(Classifica!$B$5:$B$24,$V56),KRI_Ciclo,cicloCorrente,KRI_In_Vigore,"Sì",KRI_Stato,"Rosso")&" KRI in rosso; ","")&IF(INDEX(posNetti,INDEX(Classifica!$U$5:$U$24,$V56))>=sogliaDirezione,"notizie in peggioramento (+"&INDEX(posNetti,INDEX(Classifica!$U$5:$U$24,$V56))&" segnali netti in 4 settimane); ",IF(INDEX(posNetti,INDEX(Classifica!$U$5:$U$24,$V56))<=-sogliaDirezione,"notizie in miglioramento ("&INDEX(posNetti,INDEX(Classifica!$U$5:$U$24,$V56))&" segnali netti in 4 settimane); ",""))) -> AGIRE ORA: servono X + Y = 3,25 anni per decidere e mitigare, di cui 3 di adeguamento strutturale; ne restano Z = 1,5 prima che possa manifestarsi; presidio dei controlli assente; 1 KRI in rosso; | BH56: =2*PI()*51/72 -> 4.4505896 | BI56: =2*SIN($BH56) -> -1.9318517 | BJ56: =2*COS($BH56) -> -0.51763809 | BK56: =3*SIN($BH56) -> -2.8977775 | BL56: =3*COS($BH56) -> -0.77645714 | BM56: =4*SIN($BH56) -> -3.8637033 | BN56: =4*COS($BH56) -> -1.0352762 | BO56: =5*SIN($BH56) -> -4.8296291 | BP56: =5*COS($BH56) -> -1.2940952
A57: =IF($V57="","",INDEX(Classifica!$B$5:$B$24,$V57)&CHAR(10)&INDEX(Classifica!$C$5:$C$24,$V57)&IF(INDEX(ANA_Attenzione_Supervisore,INDEX(Classifica!$U$5:$U$24,$V57))="Sì",CHAR(10)&"◆ attenzione del supervisore","")) -> NFR-16 Vertenze e carenza di tecnici nei ruoli IT critici | D57: =IF($V57="","",INDEX(Radar_Mosca!$AA$5:$AA$24,INDEX(Classifica!$U$5:$U$24,$V57))&"") -> Monitoraggio | E57: =IF($W57="","",LEFT($W57,LEN($W57)-2)&".") -> variato nel ciclo: peggiora. | I57: =IF($V57="","",IF(INDEX(Classifica!$G$5:$G$24,$V57)="Nuovo","Rischio nuovo nel ciclo.",IFERROR(IF(INDEX(RR_Variazioni,MATCH(cicloCorrente&"|"&INDEX(Classifica!$B$5:$B$24,$V57),RR_Chiave,0))&""="[]","Nessun valore cambiato: confermato sulle fonti del ciclo precedente.",SUBSTITUTE(SUBSTITUTE(SUBSTITUTE(SUBSTITUTE(SUBSTITUTE(SUBSTITUTE(SUBSTITUTE(SUBSTITUTE(SUBSTITUTE(SUBSTITUTE(SUBSTITUTE(SUBSTITUTE(SUBSTITUTE(SUBSTITUTE(SUBSTITUTE(INDEX(RR_Variazioni,MATCH(cicloCorrente&"|"&INDEX(Classifica!$B$5:$B$24,$V57),RR_Chiave,0))&"","[{""dimensione"": ""","• "),"""}, {""dimensione"": """,")"&CHAR(10)&"• "),""", ""da"": "," "),", ""a"": "," → "),", ""evidenza"": """,": "),""", ""data_evidenza"": """," ("),"""}]",")")," null → "," n.v. → ")," → null:"," → n.v.:"),"• impatto","• Impatto"),"• velocity","• Velocity"),"• prossimita","• Prossimita"),"• confidence","• Confidence"),"• probabilita","• Probabilita"),"• severity","• Impatto")),""))) -> • Probabilita 2 → 3: Lo sciopero nazionale del personale bancario di ottobre ha coinvolto i tecnici IT e il piano di successione della Banca copre solo meta' dei ruoli critici: la Banca e' esposta. (2026-11-15) • Prossimita 1 → 2: La vertenza nazionale e' in corso nel settore dal 6 ottobre 2026, con due giornate di sciopero proclamate: il fenomeno puo' toccare la Banca entro tre anni. (2026-10-06) • Velocity n.v. → 3: Lo sciopero nazionale del personale bancario documenta che uscite di personale e periodi di vertenza si sviluppano in alcuni mesi: velocity valutata per la prima volta. (2026-10-06) | U57: =IF(Classifica!$B$12="","",IF(OR(8<=3,INDEX(Radar_Mosca!$AA$5:$AA$24,Classifica!$U$12)="Attivazione",INDEX(Radar_Mosca!$AA$5:$AA$24,Classifica!$U$12)="Attenzione",Classifica!$G$12="Variato",Classifica!$G$12="Nuovo"),8,"")) | V57: =IFERROR(_xlfn.AGGREGATE(15,6,$U$50:$U$69,8),"") -> 12 | W57: =IF($V57="","",IF($V57<=3,$V57&"° per score composito ("&FIXED(INDEX(Classifica!$D$5:$D$24,$V57),2)&IF(ISNUMBER(INDEX(Classifica!$F$5:$F$24,$V57)),IF(INDEX(Classifica!$F$5:$F$24,$V57)<>0,", "&IF(INDEX(Classifica!$F$5:$F$24,$V57)>0,"+","")&FIXED(INDEX(Classifica!$F$5:$F$24,$V57),2)&" sul ciclo prima",""),"")&"); ","")&IF(LEFT(INDEX(Classifica!$H$5:$H$24,$V57),9)="AGIRE ORA","AGIRE ORA: servono X + Y = "&FIXED(INDEX(Classifica!$Y$5:$Y$24,$V57)+INDEX(Classifica!$Z$5:$Z$24,$V57),2)&" anni per decidere e mitigare"&IF(N(INDEX(ANA_Anni_Adeguamento,INDEX(Classifica!$U$5:$U$24,$V57)))>0,", di cui "&N(INDEX(ANA_Anni_Adeguamento,INDEX(Classifica!$U$5:$U$24,$V57)))&" di adeguamento strutturale","")&"; ne restano Z = "&FIXED(INDEX(Classifica!$AA$5:$AA$24,$V57),1)&" prima che possa manifestarsi; ",IF(AND($V57<=3,LEFT(INDEX(Classifica!$H$5:$H$24,$V57),11)="Agire entro"),"margine di Mosca sotto l'anno ("&FIXED(INDEX(Classifica!$I$5:$I$24,$V57),2)&"); ",""))&IF(INDEX(Classifica!$G$5:$G$24,$V57)="Variato","variato nel ciclo"&IF(ISNUMBER(INDEX(Classifica!$F$5:$F$24,$V57)),IF(INDEX(Classifica!$F$5:$F$24,$V57)>0,": peggiora",IF(INDEX(Classifica!$F$5:$F$24,$V57)<0,": migliora","")),"")&"; ",IF(INDEX(Classifica!$G$5:$G$24,$V57)="Nuovo","nuovo nel ciclo; ",""))&IF(INDEX(ANA_Attenzione_Supervisore,INDEX(Classifica!$U$5:$U$24,$V57))="Sì","tema all'attenzione del supervisore; ","")&IF(INDEX(ANA_Presidio_Controlli,INDEX(Classifica!$U$5:$U$24,$V57))="Assente","presidio dei controlli assente; ","")&IF(COUNTIFS(KRI_ID_Rischio,INDEX(Classifica!$B$5:$B$24,$V57),KRI_Ciclo,cicloCorrente,KRI_In_Vigore,"Sì",KRI_Stato,"Rosso")>0,COUNTIFS(KRI_ID_Rischio,INDEX(Classifica!$B$5:$B$24,$V57),KRI_Ciclo,cicloCorrente,KRI_In_Vigore,"Sì",KRI_Stato,"Rosso")&" KRI in rosso; ","")&IF(INDEX(posNetti,INDEX(Classifica!$U$5:$U$24,$V57))>=sogliaDirezione,"notizie in peggioramento (+"&INDEX(posNetti,INDEX(Classifica!$U$5:$U$24,$V57))&" segnali netti in 4 settimane); ",IF(INDEX(posNetti,INDEX(Classifica!$U$5:$U$24,$V57))<=-sogliaDirezione,"notizie in miglioramento ("&INDEX(posNetti,INDEX(Classifica!$U$5:$U$24,$V57))&" segnali netti in 4 settimane); ",""))) -> variato nel ciclo: peggiora; | BH57: =2*PI()*52/72 -> 4.5378561 | BI57: =2*SIN($BH57) -> -1.9696155 | BJ57: =2*COS($BH57) -> -0.34729636 | BK57: =3*SIN($BH57) -> -2.9544233 | BL57: =3*COS($BH57) -> -0.52094453 | BM57: =4*SIN($BH57) -> -3.939231 | BN57: =4*COS($BH57) -> -0.69459271 | BO57: =5*SIN($BH57) -> -4.9240388 | BP57: =5*COS($BH57) -> -0.86824089
A58: =IF($V58="","",INDEX(Classifica!$B$5:$B$24,$V58)&CHAR(10)&INDEX(Classifica!$C$5:$C$24,$V58)&IF(INDEX(ANA_Attenzione_Supervisore,INDEX(Classifica!$U$5:$U$24,$V58))="Sì",CHAR(10)&"◆ attenzione del supervisore","")) | D58: =IF($V58="","",INDEX(Radar_Mosca!$AA$5:$AA$24,INDEX(Classifica!$U$5:$U$24,$V58))&"") | E58: =IF($W58="","",LEFT($W58,LEN($W58)-2)&".") | I58: =IF($V58="","",IF(INDEX(Classifica!$G$5:$G$24,$V58)="Nuovo","Rischio nuovo nel ciclo.",IFERROR(IF(INDEX(RR_Variazioni,MATCH(cicloCorrente&"|"&INDEX(Classifica!$B$5:$B$24,$V58),RR_Chiave,0))&""="[]","Nessun valore cambiato: confermato sulle fonti del ciclo precedente.",SUBSTITUTE(SUBSTITUTE(SUBSTITUTE(SUBSTITUTE(SUBSTITUTE(SUBSTITUTE(SUBSTITUTE(SUBSTITUTE(SUBSTITUTE(SUBSTITUTE(SUBSTITUTE(SUBSTITUTE(SUBSTITUTE(SUBSTITUTE(SUBSTITUTE(INDEX(RR_Variazioni,MATCH(cicloCorrente&"|"&INDEX(Classifica!$B$5:$B$24,$V58),RR_Chiave,0))&"","[{""dimensione"": ""","• "),"""}, {""dimensione"": """,")"&CHAR(10)&"• "),""", ""da"": "," "),", ""a"": "," → "),", ""evidenza"": """,": "),""", ""data_evidenza"": """," ("),"""}]",")")," null → "," n.v. → ")," → null:"," → n.v.:"),"• impatto","• Impatto"),"• velocity","• Velocity"),"• prossimita","• Prossimita"),"• confidence","• Confidence"),"• probabilita","• Probabilita"),"• severity","• Impatto")),""))) | U58: =IF(Classifica!$B$13="","",IF(OR(9<=3,INDEX(Radar_Mosca!$AA$5:$AA$24,Classifica!$U$13)="Attivazione",INDEX(Radar_Mosca!$AA$5:$AA$24,Classifica!$U$13)="Attenzione",Classifica!$G$13="Variato",Classifica!$G$13="Nuovo"),9,"")) | V58: =IFERROR(_xlfn.AGGREGATE(15,6,$U$50:$U$69,9),"") | W58: =IF($V58="","",IF($V58<=3,$V58&"° per score composito ("&FIXED(INDEX(Classifica!$D$5:$D$24,$V58),2)&IF(ISNUMBER(INDEX(Classifica!$F$5:$F$24,$V58)),IF(INDEX(Classifica!$F$5:$F$24,$V58)<>0,", "&IF(INDEX(Classifica!$F$5:$F$24,$V58)>0,"+","")&FIXED(INDEX(Classifica!$F$5:$F$24,$V58),2)&" sul ciclo prima",""),"")&"); ","")&IF(LEFT(INDEX(Classifica!$H$5:$H$24,$V58),9)="AGIRE ORA","AGIRE ORA: servono X + Y = "&FIXED(INDEX(Classifica!$Y$5:$Y$24,$V58)+INDEX(Classifica!$Z$5:$Z$24,$V58),2)&" anni per decidere e mitigare"&IF(N(INDEX(ANA_Anni_Adeguamento,INDEX(Classifica!$U$5:$U$24,$V58)))>0,", di cui "&N(INDEX(ANA_Anni_Adeguamento,INDEX(Classifica!$U$5:$U$24,$V58)))&" di adeguamento strutturale","")&"; ne restano Z = "&FIXED(INDEX(Classifica!$AA$5:$AA$24,$V58),1)&" prima che possa manifestarsi; ",IF(AND($V58<=3,LEFT(INDEX(Classifica!$H$5:$H$24,$V58),11)="Agire entro"),"margine di Mosca sotto l'anno ("&FIXED(INDEX(Classifica!$I$5:$I$24,$V58),2)&"); ",""))&IF(INDEX(Classifica!$G$5:$G$24,$V58)="Variato","variato nel ciclo"&IF(ISNUMBER(INDEX(Classifica!$F$5:$F$24,$V58)),IF(INDEX(Classifica!$F$5:$F$24,$V58)>0,": peggiora",IF(INDEX(Classifica!$F$5:$F$24,$V58)<0,": migliora","")),"")&"; ",IF(INDEX(Classifica!$G$5:$G$24,$V58)="Nuovo","nuovo nel ciclo; ",""))&IF(INDEX(ANA_Attenzione_Supervisore,INDEX(Classifica!$U$5:$U$24,$V58))="Sì","tema all'attenzione del supervisore; ","")&IF(INDEX(ANA_Presidio_Controlli,INDEX(Classifica!$U$5:$U$24,$V58))="Assente","presidio dei controlli assente; ","")&IF(COUNTIFS(KRI_ID_Rischio,INDEX(Classifica!$B$5:$B$24,$V58),KRI_Ciclo,cicloCorrente,KRI_In_Vigore,"Sì",KRI_Stato,"Rosso")>0,COUNTIFS(KRI_ID_Rischio,INDEX(Classifica!$B$5:$B$24,$V58),KRI_Ciclo,cicloCorrente,KRI_In_Vigore,"Sì",KRI_Stato,"Rosso")&" KRI in rosso; ","")&IF(INDEX(posNetti,INDEX(Classifica!$U$5:$U$24,$V58))>=sogliaDirezione,"notizie in peggioramento (+"&INDEX(posNetti,INDEX(Classifica!$U$5:$U$24,$V58))&" segnali netti in 4 settimane); ",IF(INDEX(posNetti,INDEX(Classifica!$U$5:$U$24,$V58))<=-sogliaDirezione,"notizie in miglioramento ("&INDEX(posNetti,INDEX(Classifica!$U$5:$U$24,$V58))&" segnali netti in 4 settimane); ",""))) | BH58: =2*PI()*53/72 -> 4.6251225 | BI58: =2*SIN($BH58) -> -1.9923894 | BJ58: =2*COS($BH58) -> -0.17431149 | BK58: =3*SIN($BH58) -> -2.9885841 | BL58: =3*COS($BH58) -> -0.26146723 | BM58: =4*SIN($BH58) -> -3.9847788 | BN58: =4*COS($BH58) -> -0.34862297 | BO58: =5*SIN($BH58) -> -4.9809735 | BP58: =5*COS($BH58) -> -0.43577871
A59: =IF($V59="","",INDEX(Classifica!$B$5:$B$24,$V59)&CHAR(10)&INDEX(Classifica!$C$5:$C$24,$V59)&IF(INDEX(ANA_Attenzione_Supervisore,INDEX(Classifica!$U$5:$U$24,$V59))="Sì",CHAR(10)&"◆ attenzione del supervisore","")) | D59: =IF($V59="","",INDEX(Radar_Mosca!$AA$5:$AA$24,INDEX(Classifica!$U$5:$U$24,$V59))&"") | E59: =IF($W59="","",LEFT($W59,LEN($W59)-2)&".") | I59: =IF($V59="","",IF(INDEX(Classifica!$G$5:$G$24,$V59)="Nuovo","Rischio nuovo nel ciclo.",IFERROR(IF(INDEX(RR_Variazioni,MATCH(cicloCorrente&"|"&INDEX(Classifica!$B$5:$B$24,$V59),RR_Chiave,0))&""="[]","Nessun valore cambiato: confermato sulle fonti del ciclo precedente.",SUBSTITUTE(SUBSTITUTE(SUBSTITUTE(SUBSTITUTE(SUBSTITUTE(SUBSTITUTE(SUBSTITUTE(SUBSTITUTE(SUBSTITUTE(SUBSTITUTE(SUBSTITUTE(SUBSTITUTE(SUBSTITUTE(SUBSTITUTE(SUBSTITUTE(INDEX(RR_Variazioni,MATCH(cicloCorrente&"|"&INDEX(Classifica!$B$5:$B$24,$V59),RR_Chiave,0))&"","[{""dimensione"": ""","• "),"""}, {""dimensione"": """,")"&CHAR(10)&"• "),""", ""da"": "," "),", ""a"": "," → "),", ""evidenza"": """,": "),""", ""data_evidenza"": """," ("),"""}]",")")," null → "," n.v. → ")," → null:"," → n.v.:"),"• impatto","• Impatto"),"• velocity","• Velocity"),"• prossimita","• Prossimita"),"• confidence","• Confidence"),"• probabilita","• Probabilita"),"• severity","• Impatto")),""))) | U59: =IF(Classifica!$B$14="","",IF(OR(10<=3,INDEX(Radar_Mosca!$AA$5:$AA$24,Classifica!$U$14)="Attivazione",INDEX(Radar_Mosca!$AA$5:$AA$24,Classifica!$U$14)="Attenzione",Classifica!$G$14="Variato",Classifica!$G$14="Nuovo"),10,"")) -> 10 | V59: =IFERROR(_xlfn.AGGREGATE(15,6,$U$50:$U$69,10),"") | W59: =IF($V59="","",IF($V59<=3,$V59&"° per score composito ("&FIXED(INDEX(Classifica!$D$5:$D$24,$V59),2)&IF(ISNUMBER(INDEX(Classifica!$F$5:$F$24,$V59)),IF(INDEX(Classifica!$F$5:$F$24,$V59)<>0,", "&IF(INDEX(Classifica!$F$5:$F$24,$V59)>0,"+","")&FIXED(INDEX(Classifica!$F$5:$F$24,$V59),2)&" sul ciclo prima",""),"")&"); ","")&IF(LEFT(INDEX(Classifica!$H$5:$H$24,$V59),9)="AGIRE ORA","AGIRE ORA: servono X + Y = "&FIXED(INDEX(Classifica!$Y$5:$Y$24,$V59)+INDEX(Classifica!$Z$5:$Z$24,$V59),2)&" anni per decidere e mitigare"&IF(N(INDEX(ANA_Anni_Adeguamento,INDEX(Classifica!$U$5:$U$24,$V59)))>0,", di cui "&N(INDEX(ANA_Anni_Adeguamento,INDEX(Classifica!$U$5:$U$24,$V59)))&" di adeguamento strutturale","")&"; ne restano Z = "&FIXED(INDEX(Classifica!$AA$5:$AA$24,$V59),1)&" prima che possa manifestarsi; ",IF(AND($V59<=3,LEFT(INDEX(Classifica!$H$5:$H$24,$V59),11)="Agire entro"),"margine di Mosca sotto l'anno ("&FIXED(INDEX(Classifica!$I$5:$I$24,$V59),2)&"); ",""))&IF(INDEX(Classifica!$G$5:$G$24,$V59)="Variato","variato nel ciclo"&IF(ISNUMBER(INDEX(Classifica!$F$5:$F$24,$V59)),IF(INDEX(Classifica!$F$5:$F$24,$V59)>0,": peggiora",IF(INDEX(Classifica!$F$5:$F$24,$V59)<0,": migliora","")),"")&"; ",IF(INDEX(Classifica!$G$5:$G$24,$V59)="Nuovo","nuovo nel ciclo; ",""))&IF(INDEX(ANA_Attenzione_Supervisore,INDEX(Classifica!$U$5:$U$24,$V59))="Sì","tema all'attenzione del supervisore; ","")&IF(INDEX(ANA_Presidio_Controlli,INDEX(Classifica!$U$5:$U$24,$V59))="Assente","presidio dei controlli assente; ","")&IF(COUNTIFS(KRI_ID_Rischio,INDEX(Classifica!$B$5:$B$24,$V59),KRI_Ciclo,cicloCorrente,KRI_In_Vigore,"Sì",KRI_Stato,"Rosso")>0,COUNTIFS(KRI_ID_Rischio,INDEX(Classifica!$B$5:$B$24,$V59),KRI_Ciclo,cicloCorrente,KRI_In_Vigore,"Sì",KRI_Stato,"Rosso")&" KRI in rosso; ","")&IF(INDEX(posNetti,INDEX(Classifica!$U$5:$U$24,$V59))>=sogliaDirezione,"notizie in peggioramento (+"&INDEX(posNetti,INDEX(Classifica!$U$5:$U$24,$V59))&" segnali netti in 4 settimane); ",IF(INDEX(posNetti,INDEX(Classifica!$U$5:$U$24,$V59))<=-sogliaDirezione,"notizie in miglioramento ("&INDEX(posNetti,INDEX(Classifica!$U$5:$U$24,$V59))&" segnali netti in 4 settimane); ",""))) | BH59: =2*PI()*54/72 -> 4.712389 | BI59: =2*SIN($BH59) -> -2 | BJ59: =2*COS($BH59) -> -3.6754454e-16 | BK59: =3*SIN($BH59) -> -3 | BL59: =3*COS($BH59) -> -5.513168e-16 | BM59: =4*SIN($BH59) -> -4 | BN59: =4*COS($BH59) -> -7.3508907e-16 | BO59: =5*SIN($BH59) -> -5 | BP59: =5*COS($BH59) -> -9.1886134e-16
A60: =IF($V60="","",INDEX(Classifica!$B$5:$B$24,$V60)&CHAR(10)&INDEX(Classifica!$C$5:$C$24,$V60)&IF(INDEX(ANA_Attenzione_Supervisore,INDEX(Classifica!$U$5:$U$24,$V60))="Sì",CHAR(10)&"◆ attenzione del supervisore","")) | D60: =IF($V60="","",INDEX(Radar_Mosca!$AA$5:$AA$24,INDEX(Classifica!$U$5:$U$24,$V60))&"") | E60: =IF($W60="","",LEFT($W60,LEN($W60)-2)&".") | I60: =IF($V60="","",IF(INDEX(Classifica!$G$5:$G$24,$V60)="Nuovo","Rischio nuovo nel ciclo.",IFERROR(IF(INDEX(RR_Variazioni,MATCH(cicloCorrente&"|"&INDEX(Classifica!$B$5:$B$24,$V60),RR_Chiave,0))&""="[]","Nessun valore cambiato: confermato sulle fonti del ciclo precedente.",SUBSTITUTE(SUBSTITUTE(SUBSTITUTE(SUBSTITUTE(SUBSTITUTE(SUBSTITUTE(SUBSTITUTE(SUBSTITUTE(SUBSTITUTE(SUBSTITUTE(SUBSTITUTE(SUBSTITUTE(SUBSTITUTE(SUBSTITUTE(SUBSTITUTE(INDEX(RR_Variazioni,MATCH(cicloCorrente&"|"&INDEX(Classifica!$B$5:$B$24,$V60),RR_Chiave,0))&"","[{""dimensione"": ""","• "),"""}, {""dimensione"": """,")"&CHAR(10)&"• "),""", ""da"": "," "),", ""a"": "," → "),", ""evidenza"": """,": "),""", ""data_evidenza"": """," ("),"""}]",")")," null → "," n.v. → ")," → null:"," → n.v.:"),"• impatto","• Impatto"),"• velocity","• Velocity"),"• prossimita","• Prossimita"),"• confidence","• Confidence"),"• probabilita","• Probabilita"),"• severity","• Impatto")),""))) | U60: =IF(Classifica!$B$15="","",IF(OR(11<=3,INDEX(Radar_Mosca!$AA$5:$AA$24,Classifica!$U$15)="Attivazione",INDEX(Radar_Mosca!$AA$5:$AA$24,Classifica!$U$15)="Attenzione",Classifica!$G$15="Variato",Classifica!$G$15="Nuovo"),11,"")) -> 11 | V60: =IFERROR(_xlfn.AGGREGATE(15,6,$U$50:$U$69,11),"") | W60: =IF($V60="","",IF($V60<=3,$V60&"° per score composito ("&FIXED(INDEX(Classifica!$D$5:$D$24,$V60),2)&IF(ISNUMBER(INDEX(Classifica!$F$5:$F$24,$V60)),IF(INDEX(Classifica!$F$5:$F$24,$V60)<>0,", "&IF(INDEX(Classifica!$F$5:$F$24,$V60)>0,"+","")&FIXED(INDEX(Classifica!$F$5:$F$24,$V60),2)&" sul ciclo prima",""),"")&"); ","")&IF(LEFT(INDEX(Classifica!$H$5:$H$24,$V60),9)="AGIRE ORA","AGIRE ORA: servono X + Y = "&FIXED(INDEX(Classifica!$Y$5:$Y$24,$V60)+INDEX(Classifica!$Z$5:$Z$24,$V60),2)&" anni per decidere e mitigare"&IF(N(INDEX(ANA_Anni_Adeguamento,INDEX(Classifica!$U$5:$U$24,$V60)))>0,", di cui "&N(INDEX(ANA_Anni_Adeguamento,INDEX(Classifica!$U$5:$U$24,$V60)))&" di adeguamento strutturale","")&"; ne restano Z = "&FIXED(INDEX(Classifica!$AA$5:$AA$24,$V60),1)&" prima che possa manifestarsi; ",IF(AND($V60<=3,LEFT(INDEX(Classifica!$H$5:$H$24,$V60),11)="Agire entro"),"margine di Mosca sotto l'anno ("&FIXED(INDEX(Classifica!$I$5:$I$24,$V60),2)&"); ",""))&IF(INDEX(Classifica!$G$5:$G$24,$V60)="Variato","variato nel ciclo"&IF(ISNUMBER(INDEX(Classifica!$F$5:$F$24,$V60)),IF(INDEX(Classifica!$F$5:$F$24,$V60)>0,": peggiora",IF(INDEX(Classifica!$F$5:$F$24,$V60)<0,": migliora","")),"")&"; ",IF(INDEX(Classifica!$G$5:$G$24,$V60)="Nuovo","nuovo nel ciclo; ",""))&IF(INDEX(ANA_Attenzione_Supervisore,INDEX(Classifica!$U$5:$U$24,$V60))="Sì","tema all'attenzione del supervisore; ","")&IF(INDEX(ANA_Presidio_Controlli,INDEX(Classifica!$U$5:$U$24,$V60))="Assente","presidio dei controlli assente; ","")&IF(COUNTIFS(KRI_ID_Rischio,INDEX(Classifica!$B$5:$B$24,$V60),KRI_Ciclo,cicloCorrente,KRI_In_Vigore,"Sì",KRI_Stato,"Rosso")>0,COUNTIFS(KRI_ID_Rischio,INDEX(Classifica!$B$5:$B$24,$V60),KRI_Ciclo,cicloCorrente,KRI_In_Vigore,"Sì",KRI_Stato,"Rosso")&" KRI in rosso; ","")&IF(INDEX(posNetti,INDEX(Classifica!$U$5:$U$24,$V60))>=sogliaDirezione,"notizie in peggioramento (+"&INDEX(posNetti,INDEX(Classifica!$U$5:$U$24,$V60))&" segnali netti in 4 settimane); ",IF(INDEX(posNetti,INDEX(Classifica!$U$5:$U$24,$V60))<=-sogliaDirezione,"notizie in miglioramento ("&INDEX(posNetti,INDEX(Classifica!$U$5:$U$24,$V60))&" segnali netti in 4 settimane); ",""))) | BH60: =2*PI()*55/72 -> 4.7996554 | BI60: =2*SIN($BH60) -> -1.9923894 | BJ60: =2*COS($BH60) -> 0.17431149 | BK60: =3*SIN($BH60) -> -2.9885841 | BL60: =3*COS($BH60) -> 0.26146723 | BM60: =4*SIN($BH60) -> -3.9847788 | BN60: =4*COS($BH60) -> 0.34862297 | BO60: =5*SIN($BH60) -> -4.9809735 | BP60: =5*COS($BH60) -> 0.43577871
A61: =IF($V61="","",INDEX(Classifica!$B$5:$B$24,$V61)&CHAR(10)&INDEX(Classifica!$C$5:$C$24,$V61)&IF(INDEX(ANA_Attenzione_Supervisore,INDEX(Classifica!$U$5:$U$24,$V61))="Sì",CHAR(10)&"◆ attenzione del supervisore","")) | D61: =IF($V61="","",INDEX(Radar_Mosca!$AA$5:$AA$24,INDEX(Classifica!$U$5:$U$24,$V61))&"") | E61: =IF($W61="","",LEFT($W61,LEN($W61)-2)&".") | I61: =IF($V61="","",IF(INDEX(Classifica!$G$5:$G$24,$V61)="Nuovo","Rischio nuovo nel ciclo.",IFERROR(IF(INDEX(RR_Variazioni,MATCH(cicloCorrente&"|"&INDEX(Classifica!$B$5:$B$24,$V61),RR_Chiave,0))&""="[]","Nessun valore cambiato: confermato sulle fonti del ciclo precedente.",SUBSTITUTE(SUBSTITUTE(SUBSTITUTE(SUBSTITUTE(SUBSTITUTE(SUBSTITUTE(SUBSTITUTE(SUBSTITUTE(SUBSTITUTE(SUBSTITUTE(SUBSTITUTE(SUBSTITUTE(SUBSTITUTE(SUBSTITUTE(SUBSTITUTE(INDEX(RR_Variazioni,MATCH(cicloCorrente&"|"&INDEX(Classifica!$B$5:$B$24,$V61),RR_Chiave,0))&"","[{""dimensione"": ""","• "),"""}, {""dimensione"": """,")"&CHAR(10)&"• "),""", ""da"": "," "),", ""a"": "," → "),", ""evidenza"": """,": "),""", ""data_evidenza"": """," ("),"""}]",")")," null → "," n.v. → ")," → null:"," → n.v.:"),"• impatto","• Impatto"),"• velocity","• Velocity"),"• prossimita","• Prossimita"),"• confidence","• Confidence"),"• probabilita","• Probabilita"),"• severity","• Impatto")),""))) | U61: =IF(Classifica!$B$16="","",IF(OR(12<=3,INDEX(Radar_Mosca!$AA$5:$AA$24,Classifica!$U$16)="Attivazione",INDEX(Radar_Mosca!$AA$5:$AA$24,Classifica!$U$16)="Attenzione",Classifica!$G$16="Variato",Classifica!$G$16="Nuovo"),12,"")) -> 12 | V61: =IFERROR(_xlfn.AGGREGATE(15,6,$U$50:$U$69,12),"") | W61: =IF($V61="","",IF($V61<=3,$V61&"° per score composito ("&FIXED(INDEX(Classifica!$D$5:$D$24,$V61),2)&IF(ISNUMBER(INDEX(Classifica!$F$5:$F$24,$V61)),IF(INDEX(Classifica!$F$5:$F$24,$V61)<>0,", "&IF(INDEX(Classifica!$F$5:$F$24,$V61)>0,"+","")&FIXED(INDEX(Classifica!$F$5:$F$24,$V61),2)&" sul ciclo prima",""),"")&"); ","")&IF(LEFT(INDEX(Classifica!$H$5:$H$24,$V61),9)="AGIRE ORA","AGIRE ORA: servono X + Y = "&FIXED(INDEX(Classifica!$Y$5:$Y$24,$V61)+INDEX(Classifica!$Z$5:$Z$24,$V61),2)&" anni per decidere e mitigare"&IF(N(INDEX(ANA_Anni_Adeguamento,INDEX(Classifica!$U$5:$U$24,$V61)))>0,", di cui "&N(INDEX(ANA_Anni_Adeguamento,INDEX(Classifica!$U$5:$U$24,$V61)))&" di adeguamento strutturale","")&"; ne restano Z = "&FIXED(INDEX(Classifica!$AA$5:$AA$24,$V61),1)&" prima che possa manifestarsi; ",IF(AND($V61<=3,LEFT(INDEX(Classifica!$H$5:$H$24,$V61),11)="Agire entro"),"margine di Mosca sotto l'anno ("&FIXED(INDEX(Classifica!$I$5:$I$24,$V61),2)&"); ",""))&IF(INDEX(Classifica!$G$5:$G$24,$V61)="Variato","variato nel ciclo"&IF(ISNUMBER(INDEX(Classifica!$F$5:$F$24,$V61)),IF(INDEX(Classifica!$F$5:$F$24,$V61)>0,": peggiora",IF(INDEX(Classifica!$F$5:$F$24,$V61)<0,": migliora","")),"")&"; ",IF(INDEX(Classifica!$G$5:$G$24,$V61)="Nuovo","nuovo nel ciclo; ",""))&IF(INDEX(ANA_Attenzione_Supervisore,INDEX(Classifica!$U$5:$U$24,$V61))="Sì","tema all'attenzione del supervisore; ","")&IF(INDEX(ANA_Presidio_Controlli,INDEX(Classifica!$U$5:$U$24,$V61))="Assente","presidio dei controlli assente; ","")&IF(COUNTIFS(KRI_ID_Rischio,INDEX(Classifica!$B$5:$B$24,$V61),KRI_Ciclo,cicloCorrente,KRI_In_Vigore,"Sì",KRI_Stato,"Rosso")>0,COUNTIFS(KRI_ID_Rischio,INDEX(Classifica!$B$5:$B$24,$V61),KRI_Ciclo,cicloCorrente,KRI_In_Vigore,"Sì",KRI_Stato,"Rosso")&" KRI in rosso; ","")&IF(INDEX(posNetti,INDEX(Classifica!$U$5:$U$24,$V61))>=sogliaDirezione,"notizie in peggioramento (+"&INDEX(posNetti,INDEX(Classifica!$U$5:$U$24,$V61))&" segnali netti in 4 settimane); ",IF(INDEX(posNetti,INDEX(Classifica!$U$5:$U$24,$V61))<=-sogliaDirezione,"notizie in miglioramento ("&INDEX(posNetti,INDEX(Classifica!$U$5:$U$24,$V61))&" segnali netti in 4 settimane); ",""))) | BH61: =2*PI()*56/72 -> 4.8869219 | BI61: =2*SIN($BH61) -> -1.9696155 | BJ61: =2*COS($BH61) -> 0.34729636 | BK61: =3*SIN($BH61) -> -2.9544233 | BL61: =3*COS($BH61) -> 0.52094453 | BM61: =4*SIN($BH61) -> -3.939231 | BN61: =4*COS($BH61) -> 0.69459271 | BO61: =5*SIN($BH61) -> -4.9240388 | BP61: =5*COS($BH61) -> 0.86824089
A62: =IF($V62="","",INDEX(Classifica!$B$5:$B$24,$V62)&CHAR(10)&INDEX(Classifica!$C$5:$C$24,$V62)&IF(INDEX(ANA_Attenzione_Supervisore,INDEX(Classifica!$U$5:$U$24,$V62))="Sì",CHAR(10)&"◆ attenzione del supervisore","")) | D62: =IF($V62="","",INDEX(Radar_Mosca!$AA$5:$AA$24,INDEX(Classifica!$U$5:$U$24,$V62))&"") | E62: =IF($W62="","",LEFT($W62,LEN($W62)-2)&".") | I62: =IF($V62="","",IF(INDEX(Classifica!$G$5:$G$24,$V62)="Nuovo","Rischio nuovo nel ciclo.",IFERROR(IF(INDEX(RR_Variazioni,MATCH(cicloCorrente&"|"&INDEX(Classifica!$B$5:$B$24,$V62),RR_Chiave,0))&""="[]","Nessun valore cambiato: confermato sulle fonti del ciclo precedente.",SUBSTITUTE(SUBSTITUTE(SUBSTITUTE(SUBSTITUTE(SUBSTITUTE(SUBSTITUTE(SUBSTITUTE(SUBSTITUTE(SUBSTITUTE(SUBSTITUTE(SUBSTITUTE(SUBSTITUTE(SUBSTITUTE(SUBSTITUTE(SUBSTITUTE(INDEX(RR_Variazioni,MATCH(cicloCorrente&"|"&INDEX(Classifica!$B$5:$B$24,$V62),RR_Chiave,0))&"","[{""dimensione"": ""","• "),"""}, {""dimensione"": """,")"&CHAR(10)&"• "),""", ""da"": "," "),", ""a"": "," → "),", ""evidenza"": """,": "),""", ""data_evidenza"": """," ("),"""}]",")")," null → "," n.v. → ")," → null:"," → n.v.:"),"• impatto","• Impatto"),"• velocity","• Velocity"),"• prossimita","• Prossimita"),"• confidence","• Confidence"),"• probabilita","• Probabilita"),"• severity","• Impatto")),""))) | U62: =IF(Classifica!$B$17="","",IF(OR(13<=3,INDEX(Radar_Mosca!$AA$5:$AA$24,Classifica!$U$17)="Attivazione",INDEX(Radar_Mosca!$AA$5:$AA$24,Classifica!$U$17)="Attenzione",Classifica!$G$17="Variato",Classifica!$G$17="Nuovo"),13,"")) | V62: =IFERROR(_xlfn.AGGREGATE(15,6,$U$50:$U$69,13),"") | W62: =IF($V62="","",IF($V62<=3,$V62&"° per score composito ("&FIXED(INDEX(Classifica!$D$5:$D$24,$V62),2)&IF(ISNUMBER(INDEX(Classifica!$F$5:$F$24,$V62)),IF(INDEX(Classifica!$F$5:$F$24,$V62)<>0,", "&IF(INDEX(Classifica!$F$5:$F$24,$V62)>0,"+","")&FIXED(INDEX(Classifica!$F$5:$F$24,$V62),2)&" sul ciclo prima",""),"")&"); ","")&IF(LEFT(INDEX(Classifica!$H$5:$H$24,$V62),9)="AGIRE ORA","AGIRE ORA: servono X + Y = "&FIXED(INDEX(Classifica!$Y$5:$Y$24,$V62)+INDEX(Classifica!$Z$5:$Z$24,$V62),2)&" anni per decidere e mitigare"&IF(N(INDEX(ANA_Anni_Adeguamento,INDEX(Classifica!$U$5:$U$24,$V62)))>0,", di cui "&N(INDEX(ANA_Anni_Adeguamento,INDEX(Classifica!$U$5:$U$24,$V62)))&" di adeguamento strutturale","")&"; ne restano Z = "&FIXED(INDEX(Classifica!$AA$5:$AA$24,$V62),1)&" prima che possa manifestarsi; ",IF(AND($V62<=3,LEFT(INDEX(Classifica!$H$5:$H$24,$V62),11)="Agire entro"),"margine di Mosca sotto l'anno ("&FIXED(INDEX(Classifica!$I$5:$I$24,$V62),2)&"); ",""))&IF(INDEX(Classifica!$G$5:$G$24,$V62)="Variato","variato nel ciclo"&IF(ISNUMBER(INDEX(Classifica!$F$5:$F$24,$V62)),IF(INDEX(Classifica!$F$5:$F$24,$V62)>0,": peggiora",IF(INDEX(Classifica!$F$5:$F$24,$V62)<0,": migliora","")),"")&"; ",IF(INDEX(Classifica!$G$5:$G$24,$V62)="Nuovo","nuovo nel ciclo; ",""))&IF(INDEX(ANA_Attenzione_Supervisore,INDEX(Classifica!$U$5:$U$24,$V62))="Sì","tema all'attenzione del supervisore; ","")&IF(INDEX(ANA_Presidio_Controlli,INDEX(Classifica!$U$5:$U$24,$V62))="Assente","presidio dei controlli assente; ","")&IF(COUNTIFS(KRI_ID_Rischio,INDEX(Classifica!$B$5:$B$24,$V62),KRI_Ciclo,cicloCorrente,KRI_In_Vigore,"Sì",KRI_Stato,"Rosso")>0,COUNTIFS(KRI_ID_Rischio,INDEX(Classifica!$B$5:$B$24,$V62),KRI_Ciclo,cicloCorrente,KRI_In_Vigore,"Sì",KRI_Stato,"Rosso")&" KRI in rosso; ","")&IF(INDEX(posNetti,INDEX(Classifica!$U$5:$U$24,$V62))>=sogliaDirezione,"notizie in peggioramento (+"&INDEX(posNetti,INDEX(Classifica!$U$5:$U$24,$V62))&" segnali netti in 4 settimane); ",IF(INDEX(posNetti,INDEX(Classifica!$U$5:$U$24,$V62))<=-sogliaDirezione,"notizie in miglioramento ("&INDEX(posNetti,INDEX(Classifica!$U$5:$U$24,$V62))&" segnali netti in 4 settimane); ",""))) | BH62: =2*PI()*57/72 -> 4.9741884 | BI62: =2*SIN($BH62) -> -1.9318517 | BJ62: =2*COS($BH62) -> 0.51763809 | BK62: =3*SIN($BH62) -> -2.8977775 | BL62: =3*COS($BH62) -> 0.77645714 | BM62: =4*SIN($BH62) -> -3.8637033 | BN62: =4*COS($BH62) -> 1.0352762 | BO62: =5*SIN($BH62) -> -4.8296291 | BP62: =5*COS($BH62) -> 1.2940952
A63: =IF($V63="","",INDEX(Classifica!$B$5:$B$24,$V63)&CHAR(10)&INDEX(Classifica!$C$5:$C$24,$V63)&IF(INDEX(ANA_Attenzione_Supervisore,INDEX(Classifica!$U$5:$U$24,$V63))="Sì",CHAR(10)&"◆ attenzione del supervisore","")) | D63: =IF($V63="","",INDEX(Radar_Mosca!$AA$5:$AA$24,INDEX(Classifica!$U$5:$U$24,$V63))&"") | E63: =IF($W63="","",LEFT($W63,LEN($W63)-2)&".") | I63: =IF($V63="","",IF(INDEX(Classifica!$G$5:$G$24,$V63)="Nuovo","Rischio nuovo nel ciclo.",IFERROR(IF(INDEX(RR_Variazioni,MATCH(cicloCorrente&"|"&INDEX(Classifica!$B$5:$B$24,$V63),RR_Chiave,0))&""="[]","Nessun valore cambiato: confermato sulle fonti del ciclo precedente.",SUBSTITUTE(SUBSTITUTE(SUBSTITUTE(SUBSTITUTE(SUBSTITUTE(SUBSTITUTE(SUBSTITUTE(SUBSTITUTE(SUBSTITUTE(SUBSTITUTE(SUBSTITUTE(SUBSTITUTE(SUBSTITUTE(SUBSTITUTE(SUBSTITUTE(INDEX(RR_Variazioni,MATCH(cicloCorrente&"|"&INDEX(Classifica!$B$5:$B$24,$V63),RR_Chiave,0))&"","[{""dimensione"": ""","• "),"""}, {""dimensione"": """,")"&CHAR(10)&"• "),""", ""da"": "," "),", ""a"": "," → "),", ""evidenza"": """,": "),""", ""data_evidenza"": """," ("),"""}]",")")," null → "," n.v. → ")," → null:"," → n.v.:"),"• impatto","• Impatto"),"• velocity","• Velocity"),"• prossimita","• Prossimita"),"• confidence","• Confidence"),"• probabilita","• Probabilita"),"• severity","• Impatto")),""))) | U63: =IF(Classifica!$B$18="","",IF(OR(14<=3,INDEX(Radar_Mosca!$AA$5:$AA$24,Classifica!$U$18)="Attivazione",INDEX(Radar_Mosca!$AA$5:$AA$24,Classifica!$U$18)="Attenzione",Classifica!$G$18="Variato",Classifica!$G$18="Nuovo"),14,"")) | V63: =IFERROR(_xlfn.AGGREGATE(15,6,$U$50:$U$69,14),"") | W63: =IF($V63="","",IF($V63<=3,$V63&"° per score composito ("&FIXED(INDEX(Classifica!$D$5:$D$24,$V63),2)&IF(ISNUMBER(INDEX(Classifica!$F$5:$F$24,$V63)),IF(INDEX(Classifica!$F$5:$F$24,$V63)<>0,", "&IF(INDEX(Classifica!$F$5:$F$24,$V63)>0,"+","")&FIXED(INDEX(Classifica!$F$5:$F$24,$V63),2)&" sul ciclo prima",""),"")&"); ","")&IF(LEFT(INDEX(Classifica!$H$5:$H$24,$V63),9)="AGIRE ORA","AGIRE ORA: servono X + Y = "&FIXED(INDEX(Classifica!$Y$5:$Y$24,$V63)+INDEX(Classifica!$Z$5:$Z$24,$V63),2)&" anni per decidere e mitigare"&IF(N(INDEX(ANA_Anni_Adeguamento,INDEX(Classifica!$U$5:$U$24,$V63)))>0,", di cui "&N(INDEX(ANA_Anni_Adeguamento,INDEX(Classifica!$U$5:$U$24,$V63)))&" di adeguamento strutturale","")&"; ne restano Z = "&FIXED(INDEX(Classifica!$AA$5:$AA$24,$V63),1)&" prima che possa manifestarsi; ",IF(AND($V63<=3,LEFT(INDEX(Classifica!$H$5:$H$24,$V63),11)="Agire entro"),"margine di Mosca sotto l'anno ("&FIXED(INDEX(Classifica!$I$5:$I$24,$V63),2)&"); ",""))&IF(INDEX(Classifica!$G$5:$G$24,$V63)="Variato","variato nel ciclo"&IF(ISNUMBER(INDEX(Classifica!$F$5:$F$24,$V63)),IF(INDEX(Classifica!$F$5:$F$24,$V63)>0,": peggiora",IF(INDEX(Classifica!$F$5:$F$24,$V63)<0,": migliora","")),"")&"; ",IF(INDEX(Classifica!$G$5:$G$24,$V63)="Nuovo","nuovo nel ciclo; ",""))&IF(INDEX(ANA_Attenzione_Supervisore,INDEX(Classifica!$U$5:$U$24,$V63))="Sì","tema all'attenzione del supervisore; ","")&IF(INDEX(ANA_Presidio_Controlli,INDEX(Classifica!$U$5:$U$24,$V63))="Assente","presidio dei controlli assente; ","")&IF(COUNTIFS(KRI_ID_Rischio,INDEX(Classifica!$B$5:$B$24,$V63),KRI_Ciclo,cicloCorrente,KRI_In_Vigore,"Sì",KRI_Stato,"Rosso")>0,COUNTIFS(KRI_ID_Rischio,INDEX(Classifica!$B$5:$B$24,$V63),KRI_Ciclo,cicloCorrente,KRI_In_Vigore,"Sì",KRI_Stato,"Rosso")&" KRI in rosso; ","")&IF(INDEX(posNetti,INDEX(Classifica!$U$5:$U$24,$V63))>=sogliaDirezione,"notizie in peggioramento (+"&INDEX(posNetti,INDEX(Classifica!$U$5:$U$24,$V63))&" segnali netti in 4 settimane); ",IF(INDEX(posNetti,INDEX(Classifica!$U$5:$U$24,$V63))<=-sogliaDirezione,"notizie in miglioramento ("&INDEX(posNetti,INDEX(Classifica!$U$5:$U$24,$V63))&" segnali netti in 4 settimane); ",""))) | BH63: =2*PI()*58/72 -> 5.0614548 | BI63: =2*SIN($BH63) -> -1.8793852 | BJ63: =2*COS($BH63) -> 0.68404029 | BK63: =3*SIN($BH63) -> -2.8190779 | BL63: =3*COS($BH63) -> 1.0260604 | BM63: =4*SIN($BH63) -> -3.7587705 | BN63: =4*COS($BH63) -> 1.3680806 | BO63: =5*SIN($BH63) -> -4.6984631 | BP63: =5*COS($BH63) -> 1.7101007
A64: =IF($V64="","",INDEX(Classifica!$B$5:$B$24,$V64)&CHAR(10)&INDEX(Classifica!$C$5:$C$24,$V64)&IF(INDEX(ANA_Attenzione_Supervisore,INDEX(Classifica!$U$5:$U$24,$V64))="Sì",CHAR(10)&"◆ attenzione del supervisore","")) | D64: =IF($V64="","",INDEX(Radar_Mosca!$AA$5:$AA$24,INDEX(Classifica!$U$5:$U$24,$V64))&"") | E64: =IF($W64="","",LEFT($W64,LEN($W64)-2)&".") | I64: =IF($V64="","",IF(INDEX(Classifica!$G$5:$G$24,$V64)="Nuovo","Rischio nuovo nel ciclo.",IFERROR(IF(INDEX(RR_Variazioni,MATCH(cicloCorrente&"|"&INDEX(Classifica!$B$5:$B$24,$V64),RR_Chiave,0))&""="[]","Nessun valore cambiato: confermato sulle fonti del ciclo precedente.",SUBSTITUTE(SUBSTITUTE(SUBSTITUTE(SUBSTITUTE(SUBSTITUTE(SUBSTITUTE(SUBSTITUTE(SUBSTITUTE(SUBSTITUTE(SUBSTITUTE(SUBSTITUTE(SUBSTITUTE(SUBSTITUTE(SUBSTITUTE(SUBSTITUTE(INDEX(RR_Variazioni,MATCH(cicloCorrente&"|"&INDEX(Classifica!$B$5:$B$24,$V64),RR_Chiave,0))&"","[{""dimensione"": ""","• "),"""}, {""dimensione"": """,")"&CHAR(10)&"• "),""", ""da"": "," "),", ""a"": "," → "),", ""evidenza"": """,": "),""", ""data_evidenza"": """," ("),"""}]",")")," null → "," n.v. → ")," → null:"," → n.v.:"),"• impatto","• Impatto"),"• velocity","• Velocity"),"• prossimita","• Prossimita"),"• confidence","• Confidence"),"• probabilita","• Probabilita"),"• severity","• Impatto")),""))) | U64: =IF(Classifica!$B$19="","",IF(OR(15<=3,INDEX(Radar_Mosca!$AA$5:$AA$24,Classifica!$U$19)="Attivazione",INDEX(Radar_Mosca!$AA$5:$AA$24,Classifica!$U$19)="Attenzione",Classifica!$G$19="Variato",Classifica!$G$19="Nuovo"),15,"")) | V64: =IFERROR(_xlfn.AGGREGATE(15,6,$U$50:$U$69,15),"") | W64: =IF($V64="","",IF($V64<=3,$V64&"° per score composito ("&FIXED(INDEX(Classifica!$D$5:$D$24,$V64),2)&IF(ISNUMBER(INDEX(Classifica!$F$5:$F$24,$V64)),IF(INDEX(Classifica!$F$5:$F$24,$V64)<>0,", "&IF(INDEX(Classifica!$F$5:$F$24,$V64)>0,"+","")&FIXED(INDEX(Classifica!$F$5:$F$24,$V64),2)&" sul ciclo prima",""),"")&"); ","")&IF(LEFT(INDEX(Classifica!$H$5:$H$24,$V64),9)="AGIRE ORA","AGIRE ORA: servono X + Y = "&FIXED(INDEX(Classifica!$Y$5:$Y$24,$V64)+INDEX(Classifica!$Z$5:$Z$24,$V64),2)&" anni per decidere e mitigare"&IF(N(INDEX(ANA_Anni_Adeguamento,INDEX(Classifica!$U$5:$U$24,$V64)))>0,", di cui "&N(INDEX(ANA_Anni_Adeguamento,INDEX(Classifica!$U$5:$U$24,$V64)))&" di adeguamento strutturale","")&"; ne restano Z = "&FIXED(INDEX(Classifica!$AA$5:$AA$24,$V64),1)&" prima che possa manifestarsi; ",IF(AND($V64<=3,LEFT(INDEX(Classifica!$H$5:$H$24,$V64),11)="Agire entro"),"margine di Mosca sotto l'anno ("&FIXED(INDEX(Classifica!$I$5:$I$24,$V64),2)&"); ",""))&IF(INDEX(Classifica!$G$5:$G$24,$V64)="Variato","variato nel ciclo"&IF(ISNUMBER(INDEX(Classifica!$F$5:$F$24,$V64)),IF(INDEX(Classifica!$F$5:$F$24,$V64)>0,": peggiora",IF(INDEX(Classifica!$F$5:$F$24,$V64)<0,": migliora","")),"")&"; ",IF(INDEX(Classifica!$G$5:$G$24,$V64)="Nuovo","nuovo nel ciclo; ",""))&IF(INDEX(ANA_Attenzione_Supervisore,INDEX(Classifica!$U$5:$U$24,$V64))="Sì","tema all'attenzione del supervisore; ","")&IF(INDEX(ANA_Presidio_Controlli,INDEX(Classifica!$U$5:$U$24,$V64))="Assente","presidio dei controlli assente; ","")&IF(COUNTIFS(KRI_ID_Rischio,INDEX(Classifica!$B$5:$B$24,$V64),KRI_Ciclo,cicloCorrente,KRI_In_Vigore,"Sì",KRI_Stato,"Rosso")>0,COUNTIFS(KRI_ID_Rischio,INDEX(Classifica!$B$5:$B$24,$V64),KRI_Ciclo,cicloCorrente,KRI_In_Vigore,"Sì",KRI_Stato,"Rosso")&" KRI in rosso; ","")&IF(INDEX(posNetti,INDEX(Classifica!$U$5:$U$24,$V64))>=sogliaDirezione,"notizie in peggioramento (+"&INDEX(posNetti,INDEX(Classifica!$U$5:$U$24,$V64))&" segnali netti in 4 settimane); ",IF(INDEX(posNetti,INDEX(Classifica!$U$5:$U$24,$V64))<=-sogliaDirezione,"notizie in miglioramento ("&INDEX(posNetti,INDEX(Classifica!$U$5:$U$24,$V64))&" segnali netti in 4 settimane); ",""))) | BH64: =2*PI()*59/72 -> 5.1487213 | BI64: =2*SIN($BH64) -> -1.8126156 | BJ64: =2*COS($BH64) -> 0.84523652 | BK64: =3*SIN($BH64) -> -2.7189234 | BL64: =3*COS($BH64) -> 1.2678548 | BM64: =4*SIN($BH64) -> -3.6252311 | BN64: =4*COS($BH64) -> 1.690473 | BO64: =5*SIN($BH64) -> -4.5315389 | BP64: =5*COS($BH64) -> 2.1130913
A65: =IF($V65="","",INDEX(Classifica!$B$5:$B$24,$V65)&CHAR(10)&INDEX(Classifica!$C$5:$C$24,$V65)&IF(INDEX(ANA_Attenzione_Supervisore,INDEX(Classifica!$U$5:$U$24,$V65))="Sì",CHAR(10)&"◆ attenzione del supervisore","")) | D65: =IF($V65="","",INDEX(Radar_Mosca!$AA$5:$AA$24,INDEX(Classifica!$U$5:$U$24,$V65))&"") | E65: =IF($W65="","",LEFT($W65,LEN($W65)-2)&".") | I65: =IF($V65="","",IF(INDEX(Classifica!$G$5:$G$24,$V65)="Nuovo","Rischio nuovo nel ciclo.",IFERROR(IF(INDEX(RR_Variazioni,MATCH(cicloCorrente&"|"&INDEX(Classifica!$B$5:$B$24,$V65),RR_Chiave,0))&""="[]","Nessun valore cambiato: confermato sulle fonti del ciclo precedente.",SUBSTITUTE(SUBSTITUTE(SUBSTITUTE(SUBSTITUTE(SUBSTITUTE(SUBSTITUTE(SUBSTITUTE(SUBSTITUTE(SUBSTITUTE(SUBSTITUTE(SUBSTITUTE(SUBSTITUTE(SUBSTITUTE(SUBSTITUTE(SUBSTITUTE(INDEX(RR_Variazioni,MATCH(cicloCorrente&"|"&INDEX(Classifica!$B$5:$B$24,$V65),RR_Chiave,0))&"","[{""dimensione"": ""","• "),"""}, {""dimensione"": """,")"&CHAR(10)&"• "),""", ""da"": "," "),", ""a"": "," → "),", ""evidenza"": """,": "),""", ""data_evidenza"": """," ("),"""}]",")")," null → "," n.v. → ")," → null:"," → n.v.:"),"• impatto","• Impatto"),"• velocity","• Velocity"),"• prossimita","• Prossimita"),"• confidence","• Confidence"),"• probabilita","• Probabilita"),"• severity","• Impatto")),""))) | U65: =IF(Classifica!$B$20="","",IF(OR(16<=3,INDEX(Radar_Mosca!$AA$5:$AA$24,Classifica!$U$20)="Attivazione",INDEX(Radar_Mosca!$AA$5:$AA$24,Classifica!$U$20)="Attenzione",Classifica!$G$20="Variato",Classifica!$G$20="Nuovo"),16,"")) | V65: =IFERROR(_xlfn.AGGREGATE(15,6,$U$50:$U$69,16),"") | W65: =IF($V65="","",IF($V65<=3,$V65&"° per score composito ("&FIXED(INDEX(Classifica!$D$5:$D$24,$V65),2)&IF(ISNUMBER(INDEX(Classifica!$F$5:$F$24,$V65)),IF(INDEX(Classifica!$F$5:$F$24,$V65)<>0,", "&IF(INDEX(Classifica!$F$5:$F$24,$V65)>0,"+","")&FIXED(INDEX(Classifica!$F$5:$F$24,$V65),2)&" sul ciclo prima",""),"")&"); ","")&IF(LEFT(INDEX(Classifica!$H$5:$H$24,$V65),9)="AGIRE ORA","AGIRE ORA: servono X + Y = "&FIXED(INDEX(Classifica!$Y$5:$Y$24,$V65)+INDEX(Classifica!$Z$5:$Z$24,$V65),2)&" anni per decidere e mitigare"&IF(N(INDEX(ANA_Anni_Adeguamento,INDEX(Classifica!$U$5:$U$24,$V65)))>0,", di cui "&N(INDEX(ANA_Anni_Adeguamento,INDEX(Classifica!$U$5:$U$24,$V65)))&" di adeguamento strutturale","")&"; ne restano Z = "&FIXED(INDEX(Classifica!$AA$5:$AA$24,$V65),1)&" prima che possa manifestarsi; ",IF(AND($V65<=3,LEFT(INDEX(Classifica!$H$5:$H$24,$V65),11)="Agire entro"),"margine di Mosca sotto l'anno ("&FIXED(INDEX(Classifica!$I$5:$I$24,$V65),2)&"); ",""))&IF(INDEX(Classifica!$G$5:$G$24,$V65)="Variato","variato nel ciclo"&IF(ISNUMBER(INDEX(Classifica!$F$5:$F$24,$V65)),IF(INDEX(Classifica!$F$5:$F$24,$V65)>0,": peggiora",IF(INDEX(Classifica!$F$5:$F$24,$V65)<0,": migliora","")),"")&"; ",IF(INDEX(Classifica!$G$5:$G$24,$V65)="Nuovo","nuovo nel ciclo; ",""))&IF(INDEX(ANA_Attenzione_Supervisore,INDEX(Classifica!$U$5:$U$24,$V65))="Sì","tema all'attenzione del supervisore; ","")&IF(INDEX(ANA_Presidio_Controlli,INDEX(Classifica!$U$5:$U$24,$V65))="Assente","presidio dei controlli assente; ","")&IF(COUNTIFS(KRI_ID_Rischio,INDEX(Classifica!$B$5:$B$24,$V65),KRI_Ciclo,cicloCorrente,KRI_In_Vigore,"Sì",KRI_Stato,"Rosso")>0,COUNTIFS(KRI_ID_Rischio,INDEX(Classifica!$B$5:$B$24,$V65),KRI_Ciclo,cicloCorrente,KRI_In_Vigore,"Sì",KRI_Stato,"Rosso")&" KRI in rosso; ","")&IF(INDEX(posNetti,INDEX(Classifica!$U$5:$U$24,$V65))>=sogliaDirezione,"notizie in peggioramento (+"&INDEX(posNetti,INDEX(Classifica!$U$5:$U$24,$V65))&" segnali netti in 4 settimane); ",IF(INDEX(posNetti,INDEX(Classifica!$U$5:$U$24,$V65))<=-sogliaDirezione,"notizie in miglioramento ("&INDEX(posNetti,INDEX(Classifica!$U$5:$U$24,$V65))&" segnali netti in 4 settimane); ",""))) | BH65: =2*PI()*60/72 -> 5.2359878 | BI65: =2*SIN($BH65) -> -1.7320508 | BJ65: =2*COS($BH65) -> 1 | BK65: =3*SIN($BH65) -> -2.5980762 | BL65: =3*COS($BH65) -> 1.5 | BM65: =4*SIN($BH65) -> -3.4641016 | BN65: =4*COS($BH65) -> 2 | BO65: =5*SIN($BH65) -> -4.330127 | BP65: =5*COS($BH65) -> 2.5
A66: =IF($V66="","",INDEX(Classifica!$B$5:$B$24,$V66)&CHAR(10)&INDEX(Classifica!$C$5:$C$24,$V66)&IF(INDEX(ANA_Attenzione_Supervisore,INDEX(Classifica!$U$5:$U$24,$V66))="Sì",CHAR(10)&"◆ attenzione del supervisore","")) | D66: =IF($V66="","",INDEX(Radar_Mosca!$AA$5:$AA$24,INDEX(Classifica!$U$5:$U$24,$V66))&"") | E66: =IF($W66="","",LEFT($W66,LEN($W66)-2)&".") | I66: =IF($V66="","",IF(INDEX(Classifica!$G$5:$G$24,$V66)="Nuovo","Rischio nuovo nel ciclo.",IFERROR(IF(INDEX(RR_Variazioni,MATCH(cicloCorrente&"|"&INDEX(Classifica!$B$5:$B$24,$V66),RR_Chiave,0))&""="[]","Nessun valore cambiato: confermato sulle fonti del ciclo precedente.",SUBSTITUTE(SUBSTITUTE(SUBSTITUTE(SUBSTITUTE(SUBSTITUTE(SUBSTITUTE(SUBSTITUTE(SUBSTITUTE(SUBSTITUTE(SUBSTITUTE(SUBSTITUTE(SUBSTITUTE(SUBSTITUTE(SUBSTITUTE(SUBSTITUTE(INDEX(RR_Variazioni,MATCH(cicloCorrente&"|"&INDEX(Classifica!$B$5:$B$24,$V66),RR_Chiave,0))&"","[{""dimensione"": ""","• "),"""}, {""dimensione"": """,")"&CHAR(10)&"• "),""", ""da"": "," "),", ""a"": "," → "),", ""evidenza"": """,": "),""", ""data_evidenza"": """," ("),"""}]",")")," null → "," n.v. → ")," → null:"," → n.v.:"),"• impatto","• Impatto"),"• velocity","• Velocity"),"• prossimita","• Prossimita"),"• confidence","• Confidence"),"• probabilita","• Probabilita"),"• severity","• Impatto")),""))) | U66: =IF(Classifica!$B$21="","",IF(OR(17<=3,INDEX(Radar_Mosca!$AA$5:$AA$24,Classifica!$U$21)="Attivazione",INDEX(Radar_Mosca!$AA$5:$AA$24,Classifica!$U$21)="Attenzione",Classifica!$G$21="Variato",Classifica!$G$21="Nuovo"),17,"")) | V66: =IFERROR(_xlfn.AGGREGATE(15,6,$U$50:$U$69,17),"") | W66: =IF($V66="","",IF($V66<=3,$V66&"° per score composito ("&FIXED(INDEX(Classifica!$D$5:$D$24,$V66),2)&IF(ISNUMBER(INDEX(Classifica!$F$5:$F$24,$V66)),IF(INDEX(Classifica!$F$5:$F$24,$V66)<>0,", "&IF(INDEX(Classifica!$F$5:$F$24,$V66)>0,"+","")&FIXED(INDEX(Classifica!$F$5:$F$24,$V66),2)&" sul ciclo prima",""),"")&"); ","")&IF(LEFT(INDEX(Classifica!$H$5:$H$24,$V66),9)="AGIRE ORA","AGIRE ORA: servono X + Y = "&FIXED(INDEX(Classifica!$Y$5:$Y$24,$V66)+INDEX(Classifica!$Z$5:$Z$24,$V66),2)&" anni per decidere e mitigare"&IF(N(INDEX(ANA_Anni_Adeguamento,INDEX(Classifica!$U$5:$U$24,$V66)))>0,", di cui "&N(INDEX(ANA_Anni_Adeguamento,INDEX(Classifica!$U$5:$U$24,$V66)))&" di adeguamento strutturale","")&"; ne restano Z = "&FIXED(INDEX(Classifica!$AA$5:$AA$24,$V66),1)&" prima che possa manifestarsi; ",IF(AND($V66<=3,LEFT(INDEX(Classifica!$H$5:$H$24,$V66),11)="Agire entro"),"margine di Mosca sotto l'anno ("&FIXED(INDEX(Classifica!$I$5:$I$24,$V66),2)&"); ",""))&IF(INDEX(Classifica!$G$5:$G$24,$V66)="Variato","variato nel ciclo"&IF(ISNUMBER(INDEX(Classifica!$F$5:$F$24,$V66)),IF(INDEX(Classifica!$F$5:$F$24,$V66)>0,": peggiora",IF(INDEX(Classifica!$F$5:$F$24,$V66)<0,": migliora","")),"")&"; ",IF(INDEX(Classifica!$G$5:$G$24,$V66)="Nuovo","nuovo nel ciclo; ",""))&IF(INDEX(ANA_Attenzione_Supervisore,INDEX(Classifica!$U$5:$U$24,$V66))="Sì","tema all'attenzione del supervisore; ","")&IF(INDEX(ANA_Presidio_Controlli,INDEX(Classifica!$U$5:$U$24,$V66))="Assente","presidio dei controlli assente; ","")&IF(COUNTIFS(KRI_ID_Rischio,INDEX(Classifica!$B$5:$B$24,$V66),KRI_Ciclo,cicloCorrente,KRI_In_Vigore,"Sì",KRI_Stato,"Rosso")>0,COUNTIFS(KRI_ID_Rischio,INDEX(Classifica!$B$5:$B$24,$V66),KRI_Ciclo,cicloCorrente,KRI_In_Vigore,"Sì",KRI_Stato,"Rosso")&" KRI in rosso; ","")&IF(INDEX(posNetti,INDEX(Classifica!$U$5:$U$24,$V66))>=sogliaDirezione,"notizie in peggioramento (+"&INDEX(posNetti,INDEX(Classifica!$U$5:$U$24,$V66))&" segnali netti in 4 settimane); ",IF(INDEX(posNetti,INDEX(Classifica!$U$5:$U$24,$V66))<=-sogliaDirezione,"notizie in miglioramento ("&INDEX(posNetti,INDEX(Classifica!$U$5:$U$24,$V66))&" segnali netti in 4 settimane); ",""))) | BH66: =2*PI()*61/72 -> 5.3232542 | BI66: =2*SIN($BH66) -> -1.6383041 | BJ66: =2*COS($BH66) -> 1.1471529 | BK66: =3*SIN($BH66) -> -2.4574561 | BL66: =3*COS($BH66) -> 1.7207293 | BM66: =4*SIN($BH66) -> -3.2766082 | BN66: =4*COS($BH66) -> 2.2943057 | BO66: =5*SIN($BH66) -> -4.0957602 | BP66: =5*COS($BH66) -> 2.8678822
A67: =IF($V67="","",INDEX(Classifica!$B$5:$B$24,$V67)&CHAR(10)&INDEX(Classifica!$C$5:$C$24,$V67)&IF(INDEX(ANA_Attenzione_Supervisore,INDEX(Classifica!$U$5:$U$24,$V67))="Sì",CHAR(10)&"◆ attenzione del supervisore","")) | D67: =IF($V67="","",INDEX(Radar_Mosca!$AA$5:$AA$24,INDEX(Classifica!$U$5:$U$24,$V67))&"") | E67: =IF($W67="","",LEFT($W67,LEN($W67)-2)&".") | I67: =IF($V67="","",IF(INDEX(Classifica!$G$5:$G$24,$V67)="Nuovo","Rischio nuovo nel ciclo.",IFERROR(IF(INDEX(RR_Variazioni,MATCH(cicloCorrente&"|"&INDEX(Classifica!$B$5:$B$24,$V67),RR_Chiave,0))&""="[]","Nessun valore cambiato: confermato sulle fonti del ciclo precedente.",SUBSTITUTE(SUBSTITUTE(SUBSTITUTE(SUBSTITUTE(SUBSTITUTE(SUBSTITUTE(SUBSTITUTE(SUBSTITUTE(SUBSTITUTE(SUBSTITUTE(SUBSTITUTE(SUBSTITUTE(SUBSTITUTE(SUBSTITUTE(SUBSTITUTE(INDEX(RR_Variazioni,MATCH(cicloCorrente&"|"&INDEX(Classifica!$B$5:$B$24,$V67),RR_Chiave,0))&"","[{""dimensione"": ""","• "),"""}, {""dimensione"": """,")"&CHAR(10)&"• "),""", ""da"": "," "),", ""a"": "," → "),", ""evidenza"": """,": "),""", ""data_evidenza"": """," ("),"""}]",")")," null → "," n.v. → ")," → null:"," → n.v.:"),"• impatto","• Impatto"),"• velocity","• Velocity"),"• prossimita","• Prossimita"),"• confidence","• Confidence"),"• probabilita","• Probabilita"),"• severity","• Impatto")),""))) | U67: =IF(Classifica!$B$22="","",IF(OR(18<=3,INDEX(Radar_Mosca!$AA$5:$AA$24,Classifica!$U$22)="Attivazione",INDEX(Radar_Mosca!$AA$5:$AA$24,Classifica!$U$22)="Attenzione",Classifica!$G$22="Variato",Classifica!$G$22="Nuovo"),18,"")) | V67: =IFERROR(_xlfn.AGGREGATE(15,6,$U$50:$U$69,18),"") | W67: =IF($V67="","",IF($V67<=3,$V67&"° per score composito ("&FIXED(INDEX(Classifica!$D$5:$D$24,$V67),2)&IF(ISNUMBER(INDEX(Classifica!$F$5:$F$24,$V67)),IF(INDEX(Classifica!$F$5:$F$24,$V67)<>0,", "&IF(INDEX(Classifica!$F$5:$F$24,$V67)>0,"+","")&FIXED(INDEX(Classifica!$F$5:$F$24,$V67),2)&" sul ciclo prima",""),"")&"); ","")&IF(LEFT(INDEX(Classifica!$H$5:$H$24,$V67),9)="AGIRE ORA","AGIRE ORA: servono X + Y = "&FIXED(INDEX(Classifica!$Y$5:$Y$24,$V67)+INDEX(Classifica!$Z$5:$Z$24,$V67),2)&" anni per decidere e mitigare"&IF(N(INDEX(ANA_Anni_Adeguamento,INDEX(Classifica!$U$5:$U$24,$V67)))>0,", di cui "&N(INDEX(ANA_Anni_Adeguamento,INDEX(Classifica!$U$5:$U$24,$V67)))&" di adeguamento strutturale","")&"; ne restano Z = "&FIXED(INDEX(Classifica!$AA$5:$AA$24,$V67),1)&" prima che possa manifestarsi; ",IF(AND($V67<=3,LEFT(INDEX(Classifica!$H$5:$H$24,$V67),11)="Agire entro"),"margine di Mosca sotto l'anno ("&FIXED(INDEX(Classifica!$I$5:$I$24,$V67),2)&"); ",""))&IF(INDEX(Classifica!$G$5:$G$24,$V67)="Variato","variato nel ciclo"&IF(ISNUMBER(INDEX(Classifica!$F$5:$F$24,$V67)),IF(INDEX(Classifica!$F$5:$F$24,$V67)>0,": peggiora",IF(INDEX(Classifica!$F$5:$F$24,$V67)<0,": migliora","")),"")&"; ",IF(INDEX(Classifica!$G$5:$G$24,$V67)="Nuovo","nuovo nel ciclo; ",""))&IF(INDEX(ANA_Attenzione_Supervisore,INDEX(Classifica!$U$5:$U$24,$V67))="Sì","tema all'attenzione del supervisore; ","")&IF(INDEX(ANA_Presidio_Controlli,INDEX(Classifica!$U$5:$U$24,$V67))="Assente","presidio dei controlli assente; ","")&IF(COUNTIFS(KRI_ID_Rischio,INDEX(Classifica!$B$5:$B$24,$V67),KRI_Ciclo,cicloCorrente,KRI_In_Vigore,"Sì",KRI_Stato,"Rosso")>0,COUNTIFS(KRI_ID_Rischio,INDEX(Classifica!$B$5:$B$24,$V67),KRI_Ciclo,cicloCorrente,KRI_In_Vigore,"Sì",KRI_Stato,"Rosso")&" KRI in rosso; ","")&IF(INDEX(posNetti,INDEX(Classifica!$U$5:$U$24,$V67))>=sogliaDirezione,"notizie in peggioramento (+"&INDEX(posNetti,INDEX(Classifica!$U$5:$U$24,$V67))&" segnali netti in 4 settimane); ",IF(INDEX(posNetti,INDEX(Classifica!$U$5:$U$24,$V67))<=-sogliaDirezione,"notizie in miglioramento ("&INDEX(posNetti,INDEX(Classifica!$U$5:$U$24,$V67))&" segnali netti in 4 settimane); ",""))) | BH67: =2*PI()*62/72 -> 5.4105207 | BI67: =2*SIN($BH67) -> -1.5320889 | BJ67: =2*COS($BH67) -> 1.2855752 | BK67: =3*SIN($BH67) -> -2.2981333 | BL67: =3*COS($BH67) -> 1.9283628 | BM67: =4*SIN($BH67) -> -3.0641778 | BN67: =4*COS($BH67) -> 2.5711504 | BO67: =5*SIN($BH67) -> -3.8302222 | BP67: =5*COS($BH67) -> 3.213938
A68: =IF($V68="","",INDEX(Classifica!$B$5:$B$24,$V68)&CHAR(10)&INDEX(Classifica!$C$5:$C$24,$V68)&IF(INDEX(ANA_Attenzione_Supervisore,INDEX(Classifica!$U$5:$U$24,$V68))="Sì",CHAR(10)&"◆ attenzione del supervisore","")) | D68: =IF($V68="","",INDEX(Radar_Mosca!$AA$5:$AA$24,INDEX(Classifica!$U$5:$U$24,$V68))&"") | E68: =IF($W68="","",LEFT($W68,LEN($W68)-2)&".") | I68: =IF($V68="","",IF(INDEX(Classifica!$G$5:$G$24,$V68)="Nuovo","Rischio nuovo nel ciclo.",IFERROR(IF(INDEX(RR_Variazioni,MATCH(cicloCorrente&"|"&INDEX(Classifica!$B$5:$B$24,$V68),RR_Chiave,0))&""="[]","Nessun valore cambiato: confermato sulle fonti del ciclo precedente.",SUBSTITUTE(SUBSTITUTE(SUBSTITUTE(SUBSTITUTE(SUBSTITUTE(SUBSTITUTE(SUBSTITUTE(SUBSTITUTE(SUBSTITUTE(SUBSTITUTE(SUBSTITUTE(SUBSTITUTE(SUBSTITUTE(SUBSTITUTE(SUBSTITUTE(INDEX(RR_Variazioni,MATCH(cicloCorrente&"|"&INDEX(Classifica!$B$5:$B$24,$V68),RR_Chiave,0))&"","[{""dimensione"": ""","• "),"""}, {""dimensione"": """,")"&CHAR(10)&"• "),""", ""da"": "," "),", ""a"": "," → "),", ""evidenza"": """,": "),""", ""data_evidenza"": """," ("),"""}]",")")," null → "," n.v. → ")," → null:"," → n.v.:"),"• impatto","• Impatto"),"• velocity","• Velocity"),"• prossimita","• Prossimita"),"• confidence","• Confidence"),"• probabilita","• Probabilita"),"• severity","• Impatto")),""))) | U68: =IF(Classifica!$B$23="","",IF(OR(19<=3,INDEX(Radar_Mosca!$AA$5:$AA$24,Classifica!$U$23)="Attivazione",INDEX(Radar_Mosca!$AA$5:$AA$24,Classifica!$U$23)="Attenzione",Classifica!$G$23="Variato",Classifica!$G$23="Nuovo"),19,"")) | V68: =IFERROR(_xlfn.AGGREGATE(15,6,$U$50:$U$69,19),"") | W68: =IF($V68="","",IF($V68<=3,$V68&"° per score composito ("&FIXED(INDEX(Classifica!$D$5:$D$24,$V68),2)&IF(ISNUMBER(INDEX(Classifica!$F$5:$F$24,$V68)),IF(INDEX(Classifica!$F$5:$F$24,$V68)<>0,", "&IF(INDEX(Classifica!$F$5:$F$24,$V68)>0,"+","")&FIXED(INDEX(Classifica!$F$5:$F$24,$V68),2)&" sul ciclo prima",""),"")&"); ","")&IF(LEFT(INDEX(Classifica!$H$5:$H$24,$V68),9)="AGIRE ORA","AGIRE ORA: servono X + Y = "&FIXED(INDEX(Classifica!$Y$5:$Y$24,$V68)+INDEX(Classifica!$Z$5:$Z$24,$V68),2)&" anni per decidere e mitigare"&IF(N(INDEX(ANA_Anni_Adeguamento,INDEX(Classifica!$U$5:$U$24,$V68)))>0,", di cui "&N(INDEX(ANA_Anni_Adeguamento,INDEX(Classifica!$U$5:$U$24,$V68)))&" di adeguamento strutturale","")&"; ne restano Z = "&FIXED(INDEX(Classifica!$AA$5:$AA$24,$V68),1)&" prima che possa manifestarsi; ",IF(AND($V68<=3,LEFT(INDEX(Classifica!$H$5:$H$24,$V68),11)="Agire entro"),"margine di Mosca sotto l'anno ("&FIXED(INDEX(Classifica!$I$5:$I$24,$V68),2)&"); ",""))&IF(INDEX(Classifica!$G$5:$G$24,$V68)="Variato","variato nel ciclo"&IF(ISNUMBER(INDEX(Classifica!$F$5:$F$24,$V68)),IF(INDEX(Classifica!$F$5:$F$24,$V68)>0,": peggiora",IF(INDEX(Classifica!$F$5:$F$24,$V68)<0,": migliora","")),"")&"; ",IF(INDEX(Classifica!$G$5:$G$24,$V68)="Nuovo","nuovo nel ciclo; ",""))&IF(INDEX(ANA_Attenzione_Supervisore,INDEX(Classifica!$U$5:$U$24,$V68))="Sì","tema all'attenzione del supervisore; ","")&IF(INDEX(ANA_Presidio_Controlli,INDEX(Classifica!$U$5:$U$24,$V68))="Assente","presidio dei controlli assente; ","")&IF(COUNTIFS(KRI_ID_Rischio,INDEX(Classifica!$B$5:$B$24,$V68),KRI_Ciclo,cicloCorrente,KRI_In_Vigore,"Sì",KRI_Stato,"Rosso")>0,COUNTIFS(KRI_ID_Rischio,INDEX(Classifica!$B$5:$B$24,$V68),KRI_Ciclo,cicloCorrente,KRI_In_Vigore,"Sì",KRI_Stato,"Rosso")&" KRI in rosso; ","")&IF(INDEX(posNetti,INDEX(Classifica!$U$5:$U$24,$V68))>=sogliaDirezione,"notizie in peggioramento (+"&INDEX(posNetti,INDEX(Classifica!$U$5:$U$24,$V68))&" segnali netti in 4 settimane); ",IF(INDEX(posNetti,INDEX(Classifica!$U$5:$U$24,$V68))<=-sogliaDirezione,"notizie in miglioramento ("&INDEX(posNetti,INDEX(Classifica!$U$5:$U$24,$V68))&" segnali netti in 4 settimane); ",""))) | BH68: =2*PI()*63/72 -> 5.4977871 | BI68: =2*SIN($BH68) -> -1.4142136 | BJ68: =2*COS($BH68) -> 1.4142136 | BK68: =3*SIN($BH68) -> -2.1213203 | BL68: =3*COS($BH68) -> 2.1213203 | BM68: =4*SIN($BH68) -> -2.8284271 | BN68: =4*COS($BH68) -> 2.8284271 | BO68: =5*SIN($BH68) -> -3.5355339 | BP68: =5*COS($BH68) -> 3.5355339
A69: =IF($V69="","",INDEX(Classifica!$B$5:$B$24,$V69)&CHAR(10)&INDEX(Classifica!$C$5:$C$24,$V69)&IF(INDEX(ANA_Attenzione_Supervisore,INDEX(Classifica!$U$5:$U$24,$V69))="Sì",CHAR(10)&"◆ attenzione del supervisore","")) | D69: =IF($V69="","",INDEX(Radar_Mosca!$AA$5:$AA$24,INDEX(Classifica!$U$5:$U$24,$V69))&"") | E69: =IF($W69="","",LEFT($W69,LEN($W69)-2)&".") | I69: =IF($V69="","",IF(INDEX(Classifica!$G$5:$G$24,$V69)="Nuovo","Rischio nuovo nel ciclo.",IFERROR(IF(INDEX(RR_Variazioni,MATCH(cicloCorrente&"|"&INDEX(Classifica!$B$5:$B$24,$V69),RR_Chiave,0))&""="[]","Nessun valore cambiato: confermato sulle fonti del ciclo precedente.",SUBSTITUTE(SUBSTITUTE(SUBSTITUTE(SUBSTITUTE(SUBSTITUTE(SUBSTITUTE(SUBSTITUTE(SUBSTITUTE(SUBSTITUTE(SUBSTITUTE(SUBSTITUTE(SUBSTITUTE(SUBSTITUTE(SUBSTITUTE(SUBSTITUTE(INDEX(RR_Variazioni,MATCH(cicloCorrente&"|"&INDEX(Classifica!$B$5:$B$24,$V69),RR_Chiave,0))&"","[{""dimensione"": ""","• "),"""}, {""dimensione"": """,")"&CHAR(10)&"• "),""", ""da"": "," "),", ""a"": "," → "),", ""evidenza"": """,": "),""", ""data_evidenza"": """," ("),"""}]",")")," null → "," n.v. → ")," → null:"," → n.v.:"),"• impatto","• Impatto"),"• velocity","• Velocity"),"• prossimita","• Prossimita"),"• confidence","• Confidence"),"• probabilita","• Probabilita"),"• severity","• Impatto")),""))) | U69: =IF(Classifica!$B$24="","",IF(OR(20<=3,INDEX(Radar_Mosca!$AA$5:$AA$24,Classifica!$U$24)="Attivazione",INDEX(Radar_Mosca!$AA$5:$AA$24,Classifica!$U$24)="Attenzione",Classifica!$G$24="Variato",Classifica!$G$24="Nuovo"),20,"")) | V69: =IFERROR(_xlfn.AGGREGATE(15,6,$U$50:$U$69,20),"") | W69: =IF($V69="","",IF($V69<=3,$V69&"° per score composito ("&FIXED(INDEX(Classifica!$D$5:$D$24,$V69),2)&IF(ISNUMBER(INDEX(Classifica!$F$5:$F$24,$V69)),IF(INDEX(Classifica!$F$5:$F$24,$V69)<>0,", "&IF(INDEX(Classifica!$F$5:$F$24,$V69)>0,"+","")&FIXED(INDEX(Classifica!$F$5:$F$24,$V69),2)&" sul ciclo prima",""),"")&"); ","")&IF(LEFT(INDEX(Classifica!$H$5:$H$24,$V69),9)="AGIRE ORA","AGIRE ORA: servono X + Y = "&FIXED(INDEX(Classifica!$Y$5:$Y$24,$V69)+INDEX(Classifica!$Z$5:$Z$24,$V69),2)&" anni per decidere e mitigare"&IF(N(INDEX(ANA_Anni_Adeguamento,INDEX(Classifica!$U$5:$U$24,$V69)))>0,", di cui "&N(INDEX(ANA_Anni_Adeguamento,INDEX(Classifica!$U$5:$U$24,$V69)))&" di adeguamento strutturale","")&"; ne restano Z = "&FIXED(INDEX(Classifica!$AA$5:$AA$24,$V69),1)&" prima che possa manifestarsi; ",IF(AND($V69<=3,LEFT(INDEX(Classifica!$H$5:$H$24,$V69),11)="Agire entro"),"margine di Mosca sotto l'anno ("&FIXED(INDEX(Classifica!$I$5:$I$24,$V69),2)&"); ",""))&IF(INDEX(Classifica!$G$5:$G$24,$V69)="Variato","variato nel ciclo"&IF(ISNUMBER(INDEX(Classifica!$F$5:$F$24,$V69)),IF(INDEX(Classifica!$F$5:$F$24,$V69)>0,": peggiora",IF(INDEX(Classifica!$F$5:$F$24,$V69)<0,": migliora","")),"")&"; ",IF(INDEX(Classifica!$G$5:$G$24,$V69)="Nuovo","nuovo nel ciclo; ",""))&IF(INDEX(ANA_Attenzione_Supervisore,INDEX(Classifica!$U$5:$U$24,$V69))="Sì","tema all'attenzione del supervisore; ","")&IF(INDEX(ANA_Presidio_Controlli,INDEX(Classifica!$U$5:$U$24,$V69))="Assente","presidio dei controlli assente; ","")&IF(COUNTIFS(KRI_ID_Rischio,INDEX(Classifica!$B$5:$B$24,$V69),KRI_Ciclo,cicloCorrente,KRI_In_Vigore,"Sì",KRI_Stato,"Rosso")>0,COUNTIFS(KRI_ID_Rischio,INDEX(Classifica!$B$5:$B$24,$V69),KRI_Ciclo,cicloCorrente,KRI_In_Vigore,"Sì",KRI_Stato,"Rosso")&" KRI in rosso; ","")&IF(INDEX(posNetti,INDEX(Classifica!$U$5:$U$24,$V69))>=sogliaDirezione,"notizie in peggioramento (+"&INDEX(posNetti,INDEX(Classifica!$U$5:$U$24,$V69))&" segnali netti in 4 settimane); ",IF(INDEX(posNetti,INDEX(Classifica!$U$5:$U$24,$V69))<=-sogliaDirezione,"notizie in miglioramento ("&INDEX(posNetti,INDEX(Classifica!$U$5:$U$24,$V69))&" segnali netti in 4 settimane); ",""))) | BH69: =2*PI()*64/72 -> 5.5850536 | BI69: =2*SIN($BH69) -> -1.2855752 | BJ69: =2*COS($BH69) -> 1.5320889 | BK69: =3*SIN($BH69) -> -1.9283628 | BL69: =3*COS($BH69) -> 2.2981333 | BM69: =4*SIN($BH69) -> -2.5711504 | BN69: =4*COS($BH69) -> 3.0641778 | BO69: =5*SIN($BH69) -> -3.213938 | BP69: =5*COS($BH69) -> 3.8302222
BH70: =2*PI()*65/72 -> 5.6723201 | BI70: =2*SIN($BH70) -> -1.1471529 | BJ70: =2*COS($BH70) -> 1.6383041 | BK70: =3*SIN($BH70) -> -1.7207293 | BL70: =3*COS($BH70) -> 2.4574561 | BM70: =4*SIN($BH70) -> -2.2943057 | BN70: =4*COS($BH70) -> 3.2766082 | BO70: =5*SIN($BH70) -> -2.8678822 | BP70: =5*COS($BH70) -> 4.0957602
A71: Limiti: Le valutazioni sono prodotte con il supporto di un modello linguistico ancorato alla rubrica della Banca e verificate da controlli deterministici e da un challenger indipendente. Non sono stime di perdita ne' probabilita'. Gli score cambiano solo nel ciclo trimestrale, su evidenza datata; le notizie settimanali producono segnali, non variazioni. Il controllo C4 (plausibilita' rispetto ai descrittori) e' solo di giudizio. La valutazione e' valida dopo l'approvazione indicata in Approvato_Da. | BH71: =2*PI()*66/72 -> 5.7595865 | BI71: =2*SIN($BH71) -> -1 | BJ71: =2*COS($BH71) -> 1.7320508 | BK71: =3*SIN($BH71) -> -1.5 | BL71: =3*COS($BH71) -> 2.5980762 | BM71: =4*SIN($BH71) -> -2 | BN71: =4*COS($BH71) -> 3.4641016 | BO71: =5*SIN($BH71) -> -2.5 | BP71: =5*COS($BH71) -> 4.330127
A72: Legenda — NFR-nn = codice del rischio; ◆ = tema all'attenzione del supervisore (BCE, EBA, Banca d'Italia), indicato dal validatore. P = Probabilita, I = Impatto, P x I = Probabilita x Impatto, da 1 a 25. X = anni per decidere e avviare la mitigazione (un trimestre); Y = anni per mitigare (azioni o adeguamento strutturale); Z = anni prima che il rischio possa manifestarsi (dalla Prossimita); AGIRE ORA = X + Y > Z. Radar: colore del cerchio = livello di allerta (rosso Attivazione, giallo Attenzione, verde Monitoraggio); dentro il cerchio rosso AGIRE ORA (X + Y > Z); area = P x I; settore = categoria di rischio. KRI = indicatore di rischio (Key Risk Indicator). A1 = agente che valuta i rischi ogni trimestre; A5 = agente di controllo indipendente. | BH72: =2*PI()*67/72 -> 5.846853 | BI72: =2*SIN($BH72) -> -0.84523652 | BJ72: =2*COS($BH72) -> 1.8126156 | BK72: =3*SIN($BH72) -> -1.2678548 | BL72: =3*COS($BH72) -> 2.7189234 | BM72: =4*SIN($BH72) -> -1.690473 | BN72: =4*COS($BH72) -> 3.6252311 | BO72: =5*SIN($BH72) -> -2.1130913 | BP72: =5*COS($BH72) -> 4.5315389
BH73: =2*PI()*68/72 -> 5.9341195 | BI73: =2*SIN($BH73) -> -0.68404029 | BJ73: =2*COS($BH73) -> 1.8793852 | BK73: =3*SIN($BH73) -> -1.0260604 | BL73: =3*COS($BH73) -> 2.8190779 | BM73: =4*SIN($BH73) -> -1.3680806 | BN73: =4*COS($BH73) -> 3.7587705 | BO73: =5*SIN($BH73) -> -1.7101007 | BP73: =5*COS($BH73) -> 4.6984631
BH74: =2*PI()*69/72 -> 6.0213859 | BI74: =2*SIN($BH74) -> -0.51763809 | BJ74: =2*COS($BH74) -> 1.9318517 | BK74: =3*SIN($BH74) -> -0.77645714 | BL74: =3*COS($BH74) -> 2.8977775 | BM74: =4*SIN($BH74) -> -1.0352762 | BN74: =4*COS($BH74) -> 3.8637033 | BO74: =5*SIN($BH74) -> -1.2940952 | BP74: =5*COS($BH74) -> 4.8296291
BH75: =2*PI()*70/72 -> 6.1086524 | BI75: =2*SIN($BH75) -> -0.34729636 | BJ75: =2*COS($BH75) -> 1.9696155 | BK75: =3*SIN($BH75) -> -0.52094453 | BL75: =3*COS($BH75) -> 2.9544233 | BM75: =4*SIN($BH75) -> -0.69459271 | BN75: =4*COS($BH75) -> 3.939231 | BO75: =5*SIN($BH75) -> -0.86824089 | BP75: =5*COS($BH75) -> 4.9240388
BH76: =2*PI()*71/72 -> 6.1959188 | BI76: =2*SIN($BH76) -> -0.17431149 | BJ76: =2*COS($BH76) -> 1.9923894 | BK76: =3*SIN($BH76) -> -0.26146723 | BL76: =3*COS($BH76) -> 2.9885841 | BM76: =4*SIN($BH76) -> -0.34862297 | BN76: =4*COS($BH76) -> 3.9847788 | BO76: =5*SIN($BH76) -> -0.43577871 | BP76: =5*COS($BH76) -> 4.9809735
BH77: =2*PI()*72/72 -> 6.2831853 | BI77: =2*SIN($BH77) -> -4.9005938e-16 | BJ77: =2*COS($BH77) -> 2 | BK77: =3*SIN($BH77) -> -7.3508907e-16 | BL77: =3*COS($BH77) -> 3 | BM77: =4*SIN($BH77) -> -9.8011876e-16 | BN77: =4*COS($BH77) -> 4 | BO77: =5*SIN($BH77) -> -1.2251485e-15 | BP77: =5*COS($BH77) -> 5

Sheet Classifica
A1: ="Horizon Scan NFR — Classifica e lente di Mosca · "&etichettaCiclo -> Horizon Scan NFR — Classifica e lente di Mosca · Ciclo 2026Q4 · dati al 31/12/2026 · da validare · Uso interno
A2: CICLO TRIMESTRALE — calcolato dal foglio sui valori del ciclo; nessun agente ordina o stima l'urgenza. Come si legge: un rischio per barra, dal piu' alto per score composito (1-5, 5 = peggiore). Colore = urgenza di Mosca: rosso agire ora, ambra entro l'anno, grigio c'e' margine. A destra la lente di Mosca spiega il colore: tempo necessario per decidere e mitigare (X + Y) contro tempo prima che il rischio possa manifestarsi (Z). | AL2: =IF(COUNTIF(H5:H24,"AGIRE ORA*")=0,"Nessun rischio da affrontare subito",COUNTIF(H5:H24,"AGIRE ORA*")&" da affrontare subito: "&_xlfn.TEXTJOIN(", ",TRUE,AB5:AB24)) -> 2 da affrontare subito: NFR-01, NFR-11
AL3: Lente di Mosca: chi e' in ritardo, e di quanto (anni)
A4: Pos. | B4: ID | C4: Nome | D4: Score composito | E4: Score ciclo prima | F4: Δ score | G4: Esito | H4: Urgenza (Mosca) | I4: Margine Z-(X+Y), anni | J4: Owner | K4: Etichetta del grafico | T4: Chiave d'ordine | U4: Posizione in anagrafica | V4: Barra: agire ora | W4: Barra: entro l'anno | X4: Barra: con margine | Y4: X anni | Z4: Y anni | AA4: Z anni | AB4: Da affrontare subito | AD4: Chiave della lente | AE4: Posizione nella lente | AF4: Etichetta della lente | AG4: X | AH4: Y entro Z | AI4: Y oltre Z | AJ4: Z
A5: =IF($U5="","",1) -> 1 | B5: =IF($U5="","",INDEX(posID,$U5)) -> NFR-01 | C5: =IF($U5="","",INDEX(posNome,$U5)) -> Frodi su pagamenti istantanei abilitate da AI generativa | D5: =IF($U5="","",INDEX(posScore,$U5)) -> 4.4 | E5: =IF($U5="","",IFERROR(INDEX(posScorePrec,$U5),"—")) -> 4.2 | F5: =IF(AND(ISNUMBER(D5),ISNUMBER(E5)),D5-E5,"") -> 0.2 | G5: =IF($U5="","",IFERROR(INDEX(RR_Esito,MATCH(cicloCorrente&"|"&B5,RR_Chiave,0))&"","")) -> Variato | H5: =IF($U5="","",INDEX(Radar_Mosca!$L$5:$L$24,$U5)) -> AGIRE ORA: X+Y > Z | I5: =IF($U5="","",IFERROR(INDEX(Radar_Mosca!$K$5:$K$24,$U5),"")) -> -0.5 | J5: =IF($U5="","",INDEX(ANA_Owner,$U5)&"") -> Funzione Antifrode | K5: =IF($U5="","",B5&" "&IF(ISNUMBER(F5),IF(F5>0,"▲",IF(F5<0,"▼","●")),"○")&" "&LEFT(C5,34)&IF(LEN(C5)>34,"…","")) -> NFR-01 ▲ Frodi su pagamenti istantanei abil… | T5: =IF(ISNUMBER(INDEX(posScore,1)),INDEX(posScore,1)-1/100000,"") -> 4.39999 | U5: =IFERROR(MATCH(_xlfn.AGGREGATE(14,6,$T$5:$T$24,1),$T$5:$T$24,0),"") -> 1 | V5: =IF($U5="",NA(),IF(LEFT(H5,9)="AGIRE ORA",D5,0)) -> 4.4 | W5: =IF($U5="",NA(),IF(LEFT(H5,11)="Agire entro",D5,0)) -> 0 | X5: =IF($U5="",NA(),IF(OR(LEFT(H5,9)="AGIRE ORA",LEFT(H5,11)="Agire entro"),0,D5)) -> 0 | Y5: =IF($U5="",NA(),INDEX(Radar_Mosca!$I$5:$I$24,$U5)) -> 0.25 | Z5: =IF($U5="",NA(),INDEX(Radar_Mosca!$J$5:$J$24,$U5)) -> 0.25 | AA5: =IF($U5="",NA(),INDEX(Radar_Mosca!$H$5:$H$24,$U5)) -> 0 | AB5: =IF(LEFT(H5,9)="AGIRE ORA",B5,"") -> NFR-01 | AD5: =IF(ISNUMBER(I5),I5+1/100000,"") -> -0.49999 | AE5: =IFERROR(MATCH(_xlfn.AGGREGATE(15,6,$AD$5:$AD$24,1),$AD$5:$AD$24,0),"") -> 11 | AF5: =IF($AE5="","",INDEX($B$5:$B$24,$AE5)&" ("&IF(INDEX($I$5:$I$24,$AE5)<0,"−","+")&FIXED(ABS(INDEX($I$5:$I$24,$AE5)),2)&")") -> NFR-11 (−1,75) | AG5: =IF($AE5="",NA(),INDEX($Y$5:$Y$24,$AE5)) -> 0.25 | AH5: =IF($AE5="",NA(),IF(INDEX($Y$5:$Y$24,$AE5)+INDEX($Z$5:$Z$24,$AE5)>INDEX($AA$5:$AA$24,$AE5),NA(),INDEX($Z$5:$Z$24,$AE5))) -> #N/A | AI5: =IF($AE5="",NA(),IF(INDEX($Y$5:$Y$24,$AE5)+INDEX($Z$5:$Z$24,$AE5)>INDEX($AA$5:$AA$24,$AE5),INDEX($Z$5:$Z$24,$AE5),NA())) -> 3 | AJ5: =IF($AE5="",NA(),INDEX($AA$5:$AA$24,$AE5)) -> 1.5
A6: =IF($U6="","",2) -> 2 | B6: =IF($U6="","",INDEX(posID,$U6)) -> NFR-07 | C6: =IF($U6="","",INDEX(posNome,$U6)) -> Ransomware presso un fornitore di servizi di pagamento | D6: =IF($U6="","",INDEX(posScore,$U6)) -> 3.75 | E6: =IF($U6="","",IFERROR(INDEX(posScorePrec,$U6),"—")) -> 3.75 | F6: =IF(AND(ISNUMBER(D6),ISNUMBER(E6)),D6-E6,"") -> 0 | G6: =IF($U6="","",IFERROR(INDEX(RR_Esito,MATCH(cicloCorrente&"|"&B6,RR_Chiave,0))&"","")) -> Confermato | H6: =IF($U6="","",INDEX(Radar_Mosca!$L$5:$L$24,$U6)) -> Agire entro l'anno | I6: =IF($U6="","",IFERROR(INDEX(Radar_Mosca!$K$5:$K$24,$U6),"")) -> 0.75 | J6: =IF($U6="","",INDEX(ANA_Owner,$U6)&"") -> Funzione ICT & Security Risk | K6: =IF($U6="","",B6&" "&IF(ISNUMBER(F6),IF(F6>0,"▲",IF(F6<0,"▼","●")),"○")&" "&LEFT(C6,34)&IF(LEN(C6)>34,"…","")) -> NFR-07 ● Ransomware presso un fornitore di … | T6: =IF(ISNUMBER(INDEX(posScore,2)),INDEX(posScore,2)-2/100000,"") -> 3.29998 | U6: =IFERROR(MATCH(_xlfn.AGGREGATE(14,6,$T$5:$T$24,2),$T$5:$T$24,0),"") -> 7 | V6: =IF($U6="",NA(),IF(LEFT(H6,9)="AGIRE ORA",D6,0)) -> 0 | W6: =IF($U6="",NA(),IF(LEFT(H6,11)="Agire entro",D6,0)) -> 3.75 | X6: =IF($U6="",NA(),IF(OR(LEFT(H6,9)="AGIRE ORA",LEFT(H6,11)="Agire entro"),0,D6)) -> 0 | Y6: =IF($U6="",NA(),INDEX(Radar_Mosca!$I$5:$I$24,$U6)) -> 0.25 | Z6: =IF($U6="",NA(),INDEX(Radar_Mosca!$J$5:$J$24,$U6)) -> 0.5 | AA6: =IF($U6="",NA(),INDEX(Radar_Mosca!$H$5:$H$24,$U6)) -> 1.5 | AB6: =IF(LEFT(H6,9)="AGIRE ORA",B6,"") | AD6: =IF(ISNUMBER(I6),I6+2/100000,"") -> 0.75002 | AE6: =IFERROR(MATCH(_xlfn.AGGREGATE(15,6,$AD$5:$AD$24,2),$AD$5:$AD$24,0),"") -> 1 | AF6: =IF($AE6="","",INDEX($B$5:$B$24,$AE6)&" ("&IF(INDEX($I$5:$I$24,$AE6)<0,"−","+")&FIXED(ABS(INDEX($I$5:$I$24,$AE6)),2)&")") -> NFR-01 (−0,50) | AG6: =IF($AE6="",NA(),INDEX($Y$5:$Y$24,$AE6)) -> 0.25 | AH6: =IF($AE6="",NA(),IF(INDEX($Y$5:$Y$24,$AE6)+INDEX($Z$5:$Z$24,$AE6)>INDEX($AA$5:$AA$24,$AE6),NA(),INDEX($Z$5:$Z$24,$AE6))) -> #N/A | AI6: =IF($AE6="",NA(),IF(INDEX($Y$5:$Y$24,$AE6)+INDEX($Z$5:$Z$24,$AE6)>INDEX($AA$5:$AA$24,$AE6),INDEX($Z$5:$Z$24,$AE6),NA())) -> 0.25 | AJ6: =IF($AE6="",NA(),INDEX($AA$5:$AA$24,$AE6)) -> 0
A7: =IF($U7="","",3) -> 3 | B7: =IF($U7="","",INDEX(posID,$U7)) -> NFR-12 | C7: =IF($U7="","",INDEX(posNome,$U7)) -> Errori operativi nei pagamenti istantanei obbligatori | D7: =IF($U7="","",INDEX(posScore,$U7)) -> 3.65 | E7: =IF($U7="","",IFERROR(INDEX(posScorePrec,$U7),"—")) -> 3.65 | F7: =IF(AND(ISNUMBER(D7),ISNUMBER(E7)),D7-E7,"") -> 0 | G7: =IF($U7="","",IFERROR(INDEX(RR_Esito,MATCH(cicloCorrente&"|"&B7,RR_Chiave,0))&"","")) -> Confermato | H7: =IF($U7="","",INDEX(Radar_Mosca!$L$5:$L$24,$U7)) -> Agire entro l'anno | I7: =IF($U7="","",IFERROR(INDEX(Radar_Mosca!$K$5:$K$24,$U7),"")) -> 0 | J7: =IF($U7="","",INDEX(ANA_Owner,$U7)&"") -> Funzione Operations | K7: =IF($U7="","",B7&" "&IF(ISNUMBER(F7),IF(F7>0,"▲",IF(F7<0,"▼","●")),"○")&" "&LEFT(C7,34)&IF(LEN(C7)>34,"…","")) -> NFR-12 ● Errori operativi nei pagamenti ist… | T7: =IF(ISNUMBER(INDEX(posScore,3)),INDEX(posScore,3)-3/100000,"") -> 2.99997 | U7: =IFERROR(MATCH(_xlfn.AGGREGATE(14,6,$T$5:$T$24,3),$T$5:$T$24,0),"") -> 12 | V7: =IF($U7="",NA(),IF(LEFT(H7,9)="AGIRE ORA",D7,0)) -> 0 | W7: =IF($U7="",NA(),IF(LEFT(H7,11)="Agire entro",D7,0)) -> 3.65 | X7: =IF($U7="",NA(),IF(OR(LEFT(H7,9)="AGIRE ORA",LEFT(H7,11)="Agire entro"),0,D7)) -> 0 | Y7: =IF($U7="",NA(),INDEX(Radar_Mosca!$I$5:$I$24,$U7)) -> 0.25 | Z7: =IF($U7="",NA(),INDEX(Radar_Mosca!$J$5:$J$24,$U7)) -> 0.25 | AA7: =IF($U7="",NA(),INDEX(Radar_Mosca!$H$5:$H$24,$U7)) -> 0.5 | AB7: =IF(LEFT(H7,9)="AGIRE ORA",B7,"") | AD7: =IF(ISNUMBER(I7),I7+3/100000,"") -> 3e-05 | AE7: =IFERROR(MATCH(_xlfn.AGGREGATE(15,6,$AD$5:$AD$24,3),$AD$5:$AD$24,0),"") -> 3 | AF7: =IF($AE7="","",INDEX($B$5:$B$24,$AE7)&" ("&IF(INDEX($I$5:$I$24,$AE7)<0,"−","+")&FIXED(ABS(INDEX($I$5:$I$24,$AE7)),2)&")") -> NFR-12 (+0,00) | AG7: =IF($AE7="",NA(),INDEX($Y$5:$Y$24,$AE7)) -> 0.25 | AH7: =IF($AE7="",NA(),IF(INDEX($Y$5:$Y$24,$AE7)+INDEX($Z$5:$Z$24,$AE7)>INDEX($AA$5:$AA$24,$AE7),NA(),INDEX($Z$5:$Z$24,$AE7))) -> 0.25 | AI7: =IF($AE7="",NA(),IF(INDEX($Y$5:$Y$24,$AE7)+INDEX($Z$5:$Z$24,$AE7)>INDEX($AA$5:$AA$24,$AE7),INDEX($Z$5:$Z$24,$AE7),NA())) -> #N/A | AJ7: =IF($AE7="",NA(),INDEX($AA$5:$AA$24,$AE7)) -> 0.5
A8: =IF($U8="","",4) -> 4 | B8: =IF($U8="","",INDEX(posID,$U8)) -> NFR-02 | C8: =IF($U8="","",INDEX(posNome,$U8)) -> Concentrazione su un fornitore cloud critico | D8: =IF($U8="","",INDEX(posScore,$U8)) -> 3.3 | E8: =IF($U8="","",IFERROR(INDEX(posScorePrec,$U8),"—")) -> 3.3 | F8: =IF(AND(ISNUMBER(D8),ISNUMBER(E8)),D8-E8,"") -> 0 | G8: =IF($U8="","",IFERROR(INDEX(RR_Esito,MATCH(cicloCorrente&"|"&B8,RR_Chiave,0))&"","")) -> Confermato | H8: =IF($U8="","",INDEX(Radar_Mosca!$L$5:$L$24,$U8)) -> Margine 1 anno | I8: =IF($U8="","",IFERROR(INDEX(Radar_Mosca!$K$5:$K$24,$U8),"")) -> 1 | J8: =IF($U8="","",INDEX(ANA_Owner,$U8)&"") -> Funzione ICT & Security Risk | K8: =IF($U8="","",B8&" "&IF(ISNUMBER(F8),IF(F8>0,"▲",IF(F8<0,"▼","●")),"○")&" "&LEFT(C8,34)&IF(LEN(C8)>34,"…","")) -> NFR-02 ● Concentrazione su un fornitore clo… | T8: =IF(ISNUMBER(INDEX(posScore,4)),INDEX(posScore,4)-4/100000,"") -> 2.79996 | U8: =IFERROR(MATCH(_xlfn.AGGREGATE(14,6,$T$5:$T$24,4),$T$5:$T$24,0),"") -> 2 | V8: =IF($U8="",NA(),IF(LEFT(H8,9)="AGIRE ORA",D8,0)) -> 0 | W8: =IF($U8="",NA(),IF(LEFT(H8,11)="Agire entro",D8,0)) -> 0 | X8: =IF($U8="",NA(),IF(OR(LEFT(H8,9)="AGIRE ORA",LEFT(H8,11)="Agire entro"),0,D8)) -> 3.3 | Y8: =IF($U8="",NA(),INDEX(Radar_Mosca!$I$5:$I$24,$U8)) -> 0.25 | Z8: =IF($U8="",NA(),INDEX(Radar_Mosca!$J$5:$J$24,$U8)) -> 0.25 | AA8: =IF($U8="",NA(),INDEX(Radar_Mosca!$H$5:$H$24,$U8)) -> 1.5 | AB8: =IF(LEFT(H8,9)="AGIRE ORA",B8,"") | AD8: =IF(ISNUMBER(I8),I8+4/100000,"") -> 1.00004 | AE8: =IFERROR(MATCH(_xlfn.AGGREGATE(15,6,$AD$5:$AD$24,4),$AD$5:$AD$24,0),"") -> 5 | AF8: =IF($AE8="","",INDEX($B$5:$B$24,$AE8)&" ("&IF(INDEX($I$5:$I$24,$AE8)<0,"−","+")&FIXED(ABS(INDEX($I$5:$I$24,$AE8)),2)&")") -> NFR-03 (+0,00) | AG8: =IF($AE8="",NA(),INDEX($Y$5:$Y$24,$AE8)) -> 0.25 | AH8: =IF($AE8="",NA(),IF(INDEX($Y$5:$Y$24,$AE8)+INDEX($Z$5:$Z$24,$AE8)>INDEX($AA$5:$AA$24,$AE8),NA(),INDEX($Z$5:$Z$24,$AE8))) -> 0.25 | AI8: =IF($AE8="",NA(),IF(INDEX($Y$5:$Y$24,$AE8)+INDEX($Z$5:$Z$24,$AE8)>INDEX($AA$5:$AA$24,$AE8),INDEX($Z$5:$Z$24,$AE8),NA())) -> #N/A | AJ8: =IF($AE8="",NA(),INDEX($AA$5:$AA$24,$AE8)) -> 0.5
A9: =IF($U9="","",5) -> 5 | B9: =IF($U9="","",INDEX(posID,$U9)) -> NFR-03 | C9: =IF($U9="","",INDEX(posNome,$U9)) -> Greenwashing nella commercializzazione di prodotti ESG | D9: =IF($U9="","",INDEX(posScore,$U9)) -> 3 | E9: =IF($U9="","",IFERROR(INDEX(posScorePrec,$U9),"—")) -> 3 | F9: =IF(AND(ISNUMBER(D9),ISNUMBER(E9)),D9-E9,"") -> 0 | G9: =IF($U9="","",IFERROR(INDEX(RR_Esito,MATCH(cicloCorrente&"|"&B9,RR_Chiave,0))&"","")) -> Confermato | H9: =IF($U9="","",INDEX(Radar_Mosca!$L$5:$L$24,$U9)) -> Agire entro l'anno | I9: =IF($U9="","",IFERROR(INDEX(Radar_Mosca!$K$5:$K$24,$U9),"")) -> 0 | J9: =IF($U9="","",INDEX(ANA_Owner,$U9)&"") -> Funzione Compliance | K9: =IF($U9="","",B9&" "&IF(ISNUMBER(F9),IF(F9>0,"▲",IF(F9<0,"▼","●")),"○")&" "&LEFT(C9,34)&IF(LEN(C9)>34,"…","")) -> NFR-03 ● Greenwashing nella commercializzaz… | T9: =IF(ISNUMBER(INDEX(posScore,5)),INDEX(posScore,5)-5/100000,"") -> 2.99995 | U9: =IFERROR(MATCH(_xlfn.AGGREGATE(14,6,$T$5:$T$24,5),$T$5:$T$24,0),"") -> 3 | V9: =IF($U9="",NA(),IF(LEFT(H9,9)="AGIRE ORA",D9,0)) -> 0 | W9: =IF($U9="",NA(),IF(LEFT(H9,11)="Agire entro",D9,0)) -> 3 | X9: =IF($U9="",NA(),IF(OR(LEFT(H9,9)="AGIRE ORA",LEFT(H9,11)="Agire entro"),0,D9)) -> 0 | Y9: =IF($U9="",NA(),INDEX(Radar_Mosca!$I$5:$I$24,$U9)) -> 0.25 | Z9: =IF($U9="",NA(),INDEX(Radar_Mosca!$J$5:$J$24,$U9)) -> 0.25 | AA9: =IF($U9="",NA(),INDEX(Radar_Mosca!$H$5:$H$24,$U9)) -> 0.5 | AB9: =IF(LEFT(H9,9)="AGIRE ORA",B9,"") | AD9: =IF(ISNUMBER(I9),I9+5/100000,"") -> 5e-05 | AE9: =IFERROR(MATCH(_xlfn.AGGREGATE(15,6,$AD$5:$AD$24,5),$AD$5:$AD$24,0),"") -> 7 | AF9: =IF($AE9="","",INDEX($B$5:$B$24,$AE9)&" ("&IF(INDEX($I$5:$I$24,$AE9)<0,"−","+")&FIXED(ABS(INDEX($I$5:$I$24,$AE9)),2)&")") -> NFR-06 (+0,25) | AG9: =IF($AE9="",NA(),INDEX($Y$5:$Y$24,$AE9)) -> 0.25 | AH9: =IF($AE9="",NA(),IF(INDEX($Y$5:$Y$24,$AE9)+INDEX($Z$5:$Z$24,$AE9)>INDEX($AA$5:$AA$24,$AE9),NA(),INDEX($Z$5:$Z$24,$AE9))) -> 1 | AI9: =IF($AE9="",NA(),IF(INDEX($Y$5:$Y$24,$AE9)+INDEX($Z$5:$Z$24,$AE9)>INDEX($AA$5:$AA$24,$AE9),INDEX($Z$5:$Z$24,$AE9),NA())) -> #N/A | AJ9: =IF($AE9="",NA(),INDEX($AA$5:$AA$24,$AE9)) -> 1.5
A10: =IF($U10="","",6) -> 6 | B10: =IF($U10="","",INDEX(posID,$U10)) -> NFR-05 | C10: =IF($U10="","",INDEX(posNome,$U10)) -> Errori di processo nella migrazione del core banking | D10: =IF($U10="","",INDEX(posScore,$U10)) -> 3 | E10: =IF($U10="","",IFERROR(INDEX(posScorePrec,$U10),"—")) -> 3 | F10: =IF(AND(ISNUMBER(D10),ISNUMBER(E10)),D10-E10,"") -> 0 | G10: =IF($U10="","",IFERROR(INDEX(RR_Esito,MATCH(cicloCorrente&"|"&B10,RR_Chiave,0))&"","")) -> Confermato | H10: =IF($U10="","",INDEX(Radar_Mosca!$L$5:$L$24,$U10)) -> Margine 1 anno | I10: =IF($U10="","",IFERROR(INDEX(Radar_Mosca!$K$5:$K$24,$U10),"")) -> 1 | J10: =IF($U10="","",INDEX(ANA_Owner,$U10)&"") -> Funzione Operations | K10: =IF($U10="","",B10&" "&IF(ISNUMBER(F10),IF(F10>0,"▲",IF(F10<0,"▼","●")),"○")&" "&LEFT(C10,34)&IF(LEN(C10)>34,"…","")) -> NFR-05 ● Errori di processo nella migrazion… | T10: =IF(ISNUMBER(INDEX(posScore,6)),INDEX(posScore,6)-6/100000,"") -> 2.99994 | U10: =IFERROR(MATCH(_xlfn.AGGREGATE(14,6,$T$5:$T$24,6),$T$5:$T$24,0),"") -> 5 | V10: =IF($U10="",NA(),IF(LEFT(H10,9)="AGIRE ORA",D10,0)) -> 0 | W10: =IF($U10="",NA(),IF(LEFT(H10,11)="Agire entro",D10,0)) -> 0 | X10: =IF($U10="",NA(),IF(OR(LEFT(H10,9)="AGIRE ORA",LEFT(H10,11)="Agire entro"),0,D10)) -> 3 | Y10: =IF($U10="",NA(),INDEX(Radar_Mosca!$I$5:$I$24,$U10)) -> 0.25 | Z10: =IF($U10="",NA(),INDEX(Radar_Mosca!$J$5:$J$24,$U10)) -> 0.25 | AA10: =IF($U10="",NA(),INDEX(Radar_Mosca!$H$5:$H$24,$U10)) -> 1.5 | AB10: =IF(LEFT(H10,9)="AGIRE ORA",B10,"") | AD10: =IF(ISNUMBER(I10),I10+6/100000,"") -> 1.00006 | AE10: =IFERROR(MATCH(_xlfn.AGGREGATE(15,6,$AD$5:$AD$24,6),$AD$5:$AD$24,0),"") -> 2 | AF10: =IF($AE10="","",INDEX($B$5:$B$24,$AE10)&" ("&IF(INDEX($I$5:$I$24,$AE10)<0,"−","+")&FIXED(ABS(INDEX($I$5:$I$24,$AE10)),2)&")") -> NFR-07 (+0,75) | AG10: =IF($AE10="",NA(),INDEX($Y$5:$Y$24,$AE10)) -> 0.25 | AH10: =IF($AE10="",NA(),IF(INDEX($Y$5:$Y$24,$AE10)+INDEX($Z$5:$Z$24,$AE10)>INDEX($AA$5:$AA$24,$AE10),NA(),INDEX($Z$5:$Z$24,$AE10))) -> 0.5 | AI10: =IF($AE10="",NA(),IF(INDEX($Y$5:$Y$24,$AE10)+INDEX($Z$5:$Z$24,$AE10)>INDEX($AA$5:$AA$24,$AE10),INDEX($Z$5:$Z$24,$AE10),NA())) -> #N/A | AJ10: =IF($AE10="",NA(),INDEX($AA$5:$AA$24,$AE10)) -> 1.5
A11: =IF($U11="","",7) -> 7 | B11: =IF($U11="","",INDEX(posID,$U11)) -> NFR-06 | C11: =IF($U11="","",INDEX(posNome,$U11)) -> Esfiltrazione di dati tramite strumenti di AI non autorizzati | D11: =IF($U11="","",INDEX(posScore,$U11)) -> 3 | E11: =IF($U11="","",IFERROR(INDEX(posScorePrec,$U11),"—")) -> 3 | F11: =IF(AND(ISNUMBER(D11),ISNUMBER(E11)),D11-E11,"") -> 0 | G11: =IF($U11="","",IFERROR(INDEX(RR_Esito,MATCH(cicloCorrente&"|"&B11,RR_Chiave,0))&"","")) -> Confermato | H11: =IF($U11="","",INDEX(Radar_Mosca!$L$5:$L$24,$U11)) -> Agire entro l'anno | I11: =IF($U11="","",IFERROR(INDEX(Radar_Mosca!$K$5:$K$24,$U11),"")) -> 0.25 | J11: =IF($U11="","",INDEX(ANA_Owner,$U11)&"") -> Funzione Sicurezza delle Informazioni | K11: =IF($U11="","",B11&" "&IF(ISNUMBER(F11),IF(F11>0,"▲",IF(F11<0,"▼","●")),"○")&" "&LEFT(C11,34)&IF(LEN(C11)>34,"…","")) -> NFR-06 ● Esfiltrazione di dati tramite stru… | T11: =IF(ISNUMBER(INDEX(posScore,7)),INDEX(posScore,7)-7/100000,"") -> 3.74993 | U11: =IFERROR(MATCH(_xlfn.AGGREGATE(14,6,$T$5:$T$24,7),$T$5:$T$24,0),"") -> 6 | V11: =IF($U11="",NA(),IF(LEFT(H11,9)="AGIRE ORA",D11,0)) -> 0 | W11: =IF($U11="",NA(),IF(LEFT(H11,11)="Agire entro",D11,0)) -> 3 | X11: =IF($U11="",NA(),IF(OR(LEFT(H11,9)="AGIRE ORA",LEFT(H11,11)="Agire entro"),0,D11)) -> 0 | Y11: =IF($U11="",NA(),INDEX(Radar_Mosca!$I$5:$I$24,$U11)) -> 0.25 | Z11: =IF($U11="",NA(),INDEX(Radar_Mosca!$J$5:$J$24,$U11)) -> 1 | AA11: =IF($U11="",NA(),INDEX(Radar_Mosca!$H$5:$H$24,$U11)) -> 1.5 | AB11: =IF(LEFT(H11,9)="AGIRE ORA",B11,"") | AD11: =IF(ISNUMBER(I11),I11+7/100000,"") -> 0.25007 | AE11: =IFERROR(MATCH(_xlfn.AGGREGATE(15,6,$AD$5:$AD$24,7),$AD$5:$AD$24,0),"") -> 10 | AF11: =IF($AE11="","",INDEX($B$5:$B$24,$AE11)&" ("&IF(INDEX($I$5:$I$24,$AE11)<0,"−","+")&FIXED(ABS(INDEX($I$5:$I$24,$AE11)),2)&")") -> NFR-04 (+0,75) | AG11: =IF($AE11="",NA(),INDEX($Y$5:$Y$24,$AE11)) -> 0.25 | AH11: =IF($AE11="",NA(),IF(INDEX($Y$5:$Y$24,$AE11)+INDEX($Z$5:$Z$24,$AE11)>INDEX($AA$5:$AA$24,$AE11),NA(),INDEX($Z$5:$Z$24,$AE11))) -> 0.5 | AI11: =IF($AE11="",NA(),IF(INDEX($Y$5:$Y$24,$AE11)+INDEX($Z$5:$Z$24,$AE11)>INDEX($AA$5:$AA$24,$AE11),INDEX($Z$5:$Z$24,$AE11),NA())) -> #N/A | AJ11: =IF($AE11="",NA(),INDEX($AA$5:$AA$24,$AE11)) -> 1.5
A12: =IF($U12="","",8) -> 8 | B12: =IF($U12="","",INDEX(posID,$U12)) -> NFR-10 | C12: =IF($U12="","",INDEX(posNome,$U12)) -> Informazioni errate ai clienti da assistenti di AI generativa | D12: =IF($U12="","",INDEX(posScore,$U12)) -> 3 | E12: =IF($U12="","",IFERROR(INDEX(posScorePrec,$U12),"—")) -> 3 | F12: =IF(AND(ISNUMBER(D12),ISNUMBER(E12)),D12-E12,"") -> 0 | G12: =IF($U12="","",IFERROR(INDEX(RR_Esito,MATCH(cicloCorrente&"|"&B12,RR_Chiave,0))&"","")) -> Confermato | H12: =IF($U12="","",INDEX(Radar_Mosca!$L$5:$L$24,$U12)) -> Margine 1 anno | I12: =IF($U12="","",IFERROR(INDEX(Radar_Mosca!$K$5:$K$24,$U12),"")) -> 1 | J12: =IF($U12="","",INDEX(ANA_Owner,$U12)&"") -> Funzione Customer Experience | K12: =IF($U12="","",B12&" "&IF(ISNUMBER(F12),IF(F12>0,"▲",IF(F12<0,"▼","●")),"○")&" "&LEFT(C12,34)&IF(LEN(C12)>34,"…","")) -> NFR-10 ● Informazioni errate ai clienti da … | T12: =IF(ISNUMBER(INDEX(posScore,8)),INDEX(posScore,8)-8/100000,"") -> 2.74992 | U12: =IFERROR(MATCH(_xlfn.AGGREGATE(14,6,$T$5:$T$24,8),$T$5:$T$24,0),"") -> 10 | V12: =IF($U12="",NA(),IF(LEFT(H12,9)="AGIRE ORA",D12,0)) -> 0 | W12: =IF($U12="",NA(),IF(LEFT(H12,11)="Agire entro",D12,0)) -> 0 | X12: =IF($U12="",NA(),IF(OR(LEFT(H12,9)="AGIRE ORA",LEFT(H12,11)="Agire entro"),0,D12)) -> 3 | Y12: =IF($U12="",NA(),INDEX(Radar_Mosca!$I$5:$I$24,$U12)) -> 0.25 | Z12: =IF($U12="",NA(),INDEX(Radar_Mosca!$J$5:$J$24,$U12)) -> 0.25 | AA12: =IF($U12="",NA(),INDEX(Radar_Mosca!$H$5:$H$24,$U12)) -> 1.5 | AB12: =IF(LEFT(H12,9)="AGIRE ORA",B12,"") | AD12: =IF(ISNUMBER(I12),I12+8/100000,"") -> 1.00008 | AE12: =IFERROR(MATCH(_xlfn.AGGREGATE(15,6,$AD$5:$AD$24,8),$AD$5:$AD$24,0),"") -> 4 | AF12: =IF($AE12="","",INDEX($B$5:$B$24,$AE12)&" ("&IF(INDEX($I$5:$I$24,$AE12)<0,"−","+")&FIXED(ABS(INDEX($I$5:$I$24,$AE12)),2)&")") -> NFR-02 (+1,00) | AG12: =IF($AE12="",NA(),INDEX($Y$5:$Y$24,$AE12)) -> 0.25 | AH12: =IF($AE12="",NA(),IF(INDEX($Y$5:$Y$24,$AE12)+INDEX($Z$5:$Z$24,$AE12)>INDEX($AA$5:$AA$24,$AE12),NA(),INDEX($Z$5:$Z$24,$AE12))) -> 0.25 | AI12: =IF($AE12="",NA(),IF(INDEX($Y$5:$Y$24,$AE12)+INDEX($Z$5:$Z$24,$AE12)>INDEX($AA$5:$AA$24,$AE12),INDEX($Z$5:$Z$24,$AE12),NA())) -> #N/A | AJ12: =IF($AE12="",NA(),INDEX($AA$5:$AA$24,$AE12)) -> 1.5
A13: =IF($U13="","",9) -> 9 | B13: =IF($U13="","",INDEX(posID,$U13)) -> NFR-09 | C13: =IF($U13="","",INDEX(posNome,$U13)) -> Violazione di sanzioni internazionali tramite triangolazioni | D13: =IF($U13="","",INDEX(posScore,$U13)) -> 2.9 | E13: =IF($U13="","",IFERROR(INDEX(posScorePrec,$U13),"—")) -> 2.9 | F13: =IF(AND(ISNUMBER(D13),ISNUMBER(E13)),D13-E13,"") -> 0 | G13: =IF($U13="","",IFERROR(INDEX(RR_Esito,MATCH(cicloCorrente&"|"&B13,RR_Chiave,0))&"","")) -> Confermato | H13: =IF($U13="","",INDEX(Radar_Mosca!$L$5:$L$24,$U13)) -> Margine 1,3 anni | I13: =IF($U13="","",IFERROR(INDEX(Radar_Mosca!$K$5:$K$24,$U13),"")) -> 1.25 | J13: =IF($U13="","",INDEX(ANA_Owner,$U13)&"") -> Funzione Compliance | K13: =IF($U13="","",B13&" "&IF(ISNUMBER(F13),IF(F13>0,"▲",IF(F13<0,"▼","●")),"○")&" "&LEFT(C13,34)&IF(LEN(C13)>34,"…","")) -> NFR-09 ● Violazione di sanzioni internazion… | T13: =IF(ISNUMBER(INDEX(posScore,9)),INDEX(posScore,9)-9/100000,"") -> 2.89991 | U13: =IFERROR(MATCH(_xlfn.AGGREGATE(14,6,$T$5:$T$24,9),$T$5:$T$24,0),"") -> 9 | V13: =IF($U13="",NA(),IF(LEFT(H13,9)="AGIRE ORA",D13,0)) -> 0 | W13: =IF($U13="",NA(),IF(LEFT(H13,11)="Agire entro",D13,0)) -> 0 | X13: =IF($U13="",NA(),IF(OR(LEFT(H13,9)="AGIRE ORA",LEFT(H13,11)="Agire entro"),0,D13)) -> 2.9 | Y13: =IF($U13="",NA(),INDEX(Radar_Mosca!$I$5:$I$24,$U13)) -> 0.25 | Z13: =IF($U13="",NA(),INDEX(Radar_Mosca!$J$5:$J$24,$U13)) -> 1 | AA13: =IF($U13="",NA(),INDEX(Radar_Mosca!$H$5:$H$24,$U13)) -> 2.5 | AB13: =IF(LEFT(H13,9)="AGIRE ORA",B13,"") | AD13: =IF(ISNUMBER(I13),I13+9/100000,"") -> 1.25009 | AE13: =IFERROR(MATCH(_xlfn.AGGREGATE(15,6,$AD$5:$AD$24,9),$AD$5:$AD$24,0),"") -> 6 | AF13: =IF($AE13="","",INDEX($B$5:$B$24,$AE13)&" ("&IF(INDEX($I$5:$I$24,$AE13)<0,"−","+")&FIXED(ABS(INDEX($I$5:$I$24,$AE13)),2)&")") -> NFR-05 (+1,00) | AG13: =IF($AE13="",NA(),INDEX($Y$5:$Y$24,$AE13)) -> 0.25 | AH13: =IF($AE13="",NA(),IF(INDEX($Y$5:$Y$24,$AE13)+INDEX($Z$5:$Z$24,$AE13)>INDEX($AA$5:$AA$24,$AE13),NA(),INDEX($Z$5:$Z$24,$AE13))) -> 0.25 | AI13: =IF($AE13="",NA(),IF(INDEX($Y$5:$Y$24,$AE13)+INDEX($Z$5:$Z$24,$AE13)>INDEX($AA$5:$AA$24,$AE13),INDEX($Z$5:$Z$24,$AE13),NA())) -> #N/A | AJ13: =IF($AE13="",NA(),INDEX($AA$5:$AA$24,$AE13)) -> 1.5
A14: =IF($U14="","",10) -> 10 | B14: =IF($U14="","",INDEX(posID,$U14)) -> NFR-04 | C14: =IF($U14="","",INDEX(posNome,$U14)) -> Eventi climatici estremi su sedi e data center | D14: =IF($U14="","",INDEX(posScore,$U14)) -> 2.8 | E14: =IF($U14="","",IFERROR(INDEX(posScorePrec,$U14),"—")) -> 2.8 | F14: =IF(AND(ISNUMBER(D14),ISNUMBER(E14)),D14-E14,"") -> 0 | G14: =IF($U14="","",IFERROR(INDEX(RR_Esito,MATCH(cicloCorrente&"|"&B14,RR_Chiave,0))&"","")) -> Confermato | H14: =IF($U14="","",INDEX(Radar_Mosca!$L$5:$L$24,$U14)) -> Agire entro l'anno | I14: =IF($U14="","",IFERROR(INDEX(Radar_Mosca!$K$5:$K$24,$U14),"")) -> 0.75 | J14: =IF($U14="","",INDEX(ANA_Owner,$U14)&"") -> Funzione Business Continuity | K14: =IF($U14="","",B14&" "&IF(ISNUMBER(F14),IF(F14>0,"▲",IF(F14<0,"▼","●")),"○")&" "&LEFT(C14,34)&IF(LEN(C14)>34,"…","")) -> NFR-04 ● Eventi climatici estremi su sedi e… | T14: =IF(ISNUMBER(INDEX(posScore,10)),INDEX(posScore,10)-10/100000,"") -> 2.9999 | U14: =IFERROR(MATCH(_xlfn.AGGREGATE(14,6,$T$5:$T$24,10),$T$5:$T$24,0),"") -> 4 | V14: =IF($U14="",NA(),IF(LEFT(H14,9)="AGIRE ORA",D14,0)) -> 0 | W14: =IF($U14="",NA(),IF(LEFT(H14,11)="Agire entro",D14,0)) -> 2.8 | X14: =IF($U14="",NA(),IF(OR(LEFT(H14,9)="AGIRE ORA",LEFT(H14,11)="Agire entro"),0,D14)) -> 0 | Y14: =IF($U14="",NA(),INDEX(Radar_Mosca!$I$5:$I$24,$U14)) -> 0.25 | Z14: =IF($U14="",NA(),INDEX(Radar_Mosca!$J$5:$J$24,$U14)) -> 0.5 | AA14: =IF($U14="",NA(),INDEX(Radar_Mosca!$H$5:$H$24,$U14)) -> 1.5 | AB14: =IF(LEFT(H14,9)="AGIRE ORA",B14,"") | AD14: =IF(ISNUMBER(I14),I14+10/100000,"") -> 0.7501 | AE14: =IFERROR(MATCH(_xlfn.AGGREGATE(15,6,$AD$5:$AD$24,10),$AD$5:$AD$24,0),"") -> 8 | AF14: =IF($AE14="","",INDEX($B$5:$B$24,$AE14)&" ("&IF(INDEX($I$5:$I$24,$AE14)<0,"−","+")&FIXED(ABS(INDEX($I$5:$I$24,$AE14)),2)&")") -> NFR-10 (+1,00) | AG14: =IF($AE14="",NA(),INDEX($Y$5:$Y$24,$AE14)) -> 0.25 | AH14: =IF($AE14="",NA(),IF(INDEX($Y$5:$Y$24,$AE14)+INDEX($Z$5:$Z$24,$AE14)>INDEX($AA$5:$AA$24,$AE14),NA(),INDEX($Z$5:$Z$24,$AE14))) -> 0.25 | AI14: =IF($AE14="",NA(),IF(INDEX($Y$5:$Y$24,$AE14)+INDEX($Z$5:$Z$24,$AE14)>INDEX($AA$5:$AA$24,$AE14),INDEX($Z$5:$Z$24,$AE14),NA())) -> #N/A | AJ14: =IF($AE14="",NA(),INDEX($AA$5:$AA$24,$AE14)) -> 1.5
A15: =IF($U15="","",11) -> 11 | B15: =IF($U15="","",INDEX(posID,$U15)) -> NFR-11 | C15: =IF($U15="","",INDEX(posNome,$U15)) -> Fine del supporto dei sistemi di pagamento legacy | D15: =IF($U15="","",INDEX(posScore,$U15)) -> 2.8 | E15: =IF($U15="","",IFERROR(INDEX(posScorePrec,$U15),"—")) -> 2.8 | F15: =IF(AND(ISNUMBER(D15),ISNUMBER(E15)),D15-E15,"") -> 0 | G15: =IF($U15="","",IFERROR(INDEX(RR_Esito,MATCH(cicloCorrente&"|"&B15,RR_Chiave,0))&"","")) -> Confermato | H15: =IF($U15="","",INDEX(Radar_Mosca!$L$5:$L$24,$U15)) -> AGIRE ORA: X+Y > Z | I15: =IF($U15="","",IFERROR(INDEX(Radar_Mosca!$K$5:$K$24,$U15),"")) -> -1.75 | J15: =IF($U15="","",INDEX(ANA_Owner,$U15)&"") -> Funzione IT Operations | K15: =IF($U15="","",B15&" "&IF(ISNUMBER(F15),IF(F15>0,"▲",IF(F15<0,"▼","●")),"○")&" "&LEFT(C15,34)&IF(LEN(C15)>34,"…","")) -> NFR-11 ● Fine del supporto dei sistemi di p… | T15: =IF(ISNUMBER(INDEX(posScore,11)),INDEX(posScore,11)-11/100000,"") -> 2.79989 | U15: =IFERROR(MATCH(_xlfn.AGGREGATE(14,6,$T$5:$T$24,11),$T$5:$T$24,0),"") -> 11 | V15: =IF($U15="",NA(),IF(LEFT(H15,9)="AGIRE ORA",D15,0)) -> 2.8 | W15: =IF($U15="",NA(),IF(LEFT(H15,11)="Agire entro",D15,0)) -> 0 | X15: =IF($U15="",NA(),IF(OR(LEFT(H15,9)="AGIRE ORA",LEFT(H15,11)="Agire entro"),0,D15)) -> 0 | Y15: =IF($U15="",NA(),INDEX(Radar_Mosca!$I$5:$I$24,$U15)) -> 0.25 | Z15: =IF($U15="",NA(),INDEX(Radar_Mosca!$J$5:$J$24,$U15)) -> 3 | AA15: =IF($U15="",NA(),INDEX(Radar_Mosca!$H$5:$H$24,$U15)) -> 1.5 | AB15: =IF(LEFT(H15,9)="AGIRE ORA",B15,"") -> NFR-11 | AD15: =IF(ISNUMBER(I15),I15+11/100000,"") -> -1.74989 | AE15: =IFERROR(MATCH(_xlfn.AGGREGATE(15,6,$AD$5:$AD$24,11),$AD$5:$AD$24,0),"") -> 13 | AF15: =IF($AE15="","",INDEX($B$5:$B$24,$AE15)&" ("&IF(INDEX($I$5:$I$24,$AE15)<0,"−","+")&FIXED(ABS(INDEX($I$5:$I$24,$AE15)),2)&")") -> NFR-08 (+1,00) | AG15: =IF($AE15="",NA(),INDEX($Y$5:$Y$24,$AE15)) -> 0.25 | AH15: =IF($AE15="",NA(),IF(INDEX($Y$5:$Y$24,$AE15)+INDEX($Z$5:$Z$24,$AE15)>INDEX($AA$5:$AA$24,$AE15),NA(),INDEX($Z$5:$Z$24,$AE15))) -> 0.25 | AI15: =IF($AE15="",NA(),IF(INDEX($Y$5:$Y$24,$AE15)+INDEX($Z$5:$Z$24,$AE15)>INDEX($AA$5:$AA$24,$AE15),INDEX($Z$5:$Z$24,$AE15),NA())) -> #N/A | AJ15: =IF($AE15="",NA(),INDEX($AA$5:$AA$24,$AE15)) -> 1.5
A16: =IF($U16="","",12) -> 12 | B16: =IF($U16="","",INDEX(posID,$U16)) -> NFR-16 | C16: =IF($U16="","",INDEX(posNome,$U16)) -> Vertenze e carenza di tecnici nei ruoli IT critici | D16: =IF($U16="","",INDEX(posScore,$U16)) -> 2.8 | E16: =IF($U16="","",IFERROR(INDEX(posScorePrec,$U16),"—")) -> 2.19 | F16: =IF(AND(ISNUMBER(D16),ISNUMBER(E16)),D16-E16,"") -> 0.61 | G16: =IF($U16="","",IFERROR(INDEX(RR_Esito,MATCH(cicloCorrente&"|"&B16,RR_Chiave,0))&"","")) -> Variato | H16: =IF($U16="","",INDEX(Radar_Mosca!$L$5:$L$24,$U16)) -> Margine 1,8 anni | I16: =IF($U16="","",IFERROR(INDEX(Radar_Mosca!$K$5:$K$24,$U16),"")) -> 1.75 | J16: =IF($U16="","",INDEX(ANA_Owner,$U16)&"") -> Da assegnare | K16: =IF($U16="","",B16&" "&IF(ISNUMBER(F16),IF(F16>0,"▲",IF(F16<0,"▼","●")),"○")&" "&LEFT(C16,34)&IF(LEN(C16)>34,"…","")) -> NFR-16 ▲ Vertenze e carenza di tecnici nei … | T16: =IF(ISNUMBER(INDEX(posScore,12)),INDEX(posScore,12)-12/100000,"") -> 3.64988 | U16: =IFERROR(MATCH(_xlfn.AGGREGATE(14,6,$T$5:$T$24,12),$T$5:$T$24,0),"") -> 13 | V16: =IF($U16="",NA(),IF(LEFT(H16,9)="AGIRE ORA",D16,0)) -> 0 | W16: =IF($U16="",NA(),IF(LEFT(H16,11)="Agire entro",D16,0)) -> 0 | X16: =IF($U16="",NA(),IF(OR(LEFT(H16,9)="AGIRE ORA",LEFT(H16,11)="Agire entro"),0,D16)) -> 2.8 | Y16: =IF($U16="",NA(),INDEX(Radar_Mosca!$I$5:$I$24,$U16)) -> 0.25 | Z16: =IF($U16="",NA(),INDEX(Radar_Mosca!$J$5:$J$24,$U16)) -> 0.5 | AA16: =IF($U16="",NA(),INDEX(Radar_Mosca!$H$5:$H$24,$U16)) -> 2.5 | AB16: =IF(LEFT(H16,9)="AGIRE ORA",B16,"") | AD16: =IF(ISNUMBER(I16),I16+12/100000,"") -> 1.75012 | AE16: =IFERROR(MATCH(_xlfn.AGGREGATE(15,6,$AD$5:$AD$24,12),$AD$5:$AD$24,0),"") -> 9 | AF16: =IF($AE16="","",INDEX($B$5:$B$24,$AE16)&" ("&IF(INDEX($I$5:$I$24,$AE16)<0,"−","+")&FIXED(ABS(INDEX($I$5:$I$24,$AE16)),2)&")") -> NFR-09 (+1,25) | AG16: =IF($AE16="",NA(),INDEX($Y$5:$Y$24,$AE16)) -> 0.25 | AH16: =IF($AE16="",NA(),IF(INDEX($Y$5:$Y$24,$AE16)+INDEX($Z$5:$Z$24,$AE16)>INDEX($AA$5:$AA$24,$AE16),NA(),INDEX($Z$5:$Z$24,$AE16))) -> 1 | AI16: =IF($AE16="",NA(),IF(INDEX($Y$5:$Y$24,$AE16)+INDEX($Z$5:$Z$24,$AE16)>INDEX($AA$5:$AA$24,$AE16),INDEX($Z$5:$Z$24,$AE16),NA())) -> #N/A | AJ16: =IF($AE16="",NA(),INDEX($AA$5:$AA$24,$AE16)) -> 2.5
A17: =IF($U17="","",13) -> 13 | B17: =IF($U17="","",INDEX(posID,$U17)) -> NFR-08 | C17: =IF($U17="","",INDEX(posNome,$U17)) -> Accessi impropri di dipendenti ai dati dei clienti | D17: =IF($U17="","",INDEX(posScore,$U17)) -> 2.75 | E17: =IF($U17="","",IFERROR(INDEX(posScorePrec,$U17),"—")) -> 2.75 | F17: =IF(AND(ISNUMBER(D17),ISNUMBER(E17)),D17-E17,"") -> 0 | G17: =IF($U17="","",IFERROR(INDEX(RR_Esito,MATCH(cicloCorrente&"|"&B17,RR_Chiave,0))&"","")) -> Confermato | H17: =IF($U17="","",INDEX(Radar_Mosca!$L$5:$L$24,$U17)) -> Margine 1 anno | I17: =IF($U17="","",IFERROR(INDEX(Radar_Mosca!$K$5:$K$24,$U17),"")) -> 1 | J17: =IF($U17="","",INDEX(ANA_Owner,$U17)&"") -> Funzione Sicurezza delle Informazioni | K17: =IF($U17="","",B17&" "&IF(ISNUMBER(F17),IF(F17>0,"▲",IF(F17<0,"▼","●")),"○")&" "&LEFT(C17,34)&IF(LEN(C17)>34,"…","")) -> NFR-08 ● Accessi impropri di dipendenti ai … | T17: =IF(ISNUMBER(INDEX(posScore,13)),INDEX(posScore,13)-13/100000,"") -> 2.79987 | U17: =IFERROR(MATCH(_xlfn.AGGREGATE(14,6,$T$5:$T$24,13),$T$5:$T$24,0),"") -> 8 | V17: =IF($U17="",NA(),IF(LEFT(H17,9)="AGIRE ORA",D17,0)) -> 0 | W17: =IF($U17="",NA(),IF(LEFT(H17,11)="Agire entro",D17,0)) -> 0 | X17: =IF($U17="",NA(),IF(OR(LEFT(H17,9)="AGIRE ORA",LEFT(H17,11)="Agire entro"),0,D17)) -> 2.75 | Y17: =IF($U17="",NA(),INDEX(Radar_Mosca!$I$5:$I$24,$U17)) -> 0.25 | Z17: =IF($U17="",NA(),INDEX(Radar_Mosca!$J$5:$J$24,$U17)) -> 0.25 | AA17: =IF($U17="",NA(),INDEX(Radar_Mosca!$H$5:$H$24,$U17)) -> 1.5 | AB17: =IF(LEFT(H17,9)="AGIRE ORA",B17,"") | AD17: =IF(ISNUMBER(I17),I17+13/100000,"") -> 1.00013 | AE17: =IFERROR(MATCH(_xlfn.AGGREGATE(15,6,$AD$5:$AD$24,13),$AD$5:$AD$24,0),"") -> 12 | AF17: =IF($AE17="","",INDEX($B$5:$B$24,$AE17)&" ("&IF(INDEX($I$5:$I$24,$AE17)<0,"−","+")&FIXED(ABS(INDEX($I$5:$I$24,$AE17)),2)&")") -> NFR-16 (+1,75) | AG17: =IF($AE17="",NA(),INDEX($Y$5:$Y$24,$AE17)) -> 0.25 | AH17: =IF($AE17="",NA(),IF(INDEX($Y$5:$Y$24,$AE17)+INDEX($Z$5:$Z$24,$AE17)>INDEX($AA$5:$AA$24,$AE17),NA(),INDEX($Z$5:$Z$24,$AE17))) -> 0.5 | AI17: =IF($AE17="",NA(),IF(INDEX($Y$5:$Y$24,$AE17)+INDEX($Z$5:$Z$24,$AE17)>INDEX($AA$5:$AA$24,$AE17),INDEX($Z$5:$Z$24,$AE17),NA())) -> #N/A | AJ17: =IF($AE17="",NA(),INDEX($AA$5:$AA$24,$AE17)) -> 2.5
A18: =IF($U18="","",14) | B18: =IF($U18="","",INDEX(posID,$U18)) | C18: =IF($U18="","",INDEX(posNome,$U18)) | D18: =IF($U18="","",INDEX(posScore,$U18)) | E18: =IF($U18="","",IFERROR(INDEX(posScorePrec,$U18),"—")) | F18: =IF(AND(ISNUMBER(D18),ISNUMBER(E18)),D18-E18,"") | G18: =IF($U18="","",IFERROR(INDEX(RR_Esito,MATCH(cicloCorrente&"|"&B18,RR_Chiave,0))&"","")) | H18: =IF($U18="","",INDEX(Radar_Mosca!$L$5:$L$24,$U18)) | I18: =IF($U18="","",IFERROR(INDEX(Radar_Mosca!$K$5:$K$24,$U18),"")) | J18: =IF($U18="","",INDEX(ANA_Owner,$U18)&"") | K18: =IF($U18="","",B18&" "&IF(ISNUMBER(F18),IF(F18>0,"▲",IF(F18<0,"▼","●")),"○")&" "&LEFT(C18,34)&IF(LEN(C18)>34,"…","")) | T18: =IF(ISNUMBER(INDEX(posScore,14)),INDEX(posScore,14)-14/100000,"") | U18: =IFERROR(MATCH(_xlfn.AGGREGATE(14,6,$T$5:$T$24,14),$T$5:$T$24,0),"") | V18: =IF($U18="",NA(),IF(LEFT(H18,9)="AGIRE ORA",D18,0)) -> #N/A | W18: =IF($U18="",NA(),IF(LEFT(H18,11)="Agire entro",D18,0)) -> #N/A | X18: =IF($U18="",NA(),IF(OR(LEFT(H18,9)="AGIRE ORA",LEFT(H18,11)="Agire entro"),0,D18)) -> #N/A | Y18: =IF($U18="",NA(),INDEX(Radar_Mosca!$I$5:$I$24,$U18)) -> #N/A | Z18: =IF($U18="",NA(),INDEX(Radar_Mosca!$J$5:$J$24,$U18)) -> #N/A | AA18: =IF($U18="",NA(),INDEX(Radar_Mosca!$H$5:$H$24,$U18)) -> #N/A | AB18: =IF(LEFT(H18,9)="AGIRE ORA",B18,"") | AD18: =IF(ISNUMBER(I18),I18+14/100000,"") | AE18: =IFERROR(MATCH(_xlfn.AGGREGATE(15,6,$AD$5:$AD$24,14),$AD$5:$AD$24,0),"") | AF18: =IF($AE18="","",INDEX($B$5:$B$24,$AE18)&" ("&IF(INDEX($I$5:$I$24,$AE18)<0,"−","+")&FIXED(ABS(INDEX($I$5:$I$24,$AE18)),2)&")") | AG18: =IF($AE18="",NA(),INDEX($Y$5:$Y$24,$AE18)) -> #N/A | AH18: =IF($AE18="",NA(),IF(INDEX($Y$5:$Y$24,$AE18)+INDEX($Z$5:$Z$24,$AE18)>INDEX($AA$5:$AA$24,$AE18),NA(),INDEX($Z$5:$Z$24,$AE18))) -> #N/A | AI18: =IF($AE18="",NA(),IF(INDEX($Y$5:$Y$24,$AE18)+INDEX($Z$5:$Z$24,$AE18)>INDEX($AA$5:$AA$24,$AE18),INDEX($Z$5:$Z$24,$AE18),NA())) -> #N/A | AJ18: =IF($AE18="",NA(),INDEX($AA$5:$AA$24,$AE18)) -> #N/A
A19: =IF($U19="","",15) | B19: =IF($U19="","",INDEX(posID,$U19)) | C19: =IF($U19="","",INDEX(posNome,$U19)) | D19: =IF($U19="","",INDEX(posScore,$U19)) | E19: =IF($U19="","",IFERROR(INDEX(posScorePrec,$U19),"—")) | F19: =IF(AND(ISNUMBER(D19),ISNUMBER(E19)),D19-E19,"") | G19: =IF($U19="","",IFERROR(INDEX(RR_Esito,MATCH(cicloCorrente&"|"&B19,RR_Chiave,0))&"","")) | H19: =IF($U19="","",INDEX(Radar_Mosca!$L$5:$L$24,$U19)) | I19: =IF($U19="","",IFERROR(INDEX(Radar_Mosca!$K$5:$K$24,$U19),"")) | J19: =IF($U19="","",INDEX(ANA_Owner,$U19)&"") | K19: =IF($U19="","",B19&" "&IF(ISNUMBER(F19),IF(F19>0,"▲",IF(F19<0,"▼","●")),"○")&" "&LEFT(C19,34)&IF(LEN(C19)>34,"…","")) | T19: =IF(ISNUMBER(INDEX(posScore,15)),INDEX(posScore,15)-15/100000,"") | U19: =IFERROR(MATCH(_xlfn.AGGREGATE(14,6,$T$5:$T$24,15),$T$5:$T$24,0),"") | V19: =IF($U19="",NA(),IF(LEFT(H19,9)="AGIRE ORA",D19,0)) -> #N/A | W19: =IF($U19="",NA(),IF(LEFT(H19,11)="Agire entro",D19,0)) -> #N/A | X19: =IF($U19="",NA(),IF(OR(LEFT(H19,9)="AGIRE ORA",LEFT(H19,11)="Agire entro"),0,D19)) -> #N/A | Y19: =IF($U19="",NA(),INDEX(Radar_Mosca!$I$5:$I$24,$U19)) -> #N/A | Z19: =IF($U19="",NA(),INDEX(Radar_Mosca!$J$5:$J$24,$U19)) -> #N/A | AA19: =IF($U19="",NA(),INDEX(Radar_Mosca!$H$5:$H$24,$U19)) -> #N/A | AB19: =IF(LEFT(H19,9)="AGIRE ORA",B19,"") | AD19: =IF(ISNUMBER(I19),I19+15/100000,"") | AE19: =IFERROR(MATCH(_xlfn.AGGREGATE(15,6,$AD$5:$AD$24,15),$AD$5:$AD$24,0),"") | AF19: =IF($AE19="","",INDEX($B$5:$B$24,$AE19)&" ("&IF(INDEX($I$5:$I$24,$AE19)<0,"−","+")&FIXED(ABS(INDEX($I$5:$I$24,$AE19)),2)&")") | AG19: =IF($AE19="",NA(),INDEX($Y$5:$Y$24,$AE19)) -> #N/A | AH19: =IF($AE19="",NA(),IF(INDEX($Y$5:$Y$24,$AE19)+INDEX($Z$5:$Z$24,$AE19)>INDEX($AA$5:$AA$24,$AE19),NA(),INDEX($Z$5:$Z$24,$AE19))) -> #N/A | AI19: =IF($AE19="",NA(),IF(INDEX($Y$5:$Y$24,$AE19)+INDEX($Z$5:$Z$24,$AE19)>INDEX($AA$5:$AA$24,$AE19),INDEX($Z$5:$Z$24,$AE19),NA())) -> #N/A | AJ19: =IF($AE19="",NA(),INDEX($AA$5:$AA$24,$AE19)) -> #N/A
