Workbook
Name ANA_Anni_Adeguamento: Parametri!$M$4:$M$18
Name ANA_Attenzione_Supervisore: Parametri!$N$4:$N$18
Name ANA_Driver: Parametri!$K$4:$K$18
Name ANA_Event_Type: Parametri!$J$4:$J$18
Name ANA_ID: Parametri!$H$4:$H$18
Name ANA_Nome: Parametri!$I$4:$I$18
Name ANA_Owner: Parametri!$L$4:$L$18
Name anagrafica: Parametri!$H$4:$N$18
Name anniProssimita: Parametri!$B$51:$B$55
Name AZ_Ciclo: Azioni!$A$6:$A$20015
Name AZ_Data_Decisione: Azioni!$K$6:$K$20015
Name AZ_Decisa_Da: Azioni!$L$6:$L$20015
Name AZ_Descrizione: Azioni!$D$6:$D$20015
Name AZ_Dimensione: Azioni!$F$6:$F$20015
Name AZ_ID_Azione: Azioni!$C$6:$C$20015
Name AZ_ID_Rischio: Azioni!$B$6:$B$20015
Name AZ_Mesi_Orizzonte: Azioni!$H$6:$H$20015
Name AZ_Orizzonte: Azioni!$G$6:$G$20015
Name AZ_Owner: Azioni!$E$6:$E$20015
Name AZ_Razionale: Azioni!$I$6:$I$20015
Name AZ_Stato: Azioni!$J$6:$J$20015
Name AZ_Validazione: Azioni!$M$6:$M$20015
Name capienzaElencoKRI: 150
Name capienzaKRICorrenti: 60
Name capienzaPianoAzioni: 150
Name cicliTrend: Parametri!$B$20:$B$27
Name cicloCorrente: Parametri!$B$15
Name cicloMeno2: Parametri!$B$17
Name cicloPrecedente: Parametri!$B$16
Name classificaAgire: OFFSET(Classifica!$V$5,0,0,MAX(1,COUNT(Classifica!$D$5:$D$19)),1)
Name classificaEntro: OFFSET(Classifica!$W$5,0,0,MAX(1,COUNT(Classifica!$D$5:$D$19)),1)
Name classificaEtichette: OFFSET(Classifica!$K$5,0,0,MAX(1,COUNT(Classifica!$D$5:$D$19)),1)
Name classificaID: OFFSET(Classifica!$B$5,0,0,MAX(1,COUNT(Classifica!$D$5:$D$19)),1)
Name classificaMargine: OFFSET(Classifica!$X$5,0,0,MAX(1,COUNT(Classifica!$D$5:$D$19)),1)
Name codiciL1: Parametri!$E$4:$E$10
Name coperturaAnagrafica: Registro!$D$5
Name coperturaValutati: Registro!$G$5
Name decisioniDaPrendere: Registro!$D$4
Name deltaEtichette: OFFSET(Delta!$AN$5,0,0,MAX(1,COUNT(Delta!$AK$5:$AK$19)),1)
Name deltaGiu: OFFSET(Delta!$AP$5,0,0,MAX(1,COUNT(Delta!$AK$5:$AK$19)),1)
Name deltaMotivi: Delta!$K$6:$Q$20
Name deltaSu: OFFSET(Delta!$AO$5,0,0,MAX(1,COUNT(Delta!$AK$5:$AK$19)),1)
Name deltaZero: OFFSET(Delta!$AQ$5,0,0,MAX(1,COUNT(Delta!$AK$5:$AK$19)),1)
Name elencoKRI: OFFSET(Indicatori!$AB$12,0,0,MAX(1,COUNTIF(Indicatori!$AB$12:$AB$161,"?*")),1)
Name etichettaCiclo: Parametri!$B$57
Name inizioFinestra4: Parametri!$B$31
Name KRI_Chiave: KRI!$R$6:$R$20037
Name KRI_Ciclo: KRI!$A$6:$A$20037
Name KRI_Ciclo_Aggiornamento: KRI!$P$6:$P$20037
Name KRI_Ciclo_Definizione: KRI!$O$6:$O$20037
Name KRI_Data_Rilevazione: KRI!$J$6:$J$20037
Name KRI_Fonte_Dati: KRI!$F$6:$F$20037
Name KRI_Fonte_Rilevazione: KRI!$K$6:$K$20037
Name KRI_ID_Rischio: KRI!$C$6:$C$20037
Name KRI_In_Vigore: KRI!$N$6:$N$20037
Name KRI_KRI_ID: KRI!$B$6:$B$20037
Name KRI_Nome: KRI!$D$6:$D$20037
Name KRI_Nota_Rilevazione: KRI!$L$6:$L$20037
Name KRI_Razionale: KRI!$Q$6:$Q$20037
Name KRI_Soglia_Allerta: KRI!$H$6:$H$20037

Sheet Guida
A1: ="Horizon Scan NFR — Guida: come si usa questo workbook · "&etichettaCiclo -> Horizon Scan NFR — Guida: come si usa questo workbook · Ciclo 2026Q3 · dati al 30/09/2026 · validato · Uso interno
A3: A COSA SERVE
A4: Horizon Scan NFR: registro dei rischi non finanziari emergenti della Banca. Ogni trimestre gli agenti valutano i rischi, lo script controlla e scrive qui, il validatore decide; i fogli da Quadro a Metodologia sono il report al comitato, le schede dei rischi un file a parte. Ogni foglio ha in testa (riga 2) chi lo aggiorna, cosa contiene e come si legge; il foglio Dizionario spiega ogni dato.
A6: CHI AGGIORNA COSA E QUANDO
A7: Foglio | B7: Settimanale · lunedi', A3 | C7: Trimestrale · A1, poi A5 | D7: Validatore · dopo il trimestre | E7: A che cosa serve
A8: REPORT AL COMITATO
A9: Quadro | C9: commento di A1, sintesi di A5, numeri | D9: stato della validazione; avviso rettifiche | E9: prima pagina: il quadro e il perche'
A10: Classifica | C10: score e urgenza | D10: valori validati | E10: rischi per score; lente di Mosca
A11: Radar_Mosca | C11: score, azioni (Y) | D11: anni di adeguamento, attenzione del supervisore | E11: quanto presto agire, quanto e' grande
A12: Matrice | C12: Probabilita e Severity | D12: valori validati | E12: gravita' dei rischi
A13: Delta | C13: confronto con il ciclo prima | E13: che cosa e' cambiato e perche'
A14: Metodologia | D14: pesi e parametri (Parametri) | E14: come si leggono i numeri
A15: LAVORO
A16: Registro | B16: segnali netti (colonna S) | C16: dimensioni, score, urgenza, KRI | D16: righe 4-5 | E16: il ciclo corrente, un rischio per riga
A17: Storico, Indicatori | C17: si aggiornano | E17: score negli ultimi cicli; KRI del ciclo e storia di uno
A18: Notizie | B18: si aggiorna | E18: pressione delle notizie, aree non presidiate
A19: Piano_azioni | C19: azioni proposte da A1 | D19: decisione; Stato In corso/Completata (foglio Azioni) | E19: tutte le azioni e la loro scadenza
A20: Validazione | B20: righe delle notizie | C20: righe di rischi, KRI, azioni | D20: DECISIONI, a mano | E20: unico foglio da compilare
A21: Parametri | B21: settimana corrente | C21: ciclo corrente; anagrafica H-K | D21: celle gialle | E21: pesi, soglie, urgenza, anagrafica
A22: Dizionario | E22: ogni dato: chi lo scrive, come si calcola
A23: DATI (solo lo script)
A24: RiskRegister | C24: valutazioni di A1 | D24: valori validati | E24: una riga per rischio per ciclo
A25: Azioni | C25: azioni proposte da A1 | D25: delibera; Stato In corso/Completata a mano | E25: una riga per azione
A26: KRI | C26: KRI e valori riletti da A1 | D26: rettifiche, KRI respinti | E26: storico, una riga per KRI per ciclo
A27: NewsLog | B27: notizie valutate da A3 | D27: rettifiche (facoltative) | E27: una riga per notizia
A28: Sintesi_Cicli | C28: commento di A1 e di A5 | E28: una riga per ciclo
A29: FILE A PARTE
A30: Schede_<ciclo>.xlsx | C30: testi di A6 dopo la validazione | D30: dati validati | E30: una scheda per rischio (comando schede)
A31: Giornaliero: la raccolta delle notizie riempie la cartella News_Inbox, non questo file. A4 (pareri su richiesta, in qualsiasi momento) non scrive qui: se un parere suggerisce di rivedere un rischio, la via e' il ciclo trimestrale successivo.
A33: QUANDO SI LANCIANO A5 E A6
A34: A5 (challenger): ogni trimestre, subito dopo A1 e prima del comando trimestrale, allegando SOLO l'output di A1 e Baseline_corrente.json. Senza l'esito di A5 lo script non scrive il ciclo. Di nuovo ogni volta che A1 viene rifatto: l'approvazione vale solo per l'output esaminato. Non si lancia per le settimane, per A4 ne' dopo la validazione.
A35: A6 (schede): dopo la validazione del trimestre. Il comando schede-input prepara i dati validati; A6 scrive i testi; il comando schede li controlla e produce Schede_<ciclo>.xlsx. Senza A6 il comando schede produce comunque le schede con i testi del registro.
A37: DOVE SI SCRIVE A MANO (solo qui)
A38: Validazione: le decisioni sulle proposte degli agenti (istruzioni e criteri in testa al foglio), poi il comando valida.
A39: Parametri, celle gialle: pesi, soglie, urgenza (decisione della funzione di rischio); nell'anagrafica Owner, anni di adeguamento e attenzione del supervisore (decisi dal validatore, restano da un ciclo all'altro).
A40: Azioni, colonna Stato: avanzamento di un'azione approvata (In corso, Completata); il Piano_azioni si aggiorna da solo.
A41: Indicatori, cella N4: il KRI di cui guardare la storia.
A42: Tutto il resto lo scrive lo script o e' una formula: non modificarlo.
A44: REGOLE
A45: 1. Score composito, urgenza e stato dei KRI li calcola il foglio. Nessun agente li fornisce.
... A55: Generato da 03_Excel/genera_dashboard.py (versione della struttura 2026-09-25c). Per rifarlo a mano: 03_Excel/costruzione_manuale_template.md.

Sheet Quadro
A1: ="Horizon Scan NFR — Quadro d'insieme · "&etichettaCiclo -> Horizon Scan NFR — Quadro d'insieme · Ciclo 2026Q3 · dati al 30/09/2026 · validato · Uso interno
A2: CICLO TRIMESTRALE — A1 valuta i rischi, A5 controlla la valutazione, il validatore la conferma o la rettifica. Come si legge: i cinque riquadri in alto dicono se il ciclo e' completo e validato; poi le priorita' per score, la gravita' (matrice) e l'urgenza (radar). A pagina 2 il commento di A1 (scritto prima della validazione: se dopo ci sono state rettifiche lo dice la riga "Dopo il commento" e valgono i numeri validati) e i rischi segnalati, con il perche' calcolato dal foglio. Metodo e scale: Metodologia; ogni dato: Dizionario.
BH3: Appoggio del grafico: non modificare | CM3: vigilanza | CN3: vigilanza | CO3: vigilanza | CP3: vigilanza | CQ3: vigilanza | CR3: vigilanza | CS3: vigilanza | CT3: vigilanza | CU3: vigilanza | CV3: vigilanza | CW3: vigilanza | CX3: vigilanza | CY3: vigilanza | CZ3: vigilanza
A4: Rischi valutati | D4: Da affrontare subito | G4: Variati · nuovi | J4: KRI in rosso | M4: Validazione | BY4: 1 | BZ4: 2 | CA4: 3 | CB4: 4 | CC4: 5 | CD4: 6 | CE4: 8 | CF4: 9 | CG4: 10 | CH4: 12 | CI4: 15 | CJ4: 16 | CK4: 20 | CL4: 25 | CM4: 1 | CN4: 2 | CO4: 3 | CP4: 4 | CQ4: 5 | CR4: 6 | CS4: 8 | CT4: 9 | CU4: 10 | CV4: 12 | CW4: 15 | CX4: 16 | CY4: 20 | CZ4: 25
A5: =coperturaValutati -> 12 | D5: =COUNTIF(Radar_Mosca!$L$5:$L$19,"AGIRE ORA*") -> 2 | G5: =COUNTIFS(RR_Ciclo,cicloCorrente,RR_Esito,"Variato")&" · "&COUNTIFS(RR_Ciclo,cicloCorrente,RR_Esito,"Nuovo") -> 3 · 0 | J5: =COUNTIFS(KRI_Ciclo,cicloCorrente,KRI_In_Vigore,"Sì",KRI_Stato,"Rosso") -> 0 | M5: =IF(decisioniDaPrendere>0,decisioniDaPrendere,"✓") -> ✓ | T5: =IF(LEFT(Radar_Mosca!$L$5,9)="AGIRE ORA",Radar_Mosca!$A$5,"") -> NFR-01 | BH5: =2*PI()*0/72 -> 0 | BI5: =2*SIN($BH5) -> 0 | BJ5: =2*COS($BH5) -> 2 | BK5: =3*SIN($BH5) -> 0 | BL5: =3*COS($BH5) -> 3 | BM5: =4*SIN($BH5) -> 0 | BN5: =4*COS($BH5) -> 4 | BO5: =5*SIN($BH5) -> 0 | BP5: =5*COS($BH5) -> 5 | BR5: 0 | BS5: 0 | BU5: L1-01 Frode interna | BV5: =6.95*SIN(2*PI()*(0+0.5)/ROWS(codiciL1)) -> 3.015492 | BW5: =6.95*COS(2*PI()*(0+0.5)/ROWS(codiciL1)) -> 6.2617336 | BY5: =IF(AND(ISNUMBER(Radar_Mosca!$F5),ISNUMBER(Radar_Mosca!$S5)),IF(AND(Radar_Mosca!$F5=BY$4,Radar_Mosca!$T5<>"Sì"),Radar_Mosca!$S5,NA()),NA()) -> #N/A | BZ5: =IF(AND(ISNUMBER(Radar_Mosca!$F5),ISNUMBER(Radar_Mosca!$S5)),IF(AND(Radar_Mosca!$F5=BZ$4,Radar_Mosca!$T5<>"Sì"),Radar_Mosca!$S5,NA()),NA()) -> #N/A | CA5: =IF(AND(ISNUMBER(Radar_Mosca!$F5),ISNUMBER(Radar_Mosca!$S5)),IF(AND(Radar_Mosca!$F5=CA$4,Radar_Mosca!$T5<>"Sì"),Radar_Mosca!$S5,NA()),NA()) -> #N/A | CB5: =IF(AND(ISNUMBER(Radar_Mosca!$F5),ISNUMBER(Radar_Mosca!$S5)),IF(AND(Radar_Mosca!$F5=CB$4,Radar_Mosca!$T5<>"Sì"),Radar_Mosca!$S5,NA()),NA()) -> #N/A | CC5: =IF(AND(ISNUMBER(Radar_Mosca!$F5),ISNUMBER(Radar_Mosca!$S5)),IF(AND(Radar_Mosca!$F5=CC$4,Radar_Mosca!$T5<>"Sì"),Radar_Mosca!$S5,NA()),NA()) -> #N/A | CD5: =IF(AND(ISNUMBER(Radar_Mosca!$F5),ISNUMBER(Radar_Mosca!$S5)),IF(AND(Radar_Mosca!$F5=CD$4,Radar_Mosca!$T5<>"Sì"),Radar_Mosca!$S5,NA()),NA()) -> #N/A | CE5: =IF(AND(ISNUMBER(Radar_Mosca!$F5),ISNUMBER(Radar_Mosca!$S5)),IF(AND(Radar_Mosca!$F5=CE$4,Radar_Mosca!$T5<>"Sì"),Radar_Mosca!$S5,NA()),NA()) -> #N/A | CF5: =IF(AND(ISNUMBER(Radar_Mosca!$F5),ISNUMBER(Radar_Mosca!$S5)),IF(AND(Radar_Mosca!$F5=CF$4,Radar_Mosca!$T5<>"Sì"),Radar_Mosca!$S5,NA()),NA()) -> #N/A | ... CL5: =IF(AND(ISNUMBER(Radar_Mosca!$F5),ISNUMBER(Radar_Mosca!$S5)),IF(AND(Radar_Mosca!$F5=CL$4,Radar_Mosca!$T5<>"Sì"),Radar_Mosca!$S5,NA()),NA()) -> #N/A | CM5: =IF(AND(ISNUMBER(Radar_Mosca!$F5),ISNUMBER(Radar_Mosca!$S5)),IF(AND(Radar_Mosca!$F5=CM$4,Radar_Mosca!$T5="Sì"),Radar_Mosca!$S5,NA()),NA()) -> #N/A | CN5: =IF(AND(ISNUMBER(Radar_Mosca!$F5),ISNUMBER(Radar_Mosca!$S5)),IF(AND(Radar_Mosca!$F5=CN$4,Radar_Mosca!$T5="Sì"),Radar_Mosca!$S5,NA()),NA()) -> #N/A | CO5: =IF(AND(ISNUMBER(Radar_Mosca!$F5),ISNUMBER(Radar_Mosca!$S5)),IF(AND(Radar_Mosca!$F5=CO$4,Radar_Mosca!$T5="Sì"),Radar_Mosca!$S5,NA()),NA()) -> #N/A | CP5: =IF(AND(ISNUMBER(Radar_Mosca!$F5),ISNUMBER(Radar_Mosca!$S5)),IF(AND(Radar_Mosca!$F5=CP$4,Radar_Mosca!$T5="Sì"),Radar_Mosca!$S5,NA()),NA()) -> #N/A | CQ5: =IF(AND(ISNUMBER(Radar_Mosca!$F5),ISNUMBER(Radar_Mosca!$S5)),IF(AND(Radar_Mosca!$F5=CQ$4,Radar_Mosca!$T5="Sì"),Radar_Mosca!$S5,NA()),NA()) -> #N/A | CR5: =IF(AND(ISNUMBER(Radar_Mosca!$F5),ISNUMBER(Radar_Mosca!$S5)),IF(AND(Radar_Mosca!$F5=CR$4,Radar_Mosca!$T5="Sì"),Radar_Mosca!$S5,NA()),NA()) -> #N/A | CS5: =IF(AND(ISNUMBER(Radar_Mosca!$F5),ISNUMBER(Radar_Mosca!$S5)),IF(AND(Radar_Mosca!$F5=CS$4,Radar_Mosca!$T5="Sì"),Radar_Mosca!$S5,NA()),NA()) -> #N/A | CT5: =IF(AND(ISNUMBER(Radar_Mosca!$F5),ISNUMBER(Radar_Mosca!$S5)),IF(AND(Radar_Mosca!$F5=CT$4,Radar_Mosca!$T5="Sì"),Radar_Mosca!$S5,NA()),NA()) -> #N/A | ... CZ5: =IF(AND(ISNUMBER(Radar_Mosca!$F5),ISNUMBER(Radar_Mosca!$S5)),IF(AND(Radar_Mosca!$F5=CZ$4,Radar_Mosca!$T5="Sì"),Radar_Mosca!$S5,NA()),NA()) -> #N/A | DA5: =IF(ISNUMBER(Radar_Mosca!$R5),Radar_Mosca!$R5,NA()) -> 1.7061238 | DB5: =IF(Radar_Mosca!$A5="","",MID(Radar_Mosca!$A5,5,3)) -> 01 | DC5: =IF(ISNUMBER(Radar_Mosca!$S5),Radar_Mosca!$S5,NA()) -> 0.38941163 | DD5: attenzione supervisore | DE5: -6.9 | DF5: -6.35
A6: ="su "&coperturaAnagrafica&" in anagrafica · "&IF(coperturaValutati=coperturaAnagrafica,"completo","INCOMPLETO") -> su 12 in anagrafica · completo | D6: =IF(D5=0,"nessun rischio con X + Y > Z","X + Y > Z: "&_xlfn.TEXTJOIN(", ",TRUE,$T$5:$T$19)) -> X + Y > Z: NFR-01, NFR-11 | G6: ="rispetto al "&cicloPrecedente -> rispetto al 2026Q2 | J6: ="su "&COUNTIFS(KRI_Ciclo,cicloCorrente,KRI_In_Vigore,"Sì")&" in vigore" -> su 36 in vigore | M6: =IF(decisioniDaPrendere>0,"decisioni da prendere: ciclo non validato","ciclo validato") -> ciclo validato | T6: =IF(LEFT(Radar_Mosca!$L$6,9)="AGIRE ORA",Radar_Mosca!$A$6,"") | BH6: =2*PI()*1/72 -> 0.087266463 | BI6: =2*SIN($BH6) -> 0.17431149 | BJ6: =2*COS($BH6) -> 1.9923894 | BK6: =3*SIN($BH6) -> 0.26146723 | BL6: =3*COS($BH6) -> 2.9885841 | BM6: =4*SIN($BH6) -> 0.34862297 | BN6: =4*COS($BH6) -> 3.9847788 | BO6: =5*SIN($BH6) -> 0.43577871 | BP6: =5*COS($BH6) -> 4.9809735 | BR6: =6.3*SIN(2*PI()*0/ROWS(codiciL1)) -> 0 | BS6: =6.3*COS(2*PI()*0/ROWS(codiciL1)) -> 6.3 | BU6: L1-02 Frode esterna | BV6: =6.95*SIN(2*PI()*(1+0.5)/ROWS(codiciL1)) -> 6.775749 | BW6: =6.95*COS(2*PI()*(1+0.5)/ROWS(codiciL1)) -> 1.5465205 | BY6: =IF(AND(ISNUMBER(Radar_Mosca!$F6),ISNUMBER(Radar_Mosca!$S6)),IF(AND(Radar_Mosca!$F6=BY$4,Radar_Mosca!$T6<>"Sì"),Radar_Mosca!$S6,NA()),NA()) -> #N/A | BZ6: =IF(AND(ISNUMBER(Radar_Mosca!$F6),ISNUMBER(Radar_Mosca!$S6)),IF(AND(Radar_Mosca!$F6=BZ$4,Radar_Mosca!$T6<>"Sì"),Radar_Mosca!$S6,NA()),NA()) -> #N/A | CA6: =IF(AND(ISNUMBER(Radar_Mosca!$F6),ISNUMBER(Radar_Mosca!$S6)),IF(AND(Radar_Mosca!$F6=CA$4,Radar_Mosca!$T6<>"Sì"),Radar_Mosca!$S6,NA()),NA()) -> #N/A | CB6: =IF(AND(ISNUMBER(Radar_Mosca!$F6),ISNUMBER(Radar_Mosca!$S6)),IF(AND(Radar_Mosca!$F6=CB$4,Radar_Mosca!$T6<>"Sì"),Radar_Mosca!$S6,NA()),NA()) -> #N/A | CC6: =IF(AND(ISNUMBER(Radar_Mosca!$F6),ISNUMBER(Radar_Mosca!$S6)),IF(AND(Radar_Mosca!$F6=CC$4,Radar_Mosca!$T6<>"Sì"),Radar_Mosca!$S6,NA()),NA()) -> #N/A | CD6: =IF(AND(ISNUMBER(Radar_Mosca!$F6),ISNUMBER(Radar_Mosca!$S6)),IF(AND(Radar_Mosca!$F6=CD$4,Radar_Mosca!$T6<>"Sì"),Radar_Mosca!$S6,NA()),NA()) -> #N/A | CE6: =IF(AND(ISNUMBER(Radar_Mosca!$F6),ISNUMBER(Radar_Mosca!$S6)),IF(AND(Radar_Mosca!$F6=CE$4,Radar_Mosca!$T6<>"Sì"),Radar_Mosca!$S6,NA()),NA()) -> #N/A | CF6: =IF(AND(ISNUMBER(Radar_Mosca!$F6),ISNUMBER(Radar_Mosca!$S6)),IF(AND(Radar_Mosca!$F6=CF$4,Radar_Mosca!$T6<>"Sì"),Radar_Mosca!$S6,NA()),NA()) -> #N/A | ... CL6: =IF(AND(ISNUMBER(Radar_Mosca!$F6),ISNUMBER(Radar_Mosca!$S6)),IF(AND(Radar_Mosca!$F6=CL$4,Radar_Mosca!$T6<>"Sì"),Radar_Mosca!$S6,NA()),NA()) -> #N/A | CM6: =IF(AND(ISNUMBER(Radar_Mosca!$F6),ISNUMBER(Radar_Mosca!$S6)),IF(AND(Radar_Mosca!$F6=CM$4,Radar_Mosca!$T6="Sì"),Radar_Mosca!$S6,NA()),NA()) -> #N/A | CN6: =IF(AND(ISNUMBER(Radar_Mosca!$F6),ISNUMBER(Radar_Mosca!$S6)),IF(AND(Radar_Mosca!$F6=CN$4,Radar_Mosca!$T6="Sì"),Radar_Mosca!$S6,NA()),NA()) -> #N/A | CO6: =IF(AND(ISNUMBER(Radar_Mosca!$F6),ISNUMBER(Radar_Mosca!$S6)),IF(AND(Radar_Mosca!$F6=CO$4,Radar_Mosca!$T6="Sì"),Radar_Mosca!$S6,NA()),NA()) -> #N/A | CP6: =IF(AND(ISNUMBER(Radar_Mosca!$F6),ISNUMBER(Radar_Mosca!$S6)),IF(AND(Radar_Mosca!$F6=CP$4,Radar_Mosca!$T6="Sì"),Radar_Mosca!$S6,NA()),NA()) -> #N/A | CQ6: =IF(AND(ISNUMBER(Radar_Mosca!$F6),ISNUMBER(Radar_Mosca!$S6)),IF(AND(Radar_Mosca!$F6=CQ$4,Radar_Mosca!$T6="Sì"),Radar_Mosca!$S6,NA()),NA()) -> #N/A | CR6: =IF(AND(ISNUMBER(Radar_Mosca!$F6),ISNUMBER(Radar_Mosca!$S6)),IF(AND(Radar_Mosca!$F6=CR$4,Radar_Mosca!$T6="Sì"),Radar_Mosca!$S6,NA()),NA()) -> #N/A | CS6: =IF(AND(ISNUMBER(Radar_Mosca!$F6),ISNUMBER(Radar_Mosca!$S6)),IF(AND(Radar_Mosca!$F6=CS$4,Radar_Mosca!$T6="Sì"),Radar_Mosca!$S6,NA()),NA()) -> -0.16814271 | CT6: =IF(AND(ISNUMBER(Radar_Mosca!$F6),ISNUMBER(Radar_Mosca!$S6)),IF(AND(Radar_Mosca!$F6=CT$4,Radar_Mosca!$T6="Sì"),Radar_Mosca!$S6,NA()),NA()) -> #N/A | ... CZ6: =IF(AND(ISNUMBER(Radar_Mosca!$F6),ISNUMBER(Radar_Mosca!$S6)),IF(AND(Radar_Mosca!$F6=CZ$4,Radar_Mosca!$T6="Sì"),Radar_Mosca!$S6,NA()),NA()) -> #N/A | DA6: =IF(ISNUMBER(Radar_Mosca!$R6),Radar_Mosca!$R6,NA()) -> -2.2437085 | DB6: =IF(Radar_Mosca!$A6="","",MID(Radar_Mosca!$A6,5,3)) -> 02 | DC6: =IF(ISNUMBER(Radar_Mosca!$S6),Radar_Mosca!$S6,NA()) -> -0.16814271 | DD6: AGIRE ORA: X + Y > Z | DE6: -7.35 | DF6: -7.35
T7: =IF(LEFT(Radar_Mosca!$L$7,9)="AGIRE ORA",Radar_Mosca!$A$7,"") | BH7: =2*PI()*2/72 -> 0.17453293 | BI7: =2*SIN($BH7) -> 0.34729636 | BJ7: =2*COS($BH7) -> 1.9696155 | BK7: =3*SIN($BH7) -> 0.52094453 | BL7: =3*COS($BH7) -> 2.9544233 | BM7: =4*SIN($BH7) -> 0.69459271 | BN7: =4*COS($BH7) -> 3.939231 | BO7: =5*SIN($BH7) -> 0.86824089 | BP7: =5*COS($BH7) -> 4.9240388 | BR7: 0 | BS7: 0 | BU7: L1-03 Impiego e sicurezza | BV7: =6.95*SIN(2*PI()*(2+0.5)/ROWS(codiciL1)) -> 5.4337288 | BW7: =6.95*COS(2*PI()*(2+0.5)/ROWS(codiciL1)) -> -4.3332541 | BY7: =IF(AND(ISNUMBER(Radar_Mosca!$F7),ISNUMBER(Radar_Mosca!$S7)),IF(AND(Radar_Mosca!$F7=BY$4,Radar_Mosca!$T7<>"Sì"),Radar_Mosca!$S7,NA()),NA()) -> #N/A | BZ7: =IF(AND(ISNUMBER(Radar_Mosca!$F7),ISNUMBER(Radar_Mosca!$S7)),IF(AND(Radar_Mosca!$F7=BZ$4,Radar_Mosca!$T7<>"Sì"),Radar_Mosca!$S7,NA()),NA()) -> #N/A | CA7: =IF(AND(ISNUMBER(Radar_Mosca!$F7),ISNUMBER(Radar_Mosca!$S7)),IF(AND(Radar_Mosca!$F7=CA$4,Radar_Mosca!$T7<>"Sì"),Radar_Mosca!$S7,NA()),NA()) -> #N/A | CB7: =IF(AND(ISNUMBER(Radar_Mosca!$F7),ISNUMBER(Radar_Mosca!$S7)),IF(AND(Radar_Mosca!$F7=CB$4,Radar_Mosca!$T7<>"Sì"),Radar_Mosca!$S7,NA()),NA()) -> #N/A | CC7: =IF(AND(ISNUMBER(Radar_Mosca!$F7),ISNUMBER(Radar_Mosca!$S7)),IF(AND(Radar_Mosca!$F7=CC$4,Radar_Mosca!$T7<>"Sì"),Radar_Mosca!$S7,NA()),NA()) -> #N/A | CD7: =IF(AND(ISNUMBER(Radar_Mosca!$F7),ISNUMBER(Radar_Mosca!$S7)),IF(AND(Radar_Mosca!$F7=CD$4,Radar_Mosca!$T7<>"Sì"),Radar_Mosca!$S7,NA()),NA()) -> #N/A | CE7: =IF(AND(ISNUMBER(Radar_Mosca!$F7),ISNUMBER(Radar_Mosca!$S7)),IF(AND(Radar_Mosca!$F7=CE$4,Radar_Mosca!$T7<>"Sì"),Radar_Mosca!$S7,NA()),NA()) -> #N/A | CF7: =IF(AND(ISNUMBER(Radar_Mosca!$F7),ISNUMBER(Radar_Mosca!$S7)),IF(AND(Radar_Mosca!$F7=CF$4,Radar_Mosca!$T7<>"Sì"),Radar_Mosca!$S7,NA()),NA()) -> -1.9111456 | ... CL7: =IF(AND(ISNUMBER(Radar_Mosca!$F7),ISNUMBER(Radar_Mosca!$S7)),IF(AND(Radar_Mosca!$F7=CL$4,Radar_Mosca!$T7<>"Sì"),Radar_Mosca!$S7,NA()),NA()) -> #N/A | CM7: =IF(AND(ISNUMBER(Radar_Mosca!$F7),ISNUMBER(Radar_Mosca!$S7)),IF(AND(Radar_Mosca!$F7=CM$4,Radar_Mosca!$T7="Sì"),Radar_Mosca!$S7,NA()),NA()) -> #N/A | CN7: =IF(AND(ISNUMBER(Radar_Mosca!$F7),ISNUMBER(Radar_Mosca!$S7)),IF(AND(Radar_Mosca!$F7=CN$4,Radar_Mosca!$T7="Sì"),Radar_Mosca!$S7,NA()),NA()) -> #N/A | CO7: =IF(AND(ISNUMBER(Radar_Mosca!$F7),ISNUMBER(Radar_Mosca!$S7)),IF(AND(Radar_Mosca!$F7=CO$4,Radar_Mosca!$T7="Sì"),Radar_Mosca!$S7,NA()),NA()) -> #N/A | CP7: =IF(AND(ISNUMBER(Radar_Mosca!$F7),ISNUMBER(Radar_Mosca!$S7)),IF(AND(Radar_Mosca!$F7=CP$4,Radar_Mosca!$T7="Sì"),Radar_Mosca!$S7,NA()),NA()) -> #N/A | CQ7: =IF(AND(ISNUMBER(Radar_Mosca!$F7),ISNUMBER(Radar_Mosca!$S7)),IF(AND(Radar_Mosca!$F7=CQ$4,Radar_Mosca!$T7="Sì"),Radar_Mosca!$S7,NA()),NA()) -> #N/A | CR7: =IF(AND(ISNUMBER(Radar_Mosca!$F7),ISNUMBER(Radar_Mosca!$S7)),IF(AND(Radar_Mosca!$F7=CR$4,Radar_Mosca!$T7="Sì"),Radar_Mosca!$S7,NA()),NA()) -> #N/A | CS7: =IF(AND(ISNUMBER(Radar_Mosca!$F7),ISNUMBER(Radar_Mosca!$S7)),IF(AND(Radar_Mosca!$F7=CS$4,Radar_Mosca!$T7="Sì"),Radar_Mosca!$S7,NA()),NA()) -> #N/A | CT7: =IF(AND(ISNUMBER(Radar_Mosca!$F7),ISNUMBER(Radar_Mosca!$S7)),IF(AND(Radar_Mosca!$F7=CT$4,Radar_Mosca!$T7="Sì"),Radar_Mosca!$S7,NA()),NA()) -> #N/A | ... CZ7: =IF(AND(ISNUMBER(Radar_Mosca!$F7),ISNUMBER(Radar_Mosca!$S7)),IF(AND(Radar_Mosca!$F7=CZ$4,Radar_Mosca!$T7="Sì"),Radar_Mosca!$S7,NA()),NA()) -> #N/A | DA7: =IF(ISNUMBER(Radar_Mosca!$R7),Radar_Mosca!$R7,NA()) -> 0.58951035 | DB7: =IF(Radar_Mosca!$A7="","",MID(Radar_Mosca!$A7,5,3)) -> 03 | DC7: =IF(ISNUMBER(Radar_Mosca!$S7),Radar_Mosca!$S7,NA()) -> -1.9111456 | DE7: -6.45 | DF7: -7.35
A8: Priorita' — primi cinque per score composito | J8: Gravita': Probabilita x Severity | T8: =IF(LEFT(Radar_Mosca!$L$8,9)="AGIRE ORA",Radar_Mosca!$A$8,"") | BH8: =2*PI()*3/72 -> 0.26179939 | BI8: =2*SIN($BH8) -> 0.51763809 | BJ8: =2*COS($BH8) -> 1.9318517 | BK8: =3*SIN($BH8) -> 0.77645714 | BL8: =3*COS($BH8) -> 2.8977775 | BM8: =4*SIN($BH8) -> 1.0352762 | BN8: =4*COS($BH8) -> 3.8637033 | BO8: =5*SIN($BH8) -> 1.2940952 | BP8: =5*COS($BH8) -> 4.8296291 | BR8: =6.3*SIN(2*PI()*1/ROWS(codiciL1)) -> 4.9255383 | BS8: =6.3*COS(2*PI()*1/ROWS(codiciL1)) -> 3.9279858 | BU8: L1-04 Clientela e prodotti | BV8: =6.95*SIN(2*PI()*(3+0.5)/ROWS(codiciL1)) -> 8.5147818e-16 | BW8: =6.95*COS(2*PI()*(3+0.5)/ROWS(codiciL1)) -> -6.95 | BY8: =IF(AND(ISNUMBER(Radar_Mosca!$F8),ISNUMBER(Radar_Mosca!$S8)),IF(AND(Radar_Mosca!$F8=BY$4,Radar_Mosca!$T8<>"Sì"),Radar_Mosca!$S8,NA()),NA()) -> #N/A | BZ8: =IF(AND(ISNUMBER(Radar_Mosca!$F8),ISNUMBER(Radar_Mosca!$S8)),IF(AND(Radar_Mosca!$F8=BZ$4,Radar_Mosca!$T8<>"Sì"),Radar_Mosca!$S8,NA()),NA()) -> #N/A | CA8: =IF(AND(ISNUMBER(Radar_Mosca!$F8),ISNUMBER(Radar_Mosca!$S8)),IF(AND(Radar_Mosca!$F8=CA$4,Radar_Mosca!$T8<>"Sì"),Radar_Mosca!$S8,NA()),NA()) -> #N/A | CB8: =IF(AND(ISNUMBER(Radar_Mosca!$F8),ISNUMBER(Radar_Mosca!$S8)),IF(AND(Radar_Mosca!$F8=CB$4,Radar_Mosca!$T8<>"Sì"),Radar_Mosca!$S8,NA()),NA()) -> #N/A | CC8: =IF(AND(ISNUMBER(Radar_Mosca!$F8),ISNUMBER(Radar_Mosca!$S8)),IF(AND(Radar_Mosca!$F8=CC$4,Radar_Mosca!$T8<>"Sì"),Radar_Mosca!$S8,NA()),NA()) -> #N/A | CD8: =IF(AND(ISNUMBER(Radar_Mosca!$F8),ISNUMBER(Radar_Mosca!$S8)),IF(AND(Radar_Mosca!$F8=CD$4,Radar_Mosca!$T8<>"Sì"),Radar_Mosca!$S8,NA()),NA()) -> #N/A | CE8: =IF(AND(ISNUMBER(Radar_Mosca!$F8),ISNUMBER(Radar_Mosca!$S8)),IF(AND(Radar_Mosca!$F8=CE$4,Radar_Mosca!$T8<>"Sì"),Radar_Mosca!$S8,NA()),NA()) -> #N/A | CF8: =IF(AND(ISNUMBER(Radar_Mosca!$F8),ISNUMBER(Radar_Mosca!$S8)),IF(AND(Radar_Mosca!$F8=CF$4,Radar_Mosca!$T8<>"Sì"),Radar_Mosca!$S8,NA()),NA()) -> -1.714597 | ... CL8: =IF(AND(ISNUMBER(Radar_Mosca!$F8),ISNUMBER(Radar_Mosca!$S8)),IF(AND(Radar_Mosca!$F8=CL$4,Radar_Mosca!$T8<>"Sì"),Radar_Mosca!$S8,NA()),NA()) -> #N/A | CM8: =IF(AND(ISNUMBER(Radar_Mosca!$F8),ISNUMBER(Radar_Mosca!$S8)),IF(AND(Radar_Mosca!$F8=CM$4,Radar_Mosca!$T8="Sì"),Radar_Mosca!$S8,NA()),NA()) -> #N/A | CN8: =IF(AND(ISNUMBER(Radar_Mosca!$F8),ISNUMBER(Radar_Mosca!$S8)),IF(AND(Radar_Mosca!$F8=CN$4,Radar_Mosca!$T8="Sì"),Radar_Mosca!$S8,NA()),NA()) -> #N/A | CO8: =IF(AND(ISNUMBER(Radar_Mosca!$F8),ISNUMBER(Radar_Mosca!$S8)),IF(AND(Radar_Mosca!$F8=CO$4,Radar_Mosca!$T8="Sì"),Radar_Mosca!$S8,NA()),NA()) -> #N/A | CP8: =IF(AND(ISNUMBER(Radar_Mosca!$F8),ISNUMBER(Radar_Mosca!$S8)),IF(AND(Radar_Mosca!$F8=CP$4,Radar_Mosca!$T8="Sì"),Radar_Mosca!$S8,NA()),NA()) -> #N/A | CQ8: =IF(AND(ISNUMBER(Radar_Mosca!$F8),ISNUMBER(Radar_Mosca!$S8)),IF(AND(Radar_Mosca!$F8=CQ$4,Radar_Mosca!$T8="Sì"),Radar_Mosca!$S8,NA()),NA()) -> #N/A | CR8: =IF(AND(ISNUMBER(Radar_Mosca!$F8),ISNUMBER(Radar_Mosca!$S8)),IF(AND(Radar_Mosca!$F8=CR$4,Radar_Mosca!$T8="Sì"),Radar_Mosca!$S8,NA()),NA()) -> #N/A | CS8: =IF(AND(ISNUMBER(Radar_Mosca!$F8),ISNUMBER(Radar_Mosca!$S8)),IF(AND(Radar_Mosca!$F8=CS$4,Radar_Mosca!$T8="Sì"),Radar_Mosca!$S8,NA()),NA()) -> #N/A | CT8: =IF(AND(ISNUMBER(Radar_Mosca!$F8),ISNUMBER(Radar_Mosca!$S8)),IF(AND(Radar_Mosca!$F8=CT$4,Radar_Mosca!$T8="Sì"),Radar_Mosca!$S8,NA()),NA()) -> #N/A | ... CZ8: =IF(AND(ISNUMBER(Radar_Mosca!$F8),ISNUMBER(Radar_Mosca!$S8)),IF(AND(Radar_Mosca!$F8=CZ$4,Radar_Mosca!$T8="Sì"),Radar_Mosca!$S8,NA()),NA()) -> #N/A | DA8: =IF(ISNUMBER(Radar_Mosca!$R8),Radar_Mosca!$R8,NA()) -> -2.1500366 | DB8: =IF(Radar_Mosca!$A8="","",MID(Radar_Mosca!$A8,5,3)) -> 04 | DC8: =IF(ISNUMBER(Radar_Mosca!$S8),Radar_Mosca!$S8,NA()) -> -1.714597 | DD8: Area del cerchio = P x I | DE8: 4.4 | DF8: -5.6
A9: # | B9: Rischio | F9: Score | G9: Variazione | H9: Urgenza | J9: P \ S | K9: 1 | L9: 2 | M9: 3 | N9: 4 | O9: 5 | T9: =IF(LEFT(Radar_Mosca!$L$9,9)="AGIRE ORA",Radar_Mosca!$A$9,"") | BH9: =2*PI()*4/72 -> 0.34906585 | BI9: =2*SIN($BH9) -> 0.68404029 | BJ9: =2*COS($BH9) -> 1.8793852 | BK9: =3*SIN($BH9) -> 1.0260604 | BL9: =3*COS($BH9) -> 2.8190779 | BM9: =4*SIN($BH9) -> 1.3680806 | BN9: =4*COS($BH9) -> 3.7587705 | BO9: =5*SIN($BH9) -> 1.7101007 | BP9: =5*COS($BH9) -> 4.6984631 | BR9: 0 | BS9: 0 | BU9: L1-05 Danni a beni materiali | BV9: =6.95*SIN(2*PI()*(4+0.5)/ROWS(codiciL1)) -> -5.4337288 | BW9: =6.95*COS(2*PI()*(4+0.5)/ROWS(codiciL1)) -> -4.3332541 | BY9: =IF(AND(ISNUMBER(Radar_Mosca!$F9),ISNUMBER(Radar_Mosca!$S9)),IF(AND(Radar_Mosca!$F9=BY$4,Radar_Mosca!$T9<>"Sì"),Radar_Mosca!$S9,NA()),NA()) -> #N/A | BZ9: =IF(AND(ISNUMBER(Radar_Mosca!$F9),ISNUMBER(Radar_Mosca!$S9)),IF(AND(Radar_Mosca!$F9=BZ$4,Radar_Mosca!$T9<>"Sì"),Radar_Mosca!$S9,NA()),NA()) -> #N/A | CA9: =IF(AND(ISNUMBER(Radar_Mosca!$F9),ISNUMBER(Radar_Mosca!$S9)),IF(AND(Radar_Mosca!$F9=CA$4,Radar_Mosca!$T9<>"Sì"),Radar_Mosca!$S9,NA()),NA()) -> #N/A | CB9: =IF(AND(ISNUMBER(Radar_Mosca!$F9),ISNUMBER(Radar_Mosca!$S9)),IF(AND(Radar_Mosca!$F9=CB$4,Radar_Mosca!$T9<>"Sì"),Radar_Mosca!$S9,NA()),NA()) -> #N/A | CC9: =IF(AND(ISNUMBER(Radar_Mosca!$F9),ISNUMBER(Radar_Mosca!$S9)),IF(AND(Radar_Mosca!$F9=CC$4,Radar_Mosca!$T9<>"Sì"),Radar_Mosca!$S9,NA()),NA()) -> #N/A | CD9: =IF(AND(ISNUMBER(Radar_Mosca!$F9),ISNUMBER(Radar_Mosca!$S9)),IF(AND(Radar_Mosca!$F9=CD$4,Radar_Mosca!$T9<>"Sì"),Radar_Mosca!$S9,NA()),NA()) -> #N/A | CE9: =IF(AND(ISNUMBER(Radar_Mosca!$F9),ISNUMBER(Radar_Mosca!$S9)),IF(AND(Radar_Mosca!$F9=CE$4,Radar_Mosca!$T9<>"Sì"),Radar_Mosca!$S9,NA()),NA()) -> #N/A | CF9: =IF(AND(ISNUMBER(Radar_Mosca!$F9),ISNUMBER(Radar_Mosca!$S9)),IF(AND(Radar_Mosca!$F9=CF$4,Radar_Mosca!$T9<>"Sì"),Radar_Mosca!$S9,NA()),NA()) -> 2.3454944 | ... CL9: =IF(AND(ISNUMBER(Radar_Mosca!$F9),ISNUMBER(Radar_Mosca!$S9)),IF(AND(Radar_Mosca!$F9=CL$4,Radar_Mosca!$T9<>"Sì"),Radar_Mosca!$S9,NA()),NA()) -> #N/A | CM9: =IF(AND(ISNUMBER(Radar_Mosca!$F9),ISNUMBER(Radar_Mosca!$S9)),IF(AND(Radar_Mosca!$F9=CM$4,Radar_Mosca!$T9="Sì"),Radar_Mosca!$S9,NA()),NA()) -> #N/A | CN9: =IF(AND(ISNUMBER(Radar_Mosca!$F9),ISNUMBER(Radar_Mosca!$S9)),IF(AND(Radar_Mosca!$F9=CN$4,Radar_Mosca!$T9="Sì"),Radar_Mosca!$S9,NA()),NA()) -> #N/A | CO9: =IF(AND(ISNUMBER(Radar_Mosca!$F9),ISNUMBER(Radar_Mosca!$S9)),IF(AND(Radar_Mosca!$F9=CO$4,Radar_Mosca!$T9="Sì"),Radar_Mosca!$S9,NA()),NA()) -> #N/A | CP9: =IF(AND(ISNUMBER(Radar_Mosca!$F9),ISNUMBER(Radar_Mosca!$S9)),IF(AND(Radar_Mosca!$F9=CP$4,Radar_Mosca!$T9="Sì"),Radar_Mosca!$S9,NA()),NA()) -> #N/A | CQ9: =IF(AND(ISNUMBER(Radar_Mosca!$F9),ISNUMBER(Radar_Mosca!$S9)),IF(AND(Radar_Mosca!$F9=CQ$4,Radar_Mosca!$T9="Sì"),Radar_Mosca!$S9,NA()),NA()) -> #N/A | CR9: =IF(AND(ISNUMBER(Radar_Mosca!$F9),ISNUMBER(Radar_Mosca!$S9)),IF(AND(Radar_Mosca!$F9=CR$4,Radar_Mosca!$T9="Sì"),Radar_Mosca!$S9,NA()),NA()) -> #N/A | CS9: =IF(AND(ISNUMBER(Radar_Mosca!$F9),ISNUMBER(Radar_Mosca!$S9)),IF(AND(Radar_Mosca!$F9=CS$4,Radar_Mosca!$T9="Sì"),Radar_Mosca!$S9,NA()),NA()) -> #N/A | CT9: =IF(AND(ISNUMBER(Radar_Mosca!$F9),ISNUMBER(Radar_Mosca!$S9)),IF(AND(Radar_Mosca!$F9=CT$4,Radar_Mosca!$T9="Sì"),Radar_Mosca!$S9,NA()),NA()) -> #N/A | ... CZ9: =IF(AND(ISNUMBER(Radar_Mosca!$F9),ISNUMBER(Radar_Mosca!$S9)),IF(AND(Radar_Mosca!$F9=CZ$4,Radar_Mosca!$T9="Sì"),Radar_Mosca!$S9,NA()),NA()) -> #N/A | DA9: =IF(ISNUMBER(Radar_Mosca!$R9),Radar_Mosca!$R9,NA()) -> -1.8704694 | DB9: =IF(Radar_Mosca!$A9="","",MID(Radar_Mosca!$A9,5,3)) -> 05 | DC9: =IF(ISNUMBER(Radar_Mosca!$S9),Radar_Mosca!$S9,NA()) -> 2.3454944 | DD9: 4 | DE9: 3.5 | DF9: -6.6
A10: =Classifica!$A$5 -> 1 | B10: =IF(Classifica!$B$5="","",Classifica!$B$5&" "&Classifica!$C$5&IFERROR(IF(INDEX(ANA_Attenzione_Supervisore,Classifica!$U$5)="Sì"," ◆",""),"")) -> NFR-01 Frodi su pagamenti istantanei abilitate da AI generativa ◆ | F10: =IF(Classifica!$B$5="","",Classifica!$D$5) -> 3.8 | G10: =IF(Classifica!$B$5="","",IF(ISNUMBER(Classifica!$F$5),Classifica!$F$5,"nuovo")) -> 0 | H10: =IF(Classifica!$B$5="","",IF(LEFT(Classifica!$H$5,9)="AGIRE ORA","AGIRE ORA",IF(LEFT(Classifica!$H$5,11)="Agire entro","Entro l'anno",Classifica!$H$5))) -> AGIRE ORA | J10: 5 | K10: =SUBSTITUTE(SUBSTITUTE(Matrice!C5," ◆",""),"NFR-","") | L10: =SUBSTITUTE(SUBSTITUTE(Matrice!D5," ◆",""),"NFR-","") | M10: =SUBSTITUTE(SUBSTITUTE(Matrice!E5," ◆",""),"NFR-","") | N10: =SUBSTITUTE(SUBSTITUTE(Matrice!F5," ◆",""),"NFR-","") | O10: =SUBSTITUTE(SUBSTITUTE(Matrice!G5," ◆",""),"NFR-","") | T10: =IF(LEFT(Radar_Mosca!$L$10,9)="AGIRE ORA",Radar_Mosca!$A$10,"") | BH10: =2*PI()*5/72 -> 0.43633231 | BI10: =2*SIN($BH10) -> 0.84523652 | BJ10: =2*COS($BH10) -> 1.8126156 | BK10: =3*SIN($BH10) -> 1.2678548 | BL10: =3*COS($BH10) -> 2.7189234 | BM10: =4*SIN($BH10) -> 1.690473 | BN10: =4*COS($BH10) -> 3.6252311 | BO10: =5*SIN($BH10) -> 2.1130913 | BP10: =5*COS($BH10) -> 4.5315389 | BR10: =6.3*SIN(2*PI()*2/ROWS(codiciL1)) -> 6.1420458 | BS10: =6.3*COS(2*PI()*2/ROWS(codiciL1)) -> -1.4018819 | BU10: L1-06 Interruzione e sistemi | BV10: =6.95*SIN(2*PI()*(5+0.5)/ROWS(codiciL1)) -> -6.775749 | BW10: =6.95*COS(2*PI()*(5+0.5)/ROWS(codiciL1)) -> 1.5465205 | BY10: =IF(AND(ISNUMBER(Radar_Mosca!$F10),ISNUMBER(Radar_Mosca!$S10)),IF(AND(Radar_Mosca!$F10=BY$4,Radar_Mosca!$T10<>"Sì"),Radar_Mosca!$S10,NA()),NA()) -> #N/A | BZ10: =IF(AND(ISNUMBER(Radar_Mosca!$F10),ISNUMBER(Radar_Mosca!$S10)),IF(AND(Radar_Mosca!$F10=BZ$4,Radar_Mosca!$T10<>"Sì"),Radar_Mosca!$S10,NA()),NA()) -> #N/A | CA10: =IF(AND(ISNUMBER(Radar_Mosca!$F10),ISNUMBER(Radar_Mosca!$S10)),IF(AND(Radar_Mosca!$F10=CA$4,Radar_Mosca!$T10<>"Sì"),Radar_Mosca!$S10,NA()),NA()) -> #N/A | CB10: =IF(AND(ISNUMBER(Radar_Mosca!$F10),ISNUMBER(Radar_Mosca!$S10)),IF(AND(Radar_Mosca!$F10=CB$4,Radar_Mosca!$T10<>"Sì"),Radar_Mosca!$S10,NA()),NA()) -> #N/A | CC10: =IF(AND(ISNUMBER(Radar_Mosca!$F10),ISNUMBER(Radar_Mosca!$S10)),IF(AND(Radar_Mosca!$F10=CC$4,Radar_Mosca!$T10<>"Sì"),Radar_Mosca!$S10,NA()),NA()) -> #N/A | CD10: =IF(AND(ISNUMBER(Radar_Mosca!$F10),ISNUMBER(Radar_Mosca!$S10)),IF(AND(Radar_Mosca!$F10=CD$4,Radar_Mosca!$T10<>"Sì"),Radar_Mosca!$S10,NA()),NA()) -> #N/A | CE10: =IF(AND(ISNUMBER(Radar_Mosca!$F10),ISNUMBER(Radar_Mosca!$S10)),IF(AND(Radar_Mosca!$F10=CE$4,Radar_Mosca!$T10<>"Sì"),Radar_Mosca!$S10,NA()),NA()) -> #N/A | CF10: =IF(AND(ISNUMBER(Radar_Mosca!$F10),ISNUMBER(Radar_Mosca!$S10)),IF(AND(Radar_Mosca!$F10=CF$4,Radar_Mosca!$T10<>"Sì"),Radar_Mosca!$S10,NA()),NA()) -> 2.6810518 | ... CL10: =IF(AND(ISNUMBER(Radar_Mosca!$F10),ISNUMBER(Radar_Mosca!$S10)),IF(AND(Radar_Mosca!$F10=CL$4,Radar_Mosca!$T10<>"Sì"),Radar_Mosca!$S10,NA()),NA()) -> #N/A | CM10: =IF(AND(ISNUMBER(Radar_Mosca!$F10),ISNUMBER(Radar_Mosca!$S10)),IF(AND(Radar_Mosca!$F10=CM$4,Radar_Mosca!$T10="Sì"),Radar_Mosca!$S10,NA()),NA()) -> #N/A | CN10: =IF(AND(ISNUMBER(Radar_Mosca!$F10),ISNUMBER(Radar_Mosca!$S10)),IF(AND(Radar_Mosca!$F10=CN$4,Radar_Mosca!$T10="Sì"),Radar_Mosca!$S10,NA()),NA()) -> #N/A | CO10: =IF(AND(ISNUMBER(Radar_Mosca!$F10),ISNUMBER(Radar_Mosca!$S10)),IF(AND(Radar_Mosca!$F10=CO$4,Radar_Mosca!$T10="Sì"),Radar_Mosca!$S10,NA()),NA()) -> #N/A | CP10: =IF(AND(ISNUMBER(Radar_Mosca!$F10),ISNUMBER(Radar_Mosca!$S10)),IF(AND(Radar_Mosca!$F10=CP$4,Radar_Mosca!$T10="Sì"),Radar_Mosca!$S10,NA()),NA()) -> #N/A | CQ10: =IF(AND(ISNUMBER(Radar_Mosca!$F10),ISNUMBER(Radar_Mosca!$S10)),IF(AND(Radar_Mosca!$F10=CQ$4,Radar_Mosca!$T10="Sì"),Radar_Mosca!$S10,NA()),NA()) -> #N/A | CR10: =IF(AND(ISNUMBER(Radar_Mosca!$F10),ISNUMBER(Radar_Mosca!$S10)),IF(AND(Radar_Mosca!$F10=CR$4,Radar_Mosca!$T10="Sì"),Radar_Mosca!$S10,NA()),NA()) -> #N/A | CS10: =IF(AND(ISNUMBER(Radar_Mosca!$F10),ISNUMBER(Radar_Mosca!$S10)),IF(AND(Radar_Mosca!$F10=CS$4,Radar_Mosca!$T10="Sì"),Radar_Mosca!$S10,NA()),NA()) -> #N/A | CT10: =IF(AND(ISNUMBER(Radar_Mosca!$F10),ISNUMBER(Radar_Mosca!$S10)),IF(AND(Radar_Mosca!$F10=CT$4,Radar_Mosca!$T10="Sì"),Radar_Mosca!$S10,NA()),NA()) -> #N/A | ... CZ10: =IF(AND(ISNUMBER(Radar_Mosca!$F10),ISNUMBER(Radar_Mosca!$S10)),IF(AND(Radar_Mosca!$F10=CZ$4,Radar_Mosca!$T10="Sì"),Radar_Mosca!$S10,NA()),NA()) -> #N/A | DA10: =IF(ISNUMBER(Radar_Mosca!$R10),Radar_Mosca!$R10,NA()) -> 0.61193257 | DB10: =IF(Radar_Mosca!$A10="","",MID(Radar_Mosca!$A10,5,3)) -> 06 | DC10: =IF(ISNUMBER(Radar_Mosca!$S10),Radar_Mosca!$S10,NA()) -> 2.6810518 | DD10: 12 | DE10: 4.8 | DF10: -6.6
A11: =Classifica!$A$6 -> 2 | B11: =IF(Classifica!$B$6="","",Classifica!$B$6&" "&Classifica!$C$6&IFERROR(IF(INDEX(ANA_Attenzione_Supervisore,Classifica!$U$6)="Sì"," ◆",""),"")) -> NFR-07 Ransomware presso un fornitore di servizi di pagamento ◆ | F11: =IF(Classifica!$B$6="","",Classifica!$D$6) -> 3.6 | G11: =IF(Classifica!$B$6="","",IF(ISNUMBER(Classifica!$F$6),Classifica!$F$6,"nuovo")) -> 0 | H11: =IF(Classifica!$B$6="","",IF(LEFT(Classifica!$H$6,9)="AGIRE ORA","AGIRE ORA",IF(LEFT(Classifica!$H$6,11)="Agire entro","Entro l'anno",Classifica!$H$6))) -> Entro l'anno | J11: 4 | K11: =SUBSTITUTE(SUBSTITUTE(Matrice!C6," ◆",""),"NFR-","") | L11: =SUBSTITUTE(SUBSTITUTE(Matrice!D6," ◆",""),"NFR-","") | M11: =SUBSTITUTE(SUBSTITUTE(Matrice!E6," ◆",""),"NFR-","") -> 12 | N11: =SUBSTITUTE(SUBSTITUTE(Matrice!F6," ◆",""),"NFR-","") -> 01 | O11: =SUBSTITUTE(SUBSTITUTE(Matrice!G6," ◆",""),"NFR-","") | T11: =IF(LEFT(Radar_Mosca!$L$11,9)="AGIRE ORA",Radar_Mosca!$A$11,"") | BH11: =2*PI()*6/72 -> 0.52359878 | BI11: =2*SIN($BH11) -> 1 | BJ11: =2*COS($BH11) -> 1.7320508 | BK11: =3*SIN($BH11) -> 1.5 | BL11: =3*COS($BH11) -> 2.5980762 | BM11: =4*SIN($BH11) -> 2 | BN11: =4*COS($BH11) -> 3.4641016 | BO11: =5*SIN($BH11) -> 2.5 | BP11: =5*COS($BH11) -> 4.330127 | BR11: 0 | BS11: 0 | BU11: L1-07 Processi | BV11: =6.95*SIN(2*PI()*(6+0.5)/ROWS(codiciL1)) -> -3.015492 | BW11: =6.95*COS(2*PI()*(6+0.5)/ROWS(codiciL1)) -> 6.2617336 | BY11: =IF(AND(ISNUMBER(Radar_Mosca!$F11),ISNUMBER(Radar_Mosca!$S11)),IF(AND(Radar_Mosca!$F11=BY$4,Radar_Mosca!$T11<>"Sì"),Radar_Mosca!$S11,NA()),NA()) -> #N/A | BZ11: =IF(AND(ISNUMBER(Radar_Mosca!$F11),ISNUMBER(Radar_Mosca!$S11)),IF(AND(Radar_Mosca!$F11=BZ$4,Radar_Mosca!$T11<>"Sì"),Radar_Mosca!$S11,NA()),NA()) -> #N/A | CA11: =IF(AND(ISNUMBER(Radar_Mosca!$F11),ISNUMBER(Radar_Mosca!$S11)),IF(AND(Radar_Mosca!$F11=CA$4,Radar_Mosca!$T11<>"Sì"),Radar_Mosca!$S11,NA()),NA()) -> #N/A | CB11: =IF(AND(ISNUMBER(Radar_Mosca!$F11),ISNUMBER(Radar_Mosca!$S11)),IF(AND(Radar_Mosca!$F11=CB$4,Radar_Mosca!$T11<>"Sì"),Radar_Mosca!$S11,NA()),NA()) -> #N/A | CC11: =IF(AND(ISNUMBER(Radar_Mosca!$F11),ISNUMBER(Radar_Mosca!$S11)),IF(AND(Radar_Mosca!$F11=CC$4,Radar_Mosca!$T11<>"Sì"),Radar_Mosca!$S11,NA()),NA()) -> #N/A | CD11: =IF(AND(ISNUMBER(Radar_Mosca!$F11),ISNUMBER(Radar_Mosca!$S11)),IF(AND(Radar_Mosca!$F11=CD$4,Radar_Mosca!$T11<>"Sì"),Radar_Mosca!$S11,NA()),NA()) -> #N/A | CE11: =IF(AND(ISNUMBER(Radar_Mosca!$F11),ISNUMBER(Radar_Mosca!$S11)),IF(AND(Radar_Mosca!$F11=CE$4,Radar_Mosca!$T11<>"Sì"),Radar_Mosca!$S11,NA()),NA()) -> #N/A | CF11: =IF(AND(ISNUMBER(Radar_Mosca!$F11),ISNUMBER(Radar_Mosca!$S11)),IF(AND(Radar_Mosca!$F11=CF$4,Radar_Mosca!$T11<>"Sì"),Radar_Mosca!$S11,NA()),NA()) -> #N/A | ... CL11: =IF(AND(ISNUMBER(Radar_Mosca!$F11),ISNUMBER(Radar_Mosca!$S11)),IF(AND(Radar_Mosca!$F11=CL$4,Radar_Mosca!$T11<>"Sì"),Radar_Mosca!$S11,NA()),NA()) -> #N/A | CM11: =IF(AND(ISNUMBER(Radar_Mosca!$F11),ISNUMBER(Radar_Mosca!$S11)),IF(AND(Radar_Mosca!$F11=CM$4,Radar_Mosca!$T11="Sì"),Radar_Mosca!$S11,NA()),NA()) -> #N/A | CN11: =IF(AND(ISNUMBER(Radar_Mosca!$F11),ISNUMBER(Radar_Mosca!$S11)),IF(AND(Radar_Mosca!$F11=CN$4,Radar_Mosca!$T11="Sì"),Radar_Mosca!$S11,NA()),NA()) -> #N/A | CO11: =IF(AND(ISNUMBER(Radar_Mosca!$F11),ISNUMBER(Radar_Mosca!$S11)),IF(AND(Radar_Mosca!$F11=CO$4,Radar_Mosca!$T11="Sì"),Radar_Mosca!$S11,NA()),NA()) -> #N/A | CP11: =IF(AND(ISNUMBER(Radar_Mosca!$F11),ISNUMBER(Radar_Mosca!$S11)),IF(AND(Radar_Mosca!$F11=CP$4,Radar_Mosca!$T11="Sì"),Radar_Mosca!$S11,NA()),NA()) -> #N/A | CQ11: =IF(AND(ISNUMBER(Radar_Mosca!$F11),ISNUMBER(Radar_Mosca!$S11)),IF(AND(Radar_Mosca!$F11=CQ$4,Radar_Mosca!$T11="Sì"),Radar_Mosca!$S11,NA()),NA()) -> #N/A | CR11: =IF(AND(ISNUMBER(Radar_Mosca!$F11),ISNUMBER(Radar_Mosca!$S11)),IF(AND(Radar_Mosca!$F11=CR$4,Radar_Mosca!$T11="Sì"),Radar_Mosca!$S11,NA()),NA()) -> #N/A | CS11: =IF(AND(ISNUMBER(Radar_Mosca!$F11),ISNUMBER(Radar_Mosca!$S11)),IF(AND(Radar_Mosca!$F11=CS$4,Radar_Mosca!$T11="Sì"),Radar_Mosca!$S11,NA()),NA()) -> #N/A | CT11: =IF(AND(ISNUMBER(Radar_Mosca!$F11),ISNUMBER(Radar_Mosca!$S11)),IF(AND(Radar_Mosca!$F11=CT$4,Radar_Mosca!$T11="Sì"),Radar_Mosca!$S11,NA()),NA()) -> #N/A | ... CZ11: =IF(AND(ISNUMBER(Radar_Mosca!$F11),ISNUMBER(Radar_Mosca!$S11)),IF(AND(Radar_Mosca!$F11=CZ$4,Radar_Mosca!$T11="Sì"),Radar_Mosca!$S11,NA()),NA()) -> #N/A | DA11: =IF(ISNUMBER(Radar_Mosca!$R11),Radar_Mosca!$R11,NA()) -> -2.6810518 | DB11: =IF(Radar_Mosca!$A11="","",MID(Radar_Mosca!$A11,5,3)) -> 07 | DC11: =IF(ISNUMBER(Radar_Mosca!$S11),Radar_Mosca!$S11,NA()) -> 0.61193257 | DD11: 25 | DE11: 6.5 | DF11: -6.6
A12: =Classifica!$A$7 -> 3 | B12: =IF(Classifica!$B$7="","",Classifica!$B$7&" "&Classifica!$C$7&IFERROR(IF(INDEX(ANA_Attenzione_Supervisore,Classifica!$U$7)="Sì"," ◆",""),"")) -> NFR-12 Errori operativi nei pagamenti istantanei obbligatori | F12: =IF(Classifica!$B$7="","",Classifica!$D$7) -> 3.5 | G12: =IF(Classifica!$B$7="","",IF(ISNUMBER(Classifica!$F$7),Classifica!$F$7,"nuovo")) -> 0 | H12: =IF(Classifica!$B$7="","",IF(LEFT(Classifica!$H$7,9)="AGIRE ORA","AGIRE ORA",IF(LEFT(Classifica!$H$7,11)="Agire entro","Entro l'anno",Classifica!$H$7))) -> Entro l'anno | J12: 3 | K12: =SUBSTITUTE(SUBSTITUTE(Matrice!C7," ◆",""),"NFR-","") | L12: =SUBSTITUTE(SUBSTITUTE(Matrice!D7," ◆",""),"NFR-","") | M12: =SUBSTITUTE(SUBSTITUTE(Matrice!E7," ◆",""),"NFR-","") -> 03 04 05 06 10 11 | N12: =SUBSTITUTE(SUBSTITUTE(Matrice!F7," ◆",""),"NFR-","") -> 07 | O12: =SUBSTITUTE(SUBSTITUTE(Matrice!G7," ◆",""),"NFR-","") | T12: =IF(LEFT(Radar_Mosca!$L$12,9)="AGIRE ORA",Radar_Mosca!$A$12,"") | BH12: =2*PI()*7/72 -> 0.61086524 | BI12: =2*SIN($BH12) -> 1.1471529 | BJ12: =2*COS($BH12) -> 1.6383041 | BK12: =3*SIN($BH12) -> 1.7207293 | BL12: =3*COS($BH12) -> 2.4574561 | BM12: =4*SIN($BH12) -> 2.2943057 | BN12: =4*COS($BH12) -> 3.2766082 | BO12: =5*SIN($BH12) -> 2.8678822 | BP12: =5*COS($BH12) -> 4.0957602 | BR12: =6.3*SIN(2*PI()*3/ROWS(codiciL1)) -> 2.7334676 | BS12: =6.3*COS(2*PI()*3/ROWS(codiciL1)) -> -5.6761039 | BY12: =IF(AND(ISNUMBER(Radar_Mosca!$F12),ISNUMBER(Radar_Mosca!$S12)),IF(AND(Radar_Mosca!$F12=BY$4,Radar_Mosca!$T12<>"Sì"),Radar_Mosca!$S12,NA()),NA()) -> #N/A | BZ12: =IF(AND(ISNUMBER(Radar_Mosca!$F12),ISNUMBER(Radar_Mosca!$S12)),IF(AND(Radar_Mosca!$F12=BZ$4,Radar_Mosca!$T12<>"Sì"),Radar_Mosca!$S12,NA()),NA()) -> #N/A | CA12: =IF(AND(ISNUMBER(Radar_Mosca!$F12),ISNUMBER(Radar_Mosca!$S12)),IF(AND(Radar_Mosca!$F12=CA$4,Radar_Mosca!$T12<>"Sì"),Radar_Mosca!$S12,NA()),NA()) -> #N/A | CB12: =IF(AND(ISNUMBER(Radar_Mosca!$F12),ISNUMBER(Radar_Mosca!$S12)),IF(AND(Radar_Mosca!$F12=CB$4,Radar_Mosca!$T12<>"Sì"),Radar_Mosca!$S12,NA()),NA()) -> #N/A | CC12: =IF(AND(ISNUMBER(Radar_Mosca!$F12),ISNUMBER(Radar_Mosca!$S12)),IF(AND(Radar_Mosca!$F12=CC$4,Radar_Mosca!$T12<>"Sì"),Radar_Mosca!$S12,NA()),NA()) -> #N/A | CD12: =IF(AND(ISNUMBER(Radar_Mosca!$F12),ISNUMBER(Radar_Mosca!$S12)),IF(AND(Radar_Mosca!$F12=CD$4,Radar_Mosca!$T12<>"Sì"),Radar_Mosca!$S12,NA()),NA()) -> 1.7591208 | CE12: =IF(AND(ISNUMBER(Radar_Mosca!$F12),ISNUMBER(Radar_Mosca!$S12)),IF(AND(Radar_Mosca!$F12=CE$4,Radar_Mosca!$T12<>"Sì"),Radar_Mosca!$S12,NA()),NA()) -> #N/A | CF12: =IF(AND(ISNUMBER(Radar_Mosca!$F12),ISNUMBER(Radar_Mosca!$S12)),IF(AND(Radar_Mosca!$F12=CF$4,Radar_Mosca!$T12<>"Sì"),Radar_Mosca!$S12,NA()),NA()) -> #N/A | ... CL12: =IF(AND(ISNUMBER(Radar_Mosca!$F12),ISNUMBER(Radar_Mosca!$S12)),IF(AND(Radar_Mosca!$F12=CL$4,Radar_Mosca!$T12<>"Sì"),Radar_Mosca!$S12,NA()),NA()) -> #N/A | CM12: =IF(AND(ISNUMBER(Radar_Mosca!$F12),ISNUMBER(Radar_Mosca!$S12)),IF(AND(Radar_Mosca!$F12=CM$4,Radar_Mosca!$T12="Sì"),Radar_Mosca!$S12,NA()),NA()) -> #N/A | CN12: =IF(AND(ISNUMBER(Radar_Mosca!$F12),ISNUMBER(Radar_Mosca!$S12)),IF(AND(Radar_Mosca!$F12=CN$4,Radar_Mosca!$T12="Sì"),Radar_Mosca!$S12,NA()),NA()) -> #N/A | CO12: =IF(AND(ISNUMBER(Radar_Mosca!$F12),ISNUMBER(Radar_Mosca!$S12)),IF(AND(Radar_Mosca!$F12=CO$4,Radar_Mosca!$T12="Sì"),Radar_Mosca!$S12,NA()),NA()) -> #N/A | CP12: =IF(AND(ISNUMBER(Radar_Mosca!$F12),ISNUMBER(Radar_Mosca!$S12)),IF(AND(Radar_Mosca!$F12=CP$4,Radar_Mosca!$T12="Sì"),Radar_Mosca!$S12,NA()),NA()) -> #N/A | CQ12: =IF(AND(ISNUMBER(Radar_Mosca!$F12),ISNUMBER(Radar_Mosca!$S12)),IF(AND(Radar_Mosca!$F12=CQ$4,Radar_Mosca!$T12="Sì"),Radar_Mosca!$S12,NA()),NA()) -> #N/A | CR12: =IF(AND(ISNUMBER(Radar_Mosca!$F12),ISNUMBER(Radar_Mosca!$S12)),IF(AND(Radar_Mosca!$F12=CR$4,Radar_Mosca!$T12="Sì"),Radar_Mosca!$S12,NA()),NA()) -> #N/A | CS12: =IF(AND(ISNUMBER(Radar_Mosca!$F12),ISNUMBER(Radar_Mosca!$S12)),IF(AND(Radar_Mosca!$F12=CS$4,Radar_Mosca!$T12="Sì"),Radar_Mosca!$S12,NA()),NA()) -> #N/A | CT12: =IF(AND(ISNUMBER(Radar_Mosca!$F12),ISNUMBER(Radar_Mosca!$S12)),IF(AND(Radar_Mosca!$F12=CT$4,Radar_Mosca!$T12="Sì"),Radar_Mosca!$S12,NA()),NA()) -> #N/A | ... CZ12: =IF(AND(ISNUMBER(Radar_Mosca!$F12),ISNUMBER(Radar_Mosca!$S12)),IF(AND(Radar_Mosca!$F12=CZ$4,Radar_Mosca!$T12="Sì"),Radar_Mosca!$S12,NA()),NA()) -> #N/A | DA12: =IF(ISNUMBER(Radar_Mosca!$R12),Radar_Mosca!$R12,NA()) -> 1.4028521 | DB12: =IF(Radar_Mosca!$A12="","",MID(Radar_Mosca!$A12,5,3)) -> 08 | DC12: =IF(ISNUMBER(Radar_Mosca!$S12),Radar_Mosca!$S12,NA()) -> 1.7591208
A13: =Classifica!$A$8 -> 4 | B13: =IF(Classifica!$B$8="","",Classifica!$B$8&" "&Classifica!$C$8&IFERROR(IF(INDEX(ANA_Attenzione_Supervisore,Classifica!$U$8)="Sì"," ◆",""),"")) -> NFR-02 Concentrazione su un fornitore cloud critico ◆ | F13: =IF(Classifica!$B$8="","",Classifica!$D$8) -> 3.25 | G13: =IF(Classifica!$B$8="","",IF(ISNUMBER(Classifica!$F$8),Classifica!$F$8,"nuovo")) -> -0.2 | H13: =IF(Classifica!$B$8="","",IF(LEFT(Classifica!$H$8,9)="AGIRE ORA","AGIRE ORA",IF(LEFT(Classifica!$H$8,11)="Agire entro","Entro l'anno",Classifica!$H$8))) -> Entro l'anno | J13: 2 | K13: =SUBSTITUTE(SUBSTITUTE(Matrice!C8," ◆",""),"NFR-","") | L13: =SUBSTITUTE(SUBSTITUTE(Matrice!D8," ◆",""),"NFR-","") | M13: =SUBSTITUTE(SUBSTITUTE(Matrice!E8," ◆",""),"NFR-","") -> 08 | N13: =SUBSTITUTE(SUBSTITUTE(Matrice!F8," ◆",""),"NFR-","") -> 02 09 | O13: =SUBSTITUTE(SUBSTITUTE(Matrice!G8," ◆",""),"NFR-","") | T13: =IF(LEFT(Radar_Mosca!$L$13,9)="AGIRE ORA",Radar_Mosca!$A$13,"") | BH13: =2*PI()*8/72 -> 0.6981317 | BI13: =2*SIN($BH13) -> 1.2855752 | BJ13: =2*COS($BH13) -> 1.5320889 | BK13: =3*SIN($BH13) -> 1.9283628 | BL13: =3*COS($BH13) -> 2.2981333 | BM13: =4*SIN($BH13) -> 2.5711504 | BN13: =4*COS($BH13) -> 3.0641778 | BO13: =5*SIN($BH13) -> 3.213938 | BP13: =5*COS($BH13) -> 3.8302222 | BR13: 0 | BS13: 0 | BY13: =IF(AND(ISNUMBER(Radar_Mosca!$F13),ISNUMBER(Radar_Mosca!$S13)),IF(AND(Radar_Mosca!$F13=BY$4,Radar_Mosca!$T13<>"Sì"),Radar_Mosca!$S13,NA()),NA()) -> #N/A | BZ13: =IF(AND(ISNUMBER(Radar_Mosca!$F13),ISNUMBER(Radar_Mosca!$S13)),IF(AND(Radar_Mosca!$F13=BZ$4,Radar_Mosca!$T13<>"Sì"),Radar_Mosca!$S13,NA()),NA()) -> #N/A | CA13: =IF(AND(ISNUMBER(Radar_Mosca!$F13),ISNUMBER(Radar_Mosca!$S13)),IF(AND(Radar_Mosca!$F13=CA$4,Radar_Mosca!$T13<>"Sì"),Radar_Mosca!$S13,NA()),NA()) -> #N/A | CB13: =IF(AND(ISNUMBER(Radar_Mosca!$F13),ISNUMBER(Radar_Mosca!$S13)),IF(AND(Radar_Mosca!$F13=CB$4,Radar_Mosca!$T13<>"Sì"),Radar_Mosca!$S13,NA()),NA()) -> #N/A | CC13: =IF(AND(ISNUMBER(Radar_Mosca!$F13),ISNUMBER(Radar_Mosca!$S13)),IF(AND(Radar_Mosca!$F13=CC$4,Radar_Mosca!$T13<>"Sì"),Radar_Mosca!$S13,NA()),NA()) -> #N/A | CD13: =IF(AND(ISNUMBER(Radar_Mosca!$F13),ISNUMBER(Radar_Mosca!$S13)),IF(AND(Radar_Mosca!$F13=CD$4,Radar_Mosca!$T13<>"Sì"),Radar_Mosca!$S13,NA()),NA()) -> #N/A | CE13: =IF(AND(ISNUMBER(Radar_Mosca!$F13),ISNUMBER(Radar_Mosca!$S13)),IF(AND(Radar_Mosca!$F13=CE$4,Radar_Mosca!$T13<>"Sì"),Radar_Mosca!$S13,NA()),NA()) -> #N/A | CF13: =IF(AND(ISNUMBER(Radar_Mosca!$F13),ISNUMBER(Radar_Mosca!$S13)),IF(AND(Radar_Mosca!$F13=CF$4,Radar_Mosca!$T13<>"Sì"),Radar_Mosca!$S13,NA()),NA()) -> #N/A | ... CL13: =IF(AND(ISNUMBER(Radar_Mosca!$F13),ISNUMBER(Radar_Mosca!$S13)),IF(AND(Radar_Mosca!$F13=CL$4,Radar_Mosca!$T13<>"Sì"),Radar_Mosca!$S13,NA()),NA()) -> #N/A | CM13: =IF(AND(ISNUMBER(Radar_Mosca!$F13),ISNUMBER(Radar_Mosca!$S13)),IF(AND(Radar_Mosca!$F13=CM$4,Radar_Mosca!$T13="Sì"),Radar_Mosca!$S13,NA()),NA()) -> #N/A | CN13: =IF(AND(ISNUMBER(Radar_Mosca!$F13),ISNUMBER(Radar_Mosca!$S13)),IF(AND(Radar_Mosca!$F13=CN$4,Radar_Mosca!$T13="Sì"),Radar_Mosca!$S13,NA()),NA()) -> #N/A | CO13: =IF(AND(ISNUMBER(Radar_Mosca!$F13),ISNUMBER(Radar_Mosca!$S13)),IF(AND(Radar_Mosca!$F13=CO$4,Radar_Mosca!$T13="Sì"),Radar_Mosca!$S13,NA()),NA()) -> #N/A | CP13: =IF(AND(ISNUMBER(Radar_Mosca!$F13),ISNUMBER(Radar_Mosca!$S13)),IF(AND(Radar_Mosca!$F13=CP$4,Radar_Mosca!$T13="Sì"),Radar_Mosca!$S13,NA()),NA()) -> #N/A | CQ13: =IF(AND(ISNUMBER(Radar_Mosca!$F13),ISNUMBER(Radar_Mosca!$S13)),IF(AND(Radar_Mosca!$F13=CQ$4,Radar_Mosca!$T13="Sì"),Radar_Mosca!$S13,NA()),NA()) -> #N/A | CR13: =IF(AND(ISNUMBER(Radar_Mosca!$F13),ISNUMBER(Radar_Mosca!$S13)),IF(AND(Radar_Mosca!$F13=CR$4,Radar_Mosca!$T13="Sì"),Radar_Mosca!$S13,NA()),NA()) -> #N/A | CS13: =IF(AND(ISNUMBER(Radar_Mosca!$F13),ISNUMBER(Radar_Mosca!$S13)),IF(AND(Radar_Mosca!$F13=CS$4,Radar_Mosca!$T13="Sì"),Radar_Mosca!$S13,NA()),NA()) -> -3.25 | CT13: =IF(AND(ISNUMBER(Radar_Mosca!$F13),ISNUMBER(Radar_Mosca!$S13)),IF(AND(Radar_Mosca!$F13=CT$4,Radar_Mosca!$T13="Sì"),Radar_Mosca!$S13,NA()),NA()) -> #N/A | ... CZ13: =IF(AND(ISNUMBER(Radar_Mosca!$F13),ISNUMBER(Radar_Mosca!$S13)),IF(AND(Radar_Mosca!$F13=CZ$4,Radar_Mosca!$T13="Sì"),Radar_Mosca!$S13,NA()),NA()) -> #N/A | DA13: =IF(ISNUMBER(Radar_Mosca!$R13),Radar_Mosca!$R13,NA()) -> 3.9817325e-16 | DB13: =IF(Radar_Mosca!$A13="","",MID(Radar_Mosca!$A13,5,3)) -> 09 | DC13: =IF(ISNUMBER(Radar_Mosca!$S13),Radar_Mosca!$S13,NA()) -> -3.25
A14: =Classifica!$A$9 -> 5 | B14: =IF(Classifica!$B$9="","",Classifica!$B$9&" "&Classifica!$C$9&IFERROR(IF(INDEX(ANA_Attenzione_Supervisore,Classifica!$U$9)="Sì"," ◆",""),"")) -> NFR-10 Informazioni errate ai clienti da assistenti di AI generativa | F14: =IF(Classifica!$B$9="","",Classifica!$D$9) -> 3.2 | G14: =IF(Classifica!$B$9="","",IF(ISNUMBER(Classifica!$F$9),Classifica!$F$9,"nuovo")) -> 0 | H14: =IF(Classifica!$B$9="","",IF(LEFT(Classifica!$H$9,9)="AGIRE ORA","AGIRE ORA",IF(LEFT(Classifica!$H$9,11)="Agire entro","Entro l'anno",Classifica!$H$9))) -> Margine 1 anno | J14: 1 | K14: =SUBSTITUTE(SUBSTITUTE(Matrice!C9," ◆",""),"NFR-","") | L14: =SUBSTITUTE(SUBSTITUTE(Matrice!D9," ◆",""),"NFR-","") | M14: =SUBSTITUTE(SUBSTITUTE(Matrice!E9," ◆",""),"NFR-","") | N14: =SUBSTITUTE(SUBSTITUTE(Matrice!F9," ◆",""),"NFR-","") | O14: =SUBSTITUTE(SUBSTITUTE(Matrice!G9," ◆",""),"NFR-","") | T14: =IF(LEFT(Radar_Mosca!$L$14,9)="AGIRE ORA",Radar_Mosca!$A$14,"") | BH14: =2*PI()*9/72 -> 0.78539816 | BI14: =2*SIN($BH14) -> 1.4142136 | BJ14: =2*COS($BH14) -> 1.4142136 | BK14: =3*SIN($BH14) -> 2.1213203 | BL14: =3*COS($BH14) -> 2.1213203 | BM14: =4*SIN($BH14) -> 2.8284271 | BN14: =4*COS($BH14) -> 2.8284271 | BO14: =5*SIN($BH14) -> 3.5355339 | BP14: =5*COS($BH14) -> 3.5355339 | BR14: =6.3*SIN(2*PI()*4/ROWS(codiciL1)) -> -2.7334676 | BS14: =6.3*COS(2*PI()*4/ROWS(codiciL1)) -> -5.6761039 | BY14: =IF(AND(ISNUMBER(Radar_Mosca!$F14),ISNUMBER(Radar_Mosca!$S14)),IF(AND(Radar_Mosca!$F14=BY$4,Radar_Mosca!$T14<>"Sì"),Radar_Mosca!$S14,NA()),NA()) -> #N/A | BZ14: =IF(AND(ISNUMBER(Radar_Mosca!$F14),ISNUMBER(Radar_Mosca!$S14)),IF(AND(Radar_Mosca!$F14=BZ$4,Radar_Mosca!$T14<>"Sì"),Radar_Mosca!$S14,NA()),NA()) -> #N/A | CA14: =IF(AND(ISNUMBER(Radar_Mosca!$F14),ISNUMBER(Radar_Mosca!$S14)),IF(AND(Radar_Mosca!$F14=CA$4,Radar_Mosca!$T14<>"Sì"),Radar_Mosca!$S14,NA()),NA()) -> #N/A | CB14: =IF(AND(ISNUMBER(Radar_Mosca!$F14),ISNUMBER(Radar_Mosca!$S14)),IF(AND(Radar_Mosca!$F14=CB$4,Radar_Mosca!$T14<>"Sì"),Radar_Mosca!$S14,NA()),NA()) -> #N/A | CC14: =IF(AND(ISNUMBER(Radar_Mosca!$F14),ISNUMBER(Radar_Mosca!$S14)),IF(AND(Radar_Mosca!$F14=CC$4,Radar_Mosca!$T14<>"Sì"),Radar_Mosca!$S14,NA()),NA()) -> #N/A | CD14: =IF(AND(ISNUMBER(Radar_Mosca!$F14),ISNUMBER(Radar_Mosca!$S14)),IF(AND(Radar_Mosca!$F14=CD$4,Radar_Mosca!$T14<>"Sì"),Radar_Mosca!$S14,NA()),NA()) -> #N/A | CE14: =IF(AND(ISNUMBER(Radar_Mosca!$F14),ISNUMBER(Radar_Mosca!$S14)),IF(AND(Radar_Mosca!$F14=CE$4,Radar_Mosca!$T14<>"Sì"),Radar_Mosca!$S14,NA()),NA()) -> #N/A | CF14: =IF(AND(ISNUMBER(Radar_Mosca!$F14),ISNUMBER(Radar_Mosca!$S14)),IF(AND(Radar_Mosca!$F14=CF$4,Radar_Mosca!$T14<>"Sì"),Radar_Mosca!$S14,NA()),NA()) -> -2.8667184 | ... CL14: =IF(AND(ISNUMBER(Radar_Mosca!$F14),ISNUMBER(Radar_Mosca!$S14)),IF(AND(Radar_Mosca!$F14=CL$4,Radar_Mosca!$T14<>"Sì"),Radar_Mosca!$S14,NA()),NA()) -> #N/A | CM14: =IF(AND(ISNUMBER(Radar_Mosca!$F14),ISNUMBER(Radar_Mosca!$S14)),IF(AND(Radar_Mosca!$F14=CM$4,Radar_Mosca!$T14="Sì"),Radar_Mosca!$S14,NA()),NA()) -> #N/A | CN14: =IF(AND(ISNUMBER(Radar_Mosca!$F14),ISNUMBER(Radar_Mosca!$S14)),IF(AND(Radar_Mosca!$F14=CN$4,Radar_Mosca!$T14="Sì"),Radar_Mosca!$S14,NA()),NA()) -> #N/A | CO14: =IF(AND(ISNUMBER(Radar_Mosca!$F14),ISNUMBER(Radar_Mosca!$S14)),IF(AND(Radar_Mosca!$F14=CO$4,Radar_Mosca!$T14="Sì"),Radar_Mosca!$S14,NA()),NA()) -> #N/A | CP14: =IF(AND(ISNUMBER(Radar_Mosca!$F14),ISNUMBER(Radar_Mosca!$S14)),IF(AND(Radar_Mosca!$F14=CP$4,Radar_Mosca!$T14="Sì"),Radar_Mosca!$S14,NA()),NA()) -> #N/A | CQ14: =IF(AND(ISNUMBER(Radar_Mosca!$F14),ISNUMBER(Radar_Mosca!$S14)),IF(AND(Radar_Mosca!$F14=CQ$4,Radar_Mosca!$T14="Sì"),Radar_Mosca!$S14,NA()),NA()) -> #N/A | CR14: =IF(AND(ISNUMBER(Radar_Mosca!$F14),ISNUMBER(Radar_Mosca!$S14)),IF(AND(Radar_Mosca!$F14=CR$4,Radar_Mosca!$T14="Sì"),Radar_Mosca!$S14,NA()),NA()) -> #N/A | CS14: =IF(AND(ISNUMBER(Radar_Mosca!$F14),ISNUMBER(Radar_Mosca!$S14)),IF(AND(Radar_Mosca!$F14=CS$4,Radar_Mosca!$T14="Sì"),Radar_Mosca!$S14,NA()),NA()) -> #N/A | CT14: =IF(AND(ISNUMBER(Radar_Mosca!$F14),ISNUMBER(Radar_Mosca!$S14)),IF(AND(Radar_Mosca!$F14=CT$4,Radar_Mosca!$T14="Sì"),Radar_Mosca!$S14,NA()),NA()) -> #N/A | ... CZ14: =IF(AND(ISNUMBER(Radar_Mosca!$F14),ISNUMBER(Radar_Mosca!$S14)),IF(AND(Radar_Mosca!$F14=CZ$4,Radar_Mosca!$T14="Sì"),Radar_Mosca!$S14,NA()),NA()) -> #N/A | DA14: =IF(ISNUMBER(Radar_Mosca!$R14),Radar_Mosca!$R14,NA()) -> -0.88426552 | DB14: =IF(Radar_Mosca!$A14="","",MID(Radar_Mosca!$A14,5,3)) -> 10 | DC14: =IF(ISNUMBER(Radar_Mosca!$S14),Radar_Mosca!$S14,NA()) -> -2.8667184
A15: Score 1-5, 5 = peggiore; barra su scala fissa 0-5. Variazione sul ciclo precedente. | J15: Numeri = NFR-nn. Verde P x I fino a 6, ambra 8-12, rosso da 15. | T15: =IF(LEFT(Radar_Mosca!$L$15,9)="AGIRE ORA",Radar_Mosca!$A$15,"") -> NFR-11 | BH15: =2*PI()*10/72 -> 0.87266463 | BI15: =2*SIN($BH15) -> 1.5320889 | BJ15: =2*COS($BH15) -> 1.2855752 | BK15: =3*SIN($BH15) -> 2.2981333 | BL15: =3*COS($BH15) -> 1.9283628 | BM15: =4*SIN($BH15) -> 3.0641778 | BN15: =4*COS($BH15) -> 2.5711504 | BO15: =5*SIN($BH15) -> 3.8302222 | BP15: =5*COS($BH15) -> 3.213938 | BR15: 0 | BS15: 0 | BY15: =IF(AND(ISNUMBER(Radar_Mosca!$F15),ISNUMBER(Radar_Mosca!$S15)),IF(AND(Radar_Mosca!$F15=BY$4,Radar_Mosca!$T15<>"Sì"),Radar_Mosca!$S15,NA()),NA()) -> #N/A | BZ15: =IF(AND(ISNUMBER(Radar_Mosca!$F15),ISNUMBER(Radar_Mosca!$S15)),IF(AND(Radar_Mosca!$F15=BZ$4,Radar_Mosca!$T15<>"Sì"),Radar_Mosca!$S15,NA()),NA()) -> #N/A | CA15: =IF(AND(ISNUMBER(Radar_Mosca!$F15),ISNUMBER(Radar_Mosca!$S15)),IF(AND(Radar_Mosca!$F15=CA$4,Radar_Mosca!$T15<>"Sì"),Radar_Mosca!$S15,NA()),NA()) -> #N/A | CB15: =IF(AND(ISNUMBER(Radar_Mosca!$F15),ISNUMBER(Radar_Mosca!$S15)),IF(AND(Radar_Mosca!$F15=CB$4,Radar_Mosca!$T15<>"Sì"),Radar_Mosca!$S15,NA()),NA()) -> #N/A | CC15: =IF(AND(ISNUMBER(Radar_Mosca!$F15),ISNUMBER(Radar_Mosca!$S15)),IF(AND(Radar_Mosca!$F15=CC$4,Radar_Mosca!$T15<>"Sì"),Radar_Mosca!$S15,NA()),NA()) -> #N/A | CD15: =IF(AND(ISNUMBER(Radar_Mosca!$F15),ISNUMBER(Radar_Mosca!$S15)),IF(AND(Radar_Mosca!$F15=CD$4,Radar_Mosca!$T15<>"Sì"),Radar_Mosca!$S15,NA()),NA()) -> #N/A | CE15: =IF(AND(ISNUMBER(Radar_Mosca!$F15),ISNUMBER(Radar_Mosca!$S15)),IF(AND(Radar_Mosca!$F15=CE$4,Radar_Mosca!$T15<>"Sì"),Radar_Mosca!$S15,NA()),NA()) -> #N/A | CF15: =IF(AND(ISNUMBER(Radar_Mosca!$F15),ISNUMBER(Radar_Mosca!$S15)),IF(AND(Radar_Mosca!$F15=CF$4,Radar_Mosca!$T15<>"Sì"),Radar_Mosca!$S15,NA()),NA()) -> 0.3 | ... CL15: =IF(AND(ISNUMBER(Radar_Mosca!$F15),ISNUMBER(Radar_Mosca!$S15)),IF(AND(Radar_Mosca!$F15=CL$4,Radar_Mosca!$T15<>"Sì"),Radar_Mosca!$S15,NA()),NA()) -> #N/A | CM15: =IF(AND(ISNUMBER(Radar_Mosca!$F15),ISNUMBER(Radar_Mosca!$S15)),IF(AND(Radar_Mosca!$F15=CM$4,Radar_Mosca!$T15="Sì"),Radar_Mosca!$S15,NA()),NA()) -> #N/A | CN15: =IF(AND(ISNUMBER(Radar_Mosca!$F15),ISNUMBER(Radar_Mosca!$S15)),IF(AND(Radar_Mosca!$F15=CN$4,Radar_Mosca!$T15="Sì"),Radar_Mosca!$S15,NA()),NA()) -> #N/A | CO15: =IF(AND(ISNUMBER(Radar_Mosca!$F15),ISNUMBER(Radar_Mosca!$S15)),IF(AND(Radar_Mosca!$F15=CO$4,Radar_Mosca!$T15="Sì"),Radar_Mosca!$S15,NA()),NA()) -> #N/A | CP15: =IF(AND(ISNUMBER(Radar_Mosca!$F15),ISNUMBER(Radar_Mosca!$S15)),IF(AND(Radar_Mosca!$F15=CP$4,Radar_Mosca!$T15="Sì"),Radar_Mosca!$S15,NA()),NA()) -> #N/A | CQ15: =IF(AND(ISNUMBER(Radar_Mosca!$F15),ISNUMBER(Radar_Mosca!$S15)),IF(AND(Radar_Mosca!$F15=CQ$4,Radar_Mosca!$T15="Sì"),Radar_Mosca!$S15,NA()),NA()) -> #N/A | CR15: =IF(AND(ISNUMBER(Radar_Mosca!$F15),ISNUMBER(Radar_Mosca!$S15)),IF(AND(Radar_Mosca!$F15=CR$4,Radar_Mosca!$T15="Sì"),Radar_Mosca!$S15,NA()),NA()) -> #N/A | CS15: =IF(AND(ISNUMBER(Radar_Mosca!$F15),ISNUMBER(Radar_Mosca!$S15)),IF(AND(Radar_Mosca!$F15=CS$4,Radar_Mosca!$T15="Sì"),Radar_Mosca!$S15,NA()),NA()) -> #N/A | CT15: =IF(AND(ISNUMBER(Radar_Mosca!$F15),ISNUMBER(Radar_Mosca!$S15)),IF(AND(Radar_Mosca!$F15=CT$4,Radar_Mosca!$T15="Sì"),Radar_Mosca!$S15,NA()),NA()) -> #N/A | ... CZ15: =IF(AND(ISNUMBER(Radar_Mosca!$F15),ISNUMBER(Radar_Mosca!$S15)),IF(AND(Radar_Mosca!$F15=CZ$4,Radar_Mosca!$T15="Sì"),Radar_Mosca!$S15,NA()),NA()) -> #N/A | DA15: =IF(ISNUMBER(Radar_Mosca!$R15),Radar_Mosca!$R15,NA()) -> -0.51961524 | DB15: =IF(Radar_Mosca!$A15="","",MID(Radar_Mosca!$A15,5,3)) -> 11 | DC15: =IF(ISNUMBER(Radar_Mosca!$S15),Radar_Mosca!$S15,NA()) -> 0.3
T16: =IF(LEFT(Radar_Mosca!$L$16,9)="AGIRE ORA",Radar_Mosca!$A$16,"") | BH16: =2*PI()*11/72 -> 0.95993109 | BI16: =2*SIN($BH16) -> 1.6383041 | BJ16: =2*COS($BH16) -> 1.1471529 | BK16: =3*SIN($BH16) -> 2.4574561 | BL16: =3*COS($BH16) -> 1.7207293 | BM16: =4*SIN($BH16) -> 3.2766082 | BN16: =4*COS($BH16) -> 2.2943057 | BO16: =5*SIN($BH16) -> 4.0957602 | BP16: =5*COS($BH16) -> 2.8678822 | BR16: =6.3*SIN(2*PI()*5/ROWS(codiciL1)) -> -6.1420458 | BS16: =6.3*COS(2*PI()*5/ROWS(codiciL1)) -> -1.4018819 | BY16: =IF(AND(ISNUMBER(Radar_Mosca!$F16),ISNUMBER(Radar_Mosca!$S16)),IF(AND(Radar_Mosca!$F16=BY$4,Radar_Mosca!$T16<>"Sì"),Radar_Mosca!$S16,NA()),NA()) -> #N/A | BZ16: =IF(AND(ISNUMBER(Radar_Mosca!$F16),ISNUMBER(Radar_Mosca!$S16)),IF(AND(Radar_Mosca!$F16=BZ$4,Radar_Mosca!$T16<>"Sì"),Radar_Mosca!$S16,NA()),NA()) -> #N/A | CA16: =IF(AND(ISNUMBER(Radar_Mosca!$F16),ISNUMBER(Radar_Mosca!$S16)),IF(AND(Radar_Mosca!$F16=CA$4,Radar_Mosca!$T16<>"Sì"),Radar_Mosca!$S16,NA()),NA()) -> #N/A | CB16: =IF(AND(ISNUMBER(Radar_Mosca!$F16),ISNUMBER(Radar_Mosca!$S16)),IF(AND(Radar_Mosca!$F16=CB$4,Radar_Mosca!$T16<>"Sì"),Radar_Mosca!$S16,NA()),NA()) -> #N/A | CC16: =IF(AND(ISNUMBER(Radar_Mosca!$F16),ISNUMBER(Radar_Mosca!$S16)),IF(AND(Radar_Mosca!$F16=CC$4,Radar_Mosca!$T16<>"Sì"),Radar_Mosca!$S16,NA()),NA()) -> #N/A | CD16: =IF(AND(ISNUMBER(Radar_Mosca!$F16),ISNUMBER(Radar_Mosca!$S16)),IF(AND(Radar_Mosca!$F16=CD$4,Radar_Mosca!$T16<>"Sì"),Radar_Mosca!$S16,NA()),NA()) -> #N/A | CE16: =IF(AND(ISNUMBER(Radar_Mosca!$F16),ISNUMBER(Radar_Mosca!$S16)),IF(AND(Radar_Mosca!$F16=CE$4,Radar_Mosca!$T16<>"Sì"),Radar_Mosca!$S16,NA()),NA()) -> #N/A | CF16: =IF(AND(ISNUMBER(Radar_Mosca!$F16),ISNUMBER(Radar_Mosca!$S16)),IF(AND(Radar_Mosca!$F16=CF$4,Radar_Mosca!$T16<>"Sì"),Radar_Mosca!$S16,NA()),NA()) -> #N/A | ... CL16: =IF(AND(ISNUMBER(Radar_Mosca!$F16),ISNUMBER(Radar_Mosca!$S16)),IF(AND(Radar_Mosca!$F16=CL$4,Radar_Mosca!$T16<>"Sì"),Radar_Mosca!$S16,NA()),NA()) -> #N/A | CM16: =IF(AND(ISNUMBER(Radar_Mosca!$F16),ISNUMBER(Radar_Mosca!$S16)),IF(AND(Radar_Mosca!$F16=CM$4,Radar_Mosca!$T16="Sì"),Radar_Mosca!$S16,NA()),NA()) -> #N/A | CN16: =IF(AND(ISNUMBER(Radar_Mosca!$F16),ISNUMBER(Radar_Mosca!$S16)),IF(AND(Radar_Mosca!$F16=CN$4,Radar_Mosca!$T16="Sì"),Radar_Mosca!$S16,NA()),NA()) -> #N/A | CO16: =IF(AND(ISNUMBER(Radar_Mosca!$F16),ISNUMBER(Radar_Mosca!$S16)),IF(AND(Radar_Mosca!$F16=CO$4,Radar_Mosca!$T16="Sì"),Radar_Mosca!$S16,NA()),NA()) -> #N/A | CP16: =IF(AND(ISNUMBER(Radar_Mosca!$F16),ISNUMBER(Radar_Mosca!$S16)),IF(AND(Radar_Mosca!$F16=CP$4,Radar_Mosca!$T16="Sì"),Radar_Mosca!$S16,NA()),NA()) -> #N/A | CQ16: =IF(AND(ISNUMBER(Radar_Mosca!$F16),ISNUMBER(Radar_Mosca!$S16)),IF(AND(Radar_Mosca!$F16=CQ$4,Radar_Mosca!$T16="Sì"),Radar_Mosca!$S16,NA()),NA()) -> #N/A | CR16: =IF(AND(ISNUMBER(Radar_Mosca!$F16),ISNUMBER(Radar_Mosca!$S16)),IF(AND(Radar_Mosca!$F16=CR$4,Radar_Mosca!$T16="Sì"),Radar_Mosca!$S16,NA()),NA()) -> #N/A | CS16: =IF(AND(ISNUMBER(Radar_Mosca!$F16),ISNUMBER(Radar_Mosca!$S16)),IF(AND(Radar_Mosca!$F16=CS$4,Radar_Mosca!$T16="Sì"),Radar_Mosca!$S16,NA()),NA()) -> #N/A | CT16: =IF(AND(ISNUMBER(Radar_Mosca!$F16),ISNUMBER(Radar_Mosca!$S16)),IF(AND(Radar_Mosca!$F16=CT$4,Radar_Mosca!$T16="Sì"),Radar_Mosca!$S16,NA()),NA()) -> #N/A | ... CZ16: =IF(AND(ISNUMBER(Radar_Mosca!$F16),ISNUMBER(Radar_Mosca!$S16)),IF(AND(Radar_Mosca!$F16=CZ$4,Radar_Mosca!$T16="Sì"),Radar_Mosca!$S16,NA()),NA()) -> #N/A | DA16: =IF(ISNUMBER(Radar_Mosca!$R16),Radar_Mosca!$R16,NA()) -> -0.44504187 | DB16: =IF(Radar_Mosca!$A16="","",MID(Radar_Mosca!$A16,5,3)) -> 12 | DC16: =IF(ISNUMBER(Radar_Mosca!$S16),Radar_Mosca!$S16,NA()) -> 1.9498558
A17: Urgenza: radar di Mosca | J17: I rischi del ciclo | T17: =IF(LEFT(Radar_Mosca!$L$17,9)="AGIRE ORA",Radar_Mosca!$A$17,"") | BH17: =2*PI()*12/72 -> 1.0471976 | BI17: =2*SIN($BH17) -> 1.7320508 | BJ17: =2*COS($BH17) -> 1 | BK17: =3*SIN($BH17) -> 2.5980762 | BL17: =3*COS($BH17) -> 1.5 | BM17: =4*SIN($BH17) -> 3.4641016 | BN17: =4*COS($BH17) -> 2 | BO17: =5*SIN($BH17) -> 4.330127 | BP17: =5*COS($BH17) -> 2.5 | BR17: 0 | BS17: 0 | BY17: =IF(AND(ISNUMBER(Radar_Mosca!$F17),ISNUMBER(Radar_Mosca!$S17)),IF(AND(Radar_Mosca!$F17=BY$4,Radar_Mosca!$T17<>"Sì"),Radar_Mosca!$S17,NA()),NA()) -> #N/A | BZ17: =IF(AND(ISNUMBER(Radar_Mosca!$F17),ISNUMBER(Radar_Mosca!$S17)),IF(AND(Radar_Mosca!$F17=BZ$4,Radar_Mosca!$T17<>"Sì"),Radar_Mosca!$S17,NA()),NA()) -> #N/A | CA17: =IF(AND(ISNUMBER(Radar_Mosca!$F17),ISNUMBER(Radar_Mosca!$S17)),IF(AND(Radar_Mosca!$F17=CA$4,Radar_Mosca!$T17<>"Sì"),Radar_Mosca!$S17,NA()),NA()) -> #N/A | CB17: =IF(AND(ISNUMBER(Radar_Mosca!$F17),ISNUMBER(Radar_Mosca!$S17)),IF(AND(Radar_Mosca!$F17=CB$4,Radar_Mosca!$T17<>"Sì"),Radar_Mosca!$S17,NA()),NA()) -> #N/A | CC17: =IF(AND(ISNUMBER(Radar_Mosca!$F17),ISNUMBER(Radar_Mosca!$S17)),IF(AND(Radar_Mosca!$F17=CC$4,Radar_Mosca!$T17<>"Sì"),Radar_Mosca!$S17,NA()),NA()) -> #N/A | CD17: =IF(AND(ISNUMBER(Radar_Mosca!$F17),ISNUMBER(Radar_Mosca!$S17)),IF(AND(Radar_Mosca!$F17=CD$4,Radar_Mosca!$T17<>"Sì"),Radar_Mosca!$S17,NA()),NA()) -> #N/A | CE17: =IF(AND(ISNUMBER(Radar_Mosca!$F17),ISNUMBER(Radar_Mosca!$S17)),IF(AND(Radar_Mosca!$F17=CE$4,Radar_Mosca!$T17<>"Sì"),Radar_Mosca!$S17,NA()),NA()) -> #N/A | CF17: =IF(AND(ISNUMBER(Radar_Mosca!$F17),ISNUMBER(Radar_Mosca!$S17)),IF(AND(Radar_Mosca!$F17=CF$4,Radar_Mosca!$T17<>"Sì"),Radar_Mosca!$S17,NA()),NA()) -> #N/A | ... CL17: =IF(AND(ISNUMBER(Radar_Mosca!$F17),ISNUMBER(Radar_Mosca!$S17)),IF(AND(Radar_Mosca!$F17=CL$4,Radar_Mosca!$T17<>"Sì"),Radar_Mosca!$S17,NA()),NA()) -> #N/A | CM17: =IF(AND(ISNUMBER(Radar_Mosca!$F17),ISNUMBER(Radar_Mosca!$S17)),IF(AND(Radar_Mosca!$F17=CM$4,Radar_Mosca!$T17="Sì"),Radar_Mosca!$S17,NA()),NA()) -> #N/A | CN17: =IF(AND(ISNUMBER(Radar_Mosca!$F17),ISNUMBER(Radar_Mosca!$S17)),IF(AND(Radar_Mosca!$F17=CN$4,Radar_Mosca!$T17="Sì"),Radar_Mosca!$S17,NA()),NA()) -> #N/A | CO17: =IF(AND(ISNUMBER(Radar_Mosca!$F17),ISNUMBER(Radar_Mosca!$S17)),IF(AND(Radar_Mosca!$F17=CO$4,Radar_Mosca!$T17="Sì"),Radar_Mosca!$S17,NA()),NA()) -> #N/A | CP17: =IF(AND(ISNUMBER(Radar_Mosca!$F17),ISNUMBER(Radar_Mosca!$S17)),IF(AND(Radar_Mosca!$F17=CP$4,Radar_Mosca!$T17="Sì"),Radar_Mosca!$S17,NA()),NA()) -> #N/A | CQ17: =IF(AND(ISNUMBER(Radar_Mosca!$F17),ISNUMBER(Radar_Mosca!$S17)),IF(AND(Radar_Mosca!$F17=CQ$4,Radar_Mosca!$T17="Sì"),Radar_Mosca!$S17,NA()),NA()) -> #N/A | CR17: =IF(AND(ISNUMBER(Radar_Mosca!$F17),ISNUMBER(Radar_Mosca!$S17)),IF(AND(Radar_Mosca!$F17=CR$4,Radar_Mosca!$T17="Sì"),Radar_Mosca!$S17,NA()),NA()) -> #N/A | CS17: =IF(AND(ISNUMBER(Radar_Mosca!$F17),ISNUMBER(Radar_Mosca!$S17)),IF(AND(Radar_Mosca!$F17=CS$4,Radar_Mosca!$T17="Sì"),Radar_Mosca!$S17,NA()),NA()) -> #N/A | CT17: =IF(AND(ISNUMBER(Radar_Mosca!$F17),ISNUMBER(Radar_Mosca!$S17)),IF(AND(Radar_Mosca!$F17=CT$4,Radar_Mosca!$T17="Sì"),Radar_Mosca!$S17,NA()),NA()) -> #N/A | ... CZ17: =IF(AND(ISNUMBER(Radar_Mosca!$F17),ISNUMBER(Radar_Mosca!$S17)),IF(AND(Radar_Mosca!$F17=CZ$4,Radar_Mosca!$T17="Sì"),Radar_Mosca!$S17,NA()),NA()) -> #N/A | DA17: =IF(ISNUMBER(Radar_Mosca!$R17),Radar_Mosca!$R17,NA()) -> #N/A | DB17: =IF(Radar_Mosca!$A17="","",MID(Radar_Mosca!$A17,5,3)) | DC17: =IF(ISNUMBER(Radar_Mosca!$S17),Radar_Mosca!$S17,NA()) -> #N/A
J18: =INDEX(posID,1)&"" -> NFR-01 | K18: =IF(J18="","",INDEX(posNome,1)&IF(INDEX(ANA_Attenzione_Supervisore,1)="Sì"," ◆","")) -> Frodi su pagamenti istantanei abilitate da AI generativa ◆ | T18: =IF(LEFT(Radar_Mosca!$L$18,9)="AGIRE ORA",Radar_Mosca!$A$18,"") | BH18: =2*PI()*13/72 -> 1.134464 | BI18: =2*SIN($BH18) -> 1.8126156 | BJ18: =2*COS($BH18) -> 0.84523652 | BK18: =3*SIN($BH18) -> 2.7189234 | BL18: =3*COS($BH18) -> 1.2678548 | BM18: =4*SIN($BH18) -> 3.6252311 | BN18: =4*COS($BH18) -> 1.690473 | BO18: =5*SIN($BH18) -> 4.5315389 | BP18: =5*COS($BH18) -> 2.1130913 | BR18: =6.3*SIN(2*PI()*6/ROWS(codiciL1)) -> -4.9255383 | BS18: =6.3*COS(2*PI()*6/ROWS(codiciL1)) -> 3.9279858 | BY18: =IF(AND(ISNUMBER(Radar_Mosca!$F18),ISNUMBER(Radar_Mosca!$S18)),IF(AND(Radar_Mosca!$F18=BY$4,Radar_Mosca!$T18<>"Sì"),Radar_Mosca!$S18,NA()),NA()) -> #N/A | BZ18: =IF(AND(ISNUMBER(Radar_Mosca!$F18),ISNUMBER(Radar_Mosca!$S18)),IF(AND(Radar_Mosca!$F18=BZ$4,Radar_Mosca!$T18<>"Sì"),Radar_Mosca!$S18,NA()),NA()) -> #N/A | CA18: =IF(AND(ISNUMBER(Radar_Mosca!$F18),ISNUMBER(Radar_Mosca!$S18)),IF(AND(Radar_Mosca!$F18=CA$4,Radar_Mosca!$T18<>"Sì"),Radar_Mosca!$S18,NA()),NA()) -> #N/A | CB18: =IF(AND(ISNUMBER(Radar_Mosca!$F18),ISNUMBER(Radar_Mosca!$S18)),IF(AND(Radar_Mosca!$F18=CB$4,Radar_Mosca!$T18<>"Sì"),Radar_Mosca!$S18,NA()),NA()) -> #N/A | CC18: =IF(AND(ISNUMBER(Radar_Mosca!$F18),ISNUMBER(Radar_Mosca!$S18)),IF(AND(Radar_Mosca!$F18=CC$4,Radar_Mosca!$T18<>"Sì"),Radar_Mosca!$S18,NA()),NA()) -> #N/A | CD18: =IF(AND(ISNUMBER(Radar_Mosca!$F18),ISNUMBER(Radar_Mosca!$S18)),IF(AND(Radar_Mosca!$F18=CD$4,Radar_Mosca!$T18<>"Sì"),Radar_Mosca!$S18,NA()),NA()) -> #N/A | CE18: =IF(AND(ISNUMBER(Radar_Mosca!$F18),ISNUMBER(Radar_Mosca!$S18)),IF(AND(Radar_Mosca!$F18=CE$4,Radar_Mosca!$T18<>"Sì"),Radar_Mosca!$S18,NA()),NA()) -> #N/A | CF18: =IF(AND(ISNUMBER(Radar_Mosca!$F18),ISNUMBER(Radar_Mosca!$S18)),IF(AND(Radar_Mosca!$F18=CF$4,Radar_Mosca!$T18<>"Sì"),Radar_Mosca!$S18,NA()),NA()) -> #N/A | ... CL18: =IF(AND(ISNUMBER(Radar_Mosca!$F18),ISNUMBER(Radar_Mosca!$S18)),IF(AND(Radar_Mosca!$F18=CL$4,Radar_Mosca!$T18<>"Sì"),Radar_Mosca!$S18,NA()),NA()) -> #N/A | CM18: =IF(AND(ISNUMBER(Radar_Mosca!$F18),ISNUMBER(Radar_Mosca!$S18)),IF(AND(Radar_Mosca!$F18=CM$4,Radar_Mosca!$T18="Sì"),Radar_Mosca!$S18,NA()),NA()) -> #N/A | CN18: =IF(AND(ISNUMBER(Radar_Mosca!$F18),ISNUMBER(Radar_Mosca!$S18)),IF(AND(Radar_Mosca!$F18=CN$4,Radar_Mosca!$T18="Sì"),Radar_Mosca!$S18,NA()),NA()) -> #N/A | CO18: =IF(AND(ISNUMBER(Radar_Mosca!$F18),ISNUMBER(Radar_Mosca!$S18)),IF(AND(Radar_Mosca!$F18=CO$4,Radar_Mosca!$T18="Sì"),Radar_Mosca!$S18,NA()),NA()) -> #N/A | CP18: =IF(AND(ISNUMBER(Radar_Mosca!$F18),ISNUMBER(Radar_Mosca!$S18)),IF(AND(Radar_Mosca!$F18=CP$4,Radar_Mosca!$T18="Sì"),Radar_Mosca!$S18,NA()),NA()) -> #N/A | CQ18: =IF(AND(ISNUMBER(Radar_Mosca!$F18),ISNUMBER(Radar_Mosca!$S18)),IF(AND(Radar_Mosca!$F18=CQ$4,Radar_Mosca!$T18="Sì"),Radar_Mosca!$S18,NA()),NA()) -> #N/A | CR18: =IF(AND(ISNUMBER(Radar_Mosca!$F18),ISNUMBER(Radar_Mosca!$S18)),IF(AND(Radar_Mosca!$F18=CR$4,Radar_Mosca!$T18="Sì"),Radar_Mosca!$S18,NA()),NA()) -> #N/A | CS18: =IF(AND(ISNUMBER(Radar_Mosca!$F18),ISNUMBER(Radar_Mosca!$S18)),IF(AND(Radar_Mosca!$F18=CS$4,Radar_Mosca!$T18="Sì"),Radar_Mosca!$S18,NA()),NA()) -> #N/A | CT18: =IF(AND(ISNUMBER(Radar_Mosca!$F18),ISNUMBER(Radar_Mosca!$S18)),IF(AND(Radar_Mosca!$F18=CT$4,Radar_Mosca!$T18="Sì"),Radar_Mosca!$S18,NA()),NA()) -> #N/A | ... CZ18: =IF(AND(ISNUMBER(Radar_Mosca!$F18),ISNUMBER(Radar_Mosca!$S18)),IF(AND(Radar_Mosca!$F18=CZ$4,Radar_Mosca!$T18="Sì"),Radar_Mosca!$S18,NA()),NA()) -> #N/A | DA18: =IF(ISNUMBER(Radar_Mosca!$R18),Radar_Mosca!$R18,NA()) -> #N/A | DB18: =IF(Radar_Mosca!$A18="","",MID(Radar_Mosca!$A18,5,3)) | DC18: =IF(ISNUMBER(Radar_Mosca!$S18),Radar_Mosca!$S18,NA()) -> #N/A
J19: =INDEX(posID,2)&"" -> NFR-02 | K19: =IF(J19="","",INDEX(posNome,2)&IF(INDEX(ANA_Attenzione_Supervisore,2)="Sì"," ◆","")) -> Concentrazione su un fornitore cloud critico ◆ | T19: =IF(LEFT(Radar_Mosca!$L$19,9)="AGIRE ORA",Radar_Mosca!$A$19,"") | BH19: =2*PI()*14/72 -> 1.2217305 | BI19: =2*SIN($BH19) -> 1.8793852 | BJ19: =2*COS($BH19) -> 0.68404029 | BK19: =3*SIN($BH19) -> 2.8190779 | BL19: =3*COS($BH19) -> 1.0260604 | BM19: =4*SIN($BH19) -> 3.7587705 | BN19: =4*COS($BH19) -> 1.3680806 | BO19: =5*SIN($BH19) -> 4.6984631 | BP19: =5*COS($BH19) -> 1.7101007 | BY19: =IF(AND(ISNUMBER(Radar_Mosca!$F19),ISNUMBER(Radar_Mosca!$S19)),IF(AND(Radar_Mosca!$F19=BY$4,Radar_Mosca!$T19<>"Sì"),Radar_Mosca!$S19,NA()),NA()) -> #N/A | BZ19: =IF(AND(ISNUMBER(Radar_Mosca!$F19),ISNUMBER(Radar_Mosca!$S19)),IF(AND(Radar_Mosca!$F19=BZ$4,Radar_Mosca!$T19<>"Sì"),Radar_Mosca!$S19,NA()),NA()) -> #N/A | CA19: =IF(AND(ISNUMBER(Radar_Mosca!$F19),ISNUMBER(Radar_Mosca!$S19)),IF(AND(Radar_Mosca!$F19=CA$4,Radar_Mosca!$T19<>"Sì"),Radar_Mosca!$S19,NA()),NA()) -> #N/A | CB19: =IF(AND(ISNUMBER(Radar_Mosca!$F19),ISNUMBER(Radar_Mosca!$S19)),IF(AND(Radar_Mosca!$F19=CB$4,Radar_Mosca!$T19<>"Sì"),Radar_Mosca!$S19,NA()),NA()) -> #N/A | CC19: =IF(AND(ISNUMBER(Radar_Mosca!$F19),ISNUMBER(Radar_Mosca!$S19)),IF(AND(Radar_Mosca!$F19=CC$4,Radar_Mosca!$T19<>"Sì"),Radar_Mosca!$S19,NA()),NA()) -> #N/A | CD19: =IF(AND(ISNUMBER(Radar_Mosca!$F19),ISNUMBER(Radar_Mosca!$S19)),IF(AND(Radar_Mosca!$F19=CD$4,Radar_Mosca!$T19<>"Sì"),Radar_Mosca!$S19,NA()),NA()) -> #N/A | CE19: =IF(AND(ISNUMBER(Radar_Mosca!$F19),ISNUMBER(Radar_Mosca!$S19)),IF(AND(Radar_Mosca!$F19=CE$4,Radar_Mosca!$T19<>"Sì"),Radar_Mosca!$S19,NA()),NA()) -> #N/A | CF19: =IF(AND(ISNUMBER(Radar_Mosca!$F19),ISNUMBER(Radar_Mosca!$S19)),IF(AND(Radar_Mosca!$F19=CF$4,Radar_Mosca!$T19<>"Sì"),Radar_Mosca!$S19,NA()),NA()) -> #N/A | ... CL19: =IF(AND(ISNUMBER(Radar_Mosca!$F19),ISNUMBER(Radar_Mosca!$S19)),IF(AND(Radar_Mosca!$F19=CL$4,Radar_Mosca!$T19<>"Sì"),Radar_Mosca!$S19,NA()),NA()) -> #N/A | CM19: =IF(AND(ISNUMBER(Radar_Mosca!$F19),ISNUMBER(Radar_Mosca!$S19)),IF(AND(Radar_Mosca!$F19=CM$4,Radar_Mosca!$T19="Sì"),Radar_Mosca!$S19,NA()),NA()) -> #N/A | CN19: =IF(AND(ISNUMBER(Radar_Mosca!$F19),ISNUMBER(Radar_Mosca!$S19)),IF(AND(Radar_Mosca!$F19=CN$4,Radar_Mosca!$T19="Sì"),Radar_Mosca!$S19,NA()),NA()) -> #N/A | CO19: =IF(AND(ISNUMBER(Radar_Mosca!$F19),ISNUMBER(Radar_Mosca!$S19)),IF(AND(Radar_Mosca!$F19=CO$4,Radar_Mosca!$T19="Sì"),Radar_Mosca!$S19,NA()),NA()) -> #N/A | CP19: =IF(AND(ISNUMBER(Radar_Mosca!$F19),ISNUMBER(Radar_Mosca!$S19)),IF(AND(Radar_Mosca!$F19=CP$4,Radar_Mosca!$T19="Sì"),Radar_Mosca!$S19,NA()),NA()) -> #N/A | CQ19: =IF(AND(ISNUMBER(Radar_Mosca!$F19),ISNUMBER(Radar_Mosca!$S19)),IF(AND(Radar_Mosca!$F19=CQ$4,Radar_Mosca!$T19="Sì"),Radar_Mosca!$S19,NA()),NA()) -> #N/A | CR19: =IF(AND(ISNUMBER(Radar_Mosca!$F19),ISNUMBER(Radar_Mosca!$S19)),IF(AND(Radar_Mosca!$F19=CR$4,Radar_Mosca!$T19="Sì"),Radar_Mosca!$S19,NA()),NA()) -> #N/A | CS19: =IF(AND(ISNUMBER(Radar_Mosca!$F19),ISNUMBER(Radar_Mosca!$S19)),IF(AND(Radar_Mosca!$F19=CS$4,Radar_Mosca!$T19="Sì"),Radar_Mosca!$S19,NA()),NA()) -> #N/A | CT19: =IF(AND(ISNUMBER(Radar_Mosca!$F19),ISNUMBER(Radar_Mosca!$S19)),IF(AND(Radar_Mosca!$F19=CT$4,Radar_Mosca!$T19="Sì"),Radar_Mosca!$S19,NA()),NA()) -> #N/A | ... CZ19: =IF(AND(ISNUMBER(Radar_Mosca!$F19),ISNUMBER(Radar_Mosca!$S19)),IF(AND(Radar_Mosca!$F19=CZ$4,Radar_Mosca!$T19="Sì"),Radar_Mosca!$S19,NA()),NA()) -> #N/A | DA19: =IF(ISNUMBER(Radar_Mosca!$R19),Radar_Mosca!$R19,NA()) -> #N/A | DB19: =IF(Radar_Mosca!$A19="","",MID(Radar_Mosca!$A19,5,3)) | DC19: =IF(ISNUMBER(Radar_Mosca!$S19),Radar_Mosca!$S19,NA()) -> #N/A
J20: =INDEX(posID,3)&"" -> NFR-03 | K20: =IF(J20="","",INDEX(posNome,3)&IF(INDEX(ANA_Attenzione_Supervisore,3)="Sì"," ◆","")) -> Greenwashing nella commercializzazione di prodotti ESG | BH20: =2*PI()*15/72 -> 1.3089969 | BI20: =2*SIN($BH20) -> 1.9318517 | BJ20: =2*COS($BH20) -> 0.51763809 | BK20: =3*SIN($BH20) -> 2.8977775 | BL20: =3*COS($BH20) -> 0.77645714 | BM20: =4*SIN($BH20) -> 3.8637033 | BN20: =4*COS($BH20) -> 1.0352762 | BO20: =5*SIN($BH20) -> 4.8296291 | BP20: =5*COS($BH20) -> 1.2940952
J21: =INDEX(posID,4)&"" -> NFR-04 | K21: =IF(J21="","",INDEX(posNome,4)&IF(INDEX(ANA_Attenzione_Supervisore,4)="Sì"," ◆","")) -> Eventi climatici estremi su sedi e data center | BH21: =2*PI()*16/72 -> 1.3962634 | BI21: =2*SIN($BH21) -> 1.9696155 | BJ21: =2*COS($BH21) -> 0.34729636 | BK21: =3*SIN($BH21) -> 2.9544233 | BL21: =3*COS($BH21) -> 0.52094453 | BM21: =4*SIN($BH21) -> 3.939231 | BN21: =4*COS($BH21) -> 0.69459271 | BO21: =5*SIN($BH21) -> 4.9240388 | BP21: =5*COS($BH21) -> 0.86824089
J22: =INDEX(posID,5)&"" -> NFR-05 | K22: =IF(J22="","",INDEX(posNome,5)&IF(INDEX(ANA_Attenzione_Supervisore,5)="Sì"," ◆","")) -> Errori di processo nella migrazione del core banking | BH22: =2*PI()*17/72 -> 1.4835299 | BI22: =2*SIN($BH22) -> 1.9923894 | BJ22: =2*COS($BH22) -> 0.17431149 | BK22: =3*SIN($BH22) -> 2.9885841 | BL22: =3*COS($BH22) -> 0.26146723 | BM22: =4*SIN($BH22) -> 3.9847788 | BN22: =4*COS($BH22) -> 0.34862297 | BO22: =5*SIN($BH22) -> 4.9809735 | BP22: =5*COS($BH22) -> 0.43577871
J23: =INDEX(posID,6)&"" -> NFR-06 | K23: =IF(J23="","",INDEX(posNome,6)&IF(INDEX(ANA_Attenzione_Supervisore,6)="Sì"," ◆","")) -> Esfiltrazione di dati tramite strumenti di AI non autorizzati | BH23: =2*PI()*18/72 -> 1.5707963 | BI23: =2*SIN($BH23) -> 2 | BJ23: =2*COS($BH23) -> 1.2251485e-16 | BK23: =3*SIN($BH23) -> 3 | BL23: =3*COS($BH23) -> 1.8377227e-16 | BM23: =4*SIN($BH23) -> 4 | BN23: =4*COS($BH23) -> 2.4502969e-16 | BO23: =5*SIN($BH23) -> 5 | BP23: =5*COS($BH23) -> 3.0628711e-16
J24: =INDEX(posID,7)&"" -> NFR-07 | K24: =IF(J24="","",INDEX(posNome,7)&IF(INDEX(ANA_Attenzione_Supervisore,7)="Sì"," ◆","")) -> Ransomware presso un fornitore di servizi di pagamento ◆ | BH24: =2*PI()*19/72 -> 1.6580628 | BI24: =2*SIN($BH24) -> 1.9923894 | BJ24: =2*COS($BH24) -> -0.17431149 | BK24: =3*SIN($BH24) -> 2.9885841 | BL24: =3*COS($BH24) -> -0.26146723 | BM24: =4*SIN($BH24) -> 3.9847788 | BN24: =4*COS($BH24) -> -0.34862297 | BO24: =5*SIN($BH24) -> 4.9809735 | BP24: =5*COS($BH24) -> -0.43577871
J25: =INDEX(posID,8)&"" -> NFR-08 | K25: =IF(J25="","",INDEX(posNome,8)&IF(INDEX(ANA_Attenzione_Supervisore,8)="Sì"," ◆","")) -> Accessi impropri di dipendenti ai dati dei clienti | BH25: =2*PI()*20/72 -> 1.7453293 | BI25: =2*SIN($BH25) -> 1.9696155 | BJ25: =2*COS($BH25) -> -0.34729636 | BK25: =3*SIN($BH25) -> 2.9544233 | BL25: =3*COS($BH25) -> -0.52094453 | BM25: =4*SIN($BH25) -> 3.939231 | BN25: =4*COS($BH25) -> -0.69459271 | BO25: =5*SIN($BH25) -> 4.9240388 | BP25: =5*COS($BH25) -> -0.86824089
J26: =INDEX(posID,9)&"" -> NFR-09 | K26: =IF(J26="","",INDEX(posNome,9)&IF(INDEX(ANA_Attenzione_Supervisore,9)="Sì"," ◆","")) -> Violazione di sanzioni internazionali tramite triangolazioni ◆ | BH26: =2*PI()*21/72 -> 1.8325957 | BI26: =2*SIN($BH26) -> 1.9318517 | BJ26: =2*COS($BH26) -> -0.51763809 | BK26: =3*SIN($BH26) -> 2.8977775 | BL26: =3*COS($BH26) -> -0.77645714 | BM26: =4*SIN($BH26) -> 3.8637033 | BN26: =4*COS($BH26) -> -1.0352762 | BO26: =5*SIN($BH26) -> 4.8296291 | BP26: =5*COS($BH26) -> -1.2940952
J27: =INDEX(posID,10)&"" -> NFR-10 | K27: =IF(J27="","",INDEX(posNome,10)&IF(INDEX(ANA_Attenzione_Supervisore,10)="Sì"," ◆","")) -> Informazioni errate ai clienti da assistenti di AI generativa | BH27: =2*PI()*22/72 -> 1.9198622 | BI27: =2*SIN($BH27) -> 1.8793852 | BJ27: =2*COS($BH27) -> -0.68404029 | BK27: =3*SIN($BH27) -> 2.8190779 | BL27: =3*COS($BH27) -> -1.0260604 | BM27: =4*SIN($BH27) -> 3.7587705 | BN27: =4*COS($BH27) -> -1.3680806 | BO27: =5*SIN($BH27) -> 4.6984631 | BP27: =5*COS($BH27) -> -1.7101007
J28: =INDEX(posID,11)&"" -> NFR-11 | K28: =IF(J28="","",INDEX(posNome,11)&IF(INDEX(ANA_Attenzione_Supervisore,11)="Sì"," ◆","")) -> Fine del supporto dei sistemi di pagamento legacy | BH28: =2*PI()*23/72 -> 2.0071286 | BI28: =2*SIN($BH28) -> 1.8126156 | BJ28: =2*COS($BH28) -> -0.84523652 | BK28: =3*SIN($BH28) -> 2.7189234 | BL28: =3*COS($BH28) -> -1.2678548 | BM28: =4*SIN($BH28) -> 3.6252311 | BN28: =4*COS($BH28) -> -1.690473 | BO28: =5*SIN($BH28) -> 4.5315389 | BP28: =5*COS($BH28) -> -2.1130913
J29: =INDEX(posID,12)&"" -> NFR-12 | K29: =IF(J29="","",INDEX(posNome,12)&IF(INDEX(ANA_Attenzione_Supervisore,12)="Sì"," ◆","")) -> Errori operativi nei pagamenti istantanei obbligatori | BH29: =2*PI()*24/72 -> 2.0943951 | BI29: =2*SIN($BH29) -> 1.7320508 | BJ29: =2*COS($BH29) -> -1 | BK29: =3*SIN($BH29) -> 2.5980762 | BL29: =3*COS($BH29) -> -1.5 | BM29: =4*SIN($BH29) -> 3.4641016 | BN29: =4*COS($BH29) -> -2 | BO29: =5*SIN($BH29) -> 4.330127 | BP29: =5*COS($BH29) -> -2.5
J30: =INDEX(posID,13)&"" | K30: =IF(J30="","",INDEX(posNome,13)&IF(INDEX(ANA_Attenzione_Supervisore,13)="Sì"," ◆","")) | BH30: =2*PI()*25/72 -> 2.1816616 | BI30: =2*SIN($BH30) -> 1.6383041 | BJ30: =2*COS($BH30) -> -1.1471529 | BK30: =3*SIN($BH30) -> 2.4574561 | BL30: =3*COS($BH30) -> -1.7207293 | BM30: =4*SIN($BH30) -> 3.2766082 | BN30: =4*COS($BH30) -> -2.2943057 | BO30: =5*SIN($BH30) -> 4.0957602 | BP30: =5*COS($BH30) -> -2.8678822
J31: =INDEX(posID,14)&"" | K31: =IF(J31="","",INDEX(posNome,14)&IF(INDEX(ANA_Attenzione_Supervisore,14)="Sì"," ◆","")) | BH31: =2*PI()*26/72 -> 2.268928 | BI31: =2*SIN($BH31) -> 1.5320889 | BJ31: =2*COS($BH31) -> -1.2855752 | BK31: =3*SIN($BH31) -> 2.2981333 | BL31: =3*COS($BH31) -> -1.9283628 | BM31: =4*SIN($BH31) -> 3.0641778 | BN31: =4*COS($BH31) -> -2.5711504 | BO31: =5*SIN($BH31) -> 3.8302222 | BP31: =5*COS($BH31) -> -3.213938
J32: =INDEX(posID,15)&"" | K32: =IF(J32="","",INDEX(posNome,15)&IF(INDEX(ANA_Attenzione_Supervisore,15)="Sì"," ◆","")) | BH32: =2*PI()*27/72 -> 2.3561945 | BI32: =2*SIN($BH32) -> 1.4142136 | BJ32: =2*COS($BH32) -> -1.4142136 | BK32: =3*SIN($BH32) -> 2.1213203 | BL32: =3*COS($BH32) -> -2.1213203 | BM32: =4*SIN($BH32) -> 2.8284271 | BN32: =4*COS($BH32) -> -2.8284271 | BO32: =5*SIN($BH32) -> 3.5355339 | BP32: =5*COS($BH32) -> -3.5355339
A33: Radar: piu' vicino al centro = agire prima; area del cerchio = P x I; bordo giallo = attenzione del supervisore. Numeri nel radar = NFR-nn. | BH33: =2*PI()*28/72 -> 2.443461 | BI33: =2*SIN($BH33) -> 1.2855752 | BJ33: =2*COS($BH33) -> -1.5320889 | BK33: =3*SIN($BH33) -> 1.9283628 | BL33: =3*COS($BH33) -> -2.2981333 | BM33: =4*SIN($BH33) -> 2.5711504 | BN33: =4*COS($BH33) -> -3.0641778 | BO33: =5*SIN($BH33) -> 3.213938 | BP33: =5*COS($BH33) -> -3.8302222
BH34: =2*PI()*29/72 -> 2.5307274 | BI34: =2*SIN($BH34) -> 1.1471529 | BJ34: =2*COS($BH34) -> -1.6383041 | BK34: =3*SIN($BH34) -> 1.7207293 | BL34: =3*COS($BH34) -> -2.4574561 | BM34: =4*SIN($BH34) -> 2.2943057 | BN34: =4*COS($BH34) -> -3.2766082 | BO34: =5*SIN($BH34) -> 2.8678822 | BP34: =5*COS($BH34) -> -4.0957602
A35: Il commento dell'analisi (agente A1, scritto prima della validazione) | BH35: =2*PI()*30/72 -> 2.6179939 | BI35: =2*SIN($BH35) -> 1 | BJ35: =2*COS($BH35) -> -1.7320508 | BK35: =3*SIN($BH35) -> 1.5 | BL35: =3*COS($BH35) -> -2.5980762 | BM35: =4*SIN($BH35) -> 2 | BN35: =4*COS($BH35) -> -3.4641016 | BO35: =5*SIN($BH35) -> 2.5 | BP35: =5*COS($BH35) -> -4.330127
A36: Messaggio chiave | D36: =IF(T36="","Nessun commento registrato per il ciclo corrente.",TRIM(SUBSTITUTE(SUBSTITUTE(IF(T37>0,LEFT(T36,T37-1),T36),"MESSAGGIO:",""),"Messaggio:",""))) -> nel terzo trimestre 2026 il profilo complessivo resta stabile. Due rischi migliorano per effetto di controlli testati: la exit strategy dal fornitore cloud critico e' ora testata su tutti i servizi (NFR-02) e il DLP copre tutti i servizi di AI generativa (NFR-06). Peggiora la prossimita' del rischio di greenwashing (NFR-03) dopo la sanzione a una banca comparabile. Gli altri nove rischi sono confermati con le fonti del ciclo precedente, integrate dai dati del trimestre. | T36: =IFERROR(INDEX(SI_Sintesi_A1,MATCH(cicloCorrente,SI_Ciclo,0))&"","") -> MESSAGGIO: nel terzo trimestre 2026 il profilo complessivo resta stabile. Due rischi migliorano per effetto di controlli testati: la exit strategy dal fornitore cloud critico e' ora testata su tutti i servizi (NFR-02) e il DLP copre tutti i servizi di AI generativa (NFR-06). Peggiora la prossimita' del rischio di greenwashing (NFR-03) dopo la sanzione a una banca comparabile. Gli altri nove rischi sono confermati con le fonti del ciclo precedente, integrate dai dati del trimestre. DECISIONI: prendere atto della chiusura dei gap su NFR-02 e NFR-06 e chiedere alla Funzione Compliance la revisione dei claim ESG (NFR-03). | BH36: =2*PI()*31/72 -> 2.7052603 | BI36: =2*SIN($BH36) -> 0.84523652 | BJ36: =2*COS($BH36) -> -1.8126156 | BK36: =3*SIN($BH36) -> 1.2678548 | BL36: =3*COS($BH36) -> -2.7189234 | BM36: =4*SIN($BH36) -> 1.690473 | BN36: =4*COS($BH36) -> -3.6252311 | BO36: =5*SIN($BH36) -> 2.1130913 | BP36: =5*COS($BH36) -> -4.5315389
A37: Decisioni richieste | D37: =IF(T37>0,TRIM(MID(T36,T37+10,4000)),"—") -> prendere atto della chiusura dei gap su NFR-02 e NFR-06 e chiedere alla Funzione Compliance la revisione dei claim ESG (NFR-03). | T37: =IFERROR(SEARCH("DECISIONI:",T36),0) -> 487 | BH37: =2*PI()*32/72 -> 2.7925268 | BI37: =2*SIN($BH37) -> 0.68404029 | BJ37: =2*COS($BH37) -> -1.8793852 | BK37: =3*SIN($BH37) -> 1.0260604 | BL37: =3*COS($BH37) -> -2.8190779 | BM37: =4*SIN($BH37) -> 1.3680806 | BN37: =4*COS($BH37) -> -3.7587705 | BO37: =5*SIN($BH37) -> 1.7101007 | BP37: =5*COS($BH37) -> -4.6984631
A38: Controllo indipendente (A5) | D38: =IFERROR(INDEX(SI_Sintesi_A5,MATCH(cicloCorrente,SI_Ciclo,0))&"","")&IFERROR(" Osservazioni non bloccanti: "&INDEX(SI_Osservazioni_Controlli,MATCH(cicloCorrente,SI_Ciclo,0))&".","") -> Valutazione sostenuta dalle fonti citate. Le due riduzioni di Gap_Controlli poggiano su test documentati; l'aumento di prossimita' di NFR-03 su un caso nel settore. Un'osservazione di giudizio su NFR-06. Osservazioni non bloccanti: 1. | BH38: =2*PI()*33/72 -> 2.8797933 | BI38: =2*SIN($BH38) -> 0.51763809 | BJ38: =2*COS($BH38) -> -1.9318517 | BK38: =3*SIN($BH38) -> 0.77645714 | BL38: =3*COS($BH38) -> -2.8977775 | BM38: =4*SIN($BH38) -> 1.0352762 | BN38: =4*COS($BH38) -> -3.8637033 | BO38: =5*SIN($BH38) -> 1.2940952 | BP38: =5*COS($BH38) -> -4.8296291
A39: Dopo il commento | D39: =IF((COUNTIFS(VAL_Periodo,cicloCorrente,VAL_Stato,"Applicata",VAL_Decisione,"Rettificato")+COUNTIFS(VAL_Periodo,cicloCorrente,VAL_Stato,"Applicata",VAL_Decisione,"Respinto"))>0,"Il validatore ha applicato "&(COUNTIFS(VAL_Periodo,cicloCorrente,VAL_Stato,"Applicata",VAL_Decisione,"Rettificato")+COUNTIFS(VAL_Periodo,cicloCorrente,VAL_Stato,"Applicata",VAL_Decisione,"Respinto"))&" rettifiche o respingimenti: numeri e grafici del report sono quelli validati e prevalgono sul commento.","") -> Il validatore ha applicato 3 rettifiche o respingimenti: numeri e grafici del report sono quelli validati e prevalgono sul commento. | BH39: =2*PI()*34/72 -> 2.9670597 | BI39: =2*SIN($BH39) -> 0.34729636 | BJ39: =2*COS($BH39) -> -1.9696155 | BK39: =3*SIN($BH39) -> 0.52094453 | BL39: =3*COS($BH39) -> -2.9544233 | BM39: =4*SIN($BH39) -> 0.69459271 | BN39: =4*COS($BH39) -> -3.939231 | BO39: =5*SIN($BH39) -> 0.86824089 | BP39: =5*COS($BH39) -> -4.9240388
BH40: =2*PI()*35/72 -> 3.0543262 | BI40: =2*SIN($BH40) -> 0.17431149 | BJ40: =2*COS($BH40) -> -1.9923894 | BK40: =3*SIN($BH40) -> 0.26146723 | BL40: =3*COS($BH40) -> -2.9885841 | BM40: =4*SIN($BH40) -> 0.34862297 | BN40: =4*COS($BH40) -> -3.9847788 | BO40: =5*SIN($BH40) -> 0.43577871 | BP40: =5*COS($BH40) -> -4.9809735
A41: Rischi segnalati e perche' | BH41: =2*PI()*36/72 -> 3.1415927 | BI41: =2*SIN($BH41) -> 2.4502969e-16 | BJ41: =2*COS($BH41) -> -2 | BK41: =3*SIN($BH41) -> 3.6754454e-16 | BL41: =3*COS($BH41) -> -3 | BM41: =4*SIN($BH41) -> 4.9005938e-16 | BN41: =4*COS($BH41) -> -4 | BO41: =5*SIN($BH41) -> 6.1257423e-16 | BP41: =5*COS($BH41) -> -5
A42: Rischi fra i primi tre per score, da affrontare subito, variati o nuovi nel ciclo. Tutto calcolato dai dati validati del registro. | BH42: =2*PI()*37/72 -> 3.2288591 | BI42: =2*SIN($BH42) -> -0.17431149 | BJ42: =2*COS($BH42) -> -1.9923894 | BK42: =3*SIN($BH42) -> -0.26146723 | BL42: =3*COS($BH42) -> -2.9885841 | BM42: =4*SIN($BH42) -> -0.34862297 | BN42: =4*COS($BH42) -> -3.9847788 | BO42: =5*SIN($BH42) -> -0.43577871 | BP42: =5*COS($BH42) -> -4.9809735
A43: Rischio | D43: Urgenza | E43: Perche' lo segnaliamo | I43: Cosa e' cambiato, e su quale evidenza | BH43: =2*PI()*38/72 -> 3.3161256 | BI43: =2*SIN($BH43) -> -0.34729636 | BJ43: =2*COS($BH43) -> -1.9696155 | BK43: =3*SIN($BH43) -> -0.52094453 | BL43: =3*COS($BH43) -> -2.9544233 | BM43: =4*SIN($BH43) -> -0.69459271 | BN43: =4*COS($BH43) -> -3.939231 | BO43: =5*SIN($BH43) -> -0.86824089 | BP43: =5*COS($BH43) -> -4.9240388
A44: =IF($V44="","",INDEX(Classifica!$B$5:$B$19,$V44)&CHAR(10)&INDEX(Classifica!$C$5:$C$19,$V44)&IF(INDEX(ANA_Attenzione_Supervisore,INDEX(Classifica!$U$5:$U$19,$V44))="Sì",CHAR(10)&"◆ attenzione del supervisore","")) -> NFR-01 Frodi su pagamenti istantanei abilitate da AI generativa ◆ attenzione del supervisore | D44: =IF($V44="","",IF(LEFT(INDEX(Classifica!$H$5:$H$19,$V44),9)="AGIRE ORA","AGIRE ORA",IF(LEFT(INDEX(Classifica!$H$5:$H$19,$V44),11)="Agire entro","Entro l'anno",INDEX(Classifica!$H$5:$H$19,$V44)))) -> AGIRE ORA | E44: =IF($W44="","",LEFT($W44,LEN($W44)-2)&".") -> 1° per score composito (3,80); AGIRE ORA: servono X + Y = 0,75 anni per decidere e mitigare; ne restano Z = 0,5 prima che possa manifestarsi; tema all'attenzione del supervisore; notizie in peggioramento (+3 segnali netti in 4 settimane). | I44: =IF($V44="","",IF(INDEX(Classifica!$G$5:$G$19,$V44)="Nuovo","Rischio nuovo nel ciclo.",IFERROR(IF(INDEX(RR_Variazioni,MATCH(cicloCorrente&"|"&INDEX(Classifica!$B$5:$B$19,$V44),RR_Chiave,0))&""="[]","Nessun valore cambiato: confermato sulle fonti del ciclo precedente.",SUBSTITUTE(SUBSTITUTE(SUBSTITUTE(SUBSTITUTE(SUBSTITUTE(SUBSTITUTE(SUBSTITUTE(SUBSTITUTE(SUBSTITUTE(SUBSTITUTE(SUBSTITUTE(SUBSTITUTE(SUBSTITUTE(INDEX(RR_Variazioni,MATCH(cicloCorrente&"|"&INDEX(Classifica!$B$5:$B$19,$V44),RR_Chiave,0))&"","[{""dimensione"": ""","• "),"""}, {""dimensione"": """,")"&CHAR(10)&"• "),""", ""da"": "," "),", ""a"": "," → "),", ""evidenza"": """,": "),""", ""data_evidenza"": """," ("),"""}]",")"),"• severity","• Severity"),"• velocity","• Velocity"),"• prossimita","• Prossimita"),"• gap_controlli","• Gap_Controlli"),"• confidence","• Confidence"),"• probabilita","• Probabilita")),""))) -> Nessun valore cambiato: confermato sulle fonti del ciclo precedente. | U44: =IF(Classifica!$B$5="","",IF(OR(1<=3,LEFT(Classifica!$H$5,9)="AGIRE ORA",Classifica!$G$5="Variato",Classifica!$G$5="Nuovo"),1,"")) -> 1 | V44: =IFERROR(_xlfn.AGGREGATE(15,6,$U$44:$U$58,1),"") -> 1 | W44: =IF($V44="","",IF($V44<=3,$V44&"° per score composito ("&FIXED(INDEX(Classifica!$D$5:$D$19,$V44),2)&IF(ISNUMBER(INDEX(Classifica!$F$5:$F$19,$V44)),IF(INDEX(Classifica!$F$5:$F$19,$V44)<>0,", "&IF(INDEX(Classifica!$F$5:$F$19,$V44)>0,"+","")&FIXED(INDEX(Classifica!$F$5:$F$19,$V44),2)&" sul ciclo prima",""),"")&"); ","")&IF(LEFT(INDEX(Classifica!$H$5:$H$19,$V44),9)="AGIRE ORA","AGIRE ORA: servono X + Y = "&FIXED(INDEX(Classifica!$Y$5:$Y$19,$V44)+INDEX(Classifica!$Z$5:$Z$19,$V44),2)&" anni per decidere e mitigare"&IF(N(INDEX(ANA_Anni_Adeguamento,INDEX(Classifica!$U$5:$U$19,$V44)))>0,", di cui "&N(INDEX(ANA_Anni_Adeguamento,INDEX(Classifica!$U$5:$U$19,$V44)))&" di adeguamento strutturale","")&"; ne restano Z = "&FIXED(INDEX(Classifica!$AA$5:$AA$19,$V44),1)&" prima che possa manifestarsi; ",IF(AND($V44<=3,LEFT(INDEX(Classifica!$H$5:$H$19,$V44),11)="Agire entro"),"margine di Mosca sotto l'anno ("&FIXED(INDEX(Classifica!$I$5:$I$19,$V44),2)&"); ",""))&IF(INDEX(Classifica!$G$5:$G$19,$V44)="Variato","variato nel ciclo"&IF(ISNUMBER(INDEX(Classifica!$F$5:$F$19,$V44)),IF(INDEX(Classifica!$F$5:$F$19,$V44)>0,": peggiora",IF(INDEX(Classifica!$F$5:$F$19,$V44)<0,": migliora","")),"")&"; ",IF(INDEX(Classifica!$G$5:$G$19,$V44)="Nuovo","nuovo nel ciclo; ",""))&IF(INDEX(ANA_Attenzione_Supervisore,INDEX(Classifica!$U$5:$U$19,$V44))="Sì","tema all'attenzione del supervisore; ","")&IF(COUNTIFS(KRI_ID_Rischio,INDEX(Classifica!$B$5:$B$19,$V44),KRI_Ciclo,cicloCorrente,KRI_In_Vigore,"Sì",KRI_Stato,"Rosso")>0,COUNTIFS(KRI_ID_Rischio,INDEX(Classifica!$B$5:$B$19,$V44),KRI_Ciclo,cicloCorrente,KRI_In_Vigore,"Sì",KRI_Stato,"Rosso")&" KRI in rosso; ","")&IF(INDEX(posNetti,INDEX(Classifica!$U$5:$U$19,$V44))>=sogliaDirezione,"notizie in peggioramento (+"&INDEX(posNetti,INDEX(Classifica!$U$5:$U$19,$V44))&" segnali netti in 4 settimane); ",IF(INDEX(posNetti,INDEX(Classifica!$U$5:$U$19,$V44))<=-sogliaDirezione,"notizie in miglioramento ("&INDEX(posNetti,INDEX(Classifica!$U$5:$U$19,$V44))&" segnali netti in 4 settimane); ",""))) -> 1° per score composito (3,80); AGIRE ORA: servono X + Y = 0,75 anni per decidere e mitigare; ne restano Z = 0,5 prima che possa manifestarsi; tema all'attenzione del supervisore; notizie in peggioramento (+3 segnali netti in 4 settimane); | BH44: =2*PI()*39/72 -> 3.403392 | BI44: =2*SIN($BH44) -> -0.51763809 | BJ44: =2*COS($BH44) -> -1.9318517 | BK44: =3*SIN($BH44) -> -0.77645714 | BL44: =3*COS($BH44) -> -2.8977775 | BM44: =4*SIN($BH44) -> -1.0352762 | BN44: =4*COS($BH44) -> -3.8637033 | BO44: =5*SIN($BH44) -> -1.2940952 | BP44: =5*COS($BH44) -> -4.8296291
A45: =IF($V45="","",INDEX(Classifica!$B$5:$B$19,$V45)&CHAR(10)&INDEX(Classifica!$C$5:$C$19,$V45)&IF(INDEX(ANA_Attenzione_Supervisore,INDEX(Classifica!$U$5:$U$19,$V45))="Sì",CHAR(10)&"◆ attenzione del supervisore","")) -> NFR-07 Ransomware presso un fornitore di servizi di pagamento ◆ attenzione del supervisore | D45: =IF($V45="","",IF(LEFT(INDEX(Classifica!$H$5:$H$19,$V45),9)="AGIRE ORA","AGIRE ORA",IF(LEFT(INDEX(Classifica!$H$5:$H$19,$V45),11)="Agire entro","Entro l'anno",INDEX(Classifica!$H$5:$H$19,$V45)))) -> Entro l'anno | E45: =IF($W45="","",LEFT($W45,LEN($W45)-2)&".") -> 2° per score composito (3,60); margine di Mosca sotto l'anno (0,75); tema all'attenzione del supervisore. | I45: =IF($V45="","",IF(INDEX(Classifica!$G$5:$G$19,$V45)="Nuovo","Rischio nuovo nel ciclo.",IFERROR(IF(INDEX(RR_Variazioni,MATCH(cicloCorrente&"|"&INDEX(Classifica!$B$5:$B$19,$V45),RR_Chiave,0))&""="[]","Nessun valore cambiato: confermato sulle fonti del ciclo precedente.",SUBSTITUTE(SUBSTITUTE(SUBSTITUTE(SUBSTITUTE(SUBSTITUTE(SUBSTITUTE(SUBSTITUTE(SUBSTITUTE(SUBSTITUTE(SUBSTITUTE(SUBSTITUTE(SUBSTITUTE(SUBSTITUTE(INDEX(RR_Variazioni,MATCH(cicloCorrente&"|"&INDEX(Classifica!$B$5:$B$19,$V45),RR_Chiave,0))&"","[{""dimensione"": ""","• "),"""}, {""dimensione"": """,")"&CHAR(10)&"• "),""", ""da"": "," "),", ""a"": "," → "),", ""evidenza"": """,": "),""", ""data_evidenza"": """," ("),"""}]",")"),"• severity","• Severity"),"• velocity","• Velocity"),"• prossimita","• Prossimita"),"• gap_controlli","• Gap_Controlli"),"• confidence","• Confidence"),"• probabilita","• Probabilita")),""))) -> Nessun valore cambiato: confermato sulle fonti del ciclo precedente. | U45: =IF(Classifica!$B$6="","",IF(OR(2<=3,LEFT(Classifica!$H$6,9)="AGIRE ORA",Classifica!$G$6="Variato",Classifica!$G$6="Nuovo"),2,"")) -> 2 | V45: =IFERROR(_xlfn.AGGREGATE(15,6,$U$44:$U$58,2),"") -> 2 | W45: =IF($V45="","",IF($V45<=3,$V45&"° per score composito ("&FIXED(INDEX(Classifica!$D$5:$D$19,$V45),2)&IF(ISNUMBER(INDEX(Classifica!$F$5:$F$19,$V45)),IF(INDEX(Classifica!$F$5:$F$19,$V45)<>0,", "&IF(INDEX(Classifica!$F$5:$F$19,$V45)>0,"+","")&FIXED(INDEX(Classifica!$F$5:$F$19,$V45),2)&" sul ciclo prima",""),"")&"); ","")&IF(LEFT(INDEX(Classifica!$H$5:$H$19,$V45),9)="AGIRE ORA","AGIRE ORA: servono X + Y = "&FIXED(INDEX(Classifica!$Y$5:$Y$19,$V45)+INDEX(Classifica!$Z$5:$Z$19,$V45),2)&" anni per decidere e mitigare"&IF(N(INDEX(ANA_Anni_Adeguamento,INDEX(Classifica!$U$5:$U$19,$V45)))>0,", di cui "&N(INDEX(ANA_Anni_Adeguamento,INDEX(Classifica!$U$5:$U$19,$V45)))&" di adeguamento strutturale","")&"; ne restano Z = "&FIXED(INDEX(Classifica!$AA$5:$AA$19,$V45),1)&" prima che possa manifestarsi; ",IF(AND($V45<=3,LEFT(INDEX(Classifica!$H$5:$H$19,$V45),11)="Agire entro"),"margine di Mosca sotto l'anno ("&FIXED(INDEX(Classifica!$I$5:$I$19,$V45),2)&"); ",""))&IF(INDEX(Classifica!$G$5:$G$19,$V45)="Variato","variato nel ciclo"&IF(ISNUMBER(INDEX(Classifica!$F$5:$F$19,$V45)),IF(INDEX(Classifica!$F$5:$F$19,$V45)>0,": peggiora",IF(INDEX(Classifica!$F$5:$F$19,$V45)<0,": migliora","")),"")&"; ",IF(INDEX(Classifica!$G$5:$G$19,$V45)="Nuovo","nuovo nel ciclo; ",""))&IF(INDEX(ANA_Attenzione_Supervisore,INDEX(Classifica!$U$5:$U$19,$V45))="Sì","tema all'attenzione del supervisore; ","")&IF(COUNTIFS(KRI_ID_Rischio,INDEX(Classifica!$B$5:$B$19,$V45),KRI_Ciclo,cicloCorrente,KRI_In_Vigore,"Sì",KRI_Stato,"Rosso")>0,COUNTIFS(KRI_ID_Rischio,INDEX(Classifica!$B$5:$B$19,$V45),KRI_Ciclo,cicloCorrente,KRI_In_Vigore,"Sì",KRI_Stato,"Rosso")&" KRI in rosso; ","")&IF(INDEX(posNetti,INDEX(Classifica!$U$5:$U$19,$V45))>=sogliaDirezione,"notizie in peggioramento (+"&INDEX(posNetti,INDEX(Classifica!$U$5:$U$19,$V45))&" segnali netti in 4 settimane); ",IF(INDEX(posNetti,INDEX(Classifica!$U$5:$U$19,$V45))<=-sogliaDirezione,"notizie in miglioramento ("&INDEX(posNetti,INDEX(Classifica!$U$5:$U$19,$V45))&" segnali netti in 4 settimane); ",""))) -> 2° per score composito (3,60); margine di Mosca sotto l'anno (0,75); tema all'attenzione del supervisore; | BH45: =2*PI()*40/72 -> 3.4906585 | BI45: =2*SIN($BH45) -> -0.68404029 | BJ45: =2*COS($BH45) -> -1.8793852 | BK45: =3*SIN($BH45) -> -1.0260604 | BL45: =3*COS($BH45) -> -2.8190779 | BM45: =4*SIN($BH45) -> -1.3680806 | BN45: =4*COS($BH45) -> -3.7587705 | BO45: =5*SIN($BH45) -> -1.7101007 | BP45: =5*COS($BH45) -> -4.6984631
A46: =IF($V46="","",INDEX(Classifica!$B$5:$B$19,$V46)&CHAR(10)&INDEX(Classifica!$C$5:$C$19,$V46)&IF(INDEX(ANA_Attenzione_Supervisore,INDEX(Classifica!$U$5:$U$19,$V46))="Sì",CHAR(10)&"◆ attenzione del supervisore","")) -> NFR-12 Errori operativi nei pagamenti istantanei obbligatori | D46: =IF($V46="","",IF(LEFT(INDEX(Classifica!$H$5:$H$19,$V46),9)="AGIRE ORA","AGIRE ORA",IF(LEFT(INDEX(Classifica!$H$5:$H$19,$V46),11)="Agire entro","Entro l'anno",INDEX(Classifica!$H$5:$H$19,$V46)))) -> Entro l'anno | E46: =IF($W46="","",LEFT($W46,LEN($W46)-2)&".") -> 3° per score composito (3,50); margine di Mosca sotto l'anno (0,00). | I46: =IF($V46="","",IF(INDEX(Classifica!$G$5:$G$19,$V46)="Nuovo","Rischio nuovo nel ciclo.",IFERROR(IF(INDEX(RR_Variazioni,MATCH(cicloCorrente&"|"&INDEX(Classifica!$B$5:$B$19,$V46),RR_Chiave,0))&""="[]","Nessun valore cambiato: confermato sulle fonti del ciclo precedente.",SUBSTITUTE(SUBSTITUTE(SUBSTITUTE(SUBSTITUTE(SUBSTITUTE(SUBSTITUTE(SUBSTITUTE(SUBSTITUTE(SUBSTITUTE(SUBSTITUTE(SUBSTITUTE(SUBSTITUTE(SUBSTITUTE(INDEX(RR_Variazioni,MATCH(cicloCorrente&"|"&INDEX(Classifica!$B$5:$B$19,$V46),RR_Chiave,0))&"","[{""dimensione"": ""","• "),"""}, {""dimensione"": """,")"&CHAR(10)&"• "),""", ""da"": "," "),", ""a"": "," → "),", ""evidenza"": """,": "),""", ""data_evidenza"": """," ("),"""}]",")"),"• severity","• Severity"),"• velocity","• Velocity"),"• prossimita","• Prossimita"),"• gap_controlli","• Gap_Controlli"),"• confidence","• Confidence"),"• probabilita","• Probabilita")),""))) -> Nessun valore cambiato: confermato sulle fonti del ciclo precedente. | U46: =IF(Classifica!$B$7="","",IF(OR(3<=3,LEFT(Classifica!$H$7,9)="AGIRE ORA",Classifica!$G$7="Variato",Classifica!$G$7="Nuovo"),3,"")) -> 3 | V46: =IFERROR(_xlfn.AGGREGATE(15,6,$U$44:$U$58,3),"") -> 3 | W46: =IF($V46="","",IF($V46<=3,$V46&"° per score composito ("&FIXED(INDEX(Classifica!$D$5:$D$19,$V46),2)&IF(ISNUMBER(INDEX(Classifica!$F$5:$F$19,$V46)),IF(INDEX(Classifica!$F$5:$F$19,$V46)<>0,", "&IF(INDEX(Classifica!$F$5:$F$19,$V46)>0,"+","")&FIXED(INDEX(Classifica!$F$5:$F$19,$V46),2)&" sul ciclo prima",""),"")&"); ","")&IF(LEFT(INDEX(Classifica!$H$5:$H$19,$V46),9)="AGIRE ORA","AGIRE ORA: servono X + Y = "&FIXED(INDEX(Classifica!$Y$5:$Y$19,$V46)+INDEX(Classifica!$Z$5:$Z$19,$V46),2)&" anni per decidere e mitigare"&IF(N(INDEX(ANA_Anni_Adeguamento,INDEX(Classifica!$U$5:$U$19,$V46)))>0,", di cui "&N(INDEX(ANA_Anni_Adeguamento,INDEX(Classifica!$U$5:$U$19,$V46)))&" di adeguamento strutturale","")&"; ne restano Z = "&FIXED(INDEX(Classifica!$AA$5:$AA$19,$V46),1)&" prima che possa manifestarsi; ",IF(AND($V46<=3,LEFT(INDEX(Classifica!$H$5:$H$19,$V46),11)="Agire entro"),"margine di Mosca sotto l'anno ("&FIXED(INDEX(Classifica!$I$5:$I$19,$V46),2)&"); ",""))&IF(INDEX(Classifica!$G$5:$G$19,$V46)="Variato","variato nel ciclo"&IF(ISNUMBER(INDEX(Classifica!$F$5:$F$19,$V46)),IF(INDEX(Classifica!$F$5:$F$19,$V46)>0,": peggiora",IF(INDEX(Classifica!$F$5:$F$19,$V46)<0,": migliora","")),"")&"; ",IF(INDEX(Classifica!$G$5:$G$19,$V46)="Nuovo","nuovo nel ciclo; ",""))&IF(INDEX(ANA_Attenzione_Supervisore,INDEX(Classifica!$U$5:$U$19,$V46))="Sì","tema all'attenzione del supervisore; ","")&IF(COUNTIFS(KRI_ID_Rischio,INDEX(Classifica!$B$5:$B$19,$V46),KRI_Ciclo,cicloCorrente,KRI_In_Vigore,"Sì",KRI_Stato,"Rosso")>0,COUNTIFS(KRI_ID_Rischio,INDEX(Classifica!$B$5:$B$19,$V46),KRI_Ciclo,cicloCorrente,KRI_In_Vigore,"Sì",KRI_Stato,"Rosso")&" KRI in rosso; ","")&IF(INDEX(posNetti,INDEX(Classifica!$U$5:$U$19,$V46))>=sogliaDirezione,"notizie in peggioramento (+"&INDEX(posNetti,INDEX(Classifica!$U$5:$U$19,$V46))&" segnali netti in 4 settimane); ",IF(INDEX(posNetti,INDEX(Classifica!$U$5:$U$19,$V46))<=-sogliaDirezione,"notizie in miglioramento ("&INDEX(posNetti,INDEX(Classifica!$U$5:$U$19,$V46))&" segnali netti in 4 settimane); ",""))) -> 3° per score composito (3,50); margine di Mosca sotto l'anno (0,00); | BH46: =2*PI()*41/72 -> 3.577925 | BI46: =2*SIN($BH46) -> -0.84523652 | BJ46: =2*COS($BH46) -> -1.8126156 | BK46: =3*SIN($BH46) -> -1.2678548 | BL46: =3*COS($BH46) -> -2.7189234 | BM46: =4*SIN($BH46) -> -1.690473 | BN46: =4*COS($BH46) -> -3.6252311 | BO46: =5*SIN($BH46) -> -2.1130913 | BP46: =5*COS($BH46) -> -4.5315389
A47: =IF($V47="","",INDEX(Classifica!$B$5:$B$19,$V47)&CHAR(10)&INDEX(Classifica!$C$5:$C$19,$V47)&IF(INDEX(ANA_Attenzione_Supervisore,INDEX(Classifica!$U$5:$U$19,$V47))="Sì",CHAR(10)&"◆ attenzione del supervisore","")) -> NFR-02 Concentrazione su un fornitore cloud critico ◆ attenzione del supervisore | D47: =IF($V47="","",IF(LEFT(INDEX(Classifica!$H$5:$H$19,$V47),9)="AGIRE ORA","AGIRE ORA",IF(LEFT(INDEX(Classifica!$H$5:$H$19,$V47),11)="Agire entro","Entro l'anno",INDEX(Classifica!$H$5:$H$19,$V47)))) -> Entro l'anno | E47: =IF($W47="","",LEFT($W47,LEN($W47)-2)&".") -> variato nel ciclo: migliora; tema all'attenzione del supervisore. | I47: =IF($V47="","",IF(INDEX(Classifica!$G$5:$G$19,$V47)="Nuovo","Rischio nuovo nel ciclo.",IFERROR(IF(INDEX(RR_Variazioni,MATCH(cicloCorrente&"|"&INDEX(Classifica!$B$5:$B$19,$V47),RR_Chiave,0))&""="[]","Nessun valore cambiato: confermato sulle fonti del ciclo precedente.",SUBSTITUTE(SUBSTITUTE(SUBSTITUTE(SUBSTITUTE(SUBSTITUTE(SUBSTITUTE(SUBSTITUTE(SUBSTITUTE(SUBSTITUTE(SUBSTITUTE(SUBSTITUTE(SUBSTITUTE(SUBSTITUTE(INDEX(RR_Variazioni,MATCH(cicloCorrente&"|"&INDEX(Classifica!$B$5:$B$19,$V47),RR_Chiave,0))&"","[{""dimensione"": ""","• "),"""}, {""dimensione"": """,")"&CHAR(10)&"• "),""", ""da"": "," "),", ""a"": "," → "),", ""evidenza"": """,": "),""", ""data_evidenza"": """," ("),"""}]",")"),"• severity","• Severity"),"• velocity","• Velocity"),"• prossimita","• Prossimita"),"• gap_controlli","• Gap_Controlli"),"• confidence","• Confidence"),"• probabilita","• Probabilita")),""))) -> • Gap_Controlli 4 → 3: Il report del 28 agosto 2026 documenta il test completo della exit strategy sui due servizi critici residui, con esito positivo e rilievi minori. (2026-08-28) • Confidence 3 → 4: Aggiunta una fonte interna recente e concordante (report del test di exit strategy) alle fonti del registro DORA. (2026-08-28) | U47: =IF(Classifica!$B$8="","",IF(OR(4<=3,LEFT(Classifica!$H$8,9)="AGIRE ORA",Classifica!$G$8="Variato",Classifica!$G$8="Nuovo"),4,"")) -> 4 | V47: =IFERROR(_xlfn.AGGREGATE(15,6,$U$44:$U$58,4),"") -> 4 | W47: =IF($V47="","",IF($V47<=3,$V47&"° per score composito ("&FIXED(INDEX(Classifica!$D$5:$D$19,$V47),2)&IF(ISNUMBER(INDEX(Classifica!$F$5:$F$19,$V47)),IF(INDEX(Classifica!$F$5:$F$19,$V47)<>0,", "&IF(INDEX(Classifica!$F$5:$F$19,$V47)>0,"+","")&FIXED(INDEX(Classifica!$F$5:$F$19,$V47),2)&" sul ciclo prima",""),"")&"); ","")&IF(LEFT(INDEX(Classifica!$H$5:$H$19,$V47),9)="AGIRE ORA","AGIRE ORA: servono X + Y = "&FIXED(INDEX(Classifica!$Y$5:$Y$19,$V47)+INDEX(Classifica!$Z$5:$Z$19,$V47),2)&" anni per decidere e mitigare"&IF(N(INDEX(ANA_Anni_Adeguamento,INDEX(Classifica!$U$5:$U$19,$V47)))>0,", di cui "&N(INDEX(ANA_Anni_Adeguamento,INDEX(Classifica!$U$5:$U$19,$V47)))&" di adeguamento strutturale","")&"; ne restano Z = "&FIXED(INDEX(Classifica!$AA$5:$AA$19,$V47),1)&" prima che possa manifestarsi; ",IF(AND($V47<=3,LEFT(INDEX(Classifica!$H$5:$H$19,$V47),11)="Agire entro"),"margine di Mosca sotto l'anno ("&FIXED(INDEX(Classifica!$I$5:$I$19,$V47),2)&"); ",""))&IF(INDEX(Classifica!$G$5:$G$19,$V47)="Variato","variato nel ciclo"&IF(ISNUMBER(INDEX(Classifica!$F$5:$F$19,$V47)),IF(INDEX(Classifica!$F$5:$F$19,$V47)>0,": peggiora",IF(INDEX(Classifica!$F$5:$F$19,$V47)<0,": migliora","")),"")&"; ",IF(INDEX(Classifica!$G$5:$G$19,$V47)="Nuovo","nuovo nel ciclo; ",""))&IF(INDEX(ANA_Attenzione_Supervisore,INDEX(Classifica!$U$5:$U$19,$V47))="Sì","tema all'attenzione del supervisore; ","")&IF(COUNTIFS(KRI_ID_Rischio,INDEX(Classifica!$B$5:$B$19,$V47),KRI_Ciclo,cicloCorrente,KRI_In_Vigore,"Sì",KRI_Stato,"Rosso")>0,COUNTIFS(KRI_ID_Rischio,INDEX(Classifica!$B$5:$B$19,$V47),KRI_Ciclo,cicloCorrente,KRI_In_Vigore,"Sì",KRI_Stato,"Rosso")&" KRI in rosso; ","")&IF(INDEX(posNetti,INDEX(Classifica!$U$5:$U$19,$V47))>=sogliaDirezione,"notizie in peggioramento (+"&INDEX(posNetti,INDEX(Classifica!$U$5:$U$19,$V47))&" segnali netti in 4 settimane); ",IF(INDEX(posNetti,INDEX(Classifica!$U$5:$U$19,$V47))<=-sogliaDirezione,"notizie in miglioramento ("&INDEX(posNetti,INDEX(Classifica!$U$5:$U$19,$V47))&" segnali netti in 4 settimane); ",""))) -> variato nel ciclo: migliora; tema all'attenzione del supervisore; | BH47: =2*PI()*42/72 -> 3.6651914 | BI47: =2*SIN($BH47) -> -1 | BJ47: =2*COS($BH47) -> -1.7320508 | BK47: =3*SIN($BH47) -> -1.5 | BL47: =3*COS($BH47) -> -2.5980762 | BM47: =4*SIN($BH47) -> -2 | BN47: =4*COS($BH47) -> -3.4641016 | BO47: =5*SIN($BH47) -> -2.5 | BP47: =5*COS($BH47) -> -4.330127
A48: =IF($V48="","",INDEX(Classifica!$B$5:$B$19,$V48)&CHAR(10)&INDEX(Classifica!$C$5:$C$19,$V48)&IF(INDEX(ANA_Attenzione_Supervisore,INDEX(Classifica!$U$5:$U$19,$V48))="Sì",CHAR(10)&"◆ attenzione del supervisore","")) -> NFR-11 Fine del supporto dei sistemi di pagamento legacy | D48: =IF($V48="","",IF(LEFT(INDEX(Classifica!$H$5:$H$19,$V48),9)="AGIRE ORA","AGIRE ORA",IF(LEFT(INDEX(Classifica!$H$5:$H$19,$V48),11)="Agire entro","Entro l'anno",INDEX(Classifica!$H$5:$H$19,$V48)))) -> AGIRE ORA | E48: =IF($W48="","",LEFT($W48,LEN($W48)-2)&".") -> AGIRE ORA: servono X + Y = 3,25 anni per decidere e mitigare, di cui 3 di adeguamento strutturale; ne restano Z = 1,5 prima che possa manifestarsi. | I48: =IF($V48="","",IF(INDEX(Classifica!$G$5:$G$19,$V48)="Nuovo","Rischio nuovo nel ciclo.",IFERROR(IF(INDEX(RR_Variazioni,MATCH(cicloCorrente&"|"&INDEX(Classifica!$B$5:$B$19,$V48),RR_Chiave,0))&""="[]","Nessun valore cambiato: confermato sulle fonti del ciclo precedente.",SUBSTITUTE(SUBSTITUTE(SUBSTITUTE(SUBSTITUTE(SUBSTITUTE(SUBSTITUTE(SUBSTITUTE(SUBSTITUTE(SUBSTITUTE(SUBSTITUTE(SUBSTITUTE(SUBSTITUTE(SUBSTITUTE(INDEX(RR_Variazioni,MATCH(cicloCorrente&"|"&INDEX(Classifica!$B$5:$B$19,$V48),RR_Chiave,0))&"","[{""dimensione"": ""","• "),"""}, {""dimensione"": """,")"&CHAR(10)&"• "),""", ""da"": "," "),", ""a"": "," → "),", ""evidenza"": """,": "),""", ""data_evidenza"": """," ("),"""}]",")"),"• severity","• Severity"),"• velocity","• Velocity"),"• prossimita","• Prossimita"),"• gap_controlli","• Gap_Controlli"),"• confidence","• Confidence"),"• probabilita","• Probabilita")),""))) -> Nessun valore cambiato: confermato sulle fonti del ciclo precedente. | U48: =IF(Classifica!$B$9="","",IF(OR(5<=3,LEFT(Classifica!$H$9,9)="AGIRE ORA",Classifica!$G$9="Variato",Classifica!$G$9="Nuovo"),5,"")) | V48: =IFERROR(_xlfn.AGGREGATE(15,6,$U$44:$U$58,5),"") -> 6 | W48: =IF($V48="","",IF($V48<=3,$V48&"° per score composito ("&FIXED(INDEX(Classifica!$D$5:$D$19,$V48),2)&IF(ISNUMBER(INDEX(Classifica!$F$5:$F$19,$V48)),IF(INDEX(Classifica!$F$5:$F$19,$V48)<>0,", "&IF(INDEX(Classifica!$F$5:$F$19,$V48)>0,"+","")&FIXED(INDEX(Classifica!$F$5:$F$19,$V48),2)&" sul ciclo prima",""),"")&"); ","")&IF(LEFT(INDEX(Classifica!$H$5:$H$19,$V48),9)="AGIRE ORA","AGIRE ORA: servono X + Y = "&FIXED(INDEX(Classifica!$Y$5:$Y$19,$V48)+INDEX(Classifica!$Z$5:$Z$19,$V48),2)&" anni per decidere e mitigare"&IF(N(INDEX(ANA_Anni_Adeguamento,INDEX(Classifica!$U$5:$U$19,$V48)))>0,", di cui "&N(INDEX(ANA_Anni_Adeguamento,INDEX(Classifica!$U$5:$U$19,$V48)))&" di adeguamento strutturale","")&"; ne restano Z = "&FIXED(INDEX(Classifica!$AA$5:$AA$19,$V48),1)&" prima che possa manifestarsi; ",IF(AND($V48<=3,LEFT(INDEX(Classifica!$H$5:$H$19,$V48),11)="Agire entro"),"margine di Mosca sotto l'anno ("&FIXED(INDEX(Classifica!$I$5:$I$19,$V48),2)&"); ",""))&IF(INDEX(Classifica!$G$5:$G$19,$V48)="Variato","variato nel ciclo"&IF(ISNUMBER(INDEX(Classifica!$F$5:$F$19,$V48)),IF(INDEX(Classifica!$F$5:$F$19,$V48)>0,": peggiora",IF(INDEX(Classifica!$F$5:$F$19,$V48)<0,": migliora","")),"")&"; ",IF(INDEX(Classifica!$G$5:$G$19,$V48)="Nuovo","nuovo nel ciclo; ",""))&IF(INDEX(ANA_Attenzione_Supervisore,INDEX(Classifica!$U$5:$U$19,$V48))="Sì","tema all'attenzione del supervisore; ","")&IF(COUNTIFS(KRI_ID_Rischio,INDEX(Classifica!$B$5:$B$19,$V48),KRI_Ciclo,cicloCorrente,KRI_In_Vigore,"Sì",KRI_Stato,"Rosso")>0,COUNTIFS(KRI_ID_Rischio,INDEX(Classifica!$B$5:$B$19,$V48),KRI_Ciclo,cicloCorrente,KRI_In_Vigore,"Sì",KRI_Stato,"Rosso")&" KRI in rosso; ","")&IF(INDEX(posNetti,INDEX(Classifica!$U$5:$U$19,$V48))>=sogliaDirezione,"notizie in peggioramento (+"&INDEX(posNetti,INDEX(Classifica!$U$5:$U$19,$V48))&" segnali netti in 4 settimane); ",IF(INDEX(posNetti,INDEX(Classifica!$U$5:$U$19,$V48))<=-sogliaDirezione,"notizie in miglioramento ("&INDEX(posNetti,INDEX(Classifica!$U$5:$U$19,$V48))&" segnali netti in 4 settimane); ",""))) -> AGIRE ORA: servono X + Y = 3,25 anni per decidere e mitigare, di cui 3 di adeguamento strutturale; ne restano Z = 1,5 prima che possa manifestarsi; | BH48: =2*PI()*43/72 -> 3.7524579 | BI48: =2*SIN($BH48) -> -1.1471529 | BJ48: =2*COS($BH48) -> -1.6383041 | BK48: =3*SIN($BH48) -> -1.7207293 | BL48: =3*COS($BH48) -> -2.4574561 | BM48: =4*SIN($BH48) -> -2.2943057 | BN48: =4*COS($BH48) -> -3.2766082 | BO48: =5*SIN($BH48) -> -2.8678822 | BP48: =5*COS($BH48) -> -4.0957602
A49: =IF($V49="","",INDEX(Classifica!$B$5:$B$19,$V49)&CHAR(10)&INDEX(Classifica!$C$5:$C$19,$V49)&IF(INDEX(ANA_Attenzione_Supervisore,INDEX(Classifica!$U$5:$U$19,$V49))="Sì",CHAR(10)&"◆ attenzione del supervisore","")) -> NFR-03 Greenwashing nella commercializzazione di prodotti ESG | D49: =IF($V49="","",IF(LEFT(INDEX(Classifica!$H$5:$H$19,$V49),9)="AGIRE ORA","AGIRE ORA",IF(LEFT(INDEX(Classifica!$H$5:$H$19,$V49),11)="Agire entro","Entro l'anno",INDEX(Classifica!$H$5:$H$19,$V49)))) -> Entro l'anno | E49: =IF($W49="","",LEFT($W49,LEN($W49)-2)&".") -> variato nel ciclo: peggiora. | I49: =IF($V49="","",IF(INDEX(Classifica!$G$5:$G$19,$V49)="Nuovo","Rischio nuovo nel ciclo.",IFERROR(IF(INDEX(RR_Variazioni,MATCH(cicloCorrente&"|"&INDEX(Classifica!$B$5:$B$19,$V49),RR_Chiave,0))&""="[]","Nessun valore cambiato: confermato sulle fonti del ciclo precedente.",SUBSTITUTE(SUBSTITUTE(SUBSTITUTE(SUBSTITUTE(SUBSTITUTE(SUBSTITUTE(SUBSTITUTE(SUBSTITUTE(SUBSTITUTE(SUBSTITUTE(SUBSTITUTE(SUBSTITUTE(SUBSTITUTE(INDEX(RR_Variazioni,MATCH(cicloCorrente&"|"&INDEX(Classifica!$B$5:$B$19,$V49),RR_Chiave,0))&"","[{""dimensione"": ""","• "),"""}, {""dimensione"": """,")"&CHAR(10)&"• "),""", ""da"": "," "),", ""a"": "," → "),", ""evidenza"": """,": "),""", ""data_evidenza"": """," ("),"""}]",")"),"• severity","• Severity"),"• velocity","• Velocity"),"• prossimita","• Prossimita"),"• gap_controlli","• Gap_Controlli"),"• confidence","• Confidence"),"• probabilita","• Probabilita")),""))) -> • Prossimita 3 → 4: Il 22 luglio 2026 l'autorita' ha sanzionato una banca italiana comparabile per claim ambientali non sostanziati su fondi ESG distribuiti alla clientela retail. (2026-07-22) | U49: =IF(Classifica!$B$10="","",IF(OR(6<=3,LEFT(Classifica!$H$10,9)="AGIRE ORA",Classifica!$G$10="Variato",Classifica!$G$10="Nuovo"),6,"")) -> 6 | V49: =IFERROR(_xlfn.AGGREGATE(15,6,$U$44:$U$58,6),"") -> 7 | W49: =IF($V49="","",IF($V49<=3,$V49&"° per score composito ("&FIXED(INDEX(Classifica!$D$5:$D$19,$V49),2)&IF(ISNUMBER(INDEX(Classifica!$F$5:$F$19,$V49)),IF(INDEX(Classifica!$F$5:$F$19,$V49)<>0,", "&IF(INDEX(Classifica!$F$5:$F$19,$V49)>0,"+","")&FIXED(INDEX(Classifica!$F$5:$F$19,$V49),2)&" sul ciclo prima",""),"")&"); ","")&IF(LEFT(INDEX(Classifica!$H$5:$H$19,$V49),9)="AGIRE ORA","AGIRE ORA: servono X + Y = "&FIXED(INDEX(Classifica!$Y$5:$Y$19,$V49)+INDEX(Classifica!$Z$5:$Z$19,$V49),2)&" anni per decidere e mitigare"&IF(N(INDEX(ANA_Anni_Adeguamento,INDEX(Classifica!$U$5:$U$19,$V49)))>0,", di cui "&N(INDEX(ANA_Anni_Adeguamento,INDEX(Classifica!$U$5:$U$19,$V49)))&" di adeguamento strutturale","")&"; ne restano Z = "&FIXED(INDEX(Classifica!$AA$5:$AA$19,$V49),1)&" prima che possa manifestarsi; ",IF(AND($V49<=3,LEFT(INDEX(Classifica!$H$5:$H$19,$V49),11)="Agire entro"),"margine di Mosca sotto l'anno ("&FIXED(INDEX(Classifica!$I$5:$I$19,$V49),2)&"); ",""))&IF(INDEX(Classifica!$G$5:$G$19,$V49)="Variato","variato nel ciclo"&IF(ISNUMBER(INDEX(Classifica!$F$5:$F$19,$V49)),IF(INDEX(Classifica!$F$5:$F$19,$V49)>0,": peggiora",IF(INDEX(Classifica!$F$5:$F$19,$V49)<0,": migliora","")),"")&"; ",IF(INDEX(Classifica!$G$5:$G$19,$V49)="Nuovo","nuovo nel ciclo; ",""))&IF(INDEX(ANA_Attenzione_Supervisore,INDEX(Classifica!$U$5:$U$19,$V49))="Sì","tema all'attenzione del supervisore; ","")&IF(COUNTIFS(KRI_ID_Rischio,INDEX(Classifica!$B$5:$B$19,$V49),KRI_Ciclo,cicloCorrente,KRI_In_Vigore,"Sì",KRI_Stato,"Rosso")>0,COUNTIFS(KRI_ID_Rischio,INDEX(Classifica!$B$5:$B$19,$V49),KRI_Ciclo,cicloCorrente,KRI_In_Vigore,"Sì",KRI_Stato,"Rosso")&" KRI in rosso; ","")&IF(INDEX(posNetti,INDEX(Classifica!$U$5:$U$19,$V49))>=sogliaDirezione,"notizie in peggioramento (+"&INDEX(posNetti,INDEX(Classifica!$U$5:$U$19,$V49))&" segnali netti in 4 settimane); ",IF(INDEX(posNetti,INDEX(Classifica!$U$5:$U$19,$V49))<=-sogliaDirezione,"notizie in miglioramento ("&INDEX(posNetti,INDEX(Classifica!$U$5:$U$19,$V49))&" segnali netti in 4 settimane); ",""))) -> variato nel ciclo: peggiora; | BH49: =2*PI()*44/72 -> 3.8397244 | BI49: =2*SIN($BH49) -> -1.2855752 | BJ49: =2*COS($BH49) -> -1.5320889 | BK49: =3*SIN($BH49) -> -1.9283628 | BL49: =3*COS($BH49) -> -2.2981333 | BM49: =4*SIN($BH49) -> -2.5711504 | BN49: =4*COS($BH49) -> -3.0641778 | BO49: =5*SIN($BH49) -> -3.213938 | BP49: =5*COS($BH49) -> -3.8302222
A50: =IF($V50="","",INDEX(Classifica!$B$5:$B$19,$V50)&CHAR(10)&INDEX(Classifica!$C$5:$C$19,$V50)&IF(INDEX(ANA_Attenzione_Supervisore,INDEX(Classifica!$U$5:$U$19,$V50))="Sì",CHAR(10)&"◆ attenzione del supervisore","")) -> NFR-06 Esfiltrazione di dati tramite strumenti di AI non autorizzati | D50: =IF($V50="","",IF(LEFT(INDEX(Classifica!$H$5:$H$19,$V50),9)="AGIRE ORA","AGIRE ORA",IF(LEFT(INDEX(Classifica!$H$5:$H$19,$V50),11)="Agire entro","Entro l'anno",INDEX(Classifica!$H$5:$H$19,$V50)))) -> Entro l'anno | E50: =IF($W50="","",LEFT($W50,LEN($W50)-2)&".") -> variato nel ciclo: migliora. | I50: =IF($V50="","",IF(INDEX(Classifica!$G$5:$G$19,$V50)="Nuovo","Rischio nuovo nel ciclo.",IFERROR(IF(INDEX(RR_Variazioni,MATCH(cicloCorrente&"|"&INDEX(Classifica!$B$5:$B$19,$V50),RR_Chiave,0))&""="[]","Nessun valore cambiato: confermato sulle fonti del ciclo precedente.",SUBSTITUTE(SUBSTITUTE(SUBSTITUTE(SUBSTITUTE(SUBSTITUTE(SUBSTITUTE(SUBSTITUTE(SUBSTITUTE(SUBSTITUTE(SUBSTITUTE(SUBSTITUTE(SUBSTITUTE(SUBSTITUTE(INDEX(RR_Variazioni,MATCH(cicloCorrente&"|"&INDEX(Classifica!$B$5:$B$19,$V50),RR_Chiave,0))&"","[{""dimensione"": ""","• "),"""}, {""dimensione"": """,")"&CHAR(10)&"• "),""", ""da"": "," "),", ""a"": "," → "),", ""evidenza"": """,": "),""", ""data_evidenza"": """," ("),"""}]",")"),"• severity","• Severity"),"• velocity","• Velocity"),"• prossimita","• Prossimita"),"• gap_controlli","• Gap_Controlli"),"• confidence","• Confidence"),"• probabilita","• Probabilita")),""))) -> • Gap_Controlli 4 → 3: Dal 5 settembre 2026 il DLP copre tutti i servizi di AI generativa; il test di blocco eseguito dalla Sicurezza delle Informazioni ha dato esito positivo. (2026-09-05) | U50: =IF(Classifica!$B$11="","",IF(OR(7<=3,LEFT(Classifica!$H$11,9)="AGIRE ORA",Classifica!$G$11="Variato",Classifica!$G$11="Nuovo"),7,"")) -> 7 | V50: =IFERROR(_xlfn.AGGREGATE(15,6,$U$44:$U$58,7),"") -> 9 | W50: =IF($V50="","",IF($V50<=3,$V50&"° per score composito ("&FIXED(INDEX(Classifica!$D$5:$D$19,$V50),2)&IF(ISNUMBER(INDEX(Classifica!$F$5:$F$19,$V50)),IF(INDEX(Classifica!$F$5:$F$19,$V50)<>0,", "&IF(INDEX(Classifica!$F$5:$F$19,$V50)>0,"+","")&FIXED(INDEX(Classifica!$F$5:$F$19,$V50),2)&" sul ciclo prima",""),"")&"); ","")&IF(LEFT(INDEX(Classifica!$H$5:$H$19,$V50),9)="AGIRE ORA","AGIRE ORA: servono X + Y = "&FIXED(INDEX(Classifica!$Y$5:$Y$19,$V50)+INDEX(Classifica!$Z$5:$Z$19,$V50),2)&" anni per decidere e mitigare"&IF(N(INDEX(ANA_Anni_Adeguamento,INDEX(Classifica!$U$5:$U$19,$V50)))>0,", di cui "&N(INDEX(ANA_Anni_Adeguamento,INDEX(Classifica!$U$5:$U$19,$V50)))&" di adeguamento strutturale","")&"; ne restano Z = "&FIXED(INDEX(Classifica!$AA$5:$AA$19,$V50),1)&" prima che possa manifestarsi; ",IF(AND($V50<=3,LEFT(INDEX(Classifica!$H$5:$H$19,$V50),11)="Agire entro"),"margine di Mosca sotto l'anno ("&FIXED(INDEX(Classifica!$I$5:$I$19,$V50),2)&"); ",""))&IF(INDEX(Classifica!$G$5:$G$19,$V50)="Variato","variato nel ciclo"&IF(ISNUMBER(INDEX(Classifica!$F$5:$F$19,$V50)),IF(INDEX(Classifica!$F$5:$F$19,$V50)>0,": peggiora",IF(INDEX(Classifica!$F$5:$F$19,$V50)<0,": migliora","")),"")&"; ",IF(INDEX(Classifica!$G$5:$G$19,$V50)="Nuovo","nuovo nel ciclo; ",""))&IF(INDEX(ANA_Attenzione_Supervisore,INDEX(Classifica!$U$5:$U$19,$V50))="Sì","tema all'attenzione del supervisore; ","")&IF(COUNTIFS(KRI_ID_Rischio,INDEX(Classifica!$B$5:$B$19,$V50),KRI_Ciclo,cicloCorrente,KRI_In_Vigore,"Sì",KRI_Stato,"Rosso")>0,COUNTIFS(KRI_ID_Rischio,INDEX(Classifica!$B$5:$B$19,$V50),KRI_Ciclo,cicloCorrente,KRI_In_Vigore,"Sì",KRI_Stato,"Rosso")&" KRI in rosso; ","")&IF(INDEX(posNetti,INDEX(Classifica!$U$5:$U$19,$V50))>=sogliaDirezione,"notizie in peggioramento (+"&INDEX(posNetti,INDEX(Classifica!$U$5:$U$19,$V50))&" segnali netti in 4 settimane); ",IF(INDEX(posNetti,INDEX(Classifica!$U$5:$U$19,$V50))<=-sogliaDirezione,"notizie in miglioramento ("&INDEX(posNetti,INDEX(Classifica!$U$5:$U$19,$V50))&" segnali netti in 4 settimane); ",""))) -> variato nel ciclo: migliora; | BH50: =2*PI()*45/72 -> 3.9269908 | BI50: =2*SIN($BH50) -> -1.4142136 | BJ50: =2*COS($BH50) -> -1.4142136 | BK50: =3*SIN($BH50) -> -2.1213203 | BL50: =3*COS($BH50) -> -2.1213203 | BM50: =4*SIN($BH50) -> -2.8284271 | BN50: =4*COS($BH50) -> -2.8284271 | BO50: =5*SIN($BH50) -> -3.5355339 | BP50: =5*COS($BH50) -> -3.5355339
A51: =IF($V51="","",INDEX(Classifica!$B$5:$B$19,$V51)&CHAR(10)&INDEX(Classifica!$C$5:$C$19,$V51)&IF(INDEX(ANA_Attenzione_Supervisore,INDEX(Classifica!$U$5:$U$19,$V51))="Sì",CHAR(10)&"◆ attenzione del supervisore","")) | D51: =IF($V51="","",IF(LEFT(INDEX(Classifica!$H$5:$H$19,$V51),9)="AGIRE ORA","AGIRE ORA",IF(LEFT(INDEX(Classifica!$H$5:$H$19,$V51),11)="Agire entro","Entro l'anno",INDEX(Classifica!$H$5:$H$19,$V51)))) | E51: =IF($W51="","",LEFT($W51,LEN($W51)-2)&".") | I51: =IF($V51="","",IF(INDEX(Classifica!$G$5:$G$19,$V51)="Nuovo","Rischio nuovo nel ciclo.",IFERROR(IF(INDEX(RR_Variazioni,MATCH(cicloCorrente&"|"&INDEX(Classifica!$B$5:$B$19,$V51),RR_Chiave,0))&""="[]","Nessun valore cambiato: confermato sulle fonti del ciclo precedente.",SUBSTITUTE(SUBSTITUTE(SUBSTITUTE(SUBSTITUTE(SUBSTITUTE(SUBSTITUTE(SUBSTITUTE(SUBSTITUTE(SUBSTITUTE(SUBSTITUTE(SUBSTITUTE(SUBSTITUTE(SUBSTITUTE(INDEX(RR_Variazioni,MATCH(cicloCorrente&"|"&INDEX(Classifica!$B$5:$B$19,$V51),RR_Chiave,0))&"","[{""dimensione"": ""","• "),"""}, {""dimensione"": """,")"&CHAR(10)&"• "),""", ""da"": "," "),", ""a"": "," → "),", ""evidenza"": """,": "),""", ""data_evidenza"": """," ("),"""}]",")"),"• severity","• Severity"),"• velocity","• Velocity"),"• prossimita","• Prossimita"),"• gap_controlli","• Gap_Controlli"),"• confidence","• Confidence"),"• probabilita","• Probabilita")),""))) | U51: =IF(Classifica!$B$12="","",IF(OR(8<=3,LEFT(Classifica!$H$12,9)="AGIRE ORA",Classifica!$G$12="Variato",Classifica!$G$12="Nuovo"),8,"")) | V51: =IFERROR(_xlfn.AGGREGATE(15,6,$U$44:$U$58,8),"") | W51: =IF($V51="","",IF($V51<=3,$V51&"° per score composito ("&FIXED(INDEX(Classifica!$D$5:$D$19,$V51),2)&IF(ISNUMBER(INDEX(Classifica!$F$5:$F$19,$V51)),IF(INDEX(Classifica!$F$5:$F$19,$V51)<>0,", "&IF(INDEX(Classifica!$F$5:$F$19,$V51)>0,"+","")&FIXED(INDEX(Classifica!$F$5:$F$19,$V51),2)&" sul ciclo prima",""),"")&"); ","")&IF(LEFT(INDEX(Classifica!$H$5:$H$19,$V51),9)="AGIRE ORA","AGIRE ORA: servono X + Y = "&FIXED(INDEX(Classifica!$Y$5:$Y$19,$V51)+INDEX(Classifica!$Z$5:$Z$19,$V51),2)&" anni per decidere e mitigare"&IF(N(INDEX(ANA_Anni_Adeguamento,INDEX(Classifica!$U$5:$U$19,$V51)))>0,", di cui "&N(INDEX(ANA_Anni_Adeguamento,INDEX(Classifica!$U$5:$U$19,$V51)))&" di adeguamento strutturale","")&"; ne restano Z = "&FIXED(INDEX(Classifica!$AA$5:$AA$19,$V51),1)&" prima che possa manifestarsi; ",IF(AND($V51<=3,LEFT(INDEX(Classifica!$H$5:$H$19,$V51),11)="Agire entro"),"margine di Mosca sotto l'anno ("&FIXED(INDEX(Classifica!$I$5:$I$19,$V51),2)&"); ",""))&IF(INDEX(Classifica!$G$5:$G$19,$V51)="Variato","variato nel ciclo"&IF(ISNUMBER(INDEX(Classifica!$F$5:$F$19,$V51)),IF(INDEX(Classifica!$F$5:$F$19,$V51)>0,": peggiora",IF(INDEX(Classifica!$F$5:$F$19,$V51)<0,": migliora","")),"")&"; ",IF(INDEX(Classifica!$G$5:$G$19,$V51)="Nuovo","nuovo nel ciclo; ",""))&IF(INDEX(ANA_Attenzione_Supervisore,INDEX(Classifica!$U$5:$U$19,$V51))="Sì","tema all'attenzione del supervisore; ","")&IF(COUNTIFS(KRI_ID_Rischio,INDEX(Classifica!$B$5:$B$19,$V51),KRI_Ciclo,cicloCorrente,KRI_In_Vigore,"Sì",KRI_Stato,"Rosso")>0,COUNTIFS(KRI_ID_Rischio,INDEX(Classifica!$B$5:$B$19,$V51),KRI_Ciclo,cicloCorrente,KRI_In_Vigore,"Sì",KRI_Stato,"Rosso")&" KRI in rosso; ","")&IF(INDEX(posNetti,INDEX(Classifica!$U$5:$U$19,$V51))>=sogliaDirezione,"notizie in peggioramento (+"&INDEX(posNetti,INDEX(Classifica!$U$5:$U$19,$V51))&" segnali netti in 4 settimane); ",IF(INDEX(posNetti,INDEX(Classifica!$U$5:$U$19,$V51))<=-sogliaDirezione,"notizie in miglioramento ("&INDEX(posNetti,INDEX(Classifica!$U$5:$U$19,$V51))&" segnali netti in 4 settimane); ",""))) | BH51: =2*PI()*46/72 -> 4.0142573 | BI51: =2*SIN($BH51) -> -1.5320889 | BJ51: =2*COS($BH51) -> -1.2855752 | BK51: =3*SIN($BH51) -> -2.2981333 | BL51: =3*COS($BH51) -> -1.9283628 | BM51: =4*SIN($BH51) -> -3.0641778 | BN51: =4*COS($BH51) -> -2.5711504 | BO51: =5*SIN($BH51) -> -3.8302222 | BP51: =5*COS($BH51) -> -3.213938
A52: =IF($V52="","",INDEX(Classifica!$B$5:$B$19,$V52)&CHAR(10)&INDEX(Classifica!$C$5:$C$19,$V52)&IF(INDEX(ANA_Attenzione_Supervisore,INDEX(Classifica!$U$5:$U$19,$V52))="Sì",CHAR(10)&"◆ attenzione del supervisore","")) | D52: =IF($V52="","",IF(LEFT(INDEX(Classifica!$H$5:$H$19,$V52),9)="AGIRE ORA","AGIRE ORA",IF(LEFT(INDEX(Classifica!$H$5:$H$19,$V52),11)="Agire entro","Entro l'anno",INDEX(Classifica!$H$5:$H$19,$V52)))) | E52: =IF($W52="","",LEFT($W52,LEN($W52)-2)&".") | I52: =IF($V52="","",IF(INDEX(Classifica!$G$5:$G$19,$V52)="Nuovo","Rischio nuovo nel ciclo.",IFERROR(IF(INDEX(RR_Variazioni,MATCH(cicloCorrente&"|"&INDEX(Classifica!$B$5:$B$19,$V52),RR_Chiave,0))&""="[]","Nessun valore cambiato: confermato sulle fonti del ciclo precedente.",SUBSTITUTE(SUBSTITUTE(SUBSTITUTE(SUBSTITUTE(SUBSTITUTE(SUBSTITUTE(SUBSTITUTE(SUBSTITUTE(SUBSTITUTE(SUBSTITUTE(SUBSTITUTE(SUBSTITUTE(SUBSTITUTE(INDEX(RR_Variazioni,MATCH(cicloCorrente&"|"&INDEX(Classifica!$B$5:$B$19,$V52),RR_Chiave,0))&"","[{""dimensione"": ""","• "),"""}, {""dimensione"": """,")"&CHAR(10)&"• "),""", ""da"": "," "),", ""a"": "," → "),", ""evidenza"": """,": "),""", ""data_evidenza"": """," ("),"""}]",")"),"• severity","• Severity"),"• velocity","• Velocity"),"• prossimita","• Prossimita"),"• gap_controlli","• Gap_Controlli"),"• confidence","• Confidence"),"• probabilita","• Probabilita")),""))) | U52: =IF(Classifica!$B$13="","",IF(OR(9<=3,LEFT(Classifica!$H$13,9)="AGIRE ORA",Classifica!$G$13="Variato",Classifica!$G$13="Nuovo"),9,"")) -> 9 | V52: =IFERROR(_xlfn.AGGREGATE(15,6,$U$44:$U$58,9),"") | W52: =IF($V52="","",IF($V52<=3,$V52&"° per score composito ("&FIXED(INDEX(Classifica!$D$5:$D$19,$V52),2)&IF(ISNUMBER(INDEX(Classifica!$F$5:$F$19,$V52)),IF(INDEX(Classifica!$F$5:$F$19,$V52)<>0,", "&IF(INDEX(Classifica!$F$5:$F$19,$V52)>0,"+","")&FIXED(INDEX(Classifica!$F$5:$F$19,$V52),2)&" sul ciclo prima",""),"")&"); ","")&IF(LEFT(INDEX(Classifica!$H$5:$H$19,$V52),9)="AGIRE ORA","AGIRE ORA: servono X + Y = "&FIXED(INDEX(Classifica!$Y$5:$Y$19,$V52)+INDEX(Classifica!$Z$5:$Z$19,$V52),2)&" anni per decidere e mitigare"&IF(N(INDEX(ANA_Anni_Adeguamento,INDEX(Classifica!$U$5:$U$19,$V52)))>0,", di cui "&N(INDEX(ANA_Anni_Adeguamento,INDEX(Classifica!$U$5:$U$19,$V52)))&" di adeguamento strutturale","")&"; ne restano Z = "&FIXED(INDEX(Classifica!$AA$5:$AA$19,$V52),1)&" prima che possa manifestarsi; ",IF(AND($V52<=3,LEFT(INDEX(Classifica!$H$5:$H$19,$V52),11)="Agire entro"),"margine di Mosca sotto l'anno ("&FIXED(INDEX(Classifica!$I$5:$I$19,$V52),2)&"); ",""))&IF(INDEX(Classifica!$G$5:$G$19,$V52)="Variato","variato nel ciclo"&IF(ISNUMBER(INDEX(Classifica!$F$5:$F$19,$V52)),IF(INDEX(Classifica!$F$5:$F$19,$V52)>0,": peggiora",IF(INDEX(Classifica!$F$5:$F$19,$V52)<0,": migliora","")),"")&"; ",IF(INDEX(Classifica!$G$5:$G$19,$V52)="Nuovo","nuovo nel ciclo; ",""))&IF(INDEX(ANA_Attenzione_Supervisore,INDEX(Classifica!$U$5:$U$19,$V52))="Sì","tema all'attenzione del supervisore; ","")&IF(COUNTIFS(KRI_ID_Rischio,INDEX(Classifica!$B$5:$B$19,$V52),KRI_Ciclo,cicloCorrente,KRI_In_Vigore,"Sì",KRI_Stato,"Rosso")>0,COUNTIFS(KRI_ID_Rischio,INDEX(Classifica!$B$5:$B$19,$V52),KRI_Ciclo,cicloCorrente,KRI_In_Vigore,"Sì",KRI_Stato,"Rosso")&" KRI in rosso; ","")&IF(INDEX(posNetti,INDEX(Classifica!$U$5:$U$19,$V52))>=sogliaDirezione,"notizie in peggioramento (+"&INDEX(posNetti,INDEX(Classifica!$U$5:$U$19,$V52))&" segnali netti in 4 settimane); ",IF(INDEX(posNetti,INDEX(Classifica!$U$5:$U$19,$V52))<=-sogliaDirezione,"notizie in miglioramento ("&INDEX(posNetti,INDEX(Classifica!$U$5:$U$19,$V52))&" segnali netti in 4 settimane); ",""))) | BH52: =2*PI()*47/72 -> 4.1015237 | BI52: =2*SIN($BH52) -> -1.6383041 | BJ52: =2*COS($BH52) -> -1.1471529 | BK52: =3*SIN($BH52) -> -2.4574561 | BL52: =3*COS($BH52) -> -1.7207293 | BM52: =4*SIN($BH52) -> -3.2766082 | BN52: =4*COS($BH52) -> -2.2943057 | BO52: =5*SIN($BH52) -> -4.0957602 | BP52: =5*COS($BH52) -> -2.8678822
A53: =IF($V53="","",INDEX(Classifica!$B$5:$B$19,$V53)&CHAR(10)&INDEX(Classifica!$C$5:$C$19,$V53)&IF(INDEX(ANA_Attenzione_Supervisore,INDEX(Classifica!$U$5:$U$19,$V53))="Sì",CHAR(10)&"◆ attenzione del supervisore","")) | D53: =IF($V53="","",IF(LEFT(INDEX(Classifica!$H$5:$H$19,$V53),9)="AGIRE ORA","AGIRE ORA",IF(LEFT(INDEX(Classifica!$H$5:$H$19,$V53),11)="Agire entro","Entro l'anno",INDEX(Classifica!$H$5:$H$19,$V53)))) | E53: =IF($W53="","",LEFT($W53,LEN($W53)-2)&".") | I53: =IF($V53="","",IF(INDEX(Classifica!$G$5:$G$19,$V53)="Nuovo","Rischio nuovo nel ciclo.",IFERROR(IF(INDEX(RR_Variazioni,MATCH(cicloCorrente&"|"&INDEX(Classifica!$B$5:$B$19,$V53),RR_Chiave,0))&""="[]","Nessun valore cambiato: confermato sulle fonti del ciclo precedente.",SUBSTITUTE(SUBSTITUTE(SUBSTITUTE(SUBSTITUTE(SUBSTITUTE(SUBSTITUTE(SUBSTITUTE(SUBSTITUTE(SUBSTITUTE(SUBSTITUTE(SUBSTITUTE(SUBSTITUTE(SUBSTITUTE(INDEX(RR_Variazioni,MATCH(cicloCorrente&"|"&INDEX(Classifica!$B$5:$B$19,$V53),RR_Chiave,0))&"","[{""dimensione"": ""","• "),"""}, {""dimensione"": """,")"&CHAR(10)&"• "),""", ""da"": "," "),", ""a"": "," → "),", ""evidenza"": """,": "),""", ""data_evidenza"": """," ("),"""}]",")"),"• severity","• Severity"),"• velocity","• Velocity"),"• prossimita","• Prossimita"),"• gap_controlli","• Gap_Controlli"),"• confidence","• Confidence"),"• probabilita","• Probabilita")),""))) | U53: =IF(Classifica!$B$14="","",IF(OR(10<=3,LEFT(Classifica!$H$14,9)="AGIRE ORA",Classifica!$G$14="Variato",Classifica!$G$14="Nuovo"),10,"")) | V53: =IFERROR(_xlfn.AGGREGATE(15,6,$U$44:$U$58,10),"") | W53: =IF($V53="","",IF($V53<=3,$V53&"° per score composito ("&FIXED(INDEX(Classifica!$D$5:$D$19,$V53),2)&IF(ISNUMBER(INDEX(Classifica!$F$5:$F$19,$V53)),IF(INDEX(Classifica!$F$5:$F$19,$V53)<>0,", "&IF(INDEX(Classifica!$F$5:$F$19,$V53)>0,"+","")&FIXED(INDEX(Classifica!$F$5:$F$19,$V53),2)&" sul ciclo prima",""),"")&"); ","")&IF(LEFT(INDEX(Classifica!$H$5:$H$19,$V53),9)="AGIRE ORA","AGIRE ORA: servono X + Y = "&FIXED(INDEX(Classifica!$Y$5:$Y$19,$V53)+INDEX(Classifica!$Z$5:$Z$19,$V53),2)&" anni per decidere e mitigare"&IF(N(INDEX(ANA_Anni_Adeguamento,INDEX(Classifica!$U$5:$U$19,$V53)))>0,", di cui "&N(INDEX(ANA_Anni_Adeguamento,INDEX(Classifica!$U$5:$U$19,$V53)))&" di adeguamento strutturale","")&"; ne restano Z = "&FIXED(INDEX(Classifica!$AA$5:$AA$19,$V53),1)&" prima che possa manifestarsi; ",IF(AND($V53<=3,LEFT(INDEX(Classifica!$H$5:$H$19,$V53),11)="Agire entro"),"margine di Mosca sotto l'anno ("&FIXED(INDEX(Classifica!$I$5:$I$19,$V53),2)&"); ",""))&IF(INDEX(Classifica!$G$5:$G$19,$V53)="Variato","variato nel ciclo"&IF(ISNUMBER(INDEX(Classifica!$F$5:$F$19,$V53)),IF(INDEX(Classifica!$F$5:$F$19,$V53)>0,": peggiora",IF(INDEX(Classifica!$F$5:$F$19,$V53)<0,": migliora","")),"")&"; ",IF(INDEX(Classifica!$G$5:$G$19,$V53)="Nuovo","nuovo nel ciclo; ",""))&IF(INDEX(ANA_Attenzione_Supervisore,INDEX(Classifica!$U$5:$U$19,$V53))="Sì","tema all'attenzione del supervisore; ","")&IF(COUNTIFS(KRI_ID_Rischio,INDEX(Classifica!$B$5:$B$19,$V53),KRI_Ciclo,cicloCorrente,KRI_In_Vigore,"Sì",KRI_Stato,"Rosso")>0,COUNTIFS(KRI_ID_Rischio,INDEX(Classifica!$B$5:$B$19,$V53),KRI_Ciclo,cicloCorrente,KRI_In_Vigore,"Sì",KRI_Stato,"Rosso")&" KRI in rosso; ","")&IF(INDEX(posNetti,INDEX(Classifica!$U$5:$U$19,$V53))>=sogliaDirezione,"notizie in peggioramento (+"&INDEX(posNetti,INDEX(Classifica!$U$5:$U$19,$V53))&" segnali netti in 4 settimane); ",IF(INDEX(posNetti,INDEX(Classifica!$U$5:$U$19,$V53))<=-sogliaDirezione,"notizie in miglioramento ("&INDEX(posNetti,INDEX(Classifica!$U$5:$U$19,$V53))&" segnali netti in 4 settimane); ",""))) | BH53: =2*PI()*48/72 -> 4.1887902 | BI53: =2*SIN($BH53) -> -1.7320508 | BJ53: =2*COS($BH53) -> -1 | BK53: =3*SIN($BH53) -> -2.5980762 | BL53: =3*COS($BH53) -> -1.5 | BM53: =4*SIN($BH53) -> -3.4641016 | BN53: =4*COS($BH53) -> -2 | BO53: =5*SIN($BH53) -> -4.330127 | BP53: =5*COS($BH53) -> -2.5
A54: =IF($V54="","",INDEX(Classifica!$B$5:$B$19,$V54)&CHAR(10)&INDEX(Classifica!$C$5:$C$19,$V54)&IF(INDEX(ANA_Attenzione_Supervisore,INDEX(Classifica!$U$5:$U$19,$V54))="Sì",CHAR(10)&"◆ attenzione del supervisore","")) | D54: =IF($V54="","",IF(LEFT(INDEX(Classifica!$H$5:$H$19,$V54),9)="AGIRE ORA","AGIRE ORA",IF(LEFT(INDEX(Classifica!$H$5:$H$19,$V54),11)="Agire entro","Entro l'anno",INDEX(Classifica!$H$5:$H$19,$V54)))) | E54: =IF($W54="","",LEFT($W54,LEN($W54)-2)&".") | I54: =IF($V54="","",IF(INDEX(Classifica!$G$5:$G$19,$V54)="Nuovo","Rischio nuovo nel ciclo.",IFERROR(IF(INDEX(RR_Variazioni,MATCH(cicloCorrente&"|"&INDEX(Classifica!$B$5:$B$19,$V54),RR_Chiave,0))&""="[]","Nessun valore cambiato: confermato sulle fonti del ciclo precedente.",SUBSTITUTE(SUBSTITUTE(SUBSTITUTE(SUBSTITUTE(SUBSTITUTE(SUBSTITUTE(SUBSTITUTE(SUBSTITUTE(SUBSTITUTE(SUBSTITUTE(SUBSTITUTE(SUBSTITUTE(SUBSTITUTE(INDEX(RR_Variazioni,MATCH(cicloCorrente&"|"&INDEX(Classifica!$B$5:$B$19,$V54),RR_Chiave,0))&"","[{""dimensione"": ""","• "),"""}, {""dimensione"": """,")"&CHAR(10)&"• "),""", ""da"": "," "),", ""a"": "," → "),", ""evidenza"": """,": "),""", ""data_evidenza"": """," ("),"""}]",")"),"• severity","• Severity"),"• velocity","• Velocity"),"• prossimita","• Prossimita"),"• gap_controlli","• Gap_Controlli"),"• confidence","• Confidence"),"• probabilita","• Probabilita")),""))) | U54: =IF(Classifica!$B$15="","",IF(OR(11<=3,LEFT(Classifica!$H$15,9)="AGIRE ORA",Classifica!$G$15="Variato",Classifica!$G$15="Nuovo"),11,"")) | V54: =IFERROR(_xlfn.AGGREGATE(15,6,$U$44:$U$58,11),"") | W54: =IF($V54="","",IF($V54<=3,$V54&"° per score composito ("&FIXED(INDEX(Classifica!$D$5:$D$19,$V54),2)&IF(ISNUMBER(INDEX(Classifica!$F$5:$F$19,$V54)),IF(INDEX(Classifica!$F$5:$F$19,$V54)<>0,", "&IF(INDEX(Classifica!$F$5:$F$19,$V54)>0,"+","")&FIXED(INDEX(Classifica!$F$5:$F$19,$V54),2)&" sul ciclo prima",""),"")&"); ","")&IF(LEFT(INDEX(Classifica!$H$5:$H$19,$V54),9)="AGIRE ORA","AGIRE ORA: servono X + Y = "&FIXED(INDEX(Classifica!$Y$5:$Y$19,$V54)+INDEX(Classifica!$Z$5:$Z$19,$V54),2)&" anni per decidere e mitigare"&IF(N(INDEX(ANA_Anni_Adeguamento,INDEX(Classifica!$U$5:$U$19,$V54)))>0,", di cui "&N(INDEX(ANA_Anni_Adeguamento,INDEX(Classifica!$U$5:$U$19,$V54)))&" di adeguamento strutturale","")&"; ne restano Z = "&FIXED(INDEX(Classifica!$AA$5:$AA$19,$V54),1)&" prima che possa manifestarsi; ",IF(AND($V54<=3,LEFT(INDEX(Classifica!$H$5:$H$19,$V54),11)="Agire entro"),"margine di Mosca sotto l'anno ("&FIXED(INDEX(Classifica!$I$5:$I$19,$V54),2)&"); ",""))&IF(INDEX(Classifica!$G$5:$G$19,$V54)="Variato","variato nel ciclo"&IF(ISNUMBER(INDEX(Classifica!$F$5:$F$19,$V54)),IF(INDEX(Classifica!$F$5:$F$19,$V54)>0,": peggiora",IF(INDEX(Classifica!$F$5:$F$19,$V54)<0,": migliora","")),"")&"; ",IF(INDEX(Classifica!$G$5:$G$19,$V54)="Nuovo","nuovo nel ciclo; ",""))&IF(INDEX(ANA_Attenzione_Supervisore,INDEX(Classifica!$U$5:$U$19,$V54))="Sì","tema all'attenzione del supervisore; ","")&IF(COUNTIFS(KRI_ID_Rischio,INDEX(Classifica!$B$5:$B$19,$V54),KRI_Ciclo,cicloCorrente,KRI_In_Vigore,"Sì",KRI_Stato,"Rosso")>0,COUNTIFS(KRI_ID_Rischio,INDEX(Classifica!$B$5:$B$19,$V54),KRI_Ciclo,cicloCorrente,KRI_In_Vigore,"Sì",KRI_Stato,"Rosso")&" KRI in rosso; ","")&IF(INDEX(posNetti,INDEX(Classifica!$U$5:$U$19,$V54))>=sogliaDirezione,"notizie in peggioramento (+"&INDEX(posNetti,INDEX(Classifica!$U$5:$U$19,$V54))&" segnali netti in 4 settimane); ",IF(INDEX(posNetti,INDEX(Classifica!$U$5:$U$19,$V54))<=-sogliaDirezione,"notizie in miglioramento ("&INDEX(posNetti,INDEX(Classifica!$U$5:$U$19,$V54))&" segnali netti in 4 settimane); ",""))) | BH54: =2*PI()*49/72 -> 4.2760567 | BI54: =2*SIN($BH54) -> -1.8126156 | BJ54: =2*COS($BH54) -> -0.84523652 | BK54: =3*SIN($BH54) -> -2.7189234 | BL54: =3*COS($BH54) -> -1.2678548 | BM54: =4*SIN($BH54) -> -3.6252311 | BN54: =4*COS($BH54) -> -1.690473 | BO54: =5*SIN($BH54) -> -4.5315389 | BP54: =5*COS($BH54) -> -2.1130913
A55: =IF($V55="","",INDEX(Classifica!$B$5:$B$19,$V55)&CHAR(10)&INDEX(Classifica!$C$5:$C$19,$V55)&IF(INDEX(ANA_Attenzione_Supervisore,INDEX(Classifica!$U$5:$U$19,$V55))="Sì",CHAR(10)&"◆ attenzione del supervisore","")) | D55: =IF($V55="","",IF(LEFT(INDEX(Classifica!$H$5:$H$19,$V55),9)="AGIRE ORA","AGIRE ORA",IF(LEFT(INDEX(Classifica!$H$5:$H$19,$V55),11)="Agire entro","Entro l'anno",INDEX(Classifica!$H$5:$H$19,$V55)))) | E55: =IF($W55="","",LEFT($W55,LEN($W55)-2)&".") | I55: =IF($V55="","",IF(INDEX(Classifica!$G$5:$G$19,$V55)="Nuovo","Rischio nuovo nel ciclo.",IFERROR(IF(INDEX(RR_Variazioni,MATCH(cicloCorrente&"|"&INDEX(Classifica!$B$5:$B$19,$V55),RR_Chiave,0))&""="[]","Nessun valore cambiato: confermato sulle fonti del ciclo precedente.",SUBSTITUTE(SUBSTITUTE(SUBSTITUTE(SUBSTITUTE(SUBSTITUTE(SUBSTITUTE(SUBSTITUTE(SUBSTITUTE(SUBSTITUTE(SUBSTITUTE(SUBSTITUTE(SUBSTITUTE(SUBSTITUTE(INDEX(RR_Variazioni,MATCH(cicloCorrente&"|"&INDEX(Classifica!$B$5:$B$19,$V55),RR_Chiave,0))&"","[{""dimensione"": ""","• "),"""}, {""dimensione"": """,")"&CHAR(10)&"• "),""", ""da"": "," "),", ""a"": "," → "),", ""evidenza"": """,": "),""", ""data_evidenza"": """," ("),"""}]",")"),"• severity","• Severity"),"• velocity","• Velocity"),"• prossimita","• Prossimita"),"• gap_controlli","• Gap_Controlli"),"• confidence","• Confidence"),"• probabilita","• Probabilita")),""))) | U55: =IF(Classifica!$B$16="","",IF(OR(12<=3,LEFT(Classifica!$H$16,9)="AGIRE ORA",Classifica!$G$16="Variato",Classifica!$G$16="Nuovo"),12,"")) | V55: =IFERROR(_xlfn.AGGREGATE(15,6,$U$44:$U$58,12),"") | W55: =IF($V55="","",IF($V55<=3,$V55&"° per score composito ("&FIXED(INDEX(Classifica!$D$5:$D$19,$V55),2)&IF(ISNUMBER(INDEX(Classifica!$F$5:$F$19,$V55)),IF(INDEX(Classifica!$F$5:$F$19,$V55)<>0,", "&IF(INDEX(Classifica!$F$5:$F$19,$V55)>0,"+","")&FIXED(INDEX(Classifica!$F$5:$F$19,$V55),2)&" sul ciclo prima",""),"")&"); ","")&IF(LEFT(INDEX(Classifica!$H$5:$H$19,$V55),9)="AGIRE ORA","AGIRE ORA: servono X + Y = "&FIXED(INDEX(Classifica!$Y$5:$Y$19,$V55)+INDEX(Classifica!$Z$5:$Z$19,$V55),2)&" anni per decidere e mitigare"&IF(N(INDEX(ANA_Anni_Adeguamento,INDEX(Classifica!$U$5:$U$19,$V55)))>0,", di cui "&N(INDEX(ANA_Anni_Adeguamento,INDEX(Classifica!$U$5:$U$19,$V55)))&" di adeguamento strutturale","")&"; ne restano Z = "&FIXED(INDEX(Classifica!$AA$5:$AA$19,$V55),1)&" prima che possa manifestarsi; ",IF(AND($V55<=3,LEFT(INDEX(Classifica!$H$5:$H$19,$V55),11)="Agire entro"),"margine di Mosca sotto l'anno ("&FIXED(INDEX(Classifica!$I$5:$I$19,$V55),2)&"); ",""))&IF(INDEX(Classifica!$G$5:$G$19,$V55)="Variato","variato nel ciclo"&IF(ISNUMBER(INDEX(Classifica!$F$5:$F$19,$V55)),IF(INDEX(Classifica!$F$5:$F$19,$V55)>0,": peggiora",IF(INDEX(Classifica!$F$5:$F$19,$V55)<0,": migliora","")),"")&"; ",IF(INDEX(Classifica!$G$5:$G$19,$V55)="Nuovo","nuovo nel ciclo; ",""))&IF(INDEX(ANA_Attenzione_Supervisore,INDEX(Classifica!$U$5:$U$19,$V55))="Sì","tema all'attenzione del supervisore; ","")&IF(COUNTIFS(KRI_ID_Rischio,INDEX(Classifica!$B$5:$B$19,$V55),KRI_Ciclo,cicloCorrente,KRI_In_Vigore,"Sì",KRI_Stato,"Rosso")>0,COUNTIFS(KRI_ID_Rischio,INDEX(Classifica!$B$5:$B$19,$V55),KRI_Ciclo,cicloCorrente,KRI_In_Vigore,"Sì",KRI_Stato,"Rosso")&" KRI in rosso; ","")&IF(INDEX(posNetti,INDEX(Classifica!$U$5:$U$19,$V55))>=sogliaDirezione,"notizie in peggioramento (+"&INDEX(posNetti,INDEX(Classifica!$U$5:$U$19,$V55))&" segnali netti in 4 settimane); ",IF(INDEX(posNetti,INDEX(Classifica!$U$5:$U$19,$V55))<=-sogliaDirezione,"notizie in miglioramento ("&INDEX(posNetti,INDEX(Classifica!$U$5:$U$19,$V55))&" segnali netti in 4 settimane); ",""))) | BH55: =2*PI()*50/72 -> 4.3633231 | BI55: =2*SIN($BH55) -> -1.8793852 | BJ55: =2*COS($BH55) -> -0.68404029 | BK55: =3*SIN($BH55) -> -2.8190779 | BL55: =3*COS($BH55) -> -1.0260604 | BM55: =4*SIN($BH55) -> -3.7587705 | BN55: =4*COS($BH55) -> -1.3680806 | BO55: =5*SIN($BH55) -> -4.6984631 | BP55: =5*COS($BH55) -> -1.7101007
A56: =IF($V56="","",INDEX(Classifica!$B$5:$B$19,$V56)&CHAR(10)&INDEX(Classifica!$C$5:$C$19,$V56)&IF(INDEX(ANA_Attenzione_Supervisore,INDEX(Classifica!$U$5:$U$19,$V56))="Sì",CHAR(10)&"◆ attenzione del supervisore","")) | D56: =IF($V56="","",IF(LEFT(INDEX(Classifica!$H$5:$H$19,$V56),9)="AGIRE ORA","AGIRE ORA",IF(LEFT(INDEX(Classifica!$H$5:$H$19,$V56),11)="Agire entro","Entro l'anno",INDEX(Classifica!$H$5:$H$19,$V56)))) | E56: =IF($W56="","",LEFT($W56,LEN($W56)-2)&".") | I56: =IF($V56="","",IF(INDEX(Classifica!$G$5:$G$19,$V56)="Nuovo","Rischio nuovo nel ciclo.",IFERROR(IF(INDEX(RR_Variazioni,MATCH(cicloCorrente&"|"&INDEX(Classifica!$B$5:$B$19,$V56),RR_Chiave,0))&""="[]","Nessun valore cambiato: confermato sulle fonti del ciclo precedente.",SUBSTITUTE(SUBSTITUTE(SUBSTITUTE(SUBSTITUTE(SUBSTITUTE(SUBSTITUTE(SUBSTITUTE(SUBSTITUTE(SUBSTITUTE(SUBSTITUTE(SUBSTITUTE(SUBSTITUTE(SUBSTITUTE(INDEX(RR_Variazioni,MATCH(cicloCorrente&"|"&INDEX(Classifica!$B$5:$B$19,$V56),RR_Chiave,0))&"","[{""dimensione"": ""","• "),"""}, {""dimensione"": """,")"&CHAR(10)&"• "),""", ""da"": "," "),", ""a"": "," → "),", ""evidenza"": """,": "),""", ""data_evidenza"": """," ("),"""}]",")"),"• severity","• Severity"),"• velocity","• Velocity"),"• prossimita","• Prossimita"),"• gap_controlli","• Gap_Controlli"),"• confidence","• Confidence"),"• probabilita","• Probabilita")),""))) | U56: =IF(Classifica!$B$17="","",IF(OR(13<=3,LEFT(Classifica!$H$17,9)="AGIRE ORA",Classifica!$G$17="Variato",Classifica!$G$17="Nuovo"),13,"")) | V56: =IFERROR(_xlfn.AGGREGATE(15,6,$U$44:$U$58,13),"") | W56: =IF($V56="","",IF($V56<=3,$V56&"° per score composito ("&FIXED(INDEX(Classifica!$D$5:$D$19,$V56),2)&IF(ISNUMBER(INDEX(Classifica!$F$5:$F$19,$V56)),IF(INDEX(Classifica!$F$5:$F$19,$V56)<>0,", "&IF(INDEX(Classifica!$F$5:$F$19,$V56)>0,"+","")&FIXED(INDEX(Classifica!$F$5:$F$19,$V56),2)&" sul ciclo prima",""),"")&"); ","")&IF(LEFT(INDEX(Classifica!$H$5:$H$19,$V56),9)="AGIRE ORA","AGIRE ORA: servono X + Y = "&FIXED(INDEX(Classifica!$Y$5:$Y$19,$V56)+INDEX(Classifica!$Z$5:$Z$19,$V56),2)&" anni per decidere e mitigare"&IF(N(INDEX(ANA_Anni_Adeguamento,INDEX(Classifica!$U$5:$U$19,$V56)))>0,", di cui "&N(INDEX(ANA_Anni_Adeguamento,INDEX(Classifica!$U$5:$U$19,$V56)))&" di adeguamento strutturale","")&"; ne restano Z = "&FIXED(INDEX(Classifica!$AA$5:$AA$19,$V56),1)&" prima che possa manifestarsi; ",IF(AND($V56<=3,LEFT(INDEX(Classifica!$H$5:$H$19,$V56),11)="Agire entro"),"margine di Mosca sotto l'anno ("&FIXED(INDEX(Classifica!$I$5:$I$19,$V56),2)&"); ",""))&IF(INDEX(Classifica!$G$5:$G$19,$V56)="Variato","variato nel ciclo"&IF(ISNUMBER(INDEX(Classifica!$F$5:$F$19,$V56)),IF(INDEX(Classifica!$F$5:$F$19,$V56)>0,": peggiora",IF(INDEX(Classifica!$F$5:$F$19,$V56)<0,": migliora","")),"")&"; ",IF(INDEX(Classifica!$G$5:$G$19,$V56)="Nuovo","nuovo nel ciclo; ",""))&IF(INDEX(ANA_Attenzione_Supervisore,INDEX(Classifica!$U$5:$U$19,$V56))="Sì","tema all'attenzione del supervisore; ","")&IF(COUNTIFS(KRI_ID_Rischio,INDEX(Classifica!$B$5:$B$19,$V56),KRI_Ciclo,cicloCorrente,KRI_In_Vigore,"Sì",KRI_Stato,"Rosso")>0,COUNTIFS(KRI_ID_Rischio,INDEX(Classifica!$B$5:$B$19,$V56),KRI_Ciclo,cicloCorrente,KRI_In_Vigore,"Sì",KRI_Stato,"Rosso")&" KRI in rosso; ","")&IF(INDEX(posNetti,INDEX(Classifica!$U$5:$U$19,$V56))>=sogliaDirezione,"notizie in peggioramento (+"&INDEX(posNetti,INDEX(Classifica!$U$5:$U$19,$V56))&" segnali netti in 4 settimane); ",IF(INDEX(posNetti,INDEX(Classifica!$U$5:$U$19,$V56))<=-sogliaDirezione,"notizie in miglioramento ("&INDEX(posNetti,INDEX(Classifica!$U$5:$U$19,$V56))&" segnali netti in 4 settimane); ",""))) | BH56: =2*PI()*51/72 -> 4.4505896 | BI56: =2*SIN($BH56) -> -1.9318517 | BJ56: =2*COS($BH56) -> -0.51763809 | BK56: =3*SIN($BH56) -> -2.8977775 | BL56: =3*COS($BH56) -> -0.77645714 | BM56: =4*SIN($BH56) -> -3.8637033 | BN56: =4*COS($BH56) -> -1.0352762 | BO56: =5*SIN($BH56) -> -4.8296291 | BP56: =5*COS($BH56) -> -1.2940952
A57: =IF($V57="","",INDEX(Classifica!$B$5:$B$19,$V57)&CHAR(10)&INDEX(Classifica!$C$5:$C$19,$V57)&IF(INDEX(ANA_Attenzione_Supervisore,INDEX(Classifica!$U$5:$U$19,$V57))="Sì",CHAR(10)&"◆ attenzione del supervisore","")) | D57: =IF($V57="","",IF(LEFT(INDEX(Classifica!$H$5:$H$19,$V57),9)="AGIRE ORA","AGIRE ORA",IF(LEFT(INDEX(Classifica!$H$5:$H$19,$V57),11)="Agire entro","Entro l'anno",INDEX(Classifica!$H$5:$H$19,$V57)))) | E57: =IF($W57="","",LEFT($W57,LEN($W57)-2)&".") | I57: =IF($V57="","",IF(INDEX(Classifica!$G$5:$G$19,$V57)="Nuovo","Rischio nuovo nel ciclo.",IFERROR(IF(INDEX(RR_Variazioni,MATCH(cicloCorrente&"|"&INDEX(Classifica!$B$5:$B$19,$V57),RR_Chiave,0))&""="[]","Nessun valore cambiato: confermato sulle fonti del ciclo precedente.",SUBSTITUTE(SUBSTITUTE(SUBSTITUTE(SUBSTITUTE(SUBSTITUTE(SUBSTITUTE(SUBSTITUTE(SUBSTITUTE(SUBSTITUTE(SUBSTITUTE(SUBSTITUTE(SUBSTITUTE(SUBSTITUTE(INDEX(RR_Variazioni,MATCH(cicloCorrente&"|"&INDEX(Classifica!$B$5:$B$19,$V57),RR_Chiave,0))&"","[{""dimensione"": ""","• "),"""}, {""dimensione"": """,")"&CHAR(10)&"• "),""", ""da"": "," "),", ""a"": "," → "),", ""evidenza"": """,": "),""", ""data_evidenza"": """," ("),"""}]",")"),"• severity","• Severity"),"• velocity","• Velocity"),"• prossimita","• Prossimita"),"• gap_controlli","• Gap_Controlli"),"• confidence","• Confidence"),"• probabilita","• Probabilita")),""))) | U57: =IF(Classifica!$B$18="","",IF(OR(14<=3,LEFT(Classifica!$H$18,9)="AGIRE ORA",Classifica!$G$18="Variato",Classifica!$G$18="Nuovo"),14,"")) | V57: =IFERROR(_xlfn.AGGREGATE(15,6,$U$44:$U$58,14),"") | W57: =IF($V57="","",IF($V57<=3,$V57&"° per score composito ("&FIXED(INDEX(Classifica!$D$5:$D$19,$V57),2)&IF(ISNUMBER(INDEX(Classifica!$F$5:$F$19,$V57)),IF(INDEX(Classifica!$F$5:$F$19,$V57)<>0,", "&IF(INDEX(Classifica!$F$5:$F$19,$V57)>0,"+","")&FIXED(INDEX(Classifica!$F$5:$F$19,$V57),2)&" sul ciclo prima",""),"")&"); ","")&IF(LEFT(INDEX(Classifica!$H$5:$H$19,$V57),9)="AGIRE ORA","AGIRE ORA: servono X + Y = "&FIXED(INDEX(Classifica!$Y$5:$Y$19,$V57)+INDEX(Classifica!$Z$5:$Z$19,$V57),2)&" anni per decidere e mitigare"&IF(N(INDEX(ANA_Anni_Adeguamento,INDEX(Classifica!$U$5:$U$19,$V57)))>0,", di cui "&N(INDEX(ANA_Anni_Adeguamento,INDEX(Classifica!$U$5:$U$19,$V57)))&" di adeguamento strutturale","")&"; ne restano Z = "&FIXED(INDEX(Classifica!$AA$5:$AA$19,$V57),1)&" prima che possa manifestarsi; ",IF(AND($V57<=3,LEFT(INDEX(Classifica!$H$5:$H$19,$V57),11)="Agire entro"),"margine di Mosca sotto l'anno ("&FIXED(INDEX(Classifica!$I$5:$I$19,$V57),2)&"); ",""))&IF(INDEX(Classifica!$G$5:$G$19,$V57)="Variato","variato nel ciclo"&IF(ISNUMBER(INDEX(Classifica!$F$5:$F$19,$V57)),IF(INDEX(Classifica!$F$5:$F$19,$V57)>0,": peggiora",IF(INDEX(Classifica!$F$5:$F$19,$V57)<0,": migliora","")),"")&"; ",IF(INDEX(Classifica!$G$5:$G$19,$V57)="Nuovo","nuovo nel ciclo; ",""))&IF(INDEX(ANA_Attenzione_Supervisore,INDEX(Classifica!$U$5:$U$19,$V57))="Sì","tema all'attenzione del supervisore; ","")&IF(COUNTIFS(KRI_ID_Rischio,INDEX(Classifica!$B$5:$B$19,$V57),KRI_Ciclo,cicloCorrente,KRI_In_Vigore,"Sì",KRI_Stato,"Rosso")>0,COUNTIFS(KRI_ID_Rischio,INDEX(Classifica!$B$5:$B$19,$V57),KRI_Ciclo,cicloCorrente,KRI_In_Vigore,"Sì",KRI_Stato,"Rosso")&" KRI in rosso; ","")&IF(INDEX(posNetti,INDEX(Classifica!$U$5:$U$19,$V57))>=sogliaDirezione,"notizie in peggioramento (+"&INDEX(posNetti,INDEX(Classifica!$U$5:$U$19,$V57))&" segnali netti in 4 settimane); ",IF(INDEX(posNetti,INDEX(Classifica!$U$5:$U$19,$V57))<=-sogliaDirezione,"notizie in miglioramento ("&INDEX(posNetti,INDEX(Classifica!$U$5:$U$19,$V57))&" segnali netti in 4 settimane); ",""))) | BH57: =2*PI()*52/72 -> 4.5378561 | BI57: =2*SIN($BH57) -> -1.9696155 | BJ57: =2*COS($BH57) -> -0.34729636 | BK57: =3*SIN($BH57) -> -2.9544233 | BL57: =3*COS($BH57) -> -0.52094453 | BM57: =4*SIN($BH57) -> -3.939231 | BN57: =4*COS($BH57) -> -0.69459271 | BO57: =5*SIN($BH57) -> -4.9240388 | BP57: =5*COS($BH57) -> -0.86824089
A58: =IF($V58="","",INDEX(Classifica!$B$5:$B$19,$V58)&CHAR(10)&INDEX(Classifica!$C$5:$C$19,$V58)&IF(INDEX(ANA_Attenzione_Supervisore,INDEX(Classifica!$U$5:$U$19,$V58))="Sì",CHAR(10)&"◆ attenzione del supervisore","")) | D58: =IF($V58="","",IF(LEFT(INDEX(Classifica!$H$5:$H$19,$V58),9)="AGIRE ORA","AGIRE ORA",IF(LEFT(INDEX(Classifica!$H$5:$H$19,$V58),11)="Agire entro","Entro l'anno",INDEX(Classifica!$H$5:$H$19,$V58)))) | E58: =IF($W58="","",LEFT($W58,LEN($W58)-2)&".") | I58: =IF($V58="","",IF(INDEX(Classifica!$G$5:$G$19,$V58)="Nuovo","Rischio nuovo nel ciclo.",IFERROR(IF(INDEX(RR_Variazioni,MATCH(cicloCorrente&"|"&INDEX(Classifica!$B$5:$B$19,$V58),RR_Chiave,0))&""="[]","Nessun valore cambiato: confermato sulle fonti del ciclo precedente.",SUBSTITUTE(SUBSTITUTE(SUBSTITUTE(SUBSTITUTE(SUBSTITUTE(SUBSTITUTE(SUBSTITUTE(SUBSTITUTE(SUBSTITUTE(SUBSTITUTE(SUBSTITUTE(SUBSTITUTE(SUBSTITUTE(INDEX(RR_Variazioni,MATCH(cicloCorrente&"|"&INDEX(Classifica!$B$5:$B$19,$V58),RR_Chiave,0))&"","[{""dimensione"": ""","• "),"""}, {""dimensione"": """,")"&CHAR(10)&"• "),""", ""da"": "," "),", ""a"": "," → "),", ""evidenza"": """,": "),""", ""data_evidenza"": """," ("),"""}]",")"),"• severity","• Severity"),"• velocity","• Velocity"),"• prossimita","• Prossimita"),"• gap_controlli","• Gap_Controlli"),"• confidence","• Confidence"),"• probabilita","• Probabilita")),""))) | U58: =IF(Classifica!$B$19="","",IF(OR(15<=3,LEFT(Classifica!$H$19,9)="AGIRE ORA",Classifica!$G$19="Variato",Classifica!$G$19="Nuovo"),15,"")) | V58: =IFERROR(_xlfn.AGGREGATE(15,6,$U$44:$U$58,15),"") | W58: =IF($V58="","",IF($V58<=3,$V58&"° per score composito ("&FIXED(INDEX(Classifica!$D$5:$D$19,$V58),2)&IF(ISNUMBER(INDEX(Classifica!$F$5:$F$19,$V58)),IF(INDEX(Classifica!$F$5:$F$19,$V58)<>0,", "&IF(INDEX(Classifica!$F$5:$F$19,$V58)>0,"+","")&FIXED(INDEX(Classifica!$F$5:$F$19,$V58),2)&" sul ciclo prima",""),"")&"); ","")&IF(LEFT(INDEX(Classifica!$H$5:$H$19,$V58),9)="AGIRE ORA","AGIRE ORA: servono X + Y = "&FIXED(INDEX(Classifica!$Y$5:$Y$19,$V58)+INDEX(Classifica!$Z$5:$Z$19,$V58),2)&" anni per decidere e mitigare"&IF(N(INDEX(ANA_Anni_Adeguamento,INDEX(Classifica!$U$5:$U$19,$V58)))>0,", di cui "&N(INDEX(ANA_Anni_Adeguamento,INDEX(Classifica!$U$5:$U$19,$V58)))&" di adeguamento strutturale","")&"; ne restano Z = "&FIXED(INDEX(Classifica!$AA$5:$AA$19,$V58),1)&" prima che possa manifestarsi; ",IF(AND($V58<=3,LEFT(INDEX(Classifica!$H$5:$H$19,$V58),11)="Agire entro"),"margine di Mosca sotto l'anno ("&FIXED(INDEX(Classifica!$I$5:$I$19,$V58),2)&"); ",""))&IF(INDEX(Classifica!$G$5:$G$19,$V58)="Variato","variato nel ciclo"&IF(ISNUMBER(INDEX(Classifica!$F$5:$F$19,$V58)),IF(INDEX(Classifica!$F$5:$F$19,$V58)>0,": peggiora",IF(INDEX(Classifica!$F$5:$F$19,$V58)<0,": migliora","")),"")&"; ",IF(INDEX(Classifica!$G$5:$G$19,$V58)="Nuovo","nuovo nel ciclo; ",""))&IF(INDEX(ANA_Attenzione_Supervisore,INDEX(Classifica!$U$5:$U$19,$V58))="Sì","tema all'attenzione del supervisore; ","")&IF(COUNTIFS(KRI_ID_Rischio,INDEX(Classifica!$B$5:$B$19,$V58),KRI_Ciclo,cicloCorrente,KRI_In_Vigore,"Sì",KRI_Stato,"Rosso")>0,COUNTIFS(KRI_ID_Rischio,INDEX(Classifica!$B$5:$B$19,$V58),KRI_Ciclo,cicloCorrente,KRI_In_Vigore,"Sì",KRI_Stato,"Rosso")&" KRI in rosso; ","")&IF(INDEX(posNetti,INDEX(Classifica!$U$5:$U$19,$V58))>=sogliaDirezione,"notizie in peggioramento (+"&INDEX(posNetti,INDEX(Classifica!$U$5:$U$19,$V58))&" segnali netti in 4 settimane); ",IF(INDEX(posNetti,INDEX(Classifica!$U$5:$U$19,$V58))<=-sogliaDirezione,"notizie in miglioramento ("&INDEX(posNetti,INDEX(Classifica!$U$5:$U$19,$V58))&" segnali netti in 4 settimane); ",""))) | BH58: =2*PI()*53/72 -> 4.6251225 | BI58: =2*SIN($BH58) -> -1.9923894 | BJ58: =2*COS($BH58) -> -0.17431149 | BK58: =3*SIN($BH58) -> -2.9885841 | BL58: =3*COS($BH58) -> -0.26146723 | BM58: =4*SIN($BH58) -> -3.9847788 | BN58: =4*COS($BH58) -> -0.34862297 | BO58: =5*SIN($BH58) -> -4.9809735 | BP58: =5*COS($BH58) -> -0.43577871
BH59: =2*PI()*54/72 -> 4.712389 | BI59: =2*SIN($BH59) -> -2 | BJ59: =2*COS($BH59) -> -3.6754454e-16 | BK59: =3*SIN($BH59) -> -3 | BL59: =3*COS($BH59) -> -5.513168e-16 | BM59: =4*SIN($BH59) -> -4 | BN59: =4*COS($BH59) -> -7.3508907e-16 | BO59: =5*SIN($BH59) -> -5 | BP59: =5*COS($BH59) -> -9.1886134e-16
A60: Limiti: Le valutazioni sono prodotte con il supporto di un modello linguistico ancorato alla rubrica della Banca e verificate da controlli deterministici e da un challenger indipendente. Non sono stime di perdita ne' probabilita'. Gli score cambiano solo nel ciclo trimestrale, su evidenza datata; le notizie settimanali producono segnali, non variazioni. Il controllo C4 (plausibilita' rispetto ai descrittori) e' solo di giudizio. La valutazione e' valida dopo l'approvazione indicata in Approvato_Da. | BH60: =2*PI()*55/72 -> 4.7996554 | BI60: =2*SIN($BH60) -> -1.9923894 | BJ60: =2*COS($BH60) -> 0.17431149 | BK60: =3*SIN($BH60) -> -2.9885841 | BL60: =3*COS($BH60) -> 0.26146723 | BM60: =4*SIN($BH60) -> -3.9847788 | BN60: =4*COS($BH60) -> 0.34862297 | BO60: =5*SIN($BH60) -> -4.9809735 | BP60: =5*COS($BH60) -> 0.43577871
A61: Legenda — NFR-nn = codice del rischio; ◆ = tema all'attenzione del supervisore (BCE, EBA, Banca d'Italia), indicato dal validatore. P = Probabilita, S = Severity, P x I = Probabilita x Severity (impatto), da 1 a 25. X = anni per decidere e avviare la mitigazione (un trimestre); Y = anni per mitigare (azioni o adeguamento strutturale); Z = anni prima che il rischio possa manifestarsi (dalla Prossimita); AGIRE ORA = X + Y > Z. KRI = indicatore di rischio (Key Risk Indicator). A1 = agente che valuta i rischi ogni trimestre; A5 = agente di controllo indipendente. | BH61: =2*PI()*56/72 -> 4.8869219 | BI61: =2*SIN($BH61) -> -1.9696155 | BJ61: =2*COS($BH61) -> 0.34729636 | BK61: =3*SIN($BH61) -> -2.9544233 | BL61: =3*COS($BH61) -> 0.52094453 | BM61: =4*SIN($BH61) -> -3.939231 | BN61: =4*COS($BH61) -> 0.69459271 | BO61: =5*SIN($BH61) -> -4.9240388 | BP61: =5*COS($BH61) -> 0.86824089
BH62: =2*PI()*57/72 -> 4.9741884 | BI62: =2*SIN($BH62) -> -1.9318517 | BJ62: =2*COS($BH62) -> 0.51763809 | BK62: =3*SIN($BH62) -> -2.8977775 | BL62: =3*COS($BH62) -> 0.77645714 | BM62: =4*SIN($BH62) -> -3.8637033 | BN62: =4*COS($BH62) -> 1.0352762 | BO62: =5*SIN($BH62) -> -4.8296291 | BP62: =5*COS($BH62) -> 1.2940952
BH63: =2*PI()*58/72 -> 5.0614548 | BI63: =2*SIN($BH63) -> -1.8793852 | BJ63: =2*COS($BH63) -> 0.68404029 | BK63: =3*SIN($BH63) -> -2.8190779 | BL63: =3*COS($BH63) -> 1.0260604 | BM63: =4*SIN($BH63) -> -3.7587705 | BN63: =4*COS($BH63) -> 1.3680806 | BO63: =5*SIN($BH63) -> -4.6984631 | BP63: =5*COS($BH63) -> 1.7101007
BH64: =2*PI()*59/72 -> 5.1487213 | BI64: =2*SIN($BH64) -> -1.8126156 | BJ64: =2*COS($BH64) -> 0.84523652 | BK64: =3*SIN($BH64) -> -2.7189234 | BL64: =3*COS($BH64) -> 1.2678548 | BM64: =4*SIN($BH64) -> -3.6252311 | BN64: =4*COS($BH64) -> 1.690473 | BO64: =5*SIN($BH64) -> -4.5315389 | BP64: =5*COS($BH64) -> 2.1130913
BH65: =2*PI()*60/72 -> 5.2359878 | BI65: =2*SIN($BH65) -> -1.7320508 | BJ65: =2*COS($BH65) -> 1 | BK65: =3*SIN($BH65) -> -2.5980762 | BL65: =3*COS($BH65) -> 1.5 | BM65: =4*SIN($BH65) -> -3.4641016 | BN65: =4*COS($BH65) -> 2 | BO65: =5*SIN($BH65) -> -4.330127 | BP65: =5*COS($BH65) -> 2.5
BH66: =2*PI()*61/72 -> 5.3232542 | BI66: =2*SIN($BH66) -> -1.6383041 | BJ66: =2*COS($BH66) -> 1.1471529 | BK66: =3*SIN($BH66) -> -2.4574561 | BL66: =3*COS($BH66) -> 1.7207293 | BM66: =4*SIN($BH66) -> -3.2766082 | BN66: =4*COS($BH66) -> 2.2943057 | BO66: =5*SIN($BH66) -> -4.0957602 | BP66: =5*COS($BH66) -> 2.8678822
BH67: =2*PI()*62/72 -> 5.4105207 | BI67: =2*SIN($BH67) -> -1.5320889 | BJ67: =2*COS($BH67) -> 1.2855752 | BK67: =3*SIN($BH67) -> -2.2981333 | BL67: =3*COS($BH67) -> 1.9283628 | BM67: =4*SIN($BH67) -> -3.0641778 | BN67: =4*COS($BH67) -> 2.5711504 | BO67: =5*SIN($BH67) -> -3.8302222 | BP67: =5*COS($BH67) -> 3.213938
BH68: =2*PI()*63/72 -> 5.4977871 | BI68: =2*SIN($BH68) -> -1.4142136 | BJ68: =2*COS($BH68) -> 1.4142136 | BK68: =3*SIN($BH68) -> -2.1213203 | BL68: =3*COS($BH68) -> 2.1213203 | BM68: =4*SIN($BH68) -> -2.8284271 | BN68: =4*COS($BH68) -> 2.8284271 | BO68: =5*SIN($BH68) -> -3.5355339 | BP68: =5*COS($BH68) -> 3.5355339
BH69: =2*PI()*64/72 -> 5.5850536 | BI69: =2*SIN($BH69) -> -1.2855752 | BJ69: =2*COS($BH69) -> 1.5320889 | BK69: =3*SIN($BH69) -> -1.9283628 | BL69: =3*COS($BH69) -> 2.2981333 | BM69: =4*SIN($BH69) -> -2.5711504 | BN69: =4*COS($BH69) -> 3.0641778 | BO69: =5*SIN($BH69) -> -3.213938 | BP69: =5*COS($BH69) -> 3.8302222
BH70: =2*PI()*65/72 -> 5.6723201 | BI70: =2*SIN($BH70) -> -1.1471529 | BJ70: =2*COS($BH70) -> 1.6383041 | BK70: =3*SIN($BH70) -> -1.7207293 | BL70: =3*COS($BH70) -> 2.4574561 | BM70: =4*SIN($BH70) -> -2.2943057 | BN70: =4*COS($BH70) -> 3.2766082 | BO70: =5*SIN($BH70) -> -2.8678822 | BP70: =5*COS($BH70) -> 4.0957602
BH71: =2*PI()*66/72 -> 5.7595865 | BI71: =2*SIN($BH71) -> -1 | BJ71: =2*COS($BH71) -> 1.7320508 | BK71: =3*SIN($BH71) -> -1.5 | BL71: =3*COS($BH71) -> 2.5980762 | BM71: =4*SIN($BH71) -> -2 | BN71: =4*COS($BH71) -> 3.4641016 | BO71: =5*SIN($BH71) -> -2.5 | BP71: =5*COS($BH71) -> 4.330127
BH72: =2*PI()*67/72 -> 5.846853 | BI72: =2*SIN($BH72) -> -0.84523652 | BJ72: =2*COS($BH72) -> 1.8126156 | BK72: =3*SIN($BH72) -> -1.2678548 | BL72: =3*COS($BH72) -> 2.7189234 | BM72: =4*SIN($BH72) -> -1.690473 | BN72: =4*COS($BH72) -> 3.6252311 | BO72: =5*SIN($BH72) -> -2.1130913 | BP72: =5*COS($BH72) -> 4.5315389
BH73: =2*PI()*68/72 -> 5.9341195 | BI73: =2*SIN($BH73) -> -0.68404029 | BJ73: =2*COS($BH73) -> 1.8793852 | BK73: =3*SIN($BH73) -> -1.0260604 | BL73: =3*COS($BH73) -> 2.8190779 | BM73: =4*SIN($BH73) -> -1.3680806 | BN73: =4*COS($BH73) -> 3.7587705 | BO73: =5*SIN($BH73) -> -1.7101007 | BP73: =5*COS($BH73) -> 4.6984631
BH74: =2*PI()*69/72 -> 6.0213859 | BI74: =2*SIN($BH74) -> -0.51763809 | BJ74: =2*COS($BH74) -> 1.9318517 | BK74: =3*SIN($BH74) -> -0.77645714 | BL74: =3*COS($BH74) -> 2.8977775 | BM74: =4*SIN($BH74) -> -1.0352762 | BN74: =4*COS($BH74) -> 3.8637033 | BO74: =5*SIN($BH74) -> -1.2940952 | BP74: =5*COS($BH74) -> 4.8296291
BH75: =2*PI()*70/72 -> 6.1086524 | BI75: =2*SIN($BH75) -> -0.34729636 | BJ75: =2*COS($BH75) -> 1.9696155 | BK75: =3*SIN($BH75) -> -0.52094453 | BL75: =3*COS($BH75) -> 2.9544233 | BM75: =4*SIN($BH75) -> -0.69459271 | BN75: =4*COS($BH75) -> 3.939231 | BO75: =5*SIN($BH75) -> -0.86824089 | BP75: =5*COS($BH75) -> 4.9240388
BH76: =2*PI()*71/72 -> 6.1959188 | BI76: =2*SIN($BH76) -> -0.17431149 | BJ76: =2*COS($BH76) -> 1.9923894 | BK76: =3*SIN($BH76) -> -0.26146723 | BL76: =3*COS($BH76) -> 2.9885841 | BM76: =4*SIN($BH76) -> -0.34862297 | BN76: =4*COS($BH76) -> 3.9847788 | BO76: =5*SIN($BH76) -> -0.43577871 | BP76: =5*COS($BH76) -> 4.9809735
BH77: =2*PI()*72/72 -> 6.2831853 | BI77: =2*SIN($BH77) -> -4.9005938e-16 | BJ77: =2*COS($BH77) -> 2 | BK77: =3*SIN($BH77) -> -7.3508907e-16 | BL77: =3*COS($BH77) -> 3 | BM77: =4*SIN($BH77) -> -9.8011876e-16 | BN77: =4*COS($BH77) -> 4 | BO77: =5*SIN($BH77) -> -1.2251485e-15 | BP77: =5*COS($BH77) -> 5

Sheet Classifica
A1: ="Horizon Scan NFR — Classifica e lente di Mosca · "&etichettaCiclo -> Horizon Scan NFR — Classifica e lente di Mosca · Ciclo 2026Q3 · dati al 30/09/2026 · validato · Uso interno
A2: CICLO TRIMESTRALE — calcolato dal foglio sui valori del ciclo; nessun agente ordina o stima l'urgenza. Come si legge: un rischio per barra, dal piu' alto per score composito (1-5, 5 = peggiore). Colore = urgenza di Mosca: rosso agire ora, ambra entro l'anno, grigio c'e' margine. A destra la lente di Mosca spiega il colore: tempo necessario per decidere e mitigare (X + Y) contro tempo prima che il rischio possa manifestarsi (Z). | AL2: =IF(COUNTIF(H5:H19,"AGIRE ORA*")=0,"Nessun rischio da affrontare subito",COUNTIF(H5:H19,"AGIRE ORA*")&" da affrontare subito: "&_xlfn.TEXTJOIN(", ",TRUE,AB5:AB19)) -> 2 da affrontare subito: NFR-01, NFR-11
AL3: Lente di Mosca: chi e' in ritardo, e di quanto (anni)
A4: Pos. | B4: ID | C4: Nome | D4: Score composito | E4: Score ciclo prima | F4: Δ score | G4: Esito | H4: Urgenza (Mosca) | I4: Margine Z-(X+Y), anni | J4: Owner | K4: Etichetta del grafico | T4: Chiave d'ordine | U4: Posizione in anagrafica | V4: Barra: agire ora | W4: Barra: entro l'anno | X4: Barra: con margine | Y4: X anni | Z4: Y anni | AA4: Z anni | AB4: Da affrontare subito | AD4: Chiave della lente | AE4: Posizione nella lente | AF4: Etichetta della lente | AG4: X | AH4: Y entro Z | AI4: Y oltre Z | AJ4: Z
A5: =IF($U5="","",1) -> 1 | B5: =IF($U5="","",INDEX(posID,$U5)) -> NFR-01 | C5: =IF($U5="","",INDEX(posNome,$U5)) -> Frodi su pagamenti istantanei abilitate da AI generativa | D5: =IF($U5="","",INDEX(posScore,$U5)) -> 3.8 | E5: =IF($U5="","",IFERROR(INDEX(posScorePrec,$U5),"—")) -> 3.8 | F5: =IF(AND(ISNUMBER(D5),ISNUMBER(E5)),D5-E5,"") -> 0 | G5: =IF($U5="","",IFERROR(INDEX(RR_Esito,MATCH(cicloCorrente&"|"&B5,RR_Chiave,0))&"","")) -> Confermato | H5: =IF($U5="","",INDEX(Radar_Mosca!$L$5:$L$19,$U5)) -> AGIRE ORA: X+Y > Z | I5: =IF($U5="","",IFERROR(INDEX(Radar_Mosca!$K$5:$K$19,$U5),"")) -> -0.25 | J5: =IF($U5="","",INDEX(ANA_Owner,$U5)&"") -> Funzione Antifrode | K5: =IF($U5="","",B5&" "&IF(ISNUMBER(F5),IF(F5>0,"▲",IF(F5<0,"▼","●")),"○")&" "&LEFT(C5,34)&IF(LEN(C5)>34,"…","")) -> NFR-01 ● Frodi su pagamenti istantanei abil… | T5: =IF(ISNUMBER(INDEX(posScore,1)),INDEX(posScore,1)-1/100000,"") -> 3.79999 | U5: =IFERROR(MATCH(_xlfn.AGGREGATE(14,6,$T$5:$T$19,1),$T$5:$T$19,0),"") -> 1 | V5: =IF($U5="",NA(),IF(LEFT(H5,9)="AGIRE ORA",D5,0)) -> 3.8 | W5: =IF($U5="",NA(),IF(LEFT(H5,11)="Agire entro",D5,0)) -> 0 | X5: =IF($U5="",NA(),IF(OR(LEFT(H5,9)="AGIRE ORA",LEFT(H5,11)="Agire entro"),0,D5)) -> 0 | Y5: =IF($U5="",NA(),INDEX(Radar_Mosca!$I$5:$I$19,$U5)) -> 0.25 | Z5: =IF($U5="",NA(),INDEX(Radar_Mosca!$J$5:$J$19,$U5)) -> 0.5 | AA5: =IF($U5="",NA(),INDEX(Radar_Mosca!$H$5:$H$19,$U5)) -> 0.5 | AB5: =IF(LEFT(H5,9)="AGIRE ORA",B5,"") -> NFR-01 | AD5: =IF(ISNUMBER(I5),I5+1/100000,"") -> -0.24999 | AE5: =IFERROR(MATCH(_xlfn.AGGREGATE(15,6,$AD$5:$AD$19,1),$AD$5:$AD$19,0),"") -> 6 | AF5: =IF($AE5="","",INDEX($B$5:$B$19,$AE5)&" ("&IF(INDEX($I$5:$I$19,$AE5)<0,"−","+")&FIXED(ABS(INDEX($I$5:$I$19,$AE5)),2)&")") -> NFR-11 (−1,75) | AG5: =IF($AE5="",NA(),INDEX($Y$5:$Y$19,$AE5)) -> 0.25 | AH5: =IF($AE5="",NA(),IF(INDEX($Y$5:$Y$19,$AE5)+INDEX($Z$5:$Z$19,$AE5)>INDEX($AA$5:$AA$19,$AE5),NA(),INDEX($Z$5:$Z$19,$AE5))) -> #N/A | AI5: =IF($AE5="",NA(),IF(INDEX($Y$5:$Y$19,$AE5)+INDEX($Z$5:$Z$19,$AE5)>INDEX($AA$5:$AA$19,$AE5),INDEX($Z$5:$Z$19,$AE5),NA())) -> 3 | AJ5: =IF($AE5="",NA(),INDEX($AA$5:$AA$19,$AE5)) -> 1.5
A6: =IF($U6="","",2) -> 2 | B6: =IF($U6="","",INDEX(posID,$U6)) -> NFR-07 | C6: =IF($U6="","",INDEX(posNome,$U6)) -> Ransomware presso un fornitore di servizi di pagamento | D6: =IF($U6="","",INDEX(posScore,$U6)) -> 3.6 | E6: =IF($U6="","",IFERROR(INDEX(posScorePrec,$U6),"—")) -> 3.6 | F6: =IF(AND(ISNUMBER(D6),ISNUMBER(E6)),D6-E6,"") -> 0 | G6: =IF($U6="","",IFERROR(INDEX(RR_Esito,MATCH(cicloCorrente&"|"&B6,RR_Chiave,0))&"","")) -> Confermato | H6: =IF($U6="","",INDEX(Radar_Mosca!$L$5:$L$19,$U6)) -> Agire entro l'anno | I6: =IF($U6="","",IFERROR(INDEX(Radar_Mosca!$K$5:$K$19,$U6),"")) -> 0.75 | J6: =IF($U6="","",INDEX(ANA_Owner,$U6)&"") -> Funzione ICT & Security Risk | K6: =IF($U6="","",B6&" "&IF(ISNUMBER(F6),IF(F6>0,"▲",IF(F6<0,"▼","●")),"○")&" "&LEFT(C6,34)&IF(LEN(C6)>34,"…","")) -> NFR-07 ● Ransomware presso un fornitore di … | T6: =IF(ISNUMBER(INDEX(posScore,2)),INDEX(posScore,2)-2/100000,"") -> 3.24998 | U6: =IFERROR(MATCH(_xlfn.AGGREGATE(14,6,$T$5:$T$19,2),$T$5:$T$19,0),"") -> 7 | V6: =IF($U6="",NA(),IF(LEFT(H6,9)="AGIRE ORA",D6,0)) -> 0 | W6: =IF($U6="",NA(),IF(LEFT(H6,11)="Agire entro",D6,0)) -> 3.6 | X6: =IF($U6="",NA(),IF(OR(LEFT(H6,9)="AGIRE ORA",LEFT(H6,11)="Agire entro"),0,D6)) -> 0 | Y6: =IF($U6="",NA(),INDEX(Radar_Mosca!$I$5:$I$19,$U6)) -> 0.25 | Z6: =IF($U6="",NA(),INDEX(Radar_Mosca!$J$5:$J$19,$U6)) -> 0.5 | AA6: =IF($U6="",NA(),INDEX(Radar_Mosca!$H$5:$H$19,$U6)) -> 1.5 | AB6: =IF(LEFT(H6,9)="AGIRE ORA",B6,"") | AD6: =IF(ISNUMBER(I6),I6+2/100000,"") -> 0.75002 | AE6: =IFERROR(MATCH(_xlfn.AGGREGATE(15,6,$AD$5:$AD$19,2),$AD$5:$AD$19,0),"") -> 1 | AF6: =IF($AE6="","",INDEX($B$5:$B$19,$AE6)&" ("&IF(INDEX($I$5:$I$19,$AE6)<0,"−","+")&FIXED(ABS(INDEX($I$5:$I$19,$AE6)),2)&")") -> NFR-01 (−0,25) | AG6: =IF($AE6="",NA(),INDEX($Y$5:$Y$19,$AE6)) -> 0.25 | AH6: =IF($AE6="",NA(),IF(INDEX($Y$5:$Y$19,$AE6)+INDEX($Z$5:$Z$19,$AE6)>INDEX($AA$5:$AA$19,$AE6),NA(),INDEX($Z$5:$Z$19,$AE6))) -> #N/A | AI6: =IF($AE6="",NA(),IF(INDEX($Y$5:$Y$19,$AE6)+INDEX($Z$5:$Z$19,$AE6)>INDEX($AA$5:$AA$19,$AE6),INDEX($Z$5:$Z$19,$AE6),NA())) -> 0.5 | AJ6: =IF($AE6="",NA(),INDEX($AA$5:$AA$19,$AE6)) -> 0.5
A7: =IF($U7="","",3) -> 3 | B7: =IF($U7="","",INDEX(posID,$U7)) -> NFR-12 | C7: =IF($U7="","",INDEX(posNome,$U7)) -> Errori operativi nei pagamenti istantanei obbligatori | D7: =IF($U7="","",INDEX(posScore,$U7)) -> 3.5 | E7: =IF($U7="","",IFERROR(INDEX(posScorePrec,$U7),"—")) -> 3.5 | F7: =IF(AND(ISNUMBER(D7),ISNUMBER(E7)),D7-E7,"") -> 0 | G7: =IF($U7="","",IFERROR(INDEX(RR_Esito,MATCH(cicloCorrente&"|"&B7,RR_Chiave,0))&"","")) -> Confermato | H7: =IF($U7="","",INDEX(Radar_Mosca!$L$5:$L$19,$U7)) -> Agire entro l'anno | I7: =IF($U7="","",IFERROR(INDEX(Radar_Mosca!$K$5:$K$19,$U7),"")) -> 0 | J7: =IF($U7="","",INDEX(ANA_Owner,$U7)&"") -> Funzione Operations | K7: =IF($U7="","",B7&" "&IF(ISNUMBER(F7),IF(F7>0,"▲",IF(F7<0,"▼","●")),"○")&" "&LEFT(C7,34)&IF(LEN(C7)>34,"…","")) -> NFR-12 ● Errori operativi nei pagamenti ist… | T7: =IF(ISNUMBER(INDEX(posScore,3)),INDEX(posScore,3)-3/100000,"") -> 2.99997 | U7: =IFERROR(MATCH(_xlfn.AGGREGATE(14,6,$T$5:$T$19,3),$T$5:$T$19,0),"") -> 12 | V7: =IF($U7="",NA(),IF(LEFT(H7,9)="AGIRE ORA",D7,0)) -> 0 | W7: =IF($U7="",NA(),IF(LEFT(H7,11)="Agire entro",D7,0)) -> 3.5 | X7: =IF($U7="",NA(),IF(OR(LEFT(H7,9)="AGIRE ORA",LEFT(H7,11)="Agire entro"),0,D7)) -> 0 | Y7: =IF($U7="",NA(),INDEX(Radar_Mosca!$I$5:$I$19,$U7)) -> 0.25 | Z7: =IF($U7="",NA(),INDEX(Radar_Mosca!$J$5:$J$19,$U7)) -> 0.25 | AA7: =IF($U7="",NA(),INDEX(Radar_Mosca!$H$5:$H$19,$U7)) -> 0.5 | AB7: =IF(LEFT(H7,9)="AGIRE ORA",B7,"") | AD7: =IF(ISNUMBER(I7),I7+3/100000,"") -> 3e-05 | AE7: =IFERROR(MATCH(_xlfn.AGGREGATE(15,6,$AD$5:$AD$19,3),$AD$5:$AD$19,0),"") -> 3 | AF7: =IF($AE7="","",INDEX($B$5:$B$19,$AE7)&" ("&IF(INDEX($I$5:$I$19,$AE7)<0,"−","+")&FIXED(ABS(INDEX($I$5:$I$19,$AE7)),2)&")") -> NFR-12 (+0,00) | AG7: =IF($AE7="",NA(),INDEX($Y$5:$Y$19,$AE7)) -> 0.25 | AH7: =IF($AE7="",NA(),IF(INDEX($Y$5:$Y$19,$AE7)+INDEX($Z$5:$Z$19,$AE7)>INDEX($AA$5:$AA$19,$AE7),NA(),INDEX($Z$5:$Z$19,$AE7))) -> 0.25 | AI7: =IF($AE7="",NA(),IF(INDEX($Y$5:$Y$19,$AE7)+INDEX($Z$5:$Z$19,$AE7)>INDEX($AA$5:$AA$19,$AE7),INDEX($Z$5:$Z$19,$AE7),NA())) -> #N/A | AJ7: =IF($AE7="",NA(),INDEX($AA$5:$AA$19,$AE7)) -> 0.5
A8: =IF($U8="","",4) -> 4 | B8: =IF($U8="","",INDEX(posID,$U8)) -> NFR-02 | C8: =IF($U8="","",INDEX(posNome,$U8)) -> Concentrazione su un fornitore cloud critico | D8: =IF($U8="","",INDEX(posScore,$U8)) -> 3.25 | E8: =IF($U8="","",IFERROR(INDEX(posScorePrec,$U8),"—")) -> 3.45 | F8: =IF(AND(ISNUMBER(D8),ISNUMBER(E8)),D8-E8,"") -> -0.2 | G8: =IF($U8="","",IFERROR(INDEX(RR_Esito,MATCH(cicloCorrente&"|"&B8,RR_Chiave,0))&"","")) -> Variato | H8: =IF($U8="","",INDEX(Radar_Mosca!$L$5:$L$19,$U8)) -> Agire entro l'anno | I8: =IF($U8="","",IFERROR(INDEX(Radar_Mosca!$K$5:$K$19,$U8),"")) -> 0.25 | J8: =IF($U8="","",INDEX(ANA_Owner,$U8)&"") -> Funzione ICT & Security Risk | K8: =IF($U8="","",B8&" "&IF(ISNUMBER(F8),IF(F8>0,"▲",IF(F8<0,"▼","●")),"○")&" "&LEFT(C8,34)&IF(LEN(C8)>34,"…","")) -> NFR-02 ▼ Concentrazione su un fornitore clo… | T8: =IF(ISNUMBER(INDEX(posScore,4)),INDEX(posScore,4)-4/100000,"") -> 2.84996 | U8: =IFERROR(MATCH(_xlfn.AGGREGATE(14,6,$T$5:$T$19,4),$T$5:$T$19,0),"") -> 2 | V8: =IF($U8="",NA(),IF(LEFT(H8,9)="AGIRE ORA",D8,0)) -> 0 | W8: =IF($U8="",NA(),IF(LEFT(H8,11)="Agire entro",D8,0)) -> 3.25 | X8: =IF($U8="",NA(),IF(OR(LEFT(H8,9)="AGIRE ORA",LEFT(H8,11)="Agire entro"),0,D8)) -> 0 | Y8: =IF($U8="",NA(),INDEX(Radar_Mosca!$I$5:$I$19,$U8)) -> 0.25 | Z8: =IF($U8="",NA(),INDEX(Radar_Mosca!$J$5:$J$19,$U8)) -> 1 | AA8: =IF($U8="",NA(),INDEX(Radar_Mosca!$H$5:$H$19,$U8)) -> 1.5 | AB8: =IF(LEFT(H8,9)="AGIRE ORA",B8,"") | AD8: =IF(ISNUMBER(I8),I8+4/100000,"") -> 0.25004 | AE8: =IFERROR(MATCH(_xlfn.AGGREGATE(15,6,$AD$5:$AD$19,4),$AD$5:$AD$19,0),"") -> 7 | AF8: =IF($AE8="","",INDEX($B$5:$B$19,$AE8)&" ("&IF(INDEX($I$5:$I$19,$AE8)<0,"−","+")&FIXED(ABS(INDEX($I$5:$I$19,$AE8)),2)&")") -> NFR-03 (+0,00) | AG8: =IF($AE8="",NA(),INDEX($Y$5:$Y$19,$AE8)) -> 0.25 | AH8: =IF($AE8="",NA(),IF(INDEX($Y$5:$Y$19,$AE8)+INDEX($Z$5:$Z$19,$AE8)>INDEX($AA$5:$AA$19,$AE8),NA(),INDEX($Z$5:$Z$19,$AE8))) -> 0.25 | AI8: =IF($AE8="",NA(),IF(INDEX($Y$5:$Y$19,$AE8)+INDEX($Z$5:$Z$19,$AE8)>INDEX($AA$5:$AA$19,$AE8),INDEX($Z$5:$Z$19,$AE8),NA())) -> #N/A | AJ8: =IF($AE8="",NA(),INDEX($AA$5:$AA$19,$AE8)) -> 0.5
A9: =IF($U9="","",5) -> 5 | B9: =IF($U9="","",INDEX(posID,$U9)) -> NFR-10 | C9: =IF($U9="","",INDEX(posNome,$U9)) -> Informazioni errate ai clienti da assistenti di AI generativa | D9: =IF($U9="","",INDEX(posScore,$U9)) -> 3.2 | E9: =IF($U9="","",IFERROR(INDEX(posScorePrec,$U9),"—")) -> 3.2 | F9: =IF(AND(ISNUMBER(D9),ISNUMBER(E9)),D9-E9,"") -> 0 | G9: =IF($U9="","",IFERROR(INDEX(RR_Esito,MATCH(cicloCorrente&"|"&B9,RR_Chiave,0))&"","")) -> Confermato | H9: =IF($U9="","",INDEX(Radar_Mosca!$L$5:$L$19,$U9)) -> Margine 1 anno | I9: =IF($U9="","",IFERROR(INDEX(Radar_Mosca!$K$5:$K$19,$U9),"")) -> 1 | J9: =IF($U9="","",INDEX(ANA_Owner,$U9)&"") -> Funzione Customer Experience | K9: =IF($U9="","",B9&" "&IF(ISNUMBER(F9),IF(F9>0,"▲",IF(F9<0,"▼","●")),"○")&" "&LEFT(C9,34)&IF(LEN(C9)>34,"…","")) -> NFR-10 ● Informazioni errate ai clienti da … | T9: =IF(ISNUMBER(INDEX(posScore,5)),INDEX(posScore,5)-5/100000,"") -> 2.99995 | U9: =IFERROR(MATCH(_xlfn.AGGREGATE(14,6,$T$5:$T$19,5),$T$5:$T$19,0),"") -> 10 | V9: =IF($U9="",NA(),IF(LEFT(H9,9)="AGIRE ORA",D9,0)) -> 0 | W9: =IF($U9="",NA(),IF(LEFT(H9,11)="Agire entro",D9,0)) -> 0 | X9: =IF($U9="",NA(),IF(OR(LEFT(H9,9)="AGIRE ORA",LEFT(H9,11)="Agire entro"),0,D9)) -> 3.2 | Y9: =IF($U9="",NA(),INDEX(Radar_Mosca!$I$5:$I$19,$U9)) -> 0.25 | Z9: =IF($U9="",NA(),INDEX(Radar_Mosca!$J$5:$J$19,$U9)) -> 0.25 | AA9: =IF($U9="",NA(),INDEX(Radar_Mosca!$H$5:$H$19,$U9)) -> 1.5 | AB9: =IF(LEFT(H9,9)="AGIRE ORA",B9,"") | AD9: =IF(ISNUMBER(I9),I9+5/100000,"") -> 1.00005 | AE9: =IFERROR(MATCH(_xlfn.AGGREGATE(15,6,$AD$5:$AD$19,5),$AD$5:$AD$19,0),"") -> 4 | AF9: =IF($AE9="","",INDEX($B$5:$B$19,$AE9)&" ("&IF(INDEX($I$5:$I$19,$AE9)<0,"−","+")&FIXED(ABS(INDEX($I$5:$I$19,$AE9)),2)&")") -> NFR-02 (+0,25) | AG9: =IF($AE9="",NA(),INDEX($Y$5:$Y$19,$AE9)) -> 0.25 | AH9: =IF($AE9="",NA(),IF(INDEX($Y$5:$Y$19,$AE9)+INDEX($Z$5:$Z$19,$AE9)>INDEX($AA$5:$AA$19,$AE9),NA(),INDEX($Z$5:$Z$19,$AE9))) -> 1 | AI9: =IF($AE9="",NA(),IF(INDEX($Y$5:$Y$19,$AE9)+INDEX($Z$5:$Z$19,$AE9)>INDEX($AA$5:$AA$19,$AE9),INDEX($Z$5:$Z$19,$AE9),NA())) -> #N/A | AJ9: =IF($AE9="",NA(),INDEX($AA$5:$AA$19,$AE9)) -> 1.5
A10: =IF($U10="","",6) -> 6 | B10: =IF($U10="","",INDEX(posID,$U10)) -> NFR-11 | C10: =IF($U10="","",INDEX(posNome,$U10)) -> Fine del supporto dei sistemi di pagamento legacy | D10: =IF($U10="","",INDEX(posScore,$U10)) -> 3.05 | E10: =IF($U10="","",IFERROR(INDEX(posScorePrec,$U10),"—")) -> 3.05 | F10: =IF(AND(ISNUMBER(D10),ISNUMBER(E10)),D10-E10,"") -> 0 | G10: =IF($U10="","",IFERROR(INDEX(RR_Esito,MATCH(cicloCorrente&"|"&B10,RR_Chiave,0))&"","")) -> Confermato | H10: =IF($U10="","",INDEX(Radar_Mosca!$L$5:$L$19,$U10)) -> AGIRE ORA: X+Y > Z | I10: =IF($U10="","",IFERROR(INDEX(Radar_Mosca!$K$5:$K$19,$U10),"")) -> -1.75 | J10: =IF($U10="","",INDEX(ANA_Owner,$U10)&"") -> Funzione IT Operations | K10: =IF($U10="","",B10&" "&IF(ISNUMBER(F10),IF(F10>0,"▲",IF(F10<0,"▼","●")),"○")&" "&LEFT(C10,34)&IF(LEN(C10)>34,"…","")) -> NFR-11 ● Fine del supporto dei sistemi di p… | T10: =IF(ISNUMBER(INDEX(posScore,6)),INDEX(posScore,6)-6/100000,"") -> 2.99994 | U10: =IFERROR(MATCH(_xlfn.AGGREGATE(14,6,$T$5:$T$19,6),$T$5:$T$19,0),"") -> 11 | V10: =IF($U10="",NA(),IF(LEFT(H10,9)="AGIRE ORA",D10,0)) -> 3.05 | W10: =IF($U10="",NA(),IF(LEFT(H10,11)="Agire entro",D10,0)) -> 0 | X10: =IF($U10="",NA(),IF(OR(LEFT(H10,9)="AGIRE ORA",LEFT(H10,11)="Agire entro"),0,D10)) -> 0 | Y10: =IF($U10="",NA(),INDEX(Radar_Mosca!$I$5:$I$19,$U10)) -> 0.25 | Z10: =IF($U10="",NA(),INDEX(Radar_Mosca!$J$5:$J$19,$U10)) -> 3 | AA10: =IF($U10="",NA(),INDEX(Radar_Mosca!$H$5:$H$19,$U10)) -> 1.5 | AB10: =IF(LEFT(H10,9)="AGIRE ORA",B10,"") -> NFR-11 | AD10: =IF(ISNUMBER(I10),I10+6/100000,"") -> -1.74994 | AE10: =IFERROR(MATCH(_xlfn.AGGREGATE(15,6,$AD$5:$AD$19,6),$AD$5:$AD$19,0),"") -> 12 | AF10: =IF($AE10="","",INDEX($B$5:$B$19,$AE10)&" ("&IF(INDEX($I$5:$I$19,$AE10)<0,"−","+")&FIXED(ABS(INDEX($I$5:$I$19,$AE10)),2)&")") -> NFR-08 (+0,25) | AG10: =IF($AE10="",NA(),INDEX($Y$5:$Y$19,$AE10)) -> 0.25 | AH10: =IF($AE10="",NA(),IF(INDEX($Y$5:$Y$19,$AE10)+INDEX($Z$5:$Z$19,$AE10)>INDEX($AA$5:$AA$19,$AE10),NA(),INDEX($Z$5:$Z$19,$AE10))) -> 1 | AI10: =IF($AE10="",NA(),IF(INDEX($Y$5:$Y$19,$AE10)+INDEX($Z$5:$Z$19,$AE10)>INDEX($AA$5:$AA$19,$AE10),INDEX($Z$5:$Z$19,$AE10),NA())) -> #N/A | AJ10: =IF($AE10="",NA(),INDEX($AA$5:$AA$19,$AE10)) -> 1.5
A11: =IF($U11="","",7) -> 7 | B11: =IF($U11="","",INDEX(posID,$U11)) -> NFR-03 | C11: =IF($U11="","",INDEX(posNome,$U11)) -> Greenwashing nella commercializzazione di prodotti ESG | D11: =IF($U11="","",INDEX(posScore,$U11)) -> 3 | E11: =IF($U11="","",IFERROR(INDEX(posScorePrec,$U11),"—")) -> 2.85 | F11: =IF(AND(ISNUMBER(D11),ISNUMBER(E11)),D11-E11,"") -> 0.15 | G11: =IF($U11="","",IFERROR(INDEX(RR_Esito,MATCH(cicloCorrente&"|"&B11,RR_Chiave,0))&"","")) -> Variato | H11: =IF($U11="","",INDEX(Radar_Mosca!$L$5:$L$19,$U11)) -> Agire entro l'anno | I11: =IF($U11="","",IFERROR(INDEX(Radar_Mosca!$K$5:$K$19,$U11),"")) -> 0 | J11: =IF($U11="","",INDEX(ANA_Owner,$U11)&"") -> Funzione Compliance | K11: =IF($U11="","",B11&" "&IF(ISNUMBER(F11),IF(F11>0,"▲",IF(F11<0,"▼","●")),"○")&" "&LEFT(C11,34)&IF(LEN(C11)>34,"…","")) -> NFR-03 ▲ Greenwashing nella commercializzaz… | T11: =IF(ISNUMBER(INDEX(posScore,7)),INDEX(posScore,7)-7/100000,"") -> 3.59993 | U11: =IFERROR(MATCH(_xlfn.AGGREGATE(14,6,$T$5:$T$19,7),$T$5:$T$19,0),"") -> 3 | V11: =IF($U11="",NA(),IF(LEFT(H11,9)="AGIRE ORA",D11,0)) -> 0 | W11: =IF($U11="",NA(),IF(LEFT(H11,11)="Agire entro",D11,0)) -> 3 | X11: =IF($U11="",NA(),IF(OR(LEFT(H11,9)="AGIRE ORA",LEFT(H11,11)="Agire entro"),0,D11)) -> 0 | Y11: =IF($U11="",NA(),INDEX(Radar_Mosca!$I$5:$I$19,$U11)) -> 0.25 | Z11: =IF($U11="",NA(),INDEX(Radar_Mosca!$J$5:$J$19,$U11)) -> 0.25 | AA11: =IF($U11="",NA(),INDEX(Radar_Mosca!$H$5:$H$19,$U11)) -> 0.5 | AB11: =IF(LEFT(H11,9)="AGIRE ORA",B11,"") | AD11: =IF(ISNUMBER(I11),I11+7/100000,"") -> 7e-05 | AE11: =IFERROR(MATCH(_xlfn.AGGREGATE(15,6,$AD$5:$AD$19,7),$AD$5:$AD$19,0),"") -> 2 | AF11: =IF($AE11="","",INDEX($B$5:$B$19,$AE11)&" ("&IF(INDEX($I$5:$I$19,$AE11)<0,"−","+")&FIXED(ABS(INDEX($I$5:$I$19,$AE11)),2)&")") -> NFR-07 (+0,75) | AG11: =IF($AE11="",NA(),INDEX($Y$5:$Y$19,$AE11)) -> 0.25 | AH11: =IF($AE11="",NA(),IF(INDEX($Y$5:$Y$19,$AE11)+INDEX($Z$5:$Z$19,$AE11)>INDEX($AA$5:$AA$19,$AE11),NA(),INDEX($Z$5:$Z$19,$AE11))) -> 0.5 | AI11: =IF($AE11="",NA(),IF(INDEX($Y$5:$Y$19,$AE11)+INDEX($Z$5:$Z$19,$AE11)>INDEX($AA$5:$AA$19,$AE11),INDEX($Z$5:$Z$19,$AE11),NA())) -> #N/A | AJ11: =IF($AE11="",NA(),INDEX($AA$5:$AA$19,$AE11)) -> 1.5
A12: =IF($U12="","",8) -> 8 | B12: =IF($U12="","",INDEX(posID,$U12)) -> NFR-05 | C12: =IF($U12="","",INDEX(posNome,$U12)) -> Errori di processo nella migrazione del core banking | D12: =IF($U12="","",INDEX(posScore,$U12)) -> 3 | E12: =IF($U12="","",IFERROR(INDEX(posScorePrec,$U12),"—")) -> 3 | F12: =IF(AND(ISNUMBER(D12),ISNUMBER(E12)),D12-E12,"") -> 0 | G12: =IF($U12="","",IFERROR(INDEX(RR_Esito,MATCH(cicloCorrente&"|"&B12,RR_Chiave,0))&"","")) -> Confermato | H12: =IF($U12="","",INDEX(Radar_Mosca!$L$5:$L$19,$U12)) -> Margine 1 anno | I12: =IF($U12="","",IFERROR(INDEX(Radar_Mosca!$K$5:$K$19,$U12),"")) -> 1 | J12: =IF($U12="","",INDEX(ANA_Owner,$U12)&"") -> Funzione Operations | K12: =IF($U12="","",B12&" "&IF(ISNUMBER(F12),IF(F12>0,"▲",IF(F12<0,"▼","●")),"○")&" "&LEFT(C12,34)&IF(LEN(C12)>34,"…","")) -> NFR-05 ● Errori di processo nella migrazion… | T12: =IF(ISNUMBER(INDEX(posScore,8)),INDEX(posScore,8)-8/100000,"") -> 2.79992 | U12: =IFERROR(MATCH(_xlfn.AGGREGATE(14,6,$T$5:$T$19,8),$T$5:$T$19,0),"") -> 5 | V12: =IF($U12="",NA(),IF(LEFT(H12,9)="AGIRE ORA",D12,0)) -> 0 | W12: =IF($U12="",NA(),IF(LEFT(H12,11)="Agire entro",D12,0)) -> 0 | X12: =IF($U12="",NA(),IF(OR(LEFT(H12,9)="AGIRE ORA",LEFT(H12,11)="Agire entro"),0,D12)) -> 3 | Y12: =IF($U12="",NA(),INDEX(Radar_Mosca!$I$5:$I$19,$U12)) -> 0.25 | Z12: =IF($U12="",NA(),INDEX(Radar_Mosca!$J$5:$J$19,$U12)) -> 0.25 | AA12: =IF($U12="",NA(),INDEX(Radar_Mosca!$H$5:$H$19,$U12)) -> 1.5 | AB12: =IF(LEFT(H12,9)="AGIRE ORA",B12,"") | AD12: =IF(ISNUMBER(I12),I12+8/100000,"") -> 1.00008 | AE12: =IFERROR(MATCH(_xlfn.AGGREGATE(15,6,$AD$5:$AD$19,8),$AD$5:$AD$19,0),"") -> 9 | AF12: =IF($AE12="","",INDEX($B$5:$B$19,$AE12)&" ("&IF(INDEX($I$5:$I$19,$AE12)<0,"−","+")&FIXED(ABS(INDEX($I$5:$I$19,$AE12)),2)&")") -> NFR-06 (+0,75) | AG12: =IF($AE12="",NA(),INDEX($Y$5:$Y$19,$AE12)) -> 0.25 | AH12: =IF($AE12="",NA(),IF(INDEX($Y$5:$Y$19,$AE12)+INDEX($Z$5:$Z$19,$AE12)>INDEX($AA$5:$AA$19,$AE12),NA(),INDEX($Z$5:$Z$19,$AE12))) -> 0.5 | AI12: =IF($AE12="",NA(),IF(INDEX($Y$5:$Y$19,$AE12)+INDEX($Z$5:$Z$19,$AE12)>INDEX($AA$5:$AA$19,$AE12),INDEX($Z$5:$Z$19,$AE12),NA())) -> #N/A | AJ12: =IF($AE12="",NA(),INDEX($AA$5:$AA$19,$AE12)) -> 1.5
A13: =IF($U13="","",9) -> 9 | B13: =IF($U13="","",INDEX(posID,$U13)) -> NFR-06 | C13: =IF($U13="","",INDEX(posNome,$U13)) -> Esfiltrazione di dati tramite strumenti di AI non autorizzati | D13: =IF($U13="","",INDEX(posScore,$U13)) -> 3 | E13: =IF($U13="","",IFERROR(INDEX(posScorePrec,$U13),"—")) -> 3.2 | F13: =IF(AND(ISNUMBER(D13),ISNUMBER(E13)),D13-E13,"") -> -0.2 | G13: =IF($U13="","",IFERROR(INDEX(RR_Esito,MATCH(cicloCorrente&"|"&B13,RR_Chiave,0))&"","")) -> Variato | H13: =IF($U13="","",INDEX(Radar_Mosca!$L$5:$L$19,$U13)) -> Agire entro l'anno | I13: =IF($U13="","",IFERROR(INDEX(Radar_Mosca!$K$5:$K$19,$U13),"")) -> 0.75 | J13: =IF($U13="","",INDEX(ANA_Owner,$U13)&"") -> Funzione Sicurezza delle Informazioni | K13: =IF($U13="","",B13&" "&IF(ISNUMBER(F13),IF(F13>0,"▲",IF(F13<0,"▼","●")),"○")&" "&LEFT(C13,34)&IF(LEN(C13)>34,"…","")) -> NFR-06 ▼ Esfiltrazione di dati tramite stru… | T13: =IF(ISNUMBER(INDEX(posScore,9)),INDEX(posScore,9)-9/100000,"") -> 2.94991 | U13: =IFERROR(MATCH(_xlfn.AGGREGATE(14,6,$T$5:$T$19,9),$T$5:$T$19,0),"") -> 6 | V13: =IF($U13="",NA(),IF(LEFT(H13,9)="AGIRE ORA",D13,0)) -> 0 | W13: =IF($U13="",NA(),IF(LEFT(H13,11)="Agire entro",D13,0)) -> 3 | X13: =IF($U13="",NA(),IF(OR(LEFT(H13,9)="AGIRE ORA",LEFT(H13,11)="Agire entro"),0,D13)) -> 0 | Y13: =IF($U13="",NA(),INDEX(Radar_Mosca!$I$5:$I$19,$U13)) -> 0.25 | Z13: =IF($U13="",NA(),INDEX(Radar_Mosca!$J$5:$J$19,$U13)) -> 0.5 | AA13: =IF($U13="",NA(),INDEX(Radar_Mosca!$H$5:$H$19,$U13)) -> 1.5 | AB13: =IF(LEFT(H13,9)="AGIRE ORA",B13,"") | AD13: =IF(ISNUMBER(I13),I13+9/100000,"") -> 0.75009 | AE13: =IFERROR(MATCH(_xlfn.AGGREGATE(15,6,$AD$5:$AD$19,9),$AD$5:$AD$19,0),"") -> 11 | AF13: =IF($AE13="","",INDEX($B$5:$B$19,$AE13)&" ("&IF(INDEX($I$5:$I$19,$AE13)<0,"−","+")&FIXED(ABS(INDEX($I$5:$I$19,$AE13)),2)&")") -> NFR-04 (+0,75) | AG13: =IF($AE13="",NA(),INDEX($Y$5:$Y$19,$AE13)) -> 0.25 | AH13: =IF($AE13="",NA(),IF(INDEX($Y$5:$Y$19,$AE13)+INDEX($Z$5:$Z$19,$AE13)>INDEX($AA$5:$AA$19,$AE13),NA(),INDEX($Z$5:$Z$19,$AE13))) -> 0.5 | AI13: =IF($AE13="",NA(),IF(INDEX($Y$5:$Y$19,$AE13)+INDEX($Z$5:$Z$19,$AE13)>INDEX($AA$5:$AA$19,$AE13),INDEX($Z$5:$Z$19,$AE13),NA())) -> #N/A | AJ13: =IF($AE13="",NA(),INDEX($AA$5:$AA$19,$AE13)) -> 1.5
A14: =IF($U14="","",10) -> 10 | B14: =IF($U14="","",INDEX(posID,$U14)) -> NFR-09 | C14: =IF($U14="","",INDEX(posNome,$U14)) -> Violazione di sanzioni internazionali tramite triangolazioni | D14: =IF($U14="","",INDEX(posScore,$U14)) -> 2.95 | E14: =IF($U14="","",IFERROR(INDEX(posScorePrec,$U14),"—")) -> 2.95 | F14: =IF(AND(ISNUMBER(D14),ISNUMBER(E14)),D14-E14,"") -> 0 | G14: =IF($U14="","",IFERROR(INDEX(RR_Esito,MATCH(cicloCorrente&"|"&B14,RR_Chiave,0))&"","")) -> Confermato | H14: =IF($U14="","",INDEX(Radar_Mosca!$L$5:$L$19,$U14)) -> Margine 1,3 anni | I14: =IF($U14="","",IFERROR(INDEX(Radar_Mosca!$K$5:$K$19,$U14),"")) -> 1.25 | J14: =IF($U14="","",INDEX(ANA_Owner,$U14)&"") -> Funzione Compliance | K14: =IF($U14="","",B14&" "&IF(ISNUMBER(F14),IF(F14>0,"▲",IF(F14<0,"▼","●")),"○")&" "&LEFT(C14,34)&IF(LEN(C14)>34,"…","")) -> NFR-09 ● Violazione di sanzioni internazion… | T14: =IF(ISNUMBER(INDEX(posScore,10)),INDEX(posScore,10)-10/100000,"") -> 3.1999 | U14: =IFERROR(MATCH(_xlfn.AGGREGATE(14,6,$T$5:$T$19,10),$T$5:$T$19,0),"") -> 9 | V14: =IF($U14="",NA(),IF(LEFT(H14,9)="AGIRE ORA",D14,0)) -> 0 | W14: =IF($U14="",NA(),IF(LEFT(H14,11)="Agire entro",D14,0)) -> 0 | X14: =IF($U14="",NA(),IF(OR(LEFT(H14,9)="AGIRE ORA",LEFT(H14,11)="Agire entro"),0,D14)) -> 2.95 | Y14: =IF($U14="",NA(),INDEX(Radar_Mosca!$I$5:$I$19,$U14)) -> 0.25 | Z14: =IF($U14="",NA(),INDEX(Radar_Mosca!$J$5:$J$19,$U14)) -> 1 | AA14: =IF($U14="",NA(),INDEX(Radar_Mosca!$H$5:$H$19,$U14)) -> 2.5 | AB14: =IF(LEFT(H14,9)="AGIRE ORA",B14,"") | AD14: =IF(ISNUMBER(I14),I14+10/100000,"") -> 1.2501 | AE14: =IFERROR(MATCH(_xlfn.AGGREGATE(15,6,$AD$5:$AD$19,10),$AD$5:$AD$19,0),"") -> 5 | AF14: =IF($AE14="","",INDEX($B$5:$B$19,$AE14)&" ("&IF(INDEX($I$5:$I$19,$AE14)<0,"−","+")&FIXED(ABS(INDEX($I$5:$I$19,$AE14)),2)&")") -> NFR-10 (+1,00) | AG14: =IF($AE14="",NA(),INDEX($Y$5:$Y$19,$AE14)) -> 0.25 | AH14: =IF($AE14="",NA(),IF(INDEX($Y$5:$Y$19,$AE14)+INDEX($Z$5:$Z$19,$AE14)>INDEX($AA$5:$AA$19,$AE14),NA(),INDEX($Z$5:$Z$19,$AE14))) -> 0.25 | AI14: =IF($AE14="",NA(),IF(INDEX($Y$5:$Y$19,$AE14)+INDEX($Z$5:$Z$19,$AE14)>INDEX($AA$5:$AA$19,$AE14),INDEX($Z$5:$Z$19,$AE14),NA())) -> #N/A | AJ14: =IF($AE14="",NA(),INDEX($AA$5:$AA$19,$AE14)) -> 1.5
A15: =IF($U15="","",11) -> 11 | B15: =IF($U15="","",INDEX(posID,$U15)) -> NFR-04 | C15: =IF($U15="","",INDEX(posNome,$U15)) -> Eventi climatici estremi su sedi e data center | D15: =IF($U15="","",INDEX(posScore,$U15)) -> 2.85 | E15: =IF($U15="","",IFERROR(INDEX(posScorePrec,$U15),"—")) -> 2.85 | F15: =IF(AND(ISNUMBER(D15),ISNUMBER(E15)),D15-E15,"") -> 0 | G15: =IF($U15="","",IFERROR(INDEX(RR_Esito,MATCH(cicloCorrente&"|"&B15,RR_Chiave,0))&"","")) -> Confermato | H15: =IF($U15="","",INDEX(Radar_Mosca!$L$5:$L$19,$U15)) -> Agire entro l'anno | I15: =IF($U15="","",IFERROR(INDEX(Radar_Mosca!$K$5:$K$19,$U15),"")) -> 0.75 | J15: =IF($U15="","",INDEX(ANA_Owner,$U15)&"") -> Funzione Business Continuity | K15: =IF($U15="","",B15&" "&IF(ISNUMBER(F15),IF(F15>0,"▲",IF(F15<0,"▼","●")),"○")&" "&LEFT(C15,34)&IF(LEN(C15)>34,"…","")) -> NFR-04 ● Eventi climatici estremi su sedi e… | T15: =IF(ISNUMBER(INDEX(posScore,11)),INDEX(posScore,11)-11/100000,"") -> 3.04989 | U15: =IFERROR(MATCH(_xlfn.AGGREGATE(14,6,$T$5:$T$19,11),$T$5:$T$19,0),"") -> 4 | V15: =IF($U15="",NA(),IF(LEFT(H15,9)="AGIRE ORA",D15,0)) -> 0 | W15: =IF($U15="",NA(),IF(LEFT(H15,11)="Agire entro",D15,0)) -> 2.85 | X15: =IF($U15="",NA(),IF(OR(LEFT(H15,9)="AGIRE ORA",LEFT(H15,11)="Agire entro"),0,D15)) -> 0 | Y15: =IF($U15="",NA(),INDEX(Radar_Mosca!$I$5:$I$19,$U15)) -> 0.25 | Z15: =IF($U15="",NA(),INDEX(Radar_Mosca!$J$5:$J$19,$U15)) -> 0.5 | AA15: =IF($U15="",NA(),INDEX(Radar_Mosca!$H$5:$H$19,$U15)) -> 1.5 | AB15: =IF(LEFT(H15,9)="AGIRE ORA",B15,"") | AD15: =IF(ISNUMBER(I15),I15+11/100000,"") -> 0.75011 | AE15: =IFERROR(MATCH(_xlfn.AGGREGATE(15,6,$AD$5:$AD$19,11),$AD$5:$AD$19,0),"") -> 8 | AF15: =IF($AE15="","",INDEX($B$5:$B$19,$AE15)&" ("&IF(INDEX($I$5:$I$19,$AE15)<0,"−","+")&FIXED(ABS(INDEX($I$5:$I$19,$AE15)),2)&")") -> NFR-05 (+1,00) | AG15: =IF($AE15="",NA(),INDEX($Y$5:$Y$19,$AE15)) -> 0.25 | AH15: =IF($AE15="",NA(),IF(INDEX($Y$5:$Y$19,$AE15)+INDEX($Z$5:$Z$19,$AE15)>INDEX($AA$5:$AA$19,$AE15),NA(),INDEX($Z$5:$Z$19,$AE15))) -> 0.25 | AI15: =IF($AE15="",NA(),IF(INDEX($Y$5:$Y$19,$AE15)+INDEX($Z$5:$Z$19,$AE15)>INDEX($AA$5:$AA$19,$AE15),INDEX($Z$5:$Z$19,$AE15),NA())) -> #N/A | AJ15: =IF($AE15="",NA(),INDEX($AA$5:$AA$19,$AE15)) -> 1.5
A16: =IF($U16="","",12) -> 12 | B16: =IF($U16="","",INDEX(posID,$U16)) -> NFR-08 | C16: =IF($U16="","",INDEX(posNome,$U16)) -> Accessi impropri di dipendenti ai dati dei clienti | D16: =IF($U16="","",INDEX(posScore,$U16)) -> 2.8 | E16: =IF($U16="","",IFERROR(INDEX(posScorePrec,$U16),"—")) -> 2.8 | F16: =IF(AND(ISNUMBER(D16),ISNUMBER(E16)),D16-E16,"") -> 0 | G16: =IF($U16="","",IFERROR(INDEX(RR_Esito,MATCH(cicloCorrente&"|"&B16,RR_Chiave,0))&"","")) -> Confermato | H16: =IF($U16="","",INDEX(Radar_Mosca!$L$5:$L$19,$U16)) -> Agire entro l'anno | I16: =IF($U16="","",IFERROR(INDEX(Radar_Mosca!$K$5:$K$19,$U16),"")) -> 0.25 | J16: =IF($U16="","",INDEX(ANA_Owner,$U16)&"") -> Funzione Sicurezza delle Informazioni | K16: =IF($U16="","",B16&" "&IF(ISNUMBER(F16),IF(F16>0,"▲",IF(F16<0,"▼","●")),"○")&" "&LEFT(C16,34)&IF(LEN(C16)>34,"…","")) -> NFR-08 ● Accessi impropri di dipendenti ai … | T16: =IF(ISNUMBER(INDEX(posScore,12)),INDEX(posScore,12)-12/100000,"") -> 3.49988 | U16: =IFERROR(MATCH(_xlfn.AGGREGATE(14,6,$T$5:$T$19,12),$T$5:$T$19,0),"") -> 8 | V16: =IF($U16="",NA(),IF(LEFT(H16,9)="AGIRE ORA",D16,0)) -> 0 | W16: =IF($U16="",NA(),IF(LEFT(H16,11)="Agire entro",D16,0)) -> 2.8 | X16: =IF($U16="",NA(),IF(OR(LEFT(H16,9)="AGIRE ORA",LEFT(H16,11)="Agire entro"),0,D16)) -> 0 | Y16: =IF($U16="",NA(),INDEX(Radar_Mosca!$I$5:$I$19,$U16)) -> 0.25 | Z16: =IF($U16="",NA(),INDEX(Radar_Mosca!$J$5:$J$19,$U16)) -> 1 | AA16: =IF($U16="",NA(),INDEX(Radar_Mosca!$H$5:$H$19,$U16)) -> 1.5 | AB16: =IF(LEFT(H16,9)="AGIRE ORA",B16,"") | AD16: =IF(ISNUMBER(I16),I16+12/100000,"") -> 0.25012 | AE16: =IFERROR(MATCH(_xlfn.AGGREGATE(15,6,$AD$5:$AD$19,12),$AD$5:$AD$19,0),"") -> 10 | AF16: =IF($AE16="","",INDEX($B$5:$B$19,$AE16)&" ("&IF(INDEX($I$5:$I$19,$AE16)<0,"−","+")&FIXED(ABS(INDEX($I$5:$I$19,$AE16)),2)&")") -> NFR-09 (+1,25) | AG16: =IF($AE16="",NA(),INDEX($Y$5:$Y$19,$AE16)) -> 0.25 | AH16: =IF($AE16="",NA(),IF(INDEX($Y$5:$Y$19,$AE16)+INDEX($Z$5:$Z$19,$AE16)>INDEX($AA$5:$AA$19,$AE16),NA(),INDEX($Z$5:$Z$19,$AE16))) -> 1 | AI16: =IF($AE16="",NA(),IF(INDEX($Y$5:$Y$19,$AE16)+INDEX($Z$5:$Z$19,$AE16)>INDEX($AA$5:$AA$19,$AE16),INDEX($Z$5:$Z$19,$AE16),NA())) -> #N/A | AJ16: =IF($AE16="",NA(),INDEX($AA$5:$AA$19,$AE16)) -> 2.5
A17: =IF($U17="","",13) | B17: =IF($U17="","",INDEX(posID,$U17)) | C17: =IF($U17="","",INDEX(posNome,$U17)) | D17: =IF($U17="","",INDEX(posScore,$U17)) | E17: =IF($U17="","",IFERROR(INDEX(posScorePrec,$U17),"—")) | F17: =IF(AND(ISNUMBER(D17),ISNUMBER(E17)),D17-E17,"") | G17: =IF($U17="","",IFERROR(INDEX(RR_Esito,MATCH(cicloCorrente&"|"&B17,RR_Chiave,0))&"","")) | H17: =IF($U17="","",INDEX(Radar_Mosca!$L$5:$L$19,$U17)) | I17: =IF($U17="","",IFERROR(INDEX(Radar_Mosca!$K$5:$K$19,$U17),"")) | J17: =IF($U17="","",INDEX(ANA_Owner,$U17)&"") | K17: =IF($U17="","",B17&" "&IF(ISNUMBER(F17),IF(F17>0,"▲",IF(F17<0,"▼","●")),"○")&" "&LEFT(C17,34)&IF(LEN(C17)>34,"…","")) | T17: =IF(ISNUMBER(INDEX(posScore,13)),INDEX(posScore,13)-13/100000,"") | U17: =IFERROR(MATCH(_xlfn.AGGREGATE(14,6,$T$5:$T$19,13),$T$5:$T$19,0),"") | V17: =IF($U17="",NA(),IF(LEFT(H17,9)="AGIRE ORA",D17,0)) -> #N/A | W17: =IF($U17="",NA(),IF(LEFT(H17,11)="Agire entro",D17,0)) -> #N/A | X17: =IF($U17="",NA(),IF(OR(LEFT(H17,9)="AGIRE ORA",LEFT(H17,11)="Agire entro"),0,D17)) -> #N/A | Y17: =IF($U17="",NA(),INDEX(Radar_Mosca!$I$5:$I$19,$U17)) -> #N/A | Z17: =IF($U17="",NA(),INDEX(Radar_Mosca!$J$5:$J$19,$U17)) -> #N/A | AA17: =IF($U17="",NA(),INDEX(Radar_Mosca!$H$5:$H$19,$U17)) -> #N/A | AB17: =IF(LEFT(H17,9)="AGIRE ORA",B17,"") | AD17: =IF(ISNUMBER(I17),I17+13/100000,"") | AE17: =IFERROR(MATCH(_xlfn.AGGREGATE(15,6,$AD$5:$AD$19,13),$AD$5:$AD$19,0),"") | AF17: =IF($AE17="","",INDEX($B$5:$B$19,$AE17)&" ("&IF(INDEX($I$5:$I$19,$AE17)<0,"−","+")&FIXED(ABS(INDEX($I$5:$I$19,$AE17)),2)&")") | AG17: =IF($AE17="",NA(),INDEX($Y$5:$Y$19,$AE17)) -> #N/A | AH17: =IF($AE17="",NA(),IF(INDEX($Y$5:$Y$19,$AE17)+INDEX($Z$5:$Z$19,$AE17)>INDEX($AA$5:$AA$19,$AE17),NA(),INDEX($Z$5:$Z$19,$AE17))) -> #N/A | AI17: =IF($AE17="",NA(),IF(INDEX($Y$5:$Y$19,$AE17)+INDEX($Z$5:$Z$19,$AE17)>INDEX($AA$5:$AA$19,$AE17),INDEX($Z$5:$Z$19,$AE17),NA())) -> #N/A | AJ17: =IF($AE17="",NA(),INDEX($AA$5:$AA$19,$AE17)) -> #N/A
A18: =IF($U18="","",14) | B18: =IF($U18="","",INDEX(posID,$U18)) | C18: =IF($U18="","",INDEX(posNome,$U18)) | D18: =IF($U18="","",INDEX(posScore,$U18)) | E18: =IF($U18="","",IFERROR(INDEX(posScorePrec,$U18),"—")) | F18: =IF(AND(ISNUMBER(D18),ISNUMBER(E18)),D18-E18,"") | G18: =IF($U18="","",IFERROR(INDEX(RR_Esito,MATCH(cicloCorrente&"|"&B18,RR_Chiave,0))&"","")) | H18: =IF($U18="","",INDEX(Radar_Mosca!$L$5:$L$19,$U18)) | I18: =IF($U18="","",IFERROR(INDEX(Radar_Mosca!$K$5:$K$19,$U18),"")) | J18: =IF($U18="","",INDEX(ANA_Owner,$U18)&"") | K18: =IF($U18="","",B18&" "&IF(ISNUMBER(F18),IF(F18>0,"▲",IF(F18<0,"▼","●")),"○")&" "&LEFT(C18,34)&IF(LEN(C18)>34,"…","")) | T18: =IF(ISNUMBER(INDEX(posScore,14)),INDEX(posScore,14)-14/100000,"") | U18: =IFERROR(MATCH(_xlfn.AGGREGATE(14,6,$T$5:$T$19,14),$T$5:$T$19,0),"") | V18: =IF($U18="",NA(),IF(LEFT(H18,9)="AGIRE ORA",D18,0)) -> #N/A | W18: =IF($U18="",NA(),IF(LEFT(H18,11)="Agire entro",D18,0)) -> #N/A | X18: =IF($U18="",NA(),IF(OR(LEFT(H18,9)="AGIRE ORA",LEFT(H18,11)="Agire entro"),0,D18)) -> #N/A | Y18: =IF($U18="",NA(),INDEX(Radar_Mosca!$I$5:$I$19,$U18)) -> #N/A | Z18: =IF($U18="",NA(),INDEX(Radar_Mosca!$J$5:$J$19,$U18)) -> #N/A | AA18: =IF($U18="",NA(),INDEX(Radar_Mosca!$H$5:$H$19,$U18)) -> #N/A | AB18: =IF(LEFT(H18,9)="AGIRE ORA",B18,"") | AD18: =IF(ISNUMBER(I18),I18+14/100000,"") | AE18: =IFERROR(MATCH(_xlfn.AGGREGATE(15,6,$AD$5:$AD$19,14),$AD$5:$AD$19,0),"") | AF18: =IF($AE18="","",INDEX($B$5:$B$19,$AE18)&" ("&IF(INDEX($I$5:$I$19,$AE18)<0,"−","+")&FIXED(ABS(INDEX($I$5:$I$19,$AE18)),2)&")") | AG18: =IF($AE18="",NA(),INDEX($Y$5:$Y$19,$AE18)) -> #N/A | AH18: =IF($AE18="",NA(),IF(INDEX($Y$5:$Y$19,$AE18)+INDEX($Z$5:$Z$19,$AE18)>INDEX($AA$5:$AA$19,$AE18),NA(),INDEX($Z$5:$Z$19,$AE18))) -> #N/A | AI18: =IF($AE18="",NA(),IF(INDEX($Y$5:$Y$19,$AE18)+INDEX($Z$5:$Z$19,$AE18)>INDEX($AA$5:$AA$19,$AE18),INDEX($Z$5:$Z$19,$AE18),NA())) -> #N/A | AJ18: =IF($AE18="",NA(),INDEX($AA$5:$AA$19,$AE18)) -> #N/A
A19: =IF($U19="","",15) | B19: =IF($U19="","",INDEX(posID,$U19)) | C19: =IF($U19="","",INDEX(posNome,$U19)) | D19: =IF($U19="","",INDEX(posScore,$U19)) | E19: =IF($U19="","",IFERROR(INDEX(posScorePrec,$U19),"—")) | F19: =IF(AND(ISNUMBER(D19),ISNUMBER(E19)),D19-E19,"") | G19: =IF($U19="","",IFERROR(INDEX(RR_Esito,MATCH(cicloCorrente&"|"&B19,RR_Chiave,0))&"","")) | H19: =IF($U19="","",INDEX(Radar_Mosca!$L$5:$L$19,$U19)) | I19: =IF($U19="","",IFERROR(INDEX(Radar_Mosca!$K$5:$K$19,$U19),"")) | J19: =IF($U19="","",INDEX(ANA_Owner,$U19)&"") | K19: =IF($U19="","",B19&" "&IF(ISNUMBER(F19),IF(F19>0,"▲",IF(F19<0,"▼","●")),"○")&" "&LEFT(C19,34)&IF(LEN(C19)>34,"…","")) | T19: =IF(ISNUMBER(INDEX(posScore,15)),INDEX(posScore,15)-15/100000,"") | U19: =IFERROR(MATCH(_xlfn.AGGREGATE(14,6,$T$5:$T$19,15),$T$5:$T$19,0),"") | V19: =IF($U19="",NA(),IF(LEFT(H19,9)="AGIRE ORA",D19,0)) -> #N/A | W19: =IF($U19="",NA(),IF(LEFT(H19,11)="Agire entro",D19,0)) -> #N/A | X19: =IF($U19="",NA(),IF(OR(LEFT(H19,9)="AGIRE ORA",LEFT(H19,11)="Agire entro"),0,D19)) -> #N/A | Y19: =IF($U19="",NA(),INDEX(Radar_Mosca!$I$5:$I$19,$U19)) -> #N/A | Z19: =IF($U19="",NA(),INDEX(Radar_Mosca!$J$5:$J$19,$U19)) -> #N/A | AA19: =IF($U19="",NA(),INDEX(Radar_Mosca!$H$5:$H$19,$U19)) -> #N/A | AB19: =IF(LEFT(H19,9)="AGIRE ORA",B19,"") | AD19: =IF(ISNUMBER(I19),I19+15/100000,"") | AE19: =IFERROR(MATCH(_xlfn.AGGREGATE(15,6,$AD$5:$AD$19,15),$AD$5:$AD$19,0),"") | AF19: =IF($AE19="","",INDEX($B$5:$B$19,$AE19)&" ("&IF(INDEX($I$5:$I$19,$AE19)<0,"−","+")&FIXED(ABS(INDEX($I$5:$I$19,$AE19)),2)&")") | AG19: =IF($AE19="",NA(),INDEX($Y$5:$Y$19,$AE19)) -> #N/A | AH19: =IF($AE19="",NA(),IF(INDEX($Y$5:$Y$19,$AE19)+INDEX($Z$5:$Z$19,$AE19)>INDEX($AA$5:$AA$19,$AE19),NA(),INDEX($Z$5:$Z$19,$AE19))) -> #N/A | AI19: =IF($AE19="",NA(),IF(INDEX($Y$5:$Y$19,$AE19)+INDEX($Z$5:$Z$19,$AE19)>INDEX($AA$5:$AA$19,$AE19),INDEX($Z$5:$Z$19,$AE19),NA())) -> #N/A | AJ19: =IF($AE19="",NA(),INDEX($AA$5:$AA$19,$AE19)) -> #N/A
A48: Come si legge: a sinistra un rischio per barra, dal piu' alto per score composito; colore = urgenza, freccia = variazione sul ciclo prima. A destra la lente di Mosca, dal piu' in ritardo: colonna = tempo necessario X + Y, rombo = tempo disponibile Z; la parte rossa sfora (tra parentesi il margine).
A49: Legenda — X = anni per decidere e avviare la mitigazione (un trimestre); Y = anni per mitigare (azioni o adeguamento strutturale); Z = anni prima che il rischio possa manifestarsi (dalla Prossimita); AGIRE ORA = X + Y > Z. Frecce: ▲ score in aumento, ▼ in diminuzione, ● invariato, ○ nuovo. NFR-nn = codice del rischio; ◆ = tema all'attenzione del supervisore (BCE, EBA, Banca d'Italia), indicato dal validatore.

Sheet Radar_Mosca
A1: ="Horizon Scan NFR — Radar di Mosca: quanto presto agire, e quanto e' grande ogni rischio · "&etichettaCiclo -> Horizon Scan NFR — Radar di Mosca: quanto presto agire, e quanto e' grande ogni rischio · Ciclo 2026Q3 · dati al 30/09/2026 · validato · Uso interno
A2: CICLO TRIMESTRALE — calcolato dal foglio: Z dalla Prossimita', Y dalle azioni o dagli anni di adeguamento. Come si legge: piu' vicino al centro = agire prima. Dentro il cerchio rosso (X + Y > Z) si e' gia' in ritardo anche se l'evento non e' imminente. Area del cerchio = Probabilita x Severity; bordo giallo = tema all'attenzione del supervisore; settore = event type. Parametri X, Y e Z: foglio Parametri, righe 47-55.
U3: Appoggio del grafico: non modificare | AZ3: vigilanza | BA3: vigilanza | BB3: vigilanza | BC3: vigilanza | BD3: vigilanza | BE3: vigilanza | BF3: vigilanza | BG3: vigilanza | BH3: vigilanza | BI3: vigilanza | BJ3: vigilanza | BK3: vigilanza | BL3: vigilanza | BM3: vigilanza
A4: ID | B4: Nome | C4: Event type | D4: Impatto (Severity) | E4: Probabilita | F4: P x I | G4: Prossimita | H4: Z anni alla manifestazione | I4: X anni per decidere | J4: Y anni per mitigare (azioni o adeguamento) | K4: Margine Z-(X+Y) | L4: Urgenza | M4: Settore | N4: Posizione nel settore | O4: Rischi nel settore | P4: Angolo | Q4: Raggio | R4: x | S4: y | T4: Attenzione del supervisore | AL4: 1 | AM4: 2 | AN4: 3 | AO4: 4 | AP4: 5 | AQ4: 6 | AR4: 8 | AS4: 9 | AT4: 10 | AU4: 12 | AV4: 15 | AW4: 16 | AX4: 20 | AY4: 25 | AZ4: 1 | BA4: 2 | BB4: 3 | BC4: 4 | BD4: 5 | BE4: 6 | BF4: 8 | BG4: 9 | BH4: 10 | BI4: 12 | BJ4: 15 | BK4: 16 | BL4: 20 | BM4: 25
A5: =IF(Parametri!$H4="","",Parametri!$H4) -> NFR-01 | B5: =IF($A5="","",Parametri!$I4) -> Frodi su pagamenti istantanei abilitate da AI generativa | C5: =IF($A5="","",Parametri!$J4) -> L1-02 | D5: =IF($A5="",NA(),IF(COUNTIFS(RR_ID_Rischio,$A5,RR_Ciclo,cicloCorrente)=0,NA(),SUMIFS(RR_Severity,RR_ID_Rischio,$A5,RR_Ciclo,cicloCorrente))) -> 4 | E5: =IF($A5="",NA(),IF(COUNTIFS(RR_ID_Rischio,$A5,RR_Ciclo,cicloCorrente)=0,NA(),SUMIFS(RR_Probabilita,RR_ID_Rischio,$A5,RR_Ciclo,cicloCorrente))) -> 4 | F5: =IF(AND(ISNUMBER(D5),ISNUMBER(E5)),D5*E5,NA()) -> 16 | G5: =IF($A5="",NA(),IF(COUNTIFS(RR_ID_Rischio,$A5,RR_Ciclo,cicloCorrente)=0,NA(),SUMIFS(RR_Prossimita,RR_ID_Rischio,$A5,RR_Ciclo,cicloCorrente))) -> 4 | H5: =IF(ISNUMBER(G5),INDEX(anniProssimita,G5),NA()) -> 0.5 | I5: =IF($A5="",NA(),moscaX) -> 0.25 | J5: =IF($A5="",NA(),MAX(IF(COUNTIFS(AZ_ID_Rischio,$A5,AZ_Ciclo,cicloCorrente,AZ_Stato,"<>Respinta",AZ_Mesi_Orizzonte,">0")=0,moscaYDefault,_xlfn.MAXIFS(AZ_Mesi_Orizzonte,AZ_ID_Rischio,$A5,AZ_Ciclo,cicloCorrente,AZ_Stato,"<>Respinta")/12),N(Parametri!$M4))) -> 0.5 | K5: =IF(AND(ISNUMBER(H5),ISNUMBER(J5)),H5-(I5+J5),NA()) -> -0.25 | L5: =IF(NOT(ISNUMBER(K5)),"",IF(K5<0,"AGIRE ORA: X+Y > Z",IF(K5<1,"Agire entro l'anno","Margine "&ROUND(K5,1)&IF(ROUND(K5,1)=1," anno"," anni")))) -> AGIRE ORA: X+Y > Z | M5: =IF($A5="",NA(),MATCH(C5,codiciL1,0)-1) -> 1 | N5: =IF($A5="",NA(),COUNTIF($C$4:C4,C5)) -> 0 | O5: =IF($A5="",NA(),COUNTIF(ANA_Event_Type,C5)) -> 1 | P5: =IF($A5="",NA(),2*PI()*(M5+(N5+0.5)/O5)/ROWS(codiciL1)) -> 1.3463969 | Q5: =IF(ISNUMBER(K5),MAX(0.6,MIN(6,K5+2)),NA()) -> 1.75 | R5: =IF(AND(ISNUMBER(Q5),ISNUMBER(P5)),Q5*SIN(P5),NA()) -> 1.7061238 | S5: =IF(AND(ISNUMBER(Q5),ISNUMBER(P5)),Q5*COS(P5),NA()) -> 0.38941163 | T5: =IF($A5="","",IF(Parametri!$N4="Sì","Sì","")) -> Sì | U5: =2*PI()*0/72 -> 0 | V5: =2*SIN($U5) -> 0 | W5: =2*COS($U5) -> 2 | X5: =3*SIN($U5) -> 0 | Y5: =3*COS($U5) -> 3 | Z5: =4*SIN($U5) -> 0 | AA5: =4*COS($U5) -> 4 | AB5: =5*SIN($U5) -> 0 | AC5: =5*COS($U5) -> 5 | AE5: 0 | AF5: 0 | AH5: L1-01 Frode interna | AI5: =6.95*SIN(2*PI()*(0+0.5)/ROWS(codiciL1)) -> 3.015492 | AJ5: =6.95*COS(2*PI()*(0+0.5)/ROWS(codiciL1)) -> 6.2617336 | AL5: =IF(AND(ISNUMBER($F5),ISNUMBER($S5)),IF(AND($F5=AL$4,$T5<>"Sì"),$S5,NA()),NA()) -> #N/A | AM5: =IF(AND(ISNUMBER($F5),ISNUMBER($S5)),IF(AND($F5=AM$4,$T5<>"Sì"),$S5,NA()),NA()) -> #N/A | AN5: =IF(AND(ISNUMBER($F5),ISNUMBER($S5)),IF(AND($F5=AN$4,$T5<>"Sì"),$S5,NA()),NA()) -> #N/A | AO5: =IF(AND(ISNUMBER($F5),ISNUMBER($S5)),IF(AND($F5=AO$4,$T5<>"Sì"),$S5,NA()),NA()) -> #N/A | AP5: =IF(AND(ISNUMBER($F5),ISNUMBER($S5)),IF(AND($F5=AP$4,$T5<>"Sì"),$S5,NA()),NA()) -> #N/A | AQ5: =IF(AND(ISNUMBER($F5),ISNUMBER($S5)),IF(AND($F5=AQ$4,$T5<>"Sì"),$S5,NA()),NA()) -> #N/A | AR5: =IF(AND(ISNUMBER($F5),ISNUMBER($S5)),IF(AND($F5=AR$4,$T5<>"Sì"),$S5,NA()),NA()) -> #N/A | AS5: =IF(AND(ISNUMBER($F5),ISNUMBER($S5)),IF(AND($F5=AS$4,$T5<>"Sì"),$S5,NA()),NA()) -> #N/A | ... AY5: =IF(AND(ISNUMBER($F5),ISNUMBER($S5)),IF(AND($F5=AY$4,$T5<>"Sì"),$S5,NA()),NA()) -> #N/A | AZ5: =IF(AND(ISNUMBER($F5),ISNUMBER($S5)),IF(AND($F5=AZ$4,$T5="Sì"),$S5,NA()),NA()) -> #N/A | BA5: =IF(AND(ISNUMBER($F5),ISNUMBER($S5)),IF(AND($F5=BA$4,$T5="Sì"),$S5,NA()),NA()) -> #N/A | BB5: =IF(AND(ISNUMBER($F5),ISNUMBER($S5)),IF(AND($F5=BB$4,$T5="Sì"),$S5,NA()),NA()) -> #N/A | BC5: =IF(AND(ISNUMBER($F5),ISNUMBER($S5)),IF(AND($F5=BC$4,$T5="Sì"),$S5,NA()),NA()) -> #N/A | BD5: =IF(AND(ISNUMBER($F5),ISNUMBER($S5)),IF(AND($F5=BD$4,$T5="Sì"),$S5,NA()),NA()) -> #N/A | BE5: =IF(AND(ISNUMBER($F5),ISNUMBER($S5)),IF(AND($F5=BE$4,$T5="Sì"),$S5,NA()),NA()) -> #N/A | BF5: =IF(AND(ISNUMBER($F5),ISNUMBER($S5)),IF(AND($F5=BF$4,$T5="Sì"),$S5,NA()),NA()) -> #N/A | BG5: =IF(AND(ISNUMBER($F5),ISNUMBER($S5)),IF(AND($F5=BG$4,$T5="Sì"),$S5,NA()),NA()) -> #N/A | ... BM5: =IF(AND(ISNUMBER($F5),ISNUMBER($S5)),IF(AND($F5=BM$4,$T5="Sì"),$S5,NA()),NA()) -> #N/A | BN5: =IF(ISNUMBER($R5),$R5,NA()) -> 1.7061238 | BO5: =IF($A5="","",$A5) -> NFR-01 | BP5: =IF(ISNUMBER($S5),$S5,NA()) -> 0.38941163 | BQ5: attenzione del supervisore | BR5: -6.9 | BS5: -6.35
A6: =IF(Parametri!$H5="","",Parametri!$H5) -> NFR-02 | B6: =IF($A6="","",Parametri!$I5) -> Concentrazione su un fornitore cloud critico | C6: =IF($A6="","",Parametri!$J5) -> L1-06 | D6: =IF($A6="",NA(),IF(COUNTIFS(RR_ID_Rischio,$A6,RR_Ciclo,cicloCorrente)=0,NA(),SUMIFS(RR_Severity,RR_ID_Rischio,$A6,RR_Ciclo,cicloCorrente))) -> 4 | E6: =IF($A6="",NA(),IF(COUNTIFS(RR_ID_Rischio,$A6,RR_Ciclo,cicloCorrente)=0,NA(),SUMIFS(RR_Probabilita,RR_ID_Rischio,$A6,RR_Ciclo,cicloCorrente))) -> 2 | F6: =IF(AND(ISNUMBER(D6),ISNUMBER(E6)),D6*E6,NA()) -> 8 | G6: =IF($A6="",NA(),IF(COUNTIFS(RR_ID_Rischio,$A6,RR_Ciclo,cicloCorrente)=0,NA(),SUMIFS(RR_Prossimita,RR_ID_Rischio,$A6,RR_Ciclo,cicloCorrente))) -> 3 | H6: =IF(ISNUMBER(G6),INDEX(anniProssimita,G6),NA()) -> 1.5 | I6: =IF($A6="",NA(),moscaX) -> 0.25 | J6: =IF($A6="",NA(),MAX(IF(COUNTIFS(AZ_ID_Rischio,$A6,AZ_Ciclo,cicloCorrente,AZ_Stato,"<>Respinta",AZ_Mesi_Orizzonte,">0")=0,moscaYDefault,_xlfn.MAXIFS(AZ_Mesi_Orizzonte,AZ_ID_Rischio,$A6,AZ_Ciclo,cicloCorrente,AZ_Stato,"<>Respinta")/12),N(Parametri!$M5))) -> 1 | K6: =IF(AND(ISNUMBER(H6),ISNUMBER(J6)),H6-(I6+J6),NA()) -> 0.25 | L6: =IF(NOT(ISNUMBER(K6)),"",IF(K6<0,"AGIRE ORA: X+Y > Z",IF(K6<1,"Agire entro l'anno","Margine "&ROUND(K6,1)&IF(ROUND(K6,1)=1," anno"," anni")))) -> Agire entro l'anno | M6: =IF($A6="",NA(),MATCH(C6,codiciL1,0)-1) -> 5 | N6: =IF($A6="",NA(),COUNTIF($C$4:C5,C6)) -> 0 | O6: =IF($A6="",NA(),COUNTIF(ANA_Event_Type,C6)) -> 3 | P6: =IF($A6="",NA(),2*PI()*(M6+(N6+0.5)/O6)/ROWS(codiciL1)) -> 4.6375892 | Q6: =IF(ISNUMBER(K6),MAX(0.6,MIN(6,K6+2)),NA()) -> 2.25 | R6: =IF(AND(ISNUMBER(Q6),ISNUMBER(P6)),Q6*SIN(P6),NA()) -> -2.2437085 | S6: =IF(AND(ISNUMBER(Q6),ISNUMBER(P6)),Q6*COS(P6),NA()) -> -0.16814271 | T6: =IF($A6="","",IF(Parametri!$N5="Sì","Sì","")) -> Sì | U6: =2*PI()*1/72 -> 0.087266463 | V6: =2*SIN($U6) -> 0.17431149 | W6: =2*COS($U6) -> 1.9923894 | X6: =3*SIN($U6) -> 0.26146723 | Y6: =3*COS($U6) -> 2.9885841 | Z6: =4*SIN($U6) -> 0.34862297 | AA6: =4*COS($U6) -> 3.9847788 | AB6: =5*SIN($U6) -> 0.43577871 | AC6: =5*COS($U6) -> 4.9809735 | AE6: =6.3*SIN(2*PI()*0/ROWS(codiciL1)) -> 0 | AF6: =6.3*COS(2*PI()*0/ROWS(codiciL1)) -> 6.3 | AH6: L1-02 Frode esterna | AI6: =6.95*SIN(2*PI()*(1+0.5)/ROWS(codiciL1)) -> 6.775749 | AJ6: =6.95*COS(2*PI()*(1+0.5)/ROWS(codiciL1)) -> 1.5465205 | AL6: =IF(AND(ISNUMBER($F6),ISNUMBER($S6)),IF(AND($F6=AL$4,$T6<>"Sì"),$S6,NA()),NA()) -> #N/A | AM6: =IF(AND(ISNUMBER($F6),ISNUMBER($S6)),IF(AND($F6=AM$4,$T6<>"Sì"),$S6,NA()),NA()) -> #N/A | AN6: =IF(AND(ISNUMBER($F6),ISNUMBER($S6)),IF(AND($F6=AN$4,$T6<>"Sì"),$S6,NA()),NA()) -> #N/A | AO6: =IF(AND(ISNUMBER($F6),ISNUMBER($S6)),IF(AND($F6=AO$4,$T6<>"Sì"),$S6,NA()),NA()) -> #N/A | AP6: =IF(AND(ISNUMBER($F6),ISNUMBER($S6)),IF(AND($F6=AP$4,$T6<>"Sì"),$S6,NA()),NA()) -> #N/A | AQ6: =IF(AND(ISNUMBER($F6),ISNUMBER($S6)),IF(AND($F6=AQ$4,$T6<>"Sì"),$S6,NA()),NA()) -> #N/A | AR6: =IF(AND(ISNUMBER($F6),ISNUMBER($S6)),IF(AND($F6=AR$4,$T6<>"Sì"),$S6,NA()),NA()) -> #N/A | AS6: =IF(AND(ISNUMBER($F6),ISNUMBER($S6)),IF(AND($F6=AS$4,$T6<>"Sì"),$S6,NA()),NA()) -> #N/A | ... AY6: =IF(AND(ISNUMBER($F6),ISNUMBER($S6)),IF(AND($F6=AY$4,$T6<>"Sì"),$S6,NA()),NA()) -> #N/A | AZ6: =IF(AND(ISNUMBER($F6),ISNUMBER($S6)),IF(AND($F6=AZ$4,$T6="Sì"),$S6,NA()),NA()) -> #N/A | BA6: =IF(AND(ISNUMBER($F6),ISNUMBER($S6)),IF(AND($F6=BA$4,$T6="Sì"),$S6,NA()),NA()) -> #N/A | BB6: =IF(AND(ISNUMBER($F6),ISNUMBER($S6)),IF(AND($F6=BB$4,$T6="Sì"),$S6,NA()),NA()) -> #N/A | BC6: =IF(AND(ISNUMBER($F6),ISNUMBER($S6)),IF(AND($F6=BC$4,$T6="Sì"),$S6,NA()),NA()) -> #N/A | BD6: =IF(AND(ISNUMBER($F6),ISNUMBER($S6)),IF(AND($F6=BD$4,$T6="Sì"),$S6,NA()),NA()) -> #N/A | BE6: =IF(AND(ISNUMBER($F6),ISNUMBER($S6)),IF(AND($F6=BE$4,$T6="Sì"),$S6,NA()),NA()) -> #N/A | BF6: =IF(AND(ISNUMBER($F6),ISNUMBER($S6)),IF(AND($F6=BF$4,$T6="Sì"),$S6,NA()),NA()) -> -0.16814271 | BG6: =IF(AND(ISNUMBER($F6),ISNUMBER($S6)),IF(AND($F6=BG$4,$T6="Sì"),$S6,NA()),NA()) -> #N/A | ... BM6: =IF(AND(ISNUMBER($F6),ISNUMBER($S6)),IF(AND($F6=BM$4,$T6="Sì"),$S6,NA()),NA()) -> #N/A | BN6: =IF(ISNUMBER($R6),$R6,NA()) -> -2.2437085 | BO6: =IF($A6="","",$A6) -> NFR-02 | BP6: =IF(ISNUMBER($S6),$S6,NA()) -> -0.16814271 | BQ6: dentro il cerchio rosso: AGIRE ORA (X + Y > Z) | BR6: -7.35 | BS6: -7.35
A7: =IF(Parametri!$H6="","",Parametri!$H6) -> NFR-03 | B7: =IF($A7="","",Parametri!$I6) -> Greenwashing nella commercializzazione di prodotti ESG | C7: =IF($A7="","",Parametri!$J6) -> L1-04 | D7: =IF($A7="",NA(),IF(COUNTIFS(RR_ID_Rischio,$A7,RR_Ciclo,cicloCorrente)=0,NA(),SUMIFS(RR_Severity,RR_ID_Rischio,$A7,RR_Ciclo,cicloCorrente))) -> 3 | E7: =IF($A7="",NA(),IF(COUNTIFS(RR_ID_Rischio,$A7,RR_Ciclo,cicloCorrente)=0,NA(),SUMIFS(RR_Probabilita,RR_ID_Rischio,$A7,RR_Ciclo,cicloCorrente))) -> 3 | F7: =IF(AND(ISNUMBER(D7),ISNUMBER(E7)),D7*E7,NA()) -> 9 | G7: =IF($A7="",NA(),IF(COUNTIFS(RR_ID_Rischio,$A7,RR_Ciclo,cicloCorrente)=0,NA(),SUMIFS(RR_Prossimita,RR_ID_Rischio,$A7,RR_Ciclo,cicloCorrente))) -> 4 | H7: =IF(ISNUMBER(G7),INDEX(anniProssimita,G7),NA()) -> 0.5 | I7: =IF($A7="",NA(),moscaX) -> 0.25 | J7: =IF($A7="",NA(),MAX(IF(COUNTIFS(AZ_ID_Rischio,$A7,AZ_Ciclo,cicloCorrente,AZ_Stato,"<>Respinta",AZ_Mesi_Orizzonte,">0")=0,moscaYDefault,_xlfn.MAXIFS(AZ_Mesi_Orizzonte,AZ_ID_Rischio,$A7,AZ_Ciclo,cicloCorrente,AZ_Stato,"<>Respinta")/12),N(Parametri!$M6))) -> 0.25 | K7: =IF(AND(ISNUMBER(H7),ISNUMBER(J7)),H7-(I7+J7),NA()) -> 0 | L7: =IF(NOT(ISNUMBER(K7)),"",IF(K7<0,"AGIRE ORA: X+Y > Z",IF(K7<1,"Agire entro l'anno","Margine "&ROUND(K7,1)&IF(ROUND(K7,1)=1," anno"," anni")))) -> Agire entro l'anno | M7: =IF($A7="",NA(),MATCH(C7,codiciL1,0)-1) -> 3 | N7: =IF($A7="",NA(),COUNTIF($C$4:C6,C7)) -> 0 | O7: =IF($A7="",NA(),COUNTIF(ANA_Event_Type,C7)) -> 3 | P7: =IF($A7="",NA(),2*PI()*(M7+(N7+0.5)/O7)/ROWS(codiciL1)) -> 2.8423934 | Q7: =IF(ISNUMBER(K7),MAX(0.6,MIN(6,K7+2)),NA()) -> 2 | R7: =IF(AND(ISNUMBER(Q7),ISNUMBER(P7)),Q7*SIN(P7),NA()) -> 0.58951035 | S7: =IF(AND(ISNUMBER(Q7),ISNUMBER(P7)),Q7*COS(P7),NA()) -> -1.9111456 | T7: =IF($A7="","",IF(Parametri!$N6="Sì","Sì","")) | U7: =2*PI()*2/72 -> 0.17453293 | V7: =2*SIN($U7) -> 0.34729636 | W7: =2*COS($U7) -> 1.9696155 | X7: =3*SIN($U7) -> 0.52094453 | Y7: =3*COS($U7) -> 2.9544233 | Z7: =4*SIN($U7) -> 0.69459271 | AA7: =4*COS($U7) -> 3.939231 | AB7: =5*SIN($U7) -> 0.86824089 | AC7: =5*COS($U7) -> 4.9240388 | AE7: 0 | AF7: 0 | AH7: L1-03 Impiego e sicurezza | AI7: =6.95*SIN(2*PI()*(2+0.5)/ROWS(codiciL1)) -> 5.4337288 | AJ7: =6.95*COS(2*PI()*(2+0.5)/ROWS(codiciL1)) -> -4.3332541 | AL7: =IF(AND(ISNUMBER($F7),ISNUMBER($S7)),IF(AND($F7=AL$4,$T7<>"Sì"),$S7,NA()),NA()) -> #N/A | AM7: =IF(AND(ISNUMBER($F7),ISNUMBER($S7)),IF(AND($F7=AM$4,$T7<>"Sì"),$S7,NA()),NA()) -> #N/A | AN7: =IF(AND(ISNUMBER($F7),ISNUMBER($S7)),IF(AND($F7=AN$4,$T7<>"Sì"),$S7,NA()),NA()) -> #N/A | AO7: =IF(AND(ISNUMBER($F7),ISNUMBER($S7)),IF(AND($F7=AO$4,$T7<>"Sì"),$S7,NA()),NA()) -> #N/A | AP7: =IF(AND(ISNUMBER($F7),ISNUMBER($S7)),IF(AND($F7=AP$4,$T7<>"Sì"),$S7,NA()),NA()) -> #N/A | AQ7: =IF(AND(ISNUMBER($F7),ISNUMBER($S7)),IF(AND($F7=AQ$4,$T7<>"Sì"),$S7,NA()),NA()) -> #N/A | AR7: =IF(AND(ISNUMBER($F7),ISNUMBER($S7)),IF(AND($F7=AR$4,$T7<>"Sì"),$S7,NA()),NA()) -> #N/A | AS7: =IF(AND(ISNUMBER($F7),ISNUMBER($S7)),IF(AND($F7=AS$4,$T7<>"Sì"),$S7,NA()),NA()) -> -1.9111456 | ... AY7: =IF(AND(ISNUMBER($F7),ISNUMBER($S7)),IF(AND($F7=AY$4,$T7<>"Sì"),$S7,NA()),NA()) -> #N/A | AZ7: =IF(AND(ISNUMBER($F7),ISNUMBER($S7)),IF(AND($F7=AZ$4,$T7="Sì"),$S7,NA()),NA()) -> #N/A | BA7: =IF(AND(ISNUMBER($F7),ISNUMBER($S7)),IF(AND($F7=BA$4,$T7="Sì"),$S7,NA()),NA()) -> #N/A | BB7: =IF(AND(ISNUMBER($F7),ISNUMBER($S7)),IF(AND($F7=BB$4,$T7="Sì"),$S7,NA()),NA()) -> #N/A | BC7: =IF(AND(ISNUMBER($F7),ISNUMBER($S7)),IF(AND($F7=BC$4,$T7="Sì"),$S7,NA()),NA()) -> #N/A | BD7: =IF(AND(ISNUMBER($F7),ISNUMBER($S7)),IF(AND($F7=BD$4,$T7="Sì"),$S7,NA()),NA()) -> #N/A | BE7: =IF(AND(ISNUMBER($F7),ISNUMBER($S7)),IF(AND($F7=BE$4,$T7="Sì"),$S7,NA()),NA()) -> #N/A | BF7: =IF(AND(ISNUMBER($F7),ISNUMBER($S7)),IF(AND($F7=BF$4,$T7="Sì"),$S7,NA()),NA()) -> #N/A | BG7: =IF(AND(ISNUMBER($F7),ISNUMBER($S7)),IF(AND($F7=BG$4,$T7="Sì"),$S7,NA()),NA()) -> #N/A | ... BM7: =IF(AND(ISNUMBER($F7),ISNUMBER($S7)),IF(AND($F7=BM$4,$T7="Sì"),$S7,NA()),NA()) -> #N/A | BN7: =IF(ISNUMBER($R7),$R7,NA()) -> 0.58951035 | BO7: =IF($A7="","",$A7) -> NFR-03 | BP7: =IF(ISNUMBER($S7),$S7,NA()) -> -1.9111456 | BR7: -6.45 | BS7: -7.35
