Workbook
Name ANA_Driver: Parametri!$K$4:$K$18
Name ANA_Event_Type: Parametri!$J$4:$J$18
Name ANA_ID: Parametri!$H$4:$H$18
Name ANA_Nome: Parametri!$I$4:$I$18
Name ANA_Owner: Parametri!$L$4:$L$18
Name anagrafica: Parametri!$H$4:$L$18
Name anniProssimita: Parametri!$B$51:$B$55
Name AZ_Ciclo: Azioni!$A$2:$A$20003
Name AZ_Data_Decisione: Azioni!$K$2:$K$20003
Name AZ_Decisa_Da: Azioni!$L$2:$L$20003
Name AZ_Descrizione: Azioni!$D$2:$D$20003
Name AZ_Dimensione: Azioni!$F$2:$F$20003
Name AZ_ID_Azione: Azioni!$C$2:$C$20003
Name AZ_ID_Rischio: Azioni!$B$2:$B$20003
Name AZ_Mesi_Orizzonte: Azioni!$H$2:$H$20003
Name AZ_Orizzonte: Azioni!$G$2:$G$20003
Name AZ_Owner: Azioni!$E$2:$E$20003
Name AZ_Razionale: Azioni!$I$2:$I$20003
Name AZ_Stato: Azioni!$J$2:$J$20003
Name AZ_Validazione: Azioni!$M$2:$M$20003
Name capienzaElencoKRI: 150
Name capienzaKRICorrenti: 60
Name cicliTrend: Parametri!$B$20:$B$27
Name cicloCorrente: Parametri!$B$15
Name cicloMeno2: Parametri!$B$17
Name cicloPrecedente: Parametri!$B$16
Name codiciL1: Parametri!$E$4:$E$10
Name elencoKRI: OFFSET(Andamento_KRI!$L$12,0,0,MAX(1,COUNTIF(Andamento_KRI!$L$12:$L$161,"?*")),1)
Name inizioFinestra4: Parametri!$B$31
Name KRI_Chiave: KRI!$R$2:$R$19937
Name KRI_Ciclo: KRI!$A$2:$A$19937
Name KRI_Ciclo_Aggiornamento: KRI!$P$2:$P$19937
Name KRI_Ciclo_Definizione: KRI!$O$2:$O$19937
Name KRI_Data_Rilevazione: KRI!$J$2:$J$19937
Name KRI_Fonte_Dati: KRI!$F$2:$F$19937
Name KRI_Fonte_Rilevazione: KRI!$K$2:$K$19937
Name KRI_ID_Rischio: KRI!$C$2:$C$19937
Name KRI_In_Vigore: KRI!$N$2:$N$19937
Name KRI_KRI_ID: KRI!$B$2:$B$19937
Name KRI_Nome: KRI!$D$2:$D$19937
Name KRI_Nota_Rilevazione: KRI!$L$2:$L$19937
Name KRI_Razionale: KRI!$Q$2:$Q$19937
Name KRI_Soglia_Allerta: KRI!$H$2:$H$19937
Name KRI_Soglia_Attenzione: KRI!$G$2:$G$19937
Name KRI_Stato: KRI!$M$2:$M$19937
Name KRI_Unita: KRI!$E$2:$E$19937
Name KRI_Validazione: KRI!$S$2:$S$19937
Name KRI_Valore_Corrente: KRI!$I$2:$I$19937
Name moscaX: Parametri!$B$48
Name moscaYDefault: Parametri!$B$49
Name NW_Codice_Fonte: NewsLog!$F$2:$F$19995
Name NW_Data: NewsLog!$A$2:$A$19995
Name NW_Fonte: NewsLog!$E$2:$E$19995
Name NW_ID_Notizia: NewsLog!$C$2:$C$19995
Name NW_Imp_L1_01: NewsLog!$I$2:$I$19995
Name NW_Imp_L1_02: NewsLog!$J$2:$J$19995
Name NW_Imp_L1_03: NewsLog!$K$2:$K$19995
Name NW_Imp_L1_04: NewsLog!$L$2:$L$19995
Name NW_Imp_L1_05: NewsLog!$M$2:$M$19995
Name NW_Imp_L1_06: NewsLog!$N$2:$N$19995

Sheet Leggimi
A1: Registro NFR emergenti — come si usa questo workbook
A4: CHE COSA TROVI E DOVE
A5: Dashboard: situazione del ciclo (radar, badge settimanali, controllo di copertura riga 10, stato della validazione riga 8).
A6: Radar_Mosca: quanto presto bisogna agire su ogni rischio (vicino al centro = subito) e quanto e' grande (area del cerchio).
A7: Validazione: le proposte degli agenti da accettare, correggere o respingere. E' L'UNICO FOGLIO IN CUI SI SCRIVE A MANO.
A8: Trend, Delta, Approfondimento, KRI_Correnti, Andamento_KRI, Analisi_News: viste di sola lettura, si aggiornano da sole.
A9: RiskRegister, Azioni, KRI, NewsLog: i dati. Li scrive solo lo script: NON modificarli a mano.
A10: Parametri: pesi, soglie, parametri dell'urgenza (celle gialle, da cambiare solo se deciso dalla funzione di rischio).
A12: COSA FARE, IN BREVE (la guida completa e' 00_GUIDA_PASSO_PASSO.md nel pacchetto)
A13: Ogni lunedi': lo script raccoglie le notizie, l'agente A3 le valuta, lo script le scrive qui (comando settimanale).
A14: Ogni trimestre: lo script esporta la baseline, A1 valuta i rischi, A5 li controlla, lo script scrive qui (comando trimestrale).
A15: Dopo ogni trimestre: il validatore apre il foglio Validazione, decide, salva e CHIUDE il file, poi lancia il comando valida.
... A34: Generato da 03_Excel/genera_dashboard.py. Per rifarlo a mano: 03_Excel/costruzione_manuale_template.md.

Sheet Dashboard
A1: Dashboard — registro NFR emergenti
A2: Livello VISTA: solo formule. Si aggiorna da solo quando la scrittura aggiunge righe ai dati.
A3: Ciclo corrente | B3: =cicloCorrente -> 2026Q3 | C3: Precedente | D3: =cicloPrecedente -> 2026Q2 | E3: Due cicli prima | F3: =cicloMeno2 -> 2026Q1
A5: Score composito 1-5 (5 = peggiore), calcolato dal foglio con i pesi di Parametri. #N/A = non valutato.
A6: Badge: segnali netti delle ultime 4 settimane rispetto alla soglia di direzione. Non modifica score.
A8: VALIDAZIONE DEL CICLO | B8: Decisioni da prendere | C8: =COUNTIFS(VAL_Periodo,cicloCorrente,VAL_Stato,"Da decidere") -> 0 | D8: Rettifiche applicate | E8: =COUNTIFS(VAL_Periodo,cicloCorrente,VAL_Decisione,"Rettificato",VAL_Stato,"Applicata") -> 2 | F8: =IF(C8>0,"CICLO NON ANCORA VALIDATO — vedi foglio Validazione","Ciclo validato") -> Ciclo validato
A10: CONTROLLO DI COPERTURA | B10: Rischi in anagrafica | C10: =COUNTIF(ANA_ID,"NFR-*") -> 12 | D10: Valutati nel ciclo | E10: =SUMPRODUCT((ANA_ID<>"")*(COUNTIFS(RR_ID_Rischio,ANA_ID,RR_Ciclo,cicloCorrente)>0)) -> 12 | F10: =IF(C10=E10,"Ciclo completo","CICLO INCOMPLETO — i rischi mancanti non sono valutazioni") -> Ciclo completo
A12: ID | B12: Nome | C12: Severity | D12: Velocity | E12: Prossimita' | F12: Gap_Controlli | G12: Score corrente | H12: Score precedente | I12: Score 2 cicli fa | J12: Confidence | K12: Segnali netti 4 sett. | L12: Badge
A13: =IF(Parametri!$H4="","",Parametri!$H4) -> NFR-01 | B13: =IF($A13="","",Parametri!$I4) -> Frodi su pagamenti istantanei abilitate da AI generativa | C13: =IF($A13="",NA(),IF(COUNTIFS(RR_ID_Rischio,$A13,RR_Ciclo,cicloCorrente)=0,NA(),SUMIFS(RR_Severity,RR_ID_Rischio,$A13,RR_Ciclo,cicloCorrente))) -> 4 | D13: =IF($A13="",NA(),IF(COUNTIFS(RR_ID_Rischio,$A13,RR_Ciclo,cicloCorrente)=0,NA(),SUMIFS(RR_Velocity,RR_ID_Rischio,$A13,RR_Ciclo,cicloCorrente))) -> 4 | E13: =IF($A13="",NA(),IF(COUNTIFS(RR_ID_Rischio,$A13,RR_Ciclo,cicloCorrente)=0,NA(),SUMIFS(RR_Prossimita,RR_ID_Rischio,$A13,RR_Ciclo,cicloCorrente))) -> 4 | F13: =IF($A13="",NA(),IF(COUNTIFS(RR_ID_Rischio,$A13,RR_Ciclo,cicloCorrente)=0,NA(),SUMIFS(RR_Gap_Controlli,RR_ID_Rischio,$A13,RR_Ciclo,cicloCorrente))) -> 3 | G13: =IF($A13="",NA(),IF(COUNTIFS(RR_ID_Rischio,$A13,RR_Ciclo,cicloCorrente)=0,NA(),SUMIFS(RR_Score_Composito,RR_ID_Rischio,$A13,RR_Ciclo,cicloCorrente))) -> 3.8 | H13: =IF($A13="",NA(),IF(COUNTIFS(RR_ID_Rischio,$A13,RR_Ciclo,cicloPrecedente)=0,NA(),SUMIFS(RR_Score_Composito,RR_ID_Rischio,$A13,RR_Ciclo,cicloPrecedente))) -> #N/A | I13: =IF($A13="",NA(),IF(COUNTIFS(RR_ID_Rischio,$A13,RR_Ciclo,cicloMeno2)=0,NA(),SUMIFS(RR_Score_Composito,RR_ID_Rischio,$A13,RR_Ciclo,cicloMeno2))) -> #N/A | J13: =IF($A13="",NA(),IF(COUNTIFS(RR_ID_Rischio,$A13,RR_Ciclo,cicloCorrente)=0,NA(),SUMIFS(RR_Confidence,RR_ID_Rischio,$A13,RR_Ciclo,cicloCorrente))) -> 4 | K13: =IF($A13="","",COUNTIFS(NW_Rischio_ID,$A13,NW_Segnale,"Peggiorativo",NW_Settimana,">="&inizioFinestra4,NW_Settimana,"<="&settimanaCorrente)-COUNTIFS(NW_Rischio_ID,$A13,NW_Segnale,"Migliorativo",NW_Settimana,">="&inizioFinestra4,NW_Settimana,"<="&settimanaCorrente)) -> 0 | L13: =IF($A13="","",IF(K13>=sogliaDirezione,"▲ In peggioramento",IF(K13<=-sogliaDirezione,"▼ In miglioramento","● Stabile"))) -> ● Stabile
A14: =IF(Parametri!$H5="","",Parametri!$H5) -> NFR-02 | B14: =IF($A14="","",Parametri!$I5) -> Concentrazione su un fornitore cloud critico | C14: =IF($A14="",NA(),IF(COUNTIFS(RR_ID_Rischio,$A14,RR_Ciclo,cicloCorrente)=0,NA(),SUMIFS(RR_Severity,RR_ID_Rischio,$A14,RR_Ciclo,cicloCorrente))) -> 4 | D14: =IF($A14="",NA(),IF(COUNTIFS(RR_ID_Rischio,$A14,RR_Ciclo,cicloCorrente)=0,NA(),SUMIFS(RR_Velocity,RR_ID_Rischio,$A14,RR_Ciclo,cicloCorrente))) -> 4 | E14: =IF($A14="",NA(),IF(COUNTIFS(RR_ID_Rischio,$A14,RR_Ciclo,cicloCorrente)=0,NA(),SUMIFS(RR_Prossimita,RR_ID_Rischio,$A14,RR_Ciclo,cicloCorrente))) -> 3 | F14: =IF($A14="",NA(),IF(COUNTIFS(RR_ID_Rischio,$A14,RR_Ciclo,cicloCorrente)=0,NA(),SUMIFS(RR_Gap_Controlli,RR_ID_Rischio,$A14,RR_Ciclo,cicloCorrente))) -> 3 | G14: =IF($A14="",NA(),IF(COUNTIFS(RR_ID_Rischio,$A14,RR_Ciclo,cicloCorrente)=0,NA(),SUMIFS(RR_Score_Composito,RR_ID_Rischio,$A14,RR_Ciclo,cicloCorrente))) -> 3.6 | H14: =IF($A14="",NA(),IF(COUNTIFS(RR_ID_Rischio,$A14,RR_Ciclo,cicloPrecedente)=0,NA(),SUMIFS(RR_Score_Composito,RR_ID_Rischio,$A14,RR_Ciclo,cicloPrecedente))) -> #N/A | I14: =IF($A14="",NA(),IF(COUNTIFS(RR_ID_Rischio,$A14,RR_Ciclo,cicloMeno2)=0,NA(),SUMIFS(RR_Score_Composito,RR_ID_Rischio,$A14,RR_Ciclo,cicloMeno2))) -> #N/A | J14: =IF($A14="",NA(),IF(COUNTIFS(RR_ID_Rischio,$A14,RR_Ciclo,cicloCorrente)=0,NA(),SUMIFS(RR_Confidence,RR_ID_Rischio,$A14,RR_Ciclo,cicloCorrente))) -> 4 | K14: =IF($A14="","",COUNTIFS(NW_Rischio_ID,$A14,NW_Segnale,"Peggiorativo",NW_Settimana,">="&inizioFinestra4,NW_Settimana,"<="&settimanaCorrente)-COUNTIFS(NW_Rischio_ID,$A14,NW_Segnale,"Migliorativo",NW_Settimana,">="&inizioFinestra4,NW_Settimana,"<="&settimanaCorrente)) -> 0 | L14: =IF($A14="","",IF(K14>=sogliaDirezione,"▲ In peggioramento",IF(K14<=-sogliaDirezione,"▼ In miglioramento","● Stabile"))) -> ● Stabile
A15: =IF(Parametri!$H6="","",Parametri!$H6) -> NFR-03 | B15: =IF($A15="","",Parametri!$I6) -> Greenwashing nella commercializzazione di prodotti ESG | C15: =IF($A15="",NA(),IF(COUNTIFS(RR_ID_Rischio,$A15,RR_Ciclo,cicloCorrente)=0,NA(),SUMIFS(RR_Severity,RR_ID_Rischio,$A15,RR_Ciclo,cicloCorrente))) -> 3 | D15: =IF($A15="",NA(),IF(COUNTIFS(RR_ID_Rischio,$A15,RR_Ciclo,cicloCorrente)=0,NA(),SUMIFS(RR_Velocity,RR_ID_Rischio,$A15,RR_Ciclo,cicloCorrente))) -> 2 | E15: =IF($A15="",NA(),IF(COUNTIFS(RR_ID_Rischio,$A15,RR_Ciclo,cicloCorrente)=0,NA(),SUMIFS(RR_Prossimita,RR_ID_Rischio,$A15,RR_Ciclo,cicloCorrente))) -> 4 | F15: =IF($A15="",NA(),IF(COUNTIFS(RR_ID_Rischio,$A15,RR_Ciclo,cicloCorrente)=0,NA(),SUMIFS(RR_Gap_Controlli,RR_ID_Rischio,$A15,RR_Ciclo,cicloCorrente))) -> 3 | G15: =IF($A15="",NA(),IF(COUNTIFS(RR_ID_Rischio,$A15,RR_Ciclo,cicloCorrente)=0,NA(),SUMIFS(RR_Score_Composito,RR_ID_Rischio,$A15,RR_Ciclo,cicloCorrente))) -> 3 | H15: =IF($A15="",NA(),IF(COUNTIFS(RR_ID_Rischio,$A15,RR_Ciclo,cicloPrecedente)=0,NA(),SUMIFS(RR_Score_Composito,RR_ID_Rischio,$A15,RR_Ciclo,cicloPrecedente))) -> #N/A | I15: =IF($A15="",NA(),IF(COUNTIFS(RR_ID_Rischio,$A15,RR_Ciclo,cicloMeno2)=0,NA(),SUMIFS(RR_Score_Composito,RR_ID_Rischio,$A15,RR_Ciclo,cicloMeno2))) -> #N/A | J15: =IF($A15="",NA(),IF(COUNTIFS(RR_ID_Rischio,$A15,RR_Ciclo,cicloCorrente)=0,NA(),SUMIFS(RR_Confidence,RR_ID_Rischio,$A15,RR_Ciclo,cicloCorrente))) -> 3 | K15: =IF($A15="","",COUNTIFS(NW_Rischio_ID,$A15,NW_Segnale,"Peggiorativo",NW_Settimana,">="&inizioFinestra4,NW_Settimana,"<="&settimanaCorrente)-COUNTIFS(NW_Rischio_ID,$A15,NW_Segnale,"Migliorativo",NW_Settimana,">="&inizioFinestra4,NW_Settimana,"<="&settimanaCorrente)) -> 0 | L15: =IF($A15="","",IF(K15>=sogliaDirezione,"▲ In peggioramento",IF(K15<=-sogliaDirezione,"▼ In miglioramento","● Stabile"))) -> ● Stabile
A16: =IF(Parametri!$H7="","",Parametri!$H7) -> NFR-04 | B16: =IF($A16="","",Parametri!$I7) -> Eventi climatici estremi su sedi e data center | C16: =IF($A16="",NA(),IF(COUNTIFS(RR_ID_Rischio,$A16,RR_Ciclo,cicloCorrente)=0,NA(),SUMIFS(RR_Severity,RR_ID_Rischio,$A16,RR_Ciclo,cicloCorrente))) -> 3 | D16: =IF($A16="",NA(),IF(COUNTIFS(RR_ID_Rischio,$A16,RR_Ciclo,cicloCorrente)=0,NA(),SUMIFS(RR_Velocity,RR_ID_Rischio,$A16,RR_Ciclo,cicloCorrente))) -> 2 | E16: =IF($A16="",NA(),IF(COUNTIFS(RR_ID_Rischio,$A16,RR_Ciclo,cicloCorrente)=0,NA(),SUMIFS(RR_Prossimita,RR_ID_Rischio,$A16,RR_Ciclo,cicloCorrente))) -> 3 | F16: =IF($A16="",NA(),IF(COUNTIFS(RR_ID_Rischio,$A16,RR_Ciclo,cicloCorrente)=0,NA(),SUMIFS(RR_Gap_Controlli,RR_ID_Rischio,$A16,RR_Ciclo,cicloCorrente))) -> 3 | G16: =IF($A16="",NA(),IF(COUNTIFS(RR_ID_Rischio,$A16,RR_Ciclo,cicloCorrente)=0,NA(),SUMIFS(RR_Score_Composito,RR_ID_Rischio,$A16,RR_Ciclo,cicloCorrente))) -> 2.8 | H16: =IF($A16="",NA(),IF(COUNTIFS(RR_ID_Rischio,$A16,RR_Ciclo,cicloPrecedente)=0,NA(),SUMIFS(RR_Score_Composito,RR_ID_Rischio,$A16,RR_Ciclo,cicloPrecedente))) -> #N/A | I16: =IF($A16="",NA(),IF(COUNTIFS(RR_ID_Rischio,$A16,RR_Ciclo,cicloMeno2)=0,NA(),SUMIFS(RR_Score_Composito,RR_ID_Rischio,$A16,RR_Ciclo,cicloMeno2))) -> #N/A | J16: =IF($A16="",NA(),IF(COUNTIFS(RR_ID_Rischio,$A16,RR_Ciclo,cicloCorrente)=0,NA(),SUMIFS(RR_Confidence,RR_ID_Rischio,$A16,RR_Ciclo,cicloCorrente))) -> 3 | K16: =IF($A16="","",COUNTIFS(NW_Rischio_ID,$A16,NW_Segnale,"Peggiorativo",NW_Settimana,">="&inizioFinestra4,NW_Settimana,"<="&settimanaCorrente)-COUNTIFS(NW_Rischio_ID,$A16,NW_Segnale,"Migliorativo",NW_Settimana,">="&inizioFinestra4,NW_Settimana,"<="&settimanaCorrente)) -> 0 | L16: =IF($A16="","",IF(K16>=sogliaDirezione,"▲ In peggioramento",IF(K16<=-sogliaDirezione,"▼ In miglioramento","● Stabile"))) -> ● Stabile
A17: =IF(Parametri!$H8="","",Parametri!$H8) -> NFR-05 | B17: =IF($A17="","",Parametri!$I8) -> Errori di processo nella migrazione del core banking | C17: =IF($A17="",NA(),IF(COUNTIFS(RR_ID_Rischio,$A17,RR_Ciclo,cicloCorrente)=0,NA(),SUMIFS(RR_Severity,RR_ID_Rischio,$A17,RR_Ciclo,cicloCorrente))) -> 3 | D17: =IF($A17="",NA(),IF(COUNTIFS(RR_ID_Rischio,$A17,RR_Ciclo,cicloCorrente)=0,NA(),SUMIFS(RR_Velocity,RR_ID_Rischio,$A17,RR_Ciclo,cicloCorrente))) -> 3 | E17: =IF($A17="",NA(),IF(COUNTIFS(RR_ID_Rischio,$A17,RR_Ciclo,cicloCorrente)=0,NA(),SUMIFS(RR_Prossimita,RR_ID_Rischio,$A17,RR_Ciclo,cicloCorrente))) -> 3 | F17: =IF($A17="",NA(),IF(COUNTIFS(RR_ID_Rischio,$A17,RR_Ciclo,cicloCorrente)=0,NA(),SUMIFS(RR_Gap_Controlli,RR_ID_Rischio,$A17,RR_Ciclo,cicloCorrente))) -> 3 | G17: =IF($A17="",NA(),IF(COUNTIFS(RR_ID_Rischio,$A17,RR_Ciclo,cicloCorrente)=0,NA(),SUMIFS(RR_Score_Composito,RR_ID_Rischio,$A17,RR_Ciclo,cicloCorrente))) -> 3 | H17: =IF($A17="",NA(),IF(COUNTIFS(RR_ID_Rischio,$A17,RR_Ciclo,cicloPrecedente)=0,NA(),SUMIFS(RR_Score_Composito,RR_ID_Rischio,$A17,RR_Ciclo,cicloPrecedente))) -> #N/A | I17: =IF($A17="",NA(),IF(COUNTIFS(RR_ID_Rischio,$A17,RR_Ciclo,cicloMeno2)=0,NA(),SUMIFS(RR_Score_Composito,RR_ID_Rischio,$A17,RR_Ciclo,cicloMeno2))) -> #N/A | J17: =IF($A17="",NA(),IF(COUNTIFS(RR_ID_Rischio,$A17,RR_Ciclo,cicloCorrente)=0,NA(),SUMIFS(RR_Confidence,RR_ID_Rischio,$A17,RR_Ciclo,cicloCorrente))) -> 4 | K17: =IF($A17="","",COUNTIFS(NW_Rischio_ID,$A17,NW_Segnale,"Peggiorativo",NW_Settimana,">="&inizioFinestra4,NW_Settimana,"<="&settimanaCorrente)-COUNTIFS(NW_Rischio_ID,$A17,NW_Segnale,"Migliorativo",NW_Settimana,">="&inizioFinestra4,NW_Settimana,"<="&settimanaCorrente)) -> 0 | L17: =IF($A17="","",IF(K17>=sogliaDirezione,"▲ In peggioramento",IF(K17<=-sogliaDirezione,"▼ In miglioramento","● Stabile"))) -> ● Stabile
A18: =IF(Parametri!$H9="","",Parametri!$H9) -> NFR-06 | B18: =IF($A18="","",Parametri!$I9) -> Esfiltrazione di dati tramite strumenti di AI non autorizzati | C18: =IF($A18="",NA(),IF(COUNTIFS(RR_ID_Rischio,$A18,RR_Ciclo,cicloCorrente)=0,NA(),SUMIFS(RR_Severity,RR_ID_Rischio,$A18,RR_Ciclo,cicloCorrente))) -> 3 | D18: =IF($A18="",NA(),IF(COUNTIFS(RR_ID_Rischio,$A18,RR_Ciclo,cicloCorrente)=0,NA(),SUMIFS(RR_Velocity,RR_ID_Rischio,$A18,RR_Ciclo,cicloCorrente))) -> 3 | E18: =IF($A18="",NA(),IF(COUNTIFS(RR_ID_Rischio,$A18,RR_Ciclo,cicloCorrente)=0,NA(),SUMIFS(RR_Prossimita,RR_ID_Rischio,$A18,RR_Ciclo,cicloCorrente))) -> 3 | F18: =IF($A18="",NA(),IF(COUNTIFS(RR_ID_Rischio,$A18,RR_Ciclo,cicloCorrente)=0,NA(),SUMIFS(RR_Gap_Controlli,RR_ID_Rischio,$A18,RR_Ciclo,cicloCorrente))) -> 3 | G18: =IF($A18="",NA(),IF(COUNTIFS(RR_ID_Rischio,$A18,RR_Ciclo,cicloCorrente)=0,NA(),SUMIFS(RR_Score_Composito,RR_ID_Rischio,$A18,RR_Ciclo,cicloCorrente))) -> 3 | H18: =IF($A18="",NA(),IF(COUNTIFS(RR_ID_Rischio,$A18,RR_Ciclo,cicloPrecedente)=0,NA(),SUMIFS(RR_Score_Composito,RR_ID_Rischio,$A18,RR_Ciclo,cicloPrecedente))) -> #N/A | I18: =IF($A18="",NA(),IF(COUNTIFS(RR_ID_Rischio,$A18,RR_Ciclo,cicloMeno2)=0,NA(),SUMIFS(RR_Score_Composito,RR_ID_Rischio,$A18,RR_Ciclo,cicloMeno2))) -> #N/A | J18: =IF($A18="",NA(),IF(COUNTIFS(RR_ID_Rischio,$A18,RR_Ciclo,cicloCorrente)=0,NA(),SUMIFS(RR_Confidence,RR_ID_Rischio,$A18,RR_Ciclo,cicloCorrente))) -> 3 | K18: =IF($A18="","",COUNTIFS(NW_Rischio_ID,$A18,NW_Segnale,"Peggiorativo",NW_Settimana,">="&inizioFinestra4,NW_Settimana,"<="&settimanaCorrente)-COUNTIFS(NW_Rischio_ID,$A18,NW_Segnale,"Migliorativo",NW_Settimana,">="&inizioFinestra4,NW_Settimana,"<="&settimanaCorrente)) -> 0 | L18: =IF($A18="","",IF(K18>=sogliaDirezione,"▲ In peggioramento",IF(K18<=-sogliaDirezione,"▼ In miglioramento","● Stabile"))) -> ● Stabile
A19: =IF(Parametri!$H10="","",Parametri!$H10) -> NFR-07 | B19: =IF($A19="","",Parametri!$I10) -> Ransomware presso un fornitore di servizi di pagamento | C19: =IF($A19="",NA(),IF(COUNTIFS(RR_ID_Rischio,$A19,RR_Ciclo,cicloCorrente)=0,NA(),SUMIFS(RR_Severity,RR_ID_Rischio,$A19,RR_Ciclo,cicloCorrente))) -> 4 | D19: =IF($A19="",NA(),IF(COUNTIFS(RR_ID_Rischio,$A19,RR_Ciclo,cicloCorrente)=0,NA(),SUMIFS(RR_Velocity,RR_ID_Rischio,$A19,RR_Ciclo,cicloCorrente))) -> 5 | E19: =IF($A19="",NA(),IF(COUNTIFS(RR_ID_Rischio,$A19,RR_Ciclo,cicloCorrente)=0,NA(),SUMIFS(RR_Prossimita,RR_ID_Rischio,$A19,RR_Ciclo,cicloCorrente))) -> 3 | F19: =IF($A19="",NA(),IF(COUNTIFS(RR_ID_Rischio,$A19,RR_Ciclo,cicloCorrente)=0,NA(),SUMIFS(RR_Gap_Controlli,RR_ID_Rischio,$A19,RR_Ciclo,cicloCorrente))) -> 3 | G19: =IF($A19="",NA(),IF(COUNTIFS(RR_ID_Rischio,$A19,RR_Ciclo,cicloCorrente)=0,NA(),SUMIFS(RR_Score_Composito,RR_ID_Rischio,$A19,RR_Ciclo,cicloCorrente))) -> 3.8 | H19: =IF($A19="",NA(),IF(COUNTIFS(RR_ID_Rischio,$A19,RR_Ciclo,cicloPrecedente)=0,NA(),SUMIFS(RR_Score_Composito,RR_ID_Rischio,$A19,RR_Ciclo,cicloPrecedente))) -> #N/A | I19: =IF($A19="",NA(),IF(COUNTIFS(RR_ID_Rischio,$A19,RR_Ciclo,cicloMeno2)=0,NA(),SUMIFS(RR_Score_Composito,RR_ID_Rischio,$A19,RR_Ciclo,cicloMeno2))) -> #N/A | J19: =IF($A19="",NA(),IF(COUNTIFS(RR_ID_Rischio,$A19,RR_Ciclo,cicloCorrente)=0,NA(),SUMIFS(RR_Confidence,RR_ID_Rischio,$A19,RR_Ciclo,cicloCorrente))) -> 3 | K19: =IF($A19="","",COUNTIFS(NW_Rischio_ID,$A19,NW_Segnale,"Peggiorativo",NW_Settimana,">="&inizioFinestra4,NW_Settimana,"<="&settimanaCorrente)-COUNTIFS(NW_Rischio_ID,$A19,NW_Segnale,"Migliorativo",NW_Settimana,">="&inizioFinestra4,NW_Settimana,"<="&settimanaCorrente)) -> 0 | L19: =IF($A19="","",IF(K19>=sogliaDirezione,"▲ In peggioramento",IF(K19<=-sogliaDirezione,"▼ In miglioramento","● Stabile"))) -> ● Stabile
A20: =IF(Parametri!$H11="","",Parametri!$H11) -> NFR-08 | B20: =IF($A20="","",Parametri!$I11) -> Accessi impropri di dipendenti ai dati dei clienti | C20: =IF($A20="",NA(),IF(COUNTIFS(RR_ID_Rischio,$A20,RR_Ciclo,cicloCorrente)=0,NA(),SUMIFS(RR_Severity,RR_ID_Rischio,$A20,RR_Ciclo,cicloCorrente))) -> 3 | D20: =IF($A20="",NA(),IF(COUNTIFS(RR_ID_Rischio,$A20,RR_Ciclo,cicloCorrente)=0,NA(),SUMIFS(RR_Velocity,RR_ID_Rischio,$A20,RR_Ciclo,cicloCorrente))) -> 3 | E20: =IF($A20="",NA(),IF(COUNTIFS(RR_ID_Rischio,$A20,RR_Ciclo,cicloCorrente)=0,NA(),SUMIFS(RR_Prossimita,RR_ID_Rischio,$A20,RR_Ciclo,cicloCorrente))) -> 3 | F20: =IF($A20="",NA(),IF(COUNTIFS(RR_ID_Rischio,$A20,RR_Ciclo,cicloCorrente)=0,NA(),SUMIFS(RR_Gap_Controlli,RR_ID_Rischio,$A20,RR_Ciclo,cicloCorrente))) -> 3 | G20: =IF($A20="",NA(),IF(COUNTIFS(RR_ID_Rischio,$A20,RR_Ciclo,cicloCorrente)=0,NA(),SUMIFS(RR_Score_Composito,RR_ID_Rischio,$A20,RR_Ciclo,cicloCorrente))) -> 3 | H20: =IF($A20="",NA(),IF(COUNTIFS(RR_ID_Rischio,$A20,RR_Ciclo,cicloPrecedente)=0,NA(),SUMIFS(RR_Score_Composito,RR_ID_Rischio,$A20,RR_Ciclo,cicloPrecedente))) -> #N/A | I20: =IF($A20="",NA(),IF(COUNTIFS(RR_ID_Rischio,$A20,RR_Ciclo,cicloMeno2)=0,NA(),SUMIFS(RR_Score_Composito,RR_ID_Rischio,$A20,RR_Ciclo,cicloMeno2))) -> #N/A | J20: =IF($A20="",NA(),IF(COUNTIFS(RR_ID_Rischio,$A20,RR_Ciclo,cicloCorrente)=0,NA(),SUMIFS(RR_Confidence,RR_ID_Rischio,$A20,RR_Ciclo,cicloCorrente))) -> 3 | K20: =IF($A20="","",COUNTIFS(NW_Rischio_ID,$A20,NW_Segnale,"Peggiorativo",NW_Settimana,">="&inizioFinestra4,NW_Settimana,"<="&settimanaCorrente)-COUNTIFS(NW_Rischio_ID,$A20,NW_Segnale,"Migliorativo",NW_Settimana,">="&inizioFinestra4,NW_Settimana,"<="&settimanaCorrente)) -> 0 | L20: =IF($A20="","",IF(K20>=sogliaDirezione,"▲ In peggioramento",IF(K20<=-sogliaDirezione,"▼ In miglioramento","● Stabile"))) -> ● Stabile
A21: =IF(Parametri!$H12="","",Parametri!$H12) -> NFR-09 | B21: =IF($A21="","",Parametri!$I12) -> Violazione di sanzioni internazionali tramite triangolazioni | C21: =IF($A21="",NA(),IF(COUNTIFS(RR_ID_Rischio,$A21,RR_Ciclo,cicloCorrente)=0,NA(),SUMIFS(RR_Severity,RR_ID_Rischio,$A21,RR_Ciclo,cicloCorrente))) -> 4 | D21: =IF($A21="",NA(),IF(COUNTIFS(RR_ID_Rischio,$A21,RR_Ciclo,cicloCorrente)=0,NA(),SUMIFS(RR_Velocity,RR_ID_Rischio,$A21,RR_Ciclo,cicloCorrente))) -> 3 | E21: =IF($A21="",NA(),IF(COUNTIFS(RR_ID_Rischio,$A21,RR_Ciclo,cicloCorrente)=0,NA(),SUMIFS(RR_Prossimita,RR_ID_Rischio,$A21,RR_Ciclo,cicloCorrente))) -> 2 | F21: =IF($A21="",NA(),IF(COUNTIFS(RR_ID_Rischio,$A21,RR_Ciclo,cicloCorrente)=0,NA(),SUMIFS(RR_Gap_Controlli,RR_ID_Rischio,$A21,RR_Ciclo,cicloCorrente))) -> 3 | G21: =IF($A21="",NA(),IF(COUNTIFS(RR_ID_Rischio,$A21,RR_Ciclo,cicloCorrente)=0,NA(),SUMIFS(RR_Score_Composito,RR_ID_Rischio,$A21,RR_Ciclo,cicloCorrente))) -> 3.2 | H21: =IF($A21="",NA(),IF(COUNTIFS(RR_ID_Rischio,$A21,RR_Ciclo,cicloPrecedente)=0,NA(),SUMIFS(RR_Score_Composito,RR_ID_Rischio,$A21,RR_Ciclo,cicloPrecedente))) -> #N/A | I21: =IF($A21="",NA(),IF(COUNTIFS(RR_ID_Rischio,$A21,RR_Ciclo,cicloMeno2)=0,NA(),SUMIFS(RR_Score_Composito,RR_ID_Rischio,$A21,RR_Ciclo,cicloMeno2))) -> #N/A | J21: =IF($A21="",NA(),IF(COUNTIFS(RR_ID_Rischio,$A21,RR_Ciclo,cicloCorrente)=0,NA(),SUMIFS(RR_Confidence,RR_ID_Rischio,$A21,RR_Ciclo,cicloCorrente))) -> 2 | K21: =IF($A21="","",COUNTIFS(NW_Rischio_ID,$A21,NW_Segnale,"Peggiorativo",NW_Settimana,">="&inizioFinestra4,NW_Settimana,"<="&settimanaCorrente)-COUNTIFS(NW_Rischio_ID,$A21,NW_Segnale,"Migliorativo",NW_Settimana,">="&inizioFinestra4,NW_Settimana,"<="&settimanaCorrente)) -> 0 | L21: =IF($A21="","",IF(K21>=sogliaDirezione,"▲ In peggioramento",IF(K21<=-sogliaDirezione,"▼ In miglioramento","● Stabile"))) -> ● Stabile
A22: =IF(Parametri!$H13="","",Parametri!$H13) -> NFR-10 | B22: =IF($A22="","",Parametri!$I13) -> Informazioni errate ai clienti da assistenti di AI generativa | C22: =IF($A22="",NA(),IF(COUNTIFS(RR_ID_Rischio,$A22,RR_Ciclo,cicloCorrente)=0,NA(),SUMIFS(RR_Severity,RR_ID_Rischio,$A22,RR_Ciclo,cicloCorrente))) -> 3 | D22: =IF($A22="",NA(),IF(COUNTIFS(RR_ID_Rischio,$A22,RR_Ciclo,cicloCorrente)=0,NA(),SUMIFS(RR_Velocity,RR_ID_Rischio,$A22,RR_Ciclo,cicloCorrente))) -> 3 | E22: =IF($A22="",NA(),IF(COUNTIFS(RR_ID_Rischio,$A22,RR_Ciclo,cicloCorrente)=0,NA(),SUMIFS(RR_Prossimita,RR_ID_Rischio,$A22,RR_Ciclo,cicloCorrente))) -> 3 | F22: =IF($A22="",NA(),IF(COUNTIFS(RR_ID_Rischio,$A22,RR_Ciclo,cicloCorrente)=0,NA(),SUMIFS(RR_Gap_Controlli,RR_ID_Rischio,$A22,RR_Ciclo,cicloCorrente))) -> 4 | G22: =IF($A22="",NA(),IF(COUNTIFS(RR_ID_Rischio,$A22,RR_Ciclo,cicloCorrente)=0,NA(),SUMIFS(RR_Score_Composito,RR_ID_Rischio,$A22,RR_Ciclo,cicloCorrente))) -> 3.2 | H22: =IF($A22="",NA(),IF(COUNTIFS(RR_ID_Rischio,$A22,RR_Ciclo,cicloPrecedente)=0,NA(),SUMIFS(RR_Score_Composito,RR_ID_Rischio,$A22,RR_Ciclo,cicloPrecedente))) -> #N/A | I22: =IF($A22="",NA(),IF(COUNTIFS(RR_ID_Rischio,$A22,RR_Ciclo,cicloMeno2)=0,NA(),SUMIFS(RR_Score_Composito,RR_ID_Rischio,$A22,RR_Ciclo,cicloMeno2))) -> #N/A | J22: =IF($A22="",NA(),IF(COUNTIFS(RR_ID_Rischio,$A22,RR_Ciclo,cicloCorrente)=0,NA(),SUMIFS(RR_Confidence,RR_ID_Rischio,$A22,RR_Ciclo,cicloCorrente))) -> 2 | K22: =IF($A22="","",COUNTIFS(NW_Rischio_ID,$A22,NW_Segnale,"Peggiorativo",NW_Settimana,">="&inizioFinestra4,NW_Settimana,"<="&settimanaCorrente)-COUNTIFS(NW_Rischio_ID,$A22,NW_Segnale,"Migliorativo",NW_Settimana,">="&inizioFinestra4,NW_Settimana,"<="&settimanaCorrente)) -> 0 | L22: =IF($A22="","",IF(K22>=sogliaDirezione,"▲ In peggioramento",IF(K22<=-sogliaDirezione,"▼ In miglioramento","● Stabile"))) -> ● Stabile
A23: =IF(Parametri!$H14="","",Parametri!$H14) -> NFR-11 | B23: =IF($A23="","",Parametri!$I14) -> Fine del supporto dei sistemi di pagamento legacy | C23: =IF($A23="",NA(),IF(COUNTIFS(RR_ID_Rischio,$A23,RR_Ciclo,cicloCorrente)=0,NA(),SUMIFS(RR_Severity,RR_ID_Rischio,$A23,RR_Ciclo,cicloCorrente))) -> 3 | D23: =IF($A23="",NA(),IF(COUNTIFS(RR_ID_Rischio,$A23,RR_Ciclo,cicloCorrente)=0,NA(),SUMIFS(RR_Velocity,RR_ID_Rischio,$A23,RR_Ciclo,cicloCorrente))) -> 2 | E23: =IF($A23="",NA(),IF(COUNTIFS(RR_ID_Rischio,$A23,RR_Ciclo,cicloCorrente)=0,NA(),SUMIFS(RR_Prossimita,RR_ID_Rischio,$A23,RR_Ciclo,cicloCorrente))) -> 3 | F23: =IF($A23="",NA(),IF(COUNTIFS(RR_ID_Rischio,$A23,RR_Ciclo,cicloCorrente)=0,NA(),SUMIFS(RR_Gap_Controlli,RR_ID_Rischio,$A23,RR_Ciclo,cicloCorrente))) -> 4 | G23: =IF($A23="",NA(),IF(COUNTIFS(RR_ID_Rischio,$A23,RR_Ciclo,cicloCorrente)=0,NA(),SUMIFS(RR_Score_Composito,RR_ID_Rischio,$A23,RR_Ciclo,cicloCorrente))) -> 3 | H23: =IF($A23="",NA(),IF(COUNTIFS(RR_ID_Rischio,$A23,RR_Ciclo,cicloPrecedente)=0,NA(),SUMIFS(RR_Score_Composito,RR_ID_Rischio,$A23,RR_Ciclo,cicloPrecedente))) -> #N/A | I23: =IF($A23="",NA(),IF(COUNTIFS(RR_ID_Rischio,$A23,RR_Ciclo,cicloMeno2)=0,NA(),SUMIFS(RR_Score_Composito,RR_ID_Rischio,$A23,RR_Ciclo,cicloMeno2))) -> #N/A | J23: =IF($A23="",NA(),IF(COUNTIFS(RR_ID_Rischio,$A23,RR_Ciclo,cicloCorrente)=0,NA(),SUMIFS(RR_Confidence,RR_ID_Rischio,$A23,RR_Ciclo,cicloCorrente))) -> 3 | K23: =IF($A23="","",COUNTIFS(NW_Rischio_ID,$A23,NW_Segnale,"Peggiorativo",NW_Settimana,">="&inizioFinestra4,NW_Settimana,"<="&settimanaCorrente)-COUNTIFS(NW_Rischio_ID,$A23,NW_Segnale,"Migliorativo",NW_Settimana,">="&inizioFinestra4,NW_Settimana,"<="&settimanaCorrente)) -> 0 | L23: =IF($A23="","",IF(K23>=sogliaDirezione,"▲ In peggioramento",IF(K23<=-sogliaDirezione,"▼ In miglioramento","● Stabile"))) -> ● Stabile
A24: =IF(Parametri!$H15="","",Parametri!$H15) -> NFR-12 | B24: =IF($A24="","",Parametri!$I15) -> Errori operativi nei pagamenti istantanei obbligatori | C24: =IF($A24="",NA(),IF(COUNTIFS(RR_ID_Rischio,$A24,RR_Ciclo,cicloCorrente)=0,NA(),SUMIFS(RR_Severity,RR_ID_Rischio,$A24,RR_Ciclo,cicloCorrente))) -> 3 | D24: =IF($A24="",NA(),IF(COUNTIFS(RR_ID_Rischio,$A24,RR_Ciclo,cicloCorrente)=0,NA(),SUMIFS(RR_Velocity,RR_ID_Rischio,$A24,RR_Ciclo,cicloCorrente))) -> 4 | E24: =IF($A24="",NA(),IF(COUNTIFS(RR_ID_Rischio,$A24,RR_Ciclo,cicloCorrente)=0,NA(),SUMIFS(RR_Prossimita,RR_ID_Rischio,$A24,RR_Ciclo,cicloCorrente))) -> 4 | F24: =IF($A24="",NA(),IF(COUNTIFS(RR_ID_Rischio,$A24,RR_Ciclo,cicloCorrente)=0,NA(),SUMIFS(RR_Gap_Controlli,RR_ID_Rischio,$A24,RR_Ciclo,cicloCorrente))) -> 3 | G24: =IF($A24="",NA(),IF(COUNTIFS(RR_ID_Rischio,$A24,RR_Ciclo,cicloCorrente)=0,NA(),SUMIFS(RR_Score_Composito,RR_ID_Rischio,$A24,RR_Ciclo,cicloCorrente))) -> 3.4 | H24: =IF($A24="",NA(),IF(COUNTIFS(RR_ID_Rischio,$A24,RR_Ciclo,cicloPrecedente)=0,NA(),SUMIFS(RR_Score_Composito,RR_ID_Rischio,$A24,RR_Ciclo,cicloPrecedente))) -> #N/A | I24: =IF($A24="",NA(),IF(COUNTIFS(RR_ID_Rischio,$A24,RR_Ciclo,cicloMeno2)=0,NA(),SUMIFS(RR_Score_Composito,RR_ID_Rischio,$A24,RR_Ciclo,cicloMeno2))) -> #N/A | J24: =IF($A24="",NA(),IF(COUNTIFS(RR_ID_Rischio,$A24,RR_Ciclo,cicloCorrente)=0,NA(),SUMIFS(RR_Confidence,RR_ID_Rischio,$A24,RR_Ciclo,cicloCorrente))) -> 3 | K24: =IF($A24="","",COUNTIFS(NW_Rischio_ID,$A24,NW_Segnale,"Peggiorativo",NW_Settimana,">="&inizioFinestra4,NW_Settimana,"<="&settimanaCorrente)-COUNTIFS(NW_Rischio_ID,$A24,NW_Segnale,"Migliorativo",NW_Settimana,">="&inizioFinestra4,NW_Settimana,"<="&settimanaCorrente)) -> 0 | L24: =IF($A24="","",IF(K24>=sogliaDirezione,"▲ In peggioramento",IF(K24<=-sogliaDirezione,"▼ In miglioramento","● Stabile"))) -> ● Stabile
... A27: =IF(Parametri!$H18="","",Parametri!$H18) | B27: =IF($A27="","",Parametri!$I18) | C27: =IF($A27="",NA(),IF(COUNTIFS(RR_ID_Rischio,$A27,RR_Ciclo,cicloCorrente)=0,NA(),SUMIFS(RR_Severity,RR_ID_Rischio,$A27,RR_Ciclo,cicloCorrente))) -> #N/A | D27: =IF($A27="",NA(),IF(COUNTIFS(RR_ID_Rischio,$A27,RR_Ciclo,cicloCorrente)=0,NA(),SUMIFS(RR_Velocity,RR_ID_Rischio,$A27,RR_Ciclo,cicloCorrente))) -> #N/A | E27: =IF($A27="",NA(),IF(COUNTIFS(RR_ID_Rischio,$A27,RR_Ciclo,cicloCorrente)=0,NA(),SUMIFS(RR_Prossimita,RR_ID_Rischio,$A27,RR_Ciclo,cicloCorrente))) -> #N/A | F27: =IF($A27="",NA(),IF(COUNTIFS(RR_ID_Rischio,$A27,RR_Ciclo,cicloCorrente)=0,NA(),SUMIFS(RR_Gap_Controlli,RR_ID_Rischio,$A27,RR_Ciclo,cicloCorrente))) -> #N/A | G27: =IF($A27="",NA(),IF(COUNTIFS(RR_ID_Rischio,$A27,RR_Ciclo,cicloCorrente)=0,NA(),SUMIFS(RR_Score_Composito,RR_ID_Rischio,$A27,RR_Ciclo,cicloCorrente))) -> #N/A | H27: =IF($A27="",NA(),IF(COUNTIFS(RR_ID_Rischio,$A27,RR_Ciclo,cicloPrecedente)=0,NA(),SUMIFS(RR_Score_Composito,RR_ID_Rischio,$A27,RR_Ciclo,cicloPrecedente))) -> #N/A | I27: =IF($A27="",NA(),IF(COUNTIFS(RR_ID_Rischio,$A27,RR_Ciclo,cicloMeno2)=0,NA(),SUMIFS(RR_Score_Composito,RR_ID_Rischio,$A27,RR_Ciclo,cicloMeno2))) -> #N/A | J27: =IF($A27="",NA(),IF(COUNTIFS(RR_ID_Rischio,$A27,RR_Ciclo,cicloCorrente)=0,NA(),SUMIFS(RR_Confidence,RR_ID_Rischio,$A27,RR_Ciclo,cicloCorrente))) -> #N/A | K27: =IF($A27="","",COUNTIFS(NW_Rischio_ID,$A27,NW_Segnale,"Peggiorativo",NW_Settimana,">="&inizioFinestra4,NW_Settimana,"<="&settimanaCorrente)-COUNTIFS(NW_Rischio_ID,$A27,NW_Segnale,"Migliorativo",NW_Settimana,">="&inizioFinestra4,NW_Settimana,"<="&settimanaCorrente)) | L27: =IF($A27="","",IF(K27>=sogliaDirezione,"▲ In peggioramento",IF(K27<=-sogliaDirezione,"▼ In miglioramento","● Stabile")))

Sheet Radar_Mosca
A1: Radar di Mosca — quanto presto bisogna agire, e quanto e' grande ogni rischio
A2: Piu' vicino al centro = agire prima (dentro il cerchio rosso X + Y > Z: gia' in ritardo). Area del cerchio = Probabilita x Severity. Settore = event type. Tutto calcolato: parametri X, Y di riserva e Z in Parametri (righe 47-55).
U3: Appoggio del grafico: non modificare
A4: ID | B4: Nome | C4: Event type | D4: Impatto (Severity) | E4: Probabilita | F4: P x I | G4: Prossimita | H4: Z anni alla manifestazione | I4: X anni per decidere | J4: Y anni per mitigare | K4: Margine Z-(X+Y) | L4: Urgenza | M4: Settore | N4: Posizione nel settore | O4: Rischi nel settore | P4: Angolo | Q4: Raggio | R4: x | S4: y | V4: Mosca | X4: 1 anno | Z4: 2 anni | AB4: 3 anni | AL4: 1 | AM4: 2 | AN4: 3 | AO4: 4 | AP4: 5 | AQ4: 6 | AR4: 8 | AS4: 9 | AT4: 10 | AU4: 12 | AV4: 15 | AW4: 16 | AX4: 20 | AY4: 25
A5: =IF(Parametri!$H4="","",Parametri!$H4) -> NFR-01 | B5: =IF($A5="","",Parametri!$I4) -> Frodi su pagamenti istantanei abilitate da AI generativa | C5: =IF($A5="","",Parametri!$J4) -> L1-02 | D5: =IF($A5="",NA(),IF(COUNTIFS(RR_ID_Rischio,$A5,RR_Ciclo,cicloCorrente)=0,NA(),SUMIFS(RR_Severity,RR_ID_Rischio,$A5,RR_Ciclo,cicloCorrente))) -> 4 | E5: =IF($A5="",NA(),IF(COUNTIFS(RR_ID_Rischio,$A5,RR_Ciclo,cicloCorrente)=0,NA(),SUMIFS(RR_Probabilita,RR_ID_Rischio,$A5,RR_Ciclo,cicloCorrente))) -> 4 | F5: =IF(AND(ISNUMBER(D5),ISNUMBER(E5)),D5*E5,NA()) -> 16 | G5: =IF($A5="",NA(),IF(COUNTIFS(RR_ID_Rischio,$A5,RR_Ciclo,cicloCorrente)=0,NA(),SUMIFS(RR_Prossimita,RR_ID_Rischio,$A5,RR_Ciclo,cicloCorrente))) -> 4 | H5: =IF(ISNUMBER(G5),INDEX(anniProssimita,G5),NA()) -> 0.5 | I5: =IF($A5="",NA(),moscaX) -> 0.25 | J5: =IF($A5="",NA(),IF(COUNTIFS(AZ_ID_Rischio,$A5,AZ_Ciclo,cicloCorrente,AZ_Stato,"<>Respinta",AZ_Mesi_Orizzonte,">0")=0,moscaYDefault,_xlfn.MAXIFS(AZ_Mesi_Orizzonte,AZ_ID_Rischio,$A5,AZ_Ciclo,cicloCorrente,AZ_Stato,"<>Respinta")/12)) -> 0.5 | K5: =IF(AND(ISNUMBER(H5),ISNUMBER(J5)),H5-(I5+J5),NA()) -> -0.25 | L5: =IF(NOT(ISNUMBER(K5)),"",IF(K5<0,"AGIRE ORA: X+Y > Z",IF(K5<1,"Agire entro l'anno","Margine "&ROUND(K5,1)&IF(ROUND(K5,1)=1," anno"," anni")))) -> AGIRE ORA: X+Y > Z | M5: =IF($A5="",NA(),MATCH(C5,codiciL1,0)-1) -> 1 | N5: =IF($A5="",NA(),COUNTIF($C$4:C4,C5)) -> 0 | O5: =IF($A5="",NA(),COUNTIF(ANA_Event_Type,C5)) -> 1 | P5: =IF($A5="",NA(),2*PI()*(M5+(N5+0.5)/O5)/ROWS(codiciL1)) -> 1.3463969 | Q5: =IF(ISNUMBER(K5),MAX(0.6,MIN(6,K5+2)),NA()) -> 1.75 | R5: =IF(AND(ISNUMBER(Q5),ISNUMBER(P5)),Q5*SIN(P5),NA()) -> 1.7061238 | S5: =IF(AND(ISNUMBER(Q5),ISNUMBER(P5)),Q5*COS(P5),NA()) -> 0.38941163 | U5: =2*PI()*0/72 -> 0 | V5: =2*SIN($U5) -> 0 | W5: =2*COS($U5) -> 2 | X5: =3*SIN($U5) -> 0 | Y5: =3*COS($U5) -> 3 | Z5: =4*SIN($U5) -> 0 | AA5: =4*COS($U5) -> 4 | AB5: =5*SIN($U5) -> 0 | AC5: =5*COS($U5) -> 5 | AE5: 0 | AF5: 0 | AH5: L1-01 | AI5: =6.75*SIN(2*PI()*(0+0.5)/ROWS(codiciL1)) -> 2.9287152 | AJ5: =6.75*COS(2*PI()*(0+0.5)/ROWS(codiciL1)) -> 6.0815399 | AL5: =IF(AND(ISNUMBER($F5),ISNUMBER($S5)),IF($F5=AL$4,$S5,NA()),NA()) -> #N/A | AM5: =IF(AND(ISNUMBER($F5),ISNUMBER($S5)),IF($F5=AM$4,$S5,NA()),NA()) -> #N/A | AN5: =IF(AND(ISNUMBER($F5),ISNUMBER($S5)),IF($F5=AN$4,$S5,NA()),NA()) -> #N/A | AO5: =IF(AND(ISNUMBER($F5),ISNUMBER($S5)),IF($F5=AO$4,$S5,NA()),NA()) -> #N/A | AP5: =IF(AND(ISNUMBER($F5),ISNUMBER($S5)),IF($F5=AP$4,$S5,NA()),NA()) -> #N/A | AQ5: =IF(AND(ISNUMBER($F5),ISNUMBER($S5)),IF($F5=AQ$4,$S5,NA()),NA()) -> #N/A | AR5: =IF(AND(ISNUMBER($F5),ISNUMBER($S5)),IF($F5=AR$4,$S5,NA()),NA()) -> #N/A | AS5: =IF(AND(ISNUMBER($F5),ISNUMBER($S5)),IF($F5=AS$4,$S5,NA()),NA()) -> #N/A | ... AY5: =IF(AND(ISNUMBER($F5),ISNUMBER($S5)),IF($F5=AY$4,$S5,NA()),NA()) -> #N/A
A6: =IF(Parametri!$H5="","",Parametri!$H5) -> NFR-02 | B6: =IF($A6="","",Parametri!$I5) -> Concentrazione su un fornitore cloud critico | C6: =IF($A6="","",Parametri!$J5) -> L1-06 | D6: =IF($A6="",NA(),IF(COUNTIFS(RR_ID_Rischio,$A6,RR_Ciclo,cicloCorrente)=0,NA(),SUMIFS(RR_Severity,RR_ID_Rischio,$A6,RR_Ciclo,cicloCorrente))) -> 4 | E6: =IF($A6="",NA(),IF(COUNTIFS(RR_ID_Rischio,$A6,RR_Ciclo,cicloCorrente)=0,NA(),SUMIFS(RR_Probabilita,RR_ID_Rischio,$A6,RR_Ciclo,cicloCorrente))) -> 2 | F6: =IF(AND(ISNUMBER(D6),ISNUMBER(E6)),D6*E6,NA()) -> 8 | G6: =IF($A6="",NA(),IF(COUNTIFS(RR_ID_Rischio,$A6,RR_Ciclo,cicloCorrente)=0,NA(),SUMIFS(RR_Prossimita,RR_ID_Rischio,$A6,RR_Ciclo,cicloCorrente))) -> 3 | H6: =IF(ISNUMBER(G6),INDEX(anniProssimita,G6),NA()) -> 1.5 | I6: =IF($A6="",NA(),moscaX) -> 0.25 | J6: =IF($A6="",NA(),IF(COUNTIFS(AZ_ID_Rischio,$A6,AZ_Ciclo,cicloCorrente,AZ_Stato,"<>Respinta",AZ_Mesi_Orizzonte,">0")=0,moscaYDefault,_xlfn.MAXIFS(AZ_Mesi_Orizzonte,AZ_ID_Rischio,$A6,AZ_Ciclo,cicloCorrente,AZ_Stato,"<>Respinta")/12)) -> 1 | K6: =IF(AND(ISNUMBER(H6),ISNUMBER(J6)),H6-(I6+J6),NA()) -> 0.25 | L6: =IF(NOT(ISNUMBER(K6)),"",IF(K6<0,"AGIRE ORA: X+Y > Z",IF(K6<1,"Agire entro l'anno","Margine "&ROUND(K6,1)&IF(ROUND(K6,1)=1," anno"," anni")))) -> Agire entro l'anno | M6: =IF($A6="",NA(),MATCH(C6,codiciL1,0)-1) -> 5 | N6: =IF($A6="",NA(),COUNTIF($C$4:C5,C6)) -> 0 | O6: =IF($A6="",NA(),COUNTIF(ANA_Event_Type,C6)) -> 3 | P6: =IF($A6="",NA(),2*PI()*(M6+(N6+0.5)/O6)/ROWS(codiciL1)) -> 4.6375892 | Q6: =IF(ISNUMBER(K6),MAX(0.6,MIN(6,K6+2)),NA()) -> 2.25 | R6: =IF(AND(ISNUMBER(Q6),ISNUMBER(P6)),Q6*SIN(P6),NA()) -> -2.2437085 | S6: =IF(AND(ISNUMBER(Q6),ISNUMBER(P6)),Q6*COS(P6),NA()) -> -0.16814271 | U6: =2*PI()*1/72 -> 0.087266463 | V6: =2*SIN($U6) -> 0.17431149 | W6: =2*COS($U6) -> 1.9923894 | X6: =3*SIN($U6) -> 0.26146723 | Y6: =3*COS($U6) -> 2.9885841 | Z6: =4*SIN($U6) -> 0.34862297 | AA6: =4*COS($U6) -> 3.9847788 | AB6: =5*SIN($U6) -> 0.43577871 | AC6: =5*COS($U6) -> 4.9809735 | AE6: =6.3*SIN(2*PI()*0/ROWS(codiciL1)) -> 0 | AF6: =6.3*COS(2*PI()*0/ROWS(codiciL1)) -> 6.3 | AH6: L1-02 | AI6: =6.75*SIN(2*PI()*(1+0.5)/ROWS(codiciL1)) -> 6.5807634 | AJ6: =6.75*COS(2*PI()*(1+0.5)/ROWS(codiciL1)) -> 1.5020163 | AL6: =IF(AND(ISNUMBER($F6),ISNUMBER($S6)),IF($F6=AL$4,$S6,NA()),NA()) -> #N/A | AM6: =IF(AND(ISNUMBER($F6),ISNUMBER($S6)),IF($F6=AM$4,$S6,NA()),NA()) -> #N/A | AN6: =IF(AND(ISNUMBER($F6),ISNUMBER($S6)),IF($F6=AN$4,$S6,NA()),NA()) -> #N/A | AO6: =IF(AND(ISNUMBER($F6),ISNUMBER($S6)),IF($F6=AO$4,$S6,NA()),NA()) -> #N/A | AP6: =IF(AND(ISNUMBER($F6),ISNUMBER($S6)),IF($F6=AP$4,$S6,NA()),NA()) -> #N/A | AQ6: =IF(AND(ISNUMBER($F6),ISNUMBER($S6)),IF($F6=AQ$4,$S6,NA()),NA()) -> #N/A | AR6: =IF(AND(ISNUMBER($F6),ISNUMBER($S6)),IF($F6=AR$4,$S6,NA()),NA()) -> -0.16814271 | AS6: =IF(AND(ISNUMBER($F6),ISNUMBER($S6)),IF($F6=AS$4,$S6,NA()),NA()) -> #N/A | ... AY6: =IF(AND(ISNUMBER($F6),ISNUMBER($S6)),IF($F6=AY$4,$S6,NA()),NA()) -> #N/A
A7: =IF(Parametri!$H6="","",Parametri!$H6) -> NFR-03 | B7: =IF($A7="","",Parametri!$I6) -> Greenwashing nella commercializzazione di prodotti ESG | C7: =IF($A7="","",Parametri!$J6) -> L1-04 | D7: =IF($A7="",NA(),IF(COUNTIFS(RR_ID_Rischio,$A7,RR_Ciclo,cicloCorrente)=0,NA(),SUMIFS(RR_Severity,RR_ID_Rischio,$A7,RR_Ciclo,cicloCorrente))) -> 3 | E7: =IF($A7="",NA(),IF(COUNTIFS(RR_ID_Rischio,$A7,RR_Ciclo,cicloCorrente)=0,NA(),SUMIFS(RR_Probabilita,RR_ID_Rischio,$A7,RR_Ciclo,cicloCorrente))) -> 2 | F7: =IF(AND(ISNUMBER(D7),ISNUMBER(E7)),D7*E7,NA()) -> 6 | G7: =IF($A7="",NA(),IF(COUNTIFS(RR_ID_Rischio,$A7,RR_Ciclo,cicloCorrente)=0,NA(),SUMIFS(RR_Prossimita,RR_ID_Rischio,$A7,RR_Ciclo,cicloCorrente))) -> 4 | H7: =IF(ISNUMBER(G7),INDEX(anniProssimita,G7),NA()) -> 0.5 | I7: =IF($A7="",NA(),moscaX) -> 0.25 | J7: =IF($A7="",NA(),IF(COUNTIFS(AZ_ID_Rischio,$A7,AZ_Ciclo,cicloCorrente,AZ_Stato,"<>Respinta",AZ_Mesi_Orizzonte,">0")=0,moscaYDefault,_xlfn.MAXIFS(AZ_Mesi_Orizzonte,AZ_ID_Rischio,$A7,AZ_Ciclo,cicloCorrente,AZ_Stato,"<>Respinta")/12)) -> 0.25 | K7: =IF(AND(ISNUMBER(H7),ISNUMBER(J7)),H7-(I7+J7),NA()) -> 0 | L7: =IF(NOT(ISNUMBER(K7)),"",IF(K7<0,"AGIRE ORA: X+Y > Z",IF(K7<1,"Agire entro l'anno","Margine "&ROUND(K7,1)&IF(ROUND(K7,1)=1," anno"," anni")))) -> Agire entro l'anno | M7: =IF($A7="",NA(),MATCH(C7,codiciL1,0)-1) -> 3 | N7: =IF($A7="",NA(),COUNTIF($C$4:C6,C7)) -> 0 | O7: =IF($A7="",NA(),COUNTIF(ANA_Event_Type,C7)) -> 3 | P7: =IF($A7="",NA(),2*PI()*(M7+(N7+0.5)/O7)/ROWS(codiciL1)) -> 2.8423934 | Q7: =IF(ISNUMBER(K7),MAX(0.6,MIN(6,K7+2)),NA()) -> 2 | R7: =IF(AND(ISNUMBER(Q7),ISNUMBER(P7)),Q7*SIN(P7),NA()) -> 0.58951035 | S7: =IF(AND(ISNUMBER(Q7),ISNUMBER(P7)),Q7*COS(P7),NA()) -> -1.9111456 | U7: =2*PI()*2/72 -> 0.17453293 | V7: =2*SIN($U7) -> 0.34729636 | W7: =2*COS($U7) -> 1.9696155 | X7: =3*SIN($U7) -> 0.52094453 | Y7: =3*COS($U7) -> 2.9544233 | Z7: =4*SIN($U7) -> 0.69459271 | AA7: =4*COS($U7) -> 3.939231 | AB7: =5*SIN($U7) -> 0.86824089 | AC7: =5*COS($U7) -> 4.9240388 | AE7: 0 | AF7: 0 | AH7: L1-03 | AI7: =6.75*SIN(2*PI()*(2+0.5)/ROWS(codiciL1)) -> 5.2773625 | AJ7: =6.75*COS(2*PI()*(2+0.5)/ROWS(codiciL1)) -> -4.2085562 | AL7: =IF(AND(ISNUMBER($F7),ISNUMBER($S7)),IF($F7=AL$4,$S7,NA()),NA()) -> #N/A | AM7: =IF(AND(ISNUMBER($F7),ISNUMBER($S7)),IF($F7=AM$4,$S7,NA()),NA()) -> #N/A | AN7: =IF(AND(ISNUMBER($F7),ISNUMBER($S7)),IF($F7=AN$4,$S7,NA()),NA()) -> #N/A | AO7: =IF(AND(ISNUMBER($F7),ISNUMBER($S7)),IF($F7=AO$4,$S7,NA()),NA()) -> #N/A | AP7: =IF(AND(ISNUMBER($F7),ISNUMBER($S7)),IF($F7=AP$4,$S7,NA()),NA()) -> #N/A | AQ7: =IF(AND(ISNUMBER($F7),ISNUMBER($S7)),IF($F7=AQ$4,$S7,NA()),NA()) -> -1.9111456 | AR7: =IF(AND(ISNUMBER($F7),ISNUMBER($S7)),IF($F7=AR$4,$S7,NA()),NA()) -> #N/A | AS7: =IF(AND(ISNUMBER($F7),ISNUMBER($S7)),IF($F7=AS$4,$S7,NA()),NA()) -> #N/A | ... AY7: =IF(AND(ISNUMBER($F7),ISNUMBER($S7)),IF($F7=AY$4,$S7,NA()),NA()) -> #N/A
A8: =IF(Parametri!$H7="","",Parametri!$H7) -> NFR-04 | B8: =IF($A8="","",Parametri!$I7) -> Eventi climatici estremi su sedi e data center | C8: =IF($A8="","",Parametri!$J7) -> L1-05 | D8: =IF($A8="",NA(),IF(COUNTIFS(RR_ID_Rischio,$A8,RR_Ciclo,cicloCorrente)=0,NA(),SUMIFS(RR_Severity,RR_ID_Rischio,$A8,RR_Ciclo,cicloCorrente))) -> 3 | E8: =IF($A8="",NA(),IF(COUNTIFS(RR_ID_Rischio,$A8,RR_Ciclo,cicloCorrente)=0,NA(),SUMIFS(RR_Probabilita,RR_ID_Rischio,$A8,RR_Ciclo,cicloCorrente))) -> 3 | F8: =IF(AND(ISNUMBER(D8),ISNUMBER(E8)),D8*E8,NA()) -> 9 | G8: =IF($A8="",NA(),IF(COUNTIFS(RR_ID_Rischio,$A8,RR_Ciclo,cicloCorrente)=0,NA(),SUMIFS(RR_Prossimita,RR_ID_Rischio,$A8,RR_Ciclo,cicloCorrente))) -> 3 | H8: =IF(ISNUMBER(G8),INDEX(anniProssimita,G8),NA()) -> 1.5 | I8: =IF($A8="",NA(),moscaX) -> 0.25 | J8: =IF($A8="",NA(),IF(COUNTIFS(AZ_ID_Rischio,$A8,AZ_Ciclo,cicloCorrente,AZ_Stato,"<>Respinta",AZ_Mesi_Orizzonte,">0")=0,moscaYDefault,_xlfn.MAXIFS(AZ_Mesi_Orizzonte,AZ_ID_Rischio,$A8,AZ_Ciclo,cicloCorrente,AZ_Stato,"<>Respinta")/12)) -> 0.5 | K8: =IF(AND(ISNUMBER(H8),ISNUMBER(J8)),H8-(I8+J8),NA()) -> 0.75 | L8: =IF(NOT(ISNUMBER(K8)),"",IF(K8<0,"AGIRE ORA: X+Y > Z",IF(K8<1,"Agire entro l'anno","Margine "&ROUND(K8,1)&IF(ROUND(K8,1)=1," anno"," anni")))) -> Agire entro l'anno | M8: =IF($A8="",NA(),MATCH(C8,codiciL1,0)-1) -> 4 | N8: =IF($A8="",NA(),COUNTIF($C$4:C7,C8)) -> 0 | O8: =IF($A8="",NA(),COUNTIF(ANA_Event_Type,C8)) -> 1 | P8: =IF($A8="",NA(),2*PI()*(M8+(N8+0.5)/O8)/ROWS(codiciL1)) -> 4.0391906 | Q8: =IF(ISNUMBER(K8),MAX(0.6,MIN(6,K8+2)),NA()) -> 2.75 | R8: =IF(AND(ISNUMBER(Q8),ISNUMBER(P8)),Q8*SIN(P8),NA()) -> -2.1500366 | S8: =IF(AND(ISNUMBER(Q8),ISNUMBER(P8)),Q8*COS(P8),NA()) -> -1.714597 | U8: =2*PI()*3/72 -> 0.26179939 | V8: =2*SIN($U8) -> 0.51763809 | W8: =2*COS($U8) -> 1.9318517 | X8: =3*SIN($U8) -> 0.77645714 | Y8: =3*COS($U8) -> 2.8977775 | Z8: =4*SIN($U8) -> 1.0352762 | AA8: =4*COS($U8) -> 3.8637033 | AB8: =5*SIN($U8) -> 1.2940952 | AC8: =5*COS($U8) -> 4.8296291 | AE8: =6.3*SIN(2*PI()*1/ROWS(codiciL1)) -> 4.9255383 | AF8: =6.3*COS(2*PI()*1/ROWS(codiciL1)) -> 3.9279858 | AH8: L1-04 | AI8: =6.75*SIN(2*PI()*(3+0.5)/ROWS(codiciL1)) -> 8.2697521e-16 | AJ8: =6.75*COS(2*PI()*(3+0.5)/ROWS(codiciL1)) -> -6.75 | AL8: =IF(AND(ISNUMBER($F8),ISNUMBER($S8)),IF($F8=AL$4,$S8,NA()),NA()) -> #N/A | AM8: =IF(AND(ISNUMBER($F8),ISNUMBER($S8)),IF($F8=AM$4,$S8,NA()),NA()) -> #N/A | AN8: =IF(AND(ISNUMBER($F8),ISNUMBER($S8)),IF($F8=AN$4,$S8,NA()),NA()) -> #N/A | AO8: =IF(AND(ISNUMBER($F8),ISNUMBER($S8)),IF($F8=AO$4,$S8,NA()),NA()) -> #N/A | AP8: =IF(AND(ISNUMBER($F8),ISNUMBER($S8)),IF($F8=AP$4,$S8,NA()),NA()) -> #N/A | AQ8: =IF(AND(ISNUMBER($F8),ISNUMBER($S8)),IF($F8=AQ$4,$S8,NA()),NA()) -> #N/A | AR8: =IF(AND(ISNUMBER($F8),ISNUMBER($S8)),IF($F8=AR$4,$S8,NA()),NA()) -> #N/A | AS8: =IF(AND(ISNUMBER($F8),ISNUMBER($S8)),IF($F8=AS$4,$S8,NA()),NA()) -> -1.714597 | ... AY8: =IF(AND(ISNUMBER($F8),ISNUMBER($S8)),IF($F8=AY$4,$S8,NA()),NA()) -> #N/A
A9: =IF(Parametri!$H8="","",Parametri!$H8) -> NFR-05 | B9: =IF($A9="","",Parametri!$I8) -> Errori di processo nella migrazione del core banking | C9: =IF($A9="","",Parametri!$J8) -> L1-07 | D9: =IF($A9="",NA(),IF(COUNTIFS(RR_ID_Rischio,$A9,RR_Ciclo,cicloCorrente)=0,NA(),SUMIFS(RR_Severity,RR_ID_Rischio,$A9,RR_Ciclo,cicloCorrente))) -> 3 | E9: =IF($A9="",NA(),IF(COUNTIFS(RR_ID_Rischio,$A9,RR_Ciclo,cicloCorrente)=0,NA(),SUMIFS(RR_Probabilita,RR_ID_Rischio,$A9,RR_Ciclo,cicloCorrente))) -> 3 | F9: =IF(AND(ISNUMBER(D9),ISNUMBER(E9)),D9*E9,NA()) -> 9 | G9: =IF($A9="",NA(),IF(COUNTIFS(RR_ID_Rischio,$A9,RR_Ciclo,cicloCorrente)=0,NA(),SUMIFS(RR_Prossimita,RR_ID_Rischio,$A9,RR_Ciclo,cicloCorrente))) -> 3 | H9: =IF(ISNUMBER(G9),INDEX(anniProssimita,G9),NA()) -> 1.5 | I9: =IF($A9="",NA(),moscaX) -> 0.25 | J9: =IF($A9="",NA(),IF(COUNTIFS(AZ_ID_Rischio,$A9,AZ_Ciclo,cicloCorrente,AZ_Stato,"<>Respinta",AZ_Mesi_Orizzonte,">0")=0,moscaYDefault,_xlfn.MAXIFS(AZ_Mesi_Orizzonte,AZ_ID_Rischio,$A9,AZ_Ciclo,cicloCorrente,AZ_Stato,"<>Respinta")/12)) -> 0.25 | K9: =IF(AND(ISNUMBER(H9),ISNUMBER(J9)),H9-(I9+J9),NA()) -> 1 | L9: =IF(NOT(ISNUMBER(K9)),"",IF(K9<0,"AGIRE ORA: X+Y > Z",IF(K9<1,"Agire entro l'anno","Margine "&ROUND(K9,1)&IF(ROUND(K9,1)=1," anno"," anni")))) -> Margine 1 anno | M9: =IF($A9="",NA(),MATCH(C9,codiciL1,0)-1) -> 6 | N9: =IF($A9="",NA(),COUNTIF($C$4:C8,C9)) -> 0 | O9: =IF($A9="",NA(),COUNTIF(ANA_Event_Type,C9)) -> 2 | P9: =IF($A9="",NA(),2*PI()*(M9+(N9+0.5)/O9)/ROWS(codiciL1)) -> 5.6099869 | Q9: =IF(ISNUMBER(K9),MAX(0.6,MIN(6,K9+2)),NA()) -> 3 | R9: =IF(AND(ISNUMBER(Q9),ISNUMBER(P9)),Q9*SIN(P9),NA()) -> -1.8704694 | S9: =IF(AND(ISNUMBER(Q9),ISNUMBER(P9)),Q9*COS(P9),NA()) -> 2.3454944 | U9: =2*PI()*4/72 -> 0.34906585 | V9: =2*SIN($U9) -> 0.68404029 | W9: =2*COS($U9) -> 1.8793852 | X9: =3*SIN($U9) -> 1.0260604 | Y9: =3*COS($U9) -> 2.8190779 | Z9: =4*SIN($U9) -> 1.3680806 | AA9: =4*COS($U9) -> 3.7587705 | AB9: =5*SIN($U9) -> 1.7101007 | AC9: =5*COS($U9) -> 4.6984631 | AE9: 0 | AF9: 0 | AH9: L1-05 | AI9: =6.75*SIN(2*PI()*(4+0.5)/ROWS(codiciL1)) -> -5.2773625 | AJ9: =6.75*COS(2*PI()*(4+0.5)/ROWS(codiciL1)) -> -4.2085562 | AL9: =IF(AND(ISNUMBER($F9),ISNUMBER($S9)),IF($F9=AL$4,$S9,NA()),NA()) -> #N/A | AM9: =IF(AND(ISNUMBER($F9),ISNUMBER($S9)),IF($F9=AM$4,$S9,NA()),NA()) -> #N/A | AN9: =IF(AND(ISNUMBER($F9),ISNUMBER($S9)),IF($F9=AN$4,$S9,NA()),NA()) -> #N/A | AO9: =IF(AND(ISNUMBER($F9),ISNUMBER($S9)),IF($F9=AO$4,$S9,NA()),NA()) -> #N/A | AP9: =IF(AND(ISNUMBER($F9),ISNUMBER($S9)),IF($F9=AP$4,$S9,NA()),NA()) -> #N/A | AQ9: =IF(AND(ISNUMBER($F9),ISNUMBER($S9)),IF($F9=AQ$4,$S9,NA()),NA()) -> #N/A | AR9: =IF(AND(ISNUMBER($F9),ISNUMBER($S9)),IF($F9=AR$4,$S9,NA()),NA()) -> #N/A | AS9: =IF(AND(ISNUMBER($F9),ISNUMBER($S9)),IF($F9=AS$4,$S9,NA()),NA()) -> 2.3454944 | ... AY9: =IF(AND(ISNUMBER($F9),ISNUMBER($S9)),IF($F9=AY$4,$S9,NA()),NA()) -> #N/A
A10: =IF(Parametri!$H9="","",Parametri!$H9) -> NFR-06 | B10: =IF($A10="","",Parametri!$I9) -> Esfiltrazione di dati tramite strumenti di AI non autorizzati | C10: =IF($A10="","",Parametri!$J9) -> L1-01 | D10: =IF($A10="",NA(),IF(COUNTIFS(RR_ID_Rischio,$A10,RR_Ciclo,cicloCorrente)=0,NA(),SUMIFS(RR_Severity,RR_ID_Rischio,$A10,RR_Ciclo,cicloCorrente))) -> 3 | E10: =IF($A10="",NA(),IF(COUNTIFS(RR_ID_Rischio,$A10,RR_Ciclo,cicloCorrente)=0,NA(),SUMIFS(RR_Probabilita,RR_ID_Rischio,$A10,RR_Ciclo,cicloCorrente))) -> 3 | F10: =IF(AND(ISNUMBER(D10),ISNUMBER(E10)),D10*E10,NA()) -> 9 | G10: =IF($A10="",NA(),IF(COUNTIFS(RR_ID_Rischio,$A10,RR_Ciclo,cicloCorrente)=0,NA(),SUMIFS(RR_Prossimita,RR_ID_Rischio,$A10,RR_Ciclo,cicloCorrente))) -> 3 | H10: =IF(ISNUMBER(G10),INDEX(anniProssimita,G10),NA()) -> 1.5 | I10: =IF($A10="",NA(),moscaX) -> 0.25 | J10: =IF($A10="",NA(),IF(COUNTIFS(AZ_ID_Rischio,$A10,AZ_Ciclo,cicloCorrente,AZ_Stato,"<>Respinta",AZ_Mesi_Orizzonte,">0")=0,moscaYDefault,_xlfn.MAXIFS(AZ_Mesi_Orizzonte,AZ_ID_Rischio,$A10,AZ_Ciclo,cicloCorrente,AZ_Stato,"<>Respinta")/12)) -> 0.5 | K10: =IF(AND(ISNUMBER(H10),ISNUMBER(J10)),H10-(I10+J10),NA()) -> 0.75 | L10: =IF(NOT(ISNUMBER(K10)),"",IF(K10<0,"AGIRE ORA: X+Y > Z",IF(K10<1,"Agire entro l'anno","Margine "&ROUND(K10,1)&IF(ROUND(K10,1)=1," anno"," anni")))) -> Agire entro l'anno | M10: =IF($A10="",NA(),MATCH(C10,codiciL1,0)-1) -> 0 | N10: =IF($A10="",NA(),COUNTIF($C$4:C9,C10)) -> 0 | O10: =IF($A10="",NA(),COUNTIF(ANA_Event_Type,C10)) -> 2 | P10: =IF($A10="",NA(),2*PI()*(M10+(N10+0.5)/O10)/ROWS(codiciL1)) -> 0.22439948 | Q10: =IF(ISNUMBER(K10),MAX(0.6,MIN(6,K10+2)),NA()) -> 2.75 | R10: =IF(AND(ISNUMBER(Q10),ISNUMBER(P10)),Q10*SIN(P10),NA()) -> 0.61193257 | S10: =IF(AND(ISNUMBER(Q10),ISNUMBER(P10)),Q10*COS(P10),NA()) -> 2.6810518 | U10: =2*PI()*5/72 -> 0.43633231 | V10: =2*SIN($U10) -> 0.84523652 | W10: =2*COS($U10) -> 1.8126156 | X10: =3*SIN($U10) -> 1.2678548 | Y10: =3*COS($U10) -> 2.7189234 | Z10: =4*SIN($U10) -> 1.690473 | AA10: =4*COS($U10) -> 3.6252311 | AB10: =5*SIN($U10) -> 2.1130913 | AC10: =5*COS($U10) -> 4.5315389 | AE10: =6.3*SIN(2*PI()*2/ROWS(codiciL1)) -> 6.1420458 | AF10: =6.3*COS(2*PI()*2/ROWS(codiciL1)) -> -1.4018819 | AH10: L1-06 | AI10: =6.75*SIN(2*PI()*(5+0.5)/ROWS(codiciL1)) -> -6.5807634 | AJ10: =6.75*COS(2*PI()*(5+0.5)/ROWS(codiciL1)) -> 1.5020163 | AL10: =IF(AND(ISNUMBER($F10),ISNUMBER($S10)),IF($F10=AL$4,$S10,NA()),NA()) -> #N/A | AM10: =IF(AND(ISNUMBER($F10),ISNUMBER($S10)),IF($F10=AM$4,$S10,NA()),NA()) -> #N/A | AN10: =IF(AND(ISNUMBER($F10),ISNUMBER($S10)),IF($F10=AN$4,$S10,NA()),NA()) -> #N/A | AO10: =IF(AND(ISNUMBER($F10),ISNUMBER($S10)),IF($F10=AO$4,$S10,NA()),NA()) -> #N/A | AP10: =IF(AND(ISNUMBER($F10),ISNUMBER($S10)),IF($F10=AP$4,$S10,NA()),NA()) -> #N/A | AQ10: =IF(AND(ISNUMBER($F10),ISNUMBER($S10)),IF($F10=AQ$4,$S10,NA()),NA()) -> #N/A | AR10: =IF(AND(ISNUMBER($F10),ISNUMBER($S10)),IF($F10=AR$4,$S10,NA()),NA()) -> #N/A | AS10: =IF(AND(ISNUMBER($F10),ISNUMBER($S10)),IF($F10=AS$4,$S10,NA()),NA()) -> 2.6810518 | ... AY10: =IF(AND(ISNUMBER($F10),ISNUMBER($S10)),IF($F10=AY$4,$S10,NA()),NA()) -> #N/A
A11: =IF(Parametri!$H10="","",Parametri!$H10) -> NFR-07 | B11: =IF($A11="","",Parametri!$I10) -> Ransomware presso un fornitore di servizi di pagamento | C11: =IF($A11="","",Parametri!$J10) -> L1-06 | D11: =IF($A11="",NA(),IF(COUNTIFS(RR_ID_Rischio,$A11,RR_Ciclo,cicloCorrente)=0,NA(),SUMIFS(RR_Severity,RR_ID_Rischio,$A11,RR_Ciclo,cicloCorrente))) -> 4 | E11: =IF($A11="",NA(),IF(COUNTIFS(RR_ID_Rischio,$A11,RR_Ciclo,cicloCorrente)=0,NA(),SUMIFS(RR_Probabilita,RR_ID_Rischio,$A11,RR_Ciclo,cicloCorrente))) -> 3 | F11: =IF(AND(ISNUMBER(D11),ISNUMBER(E11)),D11*E11,NA()) -> 12 | G11: =IF($A11="",NA(),IF(COUNTIFS(RR_ID_Rischio,$A11,RR_Ciclo,cicloCorrente)=0,NA(),SUMIFS(RR_Prossimita,RR_ID_Rischio,$A11,RR_Ciclo,cicloCorrente))) -> 3 | H11: =IF(ISNUMBER(G11),INDEX(anniProssimita,G11),NA()) -> 1.5 | I11: =IF($A11="",NA(),moscaX) -> 0.25 | J11: =IF($A11="",NA(),IF(COUNTIFS(AZ_ID_Rischio,$A11,AZ_Ciclo,cicloCorrente,AZ_Stato,"<>Respinta",AZ_Mesi_Orizzonte,">0")=0,moscaYDefault,_xlfn.MAXIFS(AZ_Mesi_Orizzonte,AZ_ID_Rischio,$A11,AZ_Ciclo,cicloCorrente,AZ_Stato,"<>Respinta")/12)) -> 0.5 | K11: =IF(AND(ISNUMBER(H11),ISNUMBER(J11)),H11-(I11+J11),NA()) -> 0.75 | L11: =IF(NOT(ISNUMBER(K11)),"",IF(K11<0,"AGIRE ORA: X+Y > Z",IF(K11<1,"Agire entro l'anno","Margine "&ROUND(K11,1)&IF(ROUND(K11,1)=1," anno"," anni")))) -> Agire entro l'anno | M11: =IF($A11="",NA(),MATCH(C11,codiciL1,0)-1) -> 5 | N11: =IF($A11="",NA(),COUNTIF($C$4:C10,C11)) -> 1 | O11: =IF($A11="",NA(),COUNTIF(ANA_Event_Type,C11)) -> 3 | P11: =IF($A11="",NA(),2*PI()*(M11+(N11+0.5)/O11)/ROWS(codiciL1)) -> 4.9367885 | Q11: =IF(ISNUMBER(K11),MAX(0.6,MIN(6,K11+2)),NA()) -> 2.75 | R11: =IF(AND(ISNUMBER(Q11),ISNUMBER(P11)),Q11*SIN(P11),NA()) -> -2.6810518 | S11: =IF(AND(ISNUMBER(Q11),ISNUMBER(P11)),Q11*COS(P11),NA()) -> 0.61193257 | U11: =2*PI()*6/72 -> 0.52359878 | V11: =2*SIN($U11) -> 1 | W11: =2*COS($U11) -> 1.7320508 | X11: =3*SIN($U11) -> 1.5 | Y11: =3*COS($U11) -> 2.5980762 | Z11: =4*SIN($U11) -> 2 | AA11: =4*COS($U11) -> 3.4641016 | AB11: =5*SIN($U11) -> 2.5 | AC11: =5*COS($U11) -> 4.330127 | AE11: 0 | AF11: 0 | AH11: L1-07 | AI11: =6.75*SIN(2*PI()*(6+0.5)/ROWS(codiciL1)) -> -2.9287152 | AJ11: =6.75*COS(2*PI()*(6+0.5)/ROWS(codiciL1)) -> 6.0815399 | AL11: =IF(AND(ISNUMBER($F11),ISNUMBER($S11)),IF($F11=AL$4,$S11,NA()),NA()) -> #N/A | AM11: =IF(AND(ISNUMBER($F11),ISNUMBER($S11)),IF($F11=AM$4,$S11,NA()),NA()) -> #N/A | AN11: =IF(AND(ISNUMBER($F11),ISNUMBER($S11)),IF($F11=AN$4,$S11,NA()),NA()) -> #N/A | AO11: =IF(AND(ISNUMBER($F11),ISNUMBER($S11)),IF($F11=AO$4,$S11,NA()),NA()) -> #N/A | AP11: =IF(AND(ISNUMBER($F11),ISNUMBER($S11)),IF($F11=AP$4,$S11,NA()),NA()) -> #N/A | AQ11: =IF(AND(ISNUMBER($F11),ISNUMBER($S11)),IF($F11=AQ$4,$S11,NA()),NA()) -> #N/A | AR11: =IF(AND(ISNUMBER($F11),ISNUMBER($S11)),IF($F11=AR$4,$S11,NA()),NA()) -> #N/A | AS11: =IF(AND(ISNUMBER($F11),ISNUMBER($S11)),IF($F11=AS$4,$S11,NA()),NA()) -> #N/A | ... AY11: =IF(AND(ISNUMBER($F11),ISNUMBER($S11)),IF($F11=AY$4,$S11,NA()),NA()) -> #N/A
A12: =IF(Parametri!$H11="","",Parametri!$H11) -> NFR-08 | B12: =IF($A12="","",Parametri!$I11) -> Accessi impropri di dipendenti ai dati dei clienti | C12: =IF($A12="","",Parametri!$J11) -> L1-01 | D12: =IF($A12="",NA(),IF(COUNTIFS(RR_ID_Rischio,$A12,RR_Ciclo,cicloCorrente)=0,NA(),SUMIFS(RR_Severity,RR_ID_Rischio,$A12,RR_Ciclo,cicloCorrente))) -> 3 | E12: =IF($A12="",NA(),IF(COUNTIFS(RR_ID_Rischio,$A12,RR_Ciclo,cicloCorrente)=0,NA(),SUMIFS(RR_Probabilita,RR_ID_Rischio,$A12,RR_Ciclo,cicloCorrente))) -> 2 | F12: =IF(AND(ISNUMBER(D12),ISNUMBER(E12)),D12*E12,NA()) -> 6 | G12: =IF($A12="",NA(),IF(COUNTIFS(RR_ID_Rischio,$A12,RR_Ciclo,cicloCorrente)=0,NA(),SUMIFS(RR_Prossimita,RR_ID_Rischio,$A12,RR_Ciclo,cicloCorrente))) -> 3 | H12: =IF(ISNUMBER(G12),INDEX(anniProssimita,G12),NA()) -> 1.5 | I12: =IF($A12="",NA(),moscaX) -> 0.25 | J12: =IF($A12="",NA(),IF(COUNTIFS(AZ_ID_Rischio,$A12,AZ_Ciclo,cicloCorrente,AZ_Stato,"<>Respinta",AZ_Mesi_Orizzonte,">0")=0,moscaYDefault,_xlfn.MAXIFS(AZ_Mesi_Orizzonte,AZ_ID_Rischio,$A12,AZ_Ciclo,cicloCorrente,AZ_Stato,"<>Respinta")/12)) -> 0.25 | K12: =IF(AND(ISNUMBER(H12),ISNUMBER(J12)),H12-(I12+J12),NA()) -> 1 | L12: =IF(NOT(ISNUMBER(K12)),"",IF(K12<0,"AGIRE ORA: X+Y > Z",IF(K12<1,"Agire entro l'anno","Margine "&ROUND(K12,1)&IF(ROUND(K12,1)=1," anno"," anni")))) -> Margine 1 anno | M12: =IF($A12="",NA(),MATCH(C12,codiciL1,0)-1) -> 0 | N12: =IF($A12="",NA(),COUNTIF($C$4:C11,C12)) -> 1 | O12: =IF($A12="",NA(),COUNTIF(ANA_Event_Type,C12)) -> 2 | P12: =IF($A12="",NA(),2*PI()*(M12+(N12+0.5)/O12)/ROWS(codiciL1)) -> 0.67319843 | Q12: =IF(ISNUMBER(K12),MAX(0.6,MIN(6,K12+2)),NA()) -> 3 | R12: =IF(AND(ISNUMBER(Q12),ISNUMBER(P12)),Q12*SIN(P12),NA()) -> 1.8704694 | S12: =IF(AND(ISNUMBER(Q12),ISNUMBER(P12)),Q12*COS(P12),NA()) -> 2.3454944 | U12: =2*PI()*7/72 -> 0.61086524 | V12: =2*SIN($U12) -> 1.1471529 | W12: =2*COS($U12) -> 1.6383041 | X12: =3*SIN($U12) -> 1.7207293 | Y12: =3*COS($U12) -> 2.4574561 | Z12: =4*SIN($U12) -> 2.2943057 | AA12: =4*COS($U12) -> 3.2766082 | AB12: =5*SIN($U12) -> 2.8678822 | AC12: =5*COS($U12) -> 4.0957602 | AE12: =6.3*SIN(2*PI()*3/ROWS(codiciL1)) -> 2.7334676 | AF12: =6.3*COS(2*PI()*3/ROWS(codiciL1)) -> -5.6761039 | AL12: =IF(AND(ISNUMBER($F12),ISNUMBER($S12)),IF($F12=AL$4,$S12,NA()),NA()) -> #N/A | AM12: =IF(AND(ISNUMBER($F12),ISNUMBER($S12)),IF($F12=AM$4,$S12,NA()),NA()) -> #N/A | AN12: =IF(AND(ISNUMBER($F12),ISNUMBER($S12)),IF($F12=AN$4,$S12,NA()),NA()) -> #N/A | AO12: =IF(AND(ISNUMBER($F12),ISNUMBER($S12)),IF($F12=AO$4,$S12,NA()),NA()) -> #N/A | AP12: =IF(AND(ISNUMBER($F12),ISNUMBER($S12)),IF($F12=AP$4,$S12,NA()),NA()) -> #N/A | AQ12: =IF(AND(ISNUMBER($F12),ISNUMBER($S12)),IF($F12=AQ$4,$S12,NA()),NA()) -> 2.3454944 | AR12: =IF(AND(ISNUMBER($F12),ISNUMBER($S12)),IF($F12=AR$4,$S12,NA()),NA()) -> #N/A | AS12: =IF(AND(ISNUMBER($F12),ISNUMBER($S12)),IF($F12=AS$4,$S12,NA()),NA()) -> #N/A | ... AY12: =IF(AND(ISNUMBER($F12),ISNUMBER($S12)),IF($F12=AY$4,$S12,NA()),NA()) -> #N/A
A13: =IF(Parametri!$H12="","",Parametri!$H12) -> NFR-09 | B13: =IF($A13="","",Parametri!$I12) -> Violazione di sanzioni internazionali tramite triangolazioni | C13: =IF($A13="","",Parametri!$J12) -> L1-04 | D13: =IF($A13="",NA(),IF(COUNTIFS(RR_ID_Rischio,$A13,RR_Ciclo,cicloCorrente)=0,NA(),SUMIFS(RR_Severity,RR_ID_Rischio,$A13,RR_Ciclo,cicloCorrente))) -> 4 | E13: =IF($A13="",NA(),IF(COUNTIFS(RR_ID_Rischio,$A13,RR_Ciclo,cicloCorrente)=0,NA(),SUMIFS(RR_Probabilita,RR_ID_Rischio,$A13,RR_Ciclo,cicloCorrente))) -> 2 | F13: =IF(AND(ISNUMBER(D13),ISNUMBER(E13)),D13*E13,NA()) -> 8 | G13: =IF($A13="",NA(),IF(COUNTIFS(RR_ID_Rischio,$A13,RR_Ciclo,cicloCorrente)=0,NA(),SUMIFS(RR_Prossimita,RR_ID_Rischio,$A13,RR_Ciclo,cicloCorrente))) -> 2 | H13: =IF(ISNUMBER(G13),INDEX(anniProssimita,G13),NA()) -> 2.5 | I13: =IF($A13="",NA(),moscaX) -> 0.25 | J13: =IF($A13="",NA(),IF(COUNTIFS(AZ_ID_Rischio,$A13,AZ_Ciclo,cicloCorrente,AZ_Stato,"<>Respinta",AZ_Mesi_Orizzonte,">0")=0,moscaYDefault,_xlfn.MAXIFS(AZ_Mesi_Orizzonte,AZ_ID_Rischio,$A13,AZ_Ciclo,cicloCorrente,AZ_Stato,"<>Respinta")/12)) -> 1 | K13: =IF(AND(ISNUMBER(H13),ISNUMBER(J13)),H13-(I13+J13),NA()) -> 1.25 | L13: =IF(NOT(ISNUMBER(K13)),"",IF(K13<0,"AGIRE ORA: X+Y > Z",IF(K13<1,"Agire entro l'anno","Margine "&ROUND(K13,1)&IF(ROUND(K13,1)=1," anno"," anni")))) -> Margine 1,3 anni | M13: =IF($A13="",NA(),MATCH(C13,codiciL1,0)-1) -> 3 | N13: =IF($A13="",NA(),COUNTIF($C$4:C12,C13)) -> 1 | O13: =IF($A13="",NA(),COUNTIF(ANA_Event_Type,C13)) -> 3 | P13: =IF($A13="",NA(),2*PI()*(M13+(N13+0.5)/O13)/ROWS(codiciL1)) -> 3.1415927 | Q13: =IF(ISNUMBER(K13),MAX(0.6,MIN(6,K13+2)),NA()) -> 3.25 | R13: =IF(AND(ISNUMBER(Q13),ISNUMBER(P13)),Q13*SIN(P13),NA()) -> 3.9817325e-16 | S13: =IF(AND(ISNUMBER(Q13),ISNUMBER(P13)),Q13*COS(P13),NA()) -> -3.25 | U13: =2*PI()*8/72 -> 0.6981317 | V13: =2*SIN($U13) -> 1.2855752 | W13: =2*COS($U13) -> 1.5320889 | X13: =3*SIN($U13) -> 1.9283628 | Y13: =3*COS($U13) -> 2.2981333 | Z13: =4*SIN($U13) -> 2.5711504 | AA13: =4*COS($U13) -> 3.0641778 | AB13: =5*SIN($U13) -> 3.213938 | AC13: =5*COS($U13) -> 3.8302222 | AE13: 0 | AF13: 0 | AL13: =IF(AND(ISNUMBER($F13),ISNUMBER($S13)),IF($F13=AL$4,$S13,NA()),NA()) -> #N/A | AM13: =IF(AND(ISNUMBER($F13),ISNUMBER($S13)),IF($F13=AM$4,$S13,NA()),NA()) -> #N/A | AN13: =IF(AND(ISNUMBER($F13),ISNUMBER($S13)),IF($F13=AN$4,$S13,NA()),NA()) -> #N/A | AO13: =IF(AND(ISNUMBER($F13),ISNUMBER($S13)),IF($F13=AO$4,$S13,NA()),NA()) -> #N/A | AP13: =IF(AND(ISNUMBER($F13),ISNUMBER($S13)),IF($F13=AP$4,$S13,NA()),NA()) -> #N/A | AQ13: =IF(AND(ISNUMBER($F13),ISNUMBER($S13)),IF($F13=AQ$4,$S13,NA()),NA()) -> #N/A | AR13: =IF(AND(ISNUMBER($F13),ISNUMBER($S13)),IF($F13=AR$4,$S13,NA()),NA()) -> -3.25 | AS13: =IF(AND(ISNUMBER($F13),ISNUMBER($S13)),IF($F13=AS$4,$S13,NA()),NA()) -> #N/A | ... AY13: =IF(AND(ISNUMBER($F13),ISNUMBER($S13)),IF($F13=AY$4,$S13,NA()),NA()) -> #N/A
A14: =IF(Parametri!$H13="","",Parametri!$H13) -> NFR-10 | B14: =IF($A14="","",Parametri!$I13) -> Informazioni errate ai clienti da assistenti di AI generativa | C14: =IF($A14="","",Parametri!$J13) -> L1-04 | D14: =IF($A14="",NA(),IF(COUNTIFS(RR_ID_Rischio,$A14,RR_Ciclo,cicloCorrente)=0,NA(),SUMIFS(RR_Severity,RR_ID_Rischio,$A14,RR_Ciclo,cicloCorrente))) -> 3 | E14: =IF($A14="",NA(),IF(COUNTIFS(RR_ID_Rischio,$A14,RR_Ciclo,cicloCorrente)=0,NA(),SUMIFS(RR_Probabilita,RR_ID_Rischio,$A14,RR_Ciclo,cicloCorrente))) -> 3 | F14: =IF(AND(ISNUMBER(D14),ISNUMBER(E14)),D14*E14,NA()) -> 9 | G14: =IF($A14="",NA(),IF(COUNTIFS(RR_ID_Rischio,$A14,RR_Ciclo,cicloCorrente)=0,NA(),SUMIFS(RR_Prossimita,RR_ID_Rischio,$A14,RR_Ciclo,cicloCorrente))) -> 3 | H14: =IF(ISNUMBER(G14),INDEX(anniProssimita,G14),NA()) -> 1.5 | I14: =IF($A14="",NA(),moscaX) -> 0.25 | J14: =IF($A14="",NA(),IF(COUNTIFS(AZ_ID_Rischio,$A14,AZ_Ciclo,cicloCorrente,AZ_Stato,"<>Respinta",AZ_Mesi_Orizzonte,">0")=0,moscaYDefault,_xlfn.MAXIFS(AZ_Mesi_Orizzonte,AZ_ID_Rischio,$A14,AZ_Ciclo,cicloCorrente,AZ_Stato,"<>Respinta")/12)) -> 0.25 | K14: =IF(AND(ISNUMBER(H14),ISNUMBER(J14)),H14-(I14+J14),NA()) -> 1 | L14: =IF(NOT(ISNUMBER(K14)),"",IF(K14<0,"AGIRE ORA: X+Y > Z",IF(K14<1,"Agire entro l'anno","Margine "&ROUND(K14,1)&IF(ROUND(K14,1)=1," anno"," anni")))) -> Margine 1 anno | M14: =IF($A14="",NA(),MATCH(C14,codiciL1,0)-1) -> 3 | N14: =IF($A14="",NA(),COUNTIF($C$4:C13,C14)) -> 2 | O14: =IF($A14="",NA(),COUNTIF(ANA_Event_Type,C14)) -> 3 | P14: =IF($A14="",NA(),2*PI()*(M14+(N14+0.5)/O14)/ROWS(codiciL1)) -> 3.440792 | Q14: =IF(ISNUMBER(K14),MAX(0.6,MIN(6,K14+2)),NA()) -> 3 | R14: =IF(AND(ISNUMBER(Q14),ISNUMBER(P14)),Q14*SIN(P14),NA()) -> -0.88426552 | S14: =IF(AND(ISNUMBER(Q14),ISNUMBER(P14)),Q14*COS(P14),NA()) -> -2.8667184 | U14: =2*PI()*9/72 -> 0.78539816 | V14: =2*SIN($U14) -> 1.4142136 | W14: =2*COS($U14) -> 1.4142136 | X14: =3*SIN($U14) -> 2.1213203 | Y14: =3*COS($U14) -> 2.1213203 | Z14: =4*SIN($U14) -> 2.8284271 | AA14: =4*COS($U14) -> 2.8284271 | AB14: =5*SIN($U14) -> 3.5355339 | AC14: =5*COS($U14) -> 3.5355339 | AE14: =6.3*SIN(2*PI()*4/ROWS(codiciL1)) -> -2.7334676 | AF14: =6.3*COS(2*PI()*4/ROWS(codiciL1)) -> -5.6761039 | AL14: =IF(AND(ISNUMBER($F14),ISNUMBER($S14)),IF($F14=AL$4,$S14,NA()),NA()) -> #N/A | AM14: =IF(AND(ISNUMBER($F14),ISNUMBER($S14)),IF($F14=AM$4,$S14,NA()),NA()) -> #N/A | AN14: =IF(AND(ISNUMBER($F14),ISNUMBER($S14)),IF($F14=AN$4,$S14,NA()),NA()) -> #N/A | AO14: =IF(AND(ISNUMBER($F14),ISNUMBER($S14)),IF($F14=AO$4,$S14,NA()),NA()) -> #N/A | AP14: =IF(AND(ISNUMBER($F14),ISNUMBER($S14)),IF($F14=AP$4,$S14,NA()),NA()) -> #N/A | AQ14: =IF(AND(ISNUMBER($F14),ISNUMBER($S14)),IF($F14=AQ$4,$S14,NA()),NA()) -> #N/A | AR14: =IF(AND(ISNUMBER($F14),ISNUMBER($S14)),IF($F14=AR$4,$S14,NA()),NA()) -> #N/A | AS14: =IF(AND(ISNUMBER($F14),ISNUMBER($S14)),IF($F14=AS$4,$S14,NA()),NA()) -> -2.8667184 | ... AY14: =IF(AND(ISNUMBER($F14),ISNUMBER($S14)),IF($F14=AY$4,$S14,NA()),NA()) -> #N/A
A15: =IF(Parametri!$H14="","",Parametri!$H14) -> NFR-11 | B15: =IF($A15="","",Parametri!$I14) -> Fine del supporto dei sistemi di pagamento legacy | C15: =IF($A15="","",Parametri!$J14) -> L1-06 | D15: =IF($A15="",NA(),IF(COUNTIFS(RR_ID_Rischio,$A15,RR_Ciclo,cicloCorrente)=0,NA(),SUMIFS(RR_Severity,RR_ID_Rischio,$A15,RR_Ciclo,cicloCorrente))) -> 3 | E15: =IF($A15="",NA(),IF(COUNTIFS(RR_ID_Rischio,$A15,RR_Ciclo,cicloCorrente)=0,NA(),SUMIFS(RR_Probabilita,RR_ID_Rischio,$A15,RR_Ciclo,cicloCorrente))) -> 3 | F15: =IF(AND(ISNUMBER(D15),ISNUMBER(E15)),D15*E15,NA()) -> 9 | G15: =IF($A15="",NA(),IF(COUNTIFS(RR_ID_Rischio,$A15,RR_Ciclo,cicloCorrente)=0,NA(),SUMIFS(RR_Prossimita,RR_ID_Rischio,$A15,RR_Ciclo,cicloCorrente))) -> 3 | H15: =IF(ISNUMBER(G15),INDEX(anniProssimita,G15),NA()) -> 1.5 | I15: =IF($A15="",NA(),moscaX) -> 0.25 | J15: =IF($A15="",NA(),IF(COUNTIFS(AZ_ID_Rischio,$A15,AZ_Ciclo,cicloCorrente,AZ_Stato,"<>Respinta",AZ_Mesi_Orizzonte,">0")=0,moscaYDefault,_xlfn.MAXIFS(AZ_Mesi_Orizzonte,AZ_ID_Rischio,$A15,AZ_Ciclo,cicloCorrente,AZ_Stato,"<>Respinta")/12)) -> 1 | K15: =IF(AND(ISNUMBER(H15),ISNUMBER(J15)),H15-(I15+J15),NA()) -> 0.25 | L15: =IF(NOT(ISNUMBER(K15)),"",IF(K15<0,"AGIRE ORA: X+Y > Z",IF(K15<1,"Agire entro l'anno","Margine "&ROUND(K15,1)&IF(ROUND(K15,1)=1," anno"," anni")))) -> Agire entro l'anno | M15: =IF($A15="",NA(),MATCH(C15,codiciL1,0)-1) -> 5 | N15: =IF($A15="",NA(),COUNTIF($C$4:C14,C15)) -> 2 | O15: =IF($A15="",NA(),COUNTIF(ANA_Event_Type,C15)) -> 3 | P15: =IF($A15="",NA(),2*PI()*(M15+(N15+0.5)/O15)/ROWS(codiciL1)) -> 5.2359878 | Q15: =IF(ISNUMBER(K15),MAX(0.6,MIN(6,K15+2)),NA()) -> 2.25 | R15: =IF(AND(ISNUMBER(Q15),ISNUMBER(P15)),Q15*SIN(P15),NA()) -> -1.9485572 | S15: =IF(AND(ISNUMBER(Q15),ISNUMBER(P15)),Q15*COS(P15),NA()) -> 1.125 | U15: =2*PI()*10/72 -> 0.87266463 | V15: =2*SIN($U15) -> 1.5320889 | W15: =2*COS($U15) -> 1.2855752 | X15: =3*SIN($U15) -> 2.2981333 | Y15: =3*COS($U15) -> 1.9283628 | Z15: =4*SIN($U15) -> 3.0641778 | AA15: =4*COS($U15) -> 2.5711504 | AB15: =5*SIN($U15) -> 3.8302222 | AC15: =5*COS($U15) -> 3.213938 | AE15: 0 | AF15: 0 | AL15: =IF(AND(ISNUMBER($F15),ISNUMBER($S15)),IF($F15=AL$4,$S15,NA()),NA()) -> #N/A | AM15: =IF(AND(ISNUMBER($F15),ISNUMBER($S15)),IF($F15=AM$4,$S15,NA()),NA()) -> #N/A | AN15: =IF(AND(ISNUMBER($F15),ISNUMBER($S15)),IF($F15=AN$4,$S15,NA()),NA()) -> #N/A | AO15: =IF(AND(ISNUMBER($F15),ISNUMBER($S15)),IF($F15=AO$4,$S15,NA()),NA()) -> #N/A | AP15: =IF(AND(ISNUMBER($F15),ISNUMBER($S15)),IF($F15=AP$4,$S15,NA()),NA()) -> #N/A | AQ15: =IF(AND(ISNUMBER($F15),ISNUMBER($S15)),IF($F15=AQ$4,$S15,NA()),NA()) -> #N/A | AR15: =IF(AND(ISNUMBER($F15),ISNUMBER($S15)),IF($F15=AR$4,$S15,NA()),NA()) -> #N/A | AS15: =IF(AND(ISNUMBER($F15),ISNUMBER($S15)),IF($F15=AS$4,$S15,NA()),NA()) -> 1.125 | ... AY15: =IF(AND(ISNUMBER($F15),ISNUMBER($S15)),IF($F15=AY$4,$S15,NA()),NA()) -> #N/A
A16: =IF(Parametri!$H15="","",Parametri!$H15) -> NFR-12 | B16: =IF($A16="","",Parametri!$I15) -> Errori operativi nei pagamenti istantanei obbligatori | C16: =IF($A16="","",Parametri!$J15) -> L1-07 | D16: =IF($A16="",NA(),IF(COUNTIFS(RR_ID_Rischio,$A16,RR_Ciclo,cicloCorrente)=0,NA(),SUMIFS(RR_Severity,RR_ID_Rischio,$A16,RR_Ciclo,cicloCorrente))) -> 3 | E16: =IF($A16="",NA(),IF(COUNTIFS(RR_ID_Rischio,$A16,RR_Ciclo,cicloCorrente)=0,NA(),SUMIFS(RR_Probabilita,RR_ID_Rischio,$A16,RR_Ciclo,cicloCorrente))) -> 4 | F16: =IF(AND(ISNUMBER(D16),ISNUMBER(E16)),D16*E16,NA()) -> 12 | G16: =IF($A16="",NA(),IF(COUNTIFS(RR_ID_Rischio,$A16,RR_Ciclo,cicloCorrente)=0,NA(),SUMIFS(RR_Prossimita,RR_ID_Rischio,$A16,RR_Ciclo,cicloCorrente))) -> 4 | H16: =IF(ISNUMBER(G16),INDEX(anniProssimita,G16),NA()) -> 0.5 | I16: =IF($A16="",NA(),moscaX) -> 0.25 | J16: =IF($A16="",NA(),IF(COUNTIFS(AZ_ID_Rischio,$A16,AZ_Ciclo,cicloCorrente,AZ_Stato,"<>Respinta",AZ_Mesi_Orizzonte,">0")=0,moscaYDefault,_xlfn.MAXIFS(AZ_Mesi_Orizzonte,AZ_ID_Rischio,$A16,AZ_Ciclo,cicloCorrente,AZ_Stato,"<>Respinta")/12)) -> 0.25 | K16: =IF(AND(ISNUMBER(H16),ISNUMBER(J16)),H16-(I16+J16),NA()) -> 0 | L16: =IF(NOT(ISNUMBER(K16)),"",IF(K16<0,"AGIRE ORA: X+Y > Z",IF(K16<1,"Agire entro l'anno","Margine "&ROUND(K16,1)&IF(ROUND(K16,1)=1," anno"," anni")))) -> Agire entro l'anno | M16: =IF($A16="",NA(),MATCH(C16,codiciL1,0)-1) -> 6 | N16: =IF($A16="",NA(),COUNTIF($C$4:C15,C16)) -> 1 | O16: =IF($A16="",NA(),COUNTIF(ANA_Event_Type,C16)) -> 2 | P16: =IF($A16="",NA(),2*PI()*(M16+(N16+0.5)/O16)/ROWS(codiciL1)) -> 6.0587858 | Q16: =IF(ISNUMBER(K16),MAX(0.6,MIN(6,K16+2)),NA()) -> 2 | R16: =IF(AND(ISNUMBER(Q16),ISNUMBER(P16)),Q16*SIN(P16),NA()) -> -0.44504187 | S16: =IF(AND(ISNUMBER(Q16),ISNUMBER(P16)),Q16*COS(P16),NA()) -> 1.9498558 | U16: =2*PI()*11/72 -> 0.95993109 | V16: =2*SIN($U16) -> 1.6383041 | W16: =2*COS($U16) -> 1.1471529 | X16: =3*SIN($U16) -> 2.4574561 | Y16: =3*COS($U16) -> 1.7207293 | Z16: =4*SIN($U16) -> 3.2766082 | AA16: =4*COS($U16) -> 2.2943057 | AB16: =5*SIN($U16) -> 4.0957602 | AC16: =5*COS($U16) -> 2.8678822 | AE16: =6.3*SIN(2*PI()*5/ROWS(codiciL1)) -> -6.1420458 | AF16: =6.3*COS(2*PI()*5/ROWS(codiciL1)) -> -1.4018819 | AL16: =IF(AND(ISNUMBER($F16),ISNUMBER($S16)),IF($F16=AL$4,$S16,NA()),NA()) -> #N/A | AM16: =IF(AND(ISNUMBER($F16),ISNUMBER($S16)),IF($F16=AM$4,$S16,NA()),NA()) -> #N/A | AN16: =IF(AND(ISNUMBER($F16),ISNUMBER($S16)),IF($F16=AN$4,$S16,NA()),NA()) -> #N/A | AO16: =IF(AND(ISNUMBER($F16),ISNUMBER($S16)),IF($F16=AO$4,$S16,NA()),NA()) -> #N/A | AP16: =IF(AND(ISNUMBER($F16),ISNUMBER($S16)),IF($F16=AP$4,$S16,NA()),NA()) -> #N/A | AQ16: =IF(AND(ISNUMBER($F16),ISNUMBER($S16)),IF($F16=AQ$4,$S16,NA()),NA()) -> #N/A | AR16: =IF(AND(ISNUMBER($F16),ISNUMBER($S16)),IF($F16=AR$4,$S16,NA()),NA()) -> #N/A | AS16: =IF(AND(ISNUMBER($F16),ISNUMBER($S16)),IF($F16=AS$4,$S16,NA()),NA()) -> #N/A | ... AY16: =IF(AND(ISNUMBER($F16),ISNUMBER($S16)),IF($F16=AY$4,$S16,NA()),NA()) -> #N/A
A17: =IF(Parametri!$H16="","",Parametri!$H16) | B17: =IF($A17="","",Parametri!$I16) | C17: =IF($A17="","",Parametri!$J16) | D17: =IF($A17="",NA(),IF(COUNTIFS(RR_ID_Rischio,$A17,RR_Ciclo,cicloCorrente)=0,NA(),SUMIFS(RR_Severity,RR_ID_Rischio,$A17,RR_Ciclo,cicloCorrente))) -> #N/A | E17: =IF($A17="",NA(),IF(COUNTIFS(RR_ID_Rischio,$A17,RR_Ciclo,cicloCorrente)=0,NA(),SUMIFS(RR_Probabilita,RR_ID_Rischio,$A17,RR_Ciclo,cicloCorrente))) -> #N/A | F17: =IF(AND(ISNUMBER(D17),ISNUMBER(E17)),D17*E17,NA()) -> #N/A | G17: =IF($A17="",NA(),IF(COUNTIFS(RR_ID_Rischio,$A17,RR_Ciclo,cicloCorrente)=0,NA(),SUMIFS(RR_Prossimita,RR_ID_Rischio,$A17,RR_Ciclo,cicloCorrente))) -> #N/A | H17: =IF(ISNUMBER(G17),INDEX(anniProssimita,G17),NA()) -> #N/A | I17: =IF($A17="",NA(),moscaX) -> #N/A | J17: =IF($A17="",NA(),IF(COUNTIFS(AZ_ID_Rischio,$A17,AZ_Ciclo,cicloCorrente,AZ_Stato,"<>Respinta",AZ_Mesi_Orizzonte,">0")=0,moscaYDefault,_xlfn.MAXIFS(AZ_Mesi_Orizzonte,AZ_ID_Rischio,$A17,AZ_Ciclo,cicloCorrente,AZ_Stato,"<>Respinta")/12)) -> #N/A | K17: =IF(AND(ISNUMBER(H17),ISNUMBER(J17)),H17-(I17+J17),NA()) -> #N/A | L17: =IF(NOT(ISNUMBER(K17)),"",IF(K17<0,"AGIRE ORA: X+Y > Z",IF(K17<1,"Agire entro l'anno","Margine "&ROUND(K17,1)&IF(ROUND(K17,1)=1," anno"," anni")))) | M17: =IF($A17="",NA(),MATCH(C17,codiciL1,0)-1) -> #N/A | N17: =IF($A17="",NA(),COUNTIF($C$4:C16,C17)) -> #N/A | O17: =IF($A17="",NA(),COUNTIF(ANA_Event_Type,C17)) -> #N/A | P17: =IF($A17="",NA(),2*PI()*(M17+(N17+0.5)/O17)/ROWS(codiciL1)) -> #N/A | Q17: =IF(ISNUMBER(K17),MAX(0.6,MIN(6,K17+2)),NA()) -> #N/A | R17: =IF(AND(ISNUMBER(Q17),ISNUMBER(P17)),Q17*SIN(P17),NA()) -> #N/A | S17: =IF(AND(ISNUMBER(Q17),ISNUMBER(P17)),Q17*COS(P17),NA()) -> #N/A | U17: =2*PI()*12/72 -> 1.0471976 | V17: =2*SIN($U17) -> 1.7320508 | W17: =2*COS($U17) -> 1 | X17: =3*SIN($U17) -> 2.5980762 | Y17: =3*COS($U17) -> 1.5 | Z17: =4*SIN($U17) -> 3.4641016 | AA17: =4*COS($U17) -> 2 | AB17: =5*SIN($U17) -> 4.330127 | AC17: =5*COS($U17) -> 2.5 | AE17: 0 | AF17: 0 | AL17: =IF(AND(ISNUMBER($F17),ISNUMBER($S17)),IF($F17=AL$4,$S17,NA()),NA()) -> #N/A | AM17: =IF(AND(ISNUMBER($F17),ISNUMBER($S17)),IF($F17=AM$4,$S17,NA()),NA()) -> #N/A | AN17: =IF(AND(ISNUMBER($F17),ISNUMBER($S17)),IF($F17=AN$4,$S17,NA()),NA()) -> #N/A | AO17: =IF(AND(ISNUMBER($F17),ISNUMBER($S17)),IF($F17=AO$4,$S17,NA()),NA()) -> #N/A | AP17: =IF(AND(ISNUMBER($F17),ISNUMBER($S17)),IF($F17=AP$4,$S17,NA()),NA()) -> #N/A | AQ17: =IF(AND(ISNUMBER($F17),ISNUMBER($S17)),IF($F17=AQ$4,$S17,NA()),NA()) -> #N/A | AR17: =IF(AND(ISNUMBER($F17),ISNUMBER($S17)),IF($F17=AR$4,$S17,NA()),NA()) -> #N/A | AS17: =IF(AND(ISNUMBER($F17),ISNUMBER($S17)),IF($F17=AS$4,$S17,NA()),NA()) -> #N/A | ... AY17: =IF(AND(ISNUMBER($F17),ISNUMBER($S17)),IF($F17=AY$4,$S17,NA()),NA()) -> #N/A
A18: =IF(Parametri!$H17="","",Parametri!$H17) | B18: =IF($A18="","",Parametri!$I17) | C18: =IF($A18="","",Parametri!$J17) | D18: =IF($A18="",NA(),IF(COUNTIFS(RR_ID_Rischio,$A18,RR_Ciclo,cicloCorrente)=0,NA(),SUMIFS(RR_Severity,RR_ID_Rischio,$A18,RR_Ciclo,cicloCorrente))) -> #N/A | E18: =IF($A18="",NA(),IF(COUNTIFS(RR_ID_Rischio,$A18,RR_Ciclo,cicloCorrente)=0,NA(),SUMIFS(RR_Probabilita,RR_ID_Rischio,$A18,RR_Ciclo,cicloCorrente))) -> #N/A | F18: =IF(AND(ISNUMBER(D18),ISNUMBER(E18)),D18*E18,NA()) -> #N/A | G18: =IF($A18="",NA(),IF(COUNTIFS(RR_ID_Rischio,$A18,RR_Ciclo,cicloCorrente)=0,NA(),SUMIFS(RR_Prossimita,RR_ID_Rischio,$A18,RR_Ciclo,cicloCorrente))) -> #N/A | H18: =IF(ISNUMBER(G18),INDEX(anniProssimita,G18),NA()) -> #N/A | I18: =IF($A18="",NA(),moscaX) -> #N/A | J18: =IF($A18="",NA(),IF(COUNTIFS(AZ_ID_Rischio,$A18,AZ_Ciclo,cicloCorrente,AZ_Stato,"<>Respinta",AZ_Mesi_Orizzonte,">0")=0,moscaYDefault,_xlfn.MAXIFS(AZ_Mesi_Orizzonte,AZ_ID_Rischio,$A18,AZ_Ciclo,cicloCorrente,AZ_Stato,"<>Respinta")/12)) -> #N/A | K18: =IF(AND(ISNUMBER(H18),ISNUMBER(J18)),H18-(I18+J18),NA()) -> #N/A | L18: =IF(NOT(ISNUMBER(K18)),"",IF(K18<0,"AGIRE ORA: X+Y > Z",IF(K18<1,"Agire entro l'anno","Margine "&ROUND(K18,1)&IF(ROUND(K18,1)=1," anno"," anni")))) | M18: =IF($A18="",NA(),MATCH(C18,codiciL1,0)-1) -> #N/A | N18: =IF($A18="",NA(),COUNTIF($C$4:C17,C18)) -> #N/A | O18: =IF($A18="",NA(),COUNTIF(ANA_Event_Type,C18)) -> #N/A | P18: =IF($A18="",NA(),2*PI()*(M18+(N18+0.5)/O18)/ROWS(codiciL1)) -> #N/A | Q18: =IF(ISNUMBER(K18),MAX(0.6,MIN(6,K18+2)),NA()) -> #N/A | R18: =IF(AND(ISNUMBER(Q18),ISNUMBER(P18)),Q18*SIN(P18),NA()) -> #N/A | S18: =IF(AND(ISNUMBER(Q18),ISNUMBER(P18)),Q18*COS(P18),NA()) -> #N/A | U18: =2*PI()*13/72 -> 1.134464 | V18: =2*SIN($U18) -> 1.8126156 | W18: =2*COS($U18) -> 0.84523652 | X18: =3*SIN($U18) -> 2.7189234 | Y18: =3*COS($U18) -> 1.2678548 | Z18: =4*SIN($U18) -> 3.6252311 | AA18: =4*COS($U18) -> 1.690473 | AB18: =5*SIN($U18) -> 4.5315389 | AC18: =5*COS($U18) -> 2.1130913 | AE18: =6.3*SIN(2*PI()*6/ROWS(codiciL1)) -> -4.9255383 | AF18: =6.3*COS(2*PI()*6/ROWS(codiciL1)) -> 3.9279858 | AL18: =IF(AND(ISNUMBER($F18),ISNUMBER($S18)),IF($F18=AL$4,$S18,NA()),NA()) -> #N/A | AM18: =IF(AND(ISNUMBER($F18),ISNUMBER($S18)),IF($F18=AM$4,$S18,NA()),NA()) -> #N/A | AN18: =IF(AND(ISNUMBER($F18),ISNUMBER($S18)),IF($F18=AN$4,$S18,NA()),NA()) -> #N/A | AO18: =IF(AND(ISNUMBER($F18),ISNUMBER($S18)),IF($F18=AO$4,$S18,NA()),NA()) -> #N/A | AP18: =IF(AND(ISNUMBER($F18),ISNUMBER($S18)),IF($F18=AP$4,$S18,NA()),NA()) -> #N/A | AQ18: =IF(AND(ISNUMBER($F18),ISNUMBER($S18)),IF($F18=AQ$4,$S18,NA()),NA()) -> #N/A | AR18: =IF(AND(ISNUMBER($F18),ISNUMBER($S18)),IF($F18=AR$4,$S18,NA()),NA()) -> #N/A | AS18: =IF(AND(ISNUMBER($F18),ISNUMBER($S18)),IF($F18=AS$4,$S18,NA()),NA()) -> #N/A | ... AY18: =IF(AND(ISNUMBER($F18),ISNUMBER($S18)),IF($F18=AY$4,$S18,NA()),NA()) -> #N/A
A19: =IF(Parametri!$H18="","",Parametri!$H18) | B19: =IF($A19="","",Parametri!$I18) | C19: =IF($A19="","",Parametri!$J18) | D19: =IF($A19="",NA(),IF(COUNTIFS(RR_ID_Rischio,$A19,RR_Ciclo,cicloCorrente)=0,NA(),SUMIFS(RR_Severity,RR_ID_Rischio,$A19,RR_Ciclo,cicloCorrente))) -> #N/A | E19: =IF($A19="",NA(),IF(COUNTIFS(RR_ID_Rischio,$A19,RR_Ciclo,cicloCorrente)=0,NA(),SUMIFS(RR_Probabilita,RR_ID_Rischio,$A19,RR_Ciclo,cicloCorrente))) -> #N/A | F19: =IF(AND(ISNUMBER(D19),ISNUMBER(E19)),D19*E19,NA()) -> #N/A | G19: =IF($A19="",NA(),IF(COUNTIFS(RR_ID_Rischio,$A19,RR_Ciclo,cicloCorrente)=0,NA(),SUMIFS(RR_Prossimita,RR_ID_Rischio,$A19,RR_Ciclo,cicloCorrente))) -> #N/A | H19: =IF(ISNUMBER(G19),INDEX(anniProssimita,G19),NA()) -> #N/A | I19: =IF($A19="",NA(),moscaX) -> #N/A | J19: =IF($A19="",NA(),IF(COUNTIFS(AZ_ID_Rischio,$A19,AZ_Ciclo,cicloCorrente,AZ_Stato,"<>Respinta",AZ_Mesi_Orizzonte,">0")=0,moscaYDefault,_xlfn.MAXIFS(AZ_Mesi_Orizzonte,AZ_ID_Rischio,$A19,AZ_Ciclo,cicloCorrente,AZ_Stato,"<>Respinta")/12)) -> #N/A | K19: =IF(AND(ISNUMBER(H19),ISNUMBER(J19)),H19-(I19+J19),NA()) -> #N/A | L19: =IF(NOT(ISNUMBER(K19)),"",IF(K19<0,"AGIRE ORA: X+Y > Z",IF(K19<1,"Agire entro l'anno","Margine "&ROUND(K19,1)&IF(ROUND(K19,1)=1," anno"," anni")))) | M19: =IF($A19="",NA(),MATCH(C19,codiciL1,0)-1) -> #N/A | N19: =IF($A19="",NA(),COUNTIF($C$4:C18,C19)) -> #N/A | O19: =IF($A19="",NA(),COUNTIF(ANA_Event_Type,C19)) -> #N/A | P19: =IF($A19="",NA(),2*PI()*(M19+(N19+0.5)/O19)/ROWS(codiciL1)) -> #N/A | Q19: =IF(ISNUMBER(K19),MAX(0.6,MIN(6,K19+2)),NA()) -> #N/A | R19: =IF(AND(ISNUMBER(Q19),ISNUMBER(P19)),Q19*SIN(P19),NA()) -> #N/A | S19: =IF(AND(ISNUMBER(Q19),ISNUMBER(P19)),Q19*COS(P19),NA()) -> #N/A | U19: =2*PI()*14/72 -> 1.2217305 | V19: =2*SIN($U19) -> 1.8793852 | W19: =2*COS($U19) -> 0.68404029 | X19: =3*SIN($U19) -> 2.8190779 | Y19: =3*COS($U19) -> 1.0260604 | Z19: =4*SIN($U19) -> 3.7587705 | AA19: =4*COS($U19) -> 1.3680806 | AB19: =5*SIN($U19) -> 4.6984631 | AC19: =5*COS($U19) -> 1.7101007 | AL19: =IF(AND(ISNUMBER($F19),ISNUMBER($S19)),IF($F19=AL$4,$S19,NA()),NA()) -> #N/A | AM19: =IF(AND(ISNUMBER($F19),ISNUMBER($S19)),IF($F19=AM$4,$S19,NA()),NA()) -> #N/A | AN19: =IF(AND(ISNUMBER($F19),ISNUMBER($S19)),IF($F19=AN$4,$S19,NA()),NA()) -> #N/A | AO19: =IF(AND(ISNUMBER($F19),ISNUMBER($S19)),IF($F19=AO$4,$S19,NA()),NA()) -> #N/A | AP19: =IF(AND(ISNUMBER($F19),ISNUMBER($S19)),IF($F19=AP$4,$S19,NA()),NA()) -> #N/A | AQ19: =IF(AND(ISNUMBER($F19),ISNUMBER($S19)),IF($F19=AQ$4,$S19,NA()),NA()) -> #N/A | AR19: =IF(AND(ISNUMBER($F19),ISNUMBER($S19)),IF($F19=AR$4,$S19,NA()),NA()) -> #N/A | AS19: =IF(AND(ISNUMBER($F19),ISNUMBER($S19)),IF($F19=AS$4,$S19,NA()),NA()) -> #N/A | ... AY19: =IF(AND(ISNUMBER($F19),ISNUMBER($S19)),IF($F19=AY$4,$S19,NA()),NA()) -> #N/A
U20: =2*PI()*15/72 -> 1.3089969 | V20: =2*SIN($U20) -> 1.9318517 | W20: =2*COS($U20) -> 0.51763809 | X20: =3*SIN($U20) -> 2.8977775 | Y20: =3*COS($U20) -> 0.77645714 | Z20: =4*SIN($U20) -> 3.8637033 | AA20: =4*COS($U20) -> 1.0352762 | AB20: =5*SIN($U20) -> 4.8296291 | AC20: =5*COS($U20) -> 1.2940952
A21: Come si legge: cerchio ROSSO = linea di Mosca, dentro si e' gia' in ritardo (X + Y > Z). Cerchi grigi = 1, 2 e 3 anni di margine. Area del cerchio di un rischio = Probabilita x Severity. Settori = event type. | U21: =2*PI()*16/72 -> 1.3962634 | V21: =2*SIN($U21) -> 1.9696155 | W21: =2*COS($U21) -> 0.34729636 | X21: =3*SIN($U21) -> 2.9544233 | Y21: =3*COS($U21) -> 0.52094453 | Z21: =4*SIN($U21) -> 3.939231 | AA21: =4*COS($U21) -> 0.69459271 | AB21: =5*SIN($U21) -> 4.9240388 | AC21: =5*COS($U21) -> 0.86824089
U22: =2*PI()*17/72 -> 1.4835299 | V22: =2*SIN($U22) -> 1.9923894 | W22: =2*COS($U22) -> 0.17431149 | X22: =3*SIN($U22) -> 2.9885841 | Y22: =3*COS($U22) -> 0.26146723 | Z22: =4*SIN($U22) -> 3.9847788 | AA22: =4*COS($U22) -> 0.34862297 | AB22: =5*SIN($U22) -> 4.9809735 | AC22: =5*COS($U22) -> 0.43577871
U23: =2*PI()*18/72 -> 1.5707963 | V23: =2*SIN($U23) -> 2 | W23: =2*COS($U23) -> 1.2251485e-16 | X23: =3*SIN($U23) -> 3 | Y23: =3*COS($U23) -> 1.8377227e-16 | Z23: =4*SIN($U23) -> 4 | AA23: =4*COS($U23) -> 2.4502969e-16 | AB23: =5*SIN($U23) -> 5 | AC23: =5*COS($U23) -> 3.0628711e-16
U24: =2*PI()*19/72 -> 1.6580628 | V24: =2*SIN($U24) -> 1.9923894 | W24: =2*COS($U24) -> -0.17431149 | X24: =3*SIN($U24) -> 2.9885841 | Y24: =3*COS($U24) -> -0.26146723 | Z24: =4*SIN($U24) -> 3.9847788 | AA24: =4*COS($U24) -> -0.34862297 | AB24: =5*SIN($U24) -> 4.9809735 | AC24: =5*COS($U24) -> -0.43577871
U25: =2*PI()*20/72 -> 1.7453293 | V25: =2*SIN($U25) -> 1.9696155 | W25: =2*COS($U25) -> -0.34729636 | X25: =3*SIN($U25) -> 2.9544233 | Y25: =3*COS($U25) -> -0.52094453 | Z25: =4*SIN($U25) -> 3.939231 | AA25: =4*COS($U25) -> -0.69459271 | AB25: =5*SIN($U25) -> 4.9240388 | AC25: =5*COS($U25) -> -0.86824089
U26: =2*PI()*21/72 -> 1.8325957 | V26: =2*SIN($U26) -> 1.9318517 | W26: =2*COS($U26) -> -0.51763809 | X26: =3*SIN($U26) -> 2.8977775 | Y26: =3*COS($U26) -> -0.77645714 | Z26: =4*SIN($U26) -> 3.8637033 | AA26: =4*COS($U26) -> -1.0352762 | AB26: =5*SIN($U26) -> 4.8296291 | AC26: =5*COS($U26) -> -1.2940952
U27: =2*PI()*22/72 -> 1.9198622 | V27: =2*SIN($U27) -> 1.8793852 | W27: =2*COS($U27) -> -0.68404029 | X27: =3*SIN($U27) -> 2.8190779 | Y27: =3*COS($U27) -> -1.0260604 | Z27: =4*SIN($U27) -> 3.7587705 | AA27: =4*COS($U27) -> -1.3680806 | AB27: =5*SIN($U27) -> 4.6984631 | AC27: =5*COS($U27) -> -1.7101007
U28: =2*PI()*23/72 -> 2.0071286 | V28: =2*SIN($U28) -> 1.8126156 | W28: =2*COS($U28) -> -0.84523652 | X28: =3*SIN($U28) -> 2.7189234 | Y28: =3*COS($U28) -> -1.2678548 | Z28: =4*SIN($U28) -> 3.6252311 | AA28: =4*COS($U28) -> -1.690473 | AB28: =5*SIN($U28) -> 4.5315389 | AC28: =5*COS($U28) -> -2.1130913
U29: =2*PI()*24/72 -> 2.0943951 | V29: =2*SIN($U29) -> 1.7320508 | W29: =2*COS($U29) -> -1 | X29: =3*SIN($U29) -> 2.5980762 | Y29: =3*COS($U29) -> -1.5 | Z29: =4*SIN($U29) -> 3.4641016 | AA29: =4*COS($U29) -> -2 | AB29: =5*SIN($U29) -> 4.330127 | AC29: =5*COS($U29) -> -2.5
U30: =2*PI()*25/72 -> 2.1816616 | V30: =2*SIN($U30) -> 1.6383041 | W30: =2*COS($U30) -> -1.1471529 | X30: =3*SIN($U30) -> 2.4574561 | Y30: =3*COS($U30) -> -1.7207293 | Z30: =4*SIN($U30) -> 3.2766082 | AA30: =4*COS($U30) -> -2.2943057 | AB30: =5*SIN($U30) -> 4.0957602 | AC30: =5*COS($U30) -> -2.8678822
U31: =2*PI()*26/72 -> 2.268928 | V31: =2*SIN($U31) -> 1.5320889 | W31: =2*COS($U31) -> -1.2855752 | X31: =3*SIN($U31) -> 2.2981333 | Y31: =3*COS($U31) -> -1.9283628 | Z31: =4*SIN($U31) -> 3.0641778 | AA31: =4*COS($U31) -> -2.5711504 | AB31: =5*SIN($U31) -> 3.8302222 | AC31: =5*COS($U31) -> -3.213938
U32: =2*PI()*27/72 -> 2.3561945 | V32: =2*SIN($U32) -> 1.4142136 | W32: =2*COS($U32) -> -1.4142136 | X32: =3*SIN($U32) -> 2.1213203 | Y32: =3*COS($U32) -> -2.1213203 | Z32: =4*SIN($U32) -> 2.8284271 | AA32: =4*COS($U32) -> -2.8284271 | AB32: =5*SIN($U32) -> 3.5355339 | AC32: =5*COS($U32) -> -3.5355339
U33: =2*PI()*28/72 -> 2.443461 | V33: =2*SIN($U33) -> 1.2855752 | W33: =2*COS($U33) -> -1.5320889 | X33: =3*SIN($U33) -> 1.9283628 | Y33: =3*COS($U33) -> -2.2981333 | Z33: =4*SIN($U33) -> 2.5711504 | AA33: =4*COS($U33) -> -3.0641778 | AB33: =5*SIN($U33) -> 3.213938 | AC33: =5*COS($U33) -> -3.8302222
U34: =2*PI()*29/72 -> 2.5307274 | V34: =2*SIN($U34) -> 1.1471529 | W34: =2*COS($U34) -> -1.6383041 | X34: =3*SIN($U34) -> 1.7207293 | Y34: =3*COS($U34) -> -2.4574561 | Z34: =4*SIN($U34) -> 2.2943057 | AA34: =4*COS($U34) -> -3.2766082 | AB34: =5*SIN($U34) -> 2.8678822 | AC34: =5*COS($U34) -> -4.0957602
U35: =2*PI()*30/72 -> 2.6179939 | V35: =2*SIN($U35) -> 1 | W35: =2*COS($U35) -> -1.7320508 | X35: =3*SIN($U35) -> 1.5 | Y35: =3*COS($U35) -> -2.5980762 | Z35: =4*SIN($U35) -> 2 | AA35: =4*COS($U35) -> -3.4641016 | AB35: =5*SIN($U35) -> 2.5 | AC35: =5*COS($U35) -> -4.330127
U36: =2*PI()*31/72 -> 2.7052603 | V36: =2*SIN($U36) -> 0.84523652 | W36: =2*COS($U36) -> -1.8126156 | X36: =3*SIN($U36) -> 1.2678548 | Y36: =3*COS($U36) -> -2.7189234 | Z36: =4*SIN($U36) -> 1.690473 | AA36: =4*COS($U36) -> -3.6252311 | AB36: =5*SIN($U36) -> 2.1130913 | AC36: =5*COS($U36) -> -4.5315389
U37: =2*PI()*32/72 -> 2.7925268 | V37: =2*SIN($U37) -> 0.68404029 | W37: =2*COS($U37) -> -1.8793852 | X37: =3*SIN($U37) -> 1.0260604 | Y37: =3*COS($U37) -> -2.8190779 | Z37: =4*SIN($U37) -> 1.3680806 | AA37: =4*COS($U37) -> -3.7587705 | AB37: =5*SIN($U37) -> 1.7101007 | AC37: =5*COS($U37) -> -4.6984631
U38: =2*PI()*33/72 -> 2.8797933 | V38: =2*SIN($U38) -> 0.51763809 | W38: =2*COS($U38) -> -1.9318517 | X38: =3*SIN($U38) -> 0.77645714 | Y38: =3*COS($U38) -> -2.8977775 | Z38: =4*SIN($U38) -> 1.0352762 | AA38: =4*COS($U38) -> -3.8637033 | AB38: =5*SIN($U38) -> 1.2940952 | AC38: =5*COS($U38) -> -4.8296291
U39: =2*PI()*34/72 -> 2.9670597 | V39: =2*SIN($U39) -> 0.34729636 | W39: =2*COS($U39) -> -1.9696155 | X39: =3*SIN($U39) -> 0.52094453 | Y39: =3*COS($U39) -> -2.9544233 | Z39: =4*SIN($U39) -> 0.69459271 | AA39: =4*COS($U39) -> -3.939231 | AB39: =5*SIN($U39) -> 0.86824089 | AC39: =5*COS($U39) -> -4.9240388
U40: =2*PI()*35/72 -> 3.0543262 | V40: =2*SIN($U40) -> 0.17431149 | W40: =2*COS($U40) -> -1.9923894 | X40: =3*SIN($U40) -> 0.26146723 | Y40: =3*COS($U40) -> -2.9885841 | Z40: =4*SIN($U40) -> 0.34862297 | AA40: =4*COS($U40) -> -3.9847788 | AB40: =5*SIN($U40) -> 0.43577871 | AC40: =5*COS($U40) -> -4.9809735
U41: =2*PI()*36/72 -> 3.1415927 | V41: =2*SIN($U41) -> 2.4502969e-16 | W41: =2*COS($U41) -> -2 | X41: =3*SIN($U41) -> 3.6754454e-16 | Y41: =3*COS($U41) -> -3 | Z41: =4*SIN($U41) -> 4.9005938e-16 | AA41: =4*COS($U41) -> -4 | AB41: =5*SIN($U41) -> 6.1257423e-16 | AC41: =5*COS($U41) -> -5
U42: =2*PI()*37/72 -> 3.2288591 | V42: =2*SIN($U42) -> -0.17431149 | W42: =2*COS($U42) -> -1.9923894 | X42: =3*SIN($U42) -> -0.26146723 | Y42: =3*COS($U42) -> -2.9885841 | Z42: =4*SIN($U42) -> -0.34862297 | AA42: =4*COS($U42) -> -3.9847788 | AB42: =5*SIN($U42) -> -0.43577871 | AC42: =5*COS($U42) -> -4.9809735
U43: =2*PI()*38/72 -> 3.3161256 | V43: =2*SIN($U43) -> -0.34729636 | W43: =2*COS($U43) -> -1.9696155 | X43: =3*SIN($U43) -> -0.52094453 | Y43: =3*COS($U43) -> -2.9544233 | Z43: =4*SIN($U43) -> -0.69459271 | AA43: =4*COS($U43) -> -3.939231 | AB43: =5*SIN($U43) -> -0.86824089 | AC43: =5*COS($U43) -> -4.9240388
U44: =2*PI()*39/72 -> 3.403392 | V44: =2*SIN($U44) -> -0.51763809 | W44: =2*COS($U44) -> -1.9318517 | X44: =3*SIN($U44) -> -0.77645714 | Y44: =3*COS($U44) -> -2.8977775 | Z44: =4*SIN($U44) -> -1.0352762 | AA44: =4*COS($U44) -> -3.8637033 | AB44: =5*SIN($U44) -> -1.2940952 | AC44: =5*COS($U44) -> -4.8296291
U45: =2*PI()*40/72 -> 3.4906585 | V45: =2*SIN($U45) -> -0.68404029 | W45: =2*COS($U45) -> -1.8793852 | X45: =3*SIN($U45) -> -1.0260604 | Y45: =3*COS($U45) -> -2.8190779 | Z45: =4*SIN($U45) -> -1.3680806 | AA45: =4*COS($U45) -> -3.7587705 | AB45: =5*SIN($U45) -> -1.7101007 | AC45: =5*COS($U45) -> -4.6984631
U46: =2*PI()*41/72 -> 3.577925 | V46: =2*SIN($U46) -> -0.84523652 | W46: =2*COS($U46) -> -1.8126156 | X46: =3*SIN($U46) -> -1.2678548 | Y46: =3*COS($U46) -> -2.7189234 | Z46: =4*SIN($U46) -> -1.690473 | AA46: =4*COS($U46) -> -3.6252311 | AB46: =5*SIN($U46) -> -2.1130913 | AC46: =5*COS($U46) -> -4.5315389
U47: =2*PI()*42/72 -> 3.6651914 | V47: =2*SIN($U47) -> -1 | W47: =2*COS($U47) -> -1.7320508 | X47: =3*SIN($U47) -> -1.5 | Y47: =3*COS($U47) -> -2.5980762 | Z47: =4*SIN($U47) -> -2 | AA47: =4*COS($U47) -> -3.4641016 | AB47: =5*SIN($U47) -> -2.5 | AC47: =5*COS($U47) -> -4.330127
U48: =2*PI()*43/72 -> 3.7524579 | V48: =2*SIN($U48) -> -1.1471529 | W48: =2*COS($U48) -> -1.6383041 | X48: =3*SIN($U48) -> -1.7207293 | Y48: =3*COS($U48) -> -2.4574561 | Z48: =4*SIN($U48) -> -2.2943057 | AA48: =4*COS($U48) -> -3.2766082 | AB48: =5*SIN($U48) -> -2.8678822 | AC48: =5*COS($U48) -> -4.0957602
U49: =2*PI()*44/72 -> 3.8397244 | V49: =2*SIN($U49) -> -1.2855752 | W49: =2*COS($U49) -> -1.5320889 | X49: =3*SIN($U49) -> -1.9283628 | Y49: =3*COS($U49) -> -2.2981333 | Z49: =4*SIN($U49) -> -2.5711504 | AA49: =4*COS($U49) -> -3.0641778 | AB49: =5*SIN($U49) -> -3.213938 | AC49: =5*COS($U49) -> -3.8302222
U50: =2*PI()*45/72 -> 3.9269908 | V50: =2*SIN($U50) -> -1.4142136 | W50: =2*COS($U50) -> -1.4142136 | X50: =3*SIN($U50) -> -2.1213203 | Y50: =3*COS($U50) -> -2.1213203 | Z50: =4*SIN($U50) -> -2.8284271 | AA50: =4*COS($U50) -> -2.8284271 | AB50: =5*SIN($U50) -> -3.5355339 | AC50: =5*COS($U50) -> -3.5355339
U51: =2*PI()*46/72 -> 4.0142573 | V51: =2*SIN($U51) -> -1.5320889 | W51: =2*COS($U51) -> -1.2855752 | X51: =3*SIN($U51) -> -2.2981333 | Y51: =3*COS($U51) -> -1.9283628 | Z51: =4*SIN($U51) -> -3.0641778 | AA51: =4*COS($U51) -> -2.5711504 | AB51: =5*SIN($U51) -> -3.8302222 | AC51: =5*COS($U51) -> -3.213938
U52: =2*PI()*47/72 -> 4.1015237 | V52: =2*SIN($U52) -> -1.6383041 | W52: =2*COS($U52) -> -1.1471529 | X52: =3*SIN($U52) -> -2.4574561 | Y52: =3*COS($U52) -> -1.7207293 | Z52: =4*SIN($U52) -> -3.2766082 | AA52: =4*COS($U52) -> -2.2943057 | AB52: =5*SIN($U52) -> -4.0957602 | AC52: =5*COS($U52) -> -2.8678822
U53: =2*PI()*48/72 -> 4.1887902 | V53: =2*SIN($U53) -> -1.7320508 | W53: =2*COS($U53) -> -1 | X53: =3*SIN($U53) -> -2.5980762 | Y53: =3*COS($U53) -> -1.5 | Z53: =4*SIN($U53) -> -3.4641016 | AA53: =4*COS($U53) -> -2 | AB53: =5*SIN($U53) -> -4.330127 | AC53: =5*COS($U53) -> -2.5
U54: =2*PI()*49/72 -> 4.2760567 | V54: =2*SIN($U54) -> -1.8126156 | W54: =2*COS($U54) -> -0.84523652 | X54: =3*SIN($U54) -> -2.7189234 | Y54: =3*COS($U54) -> -1.2678548 | Z54: =4*SIN($U54) -> -3.6252311 | AA54: =4*COS($U54) -> -1.690473 | AB54: =5*SIN($U54) -> -4.5315389 | AC54: =5*COS($U54) -> -2.1130913
U55: =2*PI()*50/72 -> 4.3633231 | V55: =2*SIN($U55) -> -1.8793852 | W55: =2*COS($U55) -> -0.68404029 | X55: =3*SIN($U55) -> -2.8190779 | Y55: =3*COS($U55) -> -1.0260604 | Z55: =4*SIN($U55) -> -3.7587705 | AA55: =4*COS($U55) -> -1.3680806 | AB55: =5*SIN($U55) -> -4.6984631 | AC55: =5*COS($U55) -> -1.7101007
U56: =2*PI()*51/72 -> 4.4505896 | V56: =2*SIN($U56) -> -1.9318517 | W56: =2*COS($U56) -> -0.51763809 | X56: =3*SIN($U56) -> -2.8977775 | Y56: =3*COS($U56) -> -0.77645714 | Z56: =4*SIN($U56) -> -3.8637033 | AA56: =4*COS($U56) -> -1.0352762 | AB56: =5*SIN($U56) -> -4.8296291 | AC56: =5*COS($U56) -> -1.2940952
U57: =2*PI()*52/72 -> 4.5378561 | V57: =2*SIN($U57) -> -1.9696155 | W57: =2*COS($U57) -> -0.34729636 | X57: =3*SIN($U57) -> -2.9544233 | Y57: =3*COS($U57) -> -0.52094453 | Z57: =4*SIN($U57) -> -3.939231 | AA57: =4*COS($U57) -> -0.69459271 | AB57: =5*SIN($U57) -> -4.9240388 | AC57: =5*COS($U57) -> -0.86824089
U58: =2*PI()*53/72 -> 4.6251225 | V58: =2*SIN($U58) -> -1.9923894 | W58: =2*COS($U58) -> -0.17431149 | X58: =3*SIN($U58) -> -2.9885841 | Y58: =3*COS($U58) -> -0.26146723 | Z58: =4*SIN($U58) -> -3.9847788 | AA58: =4*COS($U58) -> -0.34862297 | AB58: =5*SIN($U58) -> -4.9809735 | AC58: =5*COS($U58) -> -0.43577871
U59: =2*PI()*54/72 -> 4.712389 | V59: =2*SIN($U59) -> -2 | W59: =2*COS($U59) -> -3.6754454e-16 | X59: =3*SIN($U59) -> -3 | Y59: =3*COS($U59) -> -5.513168e-16 | Z59: =4*SIN($U59) -> -4 | AA59: =4*COS($U59) -> -7.3508907e-16 | AB59: =5*SIN($U59) -> -5 | AC59: =5*COS($U59) -> -9.1886134e-16
U60: =2*PI()*55/72 -> 4.7996554 | V60: =2*SIN($U60) -> -1.9923894 | W60: =2*COS($U60) -> 0.17431149 | X60: =3*SIN($U60) -> -2.9885841 | Y60: =3*COS($U60) -> 0.26146723 | Z60: =4*SIN($U60) -> -3.9847788 | AA60: =4*COS($U60) -> 0.34862297 | AB60: =5*SIN($U60) -> -4.9809735 | AC60: =5*COS($U60) -> 0.43577871
U61: =2*PI()*56/72 -> 4.8869219 | V61: =2*SIN($U61) -> -1.9696155 | W61: =2*COS($U61) -> 0.34729636 | X61: =3*SIN($U61) -> -2.9544233 | Y61: =3*COS($U61) -> 0.52094453 | Z61: =4*SIN($U61) -> -3.939231 | AA61: =4*COS($U61) -> 0.69459271 | AB61: =5*SIN($U61) -> -4.9240388 | AC61: =5*COS($U61) -> 0.86824089
U62: =2*PI()*57/72 -> 4.9741884 | V62: =2*SIN($U62) -> -1.9318517 | W62: =2*COS($U62) -> 0.51763809 | X62: =3*SIN($U62) -> -2.8977775 | Y62: =3*COS($U62) -> 0.77645714 | Z62: =4*SIN($U62) -> -3.8637033 | AA62: =4*COS($U62) -> 1.0352762 | AB62: =5*SIN($U62) -> -4.8296291 | AC62: =5*COS($U62) -> 1.2940952
U63: =2*PI()*58/72 -> 5.0614548 | V63: =2*SIN($U63) -> -1.8793852 | W63: =2*COS($U63) -> 0.68404029 | X63: =3*SIN($U63) -> -2.8190779 | Y63: =3*COS($U63) -> 1.0260604 | Z63: =4*SIN($U63) -> -3.7587705 | AA63: =4*COS($U63) -> 1.3680806 | AB63: =5*SIN($U63) -> -4.6984631 | AC63: =5*COS($U63) -> 1.7101007
U64: =2*PI()*59/72 -> 5.1487213 | V64: =2*SIN($U64) -> -1.8126156 | W64: =2*COS($U64) -> 0.84523652 | X64: =3*SIN($U64) -> -2.7189234 | Y64: =3*COS($U64) -> 1.2678548 | Z64: =4*SIN($U64) -> -3.6252311 | AA64: =4*COS($U64) -> 1.690473 | AB64: =5*SIN($U64) -> -4.5315389 | AC64: =5*COS($U64) -> 2.1130913
U65: =2*PI()*60/72 -> 5.2359878 | V65: =2*SIN($U65) -> -1.7320508 | W65: =2*COS($U65) -> 1 | X65: =3*SIN($U65) -> -2.5980762 | Y65: =3*COS($U65) -> 1.5 | Z65: =4*SIN($U65) -> -3.4641016 | AA65: =4*COS($U65) -> 2 | AB65: =5*SIN($U65) -> -4.330127 | AC65: =5*COS($U65) -> 2.5
U66: =2*PI()*61/72 -> 5.3232542 | V66: =2*SIN($U66) -> -1.6383041 | W66: =2*COS($U66) -> 1.1471529 | X66: =3*SIN($U66) -> -2.4574561 | Y66: =3*COS($U66) -> 1.7207293 | Z66: =4*SIN($U66) -> -3.2766082 | AA66: =4*COS($U66) -> 2.2943057 | AB66: =5*SIN($U66) -> -4.0957602 | AC66: =5*COS($U66) -> 2.8678822
U67: =2*PI()*62/72 -> 5.4105207 | V67: =2*SIN($U67) -> -1.5320889 | W67: =2*COS($U67) -> 1.2855752 | X67: =3*SIN($U67) -> -2.2981333 | Y67: =3*COS($U67) -> 1.9283628 | Z67: =4*SIN($U67) -> -3.0641778 | AA67: =4*COS($U67) -> 2.5711504 | AB67: =5*SIN($U67) -> -3.8302222 | AC67: =5*COS($U67) -> 3.213938
U68: =2*PI()*63/72 -> 5.4977871 | V68: =2*SIN($U68) -> -1.4142136 | W68: =2*COS($U68) -> 1.4142136 | X68: =3*SIN($U68) -> -2.1213203 | Y68: =3*COS($U68) -> 2.1213203 | Z68: =4*SIN($U68) -> -2.8284271 | AA68: =4*COS($U68) -> 2.8284271 | AB68: =5*SIN($U68) -> -3.5355339 | AC68: =5*COS($U68) -> 3.5355339
U69: =2*PI()*64/72 -> 5.5850536 | V69: =2*SIN($U69) -> -1.2855752 | W69: =2*COS($U69) -> 1.5320889 | X69: =3*SIN($U69) -> -1.9283628 | Y69: =3*COS($U69) -> 2.2981333 | Z69: =4*SIN($U69) -> -2.5711504 | AA69: =4*COS($U69) -> 3.0641778 | AB69: =5*SIN($U69) -> -3.213938 | AC69: =5*COS($U69) -> 3.8302222
U70: =2*PI()*65/72 -> 5.6723201 | V70: =2*SIN($U70) -> -1.1471529 | W70: =2*COS($U70) -> 1.6383041 | X70: =3*SIN($U70) -> -1.7207293 | Y70: =3*COS($U70) -> 2.4574561 | Z70: =4*SIN($U70) -> -2.2943057 | AA70: =4*COS($U70) -> 3.2766082 | AB70: =5*SIN($U70) -> -2.8678822 | AC70: =5*COS($U70) -> 4.0957602
U71: =2*PI()*66/72 -> 5.7595865 | V71: =2*SIN($U71) -> -1 | W71: =2*COS($U71) -> 1.7320508 | X71: =3*SIN($U71) -> -1.5 | Y71: =3*COS($U71) -> 2.5980762 | Z71: =4*SIN($U71) -> -2 | AA71: =4*COS($U71) -> 3.4641016 | AB71: =5*SIN($U71) -> -2.5 | AC71: =5*COS($U71) -> 4.330127
U72: =2*PI()*67/72 -> 5.846853 | V72: =2*SIN($U72) -> -0.84523652 | W72: =2*COS($U72) -> 1.8126156 | X72: =3*SIN($U72) -> -1.2678548 | Y72: =3*COS($U72) -> 2.7189234 | Z72: =4*SIN($U72) -> -1.690473 | AA72: =4*COS($U72) -> 3.6252311 | AB72: =5*SIN($U72) -> -2.1130913 | AC72: =5*COS($U72) -> 4.5315389
U73: =2*PI()*68/72 -> 5.9341195 | V73: =2*SIN($U73) -> -0.68404029 | W73: =2*COS($U73) -> 1.8793852 | X73: =3*SIN($U73) -> -1.0260604 | Y73: =3*COS($U73) -> 2.8190779 | Z73: =4*SIN($U73) -> -1.3680806 | AA73: =4*COS($U73) -> 3.7587705 | AB73: =5*SIN($U73) -> -1.7101007 | AC73: =5*COS($U73) -> 4.6984631
U74: =2*PI()*69/72 -> 6.0213859 | V74: =2*SIN($U74) -> -0.51763809 | W74: =2*COS($U74) -> 1.9318517 | X74: =3*SIN($U74) -> -0.77645714 | Y74: =3*COS($U74) -> 2.8977775 | Z74: =4*SIN($U74) -> -1.0352762 | AA74: =4*COS($U74) -> 3.8637033 | AB74: =5*SIN($U74) -> -1.2940952 | AC74: =5*COS($U74) -> 4.8296291
U75: =2*PI()*70/72 -> 6.1086524 | V75: =2*SIN($U75) -> -0.34729636 | W75: =2*COS($U75) -> 1.9696155 | X75: =3*SIN($U75) -> -0.52094453 | Y75: =3*COS($U75) -> 2.9544233 | Z75: =4*SIN($U75) -> -0.69459271 | AA75: =4*COS($U75) -> 3.939231 | AB75: =5*SIN($U75) -> -0.86824089 | AC75: =5*COS($U75) -> 4.9240388
U76: =2*PI()*71/72 -> 6.1959188 | V76: =2*SIN($U76) -> -0.17431149 | W76: =2*COS($U76) -> 1.9923894 | X76: =3*SIN($U76) -> -0.26146723 | Y76: =3*COS($U76) -> 2.9885841 | Z76: =4*SIN($U76) -> -0.34862297 | AA76: =4*COS($U76) -> 3.9847788 | AB76: =5*SIN($U76) -> -0.43577871 | AC76: =5*COS($U76) -> 4.9809735
U77: =2*PI()*72/72 -> 6.2831853 | V77: =2*SIN($U77) -> -4.9005938e-16 | W77: =2*COS($U77) -> 2 | X77: =3*SIN($U77) -> -7.3508907e-16 | Y77: =3*COS($U77) -> 3 | Z77: =4*SIN($U77) -> -9.8011876e-16 | AA77: =4*COS($U77) -> 4 | AB77: =5*SIN($U77) -> -1.2251485e-15 | AC77: =5*COS($U77) -> 5

Sheet Validazione
A1: Periodo | B1: Oggetto | C1: ID | D1: Nome | E1: Campo | F1: Proposta_Agente | G1: Decisione | H1: Valore_Validato | I1: Motivazione | J1: Validato_Da | K1: Data_Validazione | L1: Stato | N1: VALIDAZIONE — qui la persona che valida accetta o corregge cio' che hanno proposto gli agenti.
A2: 2026-10-12 | B2: Notizia | C2: N-20261006-01 | D2: Sciopero nazionale del personale bancario e carenza di tecnici IT | E2: Rischio_ID | F2: NON PRESIDIATO | G2: Accettato | H2: NON PRESIDIATO | I2: Accettato in blocco (--accetta-il-resto) | J2: Corrado | K2: 46290 | L2: Applicata | N2: COME SI USA (dopo ogni ciclo trimestrale, e se si vuole dopo ogni settimana):
A3: 2026-10-12 | B3: Notizia | C3: N-20261006-01 | D3: Sciopero nazionale del personale bancario e carenza di tecnici IT | E3: Segnale | F3: Peggiorativo | G3: Accettato | H3: Peggiorativo | I3: Accettato in blocco (--accetta-il-resto) | J3: Corrado | K3: 46290 | L3: Applicata | N3: 1. Filtrare la colonna Stato su 'Da decidere' (e Periodo sul ciclo o sulla settimana).
A4: 2026-10-12 | B4: Notizia | C4: N-20261007-01 | D4: Frode con voce clonata del direttore finanziario presso un gruppo industriale | E4: Rischio_ID | F4: NON PRESIDIATO | G4: Accettato | H4: NON PRESIDIATO | I4: Accettato in blocco (--accetta-il-resto) | J4: Corrado | K4: 46290 | L4: Applicata | N4: 2. Per ogni riga con cui NON si e' d'accordo, compilare Decisione:
A5: 2026-10-12 | B5: Notizia | C5: N-20261007-01 | D5: Frode con voce clonata del direttore finanziario presso un gruppo industriale | E5: Segnale | F5: Peggiorativo | G5: Accettato | H5: Peggiorativo | I5: Accettato in blocco (--accetta-il-resto) | J5: Corrado | K5: 46290 | L5: Applicata | N5: Rettificato = il valore giusto e' un altro: scriverlo in Valore_Validato;
A6: 2026-10-12 | B6: Notizia | C6: N-20261008-01 | D6: Il CERT finanziario segnala kit di clonazione vocale in vendita | E6: Rischio_ID | F6: NON PRESIDIATO | G6: Accettato | H6: NON PRESIDIATO | I6: Accettato in blocco (--accetta-il-resto) | J6: Corrado | K6: 46290 | L6: Applicata | N6: Respinto = KRI, azione o notizia da scartare per intero (un rischio non si respinge, si rettifica).
A7: 2026-10-12 | B7: Notizia | C7: N-20261008-01 | D7: Il CERT finanziario segnala kit di clonazione vocale in vendita | E7: Segnale | F7: Peggiorativo | G7: Accettato | H7: Peggiorativo | I7: Accettato in blocco (--accetta-il-resto) | J7: Corrado | K7: 46290 | L7: Applicata | N7: In entrambi i casi Motivazione e' obbligatoria (almeno 10 caratteri).
A8: 2026-10-12 | B8: Notizia | C8: N-20261008-02 | D8: Il fornitore cloud completa la nuova region italiana | E8: Rischio_ID | F8: NON PRESIDIATO | G8: Accettato | H8: NON PRESIDIATO | I8: Accettato in blocco (--accetta-il-resto) | J8: Corrado | K8: 46290 | L8: Applicata | N8: 3. Per accettare una riga: Decisione = Accettato (oppure lasciarla vuota e usare --accetta-il-resto).
A9: 2026-10-12 | B9: Notizia | C9: N-20261008-02 | D9: Il fornitore cloud completa la nuova region italiana | E9: Segnale | F9: Neutro | G9: Accettato | H9: Neutro | I9: Accettato in blocco (--accetta-il-resto) | J9: Corrado | K9: 46290 | L9: Applicata | N9: 4. Salvare e CHIUDERE il file, poi lanciare: python esegui_ciclo_locale.py valida --periodo <ciclo o lunedi'> --validatore "<funzione>"
A10: 2026-10-12 | B10: Notizia | C10: N-20261009-01 | D10: Autorita' europea: rimborso obbligatorio delle frodi APP dal 2027 | E10: Rischio_ID | F10: NON PRESIDIATO | G10: Accettato | H10: NON PRESIDIATO | I10: Accettato in blocco (--accetta-il-resto) | J10: Corrado | K10: 46290 | L10: Applicata | N10: (aggiungere --accetta-il-resto per accettare tutte le righe lasciate vuote).
A11: 2026-10-12 | B11: Notizia | C11: N-20261009-01 | D11: Autorita' europea: rimborso obbligatorio delle frodi APP dal 2027 | E11: Segnale | F11: Peggiorativo | G11: Accettato | H11: Peggiorativo | I11: Accettato in blocco (--accetta-il-resto) | J11: Corrado | K11: 46290 | L11: Applicata | N11: Il comando controlla le decisioni, le applica ai dati e mette Stato = Applicata. Proposta_Agente non si cancella mai:
A12: 2026Q3 | B12: Rischio | C12: NFR-01 | D12: Frodi su pagamenti istantanei abilitate da AI generativa | E12: Severity | F12: 4 | G12: Accettato | H12: 4 | I12: Accettato in blocco (--accetta-il-resto) | J12: Corrado | K12: 46290 | L12: Applicata | N12: le righe Rettificato sono la base dati per insegnare agli agenti (proposta -> decisione umana, con motivo).
A13: 2026Q3 | B13: Rischio | C13: NFR-01 | D13: Frodi su pagamenti istantanei abilitate da AI generativa | E13: Velocity | F13: 4 | G13: Accettato | H13: 4 | I13: Accettato in blocco (--accetta-il-resto) | J13: Corrado | K13: 46290 | L13: Applicata | N13: Un nuovo ciclo trimestrale non parte finche' il ciclo precedente ha righe 'Da decidere'.
A14: 2026Q3 | B14: Rischio | C14: NFR-01 | D14: Frodi su pagamenti istantanei abilitate da AI generativa | E14: Prossimita | F14: 4 | G14: Accettato | H14: 4 | I14: Accettato in blocco (--accetta-il-resto) | J14: Corrado | K14: 46290 | L14: Applicata
A15: 2026Q3 | B15: Rischio | C15: NFR-01 | D15: Frodi su pagamenti istantanei abilitate da AI generativa | E15: Gap_Controlli | F15: 3 | G15: Accettato | H15: 3 | I15: Accettato in blocco (--accetta-il-resto) | J15: Corrado | K15: 46290 | L15: Applicata
A16: 2026Q3 | B16: Rischio | C16: NFR-01 | D16: Frodi su pagamenti istantanei abilitate da AI generativa | E16: Probabilita | F16: 4 | G16: Accettato | H16: 4 | I16: Accettato in blocco (--accetta-il-resto) | J16: Corrado | K16: 46290 | L16: Applicata
A17: 2026Q3 | B17: Rischio | C17: NFR-01 | D17: Frodi su pagamenti istantanei abilitate da AI generativa | E17: Confidence | F17: 4 | G17: Accettato | H17: 4 | I17: Accettato in blocco (--accetta-il-resto) | J17: Corrado | K17: 46290 | L17: Applicata
A18: 2026Q3 | B18: Rischio | C18: NFR-02 | D18: Concentrazione su un fornitore cloud critico | E18: Severity | F18: 4 | G18: Accettato | H18: 4 | I18: Accettato in blocco (--accetta-il-resto) | J18: Corrado | K18: 46290 | L18: Applicata
A19: 2026Q3 | B19: Rischio | C19: NFR-02 | D19: Concentrazione su un fornitore cloud critico | E19: Velocity | F19: 4 | G19: Accettato | H19: 4 | I19: Accettato in blocco (--accetta-il-resto) | J19: Corrado | K19: 46290 | L19: Applicata
A20: 2026Q3 | B20: Rischio | C20: NFR-02 | D20: Concentrazione su un fornitore cloud critico | E20: Prossimita | F20: 3 | G20: Accettato | H20: 3 | I20: Accettato in blocco (--accetta-il-resto) | J20: Corrado | K20: 46290 | L20: Applicata
A21: 2026Q3 | B21: Rischio | C21: NFR-02 | D21: Concentrazione su un fornitore cloud critico | E21: Gap_Controlli | F21: 3 | G21: Accettato | H21: 3 | I21: Accettato in blocco (--accetta-il-resto) | J21: Corrado | K21: 46290 | L21: Applicata
A22: 2026Q3 | B22: Rischio | C22: NFR-02 | D22: Concentrazione su un fornitore cloud critico | E22: Probabilita | F22: 2 | G22: Accettato | H22: 2 | I22: Accettato in blocco (--accetta-il-resto) | J22: Corrado | K22: 46290 | L22: Applicata
A23: 2026Q3 | B23: Rischio | C23: NFR-02 | D23: Concentrazione su un fornitore cloud critico | E23: Confidence | F23: 4 | G23: Accettato | H23: 4 | I23: Accettato in blocco (--accetta-il-resto) | J23: Corrado | K23: 46290 | L23: Applicata
A24: 2026Q3 | B24: Rischio | C24: NFR-03 | D24: Greenwashing nella commercializzazione di prodotti ESG | E24: Severity | F24: 3 | G24: Accettato | H24: 3 | I24: Accettato in blocco (--accetta-il-resto) | J24: Corrado | K24: 46290 | L24: Applicata
A25: 2026Q3 | B25: Rischio | C25: NFR-03 | D25: Greenwashing nella commercializzazione di prodotti ESG | E25: Velocity | F25: 2 | G25: Accettato | H25: 2 | I25: Accettato in blocco (--accetta-il-resto) | J25: Corrado | K25: 46290 | L25: Applicata
... A83: 2026Q3 | B83: Rischio | C83: NFR-12 | D83: Errori operativi nei pagamenti istantanei obbligatori | E83: Confidence | F83: 3 | G83: Accettato | H83: 3 | I83: Accettato in blocco (--accetta-il-resto) | J83: Corrado | K83: 46290 | L83: Applicata
A84: 2026Q3 | B84: KRI | C84: NFR-01-K1 | D84: Tentativi di frode APP per 10.000 bonifici istantanei | E84: Valore_Corrente | G84: Rettificato | H84: 4.8 | I84: Primo valore rilevato dal sistema antifrode a fine settembre. | J84: Corrado | K84: 46290 | L84: Applicata
A85: 2026Q3 | B85: KRI | C85: NFR-01-K1 | D85: Tentativi di frode APP per 10.000 bonifici istantanei | E85: Soglia_Attenzione | F85: 3 | G85: Accettato | H85: 3 | I85: Accettato in blocco (--accetta-il-resto) | J85: Corrado | K85: 46290 | L85: Applicata
A86: 2026Q3 | B86: KRI | C86: NFR-01-K1 | D86: Tentativi di frode APP per 10.000 bonifici istantanei | E86: Soglia_Allerta | F86: 6 | G86: Accettato | H86: 6 | I86: Accettato in blocco (--accetta-il-resto) | J86: Corrado | K86: 46290 | L86: Applicata
A87: 2026Q3 | B87: KRI | C87: NFR-01-K2 | D87: Quota di frodi con voce o video sintetici accertati | E87: Valore_Corrente | G87: Accettato | I87: Accettato in blocco (--accetta-il-resto) | J87: Corrado | K87: 46290 | L87: Applicata
A88: 2026Q3 | B88: KRI | C88: NFR-01-K2 | D88: Quota di frodi con voce o video sintetici accertati | E88: Soglia_Attenzione | F88: 10 | G88: Accettato | H88: 10 | I88: Accettato in blocco (--accetta-il-resto) | J88: Corrado | K88: 46290 | L88: Applicata
A89: 2026Q3 | B89: KRI | C89: NFR-01-K2 | D89: Quota di frodi con voce o video sintetici accertati | E89: Soglia_Allerta | F89: 25 | G89: Accettato | H89: 25 | I89: Accettato in blocco (--accetta-il-resto) | J89: Corrado | K89: 46290 | L89: Applicata
A90: 2026Q3 | B90: KRI | C90: NFR-01-K3 | D90: Tempo medio di blocco di un beneficiario fraudolento | E90: Valore_Corrente | G90: Accettato | I90: Accettato in blocco (--accetta-il-resto) | J90: Corrado | K90: 46290 | L90: Applicata
A91: 2026Q3 | B91: KRI | C91: NFR-01-K3 | D91: Tempo medio di blocco di un beneficiario fraudolento | E91: Soglia_Attenzione | F91: 4 | G91: Accettato | H91: 4 | I91: Accettato in blocco (--accetta-il-resto) | J91: Corrado | K91: 46290 | L91: Applicata
A92: 2026Q3 | B92: KRI | C92: NFR-01-K3 | D92: Tempo medio di blocco di un beneficiario fraudolento | E92: Soglia_Allerta | F92: 12 | G92: Accettato | H92: 12 | I92: Accettato in blocco (--accetta-il-resto) | J92: Corrado | K92: 46290 | L92: Applicata
A93: 2026Q3 | B93: KRI | C93: NFR-02-K1 | D93: Quota di servizi critici sul fornitore cloud principale | E93: Valore_Corrente | G93: Accettato | I93: Accettato in blocco (--accetta-il-resto) | J93: Corrado | K93: 46290 | L93: Applicata
A94: 2026Q3 | B94: KRI | C94: NFR-02-K1 | D94: Quota di servizi critici sul fornitore cloud principale | E94: Soglia_Attenzione | F94: 60 | G94: Accettato | H94: 60 | I94: Accettato in blocco (--accetta-il-resto) | J94: Corrado | K94: 46290 | L94: Applicata
A95: 2026Q3 | B95: KRI | C95: NFR-02-K1 | D95: Quota di servizi critici sul fornitore cloud principale | E95: Soglia_Allerta | F95: 75 | G95: Accettato | H95: 75 | I95: Accettato in blocco (--accetta-il-resto) | J95: Corrado | K95: 46290 | L95: Applicata
A96: 2026Q3 | B96: KRI | C96: NFR-02-K2 | D96: Servizi critici senza piano di uscita testato negli ultimi 12 mesi | E96: Valore_Corrente | G96: Accettato | I96: Accettato in blocco (--accetta-il-resto) | J96: Corrado | K96: 46290 | L96: Applicata
A97: 2026Q3 | B97: KRI | C97: NFR-02-K2 | D97: Servizi critici senza piano di uscita testato negli ultimi 12 mesi | E97: Soglia_Attenzione | F97: 1 | G97: Accettato | H97: 1 | I97: Accettato in blocco (--accetta-il-resto) | J97: Corrado | K97: 46290 | L97: Applicata
A98: 2026Q3 | B98: KRI | C98: NFR-02-K2 | D98: Servizi critici senza piano di uscita testato negli ultimi 12 mesi | E98: Soglia_Allerta | F98: 2 | G98: Accettato | H98: 2 | I98: Accettato in blocco (--accetta-il-resto) | J98: Corrado | K98: 46290 | L98: Applicata
A99: 2026Q3 | B99: KRI | C99: NFR-02-K3 | D99: Incidenti del fornitore con impatto sui servizi nel trimestre | E99: Valore_Corrente | G99: Accettato | I99: Accettato in blocco (--accetta-il-resto) | J99: Corrado | K99: 46290 | L99: Applicata
A100: 2026Q3 | B100: KRI | C100: NFR-02-K3 | D100: Incidenti del fornitore con impatto sui servizi nel trimestre | E100: Soglia_Attenzione | F100: 2 | G100: Accettato | H100: 2 | I100: Accettato in blocco (--accetta-il-resto) | J100: Corrado | K100: 46290 | L100: Applicata
A101: 2026Q3 | B101: KRI | C101: NFR-02-K3 | D101: Incidenti del fornitore con impatto sui servizi nel trimestre | E101: Soglia_Allerta | F101: 4 | G101: Accettato | H101: 4 | I101: Accettato in blocco (--accetta-il-resto) | J101: Corrado | K101: 46290 | L101: Applicata
A102: 2026Q3 | B102: KRI | C102: NFR-03-K1 | D102: Reclami su prodotti ESG ogni 1.000 contratti | E102: Valore_Corrente | G102: Accettato | I102: Accettato in blocco (--accetta-il-resto) | J102: Corrado | K102: 46290 | L102: Applicata
A103: 2026Q3 | B103: KRI | C103: NFR-03-K1 | D103: Reclami su prodotti ESG ogni 1.000 contratti | E103: Soglia_Attenzione | F103: 1.5 | G103: Accettato | H103: 1.5 | I103: Accettato in blocco (--accetta-il-resto) | J103: Corrado | K103: 46290 | L103: Applicata
A104: 2026Q3 | B104: KRI | C104: NFR-03-K1 | D104: Reclami su prodotti ESG ogni 1.000 contratti | E104: Soglia_Allerta | F104: 3 | G104: Accettato | H104: 3 | I104: Accettato in blocco (--accetta-il-resto) | J104: Corrado | K104: 46290 | L104: Applicata
A105: 2026Q3 | B105: KRI | C105: NFR-03-K2 | D105: Quota di prodotti ESG senza revisione dei claim nell'anno | E105: Valore_Corrente | G105: Accettato | I105: Accettato in blocco (--accetta-il-resto) | J105: Corrado | K105: 46290 | L105: Applicata
A106: 2026Q3 | B106: KRI | C106: NFR-03-K2 | D106: Quota di prodotti ESG senza revisione dei claim nell'anno | E106: Soglia_Attenzione | F106: 20 | G106: Accettato | H106: 20 | I106: Accettato in blocco (--accetta-il-resto) | J106: Corrado | K106: 46290 | L106: Applicata
A107: 2026Q3 | B107: KRI | C107: NFR-03-K2 | D107: Quota di prodotti ESG senza revisione dei claim nell'anno | E107: Soglia_Allerta | F107: 40 | G107: Accettato | H107: 40 | I107: Accettato in blocco (--accetta-il-resto) | J107: Corrado | K107: 46290 | L107: Applicata
A108: 2026Q3 | B108: KRI | C108: NFR-03-K3 | D108: Rilievi di audit aperti sulla trasparenza ESG | E108: Valore_Corrente | G108: Accettato | I108: Accettato in blocco (--accetta-il-resto) | J108: Corrado | K108: 46290 | L108: Applicata
A109: 2026Q3 | B109: KRI | C109: NFR-03-K3 | D109: Rilievi di audit aperti sulla trasparenza ESG | E109: Soglia_Attenzione | F109: 1 | G109: Accettato | H109: 1 | I109: Accettato in blocco (--accetta-il-resto) | J109: Corrado | K109: 46290 | L109: Applicata
A110: 2026Q3 | B110: KRI | C110: NFR-03-K3 | D110: Rilievi di audit aperti sulla trasparenza ESG | E110: Soglia_Allerta | F110: 3 | G110: Accettato | H110: 3 | I110: Accettato in blocco (--accetta-il-resto) | J110: Corrado | K110: 46290 | L110: Applicata
A111: 2026Q3 | B111: KRI | C111: NFR-04-K1 | D111: Sedi critiche in aree a rischio idrogeologico senza piano specifico | E111: Valore_Corrente | G111: Accettato | I111: Accettato in blocco (--accetta-il-resto) | J111: Corrado | K111: 46290 | L111: Applicata
A112: 2026Q3 | B112: KRI | C112: NFR-04-K1 | D112: Sedi critiche in aree a rischio idrogeologico senza piano specifico | E112: Soglia_Attenzione | F112: 1 | G112: Accettato | H112: 1 | I112: Accettato in blocco (--accetta-il-resto) | J112: Corrado | K112: 46290 | L112: Applicata
A113: 2026Q3 | B113: KRI | C113: NFR-04-K1 | D113: Sedi critiche in aree a rischio idrogeologico senza piano specifico | E113: Soglia_Allerta | F113: 3 | G113: Accettato | H113: 3 | I113: Accettato in blocco (--accetta-il-resto) | J113: Corrado | K113: 46290 | L113: Applicata
A114: 2026Q3 | B114: KRI | C114: NFR-04-K2 | D114: Giorni di indisponibilita' di sedi per eventi climatici | E114: Valore_Corrente | G114: Accettato | I114: Accettato in blocco (--accetta-il-resto) | J114: Corrado | K114: 46290 | L114: Applicata
A115: 2026Q3 | B115: KRI | C115: NFR-04-K2 | D115: Giorni di indisponibilita' di sedi per eventi climatici | E115: Soglia_Attenzione | F115: 2 | G115: Accettato | H115: 2 | I115: Accettato in blocco (--accetta-il-resto) | J115: Corrado | K115: 46290 | L115: Applicata
A116: 2026Q3 | B116: KRI | C116: NFR-04-K2 | D116: Giorni di indisponibilita' di sedi per eventi climatici | E116: Soglia_Allerta | F116: 5 | G116: Accettato | H116: 5 | I116: Accettato in blocco (--accetta-il-resto) | J116: Corrado | K116: 46290 | L116: Applicata
A117: 2026Q3 | B117: KRI | C117: NFR-04-K3 | D117: Scarto fra RTO dichiarato e testato del sito secondario | E117: Valore_Corrente | G117: Accettato | I117: Accettato in blocco (--accetta-il-resto) | J117: Corrado | K117: 46290 | L117: Applicata
A118: 2026Q3 | B118: KRI | C118: NFR-04-K3 | D118: Scarto fra RTO dichiarato e testato del sito secondario | E118: Soglia_Attenzione | F118: 1 | G118: Accettato | H118: 1 | I118: Accettato in blocco (--accetta-il-resto) | J118: Corrado | K118: 46290 | L118: Applicata
A119: 2026Q3 | B119: KRI | C119: NFR-04-K3 | D119: Scarto fra RTO dichiarato e testato del sito secondario | E119: Soglia_Allerta | F119: 4 | G119: Accettato | H119: 4 | I119: Accettato in blocco (--accetta-il-resto) | J119: Corrado | K119: 46290 | L119: Applicata
A120: 2026Q3 | B120: KRI | C120: NFR-05-K1 | D120: Differenze di riconciliazione aperte oltre 5 giorni | E120: Valore_Corrente | G120: Accettato | I120: Accettato in blocco (--accetta-il-resto) | J120: Corrado | K120: 46290 | L120: Applicata
A121: 2026Q3 | B121: KRI | C121: NFR-05-K1 | D121: Differenze di riconciliazione aperte oltre 5 giorni | E121: Soglia_Attenzione | F121: 20 | G121: Accettato | H121: 20 | I121: Accettato in blocco (--accetta-il-resto) | J121: Corrado | K121: 46290 | L121: Applicata
A122: 2026Q3 | B122: KRI | C122: NFR-05-K1 | D122: Differenze di riconciliazione aperte oltre 5 giorni | E122: Soglia_Allerta | F122: 50 | G122: Accettato | H122: 50 | I122: Accettato in blocco (--accetta-il-resto) | J122: Corrado | K122: 46290 | L122: Applicata
A123: 2026Q3 | B123: KRI | C123: NFR-05-K2 | D123: Incidenti di produzione legati alla migrazione | E123: Valore_Corrente | G123: Accettato | I123: Accettato in blocco (--accetta-il-resto) | J123: Corrado | K123: 46290 | L123: Applicata
A124: 2026Q3 | B124: KRI | C124: NFR-05-K2 | D124: Incidenti di produzione legati alla migrazione | E124: Soglia_Attenzione | F124: 3 | G124: Accettato | H124: 3 | I124: Accettato in blocco (--accetta-il-resto) | J124: Corrado | K124: 46290 | L124: Applicata
A125: 2026Q3 | B125: KRI | C125: NFR-05-K2 | D125: Incidenti di produzione legati alla migrazione | E125: Soglia_Allerta | F125: 6 | G125: Accettato | H125: 6 | I125: Accettato in blocco (--accetta-il-resto) | J125: Corrado | K125: 46290 | L125: Applicata
A126: 2026Q3 | B126: KRI | C126: NFR-05-K3 | D126: Quota di controlli di processo non ridisegnati sul nuovo core | E126: Valore_Corrente | G126: Accettato | I126: Accettato in blocco (--accetta-il-resto) | J126: Corrado | K126: 46290 | L126: Applicata
A127: 2026Q3 | B127: KRI | C127: NFR-05-K3 | D127: Quota di controlli di processo non ridisegnati sul nuovo core | E127: Soglia_Attenzione | F127: 30 | G127: Accettato | H127: 30 | I127: Accettato in blocco (--accetta-il-resto) | J127: Corrado | K127: 46290 | L127: Applicata
A128: 2026Q3 | B128: KRI | C128: NFR-05-K3 | D128: Quota di controlli di processo non ridisegnati sul nuovo core | E128: Soglia_Allerta | F128: 60 | G128: Accettato | H128: 60 | I128: Accettato in blocco (--accetta-il-resto) | J128: Corrado | K128: 46290 | L128: Applicata
A129: 2026Q3 | B129: KRI | C129: NFR-06-K1 | D129: Tentativi di caricamento di dati riservati su servizi AI non autorizzati | E129: Valore_Corrente | G129: Accettato | I129: Accettato in blocco (--accetta-il-resto) | J129: Corrado | K129: 46290 | L129: Applicata
A130: 2026Q3 | B130: KRI | C130: NFR-06-K1 | D130: Tentativi di caricamento di dati riservati su servizi AI non autorizzati | E130: Soglia_Attenzione | F130: 10 | G130: Accettato | H130: 10 | I130: Accettato in blocco (--accetta-il-resto) | J130: Corrado | K130: 46290 | L130: Applicata
A131: 2026Q3 | B131: KRI | C131: NFR-06-K1 | D131: Tentativi di caricamento di dati riservati su servizi AI non autorizzati | E131: Soglia_Allerta | F131: 30 | G131: Accettato | H131: 30 | I131: Accettato in blocco (--accetta-il-resto) | J131: Corrado | K131: 46290 | L131: Applicata
A132: 2026Q3 | B132: KRI | C132: NFR-06-K2 | D132: Quota di dipendenti senza formazione sull'uso dell'AI | E132: Valore_Corrente | G132: Accettato | I132: Accettato in blocco (--accetta-il-resto) | J132: Corrado | K132: 46290 | L132: Applicata
A133: 2026Q3 | B133: KRI | C133: NFR-06-K2 | D133: Quota di dipendenti senza formazione sull'uso dell'AI | E133: Soglia_Attenzione | F133: 20 | G133: Accettato | H133: 20 | I133: Accettato in blocco (--accetta-il-resto) | J133: Corrado | K133: 46290 | L133: Applicata
A134: 2026Q3 | B134: KRI | C134: NFR-06-K2 | D134: Quota di dipendenti senza formazione sull'uso dell'AI | E134: Soglia_Allerta | F134: 40 | G134: Accettato | H134: 40 | I134: Accettato in blocco (--accetta-il-resto) | J134: Corrado | K134: 46290 | L134: Applicata
A135: 2026Q3 | B135: KRI | C135: NFR-06-K3 | D135: Utenze privilegiate senza revisione degli accessi nel trimestre | E135: Valore_Corrente | G135: Accettato | I135: Accettato in blocco (--accetta-il-resto) | J135: Corrado | K135: 46290 | L135: Applicata
A136: 2026Q3 | B136: KRI | C136: NFR-06-K3 | D136: Utenze privilegiate senza revisione degli accessi nel trimestre | E136: Soglia_Attenzione | F136: 5 | G136: Accettato | H136: 5 | I136: Accettato in blocco (--accetta-il-resto) | J136: Corrado | K136: 46290 | L136: Applicata
A137: 2026Q3 | B137: KRI | C137: NFR-06-K3 | D137: Utenze privilegiate senza revisione degli accessi nel trimestre | E137: Soglia_Allerta | F137: 15 | G137: Accettato | H137: 15 | I137: Accettato in blocco (--accetta-il-resto) | J137: Corrado | K137: 46290 | L137: Applicata
A138: 2026Q3 | B138: KRI | C138: NFR-07-K1 | D138: Fornitori di pagamento critici senza test di ripristino da ransomware | E138: Valore_Corrente | G138: Accettato | I138: Accettato in blocco (--accetta-il-resto) | J138: Corrado | K138: 46290 | L138: Applicata
A139: 2026Q3 | B139: KRI | C139: NFR-07-K1 | D139: Fornitori di pagamento critici senza test di ripristino da ransomware | E139: Soglia_Attenzione | F139: 1 | G139: Accettato | H139: 1 | I139: Accettato in blocco (--accetta-il-resto) | J139: Corrado | K139: 46290 | L139: Applicata
A140: 2026Q3 | B140: KRI | C140: NFR-07-K1 | D140: Fornitori di pagamento critici senza test di ripristino da ransomware | E140: Soglia_Allerta | F140: 2 | G140: Accettato | H140: 2 | I140: Accettato in blocco (--accetta-il-resto) | J140: Corrado | K140: 46290 | L140: Applicata
A141: 2026Q3 | B141: KRI | C141: NFR-07-K2 | D141: Ore di indisponibilita' del gateway di pagamento nel trimestre | E141: Valore_Corrente | G141: Accettato | I141: Accettato in blocco (--accetta-il-resto) | J141: Corrado | K141: 46290 | L141: Applicata
A142: 2026Q3 | B142: KRI | C142: NFR-07-K2 | D142: Ore di indisponibilita' del gateway di pagamento nel trimestre | E142: Soglia_Attenzione | F142: 4 | G142: Accettato | H142: 4 | I142: Accettato in blocco (--accetta-il-resto) | J142: Corrado | K142: 46290 | L142: Applicata
A143: 2026Q3 | B143: KRI | C143: NFR-07-K2 | D143: Ore di indisponibilita' del gateway di pagamento nel trimestre | E143: Soglia_Allerta | F143: 12 | G143: Accettato | H143: 12 | I143: Accettato in blocco (--accetta-il-resto) | J143: Corrado | K143: 46290 | L143: Applicata
A144: 2026Q3 | B144: KRI | C144: NFR-07-K3 | D144: Vulnerabilita' critiche aperte oltre 30 giorni presso il fornitore | E144: Valore_Corrente | G144: Accettato | I144: Accettato in blocco (--accetta-il-resto) | J144: Corrado | K144: 46290 | L144: Applicata
A145: 2026Q3 | B145: KRI | C145: NFR-07-K3 | D145: Vulnerabilita' critiche aperte oltre 30 giorni presso il fornitore | E145: Soglia_Attenzione | F145: 2 | G145: Accettato | H145: 2 | I145: Accettato in blocco (--accetta-il-resto) | J145: Corrado | K145: 46290 | L145: Applicata
A146: 2026Q3 | B146: KRI | C146: NFR-07-K3 | D146: Vulnerabilita' critiche aperte oltre 30 giorni presso il fornitore | E146: Soglia_Allerta | F146: 5 | G146: Accettato | H146: 5 | I146: Accettato in blocco (--accetta-il-resto) | J146: Corrado | K146: 46290 | L146: Applicata
A147: 2026Q3 | B147: KRI | C147: NFR-08-K1 | D147: Accessi ai dati clienti senza pratica associata | E147: Valore_Corrente | G147: Accettato | I147: Accettato in blocco (--accetta-il-resto) | J147: Corrado | K147: 46290 | L147: Applicata
A148: 2026Q3 | B148: KRI | C148: NFR-08-K1 | D148: Accessi ai dati clienti senza pratica associata | E148: Soglia_Attenzione | F148: 20 | G148: Accettato | H148: 20 | I148: Accettato in blocco (--accetta-il-resto) | J148: Corrado | K148: 46290 | L148: Applicata
A149: 2026Q3 | B149: KRI | C149: NFR-08-K1 | D149: Accessi ai dati clienti senza pratica associata | E149: Soglia_Allerta | F149: 50 | G149: Accettato | H149: 50 | I149: Accettato in blocco (--accetta-il-resto) | J149: Corrado | K149: 46290 | L149: Applicata
A150: 2026Q3 | B150: KRI | C150: NFR-08-K2 | D150: Utenze con profili di accesso non rivisti nell'anno | E150: Valore_Corrente | G150: Accettato | I150: Accettato in blocco (--accetta-il-resto) | J150: Corrado | K150: 46290 | L150: Applicata
A151: 2026Q3 | B151: KRI | C151: NFR-08-K2 | D151: Utenze con profili di accesso non rivisti nell'anno | E151: Soglia_Attenzione | F151: 5 | G151: Accettato | H151: 5 | I151: Accettato in blocco (--accetta-il-resto) | J151: Corrado | K151: 46290 | L151: Applicata
A152: 2026Q3 | B152: KRI | C152: NFR-08-K2 | D152: Utenze con profili di accesso non rivisti nell'anno | E152: Soglia_Allerta | F152: 15 | G152: Accettato | H152: 15 | I152: Accettato in blocco (--accetta-il-resto) | J152: Corrado | K152: 46290 | L152: Applicata
A153: 2026Q3 | B153: KRI | C153: NFR-08-K3 | D153: Accessi impropri accertati nel trimestre | E153: Valore_Corrente | G153: Accettato | I153: Accettato in blocco (--accetta-il-resto) | J153: Corrado | K153: 46290 | L153: Applicata
A154: 2026Q3 | B154: KRI | C154: NFR-08-K3 | D154: Accessi impropri accertati nel trimestre | E154: Soglia_Attenzione | F154: 1 | G154: Accettato | H154: 1 | I154: Accettato in blocco (--accetta-il-resto) | J154: Corrado | K154: 46290 | L154: Applicata
A155: 2026Q3 | B155: KRI | C155: NFR-08-K3 | D155: Accessi impropri accertati nel trimestre | E155: Soglia_Allerta | F155: 3 | G155: Accettato | H155: 3 | I155: Accettato in blocco (--accetta-il-resto) | J155: Corrado | K155: 46290 | L155: Applicata
A156: 2026Q3 | B156: KRI | C156: NFR-09-K1 | D156: Pagamenti bloccati dal filtro sanzioni ogni 10.000 verso paesi di transito | E156: Valore_Corrente | G156: Accettato | I156: Accettato in blocco (--accetta-il-resto) | J156: Corrado | K156: 46290 | L156: Applicata
A157: 2026Q3 | B157: KRI | C157: NFR-09-K1 | D157: Pagamenti bloccati dal filtro sanzioni ogni 10.000 verso paesi di transito | E157: Soglia_Attenzione | F157: 2 | G157: Accettato | H157: 2 | I157: Accettato in blocco (--accetta-il-resto) | J157: Corrado | K157: 46290 | L157: Applicata
...

Sheet Parametri
A1: Parametri
A2: Celle gialle = input. Nessuna costante e' sepolta nelle formule: si cambiano qui. | H2: Anagrafica dei rischi attivi (aggiornata dalla scrittura A2). Per togliere un rischio: comando 'dismetti' dello script. NON svuotare righe a mano: una riga vuota in mezzo toglie dal radar l'ultimo rischio.
A3: Pesi dello Score_Composito | E3: Tassonomia — event type L1 | H3: ID | I3: Nome | J3: Event_Type | K3: Driver | L3: Owner
A4: Severity | B4: 0.4 | E4: L1-01 | F4: Frode interna | H4: NFR-01 | I4: Frodi su pagamenti istantanei abilitate da AI generativa | J4: L1-02 | K4: DRV-AI, DRV-CYB | L4: Da assegnare
A5: Velocity | B5: 0.2 | E5: L1-02 | F5: Frode esterna | H5: NFR-02 | I5: Concentrazione su un fornitore cloud critico | J5: L1-06 | K5: DRV-TPR, DRV-CYB | L5: Da assegnare
A6: Prossimita' | B6: 0.2 | E6: L1-03 | F6: Rapporti di impiego e sicurezza sul lavoro | H6: NFR-03 | I6: Greenwashing nella commercializzazione di prodotti ESG | J6: L1-04 | K6: DRV-CON, DRV-CLI | L6: Da assegnare
A7: Gap_Controlli | B7: 0.2 | E7: L1-04 | F7: Clientela, prodotti e prassi professionali | H7: NFR-04 | I7: Eventi climatici estremi su sedi e data center | J7: L1-05 | K7: DRV-CLI | L7: Da assegnare
A8: Somma dei pesi | B8: =SUM(B4:B7) -> 1 | C8: =IF(ROUND(B8,6)=1,"OK","I PESI NON SOMMANO A 1") -> OK | E8: L1-05 | F8: Danni a beni materiali | H8: NFR-05 | I8: Errori di processo nella migrazione del core banking | J8: L1-07 | K8: DRV-TEC | L8: Da assegnare
E9: L1-06 | F9: Interruzione dell'operativita' e disfunzione dei sistemi | H9: NFR-06 | I9: Esfiltrazione di dati tramite strumenti di AI non autorizzati | J9: L1-01 | K9: DRV-AI, DRV-HUM | L9: Da assegnare
A10: Soglie | E10: L1-07 | F10: Esecuzione, consegna e gestione dei processi | H10: NFR-07 | I10: Ransomware presso un fornitore di servizi di pagamento | J10: L1-06 | K10: DRV-CYB, DRV-TPR | L10: Da assegnare
A11: Soglia di direzione (segnali netti in 4 settimane) | B11: 3 | H11: NFR-08 | I11: Accessi impropri di dipendenti ai dati dei clienti | J11: L1-01 | K11: DRV-HUM, DRV-CON | L11: Da assegnare
A12: Soglia di evidenziazione del Delta composito | B12: 0.4 | E12: Driver emergenti | H12: NFR-09 | I12: Violazione di sanzioni internazionali tramite triangolazioni | J12: L1-04 | K12: DRV-GEO | L12: Da assegnare
E13: DRV-CYB | F13: Cyber | H13: NFR-10 | I13: Informazioni errate ai clienti da assistenti di AI generativa | J13: L1-04 | K13: DRV-AI, DRV-CON | L13: Da assegnare
A14: Cicli del radar | E14: DRV-TPR | F14: Terze parti | H14: NFR-11 | I14: Fine del supporto dei sistemi di pagamento legacy | J14: L1-06 | K14: DRV-TEC | L14: Da assegnare
A15: Ciclo corrente (scritto dalla scrittura A2) | B15: 2026Q3 | E15: DRV-AI | F15: Intelligenza artificiale | H15: NFR-12 | I15: Errori operativi nei pagamenti istantanei obbligatori | J15: L1-07 | K15: DRV-TEC | L15: Da assegnare
A16: Ciclo precedente | B16: =IF(B15="","",IF(RIGHT(B15,1)="1",(LEFT(B15,4)-1)&"Q4",LEFT(B15,5)&(RIGHT(B15,1)-1))) -> 2026Q2 | E16: DRV-CLI | F16: Clima e ambiente
A17: Due cicli prima | B17: =IF(B16="","",IF(RIGHT(B16,1)="1",(LEFT(B16,4)-1)&"Q4",LEFT(B16,5)&(RIGHT(B16,1)-1))) -> 2026Q1 | E17: DRV-CON | F17: Condotta
E18: DRV-GEO | F18: Geopolitica
A19: Cicli del trend (dal piu' vecchio) | E19: DRV-TEC | F19: Debito tecnologico
A20: T-7 | B20: =IF(B21="","",IF(RIGHT(B21,1)="1",(LEFT(B21,4)-1)&"Q4",LEFT(B21,5)&(RIGHT(B21,1)-1))) -> 2024Q4 | E20: DRV-HUM | F20: Capitale umano
A21: T-6 | B21: =IF(B22="","",IF(RIGHT(B22,1)="1",(LEFT(B22,4)-1)&"Q4",LEFT(B22,5)&(RIGHT(B22,1)-1))) -> 2025Q1
A22: T-5 | B22: =IF(B23="","",IF(RIGHT(B23,1)="1",(LEFT(B23,4)-1)&"Q4",LEFT(B23,5)&(RIGHT(B23,1)-1))) -> 2025Q2
A23: T-4 | B23: =IF(B24="","",IF(RIGHT(B24,1)="1",(LEFT(B24,4)-1)&"Q4",LEFT(B24,5)&(RIGHT(B24,1)-1))) -> 2025Q3
A24: T-3 | B24: =IF(B25="","",IF(RIGHT(B25,1)="1",(LEFT(B25,4)-1)&"Q4",LEFT(B25,5)&(RIGHT(B25,1)-1))) -> 2025Q4
A25: T-2 | B25: =IF(B26="","",IF(RIGHT(B26,1)="1",(LEFT(B26,4)-1)&"Q4",LEFT(B26,5)&(RIGHT(B26,1)-1))) -> 2026Q1
A26: T-1 | B26: =IF(B27="","",IF(RIGHT(B27,1)="1",(LEFT(B27,4)-1)&"Q4",LEFT(B27,5)&(RIGHT(B27,1)-1))) -> 2026Q2
A27: T (corrente) | B27: =cicloCorrente -> 2026Q3
A29: Settimane
A30: Settimana corrente (lunedi', scritta dalla scrittura A3) | B30: 46307
A31: Inizio finestra del badge (4 settimane) | B31: =settimanaCorrente-21 -> 46286
A33: Finestra di 12 settimane (dal piu' vecchio)
B34: =settimanaCorrente-7*11 -> 46230
B35: =settimanaCorrente-7*10 -> 46237
B36: =settimanaCorrente-7*9 -> 46244
B37: =settimanaCorrente-7*8 -> 46251
B38: =settimanaCorrente-7*7 -> 46258
B39: =settimanaCorrente-7*6 -> 46265
B40: =settimanaCorrente-7*5 -> 46272
B41: =settimanaCorrente-7*4 -> 46279
B42: =settimanaCorrente-7*3 -> 46286
B43: =settimanaCorrente-7*2 -> 46293
B44: =settimanaCorrente-7*1 -> 46300
B45: =settimanaCorrente-7*0 -> 46307
A47: Urgenza — disuguaglianza di Mosca (X + Y > Z = agire ora)
A48: X: anni per decidere e avviare la mitigazione | B48: 0.25
A49: Y di riserva: anni di mitigazione se il rischio non ha azioni | B49: 1
A50: Z: anni prima che il rischio possa manifestarsi, per Prossimita'
A51: Prossimita 1 — oltre 3 anni | B51: 4
A52: Prossimita 2 — 2-3 anni | B52: 2.5
A53: Prossimita 3 — 1-2 anni | B53: 1.5
A54: Prossimita 4 — entro 12 mesi | B54: 0.5
A55: Prossimita 5 — in corso o imminente | B55: 0

Sheet RiskRegister
A1: Ciclo | B1: Data_Riferimento | C1: ID_Rischio | D1: Nome | E1: Event_Type | F1: Driver | G1: Severity | H1: Velocity | I1: Prossimita | J1: Gap_Controlli | K1: Score_Composito | L1: Confidence | M1: Probabilita | N1: Esito | O1: Descrizione | P1: Razionale | Q1: Variazioni | R1: Fonti | S1: Owner | T1: Chiave | U1: Data_Scrittura | V1: Approvato_Da | W1: Validazione | X1: Data_Validazione | Z1: RiskRegister — livello DATI, una riga per rischio per ciclo. Si scrive solo in append.
A2: 2026Q3 | B2: 46295 | C2: NFR-01 | D2: Frodi su pagamenti istantanei abilitate da AI generativa | E2: L1-02 | F2: DRV-AI, DRV-CYB | G2: 4 | H2: 4 | I2: 4 | J2: 3 | K2: =IF(COUNT(G2,H2,I2,J2)<4,"",ROUND(pesoSeverity*G2+pesoVelocity*H2+pesoProssimita*I2+pesoGap*J2,2)) -> 3.8 | L2: 4 | M2: 4 | N2: Nuovo | O2: Frodi a danno dei clienti tramite voci o video sintetici che inducono bonifici istantanei irrevocabili verso conti di terzi. | P2: Il report frodi del terzo trimestre conferma importi medi elevati e casi con voce sintetica in linea con il trimestre precedente: severity 4 (danno reputazionale nazionale possibile), velocity 4 (impatto in minuti), prossimita' 4 (casi in banche comparabili). Gap_Controlli resta 3: la verifica fuori banda e' approvata ma non ancora attiva sui bonifici istantanei. | Q2: [] | R2: [{"riferimento": "Analisi interna sulle frodi da ingegneria sociale", "data": "2025-10-20", "tipo": "Interna"}, {"riferimento": "Threat intelligence: campagne di frode con voce sintetica verso banche UE", "data": "2026-04-15", "tipo": "Esterna"}, {"riferimento": "Report trimestrale frodi — Funzione Antifrode", "data": "2026-06-10", "tipo": "Interna"}, {"riferimento": "Relazione annuale sui pagamenti al dettaglio dell'autorita' di vigilanza", "data": "2026-05-28", "tipo": "Esterna"}, {"riferimento": "Report trimestrale frodi Q3 — Funzione Antifrode", "data": "2026-09-12", "tipo": "Interna"}] | S2: Da assegnare | T2: =A2&"|"&C2 -> 2026Q3|NFR-01 | U2: 46290 | V2: Corrado | W2: Accettato | X2: 46290 | Z2: Score_Composito e Chiave sono formule: non si scrivono a mano.
A3: 2026Q3 | B3: 46295 | C3: NFR-02 | D3: Concentrazione su un fornitore cloud critico | E3: L1-06 | F3: DRV-TPR, DRV-CYB | G3: 4 | H3: 4 | I3: 3 | J3: 3 | K3: =IF(COUNT(G3,H3,I3,J3)<4,"",ROUND(pesoSeverity*G3+pesoVelocity*H3+pesoProssimita*I3+pesoGap*J3,2)) -> 3.6 | L3: 4 | M3: 2 | N3: Nuovo | O3: Indisponibilita' prolungata del fornitore cloud che ospita servizi critici, senza alternativa attivabile nei tempi di ripristino. | P3: Gap_Controlli scende da 4 a 3 perche' la exit strategy e' ora testata su tutti i servizi critici (descrittore 3: controlli disegnati e testati di recente ma con rilievi aperti). Severity, velocity e prossimita' invariate: la concentrazione resta al 72% dei servizi critici e non ci sono incidenti gravi nel trimestre. | Q3: [] | R3: [{"riferimento": "Contratto e piano di uscita del fornitore cloud", "data": "2025-09-30", "tipo": "Interna"}, {"riferimento": "Registro delle informazioni DORA — servizi ICT critici", "data": "2026-03-20", "tipo": "Interna"}, {"riferimento": "Esito del test di exit strategy sul fornitore cloud", "data": "2026-05-12", "tipo": "Interna"}, {"riferimento": "Report del test completo di exit strategy sui servizi critici", "data": "2026-08-28", "tipo": "Interna"}] | S3: Da assegnare | T3: =A3&"|"&C3 -> 2026Q3|NFR-02 | U3: 46290 | V3: Corrado | W3: Accettato | X3: 46290 | Z3: Righe grigie = dati di ESEMPIO: eliminarle (righe della tabella) al primo uso reale.
A4: 2026Q3 | B4: 46295 | C4: NFR-03 | D4: Greenwashing nella commercializzazione di prodotti ESG | E4: L1-04 | F4: DRV-CON, DRV-CLI | G4: 3 | H4: 2 | I4: 4 | J4: 3 | K4: =IF(COUNT(G4,H4,I4,J4)<4,"",ROUND(pesoSeverity*G4+pesoVelocity*H4+pesoProssimita*I4+pesoGap*J4,2)) -> 3 | L4: 3 | M4: 2 | N4: Nuovo | O4: Claim ambientali non sostanziati nella documentazione di prodotti di investimento ESG, con rischio di sanzioni e rimborsi. | P4: Prossimita' sale a 4: la sanzione a una banca comparabile e' un caso nel settore entro 12 mesi (descrittore 4). Severity resta 3 perche' l'impatto potenziale non cambia; Gap_Controlli resta 3 perche' la revisione dei claim non e' ancora completata. | Q4: [] | R4: [{"riferimento": "Orientamenti dell'autorita' europea sui nomi dei fondi ESG", "data": "2025-11-14", "tipo": "Esterna"}, {"riferimento": "Verifica interna dei claim ambientali — Compliance", "data": "2026-02-18", "tipo": "Interna"}, {"riferimento": "Provvedimento sanzionatorio su claim ESG di una banca comparabile", "data": "2026-07-22", "tipo": "Esterna"}] | S4: Da assegnare | T4: =A4&"|"&C4 -> 2026Q3|NFR-03 | U4: 46290 | V4: Corrado | W4: Rettificato | X4: 46290 | Z4: Validazione = Da validare / Accettato / Rettificato: la scrive il comando 'valida' dopo la decisione umana
A5: 2026Q3 | B5: 46295 | C5: NFR-04 | D5: Eventi climatici estremi su sedi e data center | E5: L1-05 | F5: DRV-CLI | G5: 3 | H5: 2 | I5: 3 | J5: 3 | K5: =IF(COUNT(G5,H5,I5,J5)<4,"",ROUND(pesoSeverity*G5+pesoVelocity*H5+pesoProssimita*I5+pesoGap*J5,2)) -> 2.8 | L5: 3 | M5: 3 | N5: Nuovo | O5: Alluvioni o ondate di calore che rendono inagibili sedi operative o degradano il data center secondario. | P5: Nessun evento nuovo sulle sedi nel trimestre e i piani specifici per le due sedi critiche non sono ancora redatti: si confermano severity 3, velocity 2, prossimita' 3 e gap 3 con le fonti del ciclo precedente. | Q5: [] | R5: [{"riferimento": "Mappa del rischio idrogeologico delle sedi — BCM", "data": "2025-10-30", "tipo": "Interna"}, {"riferimento": "Alluvione in Emilia-Romagna con chiusura di due filiali", "data": "2026-05-06", "tipo": "Esterna"}] | S5: Da assegnare | T5: =A5&"|"&C5 -> 2026Q3|NFR-04 | U5: 46290 | V5: Corrado | W5: Accettato | X5: 46290 | Z5: presa nel foglio Validazione. Approvato_Da e Data_Validazione: chi ha validato e quando.
A6: 2026Q3 | B6: 46295 | C6: NFR-05 | D6: Errori di processo nella migrazione del core banking | E6: L1-07 | F6: DRV-TEC | G6: 3 | H6: 3 | I6: 3 | J6: 3 | K6: =IF(COUNT(G6,H6,I6,J6)<4,"",ROUND(pesoSeverity*G6+pesoVelocity*H6+pesoProssimita*I6+pesoGap*J6,2)) -> 3 | L6: 4 | M6: 3 | N6: Nuovo | O6: Errori di conversione dati e controlli di processo non ridisegnati durante la migrazione a ondate del sistema core. | P6: La wave 2 resta pianificata per il 2027 e i controlli di riconciliazione testati a maggio restano efficaci: si confermano tutte le dimensioni. Gli incidenti di produzione scendono ma restano sopra la soglia di attenzione. | Q6: [] | R6: [{"riferimento": "Piano di migrazione del core banking — PMO", "data": "2025-09-15", "tipo": "Interna"}, {"riferimento": "Chiusura della wave 1 di migrazione — PMO", "data": "2026-05-04", "tipo": "Interna"}, {"riferimento": "Relazione di audit sui controlli di riconciliazione post-migrazione", "data": "2026-05-20", "tipo": "Interna"}] | S6: Da assegnare | T6: =A6&"|"&C6 -> 2026Q3|NFR-05 | U6: 46290 | V6: Corrado | W6: Accettato | X6: 46290 | Z6: I valori di questa tabella sono quelli VALIDATI; la proposta originale dell'agente resta nel foglio Validazione.
A7: 2026Q3 | B7: 46295 | C7: NFR-06 | D7: Esfiltrazione di dati tramite strumenti di AI non autorizzati | E7: L1-01 | F7: DRV-AI, DRV-HUM | G7: 3 | H7: 3 | I7: 3 | J7: 3 | K7: =IF(COUNT(G7,H7,I7,J7)<4,"",ROUND(pesoSeverity*G7+pesoVelocity*H7+pesoProssimita*I7+pesoGap*J7,2)) -> 3 | L7: 3 | M7: 3 | N7: Nuovo | O7: Dipendenti che trasferiscono intenzionalmente dati riservati su servizi di AI generativa esterni per uso personale o a favore di terzi. | P7: Gap_Controlli scende a 3 perche' il DLP ora copre tutti i servizi, ma l'estensione e' recente e non ancora verificata dall'audit (descrittore 3). Severity, velocity e prossimita' invariate: i tentativi rilevati dal DLP calano ma non si azzerano. | Q7: [] | R7: [{"riferimento": "Log DLP: tentativi di caricamento verso servizi AI esterni", "data": "2026-03-15", "tipo": "Interna"}, {"riferimento": "Survey interna sull'uso di strumenti di AI generativa", "data": "2026-02-10", "tipo": "Interna"}, {"riferimento": "Verbale del test di blocco DLP sui servizi di AI generativa", "data": "2026-09-05", "tipo": "Interna"}] | S7: Da assegnare | T7: =A7&"|"&C7 -> 2026Q3|NFR-06 | U7: 46290 | V7: Corrado | W7: Accettato | X7: 46290 | Z7: Probabilita e' fuori dallo score composito: serve al Radar_Mosca (area = Probabilita x Severity).
A8: 2026Q3 | B8: 46295 | C8: NFR-07 | D8: Ransomware presso un fornitore di servizi di pagamento | E8: L1-06 | F8: DRV-CYB, DRV-TPR | G8: 4 | H8: 5 | I8: 3 | J8: 3 | K8: =IF(COUNT(G8,H8,I8,J8)<4,"",ROUND(pesoSeverity*G8+pesoVelocity*H8+pesoProssimita*I8+pesoGap*J8,2)) -> 3.8 | L8: 3 | M8: 3 | N8: Nuovo | O8: Blocco prolungato dei pagamenti per un attacco ransomware al fornitore esterno che gestisce il gateway di pagamento della Banca. | P8: Nessuna evidenza nuova nel trimestre: si confermano severity 4, velocity 5, prossimita' 3, gap 3 e probabilita' 3 con le fonti del ciclo precedente. | Q8: [] | R8: [{"riferimento": "Registro DORA: fornitore del gateway di pagamento classificato critico", "data": "2025-10-15", "tipo": "Interna"}, {"riferimento": "Attacco ransomware a un processore di pagamenti europeo", "data": "2026-02-20", "tipo": "Esterna"}] | S8: Da assegnare | T8: =A8&"|"&C8 -> 2026Q3|NFR-07 | U8: 46290 | V8: Corrado | W8: Accettato | X8: 46290
A9: 2026Q3 | B9: 46295 | C9: NFR-08 | D9: Accessi impropri di dipendenti ai dati dei clienti | E9: L1-01 | F9: DRV-HUM, DRV-CON | G9: 3 | H9: 3 | I9: 3 | J9: 3 | K9: =IF(COUNT(G9,H9,I9,J9)<4,"",ROUND(pesoSeverity*G9+pesoVelocity*H9+pesoProssimita*I9+pesoGap*J9,2)) -> 3 | L9: 3 | M9: 2 | N9: Nuovo | O9: Dipendenti che consultano o estraggono dati di clienti senza motivo di servizio, per curiosita' o a favore di terzi. | P9: Nessuna evidenza nuova nel trimestre: si confermano severity 3, velocity 3, prossimita' 3, gap 3 e probabilita' 2 con le fonti del ciclo precedente. | Q9: [] | R9: [{"riferimento": "Esiti del monitoraggio degli accessi ai dati clienti — SOC", "data": "2025-11-10", "tipo": "Interna"}, {"riferimento": "Provvedimento dell'autorita' privacy su accessi abusivi in una banca", "data": "2026-04-08", "tipo": "Esterna"}] | S9: Da assegnare | T9: =A9&"|"&C9 -> 2026Q3|NFR-08 | U9: 46290 | V9: Corrado | W9: Accettato | X9: 46290
A10: 2026Q3 | B10: 46295 | C10: NFR-09 | D10: Violazione di sanzioni internazionali tramite triangolazioni | E10: L1-04 | F10: DRV-GEO | G10: 4 | H10: 3 | I10: 2 | J10: 3 | K10: =IF(COUNT(G10,H10,I10,J10)<4,"",ROUND(pesoSeverity*G10+pesoVelocity*H10+pesoProssimita*I10+pesoGap*J10,2)) -> 3.2 | L10: 2 | M10: 2 | N10: Nuovo | O10: Pagamenti di clientela corporate verso controparti sanzionate interposte in paesi terzi, non intercettati dal filtro sanzioni. | P10: Nessuna evidenza nuova nel trimestre: si confermano severity 4, velocity 3, prossimita' 2, gap 3 e probabilita' 2 con le fonti del ciclo precedente. | Q10: [] | R10: [{"riferimento": "Nuovo pacchetto di sanzioni UE con obblighi di due diligence rafforzata", "data": "2026-02-24", "tipo": "Esterna"}, {"riferimento": "Analisi dei flussi verso paesi di transito — Compliance", "data": "2026-03-12", "tipo": "Interna"}] | S10: Da assegnare | T10: =A10&"|"&C10 -> 2026Q3|NFR-09 | U10: 46290 | V10: Corrado | W10: Accettato | X10: 46290
A11: 2026Q3 | B11: 46295 | C11: NFR-10 | D11: Informazioni errate ai clienti da assistenti di AI generativa | E11: L1-04 | F11: DRV-AI, DRV-CON | G11: 3 | H11: 3 | I11: 3 | J11: 4 | K11: =IF(COUNT(G11,H11,I11,J11)<4,"",ROUND(pesoSeverity*G11+pesoVelocity*H11+pesoProssimita*I11+pesoGap*J11,2)) -> 3.2 | L11: 2 | M11: 3 | N11: Nuovo | O11: Chatbot di assistenza basati su AI generativa che danno ai clienti informazioni errate su condizioni, costi o diritti, con reclami e rimborsi. | P11: Nessuna evidenza nuova nel trimestre: si confermano severity 3, velocity 3, prossimita' 3, gap 4 e probabilita' 3 con le fonti del ciclo precedente. | Q11: [] | R11: [{"riferimento": "Piano di rilascio del chatbot di assistenza con AI generativa", "data": "2026-01-20", "tipo": "Interna"}, {"riferimento": "Sanzione a una compagnia aerea per risposte errate del proprio chatbot", "data": "2026-02-15", "tipo": "Esterna"}] | S11: Da assegnare | T11: =A11&"|"&C11 -> 2026Q3|NFR-10 | U11: 46290 | V11: Corrado | W11: Accettato | X11: 46290
A12: 2026Q3 | B12: 46295 | C12: NFR-11 | D12: Fine del supporto dei sistemi di pagamento legacy | E12: L1-06 | F12: DRV-TEC | G12: 3 | H12: 2 | I12: 3 | J12: 4 | K12: =IF(COUNT(G12,H12,I12,J12)<4,"",ROUND(pesoSeverity*G12+pesoVelocity*H12+pesoProssimita*I12+pesoGap*J12,2)) -> 3 | L12: 3 | M12: 3 | N12: Nuovo | O12: Componenti del sistema di pagamento fuori supporto del produttore, senza patch di sicurezza e con competenze interne in riduzione. | P12: Nessuna evidenza nuova nel trimestre: si confermano severity 3, velocity 2, prossimita' 3, gap 4 e probabilita' 3 con le fonti del ciclo precedente. | Q12: [] | R12: [{"riferimento": "Inventario delle componenti fuori supporto — IT", "data": "2025-09-30", "tipo": "Interna"}, {"riferimento": "Comunicazione del produttore sulla fine del supporto esteso", "data": "2026-01-31", "tipo": "Esterna"}] | S12: Da assegnare | T12: =A12&"|"&C12 -> 2026Q3|NFR-11 | U12: 46290 | V12: Corrado | W12: Accettato | X12: 46290
A13: 2026Q3 | B13: 46295 | C13: NFR-12 | D13: Errori operativi nei pagamenti istantanei obbligatori | E13: L1-07 | F13: DRV-TEC | G13: 3 | H13: 4 | I13: 4 | J13: 3 | K13: =IF(COUNT(G13,H13,I13,J13)<4,"",ROUND(pesoSeverity*G13+pesoVelocity*H13+pesoProssimita*I13+pesoGap*J13,2)) -> 3.4 | L13: 3 | M13: 4 | N13: Nuovo | O13: Errori di riconciliazione e rimborsi indebiti dopo l'obbligo di offrire i bonifici istantanei a tutta la clientela. | P13: Nessuna evidenza nuova nel trimestre: si confermano severity 3, velocity 4, prossimita' 4, gap 3 e probabilita' 4 con le fonti del ciclo precedente. | Q13: [] | R13: [{"riferimento": "Piano di adeguamento al regolamento sui bonifici istantanei", "data": "2025-10-01", "tipo": "Interna"}, {"riferimento": "Report operativo dei pagamenti istantanei — maggio", "data": "2026-05-15", "tipo": "Interna"}] | S13: Da assegnare | T13: =A13&"|"&C13 -> 2026Q3|NFR-12 | U13: 46290 | V13: Corrado | W13: Accettato | X13: 46290

Sheet Trend
A1: Trend — score composito sugli ultimi otto cicli
A2: Scala fissa 0-5. Un punto mancante (#N/A) = rischio non valutato in quel ciclo, non score zero.
A3: ID | B3: Nome | C3: =Parametri!$B$20 -> 2024Q4 | D3: =Parametri!$B$21 -> 2025Q1 | E3: =Parametri!$B$22 -> 2025Q2 | F3: =Parametri!$B$23 -> 2025Q3 | G3: =Parametri!$B$24 -> 2025Q4 | H3: =Parametri!$B$25 -> 2026Q1 | I3: =Parametri!$B$26 -> 2026Q2 | J3: =Parametri!$B$27 -> 2026Q3
A4: =Dashboard!A13 -> NFR-01 | B4: =Dashboard!B13 -> Frodi su pagamenti istantanei abilitate da AI generativa | C4: =IF(OR($A4="",C$3=""),NA(),IF(COUNTIFS(RR_ID_Rischio,$A4,RR_Ciclo,C$3)=0,NA(),SUMIFS(RR_Score_Composito,RR_ID_Rischio,$A4,RR_Ciclo,C$3))) -> #N/A | D4: =IF(OR($A4="",D$3=""),NA(),IF(COUNTIFS(RR_ID_Rischio,$A4,RR_Ciclo,D$3)=0,NA(),SUMIFS(RR_Score_Composito,RR_ID_Rischio,$A4,RR_Ciclo,D$3))) -> #N/A | E4: =IF(OR($A4="",E$3=""),NA(),IF(COUNTIFS(RR_ID_Rischio,$A4,RR_Ciclo,E$3)=0,NA(),SUMIFS(RR_Score_Composito,RR_ID_Rischio,$A4,RR_Ciclo,E$3))) -> #N/A | F4: =IF(OR($A4="",F$3=""),NA(),IF(COUNTIFS(RR_ID_Rischio,$A4,RR_Ciclo,F$3)=0,NA(),SUMIFS(RR_Score_Composito,RR_ID_Rischio,$A4,RR_Ciclo,F$3))) -> #N/A | G4: =IF(OR($A4="",G$3=""),NA(),IF(COUNTIFS(RR_ID_Rischio,$A4,RR_Ciclo,G$3)=0,NA(),SUMIFS(RR_Score_Composito,RR_ID_Rischio,$A4,RR_Ciclo,G$3))) -> #N/A | H4: =IF(OR($A4="",H$3=""),NA(),IF(COUNTIFS(RR_ID_Rischio,$A4,RR_Ciclo,H$3)=0,NA(),SUMIFS(RR_Score_Composito,RR_ID_Rischio,$A4,RR_Ciclo,H$3))) -> #N/A | I4: =IF(OR($A4="",I$3=""),NA(),IF(COUNTIFS(RR_ID_Rischio,$A4,RR_Ciclo,I$3)=0,NA(),SUMIFS(RR_Score_Composito,RR_ID_Rischio,$A4,RR_Ciclo,I$3))) -> #N/A | J4: =IF(OR($A4="",J$3=""),NA(),IF(COUNTIFS(RR_ID_Rischio,$A4,RR_Ciclo,J$3)=0,NA(),SUMIFS(RR_Score_Composito,RR_ID_Rischio,$A4,RR_Ciclo,J$3))) -> 3.8
A5: =Dashboard!A14 -> NFR-02 | B5: =Dashboard!B14 -> Concentrazione su un fornitore cloud critico | C5: =IF(OR($A5="",C$3=""),NA(),IF(COUNTIFS(RR_ID_Rischio,$A5,RR_Ciclo,C$3)=0,NA(),SUMIFS(RR_Score_Composito,RR_ID_Rischio,$A5,RR_Ciclo,C$3))) -> #N/A | D5: =IF(OR($A5="",D$3=""),NA(),IF(COUNTIFS(RR_ID_Rischio,$A5,RR_Ciclo,D$3)=0,NA(),SUMIFS(RR_Score_Composito,RR_ID_Rischio,$A5,RR_Ciclo,D$3))) -> #N/A | E5: =IF(OR($A5="",E$3=""),NA(),IF(COUNTIFS(RR_ID_Rischio,$A5,RR_Ciclo,E$3)=0,NA(),SUMIFS(RR_Score_Composito,RR_ID_Rischio,$A5,RR_Ciclo,E$3))) -> #N/A | F5: =IF(OR($A5="",F$3=""),NA(),IF(COUNTIFS(RR_ID_Rischio,$A5,RR_Ciclo,F$3)=0,NA(),SUMIFS(RR_Score_Composito,RR_ID_Rischio,$A5,RR_Ciclo,F$3))) -> #N/A | G5: =IF(OR($A5="",G$3=""),NA(),IF(COUNTIFS(RR_ID_Rischio,$A5,RR_Ciclo,G$3)=0,NA(),SUMIFS(RR_Score_Composito,RR_ID_Rischio,$A5,RR_Ciclo,G$3))) -> #N/A | H5: =IF(OR($A5="",H$3=""),NA(),IF(COUNTIFS(RR_ID_Rischio,$A5,RR_Ciclo,H$3)=0,NA(),SUMIFS(RR_Score_Composito,RR_ID_Rischio,$A5,RR_Ciclo,H$3))) -> #N/A | I5: =IF(OR($A5="",I$3=""),NA(),IF(COUNTIFS(RR_ID_Rischio,$A5,RR_Ciclo,I$3)=0,NA(),SUMIFS(RR_Score_Composito,RR_ID_Rischio,$A5,RR_Ciclo,I$3))) -> #N/A | J5: =IF(OR($A5="",J$3=""),NA(),IF(COUNTIFS(RR_ID_Rischio,$A5,RR_Ciclo,J$3)=0,NA(),SUMIFS(RR_Score_Composito,RR_ID_Rischio,$A5,RR_Ciclo,J$3))) -> 3.6
A6: =Dashboard!A15 -> NFR-03 | B6: =Dashboard!B15 -> Greenwashing nella commercializzazione di prodotti ESG | C6: =IF(OR($A6="",C$3=""),NA(),IF(COUNTIFS(RR_ID_Rischio,$A6,RR_Ciclo,C$3)=0,NA(),SUMIFS(RR_Score_Composito,RR_ID_Rischio,$A6,RR_Ciclo,C$3))) -> #N/A | D6: =IF(OR($A6="",D$3=""),NA(),IF(COUNTIFS(RR_ID_Rischio,$A6,RR_Ciclo,D$3)=0,NA(),SUMIFS(RR_Score_Composito,RR_ID_Rischio,$A6,RR_Ciclo,D$3))) -> #N/A | E6: =IF(OR($A6="",E$3=""),NA(),IF(COUNTIFS(RR_ID_Rischio,$A6,RR_Ciclo,E$3)=0,NA(),SUMIFS(RR_Score_Composito,RR_ID_Rischio,$A6,RR_Ciclo,E$3))) -> #N/A | F6: =IF(OR($A6="",F$3=""),NA(),IF(COUNTIFS(RR_ID_Rischio,$A6,RR_Ciclo,F$3)=0,NA(),SUMIFS(RR_Score_Composito,RR_ID_Rischio,$A6,RR_Ciclo,F$3))) -> #N/A | G6: =IF(OR($A6="",G$3=""),NA(),IF(COUNTIFS(RR_ID_Rischio,$A6,RR_Ciclo,G$3)=0,NA(),SUMIFS(RR_Score_Composito,RR_ID_Rischio,$A6,RR_Ciclo,G$3))) -> #N/A | H6: =IF(OR($A6="",H$3=""),NA(),IF(COUNTIFS(RR_ID_Rischio,$A6,RR_Ciclo,H$3)=0,NA(),SUMIFS(RR_Score_Composito,RR_ID_Rischio,$A6,RR_Ciclo,H$3))) -> #N/A | I6: =IF(OR($A6="",I$3=""),NA(),IF(COUNTIFS(RR_ID_Rischio,$A6,RR_Ciclo,I$3)=0,NA(),SUMIFS(RR_Score_Composito,RR_ID_Rischio,$A6,RR_Ciclo,I$3))) -> #N/A | J6: =IF(OR($A6="",J$3=""),NA(),IF(COUNTIFS(RR_ID_Rischio,$A6,RR_Ciclo,J$3)=0,NA(),SUMIFS(RR_Score_Composito,RR_ID_Rischio,$A6,RR_Ciclo,J$3))) -> 3
A7: =Dashboard!A16 -> NFR-04 | B7: =Dashboard!B16 -> Eventi climatici estremi su sedi e data center | C7: =IF(OR($A7="",C$3=""),NA(),IF(COUNTIFS(RR_ID_Rischio,$A7,RR_Ciclo,C$3)=0,NA(),SUMIFS(RR_Score_Composito,RR_ID_Rischio,$A7,RR_Ciclo,C$3))) -> #N/A | D7: =IF(OR($A7="",D$3=""),NA(),IF(COUNTIFS(RR_ID_Rischio,$A7,RR_Ciclo,D$3)=0,NA(),SUMIFS(RR_Score_Composito,RR_ID_Rischio,$A7,RR_Ciclo,D$3))) -> #N/A | E7: =IF(OR($A7="",E$3=""),NA(),IF(COUNTIFS(RR_ID_Rischio,$A7,RR_Ciclo,E$3)=0,NA(),SUMIFS(RR_Score_Composito,RR_ID_Rischio,$A7,RR_Ciclo,E$3))) -> #N/A | F7: =IF(OR($A7="",F$3=""),NA(),IF(COUNTIFS(RR_ID_Rischio,$A7,RR_Ciclo,F$3)=0,NA(),SUMIFS(RR_Score_Composito,RR_ID_Rischio,$A7,RR_Ciclo,F$3))) -> #N/A | G7: =IF(OR($A7="",G$3=""),NA(),IF(COUNTIFS(RR_ID_Rischio,$A7,RR_Ciclo,G$3)=0,NA(),SUMIFS(RR_Score_Composito,RR_ID_Rischio,$A7,RR_Ciclo,G$3))) -> #N/A | H7: =IF(OR($A7="",H$3=""),NA(),IF(COUNTIFS(RR_ID_Rischio,$A7,RR_Ciclo,H$3)=0,NA(),SUMIFS(RR_Score_Composito,RR_ID_Rischio,$A7,RR_Ciclo,H$3))) -> #N/A | I7: =IF(OR($A7="",I$3=""),NA(),IF(COUNTIFS(RR_ID_Rischio,$A7,RR_Ciclo,I$3)=0,NA(),SUMIFS(RR_Score_Composito,RR_ID_Rischio,$A7,RR_Ciclo,I$3))) -> #N/A | J7: =IF(OR($A7="",J$3=""),NA(),IF(COUNTIFS(RR_ID_Rischio,$A7,RR_Ciclo,J$3)=0,NA(),SUMIFS(RR_Score_Composito,RR_ID_Rischio,$A7,RR_Ciclo,J$3))) -> 2.8
A8: =Dashboard!A17 -> NFR-05 | B8: =Dashboard!B17 -> Errori di processo nella migrazione del core banking | C8: =IF(OR($A8="",C$3=""),NA(),IF(COUNTIFS(RR_ID_Rischio,$A8,RR_Ciclo,C$3)=0,NA(),SUMIFS(RR_Score_Composito,RR_ID_Rischio,$A8,RR_Ciclo,C$3))) -> #N/A | D8: =IF(OR($A8="",D$3=""),NA(),IF(COUNTIFS(RR_ID_Rischio,$A8,RR_Ciclo,D$3)=0,NA(),SUMIFS(RR_Score_Composito,RR_ID_Rischio,$A8,RR_Ciclo,D$3))) -> #N/A | E8: =IF(OR($A8="",E$3=""),NA(),IF(COUNTIFS(RR_ID_Rischio,$A8,RR_Ciclo,E$3)=0,NA(),SUMIFS(RR_Score_Composito,RR_ID_Rischio,$A8,RR_Ciclo,E$3))) -> #N/A | F8: =IF(OR($A8="",F$3=""),NA(),IF(COUNTIFS(RR_ID_Rischio,$A8,RR_Ciclo,F$3)=0,NA(),SUMIFS(RR_Score_Composito,RR_ID_Rischio,$A8,RR_Ciclo,F$3))) -> #N/A | G8: =IF(OR($A8="",G$3=""),NA(),IF(COUNTIFS(RR_ID_Rischio,$A8,RR_Ciclo,G$3)=0,NA(),SUMIFS(RR_Score_Composito,RR_ID_Rischio,$A8,RR_Ciclo,G$3))) -> #N/A | H8: =IF(OR($A8="",H$3=""),NA(),IF(COUNTIFS(RR_ID_Rischio,$A8,RR_Ciclo,H$3)=0,NA(),SUMIFS(RR_Score_Composito,RR_ID_Rischio,$A8,RR_Ciclo,H$3))) -> #N/A | I8: =IF(OR($A8="",I$3=""),NA(),IF(COUNTIFS(RR_ID_Rischio,$A8,RR_Ciclo,I$3)=0,NA(),SUMIFS(RR_Score_Composito,RR_ID_Rischio,$A8,RR_Ciclo,I$3))) -> #N/A | J8: =IF(OR($A8="",J$3=""),NA(),IF(COUNTIFS(RR_ID_Rischio,$A8,RR_Ciclo,J$3)=0,NA(),SUMIFS(RR_Score_Composito,RR_ID_Rischio,$A8,RR_Ciclo,J$3))) -> 3
A9: =Dashboard!A18 -> NFR-06 | B9: =Dashboard!B18 -> Esfiltrazione di dati tramite strumenti di AI non autorizzati | C9: =IF(OR($A9="",C$3=""),NA(),IF(COUNTIFS(RR_ID_Rischio,$A9,RR_Ciclo,C$3)=0,NA(),SUMIFS(RR_Score_Composito,RR_ID_Rischio,$A9,RR_Ciclo,C$3))) -> #N/A | D9: =IF(OR($A9="",D$3=""),NA(),IF(COUNTIFS(RR_ID_Rischio,$A9,RR_Ciclo,D$3)=0,NA(),SUMIFS(RR_Score_Composito,RR_ID_Rischio,$A9,RR_Ciclo,D$3))) -> #N/A | E9: =IF(OR($A9="",E$3=""),NA(),IF(COUNTIFS(RR_ID_Rischio,$A9,RR_Ciclo,E$3)=0,NA(),SUMIFS(RR_Score_Composito,RR_ID_Rischio,$A9,RR_Ciclo,E$3))) -> #N/A | F9: =IF(OR($A9="",F$3=""),NA(),IF(COUNTIFS(RR_ID_Rischio,$A9,RR_Ciclo,F$3)=0,NA(),SUMIFS(RR_Score_Composito,RR_ID_Rischio,$A9,RR_Ciclo,F$3))) -> #N/A | G9: =IF(OR($A9="",G$3=""),NA(),IF(COUNTIFS(RR_ID_Rischio,$A9,RR_Ciclo,G$3)=0,NA(),SUMIFS(RR_Score_Composito,RR_ID_Rischio,$A9,RR_Ciclo,G$3))) -> #N/A | H9: =IF(OR($A9="",H$3=""),NA(),IF(COUNTIFS(RR_ID_Rischio,$A9,RR_Ciclo,H$3)=0,NA(),SUMIFS(RR_Score_Composito,RR_ID_Rischio,$A9,RR_Ciclo,H$3))) -> #N/A | I9: =IF(OR($A9="",I$3=""),NA(),IF(COUNTIFS(RR_ID_Rischio,$A9,RR_Ciclo,I$3)=0,NA(),SUMIFS(RR_Score_Composito,RR_ID_Rischio,$A9,RR_Ciclo,I$3))) -> #N/A | J9: =IF(OR($A9="",J$3=""),NA(),IF(COUNTIFS(RR_ID_Rischio,$A9,RR_Ciclo,J$3)=0,NA(),SUMIFS(RR_Score_Composito,RR_ID_Rischio,$A9,RR_Ciclo,J$3))) -> 3
A10: =Dashboard!A19 -> NFR-07 | B10: =Dashboard!B19 -> Ransomware presso un fornitore di servizi di pagamento | C10: =IF(OR($A10="",C$3=""),NA(),IF(COUNTIFS(RR_ID_Rischio,$A10,RR_Ciclo,C$3)=0,NA(),SUMIFS(RR_Score_Composito,RR_ID_Rischio,$A10,RR_Ciclo,C$3))) -> #N/A | D10: =IF(OR($A10="",D$3=""),NA(),IF(COUNTIFS(RR_ID_Rischio,$A10,RR_Ciclo,D$3)=0,NA(),SUMIFS(RR_Score_Composito,RR_ID_Rischio,$A10,RR_Ciclo,D$3))) -> #N/A | E10: =IF(OR($A10="",E$3=""),NA(),IF(COUNTIFS(RR_ID_Rischio,$A10,RR_Ciclo,E$3)=0,NA(),SUMIFS(RR_Score_Composito,RR_ID_Rischio,$A10,RR_Ciclo,E$3))) -> #N/A | F10: =IF(OR($A10="",F$3=""),NA(),IF(COUNTIFS(RR_ID_Rischio,$A10,RR_Ciclo,F$3)=0,NA(),SUMIFS(RR_Score_Composito,RR_ID_Rischio,$A10,RR_Ciclo,F$3))) -> #N/A | G10: =IF(OR($A10="",G$3=""),NA(),IF(COUNTIFS(RR_ID_Rischio,$A10,RR_Ciclo,G$3)=0,NA(),SUMIFS(RR_Score_Composito,RR_ID_Rischio,$A10,RR_Ciclo,G$3))) -> #N/A | H10: =IF(OR($A10="",H$3=""),NA(),IF(COUNTIFS(RR_ID_Rischio,$A10,RR_Ciclo,H$3)=0,NA(),SUMIFS(RR_Score_Composito,RR_ID_Rischio,$A10,RR_Ciclo,H$3))) -> #N/A | I10: =IF(OR($A10="",I$3=""),NA(),IF(COUNTIFS(RR_ID_Rischio,$A10,RR_Ciclo,I$3)=0,NA(),SUMIFS(RR_Score_Composito,RR_ID_Rischio,$A10,RR_Ciclo,I$3))) -> #N/A | J10: =IF(OR($A10="",J$3=""),NA(),IF(COUNTIFS(RR_ID_Rischio,$A10,RR_Ciclo,J$3)=0,NA(),SUMIFS(RR_Score_Composito,RR_ID_Rischio,$A10,RR_Ciclo,J$3))) -> 3.8
A11: =Dashboard!A20 -> NFR-08 | B11: =Dashboard!B20 -> Accessi impropri di dipendenti ai dati dei clienti | C11: =IF(OR($A11="",C$3=""),NA(),IF(COUNTIFS(RR_ID_Rischio,$A11,RR_Ciclo,C$3)=0,NA(),SUMIFS(RR_Score_Composito,RR_ID_Rischio,$A11,RR_Ciclo,C$3))) -> #N/A | D11: =IF(OR($A11="",D$3=""),NA(),IF(COUNTIFS(RR_ID_Rischio,$A11,RR_Ciclo,D$3)=0,NA(),SUMIFS(RR_Score_Composito,RR_ID_Rischio,$A11,RR_Ciclo,D$3))) -> #N/A | E11: =IF(OR($A11="",E$3=""),NA(),IF(COUNTIFS(RR_ID_Rischio,$A11,RR_Ciclo,E$3)=0,NA(),SUMIFS(RR_Score_Composito,RR_ID_Rischio,$A11,RR_Ciclo,E$3))) -> #N/A | F11: =IF(OR($A11="",F$3=""),NA(),IF(COUNTIFS(RR_ID_Rischio,$A11,RR_Ciclo,F$3)=0,NA(),SUMIFS(RR_Score_Composito,RR_ID_Rischio,$A11,RR_Ciclo,F$3))) -> #N/A | G11: =IF(OR($A11="",G$3=""),NA(),IF(COUNTIFS(RR_ID_Rischio,$A11,RR_Ciclo,G$3)=0,NA(),SUMIFS(RR_Score_Composito,RR_ID_Rischio,$A11,RR_Ciclo,G$3))) -> #N/A | H11: =IF(OR($A11="",H$3=""),NA(),IF(COUNTIFS(RR_ID_Rischio,$A11,RR_Ciclo,H$3)=0,NA(),SUMIFS(RR_Score_Composito,RR_ID_Rischio,$A11,RR_Ciclo,H$3))) -> #N/A | I11: =IF(OR($A11="",I$3=""),NA(),IF(COUNTIFS(RR_ID_Rischio,$A11,RR_Ciclo,I$3)=0,NA(),SUMIFS(RR_Score_Composito,RR_ID_Rischio,$A11,RR_Ciclo,I$3))) -> #N/A | J11: =IF(OR($A11="",J$3=""),NA(),IF(COUNTIFS(RR_ID_Rischio,$A11,RR_Ciclo,J$3)=0,NA(),SUMIFS(RR_Score_Composito,RR_ID_Rischio,$A11,RR_Ciclo,J$3))) -> 3
A12: =Dashboard!A21 -> NFR-09 | B12: =Dashboard!B21 -> Violazione di sanzioni internazionali tramite triangolazioni | C12: =IF(OR($A12="",C$3=""),NA(),IF(COUNTIFS(RR_ID_Rischio,$A12,RR_Ciclo,C$3)=0,NA(),SUMIFS(RR_Score_Composito,RR_ID_Rischio,$A12,RR_Ciclo,C$3))) -> #N/A | D12: =IF(OR($A12="",D$3=""),NA(),IF(COUNTIFS(RR_ID_Rischio,$A12,RR_Ciclo,D$3)=0,NA(),SUMIFS(RR_Score_Composito,RR_ID_Rischio,$A12,RR_Ciclo,D$3))) -> #N/A | E12: =IF(OR($A12="",E$3=""),NA(),IF(COUNTIFS(RR_ID_Rischio,$A12,RR_Ciclo,E$3)=0,NA(),SUMIFS(RR_Score_Composito,RR_ID_Rischio,$A12,RR_Ciclo,E$3))) -> #N/A | F12: =IF(OR($A12="",F$3=""),NA(),IF(COUNTIFS(RR_ID_Rischio,$A12,RR_Ciclo,F$3)=0,NA(),SUMIFS(RR_Score_Composito,RR_ID_Rischio,$A12,RR_Ciclo,F$3))) -> #N/A | G12: =IF(OR($A12="",G$3=""),NA(),IF(COUNTIFS(RR_ID_Rischio,$A12,RR_Ciclo,G$3)=0,NA(),SUMIFS(RR_Score_Composito,RR_ID_Rischio,$A12,RR_Ciclo,G$3))) -> #N/A | H12: =IF(OR($A12="",H$3=""),NA(),IF(COUNTIFS(RR_ID_Rischio,$A12,RR_Ciclo,H$3)=0,NA(),SUMIFS(RR_Score_Composito,RR_ID_Rischio,$A12,RR_Ciclo,H$3))) -> #N/A | I12: =IF(OR($A12="",I$3=""),NA(),IF(COUNTIFS(RR_ID_Rischio,$A12,RR_Ciclo,I$3)=0,NA(),SUMIFS(RR_Score_Composito,RR_ID_Rischio,$A12,RR_Ciclo,I$3))) -> #N/A | J12: =IF(OR($A12="",J$3=""),NA(),IF(COUNTIFS(RR_ID_Rischio,$A12,RR_Ciclo,J$3)=0,NA(),SUMIFS(RR_Score_Composito,RR_ID_Rischio,$A12,RR_Ciclo,J$3))) -> 3.2
A13: =Dashboard!A22 -> NFR-10 | B13: =Dashboard!B22 -> Informazioni errate ai clienti da assistenti di AI generativa | C13: =IF(OR($A13="",C$3=""),NA(),IF(COUNTIFS(RR_ID_Rischio,$A13,RR_Ciclo,C$3)=0,NA(),SUMIFS(RR_Score_Composito,RR_ID_Rischio,$A13,RR_Ciclo,C$3))) -> #N/A | D13: =IF(OR($A13="",D$3=""),NA(),IF(COUNTIFS(RR_ID_Rischio,$A13,RR_Ciclo,D$3)=0,NA(),SUMIFS(RR_Score_Composito,RR_ID_Rischio,$A13,RR_Ciclo,D$3))) -> #N/A | E13: =IF(OR($A13="",E$3=""),NA(),IF(COUNTIFS(RR_ID_Rischio,$A13,RR_Ciclo,E$3)=0,NA(),SUMIFS(RR_Score_Composito,RR_ID_Rischio,$A13,RR_Ciclo,E$3))) -> #N/A | F13: =IF(OR($A13="",F$3=""),NA(),IF(COUNTIFS(RR_ID_Rischio,$A13,RR_Ciclo,F$3)=0,NA(),SUMIFS(RR_Score_Composito,RR_ID_Rischio,$A13,RR_Ciclo,F$3))) -> #N/A | G13: =IF(OR($A13="",G$3=""),NA(),IF(COUNTIFS(RR_ID_Rischio,$A13,RR_Ciclo,G$3)=0,NA(),SUMIFS(RR_Score_Composito,RR_ID_Rischio,$A13,RR_Ciclo,G$3))) -> #N/A | H13: =IF(OR($A13="",H$3=""),NA(),IF(COUNTIFS(RR_ID_Rischio,$A13,RR_Ciclo,H$3)=0,NA(),SUMIFS(RR_Score_Composito,RR_ID_Rischio,$A13,RR_Ciclo,H$3))) -> #N/A | I13: =IF(OR($A13="",I$3=""),NA(),IF(COUNTIFS(RR_ID_Rischio,$A13,RR_Ciclo,I$3)=0,NA(),SUMIFS(RR_Score_Composito,RR_ID_Rischio,$A13,RR_Ciclo,I$3))) -> #N/A | J13: =IF(OR($A13="",J$3=""),NA(),IF(COUNTIFS(RR_ID_Rischio,$A13,RR_Ciclo,J$3)=0,NA(),SUMIFS(RR_Score_Composito,RR_ID_Rischio,$A13,RR_Ciclo,J$3))) -> 3.2
A14: =Dashboard!A23 -> NFR-11 | B14: =Dashboard!B23 -> Fine del supporto dei sistemi di pagamento legacy | C14: =IF(OR($A14="",C$3=""),NA(),IF(COUNTIFS(RR_ID_Rischio,$A14,RR_Ciclo,C$3)=0,NA(),SUMIFS(RR_Score_Composito,RR_ID_Rischio,$A14,RR_Ciclo,C$3))) -> #N/A | D14: =IF(OR($A14="",D$3=""),NA(),IF(COUNTIFS(RR_ID_Rischio,$A14,RR_Ciclo,D$3)=0,NA(),SUMIFS(RR_Score_Composito,RR_ID_Rischio,$A14,RR_Ciclo,D$3))) -> #N/A | E14: =IF(OR($A14="",E$3=""),NA(),IF(COUNTIFS(RR_ID_Rischio,$A14,RR_Ciclo,E$3)=0,NA(),SUMIFS(RR_Score_Composito,RR_ID_Rischio,$A14,RR_Ciclo,E$3))) -> #N/A | F14: =IF(OR($A14="",F$3=""),NA(),IF(COUNTIFS(RR_ID_Rischio,$A14,RR_Ciclo,F$3)=0,NA(),SUMIFS(RR_Score_Composito,RR_ID_Rischio,$A14,RR_Ciclo,F$3))) -> #N/A | G14: =IF(OR($A14="",G$3=""),NA(),IF(COUNTIFS(RR_ID_Rischio,$A14,RR_Ciclo,G$3)=0,NA(),SUMIFS(RR_Score_Composito,RR_ID_Rischio,$A14,RR_Ciclo,G$3))) -> #N/A | H14: =IF(OR($A14="",H$3=""),NA(),IF(COUNTIFS(RR_ID_Rischio,$A14,RR_Ciclo,H$3)=0,NA(),SUMIFS(RR_Score_Composito,RR_ID_Rischio,$A14,RR_Ciclo,H$3))) -> #N/A | I14: =IF(OR($A14="",I$3=""),NA(),IF(COUNTIFS(RR_ID_Rischio,$A14,RR_Ciclo,I$3)=0,NA(),SUMIFS(RR_Score_Composito,RR_ID_Rischio,$A14,RR_Ciclo,I$3))) -> #N/A | J14: =IF(OR($A14="",J$3=""),NA(),IF(COUNTIFS(RR_ID_Rischio,$A14,RR_Ciclo,J$3)=0,NA(),SUMIFS(RR_Score_Composito,RR_ID_Rischio,$A14,RR_Ciclo,J$3))) -> 3
A15: =Dashboard!A24 -> NFR-12 | B15: =Dashboard!B24 -> Errori operativi nei pagamenti istantanei obbligatori | C15: =IF(OR($A15="",C$3=""),NA(),IF(COUNTIFS(RR_ID_Rischio,$A15,RR_Ciclo,C$3)=0,NA(),SUMIFS(RR_Score_Composito,RR_ID_Rischio,$A15,RR_Ciclo,C$3))) -> #N/A | D15: =IF(OR($A15="",D$3=""),NA(),IF(COUNTIFS(RR_ID_Rischio,$A15,RR_Ciclo,D$3)=0,NA(),SUMIFS(RR_Score_Composito,RR_ID_Rischio,$A15,RR_Ciclo,D$3))) -> #N/A | E15: =IF(OR($A15="",E$3=""),NA(),IF(COUNTIFS(RR_ID_Rischio,$A15,RR_Ciclo,E$3)=0,NA(),SUMIFS(RR_Score_Composito,RR_ID_Rischio,$A15,RR_Ciclo,E$3))) -> #N/A | F15: =IF(OR($A15="",F$3=""),NA(),IF(COUNTIFS(RR_ID_Rischio,$A15,RR_Ciclo,F$3)=0,NA(),SUMIFS(RR_Score_Composito,RR_ID_Rischio,$A15,RR_Ciclo,F$3))) -> #N/A | G15: =IF(OR($A15="",G$3=""),NA(),IF(COUNTIFS(RR_ID_Rischio,$A15,RR_Ciclo,G$3)=0,NA(),SUMIFS(RR_Score_Composito,RR_ID_Rischio,$A15,RR_Ciclo,G$3))) -> #N/A | H15: =IF(OR($A15="",H$3=""),NA(),IF(COUNTIFS(RR_ID_Rischio,$A15,RR_Ciclo,H$3)=0,NA(),SUMIFS(RR_Score_Composito,RR_ID_Rischio,$A15,RR_Ciclo,H$3))) -> #N/A | I15: =IF(OR($A15="",I$3=""),NA(),IF(COUNTIFS(RR_ID_Rischio,$A15,RR_Ciclo,I$3)=0,NA(),SUMIFS(RR_Score_Composito,RR_ID_Rischio,$A15,RR_Ciclo,I$3))) -> #N/A | J15: =IF(OR($A15="",J$3=""),NA(),IF(COUNTIFS(RR_ID_Rischio,$A15,RR_Ciclo,J$3)=0,NA(),SUMIFS(RR_Score_Composito,RR_ID_Rischio,$A15,RR_Ciclo,J$3))) -> 3.4
... A18: =Dashboard!A27 | B18: =Dashboard!B27 | C18: =IF(OR($A18="",C$3=""),NA(),IF(COUNTIFS(RR_ID_Rischio,$A18,RR_Ciclo,C$3)=0,NA(),SUMIFS(RR_Score_Composito,RR_ID_Rischio,$A18,RR_Ciclo,C$3))) -> #N/A | D18: =IF(OR($A18="",D$3=""),NA(),IF(COUNTIFS(RR_ID_Rischio,$A18,RR_Ciclo,D$3)=0,NA(),SUMIFS(RR_Score_Composito,RR_ID_Rischio,$A18,RR_Ciclo,D$3))) -> #N/A | E18: =IF(OR($A18="",E$3=""),NA(),IF(COUNTIFS(RR_ID_Rischio,$A18,RR_Ciclo,E$3)=0,NA(),SUMIFS(RR_Score_Composito,RR_ID_Rischio,$A18,RR_Ciclo,E$3))) -> #N/A | F18: =IF(OR($A18="",F$3=""),NA(),IF(COUNTIFS(RR_ID_Rischio,$A18,RR_Ciclo,F$3)=0,NA(),SUMIFS(RR_Score_Composito,RR_ID_Rischio,$A18,RR_Ciclo,F$3))) -> #N/A | G18: =IF(OR($A18="",G$3=""),NA(),IF(COUNTIFS(RR_ID_Rischio,$A18,RR_Ciclo,G$3)=0,NA(),SUMIFS(RR_Score_Composito,RR_ID_Rischio,$A18,RR_Ciclo,G$3))) -> #N/A | H18: =IF(OR($A18="",H$3=""),NA(),IF(COUNTIFS(RR_ID_Rischio,$A18,RR_Ciclo,H$3)=0,NA(),SUMIFS(RR_Score_Composito,RR_ID_Rischio,$A18,RR_Ciclo,H$3))) -> #N/A | I18: =IF(OR($A18="",I$3=""),NA(),IF(COUNTIFS(RR_ID_Rischio,$A18,RR_Ciclo,I$3)=0,NA(),SUMIFS(RR_Score_Composito,RR_ID_Rischio,$A18,RR_Ciclo,I$3))) -> #N/A | J18: =IF(OR($A18="",J$3=""),NA(),IF(COUNTIFS(RR_ID_Rischio,$A18,RR_Ciclo,J$3)=0,NA(),SUMIFS(RR_Score_Composito,RR_ID_Rischio,$A18,RR_Ciclo,J$3))) -> #N/A

Sheet Delta
A1: Delta — ciclo corrente contro ciclo precedente
A2: Evidenziato se |Delta score| >= soglia di Parametri. Nessuna dimensione puo' variare di piu' di un punto fra cicli consecutivi.
A3: ID | B3: Nome | C3: Δ Severity | D3: Δ Velocity | E3: Δ Prossimita' | F3: Δ Gap_Controlli | G3: Δ Confidence | H3: Δ Probabilita | I3: Δ Score | J3: Nota
A4: =Dashboard!A13 -> NFR-01 | B4: =Dashboard!B13 -> Frodi su pagamenti istantanei abilitate da AI generativa | C4: =IF($A4="",NA(),IF(COUNTIFS(RR_ID_Rischio,$A4,RR_Ciclo,cicloCorrente)*COUNTIFS(RR_ID_Rischio,$A4,RR_Ciclo,cicloPrecedente)=0,NA(),SUMIFS(RR_Severity,RR_ID_Rischio,$A4,RR_Ciclo,cicloCorrente)-SUMIFS(RR_Severity,RR_ID_Rischio,$A4,RR_Ciclo,cicloPrecedente))) -> #N/A | D4: =IF($A4="",NA(),IF(COUNTIFS(RR_ID_Rischio,$A4,RR_Ciclo,cicloCorrente)*COUNTIFS(RR_ID_Rischio,$A4,RR_Ciclo,cicloPrecedente)=0,NA(),SUMIFS(RR_Velocity,RR_ID_Rischio,$A4,RR_Ciclo,cicloCorrente)-SUMIFS(RR_Velocity,RR_ID_Rischio,$A4,RR_Ciclo,cicloPrecedente))) -> #N/A | E4: =IF($A4="",NA(),IF(COUNTIFS(RR_ID_Rischio,$A4,RR_Ciclo,cicloCorrente)*COUNTIFS(RR_ID_Rischio,$A4,RR_Ciclo,cicloPrecedente)=0,NA(),SUMIFS(RR_Prossimita,RR_ID_Rischio,$A4,RR_Ciclo,cicloCorrente)-SUMIFS(RR_Prossimita,RR_ID_Rischio,$A4,RR_Ciclo,cicloPrecedente))) -> #N/A | F4: =IF($A4="",NA(),IF(COUNTIFS(RR_ID_Rischio,$A4,RR_Ciclo,cicloCorrente)*COUNTIFS(RR_ID_Rischio,$A4,RR_Ciclo,cicloPrecedente)=0,NA(),SUMIFS(RR_Gap_Controlli,RR_ID_Rischio,$A4,RR_Ciclo,cicloCorrente)-SUMIFS(RR_Gap_Controlli,RR_ID_Rischio,$A4,RR_Ciclo,cicloPrecedente))) -> #N/A | G4: =IF($A4="",NA(),IF(COUNTIFS(RR_ID_Rischio,$A4,RR_Ciclo,cicloCorrente)*COUNTIFS(RR_ID_Rischio,$A4,RR_Ciclo,cicloPrecedente)=0,NA(),SUMIFS(RR_Confidence,RR_ID_Rischio,$A4,RR_Ciclo,cicloCorrente)-SUMIFS(RR_Confidence,RR_ID_Rischio,$A4,RR_Ciclo,cicloPrecedente))) -> #N/A | H4: =IF($A4="",NA(),IF(COUNTIFS(RR_ID_Rischio,$A4,RR_Ciclo,cicloCorrente)*COUNTIFS(RR_ID_Rischio,$A4,RR_Ciclo,cicloPrecedente)=0,NA(),SUMIFS(RR_Probabilita,RR_ID_Rischio,$A4,RR_Ciclo,cicloCorrente)-SUMIFS(RR_Probabilita,RR_ID_Rischio,$A4,RR_Ciclo,cicloPrecedente))) -> #N/A | I4: =IF($A4="",NA(),IF(COUNTIFS(RR_ID_Rischio,$A4,RR_Ciclo,cicloCorrente)*COUNTIFS(RR_ID_Rischio,$A4,RR_Ciclo,cicloPrecedente)=0,NA(),SUMIFS(RR_Score_Composito,RR_ID_Rischio,$A4,RR_Ciclo,cicloCorrente)-SUMIFS(RR_Score_Composito,RR_ID_Rischio,$A4,RR_Ciclo,cicloPrecedente))) -> #N/A | J4: =IF($A4="","",IF(COUNT(C4:H4)<6,"Nuovo o non valutato in uno dei due cicli",IF(MAX(C4:H4)>1,"Aumento > 1 punto: viola la rubrica",IF(MIN(C4:H4)<-1,"Riduzione > 1 punto: viola la rubrica","")))) -> Nuovo o non valutato in uno dei due cicli
A5: =Dashboard!A14 -> NFR-02 | B5: =Dashboard!B14 -> Concentrazione su un fornitore cloud critico | C5: =IF($A5="",NA(),IF(COUNTIFS(RR_ID_Rischio,$A5,RR_Ciclo,cicloCorrente)*COUNTIFS(RR_ID_Rischio,$A5,RR_Ciclo,cicloPrecedente)=0,NA(),SUMIFS(RR_Severity,RR_ID_Rischio,$A5,RR_Ciclo,cicloCorrente)-SUMIFS(RR_Severity,RR_ID_Rischio,$A5,RR_Ciclo,cicloPrecedente))) -> #N/A | D5: =IF($A5="",NA(),IF(COUNTIFS(RR_ID_Rischio,$A5,RR_Ciclo,cicloCorrente)*COUNTIFS(RR_ID_Rischio,$A5,RR_Ciclo,cicloPrecedente)=0,NA(),SUMIFS(RR_Velocity,RR_ID_Rischio,$A5,RR_Ciclo,cicloCorrente)-SUMIFS(RR_Velocity,RR_ID_Rischio,$A5,RR_Ciclo,cicloPrecedente))) -> #N/A | E5: =IF($A5="",NA(),IF(COUNTIFS(RR_ID_Rischio,$A5,RR_Ciclo,cicloCorrente)*COUNTIFS(RR_ID_Rischio,$A5,RR_Ciclo,cicloPrecedente)=0,NA(),SUMIFS(RR_Prossimita,RR_ID_Rischio,$A5,RR_Ciclo,cicloCorrente)-SUMIFS(RR_Prossimita,RR_ID_Rischio,$A5,RR_Ciclo,cicloPrecedente))) -> #N/A | F5: =IF($A5="",NA(),IF(COUNTIFS(RR_ID_Rischio,$A5,RR_Ciclo,cicloCorrente)*COUNTIFS(RR_ID_Rischio,$A5,RR_Ciclo,cicloPrecedente)=0,NA(),SUMIFS(RR_Gap_Controlli,RR_ID_Rischio,$A5,RR_Ciclo,cicloCorrente)-SUMIFS(RR_Gap_Controlli,RR_ID_Rischio,$A5,RR_Ciclo,cicloPrecedente))) -> #N/A | G5: =IF($A5="",NA(),IF(COUNTIFS(RR_ID_Rischio,$A5,RR_Ciclo,cicloCorrente)*COUNTIFS(RR_ID_Rischio,$A5,RR_Ciclo,cicloPrecedente)=0,NA(),SUMIFS(RR_Confidence,RR_ID_Rischio,$A5,RR_Ciclo,cicloCorrente)-SUMIFS(RR_Confidence,RR_ID_Rischio,$A5,RR_Ciclo,cicloPrecedente))) -> #N/A | H5: =IF($A5="",NA(),IF(COUNTIFS(RR_ID_Rischio,$A5,RR_Ciclo,cicloCorrente)*COUNTIFS(RR_ID_Rischio,$A5,RR_Ciclo,cicloPrecedente)=0,NA(),SUMIFS(RR_Probabilita,RR_ID_Rischio,$A5,RR_Ciclo,cicloCorrente)-SUMIFS(RR_Probabilita,RR_ID_Rischio,$A5,RR_Ciclo,cicloPrecedente))) -> #N/A | I5: =IF($A5="",NA(),IF(COUNTIFS(RR_ID_Rischio,$A5,RR_Ciclo,cicloCorrente)*COUNTIFS(RR_ID_Rischio,$A5,RR_Ciclo,cicloPrecedente)=0,NA(),SUMIFS(RR_Score_Composito,RR_ID_Rischio,$A5,RR_Ciclo,cicloCorrente)-SUMIFS(RR_Score_Composito,RR_ID_Rischio,$A5,RR_Ciclo,cicloPrecedente))) -> #N/A | J5: =IF($A5="","",IF(COUNT(C5:H5)<6,"Nuovo o non valutato in uno dei due cicli",IF(MAX(C5:H5)>1,"Aumento > 1 punto: viola la rubrica",IF(MIN(C5:H5)<-1,"Riduzione > 1 punto: viola la rubrica","")))) -> Nuovo o non valutato in uno dei due cicli
A6: =Dashboard!A15 -> NFR-03 | B6: =Dashboard!B15 -> Greenwashing nella commercializzazione di prodotti ESG | C6: =IF($A6="",NA(),IF(COUNTIFS(RR_ID_Rischio,$A6,RR_Ciclo,cicloCorrente)*COUNTIFS(RR_ID_Rischio,$A6,RR_Ciclo,cicloPrecedente)=0,NA(),SUMIFS(RR_Severity,RR_ID_Rischio,$A6,RR_Ciclo,cicloCorrente)-SUMIFS(RR_Severity,RR_ID_Rischio,$A6,RR_Ciclo,cicloPrecedente))) -> #N/A | D6: =IF($A6="",NA(),IF(COUNTIFS(RR_ID_Rischio,$A6,RR_Ciclo,cicloCorrente)*COUNTIFS(RR_ID_Rischio,$A6,RR_Ciclo,cicloPrecedente)=0,NA(),SUMIFS(RR_Velocity,RR_ID_Rischio,$A6,RR_Ciclo,cicloCorrente)-SUMIFS(RR_Velocity,RR_ID_Rischio,$A6,RR_Ciclo,cicloPrecedente))) -> #N/A | E6: =IF($A6="",NA(),IF(COUNTIFS(RR_ID_Rischio,$A6,RR_Ciclo,cicloCorrente)*COUNTIFS(RR_ID_Rischio,$A6,RR_Ciclo,cicloPrecedente)=0,NA(),SUMIFS(RR_Prossimita,RR_ID_Rischio,$A6,RR_Ciclo,cicloCorrente)-SUMIFS(RR_Prossimita,RR_ID_Rischio,$A6,RR_Ciclo,cicloPrecedente))) -> #N/A | F6: =IF($A6="",NA(),IF(COUNTIFS(RR_ID_Rischio,$A6,RR_Ciclo,cicloCorrente)*COUNTIFS(RR_ID_Rischio,$A6,RR_Ciclo,cicloPrecedente)=0,NA(),SUMIFS(RR_Gap_Controlli,RR_ID_Rischio,$A6,RR_Ciclo,cicloCorrente)-SUMIFS(RR_Gap_Controlli,RR_ID_Rischio,$A6,RR_Ciclo,cicloPrecedente))) -> #N/A | G6: =IF($A6="",NA(),IF(COUNTIFS(RR_ID_Rischio,$A6,RR_Ciclo,cicloCorrente)*COUNTIFS(RR_ID_Rischio,$A6,RR_Ciclo,cicloPrecedente)=0,NA(),SUMIFS(RR_Confidence,RR_ID_Rischio,$A6,RR_Ciclo,cicloCorrente)-SUMIFS(RR_Confidence,RR_ID_Rischio,$A6,RR_Ciclo,cicloPrecedente))) -> #N/A | H6: =IF($A6="",NA(),IF(COUNTIFS(RR_ID_Rischio,$A6,RR_Ciclo,cicloCorrente)*COUNTIFS(RR_ID_Rischio,$A6,RR_Ciclo,cicloPrecedente)=0,NA(),SUMIFS(RR_Probabilita,RR_ID_Rischio,$A6,RR_Ciclo,cicloCorrente)-SUMIFS(RR_Probabilita,RR_ID_Rischio,$A6,RR_Ciclo,cicloPrecedente))) -> #N/A | I6: =IF($A6="",NA(),IF(COUNTIFS(RR_ID_Rischio,$A6,RR_Ciclo,cicloCorrente)*COUNTIFS(RR_ID_Rischio,$A6,RR_Ciclo,cicloPrecedente)=0,NA(),SUMIFS(RR_Score_Composito,RR_ID_Rischio,$A6,RR_Ciclo,cicloCorrente)-SUMIFS(RR_Score_Composito,RR_ID_Rischio,$A6,RR_Ciclo,cicloPrecedente))) -> #N/A | J6: =IF($A6="","",IF(COUNT(C6:H6)<6,"Nuovo o non valutato in uno dei due cicli",IF(MAX(C6:H6)>1,"Aumento > 1 punto: viola la rubrica",IF(MIN(C6:H6)<-1,"Riduzione > 1 punto: viola la rubrica","")))) -> Nuovo o non valutato in uno dei due cicli
A7: =Dashboard!A16 -> NFR-04 | B7: =Dashboard!B16 -> Eventi climatici estremi su sedi e data center | C7: =IF($A7="",NA(),IF(COUNTIFS(RR_ID_Rischio,$A7,RR_Ciclo,cicloCorrente)*COUNTIFS(RR_ID_Rischio,$A7,RR_Ciclo,cicloPrecedente)=0,NA(),SUMIFS(RR_Severity,RR_ID_Rischio,$A7,RR_Ciclo,cicloCorrente)-SUMIFS(RR_Severity,RR_ID_Rischio,$A7,RR_Ciclo,cicloPrecedente))) -> #N/A | D7: =IF($A7="",NA(),IF(COUNTIFS(RR_ID_Rischio,$A7,RR_Ciclo,cicloCorrente)*COUNTIFS(RR_ID_Rischio,$A7,RR_Ciclo,cicloPrecedente)=0,NA(),SUMIFS(RR_Velocity,RR_ID_Rischio,$A7,RR_Ciclo,cicloCorrente)-SUMIFS(RR_Velocity,RR_ID_Rischio,$A7,RR_Ciclo,cicloPrecedente))) -> #N/A | E7: =IF($A7="",NA(),IF(COUNTIFS(RR_ID_Rischio,$A7,RR_Ciclo,cicloCorrente)*COUNTIFS(RR_ID_Rischio,$A7,RR_Ciclo,cicloPrecedente)=0,NA(),SUMIFS(RR_Prossimita,RR_ID_Rischio,$A7,RR_Ciclo,cicloCorrente)-SUMIFS(RR_Prossimita,RR_ID_Rischio,$A7,RR_Ciclo,cicloPrecedente))) -> #N/A | F7: =IF($A7="",NA(),IF(COUNTIFS(RR_ID_Rischio,$A7,RR_Ciclo,cicloCorrente)*COUNTIFS(RR_ID_Rischio,$A7,RR_Ciclo,cicloPrecedente)=0,NA(),SUMIFS(RR_Gap_Controlli,RR_ID_Rischio,$A7,RR_Ciclo,cicloCorrente)-SUMIFS(RR_Gap_Controlli,RR_ID_Rischio,$A7,RR_Ciclo,cicloPrecedente))) -> #N/A | G7: =IF($A7="",NA(),IF(COUNTIFS(RR_ID_Rischio,$A7,RR_Ciclo,cicloCorrente)*COUNTIFS(RR_ID_Rischio,$A7,RR_Ciclo,cicloPrecedente)=0,NA(),SUMIFS(RR_Confidence,RR_ID_Rischio,$A7,RR_Ciclo,cicloCorrente)-SUMIFS(RR_Confidence,RR_ID_Rischio,$A7,RR_Ciclo,cicloPrecedente))) -> #N/A | H7: =IF($A7="",NA(),IF(COUNTIFS(RR_ID_Rischio,$A7,RR_Ciclo,cicloCorrente)*COUNTIFS(RR_ID_Rischio,$A7,RR_Ciclo,cicloPrecedente)=0,NA(),SUMIFS(RR_Probabilita,RR_ID_Rischio,$A7,RR_Ciclo,cicloCorrente)-SUMIFS(RR_Probabilita,RR_ID_Rischio,$A7,RR_Ciclo,cicloPrecedente))) -> #N/A | I7: =IF($A7="",NA(),IF(COUNTIFS(RR_ID_Rischio,$A7,RR_Ciclo,cicloCorrente)*COUNTIFS(RR_ID_Rischio,$A7,RR_Ciclo,cicloPrecedente)=0,NA(),SUMIFS(RR_Score_Composito,RR_ID_Rischio,$A7,RR_Ciclo,cicloCorrente)-SUMIFS(RR_Score_Composito,RR_ID_Rischio,$A7,RR_Ciclo,cicloPrecedente))) -> #N/A | J7: =IF($A7="","",IF(COUNT(C7:H7)<6,"Nuovo o non valutato in uno dei due cicli",IF(MAX(C7:H7)>1,"Aumento > 1 punto: viola la rubrica",IF(MIN(C7:H7)<-1,"Riduzione > 1 punto: viola la rubrica","")))) -> Nuovo o non valutato in uno dei due cicli
A8: =Dashboard!A17 -> NFR-05 | B8: =Dashboard!B17 -> Errori di processo nella migrazione del core banking | C8: =IF($A8="",NA(),IF(COUNTIFS(RR_ID_Rischio,$A8,RR_Ciclo,cicloCorrente)*COUNTIFS(RR_ID_Rischio,$A8,RR_Ciclo,cicloPrecedente)=0,NA(),SUMIFS(RR_Severity,RR_ID_Rischio,$A8,RR_Ciclo,cicloCorrente)-SUMIFS(RR_Severity,RR_ID_Rischio,$A8,RR_Ciclo,cicloPrecedente))) -> #N/A | D8: =IF($A8="",NA(),IF(COUNTIFS(RR_ID_Rischio,$A8,RR_Ciclo,cicloCorrente)*COUNTIFS(RR_ID_Rischio,$A8,RR_Ciclo,cicloPrecedente)=0,NA(),SUMIFS(RR_Velocity,RR_ID_Rischio,$A8,RR_Ciclo,cicloCorrente)-SUMIFS(RR_Velocity,RR_ID_Rischio,$A8,RR_Ciclo,cicloPrecedente))) -> #N/A | E8: =IF($A8="",NA(),IF(COUNTIFS(RR_ID_Rischio,$A8,RR_Ciclo,cicloCorrente)*COUNTIFS(RR_ID_Rischio,$A8,RR_Ciclo,cicloPrecedente)=0,NA(),SUMIFS(RR_Prossimita,RR_ID_Rischio,$A8,RR_Ciclo,cicloCorrente)-SUMIFS(RR_Prossimita,RR_ID_Rischio,$A8,RR_Ciclo,cicloPrecedente))) -> #N/A | F8: =IF($A8="",NA(),IF(COUNTIFS(RR_ID_Rischio,$A8,RR_Ciclo,cicloCorrente)*COUNTIFS(RR_ID_Rischio,$A8,RR_Ciclo,cicloPrecedente)=0,NA(),SUMIFS(RR_Gap_Controlli,RR_ID_Rischio,$A8,RR_Ciclo,cicloCorrente)-SUMIFS(RR_Gap_Controlli,RR_ID_Rischio,$A8,RR_Ciclo,cicloPrecedente))) -> #N/A | G8: =IF($A8="",NA(),IF(COUNTIFS(RR_ID_Rischio,$A8,RR_Ciclo,cicloCorrente)*COUNTIFS(RR_ID_Rischio,$A8,RR_Ciclo,cicloPrecedente)=0,NA(),SUMIFS(RR_Confidence,RR_ID_Rischio,$A8,RR_Ciclo,cicloCorrente)-SUMIFS(RR_Confidence,RR_ID_Rischio,$A8,RR_Ciclo,cicloPrecedente))) -> #N/A | H8: =IF($A8="",NA(),IF(COUNTIFS(RR_ID_Rischio,$A8,RR_Ciclo,cicloCorrente)*COUNTIFS(RR_ID_Rischio,$A8,RR_Ciclo,cicloPrecedente)=0,NA(),SUMIFS(RR_Probabilita,RR_ID_Rischio,$A8,RR_Ciclo,cicloCorrente)-SUMIFS(RR_Probabilita,RR_ID_Rischio,$A8,RR_Ciclo,cicloPrecedente))) -> #N/A | I8: =IF($A8="",NA(),IF(COUNTIFS(RR_ID_Rischio,$A8,RR_Ciclo,cicloCorrente)*COUNTIFS(RR_ID_Rischio,$A8,RR_Ciclo,cicloPrecedente)=0,NA(),SUMIFS(RR_Score_Composito,RR_ID_Rischio,$A8,RR_Ciclo,cicloCorrente)-SUMIFS(RR_Score_Composito,RR_ID_Rischio,$A8,RR_Ciclo,cicloPrecedente))) -> #N/A | J8: =IF($A8="","",IF(COUNT(C8:H8)<6,"Nuovo o non valutato in uno dei due cicli",IF(MAX(C8:H8)>1,"Aumento > 1 punto: viola la rubrica",IF(MIN(C8:H8)<-1,"Riduzione > 1 punto: viola la rubrica","")))) -> Nuovo o non valutato in uno dei due cicli
A9: =Dashboard!A18 -> NFR-06 | B9: =Dashboard!B18 -> Esfiltrazione di dati tramite strumenti di AI non autorizzati | C9: =IF($A9="",NA(),IF(COUNTIFS(RR_ID_Rischio,$A9,RR_Ciclo,cicloCorrente)*COUNTIFS(RR_ID_Rischio,$A9,RR_Ciclo,cicloPrecedente)=0,NA(),SUMIFS(RR_Severity,RR_ID_Rischio,$A9,RR_Ciclo,cicloCorrente)-SUMIFS(RR_Severity,RR_ID_Rischio,$A9,RR_Ciclo,cicloPrecedente))) -> #N/A | D9: =IF($A9="",NA(),IF(COUNTIFS(RR_ID_Rischio,$A9,RR_Ciclo,cicloCorrente)*COUNTIFS(RR_ID_Rischio,$A9,RR_Ciclo,cicloPrecedente)=0,NA(),SUMIFS(RR_Velocity,RR_ID_Rischio,$A9,RR_Ciclo,cicloCorrente)-SUMIFS(RR_Velocity,RR_ID_Rischio,$A9,RR_Ciclo,cicloPrecedente))) -> #N/A | E9: =IF($A9="",NA(),IF(COUNTIFS(RR_ID_Rischio,$A9,RR_Ciclo,cicloCorrente)*COUNTIFS(RR_ID_Rischio,$A9,RR_Ciclo,cicloPrecedente)=0,NA(),SUMIFS(RR_Prossimita,RR_ID_Rischio,$A9,RR_Ciclo,cicloCorrente)-SUMIFS(RR_Prossimita,RR_ID_Rischio,$A9,RR_Ciclo,cicloPrecedente))) -> #N/A | F9: =IF($A9="",NA(),IF(COUNTIFS(RR_ID_Rischio,$A9,RR_Ciclo,cicloCorrente)*COUNTIFS(RR_ID_Rischio,$A9,RR_Ciclo,cicloPrecedente)=0,NA(),SUMIFS(RR_Gap_Controlli,RR_ID_Rischio,$A9,RR_Ciclo,cicloCorrente)-SUMIFS(RR_Gap_Controlli,RR_ID_Rischio,$A9,RR_Ciclo,cicloPrecedente))) -> #N/A | G9: =IF($A9="",NA(),IF(COUNTIFS(RR_ID_Rischio,$A9,RR_Ciclo,cicloCorrente)*COUNTIFS(RR_ID_Rischio,$A9,RR_Ciclo,cicloPrecedente)=0,NA(),SUMIFS(RR_Confidence,RR_ID_Rischio,$A9,RR_Ciclo,cicloCorrente)-SUMIFS(RR_Confidence,RR_ID_Rischio,$A9,RR_Ciclo,cicloPrecedente))) -> #N/A | H9: =IF($A9="",NA(),IF(COUNTIFS(RR_ID_Rischio,$A9,RR_Ciclo,cicloCorrente)*COUNTIFS(RR_ID_Rischio,$A9,RR_Ciclo,cicloPrecedente)=0,NA(),SUMIFS(RR_Probabilita,RR_ID_Rischio,$A9,RR_Ciclo,cicloCorrente)-SUMIFS(RR_Probabilita,RR_ID_Rischio,$A9,RR_Ciclo,cicloPrecedente))) -> #N/A | I9: =IF($A9="",NA(),IF(COUNTIFS(RR_ID_Rischio,$A9,RR_Ciclo,cicloCorrente)*COUNTIFS(RR_ID_Rischio,$A9,RR_Ciclo,cicloPrecedente)=0,NA(),SUMIFS(RR_Score_Composito,RR_ID_Rischio,$A9,RR_Ciclo,cicloCorrente)-SUMIFS(RR_Score_Composito,RR_ID_Rischio,$A9,RR_Ciclo,cicloPrecedente))) -> #N/A | J9: =IF($A9="","",IF(COUNT(C9:H9)<6,"Nuovo o non valutato in uno dei due cicli",IF(MAX(C9:H9)>1,"Aumento > 1 punto: viola la rubrica",IF(MIN(C9:H9)<-1,"Riduzione > 1 punto: viola la rubrica","")))) -> Nuovo o non valutato in uno dei due cicli
A10: =Dashboard!A19 -> NFR-07 | B10: =Dashboard!B19 -> Ransomware presso un fornitore di servizi di pagamento | C10: =IF($A10="",NA(),IF(COUNTIFS(RR_ID_Rischio,$A10,RR_Ciclo,cicloCorrente)*COUNTIFS(RR_ID_Rischio,$A10,RR_Ciclo,cicloPrecedente)=0,NA(),SUMIFS(RR_Severity,RR_ID_Rischio,$A10,RR_Ciclo,cicloCorrente)-SUMIFS(RR_Severity,RR_ID_Rischio,$A10,RR_Ciclo,cicloPrecedente))) -> #N/A | D10: =IF($A10="",NA(),IF(COUNTIFS(RR_ID_Rischio,$A10,RR_Ciclo,cicloCorrente)*COUNTIFS(RR_ID_Rischio,$A10,RR_Ciclo,cicloPrecedente)=0,NA(),SUMIFS(RR_Velocity,RR_ID_Rischio,$A10,RR_Ciclo,cicloCorrente)-SUMIFS(RR_Velocity,RR_ID_Rischio,$A10,RR_Ciclo,cicloPrecedente))) -> #N/A | E10: =IF($A10="",NA(),IF(COUNTIFS(RR_ID_Rischio,$A10,RR_Ciclo,cicloCorrente)*COUNTIFS(RR_ID_Rischio,$A10,RR_Ciclo,cicloPrecedente)=0,NA(),SUMIFS(RR_Prossimita,RR_ID_Rischio,$A10,RR_Ciclo,cicloCorrente)-SUMIFS(RR_Prossimita,RR_ID_Rischio,$A10,RR_Ciclo,cicloPrecedente))) -> #N/A | F10: =IF($A10="",NA(),IF(COUNTIFS(RR_ID_Rischio,$A10,RR_Ciclo,cicloCorrente)*COUNTIFS(RR_ID_Rischio,$A10,RR_Ciclo,cicloPrecedente)=0,NA(),SUMIFS(RR_Gap_Controlli,RR_ID_Rischio,$A10,RR_Ciclo,cicloCorrente)-SUMIFS(RR_Gap_Controlli,RR_ID_Rischio,$A10,RR_Ciclo,cicloPrecedente))) -> #N/A | G10: =IF($A10="",NA(),IF(COUNTIFS(RR_ID_Rischio,$A10,RR_Ciclo,cicloCorrente)*COUNTIFS(RR_ID_Rischio,$A10,RR_Ciclo,cicloPrecedente)=0,NA(),SUMIFS(RR_Confidence,RR_ID_Rischio,$A10,RR_Ciclo,cicloCorrente)-SUMIFS(RR_Confidence,RR_ID_Rischio,$A10,RR_Ciclo,cicloPrecedente))) -> #N/A | H10: =IF($A10="",NA(),IF(COUNTIFS(RR_ID_Rischio,$A10,RR_Ciclo,cicloCorrente)*COUNTIFS(RR_ID_Rischio,$A10,RR_Ciclo,cicloPrecedente)=0,NA(),SUMIFS(RR_Probabilita,RR_ID_Rischio,$A10,RR_Ciclo,cicloCorrente)-SUMIFS(RR_Probabilita,RR_ID_Rischio,$A10,RR_Ciclo,cicloPrecedente))) -> #N/A | I10: =IF($A10="",NA(),IF(COUNTIFS(RR_ID_Rischio,$A10,RR_Ciclo,cicloCorrente)*COUNTIFS(RR_ID_Rischio,$A10,RR_Ciclo,cicloPrecedente)=0,NA(),SUMIFS(RR_Score_Composito,RR_ID_Rischio,$A10,RR_Ciclo,cicloCorrente)-SUMIFS(RR_Score_Composito,RR_ID_Rischio,$A10,RR_Ciclo,cicloPrecedente))) -> #N/A | J10: =IF($A10="","",IF(COUNT(C10:H10)<6,"Nuovo o non valutato in uno dei due cicli",IF(MAX(C10:H10)>1,"Aumento > 1 punto: viola la rubrica",IF(MIN(C10:H10)<-1,"Riduzione > 1 punto: viola la rubrica","")))) -> Nuovo o non valutato in uno dei due cicli
A11: =Dashboard!A20 -> NFR-08 | B11: =Dashboard!B20 -> Accessi impropri di dipendenti ai dati dei clienti | C11: =IF($A11="",NA(),IF(COUNTIFS(RR_ID_Rischio,$A11,RR_Ciclo,cicloCorrente)*COUNTIFS(RR_ID_Rischio,$A11,RR_Ciclo,cicloPrecedente)=0,NA(),SUMIFS(RR_Severity,RR_ID_Rischio,$A11,RR_Ciclo,cicloCorrente)-SUMIFS(RR_Severity,RR_ID_Rischio,$A11,RR_Ciclo,cicloPrecedente))) -> #N/A | D11: =IF($A11="",NA(),IF(COUNTIFS(RR_ID_Rischio,$A11,RR_Ciclo,cicloCorrente)*COUNTIFS(RR_ID_Rischio,$A11,RR_Ciclo,cicloPrecedente)=0,NA(),SUMIFS(RR_Velocity,RR_ID_Rischio,$A11,RR_Ciclo,cicloCorrente)-SUMIFS(RR_Velocity,RR_ID_Rischio,$A11,RR_Ciclo,cicloPrecedente))) -> #N/A | E11: =IF($A11="",NA(),IF(COUNTIFS(RR_ID_Rischio,$A11,RR_Ciclo,cicloCorrente)*COUNTIFS(RR_ID_Rischio,$A11,RR_Ciclo,cicloPrecedente)=0,NA(),SUMIFS(RR_Prossimita,RR_ID_Rischio,$A11,RR_Ciclo,cicloCorrente)-SUMIFS(RR_Prossimita,RR_ID_Rischio,$A11,RR_Ciclo,cicloPrecedente))) -> #N/A | F11: =IF($A11="",NA(),IF(COUNTIFS(RR_ID_Rischio,$A11,RR_Ciclo,cicloCorrente)*COUNTIFS(RR_ID_Rischio,$A11,RR_Ciclo,cicloPrecedente)=0,NA(),SUMIFS(RR_Gap_Controlli,RR_ID_Rischio,$A11,RR_Ciclo,cicloCorrente)-SUMIFS(RR_Gap_Controlli,RR_ID_Rischio,$A11,RR_Ciclo,cicloPrecedente))) -> #N/A | G11: =IF($A11="",NA(),IF(COUNTIFS(RR_ID_Rischio,$A11,RR_Ciclo,cicloCorrente)*COUNTIFS(RR_ID_Rischio,$A11,RR_Ciclo,cicloPrecedente)=0,NA(),SUMIFS(RR_Confidence,RR_ID_Rischio,$A11,RR_Ciclo,cicloCorrente)-SUMIFS(RR_Confidence,RR_ID_Rischio,$A11,RR_Ciclo,cicloPrecedente))) -> #N/A | H11: =IF($A11="",NA(),IF(COUNTIFS(RR_ID_Rischio,$A11,RR_Ciclo,cicloCorrente)*COUNTIFS(RR_ID_Rischio,$A11,RR_Ciclo,cicloPrecedente)=0,NA(),SUMIFS(RR_Probabilita,RR_ID_Rischio,$A11,RR_Ciclo,cicloCorrente)-SUMIFS(RR_Probabilita,RR_ID_Rischio,$A11,RR_Ciclo,cicloPrecedente))) -> #N/A | I11: =IF($A11="",NA(),IF(COUNTIFS(RR_ID_Rischio,$A11,RR_Ciclo,cicloCorrente)*COUNTIFS(RR_ID_Rischio,$A11,RR_Ciclo,cicloPrecedente)=0,NA(),SUMIFS(RR_Score_Composito,RR_ID_Rischio,$A11,RR_Ciclo,cicloCorrente)-SUMIFS(RR_Score_Composito,RR_ID_Rischio,$A11,RR_Ciclo,cicloPrecedente))) -> #N/A | J11: =IF($A11="","",IF(COUNT(C11:H11)<6,"Nuovo o non valutato in uno dei due cicli",IF(MAX(C11:H11)>1,"Aumento > 1 punto: viola la rubrica",IF(MIN(C11:H11)<-1,"Riduzione > 1 punto: viola la rubrica","")))) -> Nuovo o non valutato in uno dei due cicli
A12: =Dashboard!A21 -> NFR-09 | B12: =Dashboard!B21 -> Violazione di sanzioni internazionali tramite triangolazioni | C12: =IF($A12="",NA(),IF(COUNTIFS(RR_ID_Rischio,$A12,RR_Ciclo,cicloCorrente)*COUNTIFS(RR_ID_Rischio,$A12,RR_Ciclo,cicloPrecedente)=0,NA(),SUMIFS(RR_Severity,RR_ID_Rischio,$A12,RR_Ciclo,cicloCorrente)-SUMIFS(RR_Severity,RR_ID_Rischio,$A12,RR_Ciclo,cicloPrecedente))) -> #N/A | D12: =IF($A12="",NA(),IF(COUNTIFS(RR_ID_Rischio,$A12,RR_Ciclo,cicloCorrente)*COUNTIFS(RR_ID_Rischio,$A12,RR_Ciclo,cicloPrecedente)=0,NA(),SUMIFS(RR_Velocity,RR_ID_Rischio,$A12,RR_Ciclo,cicloCorrente)-SUMIFS(RR_Velocity,RR_ID_Rischio,$A12,RR_Ciclo,cicloPrecedente))) -> #N/A | E12: =IF($A12="",NA(),IF(COUNTIFS(RR_ID_Rischio,$A12,RR_Ciclo,cicloCorrente)*COUNTIFS(RR_ID_Rischio,$A12,RR_Ciclo,cicloPrecedente)=0,NA(),SUMIFS(RR_Prossimita,RR_ID_Rischio,$A12,RR_Ciclo,cicloCorrente)-SUMIFS(RR_Prossimita,RR_ID_Rischio,$A12,RR_Ciclo,cicloPrecedente))) -> #N/A | F12: =IF($A12="",NA(),IF(COUNTIFS(RR_ID_Rischio,$A12,RR_Ciclo,cicloCorrente)*COUNTIFS(RR_ID_Rischio,$A12,RR_Ciclo,cicloPrecedente)=0,NA(),SUMIFS(RR_Gap_Controlli,RR_ID_Rischio,$A12,RR_Ciclo,cicloCorrente)-SUMIFS(RR_Gap_Controlli,RR_ID_Rischio,$A12,RR_Ciclo,cicloPrecedente))) -> #N/A | G12: =IF($A12="",NA(),IF(COUNTIFS(RR_ID_Rischio,$A12,RR_Ciclo,cicloCorrente)*COUNTIFS(RR_ID_Rischio,$A12,RR_Ciclo,cicloPrecedente)=0,NA(),SUMIFS(RR_Confidence,RR_ID_Rischio,$A12,RR_Ciclo,cicloCorrente)-SUMIFS(RR_Confidence,RR_ID_Rischio,$A12,RR_Ciclo,cicloPrecedente))) -> #N/A | H12: =IF($A12="",NA(),IF(COUNTIFS(RR_ID_Rischio,$A12,RR_Ciclo,cicloCorrente)*COUNTIFS(RR_ID_Rischio,$A12,RR_Ciclo,cicloPrecedente)=0,NA(),SUMIFS(RR_Probabilita,RR_ID_Rischio,$A12,RR_Ciclo,cicloCorrente)-SUMIFS(RR_Probabilita,RR_ID_Rischio,$A12,RR_Ciclo,cicloPrecedente))) -> #N/A | I12: =IF($A12="",NA(),IF(COUNTIFS(RR_ID_Rischio,$A12,RR_Ciclo,cicloCorrente)*COUNTIFS(RR_ID_Rischio,$A12,RR_Ciclo,cicloPrecedente)=0,NA(),SUMIFS(RR_Score_Composito,RR_ID_Rischio,$A12,RR_Ciclo,cicloCorrente)-SUMIFS(RR_Score_Composito,RR_ID_Rischio,$A12,RR_Ciclo,cicloPrecedente))) -> #N/A | J12: =IF($A12="","",IF(COUNT(C12:H12)<6,"Nuovo o non valutato in uno dei due cicli",IF(MAX(C12:H12)>1,"Aumento > 1 punto: viola la rubrica",IF(MIN(C12:H12)<-1,"Riduzione > 1 punto: viola la rubrica","")))) -> Nuovo o non valutato in uno dei due cicli
A13: =Dashboard!A22 -> NFR-10 | B13: =Dashboard!B22 -> Informazioni errate ai clienti da assistenti di AI generativa | C13: =IF($A13="",NA(),IF(COUNTIFS(RR_ID_Rischio,$A13,RR_Ciclo,cicloCorrente)*COUNTIFS(RR_ID_Rischio,$A13,RR_Ciclo,cicloPrecedente)=0,NA(),SUMIFS(RR_Severity,RR_ID_Rischio,$A13,RR_Ciclo,cicloCorrente)-SUMIFS(RR_Severity,RR_ID_Rischio,$A13,RR_Ciclo,cicloPrecedente))) -> #N/A | D13: =IF($A13="",NA(),IF(COUNTIFS(RR_ID_Rischio,$A13,RR_Ciclo,cicloCorrente)*COUNTIFS(RR_ID_Rischio,$A13,RR_Ciclo,cicloPrecedente)=0,NA(),SUMIFS(RR_Velocity,RR_ID_Rischio,$A13,RR_Ciclo,cicloCorrente)-SUMIFS(RR_Velocity,RR_ID_Rischio,$A13,RR_Ciclo,cicloPrecedente))) -> #N/A | E13: =IF($A13="",NA(),IF(COUNTIFS(RR_ID_Rischio,$A13,RR_Ciclo,cicloCorrente)*COUNTIFS(RR_ID_Rischio,$A13,RR_Ciclo,cicloPrecedente)=0,NA(),SUMIFS(RR_Prossimita,RR_ID_Rischio,$A13,RR_Ciclo,cicloCorrente)-SUMIFS(RR_Prossimita,RR_ID_Rischio,$A13,RR_Ciclo,cicloPrecedente))) -> #N/A | F13: =IF($A13="",NA(),IF(COUNTIFS(RR_ID_Rischio,$A13,RR_Ciclo,cicloCorrente)*COUNTIFS(RR_ID_Rischio,$A13,RR_Ciclo,cicloPrecedente)=0,NA(),SUMIFS(RR_Gap_Controlli,RR_ID_Rischio,$A13,RR_Ciclo,cicloCorrente)-SUMIFS(RR_Gap_Controlli,RR_ID_Rischio,$A13,RR_Ciclo,cicloPrecedente))) -> #N/A | G13: =IF($A13="",NA(),IF(COUNTIFS(RR_ID_Rischio,$A13,RR_Ciclo,cicloCorrente)*COUNTIFS(RR_ID_Rischio,$A13,RR_Ciclo,cicloPrecedente)=0,NA(),SUMIFS(RR_Confidence,RR_ID_Rischio,$A13,RR_Ciclo,cicloCorrente)-SUMIFS(RR_Confidence,RR_ID_Rischio,$A13,RR_Ciclo,cicloPrecedente))) -> #N/A | H13: =IF($A13="",NA(),IF(COUNTIFS(RR_ID_Rischio,$A13,RR_Ciclo,cicloCorrente)*COUNTIFS(RR_ID_Rischio,$A13,RR_Ciclo,cicloPrecedente)=0,NA(),SUMIFS(RR_Probabilita,RR_ID_Rischio,$A13,RR_Ciclo,cicloCorrente)-SUMIFS(RR_Probabilita,RR_ID_Rischio,$A13,RR_Ciclo,cicloPrecedente))) -> #N/A | I13: =IF($A13="",NA(),IF(COUNTIFS(RR_ID_Rischio,$A13,RR_Ciclo,cicloCorrente)*COUNTIFS(RR_ID_Rischio,$A13,RR_Ciclo,cicloPrecedente)=0,NA(),SUMIFS(RR_Score_Composito,RR_ID_Rischio,$A13,RR_Ciclo,cicloCorrente)-SUMIFS(RR_Score_Composito,RR_ID_Rischio,$A13,RR_Ciclo,cicloPrecedente))) -> #N/A | J13: =IF($A13="","",IF(COUNT(C13:H13)<6,"Nuovo o non valutato in uno dei due cicli",IF(MAX(C13:H13)>1,"Aumento > 1 punto: viola la rubrica",IF(MIN(C13:H13)<-1,"Riduzione > 1 punto: viola la rubrica","")))) -> Nuovo o non valutato in uno dei due cicli
A14: =Dashboard!A23 -> NFR-11 | B14: =Dashboard!B23 -> Fine del supporto dei sistemi di pagamento legacy | C14: =IF($A14="",NA(),IF(COUNTIFS(RR_ID_Rischio,$A14,RR_Ciclo,cicloCorrente)*COUNTIFS(RR_ID_Rischio,$A14,RR_Ciclo,cicloPrecedente)=0,NA(),SUMIFS(RR_Severity,RR_ID_Rischio,$A14,RR_Ciclo,cicloCorrente)-SUMIFS(RR_Severity,RR_ID_Rischio,$A14,RR_Ciclo,cicloPrecedente))) -> #N/A | D14: =IF($A14="",NA(),IF(COUNTIFS(RR_ID_Rischio,$A14,RR_Ciclo,cicloCorrente)*COUNTIFS(RR_ID_Rischio,$A14,RR_Ciclo,cicloPrecedente)=0,NA(),SUMIFS(RR_Velocity,RR_ID_Rischio,$A14,RR_Ciclo,cicloCorrente)-SUMIFS(RR_Velocity,RR_ID_Rischio,$A14,RR_Ciclo,cicloPrecedente))) -> #N/A | E14: =IF($A14="",NA(),IF(COUNTIFS(RR_ID_Rischio,$A14,RR_Ciclo,cicloCorrente)*COUNTIFS(RR_ID_Rischio,$A14,RR_Ciclo,cicloPrecedente)=0,NA(),SUMIFS(RR_Prossimita,RR_ID_Rischio,$A14,RR_Ciclo,cicloCorrente)-SUMIFS(RR_Prossimita,RR_ID_Rischio,$A14,RR_Ciclo,cicloPrecedente))) -> #N/A | F14: =IF($A14="",NA(),IF(COUNTIFS(RR_ID_Rischio,$A14,RR_Ciclo,cicloCorrente)*COUNTIFS(RR_ID_Rischio,$A14,RR_Ciclo,cicloPrecedente)=0,NA(),SUMIFS(RR_Gap_Controlli,RR_ID_Rischio,$A14,RR_Ciclo,cicloCorrente)-SUMIFS(RR_Gap_Controlli,RR_ID_Rischio,$A14,RR_Ciclo,cicloPrecedente))) -> #N/A | G14: =IF($A14="",NA(),IF(COUNTIFS(RR_ID_Rischio,$A14,RR_Ciclo,cicloCorrente)*COUNTIFS(RR_ID_Rischio,$A14,RR_Ciclo,cicloPrecedente)=0,NA(),SUMIFS(RR_Confidence,RR_ID_Rischio,$A14,RR_Ciclo,cicloCorrente)-SUMIFS(RR_Confidence,RR_ID_Rischio,$A14,RR_Ciclo,cicloPrecedente))) -> #N/A | H14: =IF($A14="",NA(),IF(COUNTIFS(RR_ID_Rischio,$A14,RR_Ciclo,cicloCorrente)*COUNTIFS(RR_ID_Rischio,$A14,RR_Ciclo,cicloPrecedente)=0,NA(),SUMIFS(RR_Probabilita,RR_ID_Rischio,$A14,RR_Ciclo,cicloCorrente)-SUMIFS(RR_Probabilita,RR_ID_Rischio,$A14,RR_Ciclo,cicloPrecedente))) -> #N/A | I14: =IF($A14="",NA(),IF(COUNTIFS(RR_ID_Rischio,$A14,RR_Ciclo,cicloCorrente)*COUNTIFS(RR_ID_Rischio,$A14,RR_Ciclo,cicloPrecedente)=0,NA(),SUMIFS(RR_Score_Composito,RR_ID_Rischio,$A14,RR_Ciclo,cicloCorrente)-SUMIFS(RR_Score_Composito,RR_ID_Rischio,$A14,RR_Ciclo,cicloPrecedente))) -> #N/A | J14: =IF($A14="","",IF(COUNT(C14:H14)<6,"Nuovo o non valutato in uno dei due cicli",IF(MAX(C14:H14)>1,"Aumento > 1 punto: viola la rubrica",IF(MIN(C14:H14)<-1,"Riduzione > 1 punto: viola la rubrica","")))) -> Nuovo o non valutato in uno dei due cicli
A15: =Dashboard!A24 -> NFR-12 | B15: =Dashboard!B24 -> Errori operativi nei pagamenti istantanei obbligatori | C15: =IF($A15="",NA(),IF(COUNTIFS(RR_ID_Rischio,$A15,RR_Ciclo,cicloCorrente)*COUNTIFS(RR_ID_Rischio,$A15,RR_Ciclo,cicloPrecedente)=0,NA(),SUMIFS(RR_Severity,RR_ID_Rischio,$A15,RR_Ciclo,cicloCorrente)-SUMIFS(RR_Severity,RR_ID_Rischio,$A15,RR_Ciclo,cicloPrecedente))) -> #N/A | D15: =IF($A15="",NA(),IF(COUNTIFS(RR_ID_Rischio,$A15,RR_Ciclo,cicloCorrente)*COUNTIFS(RR_ID_Rischio,$A15,RR_Ciclo,cicloPrecedente)=0,NA(),SUMIFS(RR_Velocity,RR_ID_Rischio,$A15,RR_Ciclo,cicloCorrente)-SUMIFS(RR_Velocity,RR_ID_Rischio,$A15,RR_Ciclo,cicloPrecedente))) -> #N/A | E15: =IF($A15="",NA(),IF(COUNTIFS(RR_ID_Rischio,$A15,RR_Ciclo,cicloCorrente)*COUNTIFS(RR_ID_Rischio,$A15,RR_Ciclo,cicloPrecedente)=0,NA(),SUMIFS(RR_Prossimita,RR_ID_Rischio,$A15,RR_Ciclo,cicloCorrente)-SUMIFS(RR_Prossimita,RR_ID_Rischio,$A15,RR_Ciclo,cicloPrecedente))) -> #N/A | F15: =IF($A15="",NA(),IF(COUNTIFS(RR_ID_Rischio,$A15,RR_Ciclo,cicloCorrente)*COUNTIFS(RR_ID_Rischio,$A15,RR_Ciclo,cicloPrecedente)=0,NA(),SUMIFS(RR_Gap_Controlli,RR_ID_Rischio,$A15,RR_Ciclo,cicloCorrente)-SUMIFS(RR_Gap_Controlli,RR_ID_Rischio,$A15,RR_Ciclo,cicloPrecedente))) -> #N/A | G15: =IF($A15="",NA(),IF(COUNTIFS(RR_ID_Rischio,$A15,RR_Ciclo,cicloCorrente)*COUNTIFS(RR_ID_Rischio,$A15,RR_Ciclo,cicloPrecedente)=0,NA(),SUMIFS(RR_Confidence,RR_ID_Rischio,$A15,RR_Ciclo,cicloCorrente)-SUMIFS(RR_Confidence,RR_ID_Rischio,$A15,RR_Ciclo,cicloPrecedente))) -> #N/A | H15: =IF($A15="",NA(),IF(COUNTIFS(RR_ID_Rischio,$A15,RR_Ciclo,cicloCorrente)*COUNTIFS(RR_ID_Rischio,$A15,RR_Ciclo,cicloPrecedente)=0,NA(),SUMIFS(RR_Probabilita,RR_ID_Rischio,$A15,RR_Ciclo,cicloCorrente)-SUMIFS(RR_Probabilita,RR_ID_Rischio,$A15,RR_Ciclo,cicloPrecedente))) -> #N/A | I15: =IF($A15="",NA(),IF(COUNTIFS(RR_ID_Rischio,$A15,RR_Ciclo,cicloCorrente)*COUNTIFS(RR_ID_Rischio,$A15,RR_Ciclo,cicloPrecedente)=0,NA(),SUMIFS(RR_Score_Composito,RR_ID_Rischio,$A15,RR_Ciclo,cicloCorrente)-SUMIFS(RR_Score_Composito,RR_ID_Rischio,$A15,RR_Ciclo,cicloPrecedente))) -> #N/A | J15: =IF($A15="","",IF(COUNT(C15:H15)<6,"Nuovo o non valutato in uno dei due cicli",IF(MAX(C15:H15)>1,"Aumento > 1 punto: viola la rubrica",IF(MIN(C15:H15)<-1,"Riduzione > 1 punto: viola la rubrica","")))) -> Nuovo o non valutato in uno dei due cicli
... A18: =Dashboard!A27 | B18: =Dashboard!B27 | C18: =IF($A18="",NA(),IF(COUNTIFS(RR_ID_Rischio,$A18,RR_Ciclo,cicloCorrente)*COUNTIFS(RR_ID_Rischio,$A18,RR_Ciclo,cicloPrecedente)=0,NA(),SUMIFS(RR_Severity,RR_ID_Rischio,$A18,RR_Ciclo,cicloCorrente)-SUMIFS(RR_Severity,RR_ID_Rischio,$A18,RR_Ciclo,cicloPrecedente))) -> #N/A | D18: =IF($A18="",NA(),IF(COUNTIFS(RR_ID_Rischio,$A18,RR_Ciclo,cicloCorrente)*COUNTIFS(RR_ID_Rischio,$A18,RR_Ciclo,cicloPrecedente)=0,NA(),SUMIFS(RR_Velocity,RR_ID_Rischio,$A18,RR_Ciclo,cicloCorrente)-SUMIFS(RR_Velocity,RR_ID_Rischio,$A18,RR_Ciclo,cicloPrecedente))) -> #N/A | E18: =IF($A18="",NA(),IF(COUNTIFS(RR_ID_Rischio,$A18,RR_Ciclo,cicloCorrente)*COUNTIFS(RR_ID_Rischio,$A18,RR_Ciclo,cicloPrecedente)=0,NA(),SUMIFS(RR_Prossimita,RR_ID_Rischio,$A18,RR_Ciclo,cicloCorrente)-SUMIFS(RR_Prossimita,RR_ID_Rischio,$A18,RR_Ciclo,cicloPrecedente))) -> #N/A | F18: =IF($A18="",NA(),IF(COUNTIFS(RR_ID_Rischio,$A18,RR_Ciclo,cicloCorrente)*COUNTIFS(RR_ID_Rischio,$A18,RR_Ciclo,cicloPrecedente)=0,NA(),SUMIFS(RR_Gap_Controlli,RR_ID_Rischio,$A18,RR_Ciclo,cicloCorrente)-SUMIFS(RR_Gap_Controlli,RR_ID_Rischio,$A18,RR_Ciclo,cicloPrecedente))) -> #N/A | G18: =IF($A18="",NA(),IF(COUNTIFS(RR_ID_Rischio,$A18,RR_Ciclo,cicloCorrente)*COUNTIFS(RR_ID_Rischio,$A18,RR_Ciclo,cicloPrecedente)=0,NA(),SUMIFS(RR_Confidence,RR_ID_Rischio,$A18,RR_Ciclo,cicloCorrente)-SUMIFS(RR_Confidence,RR_ID_Rischio,$A18,RR_Ciclo,cicloPrecedente))) -> #N/A | H18: =IF($A18="",NA(),IF(COUNTIFS(RR_ID_Rischio,$A18,RR_Ciclo,cicloCorrente)*COUNTIFS(RR_ID_Rischio,$A18,RR_Ciclo,cicloPrecedente)=0,NA(),SUMIFS(RR_Probabilita,RR_ID_Rischio,$A18,RR_Ciclo,cicloCorrente)-SUMIFS(RR_Probabilita,RR_ID_Rischio,$A18,RR_Ciclo,cicloPrecedente))) -> #N/A | I18: =IF($A18="",NA(),IF(COUNTIFS(RR_ID_Rischio,$A18,RR_Ciclo,cicloCorrente)*COUNTIFS(RR_ID_Rischio,$A18,RR_Ciclo,cicloPrecedente)=0,NA(),SUMIFS(RR_Score_Composito,RR_ID_Rischio,$A18,RR_Ciclo,cicloCorrente)-SUMIFS(RR_Score_Composito,RR_ID_Rischio,$A18,RR_Ciclo,cicloPrecedente))) -> #N/A | J18: =IF($A18="","",IF(COUNT(C18:H18)<6,"Nuovo o non valutato in uno dei due cicli",IF(MAX(C18:H18)>1,"Aumento > 1 punto: viola la rubrica",IF(MIN(C18:H18)<-1,"Riduzione > 1 punto: viola la rubrica",""))))

Sheet NewsLog
A1: Data | B1: Settimana | C1: ID_Notizia | D1: Titolo | E1: Fonte | F1: Codice_Fonte | G1: Rischio_ID | H1: Segnale | I1: Imp_L1_01 | J1: Imp_L1_02 | K1: Imp_L1_03 | L1: Imp_L1_04 | M1: Imp_L1_05 | N1: Imp_L1_06 | O1: Imp_L1_07 | P1: Sintesi | Q1: Validazione | S1: NewsLog — una riga per notizia, scritta da A3 ogni settimana (append senza duplicati per ID_Notizia).
A2: 46301 | B2: =A2-WEEKDAY(A2,2)+1 -> 46300 | C2: N-20261006-01 | D2: Sciopero nazionale del personale bancario e carenza di tecnici IT | E2: Agenzia di stampa | F2: FNT-17 | G2: NON PRESIDIATO | H2: Peggiorativo | I2: 0 | J2: 0 | K2: 2 | L2: 0 | M2: 0 | N2: 1 | O2: 1 | P2: I sindacati proclamano due giornate di sciopero; le banche segnalano difficolta' a coprire ruoli tecnici critici. | Q2: Accettato | S2: Segnale: solo i quattro valori del vocabolario, contati per testo esatto.
A3: 46302 | B3: =A3-WEEKDAY(A3,2)+1 -> 46300 | C3: N-20261007-01 | D3: Frode con voce clonata del direttore finanziario presso un gruppo industriale | E3: Stampa economica | F3: FNT-18 | G3: NON PRESIDIATO | H3: Peggiorativo | I3: 0 | J3: 3 | K3: 0 | L3: 1 | M3: 0 | N3: 0 | O3: 0 | P3: Bonifico istantaneo da 3 milioni disposto su richiesta telefonica con voce sintetica. | Q3: Accettato | S3: Rischio_ID = 'NON PRESIDIATO' se la notizia non tocca nessun rischio censito.
A4: 46303 | B4: =A4-WEEKDAY(A4,2)+1 -> 46300 | C4: N-20261008-01 | D4: Il CERT finanziario segnala kit di clonazione vocale in vendita | E4: CERT finanziario nazionale | F4: FNT-34 | G4: NON PRESIDIATO | H4: Peggiorativo | I4: 0 | J4: 2 | K4: 0 | L4: 0 | M4: 0 | N4: 0 | O4: 0 | P4: Strumenti pronti all'uso abbassano la soglia d'ingresso per le frodi APP. | Q4: Accettato | S4: Imp_L1_0x: intensita' 0-3 sull'event type, senza segno. Settimana e' una formula (lunedi').
A5: 46303 | B5: =A5-WEEKDAY(A5,2)+1 -> 46300 | C5: N-20261008-02 | D5: Il fornitore cloud completa la nuova region italiana | E5: Comunicato stampa del fornitore cloud, sito del fornitore | F5: MAN | G5: NON PRESIDIATO | H5: Neutro | I5: 0 | J5: 0 | K5: 0 | L5: 0 | M5: 0 | N5: 1 | O5: 0 | P5: La region e' disponibile; nessun impatto immediato sui servizi della Banca. | Q5: Accettato | S5: Una notizia Respinta in validazione diventa 'Non rilevante' con impatti 0: non pesa su badge e pressione.
A6: 46304 | B6: =A6-WEEKDAY(A6,2)+1 -> 46300 | C6: N-20261009-01 | D6: Autorita' europea: rimborso obbligatorio delle frodi APP dal 2027 | E6: Autorita' bancaria europea | F6: FNT-03 | G6: NON PRESIDIATO | H6: Peggiorativo | I6: 0 | J6: 2 | K6: 0 | L6: 2 | M6: 0 | N6: 0 | O6: 0 | P6: Il rimborso a carico del prestatore di servizi di pagamento diventa obbligatorio per le frodi autorizzate. | Q6: Accettato

Sheet Approfondimento
A1: Approfondimento — storia di un rischio
A2: Scegliere un ID in B3 (unica cella di input): tutto il resto e' formula.
A3: ID rischio | B3: NFR-01
A4: Nome | B4: =IFERROR(INDEX(ANA_Nome,MATCH($B$3,ANA_ID,0)),"ID non in anagrafica") -> Frodi su pagamenti istantanei abilitate da AI generativa
A5: Event type | B5: =IFERROR(INDEX(ANA_Event_Type,MATCH($B$3,ANA_ID,0)),"") -> L1-02
A6: Owner | B6: =IFERROR(INDEX(ANA_Owner,MATCH($B$3,ANA_ID,0)),"") -> Da assegnare
A8: Ciclo | B8: Severity | C8: Velocity | D8: Prossimita' | E8: Gap_Controlli | F8: Score | G8: Confidence | H8: Probabilita
A9: =Parametri!$B$20 -> 2024Q4 | B9: =IF($A9="",NA(),IF(COUNTIFS(RR_ID_Rischio,$B$3,RR_Ciclo,$A9)=0,NA(),SUMIFS(RR_Severity,RR_ID_Rischio,$B$3,RR_Ciclo,$A9))) -> #N/A | C9: =IF($A9="",NA(),IF(COUNTIFS(RR_ID_Rischio,$B$3,RR_Ciclo,$A9)=0,NA(),SUMIFS(RR_Velocity,RR_ID_Rischio,$B$3,RR_Ciclo,$A9))) -> #N/A | D9: =IF($A9="",NA(),IF(COUNTIFS(RR_ID_Rischio,$B$3,RR_Ciclo,$A9)=0,NA(),SUMIFS(RR_Prossimita,RR_ID_Rischio,$B$3,RR_Ciclo,$A9))) -> #N/A | E9: =IF($A9="",NA(),IF(COUNTIFS(RR_ID_Rischio,$B$3,RR_Ciclo,$A9)=0,NA(),SUMIFS(RR_Gap_Controlli,RR_ID_Rischio,$B$3,RR_Ciclo,$A9))) -> #N/A | F9: =IF($A9="",NA(),IF(COUNTIFS(RR_ID_Rischio,$B$3,RR_Ciclo,$A9)=0,NA(),SUMIFS(RR_Score_Composito,RR_ID_Rischio,$B$3,RR_Ciclo,$A9))) -> #N/A | G9: =IF($A9="",NA(),IF(COUNTIFS(RR_ID_Rischio,$B$3,RR_Ciclo,$A9)=0,NA(),SUMIFS(RR_Confidence,RR_ID_Rischio,$B$3,RR_Ciclo,$A9))) -> #N/A | H9: =IF($A9="",NA(),IF(COUNTIFS(RR_ID_Rischio,$B$3,RR_Ciclo,$A9)=0,NA(),SUMIFS(RR_Probabilita,RR_ID_Rischio,$B$3,RR_Ciclo,$A9))) -> #N/A
A10: =Parametri!$B$21 -> 2025Q1 | B10: =IF($A10="",NA(),IF(COUNTIFS(RR_ID_Rischio,$B$3,RR_Ciclo,$A10)=0,NA(),SUMIFS(RR_Severity,RR_ID_Rischio,$B$3,RR_Ciclo,$A10))) -> #N/A | C10: =IF($A10="",NA(),IF(COUNTIFS(RR_ID_Rischio,$B$3,RR_Ciclo,$A10)=0,NA(),SUMIFS(RR_Velocity,RR_ID_Rischio,$B$3,RR_Ciclo,$A10))) -> #N/A | D10: =IF($A10="",NA(),IF(COUNTIFS(RR_ID_Rischio,$B$3,RR_Ciclo,$A10)=0,NA(),SUMIFS(RR_Prossimita,RR_ID_Rischio,$B$3,RR_Ciclo,$A10))) -> #N/A | E10: =IF($A10="",NA(),IF(COUNTIFS(RR_ID_Rischio,$B$3,RR_Ciclo,$A10)=0,NA(),SUMIFS(RR_Gap_Controlli,RR_ID_Rischio,$B$3,RR_Ciclo,$A10))) -> #N/A | F10: =IF($A10="",NA(),IF(COUNTIFS(RR_ID_Rischio,$B$3,RR_Ciclo,$A10)=0,NA(),SUMIFS(RR_Score_Composito,RR_ID_Rischio,$B$3,RR_Ciclo,$A10))) -> #N/A | G10: =IF($A10="",NA(),IF(COUNTIFS(RR_ID_Rischio,$B$3,RR_Ciclo,$A10)=0,NA(),SUMIFS(RR_Confidence,RR_ID_Rischio,$B$3,RR_Ciclo,$A10))) -> #N/A | H10: =IF($A10="",NA(),IF(COUNTIFS(RR_ID_Rischio,$B$3,RR_Ciclo,$A10)=0,NA(),SUMIFS(RR_Probabilita,RR_ID_Rischio,$B$3,RR_Ciclo,$A10))) -> #N/A
A11: =Parametri!$B$22 -> 2025Q2 | B11: =IF($A11="",NA(),IF(COUNTIFS(RR_ID_Rischio,$B$3,RR_Ciclo,$A11)=0,NA(),SUMIFS(RR_Severity,RR_ID_Rischio,$B$3,RR_Ciclo,$A11))) -> #N/A | C11: =IF($A11="",NA(),IF(COUNTIFS(RR_ID_Rischio,$B$3,RR_Ciclo,$A11)=0,NA(),SUMIFS(RR_Velocity,RR_ID_Rischio,$B$3,RR_Ciclo,$A11))) -> #N/A | D11: =IF($A11="",NA(),IF(COUNTIFS(RR_ID_Rischio,$B$3,RR_Ciclo,$A11)=0,NA(),SUMIFS(RR_Prossimita,RR_ID_Rischio,$B$3,RR_Ciclo,$A11))) -> #N/A | E11: =IF($A11="",NA(),IF(COUNTIFS(RR_ID_Rischio,$B$3,RR_Ciclo,$A11)=0,NA(),SUMIFS(RR_Gap_Controlli,RR_ID_Rischio,$B$3,RR_Ciclo,$A11))) -> #N/A | F11: =IF($A11="",NA(),IF(COUNTIFS(RR_ID_Rischio,$B$3,RR_Ciclo,$A11)=0,NA(),SUMIFS(RR_Score_Composito,RR_ID_Rischio,$B$3,RR_Ciclo,$A11))) -> #N/A | G11: =IF($A11="",NA(),IF(COUNTIFS(RR_ID_Rischio,$B$3,RR_Ciclo,$A11)=0,NA(),SUMIFS(RR_Confidence,RR_ID_Rischio,$B$3,RR_Ciclo,$A11))) -> #N/A | H11: =IF($A11="",NA(),IF(COUNTIFS(RR_ID_Rischio,$B$3,RR_Ciclo,$A11)=0,NA(),SUMIFS(RR_Probabilita,RR_ID_Rischio,$B$3,RR_Ciclo,$A11))) -> #N/A
A12: =Parametri!$B$23 -> 2025Q3 | B12: =IF($A12="",NA(),IF(COUNTIFS(RR_ID_Rischio,$B$3,RR_Ciclo,$A12)=0,NA(),SUMIFS(RR_Severity,RR_ID_Rischio,$B$3,RR_Ciclo,$A12))) -> #N/A | C12: =IF($A12="",NA(),IF(COUNTIFS(RR_ID_Rischio,$B$3,RR_Ciclo,$A12)=0,NA(),SUMIFS(RR_Velocity,RR_ID_Rischio,$B$3,RR_Ciclo,$A12))) -> #N/A | D12: =IF($A12="",NA(),IF(COUNTIFS(RR_ID_Rischio,$B$3,RR_Ciclo,$A12)=0,NA(),SUMIFS(RR_Prossimita,RR_ID_Rischio,$B$3,RR_Ciclo,$A12))) -> #N/A | E12: =IF($A12="",NA(),IF(COUNTIFS(RR_ID_Rischio,$B$3,RR_Ciclo,$A12)=0,NA(),SUMIFS(RR_Gap_Controlli,RR_ID_Rischio,$B$3,RR_Ciclo,$A12))) -> #N/A | F12: =IF($A12="",NA(),IF(COUNTIFS(RR_ID_Rischio,$B$3,RR_Ciclo,$A12)=0,NA(),SUMIFS(RR_Score_Composito,RR_ID_Rischio,$B$3,RR_Ciclo,$A12))) -> #N/A | G12: =IF($A12="",NA(),IF(COUNTIFS(RR_ID_Rischio,$B$3,RR_Ciclo,$A12)=0,NA(),SUMIFS(RR_Confidence,RR_ID_Rischio,$B$3,RR_Ciclo,$A12))) -> #N/A | H12: =IF($A12="",NA(),IF(COUNTIFS(RR_ID_Rischio,$B$3,RR_Ciclo,$A12)=0,NA(),SUMIFS(RR_Probabilita,RR_ID_Rischio,$B$3,RR_Ciclo,$A12))) -> #N/A
A13: =Parametri!$B$24 -> 2025Q4 | B13: =IF($A13="",NA(),IF(COUNTIFS(RR_ID_Rischio,$B$3,RR_Ciclo,$A13)=0,NA(),SUMIFS(RR_Severity,RR_ID_Rischio,$B$3,RR_Ciclo,$A13))) -> #N/A | C13: =IF($A13="",NA(),IF(COUNTIFS(RR_ID_Rischio,$B$3,RR_Ciclo,$A13)=0,NA(),SUMIFS(RR_Velocity,RR_ID_Rischio,$B$3,RR_Ciclo,$A13))) -> #N/A | D13: =IF($A13="",NA(),IF(COUNTIFS(RR_ID_Rischio,$B$3,RR_Ciclo,$A13)=0,NA(),SUMIFS(RR_Prossimita,RR_ID_Rischio,$B$3,RR_Ciclo,$A13))) -> #N/A | E13: =IF($A13="",NA(),IF(COUNTIFS(RR_ID_Rischio,$B$3,RR_Ciclo,$A13)=0,NA(),SUMIFS(RR_Gap_Controlli,RR_ID_Rischio,$B$3,RR_Ciclo,$A13))) -> #N/A | F13: =IF($A13="",NA(),IF(COUNTIFS(RR_ID_Rischio,$B$3,RR_Ciclo,$A13)=0,NA(),SUMIFS(RR_Score_Composito,RR_ID_Rischio,$B$3,RR_Ciclo,$A13))) -> #N/A | G13: =IF($A13="",NA(),IF(COUNTIFS(RR_ID_Rischio,$B$3,RR_Ciclo,$A13)=0,NA(),SUMIFS(RR_Confidence,RR_ID_Rischio,$B$3,RR_Ciclo,$A13))) -> #N/A | H13: =IF($A13="",NA(),IF(COUNTIFS(RR_ID_Rischio,$B$3,RR_Ciclo,$A13)=0,NA(),SUMIFS(RR_Probabilita,RR_ID_Rischio,$B$3,RR_Ciclo,$A13))) -> #N/A
A14: =Parametri!$B$25 -> 2026Q1 | B14: =IF($A14="",NA(),IF(COUNTIFS(RR_ID_Rischio,$B$3,RR_Ciclo,$A14)=0,NA(),SUMIFS(RR_Severity,RR_ID_Rischio,$B$3,RR_Ciclo,$A14))) -> #N/A | C14: =IF($A14="",NA(),IF(COUNTIFS(RR_ID_Rischio,$B$3,RR_Ciclo,$A14)=0,NA(),SUMIFS(RR_Velocity,RR_ID_Rischio,$B$3,RR_Ciclo,$A14))) -> #N/A | D14: =IF($A14="",NA(),IF(COUNTIFS(RR_ID_Rischio,$B$3,RR_Ciclo,$A14)=0,NA(),SUMIFS(RR_Prossimita,RR_ID_Rischio,$B$3,RR_Ciclo,$A14))) -> #N/A | E14: =IF($A14="",NA(),IF(COUNTIFS(RR_ID_Rischio,$B$3,RR_Ciclo,$A14)=0,NA(),SUMIFS(RR_Gap_Controlli,RR_ID_Rischio,$B$3,RR_Ciclo,$A14))) -> #N/A | F14: =IF($A14="",NA(),IF(COUNTIFS(RR_ID_Rischio,$B$3,RR_Ciclo,$A14)=0,NA(),SUMIFS(RR_Score_Composito,RR_ID_Rischio,$B$3,RR_Ciclo,$A14))) -> #N/A | G14: =IF($A14="",NA(),IF(COUNTIFS(RR_ID_Rischio,$B$3,RR_Ciclo,$A14)=0,NA(),SUMIFS(RR_Confidence,RR_ID_Rischio,$B$3,RR_Ciclo,$A14))) -> #N/A | H14: =IF($A14="",NA(),IF(COUNTIFS(RR_ID_Rischio,$B$3,RR_Ciclo,$A14)=0,NA(),SUMIFS(RR_Probabilita,RR_ID_Rischio,$B$3,RR_Ciclo,$A14))) -> #N/A
A15: =Parametri!$B$26 -> 2026Q2 | B15: =IF($A15="",NA(),IF(COUNTIFS(RR_ID_Rischio,$B$3,RR_Ciclo,$A15)=0,NA(),SUMIFS(RR_Severity,RR_ID_Rischio,$B$3,RR_Ciclo,$A15))) -> #N/A | C15: =IF($A15="",NA(),IF(COUNTIFS(RR_ID_Rischio,$B$3,RR_Ciclo,$A15)=0,NA(),SUMIFS(RR_Velocity,RR_ID_Rischio,$B$3,RR_Ciclo,$A15))) -> #N/A | D15: =IF($A15="",NA(),IF(COUNTIFS(RR_ID_Rischio,$B$3,RR_Ciclo,$A15)=0,NA(),SUMIFS(RR_Prossimita,RR_ID_Rischio,$B$3,RR_Ciclo,$A15))) -> #N/A | E15: =IF($A15="",NA(),IF(COUNTIFS(RR_ID_Rischio,$B$3,RR_Ciclo,$A15)=0,NA(),SUMIFS(RR_Gap_Controlli,RR_ID_Rischio,$B$3,RR_Ciclo,$A15))) -> #N/A | F15: =IF($A15="",NA(),IF(COUNTIFS(RR_ID_Rischio,$B$3,RR_Ciclo,$A15)=0,NA(),SUMIFS(RR_Score_Composito,RR_ID_Rischio,$B$3,RR_Ciclo,$A15))) -> #N/A | G15: =IF($A15="",NA(),IF(COUNTIFS(RR_ID_Rischio,$B$3,RR_Ciclo,$A15)=0,NA(),SUMIFS(RR_Confidence,RR_ID_Rischio,$B$3,RR_Ciclo,$A15))) -> #N/A | H15: =IF($A15="",NA(),IF(COUNTIFS(RR_ID_Rischio,$B$3,RR_Ciclo,$A15)=0,NA(),SUMIFS(RR_Probabilita,RR_ID_Rischio,$B$3,RR_Ciclo,$A15))) -> #N/A
A16: =Parametri!$B$27 -> 2026Q3 | B16: =IF($A16="",NA(),IF(COUNTIFS(RR_ID_Rischio,$B$3,RR_Ciclo,$A16)=0,NA(),SUMIFS(RR_Severity,RR_ID_Rischio,$B$3,RR_Ciclo,$A16))) -> 4 | C16: =IF($A16="",NA(),IF(COUNTIFS(RR_ID_Rischio,$B$3,RR_Ciclo,$A16)=0,NA(),SUMIFS(RR_Velocity,RR_ID_Rischio,$B$3,RR_Ciclo,$A16))) -> 4 | D16: =IF($A16="",NA(),IF(COUNTIFS(RR_ID_Rischio,$B$3,RR_Ciclo,$A16)=0,NA(),SUMIFS(RR_Prossimita,RR_ID_Rischio,$B$3,RR_Ciclo,$A16))) -> 4 | E16: =IF($A16="",NA(),IF(COUNTIFS(RR_ID_Rischio,$B$3,RR_Ciclo,$A16)=0,NA(),SUMIFS(RR_Gap_Controlli,RR_ID_Rischio,$B$3,RR_Ciclo,$A16))) -> 3 | F16: =IF($A16="",NA(),IF(COUNTIFS(RR_ID_Rischio,$B$3,RR_Ciclo,$A16)=0,NA(),SUMIFS(RR_Score_Composito,RR_ID_Rischio,$B$3,RR_Ciclo,$A16))) -> 3.8 | G16: =IF($A16="",NA(),IF(COUNTIFS(RR_ID_Rischio,$B$3,RR_Ciclo,$A16)=0,NA(),SUMIFS(RR_Confidence,RR_ID_Rischio,$B$3,RR_Ciclo,$A16))) -> 4 | H16: =IF($A16="",NA(),IF(COUNTIFS(RR_ID_Rischio,$B$3,RR_Ciclo,$A16)=0,NA(),SUMIFS(RR_Probabilita,RR_ID_Rischio,$B$3,RR_Ciclo,$A16))) -> 4
A18: Razionale (ciclo corrente) | B18: =IFERROR(INDEX(RR_Razionale,MATCH(cicloCorrente&"|"&$B$3,RR_Chiave,0)),"—") -> Il report frodi del terzo trimestre conferma importi medi elevati e casi con voce sintetica in linea con il trimestre precedente: severity 4 (danno reputazionale nazionale possibile), velocity 4 (impatto in minuti), prossimita' 4 (casi in banche comparabili). Gap_Controlli resta 3: la verifica fuori banda e' approvata ma non ancora attiva sui bonifici istantanei.
A19: Variazioni (ciclo corrente) | B19: =IFERROR(INDEX(RR_Variazioni,MATCH(cicloCorrente&"|"&$B$3,RR_Chiave,0)),"—") -> []
A20: Fonti (ciclo corrente) | B20: =IFERROR(INDEX(RR_Fonti,MATCH(cicloCorrente&"|"&$B$3,RR_Chiave,0)),"—") -> [{"riferimento": "Analisi interna sulle frodi da ingegneria sociale", "data": "2025-10-20", "tipo": "Interna"}, {"riferimento": "Threat intelligence: campagne di frode con voce sintetica verso banche UE", "data": "2026-04-15", "tipo": "Esterna"}, {"riferimento": "Report trimestrale frodi — Funzione Antifrode", "data": "2026-06-10", "tipo": "Interna"}, {"riferimento": "Relazione annuale sui pagamenti al dettaglio dell'autorita' di vigilanza", "data": "2026-05-28", "tipo": "Esterna"}, {"riferimento": "Report trimestrale frodi Q3 — Funzione Antifrode", "data": "2026-09-12", "tipo": "Interna"}]
A22: KRI in vigore del rischio (ciclo corrente; la storia di ciascuno e' in Andamento_KRI)
A23: KRI_ID | B23: Nome | C23: Unita | D23: Soglia_Attenzione | E23: Soglia_Allerta | F23: Valore_Corrente | G23: Stato
A24: =IF($J24="","",INDEX(KRI!$B:$B,$J24)&"") -> NFR-01-K1 | B24: =IF($J24="","",INDEX(KRI!$D:$D,$J24)&"") -> Tentativi di frode APP per 10.000 bonifici istantanei | C24: =IF($J24="","",INDEX(KRI!$E:$E,$J24)&"") -> n/10k | D24: =IF($J24="","",INDEX(KRI!$G:$G,$J24)) -> 3 | E24: =IF($J24="","",INDEX(KRI!$H:$H,$J24)) -> 6 | F24: =IF($J24="","",INDEX(KRI!$I:$I,$J24)) -> 4.8 | G24: =IF($J24="","",INDEX(KRI!$M:$M,$J24)&"") -> Ambra | J24: =IFERROR(_xlfn.AGGREGATE(15,6,ROW(KRI_ID_Rischio)/((KRI_ID_Rischio=$B$3)*(KRI_In_Vigore="Sì")*(KRI_Ciclo=cicloCorrente)),1),"") -> 2
